Workbook
Name CURRENT_NAV: BS!$C$45
Name NAV: BS!$C$43
Name NAV_MKT: Journals!$T$1
Name TCV_STOCKS: #REF!
Name TMV_STOCKS: #REF!

Sheet Chart of Accounts
B2: Accounts Name | C2: Normal Balance
B3: Investments in stock | C3: DEBIT
B4: Interest Receivables from Bank A/C | C4: DEBIT
B5: Preliminary & issue expenses | C5: DEBIT
B6: Accrued Management Fee | C6: CREDIT
B7: Accrued Trustee Fee | C7: CREDIT
B8: Accrued Custodian Fee | C8: CREDIT
B9: Accrued BSEC fee | C9: CREDIT
B10: Accrued Audit Fee | C10: CREDIT
B11: Accrued CDBL Fee | C11: CREDIT
B12: Fixed Deposit Receipts (FDR) | C12: DEBIT
B13: Cash and cash equivalents | C13: DEBIT
... B19: Unrealized gain on securities | C19: CREDIT
B20: Unrealized gain on T-Bill
B21: Unrealized gain on T-Bond
B22: Unrealized loss on securities | C22: DEBIT
B23: Amortization of preliminary and issue expense | C23: DEBIT
B24: Management Fee | C24: DEBIT
B25: Trustee fee | C25: DEBIT
B26: BSEC Annual Fee | C26: DEBIT
B27: Audit fee | C27: DEBIT
B28: CDBL charges | C28: DEBIT
B29: Fair value adjustment | C29: DEBIT
B30: Fair value adjustment T-Bill
B31: Fair value adjustment T-Bond
B32: Interest receivables from FDR | C32: DEBIT
B33: Payable to broker | C33: CREDIT
B34: Other operating expenses | C34: DEBIT
B35: Dividend income | C35: CREDIT
B36: Dividend receivable | C36: DEBIT
B37: Custodian fee | C37: DEBIT
B38: IPO Application | C38: DEBIT
B39: IPO Application Fee | C39: DEBIT
B40: Receivable from broker | C40: DEBIT
B41: Realized gain | C41: CREDIT
B42: Realized gain on T-Bill
B43: Realized gain on T-Bond
B44: Other Income | C44: CREDIT
B45: Dividend Equalization Reserve | C45: CREDIT
B46: Retained Earnings
B47: Dividend Payable | C47: CREDIT
B48: Withholding Tax Payable | C48: CREDIT
B49: Withholding Tax Payable for News Paper | C49: CREDIT
B50: Withholding Tax Payable for Telnet | C50: CREDIT
B51: Realized Loss
B52: Accrued Interest Income
B53: Receivable from FDR
B54: Investments in T-Bond | C54: DEBIT
B55: Bond Premium | C55: DEBIT
B56: Redemption Receivable | C56: DEBIT
B57: Redemption of Investment | C57: CREDIT
B58: Interest Receivables from T-Bond | C58: DEBIT
B59: Investment in T-Bill | C59: DEBIT
B60: Interest Receivables from T-Bill | C60: DEBIT

Sheet INVESTORS_LIST
A1: INVESTOR NAME | B1: INVESTOR CODE
A2: HARI PADA SAHA | B2: A00002
A3: EKUSH WEALTH MANAGEMENT LIMITED | B3: A00003
A4: SADIA AHMED | B4: A00004
A5: MORSHEDA MIM | B5: A00005
A6: MD. JAHANGIR ALAM | B6: A00006
A7: BISWAS ARIFUR RAHMAN | B7: A00007
A8: JEWEL SAHA | B8: A00008
A9: SHIBBIR AHMED | B9: A00009
A10: SHYAMAL KRISHNA SAHA | B10: A00010
A11: NASRIN AKHTER | B11: A00011
A12: MRINMOY GHOSH | B12: A00012
... A500: MUHAMMAD SAJJAD HOSSAIN | B500: A00500

Sheet Journals
A2: Check of Journal Entries | L2: =K6-L6 -> 0.044296265
A3: Check of Trial Balance | L3: =SUM('TB-C'!H7:H5011)-SUM('TB-C'!I7:I5011) -> 0.035499945
A4: Check of Balance Seet | L4: =BS!C25-BS!C41 -> 0
A5: Check of Cash Balance | G5: =BS!C23-CF!B44 -> -3620314.1
J6: =K6-L6 -> 0.044296265 | K6: =SUBTOTAL(9,K9:K16883) -> 4.7981054e+09 | L6: =SUBTOTAL(9,L9:L16883) -> 4.7981054e+09
A7: Year | B7: Month | C7: Day | D7: Value | F7: Transaction | G7: Transaction Type | J7: Account Name | K7: Debit | L7: Credit
E8: Date
A9: 2021 | B9: 10 | C9: 13 | D9: =DATE(A9,B9,C9) -> 44482 | E9: =DATE(A9,B9,C9) -> 44482 | F9: Unit Subscription - LUMPSUM | G9: C | H9: {=IFERROR(INDEX(INVESTOR_LIST[INVESTOR NAME],MATCH(I9,INVESTOR_LIST[INVESTOR CODE],0),)," ")} -> EKUSH WEALTH MANAGEMENT LIMITED | I9: A00003 | J9: Cash and cash equivalents | K9: 1000
A10: 2021 | B10: 10 | C10: 13 | D10: =DATE(A10,B10,C10) -> 44482 | E10: =DATE(A10,B10,C10) -> 44482 | G10: C | H10: {=IFERROR(INDEX(INVESTOR_LIST[INVESTOR NAME],MATCH(I10,INVESTOR_LIST[INVESTOR CODE],0),)," ")} -> EKUSH WEALTH MANAGEMENT LIMITED | I10: A00003 | J10: Unit Capital | L10: 1000
A11: 2021 | B11: 10 | C11: 18 | D11: =DATE(A11,B11,C11) -> 44487 | E11: =DATE(A11,B11,C11) -> 44487 | F11: Unit Subscription - LUMPSUM | G11: C | H11: {=IFERROR(INDEX(INVESTOR_LIST[INVESTOR NAME],MATCH(I11,INVESTOR_LIST[INVESTOR CODE],0),)," ")} -> EKUSH WEALTH MANAGEMENT LIMITED | I11: A00003 | J11: Cash and cash equivalents | K11: 10000000
A12: 2021 | B12: 10 | C12: 18 | D12: =DATE(A12,B12,C12) -> 44487 | E12: =DATE(A12,B12,C12) -> 44487 | G12: C | H12: {=IFERROR(INDEX(INVESTOR_LIST[INVESTOR NAME],MATCH(I12,INVESTOR_LIST[INVESTOR CODE],0),)," ")} -> EKUSH WEALTH MANAGEMENT LIMITED | I12: A00003 | J12: Unit Capital | L12: 10000000
A13: 2021 | B13: 10 | C13: 18 | D13: =DATE(A13,B13,C13) -> 44487 | E13: =DATE(A13,B13,C13) -> 44487 | F13: Bank Charges | G13: C | H13: {=IFERROR(INDEX(INVESTOR_LIST[INVESTOR NAME],MATCH(I13,INVESTOR_LIST[INVESTOR CODE],0),)," ")} | J13: Bank charges and excise duties | K13: 60
A14: 2021 | B14: 10 | C14: 18 | D14: =DATE(A14,B14,C14) -> 44487 | E14: =DATE(A14,B14,C14) -> 44487 | G14: C | H14: {=IFERROR(INDEX(INVESTOR_LIST[INVESTOR NAME],MATCH(I14,INVESTOR_LIST[INVESTOR CODE],0),)," ")} | J14: Cash and cash equivalents | L14: 60
A15: 2021 | B15: 11 | C15: 4 | D15: =DATE(A15,B15,C15) -> 44504 | E15: =DATE(A15,B15,C15) -> 44504 | F15: Unit Subscription - LUMPSUM | G15: C | H15: {=IFERROR(INDEX(INVESTOR_LIST[INVESTOR NAME],MATCH(I15,INVESTOR_LIST[INVESTOR CODE],0),)," ")} -> JHARNA RANI SAHA | I15: A00077 | J15: Cash and cash equivalents | K15: 150000
A16: 2021 | B16: 11 | C16: 4 | D16: =DATE(A16,B16,C16) -> 44504 | E16: =DATE(A16,B16,C16) -> 44504 | G16: C | H16: {=IFERROR(INDEX(INVESTOR_LIST[INVESTOR NAME],MATCH(I16,INVESTOR_LIST[INVESTOR CODE],0),)," ")} -> JHARNA RANI SAHA | I16: A00077 | J16: Unit Capital | L16: 150000
A17: 2021 | B17: 11 | C17: 8 | D17: =DATE(A17,B17,C17) -> 44508 | E17: =DATE(A17,B17,C17) -> 44508 | F17: Unit Subscription - LUMPSUM | G17: C | H17: {=IFERROR(INDEX(INVESTOR_LIST[INVESTOR NAME],MATCH(I17,INVESTOR_LIST[INVESTOR CODE],0),)," ")} -> SHUVA SAHA | I17: A00053 | J17: Cash and cash equivalents | K17: 1200000
A18: 2021 | B18: 11 | C18: 8 | D18: =DATE(A18,B18,C18) -> 44508 | E18: =DATE(A18,B18,C18) -> 44508 | G18: C | H18: {=IFERROR(INDEX(INVESTOR_LIST[INVESTOR NAME],MATCH(I18,INVESTOR_LIST[INVESTOR CODE],0),)," ")} -> SHUVA SAHA | I18: A00053 | J18: Unit Capital | L18: 1200000
A19: 2021 | B19: 11 | C19: 8 | D19: =DATE(A19,B19,C19) -> 44508 | E19: =DATE(A19,B19,C19) -> 44508 | F19: Unit Subscription - LUMPSUM | G19: C | H19: {=IFERROR(INDEX(INVESTOR_LIST[INVESTOR NAME],MATCH(I19,INVESTOR_LIST[INVESTOR CODE],0),)," ")} -> SHYAMAL KRISHNA SAHA | I19: A00010 | J19: Cash and cash equivalents | K19: 500000
A20: 2021 | B20: 11 | C20: 8 | D20: =DATE(A20,B20,C20) -> 44508 | E20: =DATE(A20,B20,C20) -> 44508 | G20: C | H20: {=IFERROR(INDEX(INVESTOR_LIST[INVESTOR NAME],MATCH(I20,INVESTOR_LIST[INVESTOR CODE],0),)," ")} -> SHYAMAL KRISHNA SAHA | I20: A00010 | J20: Unit Capital | L20: 500000
A21: 2021 | B21: 11 | C21: 9 | D21: =DATE(A21,B21,C21) -> 44509 | E21: =DATE(A21,B21,C21) -> 44509 | F21: Bank Charges | G21: C | H21: {=IFERROR(INDEX(INVESTOR_LIST[INVESTOR NAME],MATCH(I21,INVESTOR_LIST[INVESTOR CODE],0),)," ")} | J21: Bank charges and excise duties | K21: 10
A22: 2021 | B22: 11 | C22: 9 | D22: =DATE(A22,B22,C22) -> 44509 | E22: =DATE(A22,B22,C22) -> 44509 | G22: C | H22: {=IFERROR(INDEX(INVESTOR_LIST[INVESTOR NAME],MATCH(I22,INVESTOR_LIST[INVESTOR CODE],0),)," ")} | J22: Cash and cash equivalents | L22: 10
A23: 2021 | B23: 11 | C23: 9 | D23: =DATE(A23,B23,C23) -> 44509 | E23: =DATE(A23,B23,C23) -> 44509 | F23: Unit Subscription - LUMPSUM | G23: C | H23: {=IFERROR(INDEX(INVESTOR_LIST[INVESTOR NAME],MATCH(I23,INVESTOR_LIST[INVESTOR CODE],0),)," ")} -> BILKISS ARA | I23: A00073 | J23: Cash and cash equivalents | K23: 450000
A24: 2021 | B24: 11 | C24: 9 | D24: =DATE(A24,B24,C24) -> 44509 | E24: =DATE(A24,B24,C24) -> 44509 | G24: C | H24: {=IFERROR(INDEX(INVESTOR_LIST[INVESTOR NAME],MATCH(I24,INVESTOR_LIST[INVESTOR CODE],0),)," ")} -> BILKISS ARA | I24: A00073 | J24: Unit Capital | L24: 450000
A25: 2021 | B25: 11 | C25: 25 | D25: =DATE(A25,B25,C25) -> 44525 | E25: =DATE(A25,B25,C25) -> 44525 | F25: Unit Subscription - LUMPSUM | G25: C | H25: {=IFERROR(INDEX(INVESTOR_LIST[INVESTOR NAME],MATCH(I25,INVESTOR_LIST[INVESTOR CODE],0),)," ")} -> HARI PADA SAHA | I25: A00002 | J25: Cash and cash equivalents | K25: 200000
A26: 2021 | B26: 11 | C26: 25 | D26: =DATE(A26,B26,C26) -> 44525 | E26: =DATE(A26,B26,C26) -> 44525 | G26: C | H26: {=IFERROR(INDEX(INVESTOR_LIST[INVESTOR NAME],MATCH(I26,INVESTOR_LIST[INVESTOR CODE],0),)," ")} -> HARI PADA SAHA | I26: A00002 | J26: Unit Capital | L26: 200000
A27: 2021 | B27: 12 | C27: 26 | D27: =DATE(A27,B27,C27) -> 44556 | E27: =DATE(A27,B27,C27) -> 44556 | F27: Bank Charges | G27: C | H27: {=IFERROR(INDEX(INVESTOR_LIST[INVESTOR NAME],MATCH(I27,INVESTOR_LIST[INVESTOR CODE],0),)," ")} | J27: Bank charges and excise duties | K27: 10
A28: 2021 | B28: 12 | C28: 26 | D28: =DATE(A28,B28,C28) -> 44556 | E28: =DATE(A28,B28,C28) -> 44556 | G28: C | H28: {=IFERROR(INDEX(INVESTOR_LIST[INVESTOR NAME],MATCH(I28,INVESTOR_LIST[INVESTOR CODE],0),)," ")} | J28: Cash and cash equivalents | L28: 10
A29: 2021 | B29: 12 | C29: 26 | D29: =DATE(A29,B29,C29) -> 44556 | E29: =DATE(A29,B29,C29) -> 44556 | F29: Bank Charges | G29: C | H29: {=IFERROR(INDEX(INVESTOR_LIST[INVESTOR NAME],MATCH(I29,INVESTOR_LIST[INVESTOR CODE],0),)," ")} | J29: Bank charges and excise duties | K29: 10
A30: 2021 | B30: 12 | C30: 26 | D30: =DATE(A30,B30,C30) -> 44556 | E30: =DATE(A30,B30,C30) -> 44556 | G30: C | H30: {=IFERROR(INDEX(INVESTOR_LIST[INVESTOR NAME],MATCH(I30,INVESTOR_LIST[INVESTOR CODE],0),)," ")} | J30: Cash and cash equivalents | L30: 10
A31: 2021 | B31: 12 | C31: 26 | D31: =DATE(A31,B31,C31) -> 44556 | E31: =DATE(A31,B31,C31) -> 44556 | F31: Unit Subscription - LUMPSUM | G31: C | H31: {=IFERROR(INDEX(INVESTOR_LIST[INVESTOR NAME],MATCH(I31,INVESTOR_LIST[INVESTOR CODE],0),)," ")} -> JANNATUL FERDOUS SHARNA | I31: A00301 | J31: Cash and cash equivalents | K31: 200000
A32: 2021 | B32: 12 | C32: 26 | D32: =DATE(A32,B32,C32) -> 44556 | E32: =DATE(A32,B32,C32) -> 44556 | G32: C | H32: {=IFERROR(INDEX(INVESTOR_LIST[INVESTOR NAME],MATCH(I32,INVESTOR_LIST[INVESTOR CODE],0),)," ")} -> JANNATUL FERDOUS SHARNA | I32: A00301 | J32: Unit Capital | L32: 200000
A33: 2021 | B33: 12 | C33: 26 | D33: =DATE(A33,B33,C33) -> 44556 | E33: =DATE(A33,B33,C33) -> 44556 | F33: Unit Subscription - LUMPSUM | G33: C | H33: {=IFERROR(INDEX(INVESTOR_LIST[INVESTOR NAME],MATCH(I33,INVESTOR_LIST[INVESTOR CODE],0),)," ")} -> BIJOY CHANDRA DAS | I33: A00224 | J33: Cash and cash equivalents | K33: 100000
A34: 2021 | B34: 12 | C34: 26 | D34: =DATE(A34,B34,C34) -> 44556 | E34: =DATE(A34,B34,C34) -> 44556 | G34: C | H34: {=IFERROR(INDEX(INVESTOR_LIST[INVESTOR NAME],MATCH(I34,INVESTOR_LIST[INVESTOR CODE],0),)," ")} -> BIJOY CHANDRA DAS | I34: A00224 | J34: Unit Capital | L34: 100000
A35: 2021 | B35: 12 | C35: 30 | D35: =DATE(A35,B35,C35) -> 44560 | E35: =DATE(A35,B35,C35) -> 44560 | F35: Unit Subscription - LUMPSUM | G35: C | H35: {=IFERROR(INDEX(INVESTOR_LIST[INVESTOR NAME],MATCH(I35,INVESTOR_LIST[INVESTOR CODE],0),)," ")} -> SHARMIN JAHAN SHANTA | I35: A00318 | J35: Cash and cash equivalents | K35: 50000
A36: 2021 | B36: 12 | C36: 30 | D36: =DATE(A36,B36,C36) -> 44560 | E36: =DATE(A36,B36,C36) -> 44560 | G36: C | H36: {=IFERROR(INDEX(INVESTOR_LIST[INVESTOR NAME],MATCH(I36,INVESTOR_LIST[INVESTOR CODE],0),)," ")} -> SHARMIN JAHAN SHANTA | I36: A00318 | J36: Unit Capital | L36: 50000
A37: 2021 | B37: 12 | C37: 30 | D37: =DATE(A37,B37,C37) -> 44560 | E37: =DATE(A37,B37,C37) -> 44560 | F37: Bank Charges | G37: C | H37: {=IFERROR(INDEX(INVESTOR_LIST[INVESTOR NAME],MATCH(I37,INVESTOR_LIST[INVESTOR CODE],0),)," ")} | J37: Bank charges and excise duties | K37: 345
A38: 2021 | B38: 12 | C38: 30 | D38: =DATE(A38,B38,C38) -> 44560 | E38: =DATE(A38,B38,C38) -> 44560 | G38: C | H38: {=IFERROR(INDEX(INVESTOR_LIST[INVESTOR NAME],MATCH(I38,INVESTOR_LIST[INVESTOR CODE],0),)," ")} | J38: Cash and cash equivalents | L38: 345
A39: 2021 | B39: 12 | C39: 30 | D39: =DATE(A39,B39,C39) -> 44560 | E39: =DATE(A39,B39,C39) -> 44560 | F39: Interest Income - Bank | G39: C | H39: {=IFERROR(INDEX(INVESTOR_LIST[INVESTOR NAME],MATCH(I39,INVESTOR_LIST[INVESTOR CODE],0),)," ")} | J39: Cash and cash equivalents | K39: 107974
A40: 2021 | B40: 12 | C40: 30 | D40: =DATE(A40,B40,C40) -> 44560 | E40: =DATE(A40,B40,C40) -> 44560 | G40: C | H40: {=IFERROR(INDEX(INVESTOR_LIST[INVESTOR NAME],MATCH(I40,INVESTOR_LIST[INVESTOR CODE],0),)," ")} | J40: Interest Income | L40: 107974
A41: 2021 | B41: 12 | C41: 30 | D41: =DATE(A41,B41,C41) -> 44560 | E41: =DATE(A41,B41,C41) -> 44560 | F41: Bank Charges | G41: C | H41: {=IFERROR(INDEX(INVESTOR_LIST[INVESTOR NAME],MATCH(I41,INVESTOR_LIST[INVESTOR CODE],0),)," ")} | J41: Bank charges and excise duties | K41: 16196
A42: 2021 | B42: 12 | C42: 30 | D42: =DATE(A42,B42,C42) -> 44560 | E42: =DATE(A42,B42,C42) -> 44560 | G42: C | H42: {=IFERROR(INDEX(INVESTOR_LIST[INVESTOR NAME],MATCH(I42,INVESTOR_LIST[INVESTOR CODE],0),)," ")} | J42: Cash and cash equivalents | L42: 16196
A43: 2021 | B43: 12 | C43: 30 | D43: =DATE(A43,B43,C43) -> 44560 | E43: =DATE(A43,B43,C43) -> 44560 | F43: Bank Charges | G43: C | H43: {=IFERROR(INDEX(INVESTOR_LIST[INVESTOR NAME],MATCH(I43,INVESTOR_LIST[INVESTOR CODE],0),)," ")} | J43: Bank charges and excise duties | K43: 15000
A44: 2021 | B44: 12 | C44: 30 | D44: =DATE(A44,B44,C44) -> 44560 | E44: =DATE(A44,B44,C44) -> 44560 | G44: C | H44: {=IFERROR(INDEX(INVESTOR_LIST[INVESTOR NAME],MATCH(I44,INVESTOR_LIST[INVESTOR CODE],0),)," ")} | J44: Cash and cash equivalents | L44: 15000
A45: 2022 | B45: 1 | C45: 3 | D45: =DATE(A45,B45,C45) -> 44564 | E45: =DATE(A45,B45,C45) -> 44564 | F45: Unit Subscription - LUMPSUM | G45: C | H45: {=IFERROR(INDEX(INVESTOR_LIST[INVESTOR NAME],MATCH(I45,INVESTOR_LIST[INVESTOR CODE],0),)," ")} -> THE GSP FINANCE COMPANY (BANGLADESH) LIMITED EMPLOYEES PROVIDENT FUND | I45: A00326 | J45: Cash and cash equivalents | K45: 1000000
A46: 2022 | B46: 1 | C46: 3 | D46: =DATE(A46,B46,C46) -> 44564 | E46: =DATE(A46,B46,C46) -> 44564 | G46: C | H46: {=IFERROR(INDEX(INVESTOR_LIST[INVESTOR NAME],MATCH(I46,INVESTOR_LIST[INVESTOR CODE],0),)," ")} -> THE GSP FINANCE COMPANY (BANGLADESH) LIMITED EMPLOYEES PROVIDENT FUND | I46: A00326 | J46: Unit Capital | L46: 1000000
A47: 2022 | B47: 1 | C47: 3 | D47: =DATE(A47,B47,C47) -> 44564 | E47: =DATE(A47,B47,C47) -> 44564 | F47: Unit Subscription - LUMPSUM | G47: C | H47: {=IFERROR(INDEX(INVESTOR_LIST[INVESTOR NAME],MATCH(I47,INVESTOR_LIST[INVESTOR CODE],0),)," ")} -> MD. MIZANUR RAHMAN | I47: A00319 | J47: Cash and cash equivalents | K47: 200000
A48: 2022 | B48: 1 | C48: 3 | D48: =DATE(A48,B48,C48) -> 44564 | E48: =DATE(A48,B48,C48) -> 44564 | G48: C | H48: {=IFERROR(INDEX(INVESTOR_LIST[INVESTOR NAME],MATCH(I48,INVESTOR_LIST[INVESTOR CODE],0),)," ")} -> MD. MIZANUR RAHMAN | I48: A00319 | J48: Unit Capital | L48: 200000
A49: 2022 | B49: 1 | C49: 3 | D49: =DATE(A49,B49,C49) -> 44564 | E49: =DATE(A49,B49,C49) -> 44564 | F49: Unit Subscription - LUMPSUM | G49: C | H49: {=IFERROR(INDEX(INVESTOR_LIST[INVESTOR NAME],MATCH(I49,INVESTOR_LIST[INVESTOR CODE],0),)," ")} -> MD. WALIULLAH. SWADESH RANJAN SAHA & MD. MIZZNUR RAHMAN | I49: A00251 | J49: Cash and cash equivalents | K49: 170000
A50: 2022 | B50: 1 | C50: 3 | D50: =DATE(A50,B50,C50) -> 44564 | E50: =DATE(A50,B50,C50) -> 44564 | G50: C | H50: {=IFERROR(INDEX(INVESTOR_LIST[INVESTOR NAME],MATCH(I50,INVESTOR_LIST[INVESTOR CODE],0),)," ")} -> MD. WALIULLAH. SWADESH RANJAN SAHA & MD. MIZZNUR RAHMAN | I50: A00251 | J50: Unit Capital | L50: 170000
A51: 2022 | B51: 1 | C51: 3 | D51: =DATE(A51,B51,C51) -> 44564 | E51: =DATE(A51,B51,C51) -> 44564 | F51: Unit Subscription - LUMPSUM | G51: C | H51: {=IFERROR(INDEX(INVESTOR_LIST[INVESTOR NAME],MATCH(I51,INVESTOR_LIST[INVESTOR CODE],0),)," ")} -> MUHAMMAD TANVIR ARAFAT | I51: A00196 | J51: Cash and cash equivalents | K51: 60000
A52: 2022 | B52: 1 | C52: 3 | D52: =DATE(A52,B52,C52) -> 44564 | E52: =DATE(A52,B52,C52) -> 44564 | G52: C | H52: {=IFERROR(INDEX(INVESTOR_LIST[INVESTOR NAME],MATCH(I52,INVESTOR_LIST[INVESTOR CODE],0),)," ")} -> MUHAMMAD TANVIR ARAFAT | I52: A00196 | J52: Unit Capital | L52: 60000
A53: 2022 | B53: 1 | C53: 3 | D53: =DATE(A53,B53,C53) -> 44564 | E53: =DATE(A53,B53,C53) -> 44564 | F53: Bank Charges | G53: C | H53: {=IFERROR(INDEX(INVESTOR_LIST[INVESTOR NAME],MATCH(I53,INVESTOR_LIST[INVESTOR CODE],0),)," ")} | J53: Bank charges and excise duties | K53: 90
A54: 2022 | B54: 1 | C54: 3 | D54: =DATE(A54,B54,C54) -> 44564 | E54: =DATE(A54,B54,C54) -> 44564 | G54: C | H54: {=IFERROR(INDEX(INVESTOR_LIST[INVESTOR NAME],MATCH(I54,INVESTOR_LIST[INVESTOR CODE],0),)," ")} | J54: Cash and cash equivalents | L54: 90
A55: 2022 | B55: 1 | C55: 5 | D55: =DATE(A55,B55,C55) -> 44566 | E55: =DATE(A55,B55,C55) -> 44566 | F55: Unit Subscription - LUMPSUM | G55: C | H55: {=IFERROR(INDEX(INVESTOR_LIST[INVESTOR NAME],MATCH(I55,INVESTOR_LIST[INVESTOR CODE],0),)," ")} -> MD. JAHIRUL ISLAM | I55: A00321 | J55: Cash and cash equivalents | K55: 50000
A56: 2022 | B56: 1 | C56: 5 | D56: =DATE(A56,B56,C56) -> 44566 | E56: =DATE(A56,B56,C56) -> 44566 | G56: C | H56: {=IFERROR(INDEX(INVESTOR_LIST[INVESTOR NAME],MATCH(I56,INVESTOR_LIST[INVESTOR CODE],0),)," ")} -> MD. JAHIRUL ISLAM | I56: A00321 | J56: Unit Capital | L56: 50000
A57: 2022 | B57: 1 | C57: 6 | D57: =DATE(A57,B57,C57) -> 44567 | E57: =DATE(A57,B57,C57) -> 44567 | F57: Unit Subscription - LUMPSUM | G57: C | H57: {=IFERROR(INDEX(INVESTOR_LIST[INVESTOR NAME],MATCH(I57,INVESTOR_LIST[INVESTOR CODE],0),)," ")} -> MD MIZANUR RAHMAN | I57: A00144 | J57: Cash and cash equivalents | K57: 102000
A58: 2022 | B58: 1 | C58: 6 | D58: =DATE(A58,B58,C58) -> 44567 | E58: =DATE(A58,B58,C58) -> 44567 | G58: C | H58: {=IFERROR(INDEX(INVESTOR_LIST[INVESTOR NAME],MATCH(I58,INVESTOR_LIST[INVESTOR CODE],0),)," ")} -> MD MIZANUR RAHMAN | I58: A00144 | J58: Unit Capital | L58: 102000
A59: 2022 | B59: 1 | C59: 10 | D59: =DATE(A59,B59,C59) -> 44571 | E59: =DATE(A59,B59,C59) -> 44571 | F59: Unit Subscription - LUMPSUM | G59: C | H59: {=IFERROR(INDEX(INVESTOR_LIST[INVESTOR NAME],MATCH(I59,INVESTOR_LIST[INVESTOR CODE],0),)," ")} -> MD. ZAKIR HOSSEN | I59: A00018 | J59: Cash and cash equivalents | K59: 202445
A60: 2022 | B60: 1 | C60: 10 | D60: =DATE(A60,B60,C60) -> 44571 | E60: =DATE(A60,B60,C60) -> 44571 | G60: C | H60: {=IFERROR(INDEX(INVESTOR_LIST[INVESTOR NAME],MATCH(I60,INVESTOR_LIST[INVESTOR CODE],0),)," ")} -> MD. ZAKIR HOSSEN | I60: A00018 | J60: Unit Capital | L60: 202450
A61: 2022 | B61: 1 | C61: 10 | D61: =DATE(A61,B61,C61) -> 44571 | E61: =DATE(A61,B61,C61) -> 44571 | G61: C | H61: {=IFERROR(INDEX(INVESTOR_LIST[INVESTOR NAME],MATCH(I61,INVESTOR_LIST[INVESTOR CODE],0),)," ")} -> MD. ZAKIR HOSSEN | I61: A00018 | J61: Unit Premium Reserve | K61: 5
A62: 2022 | B62: 1 | C62: 11 | D62: =DATE(A62,B62,C62) -> 44572 | E62: =DATE(A62,B62,C62) -> 44572 | F62: Bank Charges | G62: C | H62: {=IFERROR(INDEX(INVESTOR_LIST[INVESTOR NAME],MATCH(I62,INVESTOR_LIST[INVESTOR CODE],0),)," ")} | J62: Bank charges and excise duties | K62: 402.5
A63: 2022 | B63: 1 | C63: 11 | D63: =DATE(A63,B63,C63) -> 44572 | E63: =DATE(A63,B63,C63) -> 44572 | G63: C | H63: {=IFERROR(INDEX(INVESTOR_LIST[INVESTOR NAME],MATCH(I63,INVESTOR_LIST[INVESTOR CODE],0),)," ")} | J63: Cash and cash equivalents | L63: 402.5
A64: 2022 | B64: 1 | C64: 13 | D64: =DATE(A64,B64,C64) -> 44574 | E64: =DATE(A64,B64,C64) -> 44574 | F64: Bank Charges | G64: C | H64: {=IFERROR(INDEX(INVESTOR_LIST[INVESTOR NAME],MATCH(I64,INVESTOR_LIST[INVESTOR CODE],0),)," ")} | J64: Bank charges and excise duties | K64: 60
A65: 2022 | B65: 1 | C65: 13 | D65: =DATE(A65,B65,C65) -> 44574 | E65: =DATE(A65,B65,C65) -> 44574 | G65: C | H65: {=IFERROR(INDEX(INVESTOR_LIST[INVESTOR NAME],MATCH(I65,INVESTOR_LIST[INVESTOR CODE],0),)," ")} | J65: Cash and cash equivalents | L65: 60
A66: 2022 | B66: 1 | C66: 13 | D66: =DATE(A66,B66,C66) -> 44574 | E66: =DATE(A66,B66,C66) -> 44574 | F66: Unit Subscription - LUMPSUM | G66: C | H66: {=IFERROR(INDEX(INVESTOR_LIST[INVESTOR NAME],MATCH(I66,INVESTOR_LIST[INVESTOR CODE],0),)," ")} -> MD MIZANUR RAHMAN | I66: A00144 | J66: Cash and cash equivalents | K66: 25000
A67: 2022 | B67: 1 | C67: 13 | D67: =DATE(A67,B67,C67) -> 44574 | E67: =DATE(A67,B67,C67) -> 44574 | G67: C | H67: {=IFERROR(INDEX(INVESTOR_LIST[INVESTOR NAME],MATCH(I67,INVESTOR_LIST[INVESTOR CODE],0),)," ")} -> MD MIZANUR RAHMAN | I67: A00144 | J67: Unit Capital | L67: 25000
A68: 2022 | B68: 1 | C68: 13 | D68: =DATE(A68,B68,C68) -> 44574 | E68: =DATE(A68,B68,C68) -> 44574 | F68: Unit Subscription - LUMPSUM | G68: C | H68: {=IFERROR(INDEX(INVESTOR_LIST[INVESTOR NAME],MATCH(I68,INVESTOR_LIST[INVESTOR CODE],0),)," ")} -> MD. MONIRUZZAMAN | I68: A00113 | J68: Cash and cash equivalents | K68: 200000
A69: 2022 | B69: 1 | C69: 13 | D69: =DATE(A69,B69,C69) -> 44574 | E69: =DATE(A69,B69,C69) -> 44574 | G69: C | H69: {=IFERROR(INDEX(INVESTOR_LIST[INVESTOR NAME],MATCH(I69,INVESTOR_LIST[INVESTOR CODE],0),)," ")} -> MD. MONIRUZZAMAN | I69: A00113 | J69: Unit Capital | L69: 200000
A70: 2022 | B70: 1 | C70: 13 | D70: =DATE(A70,B70,C70) -> 44574 | E70: =DATE(A70,B70,C70) -> 44574 | F70: Unit Subscription - LUMPSUM | G70: C | H70: {=IFERROR(INDEX(INVESTOR_LIST[INVESTOR NAME],MATCH(I70,INVESTOR_LIST[INVESTOR CODE],0),)," ")} -> SAJED MADBAR | I70: A00325 | J70: Cash and cash equivalents | K70: 5000000
A71: 2022 | B71: 1 | C71: 13 | D71: =DATE(A71,B71,C71) -> 44574 | E71: =DATE(A71,B71,C71) -> 44574 | G71: C | H71: {=IFERROR(INDEX(INVESTOR_LIST[INVESTOR NAME],MATCH(I71,INVESTOR_LIST[INVESTOR CODE],0),)," ")} -> SAJED MADBAR | I71: A00325 | J71: Unit Capital | L71: 5000000
A72: 2022 | B72: 1 | C72: 16 | D72: =DATE(A72,B72,C72) -> 44577 | E72: =DATE(A72,B72,C72) -> 44577 | F72: Bank Charges | G72: C | H72: {=IFERROR(INDEX(INVESTOR_LIST[INVESTOR NAME],MATCH(I72,INVESTOR_LIST[INVESTOR CODE],0),)," ")} | J72: Bank charges and excise duties | K72: 120
A73: 2022 | B73: 1 | C73: 16 | D73: =DATE(A73,B73,C73) -> 44577 | E73: =DATE(A73,B73,C73) -> 44577 | G73: C | H73: {=IFERROR(INDEX(INVESTOR_LIST[INVESTOR NAME],MATCH(I73,INVESTOR_LIST[INVESTOR CODE],0),)," ")} | J73: Cash and cash equivalents | L73: 120
A74: 2022 | B74: 1 | C74: 16 | D74: =DATE(A74,B74,C74) -> 44577 | E74: =DATE(A74,B74,C74) -> 44577 | F74: Unit Subscription - LUMPSUM | G74: C | H74: {=IFERROR(INDEX(INVESTOR_LIST[INVESTOR NAME],MATCH(I74,INVESTOR_LIST[INVESTOR CODE],0),)," ")} -> HASIB MUSTABSIR | I74: A00194 | J74: Cash and cash equivalents | K74: 1000000
A75: 2022 | B75: 1 | C75: 16 | D75: =DATE(A75,B75,C75) -> 44577 | E75: =DATE(A75,B75,C75) -> 44577 | G75: C | H75: {=IFERROR(INDEX(INVESTOR_LIST[INVESTOR NAME],MATCH(I75,INVESTOR_LIST[INVESTOR CODE],0),)," ")} -> HASIB MUSTABSIR | I75: A00194 | J75: Unit Capital | L75: 1000000
A76: 2022 | B76: 1 | C76: 16 | D76: =DATE(A76,B76,C76) -> 44577 | E76: =DATE(A76,B76,C76) -> 44577 | F76: Unit Subscription - LUMPSUM | G76: C | H76: {=IFERROR(INDEX(INVESTOR_LIST[INVESTOR NAME],MATCH(I76,INVESTOR_LIST[INVESTOR CODE],0),)," ")} -> MD. SAIFUR RAHMAN | I76: A00123 | J76: Cash and cash equivalents | K76: 1000000
A77: 2022 | B77: 1 | C77: 16 | D77: =DATE(A77,B77,C77) -> 44577 | E77: =DATE(A77,B77,C77) -> 44577 | G77: C | H77: {=IFERROR(INDEX(INVESTOR_LIST[INVESTOR NAME],MATCH(I77,INVESTOR_LIST[INVESTOR CODE],0),)," ")} -> MD. SAIFUR RAHMAN | I77: A00123 | J77: Unit Capital | L77: 1000000
A78: 2022 | B78: 1 | C78: 17 | D78: =DATE(A78,B78,C78) -> 44578 | E78: =DATE(A78,B78,C78) -> 44578 | F78: Bank Charges | G78: C | H78: {=IFERROR(INDEX(INVESTOR_LIST[INVESTOR NAME],MATCH(I78,INVESTOR_LIST[INVESTOR CODE],0),)," ")} | J78: Bank charges and excise duties | K78: 70
A79: 2022 | B79: 1 | C79: 17 | D79: =DATE(A79,B79,C79) -> 44578 | E79: =DATE(A79,B79,C79) -> 44578 | G79: C | H79: {=IFERROR(INDEX(INVESTOR_LIST[INVESTOR NAME],MATCH(I79,INVESTOR_LIST[INVESTOR CODE],0),)," ")} | J79: Cash and cash equivalents | L79: 70
A80: 2022 | B80: 1 | C80: 17 | D80: =DATE(A80,B80,C80) -> 44578 | E80: =DATE(A80,B80,C80) -> 44578 | F80: Unit Subscription - LUMPSUM | G80: C | H80: {=IFERROR(INDEX(INVESTOR_LIST[INVESTOR NAME],MATCH(I80,INVESTOR_LIST[INVESTOR CODE],0),)," ")} -> JHARNA AHMED | I80: A00240 | J80: Cash and cash equivalents | K80: 500000
A81: 2022 | B81: 1 | C81: 17 | D81: =DATE(A81,B81,C81) -> 44578 | E81: =DATE(A81,B81,C81) -> 44578 | G81: C | H81: {=IFERROR(INDEX(INVESTOR_LIST[INVESTOR NAME],MATCH(I81,INVESTOR_LIST[INVESTOR CODE],0),)," ")} -> JHARNA AHMED | I81: A00240 | J81: Unit Capital | L81: 500000
A82: 2022 | B82: 1 | C82: 17 | D82: =DATE(A82,B82,C82) -> 44578 | E82: =DATE(A82,B82,C82) -> 44578 | F82: Unit Subscription - LUMPSUM | G82: C | H82: {=IFERROR(INDEX(INVESTOR_LIST[INVESTOR NAME],MATCH(I82,INVESTOR_LIST[INVESTOR CODE],0),)," ")} -> M.A. MALEK SIDDIQUE WALI & CO. | I82: A00327 | J82: Cash and cash equivalents | K82: 300000
A83: 2022 | B83: 1 | C83: 17 | D83: =DATE(A83,B83,C83) -> 44578 | E83: =DATE(A83,B83,C83) -> 44578 | G83: C | H83: {=IFERROR(INDEX(INVESTOR_LIST[INVESTOR NAME],MATCH(I83,INVESTOR_LIST[INVESTOR CODE],0),)," ")} -> M.A. MALEK SIDDIQUE WALI & CO. | I83: A00327 | J83: Unit Capital | L83: 300000
A84: 2022 | B84: 1 | C84: 18 | D84: =DATE(A84,B84,C84) -> 44579 | E84: =DATE(A84,B84,C84) -> 44579 | F84: Unit Subscription - LUMPSUM | G84: C | H84: {=IFERROR(INDEX(INVESTOR_LIST[INVESTOR NAME],MATCH(I84,INVESTOR_LIST[INVESTOR CODE],0),)," ")} -> SULTANA RAZIA | I84: A00231 | J84: Cash and cash equivalents | K84: 700000
A85: 2022 | B85: 1 | C85: 18 | D85: =DATE(A85,B85,C85) -> 44579 | E85: =DATE(A85,B85,C85) -> 44579 | G85: C | H85: {=IFERROR(INDEX(INVESTOR_LIST[INVESTOR NAME],MATCH(I85,INVESTOR_LIST[INVESTOR CODE],0),)," ")} -> SULTANA RAZIA | I85: A00231 | J85: Unit Capital | L85: 700000
A86: 2022 | B86: 1 | C86: 18 | D86: =DATE(A86,B86,C86) -> 44579 | E86: =DATE(A86,B86,C86) -> 44579 | F86: Bank Charges | G86: C | H86: {=IFERROR(INDEX(INVESTOR_LIST[INVESTOR NAME],MATCH(I86,INVESTOR_LIST[INVESTOR CODE],0),)," ")} | J86: Bank charges and excise duties | K86: 60
A87: 2022 | B87: 1 | C87: 18 | D87: =DATE(A87,B87,C87) -> 44579 | E87: =DATE(A87,B87,C87) -> 44579 | G87: C | H87: {=IFERROR(INDEX(INVESTOR_LIST[INVESTOR NAME],MATCH(I87,INVESTOR_LIST[INVESTOR CODE],0),)," ")} | J87: Cash and cash equivalents | L87: 60
A88: 2022 | B88: 1 | C88: 19 | D88: =DATE(A88,B88,C88) -> 44580 | E88: =DATE(A88,B88,C88) -> 44580 | F88: Bank Charges | G88: C | H88: {=IFERROR(INDEX(INVESTOR_LIST[INVESTOR NAME],MATCH(I88,INVESTOR_LIST[INVESTOR CODE],0),)," ")} | J88: Bank charges and excise duties | K88: 10
A89: 2022 | B89: 1 | C89: 19 | D89: =DATE(A89,B89,C89) -> 44580 | E89: =DATE(A89,B89,C89) -> 44580 | G89: C | H89: {=IFERROR(INDEX(INVESTOR_LIST[INVESTOR NAME],MATCH(I89,INVESTOR_LIST[INVESTOR CODE],0),)," ")} | J89: Cash and cash equivalents | L89: 10
A90: 2022 | B90: 1 | C90: 19 | D90: =DATE(A90,B90,C90) -> 44580 | E90: =DATE(A90,B90,C90) -> 44580 | F90: Unit Subscription - LUMPSUM | G90: C | H90: {=IFERROR(INDEX(INVESTOR_LIST[INVESTOR NAME],MATCH(I90,INVESTOR_LIST[INVESTOR CODE],0),)," ")} -> BISWAS ARIFUR RAHMAN | I90: A00007 | J90: Cash and cash equivalents | K90: 200000
A91: 2022 | B91: 1 | C91: 19 | D91: =DATE(A91,B91,C91) -> 44580 | E91: =DATE(A91,B91,C91) -> 44580 | G91: C | H91: {=IFERROR(INDEX(INVESTOR_LIST[INVESTOR NAME],MATCH(I91,INVESTOR_LIST[INVESTOR CODE],0),)," ")} -> BISWAS ARIFUR RAHMAN | I91: A00007 | J91: Unit Capital | L91: 200000
A92: 2022 | B92: 1 | C92: 20 | D92: =DATE(A92,B92,C92) -> 44581 | E92: =DATE(A92,B92,C92) -> 44581 | F92: Bank Charges | G92: C | H92: {=IFERROR(INDEX(INVESTOR_LIST[INVESTOR NAME],MATCH(I92,INVESTOR_LIST[INVESTOR CODE],0),)," ")} | J92: Bank charges and excise duties | K92: 60
A93: 2022 | B93: 1 | C93: 20 | D93: =DATE(A93,B93,C93) -> 44581 | E93: =DATE(A93,B93,C93) -> 44581 | G93: C | H93: {=IFERROR(INDEX(INVESTOR_LIST[INVESTOR NAME],MATCH(I93,INVESTOR_LIST[INVESTOR CODE],0),)," ")} | J93: Cash and cash equivalents | L93: 60
A94: 2022 | B94: 1 | C94: 20 | D94: =DATE(A94,B94,C94) -> 44581 | E94: =DATE(A94,B94,C94) -> 44581 | F94: Unit Subscription - LUMPSUM | G94: C | H94: {=IFERROR(INDEX(INVESTOR_LIST[INVESTOR NAME],MATCH(I94,INVESTOR_LIST[INVESTOR CODE],0),)," ")} -> AMIT KANTI SARKER | I94: A00158 | J94: Cash and cash equivalents | K94: 1000000
A95: 2022 | B95: 1 | C95: 20 | D95: =DATE(A95,B95,C95) -> 44581 | E95: =DATE(A95,B95,C95) -> 44581 | G95: C | H95: {=IFERROR(INDEX(INVESTOR_LIST[INVESTOR NAME],MATCH(I95,INVESTOR_LIST[INVESTOR CODE],0),)," ")} -> AMIT KANTI SARKER | I95: A00158 | J95: Unit Capital | L95: 1000000
A96: 2022 | B96: 1 | C96: 20 | D96: =DATE(A96,B96,C96) -> 44581 | E96: =DATE(A96,B96,C96) -> 44581 | F96: Unit Subscription - LUMPSUM | G96: C | H96: {=IFERROR(INDEX(INVESTOR_LIST[INVESTOR NAME],MATCH(I96,INVESTOR_LIST[INVESTOR CODE],0),)," ")} -> MD KAMRUL ISLAM | I96: A00189 | J96: Cash and cash equivalents | K96: 500000
A97: 2022 | B97: 1 | C97: 20 | D97: =DATE(A97,B97,C97) -> 44581 | E97: =DATE(A97,B97,C97) -> 44581 | G97: C | H97: {=IFERROR(INDEX(INVESTOR_LIST[INVESTOR NAME],MATCH(I97,INVESTOR_LIST[INVESTOR CODE],0),)," ")} -> MD KAMRUL ISLAM | I97: A00189 | J97: Unit Capital | L97: 500000
A98: 2022 | B98: 1 | C98: 23 | D98: =DATE(A98,B98,C98) -> 44584 | E98: =DATE(A98,B98,C98) -> 44584 | F98: Bank Charges | G98: C | H98: {=IFERROR(INDEX(INVESTOR_LIST[INVESTOR NAME],MATCH(I98,INVESTOR_LIST[INVESTOR CODE],0),)," ")} | J98: Bank charges and excise duties | K98: 120
A99: 2022 | B99: 1 | C99: 23 | D99: =DATE(A99,B99,C99) -> 44584 | E99: =DATE(A99,B99,C99) -> 44584 | G99: C | H99: {=IFERROR(INDEX(INVESTOR_LIST[INVESTOR NAME],MATCH(I99,INVESTOR_LIST[INVESTOR CODE],0),)," ")} | J99: Cash and cash equivalents | L99: 120
A100: 2022 | B100: 1 | C100: 23 | D100: =DATE(A100,B100,C100) -> 44584 | E100: =DATE(A100,B100,C100) -> 44584 | F100: Unit Subscription - LUMPSUM | G100: C | H100: {=IFERROR(INDEX(INVESTOR_LIST[INVESTOR NAME],MATCH(I100,INVESTOR_LIST[INVESTOR CODE],0),)," ")} -> RAJIB ROY | I100: A00041 | J100: Cash and cash equivalents | K100: 150000
A101: 2022 | B101: 1 | C101: 23 | D101: =DATE(A101,B101,C101) -> 44584 | E101: =DATE(A101,B101,C101) -> 44584 | G101: C | H101: {=IFERROR(INDEX(INVESTOR_LIST[INVESTOR NAME],MATCH(I101,INVESTOR_LIST[INVESTOR CODE],0),)," ")} -> RAJIB ROY | I101: A00041 | J101: Unit Capital | L101: 150000
...

Sheet TB-C
A1: Check of Trial Balance | G1: =SUM(H7:H88)-SUM(I7:I88) -> 0.035499945
A2: Check of Balance Sheet | G2: =BS!C25-BS!C41 -> 0
A3: Check of Cash Balance | G3: =BS!C23-CF!B44 -> -3620314.1
B5: Desired Reporting Period | H5: During the Reporting Period | J5: For Balance Sheet | N5: For Retained Earnings
B6: Year | C6: Month | D6: Day | E6: Value | F6: Value | G6: Accounts | H6: Debit | I6: Credit | J6: Carry Forward Balance | K6: Carry Forward Balance | L6: On date | M6: On date | N6: Debit | O6: Credit
A7: Beginning | B7: 2026 | C7: 1 | D7: 1 | E7: =DATE(B7,C7,D7)-1 -> 46022 | F7: =DATE(B7,C7,D7) -> 46023 | G7: ='Chart of Accounts'!B3 -> Investments in stock | H7: =MAX(0,SUMIFS(Journals!$K$9:$K$1005679,Journals!$D$9:$D$1005679,">"&$E$7,Journals!$D$9:$D$1005679,"<"&$E$8,Journals!$J$9:$J$1005679,"investments in stock")-SUMIFS(Journals!$L$9:$L$1005679,Journals!$D$9:$D$1005679,">"&$E$7,Journals!$D$9:$D$1005679,"<"&$E$8,Journals!$J$9:$J$1005679,"investments in stock")) -> 34499330 | I7: =MAX(0,SUMIFS(Journals!$L$9:$L$1005679,Journals!$D$9:$D$1005679,">"&$E$7,Journals!$D$9:$D$1005679,"<"&$E$8,Journals!$J$9:$J$1005679,"Investments in stock")-SUMIFS(Journals!$K$9:$K$1005679,Journals!$D$9:$D$1005679,">"&$E$7,Journals!$D$9:$D$1005679,"<"&$E$8,Journals!$J$9:$J$1005679,"Investments in stock")) -> 0 | J7: =SUMIFS(Journals!$K$9:$K$1005679,Journals!$D$9:$D$1005679,"<"&$F$7,Journals!$J$9:$J$1005679,"investments in stock")-SUMIFS(Journals!$L$9:$L$1005679,Journals!$D$9:$D$1005679,"<"&$F$7,Journals!$J$9:$J$1005679,"investments in stock") -> 2.0327918e+08 | L7: =J7+H7-I7 -> 2.3777851e+08
A8: Ending | B8: 2026 | C8: 12 | D8: 31 | E8: =DATE(B8,C8,D8)+1 -> 46388 | F8: =DATE(B8,C8,D8) -> 46387 | G8: ='Chart of Accounts'!B4 -> Interest Receivables from Bank A/C | H8: =MAX(0,SUMIFS(Journals!$K$9:$K$1005679,Journals!$D$9:$D$1005679,">"&$E$7,Journals!$D$9:$D$1005679,"<"&$E$8,Journals!$J$9:$J$1005679,"Interest Receivables from Bank A/C")-SUMIFS(Journals!$L$9:$L$1005679,Journals!$D$9:$D$1005679,">"&$E$7,Journals!$D$9:$D$1005679,"<"&$E$8,Journals!$J$9:$J$1005679,"Interest Receivables from Bank A/C")) -> 75951.562 | I8: =MAX(0,SUMIFS(Journals!$L$9:$L$1005679,Journals!$D$9:$D$1005679,">"&$E$7,Journals!$D$9:$D$1005679,"<"&$E$8,Journals!$J$9:$J$1005679,"Interest Receivables from Bank A/C")-SUMIFS(Journals!$K$9:$K$1005679,Journals!$D$9:$D$1005679,">"&$E$7,Journals!$D$9:$D$1005679,"<"&$E$8,Journals!$J$9:$J$1005679,"Interest Receivables from Bank A/C")) -> 0 | J8: =SUMIFS(Journals!$K$9:$K$1005679,Journals!$D$9:$D$1005679,"<"&$F$7,Journals!$J$9:$J$1005679,"Interest Receivables from Bank A/C")-SUMIFS(Journals!$L$9:$L$1005679,Journals!$D$9:$D$1005679,"<"&$F$7,Journals!$J$9:$J$1005679,"Interest Receivables from Bank A/C") -> 10693.788 | L8: =J8+H8-I8 -> 86645.35
G9: ='Chart of Accounts'!B5 -> Preliminary & issue expenses | H9: =MAX(0,SUMIFS(Journals!$K$9:$K$1005679,Journals!$D$9:$D$1005679,">"&$E$7,Journals!$D$9:$D$1005679,"<"&$E$8,Journals!$J$9:$J$1005679,"Preliminary & issue expenses")-SUMIFS(Journals!$L$9:$L$1005679,Journals!$D$9:$D$1005679,">"&$E$7,Journals!$D$9:$D$1005679,"<"&$E$8,Journals!$J$9:$J$1005679,"Preliminary & issue expenses")) -> 0 | I9: =MAX(0,SUMIFS(Journals!$L$9:$L$1005679,Journals!$D$9:$D$1005679,">"&$E$7,Journals!$D$9:$D$1005679,"<"&$E$8,Journals!$J$9:$J$1005679,"Preliminary & issue expenses")-SUMIFS(Journals!$K$9:$K$1005679,Journals!$D$9:$D$1005679,">"&$E$7,Journals!$D$9:$D$1005679,"<"&$E$8,Journals!$J$9:$J$1005679,"Preliminary & issue expenses")) -> 32967.033 | J9: =SUMIFS(Journals!$K$9:$K$1005679,Journals!$D$9:$D$1005679,"<"&$F$7,Journals!$J$9:$J$1005679,"Preliminary & issue expenses")-SUMIFS(Journals!$L$9:$L$1005679,Journals!$D$9:$D$1005679,"<"&$F$7,Journals!$J$9:$J$1005679,"Preliminary & issue expenses") -> 445054.95 | L9: =J9+H9-I9 -> 412087.91
G10: ='Chart of Accounts'!B6 -> Accrued Management Fee | H10: =SUMIFS(Journals!$K$9:$K$1005679,Journals!$D$9:$D$1005679,">"&$E$7,Journals!$D$9:$D$1005679,"<"&$E$8,Journals!$J$9:$J$1005679,"Accrued Management Fee") -> 1235848 | I10: =MAX(0,SUMIFS(Journals!$L$9:$L$1005679,Journals!$D$9:$D$1005679,">"&$E$7,Journals!$D$9:$D$1005679,"<"&$E$8,Journals!$J$9:$J$1005679,"Accrued Management Fee")) -> 1183783.6 | K10: =SUMIFS(Journals!$L$9:$L$1005679,Journals!$D$9:$D$1005679,"<"&$F$7,Journals!$J$9:$J$1005679,"Accrued Management Fee")-SUMIFS(Journals!$K$9:$K$1005679,Journals!$D$9:$D$1005679,"<"&$F$7,Journals!$J$9:$J$1005679,"Accrued Management Fee") -> 775470.14 | M10: =K10+I10-H10 -> 723405.79
G11: Accrued Trustee Fee | H11: =SUMIFS(Journals!$K$9:$K$1005679,Journals!$D$9:$D$1005679,">"&$E$7,Journals!$D$9:$D$1005679,"<"&$E$8,Journals!$J$9:$J$1005679,"Accrued Trustee Fee") -> 0 | I11: =MAX(0,SUMIFS(Journals!$L$9:$L$1005679,Journals!$D$9:$D$1005679,">"&$E$7,Journals!$D$9:$D$1005679,"<"&$E$8,Journals!$J$9:$J$1005679,"Accrued Trustee Fee")) -> 56977.77 | K11: =SUMIFS(Journals!$L$9:$L$1005679,Journals!$D$9:$D$1005679,"<"&$F$7,Journals!$J$9:$J$1005679,"Accrued Trustee Fee")-SUMIFS(Journals!$K$9:$K$1005679,Journals!$D$9:$D$1005679,"<"&$F$7,Journals!$J$9:$J$1005679,"Accrued Trustee Fee") -> 108026.58 | M11: =K11+I11-H11 -> 165004.35
G12: ='Chart of Accounts'!B8 -> Accrued Custodian Fee | H12: =MAX(0,SUMIFS(Journals!$K$9:$K$1005679,Journals!$D$9:$D$1005679,">"&$E$7,Journals!$D$9:$D$1005679,"<"&$E$8,Journals!$J$9:$J$1005679,"accrued custodian fee")-SUMIFS(Journals!$L$9:$L$1005679,Journals!$D$9:$D$1005679,">"&$E$7,Journals!$D$9:$D$1005679,"<"&$E$8,Journals!$J$9:$J$1005679,"accrued custodian fee")) -> 0 | I12: =MAX(0,SUMIFS(Journals!$L$9:$L$1005679,Journals!$D$9:$D$1005679,">"&$E$7,Journals!$D$9:$D$1005679,"<"&$E$8,Journals!$J$9:$J$1005679,"accrued custodian fee")-SUMIFS(Journals!$K$9:$K$1005679,Journals!$D$9:$D$1005679,">"&$E$7,Journals!$D$9:$D$1005679,"<"&$E$8,Journals!$J$9:$J$1005679,"accrued custodian fee")) -> 0 | K12: =SUMIFS(Journals!$L$9:$L$1005679,Journals!$D$9:$D$1005679,"<"&$F$7,Journals!$J$9:$J$1005679,"Accrued Custodian Fee")-SUMIFS(Journals!$K$9:$K$1005679,Journals!$D$9:$D$1005679,"<"&$F$7,Journals!$J$9:$J$1005679,"Accrued Custodian Fee") -> 0 | M12: =K12+I12-H12 -> 0
G13: ='Chart of Accounts'!B9 -> Accrued BSEC fee | H13: =MAX(0,SUMIFS(Journals!$K$9:$K$1005679,Journals!$D$9:$D$1005679,">"&$E$7,Journals!$D$9:$D$1005679,"<"&$E$8,Journals!$J$9:$J$1005679,"accrued bsec fee")-SUMIFS(Journals!$L$9:$L$1005679,Journals!$D$9:$D$1005679,">"&$E$7,Journals!$D$9:$D$1005679,"<"&$E$8,Journals!$J$9:$J$1005679,"accrued bsec fee")) -> 0 | I13: =MAX(0,SUMIFS(Journals!$L$9:$L$1005679,Journals!$D$9:$D$1005679,">"&$E$7,Journals!$D$9:$D$1005679,"<"&$E$8,Journals!$J$9:$J$1005679,"accrued bsec fee")-SUMIFS(Journals!$K$9:$K$1005679,Journals!$D$9:$D$1005679,">"&$E$7,Journals!$D$9:$D$1005679,"<"&$E$8,Journals!$J$9:$J$1005679,"accrued bsec fee")) -> 0 | K13: =SUMIFS(Journals!$L$9:$L$1005679,Journals!$D$9:$D$1005679,"<"&$F$7,Journals!$J$9:$J$1005679,"accrued bsec fee")-SUMIFS(Journals!$K$9:$K$1005679,Journals!$D$9:$D$1005679,"<"&$F$7,Journals!$J$9:$J$1005679,"accrued bsec fee") -> 0 | M13: =K13+I13-H13 -> 0
G14: ='Chart of Accounts'!B10 -> Accrued Audit Fee | H14: =MAX(0,SUMIFS(Journals!$K$9:$K$1005679,Journals!$D$9:$D$1005679,">"&$E$7,Journals!$D$9:$D$1005679,"<"&$E$8,Journals!$J$9:$J$1005679,"accrued audit fee")) -> 57500 | I14: =MAX(0,SUMIFS(Journals!$L$9:$L$1005679,Journals!$D$9:$D$1005679,">"&$E$7,Journals!$D$9:$D$1005679,"<"&$E$8,Journals!$J$9:$J$1005679,"accrued audit fee")) -> 0 | K14: =SUMIFS(Journals!$L$9:$L$1005679,Journals!$D$9:$D$1005679,"<"&$F$7,Journals!$J$9:$J$1005679,"accrued audit fee")-SUMIFS(Journals!$K$9:$K$1005679,Journals!$D$9:$D$1005679,"<"&$F$7,Journals!$J$9:$J$1005679,"accrued audit fee") -> 57500 | M14: =K14+I14-H14 -> 0
G15: ='Chart of Accounts'!B11 -> Accrued CDBL Fee | H15: =MAX(0,SUMIFS(Journals!$K$9:$K$1005679,Journals!$D$9:$D$1005679,">"&$E$7,Journals!$D$9:$D$1005679,"<"&$E$8,Journals!$J$9:$J$1005679,"accrued CDBL fee")-SUMIFS(Journals!$L$9:$L$1005679,Journals!$D$9:$D$1005679,">"&$E$7,Journals!$D$9:$D$1005679,"<"&$E$8,Journals!$J$9:$J$1005679,"accrued CDBL fee")) -> 0 | I15: =MAX(0,SUMIFS(Journals!$L$9:$L$1005679,Journals!$D$9:$D$1005679,">"&$E$7,Journals!$D$9:$D$1005679,"<"&$E$8,Journals!$J$9:$J$1005679,"accrued CDBL fee")-SUMIFS(Journals!$K$9:$K$1005679,Journals!$D$9:$D$1005679,">"&$E$7,Journals!$D$9:$D$1005679,"<"&$E$8,Journals!$J$9:$J$1005679,"accrued CDBL fee")) -> 0 | K15: =SUMIFS(Journals!$L$9:$L$1005679,Journals!$D$9:$D$1005679,"<"&$F$7,Journals!$J$9:$J$1005679,"accrued cdbl fee")-SUMIFS(Journals!$K$9:$K$1005679,Journals!$D$9:$D$1005679,"<"&$F$7,Journals!$J$9:$J$1005679,"accrued cdbl fee") -> 0 | M15: =K15+I15-H15 -> 0
G16: ='Chart of Accounts'!B12 -> Fixed Deposit Receipts (FDR) | H16: =MAX(0,SUMIFS(Journals!$K$9:$K$1005679,Journals!$D$9:$D$1005679,">"&$E$7,Journals!$D$9:$D$1005679,"<"&$E$8,Journals!$J$9:$J$1005679,"Fixed Deposit Receipts (FDR)")-SUMIFS(Journals!$L$9:$L$1005679,Journals!$D$9:$D$1005679,">"&$E$7,Journals!$D$9:$D$1005679,"<"&$E$8,Journals!$J$9:$J$1005679,"Fixed Deposit Receipts (FDR)")) -> 0 | I16: =MAX(0,SUMIFS(Journals!$L$9:$L$1005679,Journals!$D$9:$D$1005679,">"&$E$7,Journals!$D$9:$D$1005679,"<"&$E$8,Journals!$J$9:$J$1005679,"Fixed Deposit Receipts (FDR)")-SUMIFS(Journals!$K$9:$K$1005679,Journals!$D$9:$D$1005679,">"&$E$7,Journals!$D$9:$D$1005679,"<"&$E$8,Journals!$J$9:$J$1005679,"Fixed Deposit Receipts (FDR)")) -> 9000000 | J16: =SUMIFS(Journals!$K$9:$K$1005679,Journals!$D$9:$D$1005679,"<"&$F$7,Journals!$J$9:$J$1005679,"Fixed Deposit Receipts (FDR)")-SUMIFS(Journals!$L$9:$L$1005679,Journals!$D$9:$D$1005679,"<"&$F$7,Journals!$J$9:$J$1005679,"Fixed Deposit Receipts (FDR)") -> 13000000 | L16: =J16+H16-I16 -> 4000000
G17: ='Chart of Accounts'!B13 -> Cash and cash equivalents | H17: =MAX(0,SUMIFS(Journals!$K$9:$K$1005679,Journals!$D$9:$D$1005679,">"&$E$7,Journals!$D$9:$D$1005679,"<"&$E$8,Journals!$J$9:$J$1005679,"Cash and cash equivalents")-SUMIFS(Journals!$L$9:$L$1005679,Journals!$D$9:$D$1005679,">"&$E$7,Journals!$D$9:$D$1005679,"<"&$E$8,Journals!$J$9:$J$1005679,"Cash and cash equivalents")) -> 1793058 | I17: =MAX(0,SUMIFS(Journals!$L$9:$L$1005679,Journals!$D$9:$D$1005679,">"&$E$7,Journals!$D$9:$D$1005679,"<"&$E$8,Journals!$J$9:$J$1005679,"Cash and cash equivalents")-SUMIFS(Journals!$K$9:$K$1005679,Journals!$D$9:$D$1005679,">"&$E$7,Journals!$D$9:$D$1005679,"<"&$E$8,Journals!$J$9:$J$1005679,"Cash and cash equivalents")) -> 0 | J17: =SUMIFS(Journals!$K$9:$K$1005679,Journals!$D$9:$D$1005679,"<"&$F$7,Journals!$J$9:$J$1005679,"Cash and cash equivalents")-SUMIFS(Journals!$L$9:$L$1005679,Journals!$D$9:$D$1005679,"<"&$F$7,Journals!$J$9:$J$1005679,"Cash and cash equivalents") -> 512242.08 | L17: =J17+H17-I17 -> 2305300.1
G18: ='Chart of Accounts'!B14 -> Unit Capital | H18: =SUMIFS(Journals!$K$9:$K$1005679,Journals!$D$9:$D$1005679,">"&$E$7,Journals!$D$9:$D$1005679,"<"&$E$8,Journals!$J$9:$J$1005679,"unit capital") -> 10022120 | I18: =MAX(0,SUMIFS(Journals!$L$9:$L$1005679,Journals!$D$9:$D$1005679,">"&$E$7,Journals!$D$9:$D$1005679,"<"&$E$8,Journals!$J$9:$J$1005679,"unit capital")) -> 29659190 | K18: =SUMIFS(Journals!$L$9:$L$1005679,Journals!$D$9:$D$1005679,"<"&$F$7,Journals!$J$9:$J$1005679,"unit capital")-SUMIFS(Journals!$K$9:$K$1005679,Journals!$D$9:$D$1005679,"<"&$F$7,Journals!$J$9:$J$1005679,"unit capital") -> 188935970 | M18: =K18+I18-H18 -> 208573040
G19: ='Chart of Accounts'!B15 -> Unit premium reserve | H19: =SUMIFS(Journals!$K$9:$K$1005679,Journals!$D$9:$D$1005679,">"&$E$7,Journals!$D$9:$D$1005679,"<"&$E$8,Journals!$J$9:$J$1005679,"unit premium reserve") -> 2739914 | I19: =SUMIFS(Journals!$L$9:$L$1005679,Journals!$D$9:$D$1005679,">"&$E$7,Journals!$D$9:$D$1005679,"<"&$E$8,Journals!$J$9:$J$1005679,"unit premium reserve") -> 7480353.9 | K19: =SUMIFS(Journals!$L$9:$L$1005679,Journals!$D$9:$D$1005679,"<"&$F$7,Journals!$J$9:$J$1005679,"unit premium reserve")-SUMIFS(Journals!$K$9:$K$1005679,Journals!$D$9:$D$1005679,"<"&$F$7,Journals!$J$9:$J$1005679,"unit premium reserve") -> 2503906.3 | M19: =K19+I19-H19 -> 7244346.2
G20: ='Chart of Accounts'!B16 -> Interest income | H20: =MAX(0,SUMIFS(Journals!$K$9:$K$1005679,Journals!$D$9:$D$1005679,">"&$E$7,Journals!$D$9:$D$1005679,"<"&$E$8,Journals!$J$9:$J$1005679,"interest income")-SUMIFS(Journals!$L$9:$L$1005679,Journals!$D$9:$D$1005679,">"&$E$7,Journals!$D$9:$D$1005679,"<"&$E$8,Journals!$J$9:$J$1005679,"interest income")) -> 0 | I20: =MAX(0,SUMIFS(Journals!$L$9:$L$1005679,Journals!$D$9:$D$1005679,">"&$E$7,Journals!$D$9:$D$1005679,"<"&$E$8,Journals!$J$9:$J$1005679,"interest income")-SUMIFS(Journals!$K$9:$K$1005679,Journals!$D$9:$D$1005679,">"&$E$7,Journals!$D$9:$D$1005679,"<"&$E$8,Journals!$J$9:$J$1005679,"interest income")) -> 0 | O20: =SUMIFS(Journals!$L$9:$L$1011558,Journals!$D$9:$D$1011558,"<"&$F$7,Journals!$J$9:$J$1011558,"interest income")-SUMIFS(Journals!$K$9:$K$1011558,Journals!$D$9:$D$1011558,"<"&$F$7,Journals!$J$9:$J$1011558,"interest income") -> 21944826
G21: Interest Income from FDR | H21: =MAX(0,SUMIFS(Journals!$K$9:$K$1005679,Journals!$D$9:$D$1005679,">"&$E$7,Journals!$D$9:$D$1005679,"<"&$E$8,Journals!$J$9:$J$1005679,"Interest Income from FDR")-SUMIFS(Journals!$L$9:$L$1005679,Journals!$D$9:$D$1005679,">"&$E$7,Journals!$D$9:$D$1005679,"<"&$E$8,Journals!$J$9:$J$1005679,"Interest Income from FDR")) -> 0 | I21: =MAX(0,SUMIFS(Journals!$L$9:$L$1005679,Journals!$D$9:$D$1005679,">"&$E$7,Journals!$D$9:$D$1005679,"<"&$E$8,Journals!$J$9:$J$1005679,"Interest Income from FDR")-SUMIFS(Journals!$K$9:$K$1005679,Journals!$D$9:$D$1005679,">"&$E$7,Journals!$D$9:$D$1005679,"<"&$E$8,Journals!$J$9:$J$1005679,"Interest Income from FDR")) -> 334458.33 | O21: =SUMIFS(Journals!$L$9:$L$1005679,Journals!$D$9:$D$1005679,"<"&$F$7,Journals!$J$9:$J$1005679,"Interest Income from FDR")-SUMIFS(Journals!$K$9:$K$1005679,Journals!$D$9:$D$1005679,"<"&$F$7,Journals!$J$9:$J$1005679,"Interest Income from FDR") -> 0
G22: Interest Income from Renata Pre. Share | H22: =MAX(0,SUMIFS(Journals!$K$9:$K$1005679,Journals!$D$9:$D$1005679,">"&$E$7,Journals!$D$9:$D$1005679,"<"&$E$8,Journals!$J$9:$J$1005679,"Interest Income from Renata Pre. Share")-SUMIFS(Journals!$L$9:$L$1005679,Journals!$D$9:$D$1005679,">"&$E$7,Journals!$D$9:$D$1005679,"<"&$E$8,Journals!$J$9:$J$1005679,"Interest Income from Renata Pre. Share")) -> 0 | I22: =MAX(0,SUMIFS(Journals!$L$9:$L$1005679,Journals!$D$9:$D$1005679,">"&$E$7,Journals!$D$9:$D$1005679,"<"&$E$8,Journals!$J$9:$J$1005679,"Interest Income from Renata Pre. Share")-SUMIFS(Journals!$K$9:$K$1005679,Journals!$D$9:$D$1005679,">"&$E$7,Journals!$D$9:$D$1005679,"<"&$E$8,Journals!$J$9:$J$1005679,"Interest Income from Renata Pre. Share")) -> 519576.92 | O22: =SUMIFS(Journals!$L$9:$L$1005679,Journals!$D$9:$D$1005679,"<"&$F$7,Journals!$J$9:$J$1005679,"Interest Income from Renata Pre. Share")-SUMIFS(Journals!$K$9:$K$1005679,Journals!$D$9:$D$1005679,"<"&$F$7,Journals!$J$9:$J$1005679,"Interest Income from Renata Pre. Share") -> 402053.57
G23: Interest Income from Bank Acc | H23: =MAX(0,SUMIFS(Journals!$K$9:$K$1005679,Journals!$D$9:$D$1005679,">"&$E$7,Journals!$D$9:$D$1005679,"<"&$E$8,Journals!$J$9:$J$1005679,"Interest Income from Bank Acc")-SUMIFS(Journals!$L$9:$L$1005679,Journals!$D$9:$D$1005679,">"&$E$7,Journals!$D$9:$D$1005679,"<"&$E$8,Journals!$J$9:$J$1005679,"Interest Income from Bank Acc")) -> 0 | I23: =MAX(0,SUMIFS(Journals!$L$9:$L$1005679,Journals!$D$9:$D$1005679,">"&$E$7,Journals!$D$9:$D$1005679,"<"&$E$8,Journals!$J$9:$J$1005679,"Interest Income from Bank Acc")-SUMIFS(Journals!$K$9:$K$1005679,Journals!$D$9:$D$1005679,">"&$E$7,Journals!$D$9:$D$1005679,"<"&$E$8,Journals!$J$9:$J$1005679,"Interest Income from Bank Acc")) -> 75951.562 | O23: =SUMIFS(Journals!$L$9:$L$1005679,Journals!$D$9:$D$1005679,"<"&$F$7,Journals!$J$9:$J$1005679,"Interest Income from Bank Acc")-SUMIFS(Journals!$K$9:$K$1005679,Journals!$D$9:$D$1005679,"<"&$F$7,Journals!$J$9:$J$1005679,"Interest Income from Bank Acc") -> 0
G24: Interest Income from T-Bill | H24: =MAX(0,SUMIFS(Journals!$K$9:$K$1005679,Journals!$D$9:$D$1005679,">"&$E$7,Journals!$D$9:$D$1005679,"<"&$E$8,Journals!$J$9:$J$1005679,"Interest Income from T-Bill")-SUMIFS(Journals!$L$9:$L$1005679,Journals!$D$9:$D$1005679,">"&$E$7,Journals!$D$9:$D$1005679,"<"&$E$8,Journals!$J$9:$J$1005679,"Interest Income from T-Bill")) -> 0 | I24: =MAX(0,SUMIFS(Journals!$L$9:$L$1005679,Journals!$D$9:$D$1005679,">"&$E$7,Journals!$D$9:$D$1005679,"<"&$E$8,Journals!$J$9:$J$1005679,"Interest Income from T-Bill")-SUMIFS(Journals!$K$9:$K$1005679,Journals!$D$9:$D$1005679,">"&$E$7,Journals!$D$9:$D$1005679,"<"&$E$8,Journals!$J$9:$J$1005679,"Interest Income from T-Bill")) -> 0 | O24: =SUMIFS(Journals!$L$9:$L$1005679,Journals!$D$9:$D$1005679,"<"&$F$7,Journals!$J$9:$J$1005679,"Interest Income from T-Bill")-SUMIFS(Journals!$K$9:$K$1005679,Journals!$D$9:$D$1005679,"<"&$F$7,Journals!$J$9:$J$1005679,"Interest Income from T-Bill") -> 0
G25: Interest Income from T-Bond | H25: =MAX(0,SUMIFS(Journals!$K$9:$K$1005679,Journals!$D$9:$D$1005679,">"&$E$7,Journals!$D$9:$D$1005679,"<"&$E$8,Journals!$J$9:$J$1005679,"Interest Income from T-Bond")-SUMIFS(Journals!$L$9:$L$1005679,Journals!$D$9:$D$1005679,">"&$E$7,Journals!$D$9:$D$1005679,"<"&$E$8,Journals!$J$9:$J$1005679,"Interest Income from T-Bond")) -> 0 | I25: =MAX(0,SUMIFS(Journals!$L$9:$L$1005679,Journals!$D$9:$D$1005679,">"&$E$7,Journals!$D$9:$D$1005679,"<"&$E$8,Journals!$J$9:$J$1005679,"Interest Income from T-Bond")-SUMIFS(Journals!$K$9:$K$1005679,Journals!$D$9:$D$1005679,">"&$E$7,Journals!$D$9:$D$1005679,"<"&$E$8,Journals!$J$9:$J$1005679,"Interest Income from T-Bond")) -> 0 | O25: =SUMIFS(Journals!$L$9:$L$1005679,Journals!$D$9:$D$1005679,"<"&$F$7,Journals!$J$9:$J$1005679,"Interest Income from T-Bond")-SUMIFS(Journals!$K$9:$K$1005679,Journals!$D$9:$D$1005679,"<"&$F$7,Journals!$J$9:$J$1005679,"Interest Income from T-Bond") -> 1841200
G26: ='Chart of Accounts'!B17 -> Bank charges and excise duties | H26: =MAX(0,SUMIFS(Journals!$K$9:$K$1005679,Journals!$D$9:$D$1005679,">"&$E$7,Journals!$D$9:$D$1005679,"<"&$E$8,Journals!$J$9:$J$1005679,"Bank charges and excise duties")-SUMIFS(Journals!$L$9:$L$1005679,Journals!$D$9:$D$1005679,">"&$E$7,Journals!$D$9:$D$1005679,"<"&$E$8,Journals!$J$9:$J$1005679,"Bank charges and excise duties")) -> 25803 | I26: =MAX(0,SUMIFS(Journals!$L$9:$L$1005679,Journals!$D$9:$D$1005679,">"&$E$7,Journals!$D$9:$D$1005679,"<"&$E$8,Journals!$J$9:$J$1005679,"Bank charges and excise duties")-SUMIFS(Journals!$K$9:$K$1005679,Journals!$D$9:$D$1005679,">"&$E$7,Journals!$D$9:$D$1005679,"<"&$E$8,Journals!$J$9:$J$1005679,"Bank charges and excise duties")) -> 0 | N26: =SUMIFS(Journals!$K$9:$K$1005679,Journals!$D$9:$D$1005679,"<"&$F$7,Journals!$J$9:$J$1005679,"Bank charges and excise duties")-SUMIFS(Journals!$L$9:$L$1005679,Journals!$D$9:$D$1005679,"<"&$F$7,Journals!$J$9:$J$1005679,"Bank charges and excise duties") -> 702242.76
G27: ='Chart of Accounts'!B18 -> Brokerage commission | H27: =MAX(0,SUMIFS(Journals!$K$9:$K$1005679,Journals!$D$9:$D$1005679,">"&$E$7,Journals!$D$9:$D$1005679,"<"&$E$8,Journals!$J$9:$J$1005679,"brokerage commission")-SUMIFS(Journals!$L$9:$L$1005679,Journals!$D$9:$D$1005679,">"&$E$7,Journals!$D$9:$D$1005679,"<"&$E$8,Journals!$J$9:$J$1005679,"brokerage commission")) -> 479495.29 | I27: =MAX(0,SUMIFS(Journals!$L$9:$L$1005679,Journals!$D$9:$D$1005679,">"&$E$7,Journals!$D$9:$D$1005679,"<"&$E$8,Journals!$J$9:$J$1005679,"brokerage commission")-SUMIFS(Journals!$K$9:$K$1005679,Journals!$D$9:$D$1005679,">"&$E$7,Journals!$D$9:$D$1005679,"<"&$E$8,Journals!$J$9:$J$1005679,"brokerage commission")) -> 0 | N27: =SUMIFS(Journals!$K$9:$K$1005679,Journals!$D$9:$D$1005679,"<"&$F$7,Journals!$J$9:$J$1005679,"brokerage commission")-SUMIFS(Journals!$L$9:$L$1005679,Journals!$D$9:$D$1005679,"<"&$F$7,Journals!$J$9:$J$1005679,"brokerage commission") -> 1991875.8
G28: ='Chart of Accounts'!B19 -> Unrealized gain on securities | H28: =MAX(0,SUMIFS(Journals!$K$9:$K$1005679,Journals!$D$9:$D$1005679,">"&$E$7,Journals!$D$9:$D$1005679,"<"&$E$8,Journals!$J$9:$J$1005679,"Unrealized gain on securities")-SUMIFS(Journals!$L$9:$L$1005679,Journals!$D$9:$D$1005679,">"&$E$7,Journals!$D$9:$D$1005679,"<"&$E$8,Journals!$J$9:$J$1005679,"Unrealized gain on securities")) -> 0 | I28: =MAX(0,SUMIFS(Journals!$L$9:$L$1005679,Journals!$D$9:$D$1005679,">"&$E$7,Journals!$D$9:$D$1005679,"<"&$E$8,Journals!$J$9:$J$1005679,"Unrealized gain on securities")-SUMIFS(Journals!$K$9:$K$1005679,Journals!$D$9:$D$1005679,">"&$E$7,Journals!$D$9:$D$1005679,"<"&$E$8,Journals!$J$9:$J$1005679,"Unrealized gain on securities")) -> 8735993.6 | O28: =SUMIFS(Journals!$L$9:$L$1005679,Journals!$D$9:$D$1005679,"<"&$F$7,Journals!$J$9:$J$1005679,"unrealized gain on securities")-SUMIFS(Journals!$K$9:$K$1005679,Journals!$D$9:$D$1005679,"<"&$F$7,Journals!$J$9:$J$1005679,"unrealized gain on securities") -> 6922812.6
G29: Unrealized gain on T-Bill | H29: =MAX(0,SUMIFS(Journals!$K$9:$K$1005679,Journals!$D$9:$D$1005679,">"&$E$7,Journals!$D$9:$D$1005679,"<"&$E$8,Journals!$J$9:$J$1005679,"Unrealized gain on T-Bill")-SUMIFS(Journals!$L$9:$L$1005679,Journals!$D$9:$D$1005679,">"&$E$7,Journals!$D$9:$D$1005679,"<"&$E$8,Journals!$J$9:$J$1005679,"Unrealized gain on T-Bill")) -> 0 | I29: =MAX(0,SUMIFS(Journals!$L$9:$L$1005679,Journals!$D$9:$D$1005679,">"&$E$7,Journals!$D$9:$D$1005679,"<"&$E$8,Journals!$J$9:$J$1005679,"Unrealized gain on T-Bill")-SUMIFS(Journals!$K$9:$K$1005679,Journals!$D$9:$D$1005679,">"&$E$7,Journals!$D$9:$D$1005679,"<"&$E$8,Journals!$J$9:$J$1005679,"Unrealized gain on T-Bill")) -> 0 | O29: =SUMIFS(Journals!$L$9:$L$1005679,Journals!$D$9:$D$1005679,"<"&$F$7,Journals!$J$9:$J$1005679,"Unrealized gain on T-Bill")-SUMIFS(Journals!$K$9:$K$1005679,Journals!$D$9:$D$1005679,"<"&$F$7,Journals!$J$9:$J$1005679,"Unrealized gain on T-Bill") -> 0
G30: Unrealized gain on T-Bond | H30: =MAX(0,SUMIFS(Journals!$K$9:$K$1005679,Journals!$D$9:$D$1005679,">"&$E$7,Journals!$D$9:$D$1005679,"<"&$E$8,Journals!$J$9:$J$1005679,"Unrealized gain on T-Bond")-SUMIFS(Journals!$L$9:$L$1005679,Journals!$D$9:$D$1005679,">"&$E$7,Journals!$D$9:$D$1005679,"<"&$E$8,Journals!$J$9:$J$1005679,"Unrealized gain on T-Bond")) -> 0 | I30: =MAX(0,SUMIFS(Journals!$L$9:$L$1005679,Journals!$D$9:$D$1005679,">"&$E$7,Journals!$D$9:$D$1005679,"<"&$E$8,Journals!$J$9:$J$1005679,"Unrealized gain on T-Bond")-SUMIFS(Journals!$K$9:$K$1005679,Journals!$D$9:$D$1005679,">"&$E$7,Journals!$D$9:$D$1005679,"<"&$E$8,Journals!$J$9:$J$1005679,"Unrealized gain on T-Bond")) -> 0 | O30: =SUMIFS(Journals!$L$9:$L$1005679,Journals!$D$9:$D$1005679,"<"&$F$7,Journals!$J$9:$J$1005679,"Unrealized gain on T-Bond")-SUMIFS(Journals!$K$9:$K$1005679,Journals!$D$9:$D$1005679,"<"&$F$7,Journals!$J$9:$J$1005679,"Unrealized gain on T-Bond") -> 0
G31: ='Chart of Accounts'!B22 -> Unrealized loss on securities | H31: =MAX(0,SUMIFS(Journals!$K$9:$K$1005679,Journals!$D$9:$D$1005679,">"&$E$7,Journals!$D$9:$D$1005679,"<"&$E$8,Journals!$J$9:$J$1005679,"Unrealized loss on securities")-SUMIFS(Journals!$L$9:$L$1005679,Journals!$D$9:$D$1005679,">"&$E$7,Journals!$D$9:$D$1005679,"<"&$E$8,Journals!$J$9:$J$1005679,"Unrealized loss on securities")) -> 0 | I31: =MAX(0,SUMIFS(Journals!$L$9:$L$1005679,Journals!$D$9:$D$1005679,">"&$E$7,Journals!$D$9:$D$1005679,"<"&$E$8,Journals!$J$9:$J$1005679,"Unrealized loss on securities")-SUMIFS(Journals!$K$9:$K$1005679,Journals!$D$9:$D$1005679,">"&$E$7,Journals!$D$9:$D$1005679,"<"&$E$8,Journals!$J$9:$J$1005679,"Unrealized loss on securities")) -> 0 | N31: =SUMIFS(Journals!K9:K1005679,Journals!D9:D1005679,"<"&F7,Journals!J9:J1005679,"unrealized loss on securities")-SUMIFS(Journals!L9:L1005679,Journals!D9:D1005679,"<"&F7,Journals!J9:J1005679,"unrealized loss on securities") -> 2262855.3
G32: ='Chart of Accounts'!B23 -> Amortization of preliminary and issue expense | H32: =MAX(0,SUMIFS(Journals!$K$9:$K$1005679,Journals!$D$9:$D$1005679,">"&$E$7,Journals!$D$9:$D$1005679,"<"&$E$8,Journals!$J$9:$J$1005679,"Amortization of preliminary and issue expense")-SUMIFS(Journals!$L$9:$L$1005679,Journals!$D$9:$D$1005679,">"&$E$7,Journals!$D$9:$D$1005679,"<"&$E$8,Journals!$J$9:$J$1005679,"Amortization of preliminary and issue expense")) -> 32967.033 | I32: =MAX(0,SUMIFS(Journals!$L$9:$L$1005679,Journals!$D$9:$D$1005679,">"&$E$7,Journals!$D$9:$D$1005679,"<"&$E$8,Journals!$J$9:$J$1005679,"Amortization of preliminary and issue expense")-SUMIFS(Journals!$K$9:$K$1005679,Journals!$D$9:$D$1005679,">"&$E$7,Journals!$D$9:$D$1005679,"<"&$E$8,Journals!$J$9:$J$1005679,"Amortization of preliminary and issue expense")) -> 0 | N32: =SUMIFS(Journals!$K$9:$K$1005679,Journals!$D$9:$D$1005679,"<"&$F$7,Journals!$J$9:$J$1005679,"Amortization of preliminary and issue expense")-SUMIFS(Journals!$L$9:$L$1005679,Journals!$D$9:$D$1005679,"<"&$F$7,Journals!$J$9:$J$1005679,"Amortization of preliminary and issue expense") -> 554945.05
G33: ='Chart of Accounts'!B24 -> Management Fee | H33: =MAX(0,SUMIFS(Journals!$K$9:$K$1005679,Journals!$D$9:$D$1005679,">"&$E$7,Journals!$D$9:$D$1005679,"<"&$E$8,Journals!$J$9:$J$1005679,"management fee")-SUMIFS(Journals!$L$9:$L$1005679,Journals!$D$9:$D$1005679,">"&$E$7,Journals!$D$9:$D$1005679,"<"&$E$8,Journals!$J$9:$J$1005679,"management fee")) -> 1183783.6 | I33: =MAX(0,SUMIFS(Journals!$L$9:$L$1005679,Journals!$D$9:$D$1005679,">"&$E$7,Journals!$D$9:$D$1005679,"<"&$E$8,Journals!$J$9:$J$1005679,"management fee")-SUMIFS(Journals!$K$9:$K$1005679,Journals!$D$9:$D$1005679,">"&$E$7,Journals!$D$9:$D$1005679,"<"&$E$8,Journals!$J$9:$J$1005679,"management fee")) -> 0 | N33: =SUMIFS(Journals!$K$9:$K$1005679,Journals!$D$9:$D$1005679,"<"&$F$7,Journals!$J$9:$J$1005679,"management fee")-SUMIFS(Journals!$L$9:$L$1005679,Journals!$D$9:$D$1005679,"<"&$F$7,Journals!$J$9:$J$1005679,"management fee") -> 14959459
G34: ='Chart of Accounts'!B25 -> Trustee fee | H34: =MAX(0,SUMIFS(Journals!$K$9:$K$1005679,Journals!$D$9:$D$1005679,">"&$E$7,Journals!$D$9:$D$1005679,"<"&$E$8,Journals!$J$9:$J$1005679,"trustee fee")-SUMIFS(Journals!$L$9:$L$1005679,Journals!$D$9:$D$1005679,">"&$E$7,Journals!$D$9:$D$1005679,"<"&$E$8,Journals!$J$9:$J$1005679,"trustee fee")) -> 56977.77 | I34: =MAX(0,SUMIFS(Journals!$L$9:$L$1005679,Journals!$D$9:$D$1005679,">"&$E$7,Journals!$D$9:$D$1005679,"<"&$E$8,Journals!$J$9:$J$1005679,"trustee fee")-SUMIFS(Journals!$K$9:$K$1005679,Journals!$D$9:$D$1005679,">"&$E$7,Journals!$D$9:$D$1005679,"<"&$E$8,Journals!$J$9:$J$1005679,"trustee fee")) -> 0 | N34: =SUMIFS(Journals!$K$9:$K$1005679,Journals!$D$9:$D$1005679,"<"&$F$7,Journals!$J$9:$J$1005679,"trustee fee")-SUMIFS(Journals!$L$9:$L$1005679,Journals!$D$9:$D$1005679,"<"&$F$7,Journals!$J$9:$J$1005679,"trustee fee") -> 755462.36
G35: ='Chart of Accounts'!B26 -> BSEC Annual Fee | H35: =MAX(0,SUMIFS(Journals!$K$9:$K$1005679,Journals!$D$9:$D$1005679,">"&$E$7,Journals!$D$9:$D$1005679,"<"&$E$8,Journals!$J$9:$J$1005679,"bsec annual fee")-SUMIFS(Journals!$L$9:$L$1005679,Journals!$D$9:$D$1005679,">"&$E$7,Journals!$D$9:$D$1005679,"<"&$E$8,Journals!$J$9:$J$1005679,"bsec annual fee")) -> 0 | I35: =MAX(0,SUMIFS(Journals!$L$9:$L$1005679,Journals!$D$9:$D$1005679,">"&$E$7,Journals!$D$9:$D$1005679,"<"&$E$8,Journals!$J$9:$J$1005679,"bsec annual fee")-SUMIFS(Journals!$K$9:$K$1005679,Journals!$D$9:$D$1005679,">"&$E$7,Journals!$D$9:$D$1005679,"<"&$E$8,Journals!$J$9:$J$1005679,"bsec annual fee")) -> 0 | N35: =SUMIFS(Journals!$K$9:$K$1005679,Journals!$D$9:$D$1005679,"<"&$F$7,Journals!$J$9:$J$1005679,"bsec annual fee")-SUMIFS(Journals!$L$9:$L$1005679,Journals!$D$9:$D$1005679,"<"&$F$7,Journals!$J$9:$J$1005679,"bsec annual fee") -> 759042.18
G36: ='Chart of Accounts'!B27 -> Audit fee | H36: =MAX(0,SUMIFS(Journals!$K$9:$K$1005679,Journals!$D$9:$D$1005679,">"&$E$7,Journals!$D$9:$D$1005679,"<"&$E$8,Journals!$J$9:$J$1005679,"audit fee")-SUMIFS(Journals!$L$9:$L$1005679,Journals!$D$9:$D$1005679,">"&$E$7,Journals!$D$9:$D$1005679,"<"&$E$8,Journals!$J$9:$J$1005679,"audit fee")) -> 0 | I36: =MAX(0,SUMIFS(Journals!$L$9:$L$1005679,Journals!$D$9:$D$1005679,">"&$E$7,Journals!$D$9:$D$1005679,"<"&$E$8,Journals!$J$9:$J$1005679,"audit fee")-SUMIFS(Journals!$K$9:$K$1005679,Journals!$D$9:$D$1005679,">"&$E$7,Journals!$D$9:$D$1005679,"<"&$E$8,Journals!$J$9:$J$1005679,"audit fee")) -> 0 | N36: =SUMIFS(Journals!$K$9:$K$1005679,Journals!$D$9:$D$1005679,"<"&$F$7,Journals!$J$9:$J$1005679,"audit fee")-SUMIFS(Journals!$L$9:$L$1005679,Journals!$D$9:$D$1005679,"<"&$F$7,Journals!$J$9:$J$1005679,"audit fee") -> 166750
G37: ='Chart of Accounts'!B28 -> CDBL charges | H37: =MAX(0,SUMIFS(Journals!$K$9:$K$1005679,Journals!$D$9:$D$1005679,">"&$E$7,Journals!$D$9:$D$1005679,"<"&$E$8,Journals!$J$9:$J$1005679,"cdbl charges")-SUMIFS(Journals!$L$9:$L$1005679,Journals!$D$9:$D$1005679,">"&$E$7,Journals!$D$9:$D$1005679,"<"&$E$8,Journals!$J$9:$J$1005679,"cdbl charges")) -> 13947.744 | I37: =MAX(0,SUMIFS(Journals!$L$9:$L$1005679,Journals!$D$9:$D$1005679,">"&$E$7,Journals!$D$9:$D$1005679,"<"&$E$8,Journals!$J$9:$J$1005679,"cdbl charges")-SUMIFS(Journals!$K$9:$K$1005679,Journals!$D$9:$D$1005679,">"&$E$7,Journals!$D$9:$D$1005679,"<"&$E$8,Journals!$J$9:$J$1005679,"cdbl charges")) -> 0 | N37: =SUMIFS(Journals!$K$9:$K$1005679,Journals!$D$9:$D$1005679,"<"&$F$7,Journals!$J$9:$J$1005679,"cdbl charges")-SUMIFS(Journals!$L$9:$L$1005679,Journals!$D$9:$D$1005679,"<"&$F$7,Journals!$J$9:$J$1005679,"cdbl charges") -> 351946.43
G38: ='Chart of Accounts'!B29 -> Fair value adjustment | H38: =MAX(0,SUMIFS(Journals!$K$9:$K$1011420,Journals!$D$9:$D$1011420,">"&$E$7,Journals!$D$9:$D$1011420,"<"&$E$8,Journals!$J$9:$J$1011420,"Fair value adjustment")-SUMIFS(Journals!$L$9:$L$1011420,Journals!$D$9:$D$1011420,">"&$E$7,Journals!$D$9:$D$1011420,"<"&$E$8,Journals!$J$9:$J$1011420,"Fair value adjustment")) -> 8735993.6 | I38: =MAX(0,SUMIFS(Journals!$L$9:$L$1011420,Journals!$D$9:$D$1011420,">"&$E$7,Journals!$D$9:$D$1011420,"<"&$E$8,Journals!$J$9:$J$1011420,"fair value adjustment")-SUMIFS(Journals!$K$9:$K$1011420,Journals!$D$9:$D$1011420,">"&$E$7,Journals!$D$9:$D$1011420,"<"&$E$8,Journals!$J$9:$J$1011420,"fair value adjustment")) -> 0 | J38: =MAX(0,SUMIFS(Journals!K9:K1005679,Journals!D9:D1005679,"<"&F7,Journals!J9:J1005679,"fair value adjustment")-SUMIFS(Journals!L9:L1005679,Journals!D9:D1005679,"<"&F7,Journals!J9:J1005679,"fair value adjustment")) -> 4659957.3 | K38: =MAX(0,SUMIFS(Journals!L9:L1005679,Journals!D9:D1005679,"<"&F7,Journals!J9:J1005679,"Fair value adjustment")-SUMIFS(Journals!K9:K1005679,Journals!D9:D1005679,"<"&F7,Journals!J9:J1005679,"fair value adjustment")) -> 0 | L38: =MAX(0,H38-I38+J38-K38) -> 13395951 | M38: =MAX(0,I38-H38-J38+K38) -> 0
G39: Fair value adjustment T-Bill | H39: =MAX(0,SUMIFS(Journals!$K$9:$K$1011420,Journals!$D$9:$D$1011420,">"&$E$7,Journals!$D$9:$D$1011420,"<"&$E$8,Journals!$J$9:$J$1011420,"Fair value adjustment T-Bill")-SUMIFS(Journals!$L$9:$L$1011420,Journals!$D$9:$D$1011420,">"&$E$7,Journals!$D$9:$D$1011420,"<"&$E$8,Journals!$J$9:$J$1011420,"Fair value adjustment T-Bill")) -> 0 | I39: =MAX(0,SUMIFS(Journals!$L$9:$L$1011420,Journals!$D$9:$D$1011420,">"&$E$7,Journals!$D$9:$D$1011420,"<"&$E$8,Journals!$J$9:$J$1011420,"fair value adjustment T-Bill")-SUMIFS(Journals!$K$9:$K$1011420,Journals!$D$9:$D$1011420,">"&$E$7,Journals!$D$9:$D$1011420,"<"&$E$8,Journals!$J$9:$J$1011420,"fair value adjustment T-Bill")) -> 0 | J39: =MAX(0,SUMIFS(Journals!K9:K1005679,Journals!D9:D1005679,"<"&F7,Journals!J9:J1005679,"fair value adjustment T-Bill")-SUMIFS(Journals!L9:L1005679,Journals!D9:D1005679,"<"&F7,Journals!J9:J1005679,"fair value adjustment T-Bill")) -> 0 | K39: =MAX(0,SUMIFS(Journals!L9:L1005679,Journals!D9:D1005679,"<"&F7,Journals!J9:J1005679,"Fair value adjustment T-Bill")-SUMIFS(Journals!K9:K1005679,Journals!D9:D1005679,"<"&F7,Journals!J9:J1005679,"fair value adjustment T-Bill")) -> 0 | L39: =MAX(0,H39-I39+J39-K39) -> 0 | M39: =MAX(0,I39-H39-J39+K39) -> 0
G40: Fair value adjustment T-Bond | H40: =MAX(0,SUMIFS(Journals!$K$9:$K$1011420,Journals!$D$9:$D$1011420,">"&$E$7,Journals!$D$9:$D$1011420,"<"&$E$8,Journals!$J$9:$J$1011420,"Fair value adjustment T-Bond")-SUMIFS(Journals!$L$9:$L$1011420,Journals!$D$9:$D$1011420,">"&$E$7,Journals!$D$9:$D$1011420,"<"&$E$8,Journals!$J$9:$J$1011420,"Fair value adjustment T-Bond")) -> 0 | I40: =MAX(0,SUMIFS(Journals!$L$9:$L$1011420,Journals!$D$9:$D$1011420,">"&$E$7,Journals!$D$9:$D$1011420,"<"&$E$8,Journals!$J$9:$J$1011420,"fair value adjustment T-Bond")-SUMIFS(Journals!$K$9:$K$1011420,Journals!$D$9:$D$1011420,">"&$E$7,Journals!$D$9:$D$1011420,"<"&$E$8,Journals!$J$9:$J$1011420,"fair value adjustment T-Bond")) -> 0 | J40: =MAX(0,SUMIFS(Journals!K9:K1005679,Journals!D9:D1005679,"<"&F7,Journals!J9:J1005679,"fair value adjustment T-Bond")-SUMIFS(Journals!L9:L1005679,Journals!D9:D1005679,"<"&F7,Journals!J9:J1005679,"fair value adjustment T-Bond")) -> 0 | K40: =MAX(0,SUMIFS(Journals!L9:L1005679,Journals!D9:D1005679,"<"&F7,Journals!J9:J1005679,"Fair value adjustment T-Bond")-SUMIFS(Journals!K9:K1005679,Journals!D9:D1005679,"<"&F7,Journals!J9:J1005679,"fair value adjustment T-Bond")) -> 0 | L40: =MAX(0,H40-I40+J40-K40) -> 0 | M40: =MAX(0,I40-H40-J40+K40) -> 0
G41: Interest receivables from FDR | H41: =MAX(0,SUMIFS(Journals!$K$9:$K$1005679,Journals!$D$9:$D$1005679,">"&$E$7,Journals!$D$9:$D$1005679,"<"&$E$8,Journals!$J$9:$J$1005679,"Interest receivables from FDR")-SUMIFS(Journals!$L$9:$L$1005679,Journals!$D$9:$D$1005679,">"&$E$7,Journals!$D$9:$D$1005679,"<"&$E$8,Journals!$J$9:$J$1005679,"Interest receivables from FDR")) -> 0 | I41: =MAX(0,SUMIFS(Journals!$L$9:$L$1005679,Journals!$D$9:$D$1005679,">"&$E$7,Journals!$D$9:$D$1005679,"<"&$E$8,Journals!$J$9:$J$1005679,"Interest receivables from FDR")-SUMIFS(Journals!$K$9:$K$1005679,Journals!$D$9:$D$1005679,">"&$E$7,Journals!$D$9:$D$1005679,"<"&$E$8,Journals!$J$9:$J$1005679,"Interest receivables from FDR")) -> 70916.667 | J41: =SUMIFS(Journals!$K$9:$K$1005679,Journals!$D$9:$D$1005679,"<"&$F$7,Journals!$J$9:$J$1005679,"Interest receivables from FDR")-SUMIFS(Journals!$L$9:$L$1005679,Journals!$D$9:$D$1005679,"<"&$F$7,Journals!$J$9:$J$1005679,"Interest receivables from FDR") -> 184638.89 | L41: =J41+H41-I41 -> 113722.22
G42: Interest receivables from Renata Pre. Share | H42: =MAX(0,SUMIFS(Journals!$K$9:$K$1005679,Journals!$D$9:$D$1005679,">"&$E$7,Journals!$D$9:$D$1005679,"<"&$E$8,Journals!$J$9:$J$1005679,"Interest receivables from Renata Pre. Share")-SUMIFS(Journals!$L$9:$L$1005679,Journals!$D$9:$D$1005679,">"&$E$7,Journals!$D$9:$D$1005679,"<"&$E$8,Journals!$J$9:$J$1005679,"Interest receivables from Renata Pre. Share")) -> 519576.92 | I42: =MAX(0,SUMIFS(Journals!$L$9:$L$1005679,Journals!$D$9:$D$1005679,">"&$E$7,Journals!$D$9:$D$1005679,"<"&$E$8,Journals!$J$9:$J$1005679,"Interest receivables from Renata Pre. Share")-SUMIFS(Journals!$K$9:$K$1005679,Journals!$D$9:$D$1005679,">"&$E$7,Journals!$D$9:$D$1005679,"<"&$E$8,Journals!$J$9:$J$1005679,"Interest receivables from Renata Pre. Share")) -> 0 | J42: =SUMIFS(Journals!$K$9:$K$1005679,Journals!$D$9:$D$1005679,"<"&$F$7,Journals!$J$9:$J$1005679,"Interest receivables from Renata Pre. Share")-SUMIFS(Journals!$L$9:$L$1005679,Journals!$D$9:$D$1005679,"<"&$F$7,Journals!$J$9:$J$1005679,"Interest receivables from Renata Pre. Share") -> 402053.57 | L42: =J42+H42-I42 -> 921630.49
G43: ='Chart of Accounts'!B33 -> Payable to broker | H43: =MAX(0,SUMIFS(Journals!$K$9:$K$1005679,Journals!$D$9:$D$1005679,">"&$E$7,Journals!$D$9:$D$1005679,"<"&$E$8,Journals!$J$9:$J$1005679,"payable to broker")-SUMIFS(Journals!$L$9:$L$1005679,Journals!$D$9:$D$1005679,">"&$E$7,Journals!$D$9:$D$1005679,"<"&$E$8,Journals!$J$9:$J$1005679,"payable to broker")) -> 384972.14 | I43: =MAX(0,SUMIFS(Journals!$L$9:$L$1005679,Journals!$D$9:$D$1005679,">"&$E$7,Journals!$D$9:$D$1005679,"<"&$E$8,Journals!$J$9:$J$1005679,"payable to broker")-SUMIFS(Journals!$K$9:$K$1005679,Journals!$D$9:$D$1005679,">"&$E$7,Journals!$D$9:$D$1005679,"<"&$E$8,Journals!$J$9:$J$1005679,"payable to broker")) -> 0 | K43: =SUMIFS(Journals!$L$9:$L$1005679,Journals!$D$9:$D$1005679,"<"&$F$7,Journals!$J$9:$J$1005679,"payable to broker")-SUMIFS(Journals!$K$9:$K$1005679,Journals!$D$9:$D$1005679,"<"&$F$7,Journals!$J$9:$J$1005679,"payable to broker") -> 377790.15 | M43: =K43+I43-H43 -> -7181.99
G44: ='Chart of Accounts'!B34 -> Other operating expenses | H44: =MAX(0,SUMIFS(Journals!$K$9:$K$1005679,Journals!$D$9:$D$1005679,">"&$E$7,Journals!$D$9:$D$1005679,"<"&$E$8,Journals!$J$9:$J$1005679,"OTHER OPERATING EXPENSES")-SUMIFS(Journals!$L$9:$L$1005679,Journals!$D$9:$D$1005679,">"&$E$7,Journals!$D$9:$D$1005679,"<"&$E$8,Journals!$J$9:$J$1005679,"OTHER OPERATING EXPENSES")) -> 4725 | I44: =MAX(0,SUMIFS(Journals!$L$9:$L$1005679,Journals!$D$9:$D$1005679,">"&$E$7,Journals!$D$9:$D$1005679,"<"&$E$8,Journals!$J$9:$J$1005679,"OTHER OPERATING EXPENSES")-SUMIFS(Journals!$K$9:$K$1005679,Journals!$D$9:$D$1005679,">"&$E$7,Journals!$D$9:$D$1005679,"<"&$E$8,Journals!$J$9:$J$1005679,"OTHER OPERATING EXPENSES")) -> 0 | N44: =SUMIFS(Journals!$K$9:$K$1005679,Journals!$D$9:$D$1005679,"<"&$F$7,Journals!$J$9:$J$1005679,"OTHER OPERATING EXPENSES")-SUMIFS(Journals!$L$9:$L$1005679,Journals!$D$9:$D$1005679,"<"&$F$7,Journals!$J$9:$J$1005679,"OTHER OPERATING EXPENSES") -> 403975
G45: ='Chart of Accounts'!B35 -> Dividend income | H45: =MAX(0,SUMIFS(Journals!$K$9:$K$1005679,Journals!$D$9:$D$1005679,">"&$E$7,Journals!$D$9:$D$1005679,"<"&$E$8,Journals!$J$9:$J$1005679,"dividend income")) -> 0 | I45: =MAX(0,SUMIFS(Journals!$L$9:$L$1005679,Journals!$D$9:$D$1005679,">"&$E$7,Journals!$D$9:$D$1005679,"<"&$E$8,Journals!$J$9:$J$1005679,"dividend income")) -> 365596.5 | O45: =SUMIFS(Journals!$L$9:$L$1005679,Journals!$D$9:$D$1005679,"<"&$F$7,Journals!$J$9:$J$1005679,"dividend income")-SUMIFS(Journals!$K$9:$K$1005679,Journals!$D$9:$D$1005679,"<"&$F$7,Journals!$J$9:$J$1005679,"dividend income") -> 13838511
E46: =I46-H46 -> 1341806 | G46: ='Chart of Accounts'!B36 -> Dividend receivable | H46: =MAX(0,SUMIFS(Journals!$K$9:$K$1005679,Journals!$D$9:$D$1005679,">"&$E$7,Journals!$D$9:$D$1005679,"<"&$E$8,Journals!$J$9:$J$1005679,"dividend receivable")) -> 220542.5 | I46: =MAX(0,SUMIFS(Journals!$L$9:$L$1005679,Journals!$D$9:$D$1005679,">"&$E$7,Journals!$D$9:$D$1005679,"<"&$E$8,Journals!$J$9:$J$1005679,"dividend receivable")) -> 1562348.5 | J46: =SUMIFS(Journals!$K$9:$K$1005679,Journals!$D$9:$D$1005679,"<"&$F$7,Journals!$J$9:$J$1005679,"dividend receivable")-SUMIFS(Journals!$L$9:$L$1005679,Journals!$D$9:$D$1005679,"<"&$F$7,Journals!$J$9:$J$1005679,"dividend receivable") -> 1341806 | L46: =J46+H46-I46 -> -0.004999999
G47: ='Chart of Accounts'!B37 -> Custodian fee | H47: =MAX(0,SUMIFS(Journals!$K$9:$K$1005679,Journals!$D$9:$D$1005679,">"&$E$7,Journals!$D$9:$D$1005679,"<"&$E$8,Journals!$J$9:$J$1005679,"custodian fee")-SUMIFS(Journals!$L$9:$L$1005679,Journals!$D$9:$D$1005679,">"&$E$7,Journals!$D$9:$D$1005679,"<"&$E$8,Journals!$J$9:$J$1005679,"custodian fee")) -> 0 | N47: =SUMIFS(Journals!$K$9:$K$1005679,Journals!$D$9:$D$1005679,"<"&$F$7,Journals!$J$9:$J$1005679,"custodian fee")-SUMIFS(Journals!$L$9:$L$1005679,Journals!$D$9:$D$1005679,"<"&$F$7,Journals!$J$9:$J$1005679,"custodian fee") -> 487042.23
G48: ='Chart of Accounts'!B38 -> IPO Application | H48: =MAX(0,SUMIFS(Journals!$K$9:$K$1005679,Journals!$D$9:$D$1005679,">"&$E$7,Journals!$D$9:$D$1005679,"<"&$E$8,Journals!$J$9:$J$1005679,"IPO APPLICATION")-SUMIFS(Journals!$L$9:$L$1005679,Journals!$D$9:$D$1005679,">"&$E$7,Journals!$D$9:$D$1005679,"<"&$E$8,Journals!$J$9:$J$1005679,"IPO APPLICATION")) -> 0 | I48: =MAX(0,SUMIFS(Journals!$L$9:$L$1005679,Journals!$D$9:$D$1005679,">"&$E$7,Journals!$D$9:$D$1005679,"<"&$E$8,Journals!$J$9:$J$1005679,"IPO APPLICATION")-SUMIFS(Journals!$K$9:$K$1005679,Journals!$D$9:$D$1005679,">"&$E$7,Journals!$D$9:$D$1005679,"<"&$E$8,Journals!$J$9:$J$1005679,"IPO APPLICATION")) -> 0 | J48: =SUMIFS(Journals!$K$9:$K$1005679,Journals!$D$9:$D$1005679,"<"&$F$7,Journals!$J$9:$J$1005679,"IPO APPLICATION")-SUMIFS(Journals!$L$9:$L$1005679,Journals!$D$9:$D$1005679,"<"&$F$7,Journals!$J$9:$J$1005679,"IPO APPLICATION") -> 0 | L48: =J48+H48-I48 -> 0
G49: ='Chart of Accounts'!B39 -> IPO Application Fee | H49: =MAX(0,SUMIFS(Journals!$K$9:$K$1005679,Journals!$D$9:$D$1005679,">"&$E$7,Journals!$D$9:$D$1005679,"<"&$E$8,Journals!$J$9:$J$1005679,"IPO APPLICATION FEE")-SUMIFS(Journals!$L$9:$L$1005679,Journals!$D$9:$D$1005679,">"&$E$7,Journals!$D$9:$D$1005679,"<"&$E$8,Journals!$J$9:$J$1005679,"IPO APPLICATION FEE")) -> 0 | N49: =SUMIFS(Journals!$K$9:$K$1005679,Journals!$D$9:$D$1005679,"<"&$F$7,Journals!$J$9:$J$1005679,"IPO APPLICATION FEE")-SUMIFS(Journals!$L$9:$L$1005679,Journals!$D$9:$D$1005679,"<"&$F$7,Journals!$J$9:$J$1005679,"IPO APPLICATION FEE") -> 36000
G50: Realized gain | H50: =MAX(0,SUMIFS(Journals!$K$9:$K$1005679,Journals!$D$9:$D$1005679,">"&$E$7,Journals!$D$9:$D$1005679,"<"&$E$8,Journals!$J$9:$J$1005679,"realized gain")-SUMIFS(Journals!$L$9:$L$1005679,Journals!$D$9:$D$1005679,">"&$E$7,Journals!$D$9:$D$1005679,"<"&$E$8,Journals!$J$9:$J$1005679,"realized gain")) -> 0 | I50: =MAX(0,SUMIFS(Journals!$L$9:$L$1005679,Journals!$D$9:$D$1005679,">"&$E$7,Journals!$D$9:$D$1005679,"<"&$E$8,Journals!$J$9:$J$1005679,"realized gain")-SUMIFS(Journals!$K$9:$K$1005679,Journals!$D$9:$D$1005679,">"&$E$7,Journals!$D$9:$D$1005679,"<"&$E$8,Journals!$J$9:$J$1005679,"realized gain")) -> 11929559 | O50: =SUMIFS(Journals!$L$9:$L$1005679,Journals!$D$9:$D$1005679,"<"&$F$7,Journals!$J$9:$J$1005679,"realized gain")-SUMIFS(Journals!$K$9:$K$1005679,Journals!$D$9:$D$1005679,"<"&$F$7,Journals!$J$9:$J$1005679,"realized gain") -> 13446888
G51: Realized gain on T-Bill | H51: =MAX(0,SUMIFS(Journals!$K$9:$K$1005679,Journals!$D$9:$D$1005679,">"&$E$7,Journals!$D$9:$D$1005679,"<"&$E$8,Journals!$J$9:$J$1005679,"Realized gain on T-Bill")-SUMIFS(Journals!$L$9:$L$1005679,Journals!$D$9:$D$1005679,">"&$E$7,Journals!$D$9:$D$1005679,"<"&$E$8,Journals!$J$9:$J$1005679,"Realized gain on T-Bill")) -> 0 | I51: =MAX(0,SUMIFS(Journals!$L$9:$L$1005679,Journals!$D$9:$D$1005679,">"&$E$7,Journals!$D$9:$D$1005679,"<"&$E$8,Journals!$J$9:$J$1005679,"Realized gain on T-Bill")-SUMIFS(Journals!$K$9:$K$1005679,Journals!$D$9:$D$1005679,">"&$E$7,Journals!$D$9:$D$1005679,"<"&$E$8,Journals!$J$9:$J$1005679,"Realized gain on T-Bill")) -> 0 | O51: =SUMIFS(Journals!$L$9:$L$1005679,Journals!$D$9:$D$1005679,"<"&$F$7,Journals!$J$9:$J$1005679,"Realized gain on T-Bill")-SUMIFS(Journals!$K$9:$K$1005679,Journals!$D$9:$D$1005679,"<"&$F$7,Journals!$J$9:$J$1005679,"Realized gain on T-Bill") -> 4268649.2
G52: Realized gain on T-Bond | H52: =MAX(0,SUMIFS(Journals!$K$9:$K$1005679,Journals!$D$9:$D$1005679,">"&$E$7,Journals!$D$9:$D$1005679,"<"&$E$8,Journals!$J$9:$J$1005679,"Realized gain on T-Bond")-SUMIFS(Journals!$L$9:$L$1005679,Journals!$D$9:$D$1005679,">"&$E$7,Journals!$D$9:$D$1005679,"<"&$E$8,Journals!$J$9:$J$1005679,"Realized gain on T-Bond")) -> 0 | I52: =MAX(0,SUMIFS(Journals!$L$9:$L$1005679,Journals!$D$9:$D$1005679,">"&$E$7,Journals!$D$9:$D$1005679,"<"&$E$8,Journals!$J$9:$J$1005679,"Realized gain on T-Bond")-SUMIFS(Journals!$K$9:$K$1005679,Journals!$D$9:$D$1005679,">"&$E$7,Journals!$D$9:$D$1005679,"<"&$E$8,Journals!$J$9:$J$1005679,"Realized gain on T-Bond")) -> 0 | O52: =SUMIFS(Journals!$L$9:$L$1005679,Journals!$D$9:$D$1005679,"<"&$F$7,Journals!$J$9:$J$1005679,"Realized gain on T-Bond")-SUMIFS(Journals!$K$9:$K$1005679,Journals!$D$9:$D$1005679,"<"&$F$7,Journals!$J$9:$J$1005679,"Realized gain on T-Bond") -> 5506443.3
D53: =L53-M43 -> 4424637.7 | G53: Receivable from broker | H53: =MAX(0,SUMIFS(Journals!$K$9:$K$1005679,Journals!$D$9:$D$1005679,">"&$E$7,Journals!$D$9:$D$1005679,"<"&$E$8,Journals!$J$9:$J$1005679,"receivable from broker")-SUMIFS(Journals!$L$9:$L$1005679,Journals!$D$9:$D$1005679,">"&$E$7,Journals!$D$9:$D$1005679,"<"&$E$8,Journals!$J$9:$J$1005679,"receivable from broker")) -> 3059734.9 | I53: =MAX(0,SUMIFS(Journals!$L$9:$L$1005679,Journals!$D$9:$D$1005679,">"&$E$7,Journals!$D$9:$D$1005679,"<"&$E$8,Journals!$J$9:$J$1005679,"Receivable from broker")-SUMIFS(Journals!$K$9:$K$1005679,Journals!$D$9:$D$1005679,">"&$E$7,Journals!$D$9:$D$1005679,"<"&$E$8,Journals!$J$9:$J$1005679,"Receivable from broker")) -> 0 | J53: =SUMIFS(Journals!$K$9:$K$1005679,Journals!$D$9:$D$1005679,"<"&$F$7,Journals!$J$9:$J$1005679,"receivable from broker")-SUMIFS(Journals!$L$9:$L$1005679,Journals!$D$9:$D$1005679,"<"&$F$7,Journals!$J$9:$J$1005679,"receivable from broker") -> 1357720.8 | L53: =J53+H53-I53 -> 4417455.7
G54: Dividend Equalization Reserve | H54: =MAX(0,SUMIFS(Journals!$K$9:$K$1005679,Journals!$D$9:$D$1005679,">"&$E$7,Journals!$D$9:$D$1005679,"<"&$E$8,Journals!$J$9:$J$1005679,"Dividend Equalization Reserve")-SUMIFS(Journals!$L$9:$L$1005679,Journals!$D$9:$D$1005679,">"&$E$7,Journals!$D$9:$D$1005679,"<"&$E$8,Journals!$J$9:$J$1005679,"Dividend Equalization Reserve")) -> 0 | I54: =MAX(0,SUMIFS(Journals!$L$9:$L$1005679,Journals!$D$9:$D$1005679,">"&$E$7,Journals!$D$9:$D$1005679,"<"&$E$8,Journals!$J$9:$J$1005679,"Dividend Equalization Reserve")-SUMIFS(Journals!$K$9:$K$1005679,Journals!$D$9:$D$1005679,">"&$E$7,Journals!$D$9:$D$1005679,"<"&$E$8,Journals!$J$9:$J$1005679,"Dividend Equalization Reserve")) -> 0 | K54: =SUMIFS(Journals!$L$9:$L$1005679,Journals!$D$9:$D$1005679,"<"&$F$7,Journals!$J$9:$J$1005679,"Dividend Equalization Reserve")-SUMIFS(Journals!$K$9:$K$1005679,Journals!$D$9:$D$1005679,"<"&$F$7,Journals!$J$9:$J$1005679,"Dividend Equalization Reserve") -> 0 | M54: =K54+I54-H54 -> 0
G55: Retained Earnings | H55: =MAX(0,SUMIFS(Journals!$K$9:$K$1005679,Journals!$D$9:$D$1005679,">"&$E$7,Journals!$D$9:$D$1005679,"<"&$E$8,Journals!$J$9:$J$1005679,"Retained Earnings")-SUMIFS(Journals!$L$9:$L$1005679,Journals!$D$9:$D$1005679,">"&$E$7,Journals!$D$9:$D$1005679,"<"&$E$8,Journals!$J$9:$J$1005679,"Retained Earnings")) -> 6612758.9 | I55: =MAX(0,SUMIFS(Journals!$L$9:$L$1005679,Journals!$D$9:$D$1005679,">"&$E$7,Journals!$D$9:$D$1005679,"<"&$E$8,Journals!$J$9:$J$1005679,"Retained Earnigs")-SUMIFS(Journals!$K$9:$K$1005679,Journals!$D$9:$D$1005679,">"&$E$7,Journals!$D$9:$D$1005679,"<"&$E$8,Journals!$J$9:$J$1005679,"Retained Earnigs")) -> 0
G56: Dividend Payable | H56: =SUMIFS(Journals!$K$9:$K$1005679,Journals!$D$9:$D$1005679,">"&$E$7,Journals!$D$9:$D$1005679,"<"&$E$8,Journals!$J$9:$J$1005679,"Dividend Payable") -> 6612758.9 | I56: =MAX(0,SUMIFS(Journals!$L$9:$L$1005679,Journals!$D$9:$D$1005679,">"&$E$7,Journals!$D$9:$D$1005679,"<"&$E$8,Journals!$J$9:$J$1005679,"Dividend Payable")) -> 6612758.9 | J56: =SUMIFS(Journals!$K$9:$K$1005679,Journals!$D$9:$D$1005679,"<"&$F$7,Journals!$J$9:$J$1005679,"Dividend Payable") -> 12305680 | K56: =SUMIFS(Journals!$L$9:$L$1005679,Journals!$D$9:$D$1005679,"<"&$F$7,Journals!$J$9:$J$1005679,"Dividend Payable") -> 12305680 | M56: =I56-H56 -> 0 | N56: =J56 -> 12305680
G57: Withholding Tax Payable | H57: =SUMIFS(Journals!$K$9:$K$1005679,Journals!$D$9:$D$1005679,">"&$E$7,Journals!$D$9:$D$1005679,"<"&$E$8,Journals!$J$9:$J$1005679,"Withholding Tax Payable") -> 1394.77 | I57: =MAX(0,SUMIFS(Journals!$L$9:$L$1005679,Journals!$D$9:$D$1005679,">"&$E$7,Journals!$D$9:$D$1005679,"<"&$E$8,Journals!$J$9:$J$1005679,"Withholding Tax Payable")) -> 190521.97 | J57: =SUMIFS(Journals!$K$9:$K$1005679,Journals!$D$9:$D$1005679,"<"&$F$7,Journals!$J$9:$J$1005679,"Withholding Tax Payable")-SUMIFS(Journals!$L$9:$L$1005679,Journals!$D$9:$D$1005679,"<"&$F$7,Journals!$J$9:$J$1005679,"Withholding Tax Payable") -> -0.0044718804 | K57: =SUMIFS(Journals!$L$9:$L$1005679,Journals!$D$9:$D$1005679,"<"&$F$7,Journals!$J$9:$J$1005679,"Withholding Tax Payable")-SUMIFS(Journals!$K$9:$K$1005679,Journals!$D$9:$D$1005679,"<"&$F$7,Journals!$J$9:$J$1005679,"Withholding Tax Payable") -> 0.0044718804 | M57: =K57+I57-H57 -> 189127.21
G58: Withholding Tax Payable for News Paper | H58: =SUMIFS(Journals!$K$9:$K$1005679,Journals!$D$9:$D$1005679,">"&$E$7,Journals!$D$9:$D$1005679,"<"&$E$8,Journals!$J$9:$J$1005679,"Withholding Tax Payable for News Paper") -> 500 | I58: =MAX(0,SUMIFS(Journals!$L$9:$L$1005679,Journals!$D$9:$D$1005679,">"&$E$7,Journals!$D$9:$D$1005679,"<"&$E$8,Journals!$J$9:$J$1005679,"Withholding Tax Payable for News Paper")) -> 0 | J58: =SUMIFS(Journals!$K$9:$K$1005679,Journals!$D$9:$D$1005679,"<"&$F$7,Journals!$J$9:$J$1005679,"Withholding Tax Payable for News Paper")-SUMIFS(Journals!$L$9:$L$1005679,Journals!$D$9:$D$1005679,"<"&$F$7,Journals!$J$9:$J$1005679,"Withholding Tax Payable for News Paper") -> -500 | K58: =SUMIFS(Journals!$L$9:$L$1005679,Journals!$D$9:$D$1005679,"<"&$F$7,Journals!$J$9:$J$1005679,"Withholding Tax Payable for News Paper")-SUMIFS(Journals!$K$9:$K$1005679,Journals!$D$9:$D$1005679,"<"&$F$7,Journals!$J$9:$J$1005679,"Withholding Tax Payable for News Paper") -> 500 | M58: =K58+I58-H58 -> 0
G59: Withholding Tax Payable for Telnet | H59: =SUMIFS(Journals!$K$9:$K$1005679,Journals!$D$9:$D$1005679,">"&$E$7,Journals!$D$9:$D$1005679,"<"&$E$8,Journals!$J$9:$J$1005679,"Withholding Tax Payable for Telnet") -> 75 | I59: =MAX(0,SUMIFS(Journals!$L$9:$L$1005679,Journals!$D$9:$D$1005679,">"&$E$7,Journals!$D$9:$D$1005679,"<"&$E$8,Journals!$J$9:$J$1005679,"Withholding Tax Payable for Telnet")) -> 558774.1 | J59: =SUMIFS(Journals!$K$9:$K$1005679,Journals!$D$9:$D$1005679,"<"&$F$7,Journals!$J$9:$J$1005679,"Withholding Tax Payable for Telnet")-SUMIFS(Journals!$L$9:$L$1005679,Journals!$D$9:$D$1005679,"<"&$F$7,Journals!$J$9:$J$1005679,"Withholding Tax Payable for Telnet") -> -75 | K59: =SUMIFS(Journals!$L$9:$L$1005679,Journals!$D$9:$D$1005679,"<"&$F$7,Journals!$J$9:$J$1005679,"Withholding Tax Payable for Telnet")-SUMIFS(Journals!$K$9:$K$1005679,Journals!$D$9:$D$1005679,"<"&$F$7,Journals!$J$9:$J$1005679,"Withholding Tax Payable for Telnet") -> 75 | M59: =K59+I59-H59 -> 558774.1
G60: Receivable from FDR | H60: =MAX(0,SUMIFS(Journals!$K$9:$K$1005679,Journals!$D$9:$D$1005679,">"&$E$7,Journals!$D$9:$D$1005679,"<"&$E$8,Journals!$J$9:$J$1005679,"Receivable from FDR")-SUMIFS(Journals!$L$9:$L$1005679,Journals!$D$9:$D$1005679,">"&$E$7,Journals!$D$9:$D$1005679,"<"&$E$8,Journals!$J$9:$J$1005679,"Receivable from FDR")) -> 0 | I60: =MAX(0,SUMIFS(Journals!$L$9:$L$1005679,Journals!$D$9:$D$1005679,">"&$E$7,Journals!$D$9:$D$1005679,"<"&$E$8,Journals!$J$9:$J$1005679,"Receivable from FDR")-SUMIFS(Journals!$K$9:$K$1005679,Journals!$D$9:$D$1005679,">"&$E$7,Journals!$D$9:$D$1005679,"<"&$E$8,Journals!$J$9:$J$1005679,"Receivable from FDR")) -> 0 | J60: =SUMIFS(Journals!$K$9:$K$1005679,Journals!$D$9:$D$1005679,"<"&$F$7,Journals!$J$9:$J$1005679,"Receivable from FDR")-SUMIFS(Journals!$L$9:$L$1005679,Journals!$D$9:$D$1005679,"<"&$F$7,Journals!$J$9:$J$1005679,"Receivable from FDR") -> 0 | L60: =J60+H60-I60 -> 0
G61: Investments in T-Bond | H61: =MAX(0,SUMIFS(Journals!$K$9:$K$1003252,Journals!$D$9:$D$1003252,">"&$E$7,Journals!$D$9:$D$1003252,"<"&$E$8,Journals!$J$9:$J$1003252,"Investments in T-Bond")-SUMIFS(Journals!$L$9:$L$1003252,Journals!$D$9:$D$1003252,">"&$E$7,Journals!$D$9:$D$1003252,"<"&$E$8,Journals!$J$9:$J$1003252,"Investments in T-Bond")) -> 0 | I61: =MAX(0,SUMIFS(Journals!$L$9:$L$1003252,Journals!$D$9:$D$1003252,">"&$E$7,Journals!$D$9:$D$1003252,"<"&$E$8,Journals!$J$9:$J$1003252,"Investments in T-Bond")-SUMIFS(Journals!$K$9:$K$1003252,Journals!$D$9:$D$1003252,">"&$E$7,Journals!$D$9:$D$1003252,"<"&$E$8,Journals!$J$9:$J$1003252,"Investments in T-Bond")) -> 0 | J61: =SUMIFS(Journals!$K$9:$K$1003252,Journals!$D$9:$D$1003252,"<"&$F$7,Journals!$J$9:$J$1003252,"Investments in T-Bond")-SUMIFS(Journals!$L$9:$L$1003252,Journals!$D$9:$D$1003252,"<"&$F$7,Journals!$J$9:$J$1003252,"Investments in T-Bond") -> 0 | L61: =J61+H61-I61 -> 0
G62: Bond Premium | H62: =SUMIFS(Journals!$K$9:$K$1003252,Journals!$D$9:$D$1003252,">"&$E$7,Journals!$D$9:$D$1003252,"<"&$E$8,Journals!$J$9:$J$1003252,"Bond Premium") -> 0 | I62: =MAX(0,SUMIFS(Journals!$L$9:$L$1003252,Journals!$D$9:$D$1003252,">"&$E$7,Journals!$D$9:$D$1003252,"<"&$E$8,Journals!$J$9:$J$1003252,"Bond Premium")) -> 0 | J62: =SUMIFS(Journals!$K$9:$K$1003252,Journals!$D$9:$D$1003252,"<"&$F$7,Journals!$J$9:$J$1003252,"Bond Premium")-SUMIFS(Journals!$L$9:$L$1003252,Journals!$D$9:$D$1003252,"<"&$F$7,Journals!$J$9:$J$1003252,"Bond Premium") -> 0 | L62: =J62+H62-I62 -> 0
G63: Redemption Receivable | H63: =MAX(0,SUMIFS(Journals!$K$9:$K$1003252,Journals!$D$9:$D$1003252,">"&$E$7,Journals!$D$9:$D$1003252,"<"&$E$8,Journals!$J$9:$J$1003252,"Redemption Receivable")-SUMIFS(Journals!$L$9:$L$1003252,Journals!$D$9:$D$1003252,">"&$E$7,Journals!$D$9:$D$1003252,"<"&$E$8,Journals!$J$9:$J$1003252,"Redemption Receivable")) -> 0 | I63: =MAX(0,SUMIFS(Journals!$L$9:$L$1003252,Journals!$D$9:$D$1003252,">"&$E$7,Journals!$D$9:$D$1003252,"<"&$E$8,Journals!$J$9:$J$1003252,"Redemption Receivable")-SUMIFS(Journals!$K$9:$K$1003252,Journals!$D$9:$D$1003252,">"&$E$7,Journals!$D$9:$D$1003252,"<"&$E$8,Journals!$J$9:$J$1003252,"Redemption Receivable")) -> 0 | J63: =SUMIFS(Journals!$K$9:$K$1003252,Journals!$D$9:$D$1003252,"<"&$F$7,Journals!$J$9:$J$1003252,"Redemption Receivable")-SUMIFS(Journals!$L$9:$L$1003252,Journals!$D$9:$D$1003252,"<"&$F$7,Journals!$J$9:$J$1003252,"Redemption Receivable") -> 0 | L63: =J63+H63-I63 -> 0
G64: Redemption of Investment | H64: =MAX(0,SUMIFS(Journals!$K$9:$K$1003252,Journals!$D$9:$D$1003252,">"&$E$7,Journals!$D$9:$D$1003252,"<"&$E$8,Journals!$J$9:$J$1003252,"Redemption of Investment")-SUMIFS(Journals!$L$9:$L$1003252,Journals!$D$9:$D$1003252,">"&$E$7,Journals!$D$9:$D$1003252,"<"&$E$8,Journals!$J$9:$J$1003252,"Redemption of Investment")) -> 0 | I64: =MAX(0,SUMIFS(Journals!$L$9:$L$1003252,Journals!$D$9:$D$1003252,">"&$E$7,Journals!$D$9:$D$1003252,"<"&$E$8,Journals!$J$9:$J$1003252,"Redemption of Investment")-SUMIFS(Journals!$K$9:$K$1003252,Journals!$D$9:$D$1003252,">"&$E$7,Journals!$D$9:$D$1003252,"<"&$E$8,Journals!$J$9:$J$1003252,"Redemption of Investment")) -> 0
G65: Interest Receivables from T-Bond | H65: =MAX(0,SUMIFS(Journals!$K$9:$K$1003252,Journals!$D$9:$D$1003252,">"&$E$7,Journals!$D$9:$D$1003252,"<"&$E$8,Journals!$J$9:$J$1003252,"Interest Receivables from T-Bond")-SUMIFS(Journals!$L$9:$L$1003252,Journals!$D$9:$D$1003252,">"&$E$7,Journals!$D$9:$D$1003252,"<"&$E$8,Journals!$J$9:$J$1003252,"Interest Receivables from T-Bond")) -> 0 | I65: =MAX(0,SUMIFS(Journals!$L$9:$L$1003252,Journals!$D$9:$D$1003252,">"&$E$7,Journals!$D$9:$D$1003252,"<"&$E$8,Journals!$J$9:$J$1003252,"Interest Receivables from Bond")-SUMIFS(Journals!$K$9:$K$1003252,Journals!$D$9:$D$1003252,">"&$E$7,Journals!$D$9:$D$1003252,"<"&$E$8,Journals!$J$9:$J$1003252,"Interest Receivables from Bond")) -> 0 | J65: =SUMIFS(Journals!$K$9:$K$1003252,Journals!$D$9:$D$1003252,"<"&$F$7,Journals!$J$9:$J$1003252,"Interest Receivables from Bond")-SUMIFS(Journals!$L$9:$L$1003252,Journals!$D$9:$D$1003252,"<"&$F$7,Journals!$J$9:$J$1003252,"Interest Receivables from Bond") -> 0 | L65: =H65+J65-I65 -> 0
G66: Investment in T-Bill | H66: =MAX(0,SUMIFS(Journals!$K$9:$K$1005679,Journals!$D$9:$D$1005679,">"&$E$7,Journals!$D$9:$D$1005679,"<"&$E$8,Journals!$J$9:$J$1005679,"Investment in T-Bill")-SUMIFS(Journals!$L$9:$L$1005679,Journals!$D$9:$D$1005679,">"&$E$7,Journals!$D$9:$D$1005679,"<"&$E$8,Journals!$J$9:$J$1005679,"Investment in T-Bill")) -> 0 | I66: =MAX(0,SUMIFS(Journals!$L$9:$L$1003252,Journals!$D$9:$D$1003252,">"&$E$7,Journals!$D$9:$D$1003252,"<"&$E$8,Journals!$J$9:$J$1003252,"Investment in T-Bill")-SUMIFS(Journals!$K$9:$K$1003252,Journals!$D$9:$D$1003252,">"&$E$7,Journals!$D$9:$D$1003252,"<"&$E$8,Journals!$J$9:$J$1003252,"Investment in T-Bill")) -> 0 | J66: =SUMIFS(Journals!$K$9:$K$1003252,Journals!$D$9:$D$1003252,"<"&$F$7,Journals!$J$9:$J$1003252,"Investment in T-Bill")-SUMIFS(Journals!$L$9:$L$1003252,Journals!$D$9:$D$1003252,"<"&$F$7,Journals!$J$9:$J$1003252,"Investment in T-Bill") -> 0 | L66: =H66+J66-I66 -> 0
G67: Interest Receivables from T-Bill | H67: =MAX(0,SUMIFS(Journals!$K$9:$K$1003252,Journals!$D$9:$D$1003252,">"&$E$7,Journals!$D$9:$D$1003252,"<"&$E$8,Journals!$J$9:$J$1003252,"Interest Receivables from T-Bill")-SUMIFS(Journals!$L$9:$L$1003252,Journals!$D$9:$D$1003252,">"&$E$7,Journals!$D$9:$D$1003252,"<"&$E$8,Journals!$J$9:$J$1003252,"Interest Receivables from T-Bill")) -> 0 | I67: =MAX(0,SUMIFS(Journals!$L$9:$L$1003252,Journals!$D$9:$D$1003252,">"&$E$7,Journals!$D$9:$D$1003252,"<"&$E$8,Journals!$J$9:$J$1003252,"Interest Receivables from T-Bill")-SUMIFS(Journals!$K$9:$K$1003252,Journals!$D$9:$D$1003252,">"&$E$7,Journals!$D$9:$D$1003252,"<"&$E$8,Journals!$J$9:$J$1003252,"Interest Receivables from T-Bill")) -> 0 | J67: =SUMIFS(Journals!$K$9:$K$1003252,Journals!$D$9:$D$1003252,"<"&$F$7,Journals!$J$9:$J$1003252,"Interest Receivables from T-Bill")-SUMIFS(Journals!$L$9:$L$1003252,Journals!$D$9:$D$1003252,"<"&$F$7,Journals!$J$9:$J$1003252,"Interest Receivables from T-Bill") -> 0 | L67: =H67+J67-I67 -> 0

Sheet TB-P
A1: Check of Trial Balance | G1: =SUM(H7:H85)-SUM(I7:I85) -> 0.0043032765
A2: Check of Balance Sheet | G2: =BS!C25-BS!C41 -> 0
A3: Check of Cash Balance | G3: =BS!C23-CF!B44 -> -3620314.1
B5: Desired Reporting Period | H5: During the Reporting Period | J5: For Balance Sheet | N5: For Retained Earnings
B6: Year | C6: Month | D6: Day | E6: Value | F6: Value | G6: Accounts | H6: Debit | I6: Credit | J6: Carry Forward Balance | K6: Carry Forward Balance | L6: On date | M6: On date | N6: Debit | O6: Credit
A7: Beginning | B7: 2025 | C7: 1 | D7: 1 | E7: =DATE(B7,C7,D7)-1 -> 45657 | F7: =DATE(B7,C7,D7) -> 45658 | G7: ='Chart of Accounts'!B3 -> Investments in stock | H7: =MAX(0,SUMIFS(Journals!$K$9:$K$1005679,Journals!$D$9:$D$1005679,">"&$E$7,Journals!$D$9:$D$1005679,"<"&$E$8,Journals!$J$9:$J$1005679,"investments in stock")-SUMIFS(Journals!$L$9:$L$1005679,Journals!$D$9:$D$1005679,">"&$E$7,Journals!$D$9:$D$1005679,"<"&$E$8,Journals!$J$9:$J$1005679,"investments in stock")) -> 1.0338876e+08 | I7: =MAX(0,SUMIFS(Journals!$L$9:$L$1005679,Journals!$D$9:$D$1005679,">"&$E$7,Journals!$D$9:$D$1005679,"<"&$E$8,Journals!$J$9:$J$1005679,"Investments in stock")-SUMIFS(Journals!$K$9:$K$1005679,Journals!$D$9:$D$1005679,">"&$E$7,Journals!$D$9:$D$1005679,"<"&$E$8,Journals!$J$9:$J$1005679,"Investments in stock")) -> 0 | J7: =SUMIFS(Journals!$K$9:$K$1005679,Journals!$D$9:$D$1005679,"<"&$F$7,Journals!$J$9:$J$1005679,"investments in stock")-SUMIFS(Journals!$L$9:$L$1005679,Journals!$D$9:$D$1005679,"<"&$F$7,Journals!$J$9:$J$1005679,"investments in stock") -> 99890423 | L7: =J7+H7-I7 -> 2.0327918e+08
A8: Ending | B8: 2025 | C8: 12 | D8: 31 | E8: =DATE(B8,C8,D8)+1 -> 46023 | F8: =DATE(B8,C8,D8) -> 46022 | G8: ='Chart of Accounts'!B4 -> Interest Receivables from Bank A/C | H8: =MAX(0,SUMIFS(Journals!$K$9:$K$1005679,Journals!$D$9:$D$1005679,">"&$E$7,Journals!$D$9:$D$1005679,"<"&$E$8,Journals!$J$9:$J$1005679,"Interest Receivables from Bank A/C")-SUMIFS(Journals!$L$9:$L$1005679,Journals!$D$9:$D$1005679,">"&$E$7,Journals!$D$9:$D$1005679,"<"&$E$8,Journals!$J$9:$J$1005679,"Interest Receivables from Bank A/C")) -> 8231.3282 | I8: =MAX(0,SUMIFS(Journals!$L$9:$L$1005679,Journals!$D$9:$D$1005679,">"&$E$7,Journals!$D$9:$D$1005679,"<"&$E$8,Journals!$J$9:$J$1005679,"Interest Receivables from Bank A/C")-SUMIFS(Journals!$K$9:$K$1005679,Journals!$D$9:$D$1005679,">"&$E$7,Journals!$D$9:$D$1005679,"<"&$E$8,Journals!$J$9:$J$1005679,"Interest Receivables from Bank A/C")) -> 0 | J8: =SUMIFS(Journals!$K$9:$K$1005679,Journals!$D$9:$D$1005679,"<"&$F$7,Journals!$J$9:$J$1005679,"Interest Receivables from Bank A/C")-SUMIFS(Journals!$L$9:$L$1005679,Journals!$D$9:$D$1005679,"<"&$F$7,Journals!$J$9:$J$1005679,"Interest Receivables from Bank A/C") -> 2462.46 | L8: =J8+H8-I8 -> 10693.788
G9: ='Chart of Accounts'!B5 -> Preliminary & issue expenses | H9: =MAX(0,SUMIFS(Journals!$K$9:$K$1005679,Journals!$D$9:$D$1005679,">"&$E$7,Journals!$D$9:$D$1005679,"<"&$E$8,Journals!$J$9:$J$1005679,"Preliminary & issue expenses")-SUMIFS(Journals!$L$9:$L$1005679,Journals!$D$9:$D$1005679,">"&$E$7,Journals!$D$9:$D$1005679,"<"&$E$8,Journals!$J$9:$J$1005679,"Preliminary & issue expenses")) -> 0 | I9: =MAX(0,SUMIFS(Journals!$L$9:$L$1005679,Journals!$D$9:$D$1005679,">"&$E$7,Journals!$D$9:$D$1005679,"<"&$E$8,Journals!$J$9:$J$1005679,"Preliminary & issue expenses")-SUMIFS(Journals!$K$9:$K$1005679,Journals!$D$9:$D$1005679,">"&$E$7,Journals!$D$9:$D$1005679,"<"&$E$8,Journals!$J$9:$J$1005679,"Preliminary & issue expenses")) -> 142464.68 | J9: =SUMIFS(Journals!$K$9:$K$1005679,Journals!$D$9:$D$1005679,"<"&$F$7,Journals!$J$9:$J$1005679,"Preliminary & issue expenses")-SUMIFS(Journals!$L$9:$L$1005679,Journals!$D$9:$D$1005679,"<"&$F$7,Journals!$J$9:$J$1005679,"Preliminary & issue expenses") -> 587519.63 | L9: =J9+H9-I9 -> 445054.95
G10: ='Chart of Accounts'!B6 -> Accrued Management Fee | H10: =MAX(0,SUMIFS(Journals!$K$9:$K$1005679,Journals!$D$9:$D$1005679,">"&$E$7,Journals!$D$9:$D$1005679,"<"&$E$8,Journals!$J$9:$J$1005679,"Accrued Management Fee")-SUMIFS(Journals!$L$9:$L$1005679,Journals!$D$9:$D$1005679,">"&$E$7,Journals!$D$9:$D$1005679,"<"&$E$8,Journals!$J$9:$J$1005679,"Accrued Management Fee")) -> 0 | I10: =MAX(0,SUMIFS(Journals!$L$9:$L$1005679,Journals!$D$9:$D$1005679,">"&$E$7,Journals!$D$9:$D$1005679,"<"&$E$8,Journals!$J$9:$J$1005679,"Accrued Management Fee")-SUMIFS(Journals!$K$9:$K$1005679,Journals!$D$9:$D$1005679,">"&$E$7,Journals!$D$9:$D$1005679,"<"&$E$8,Journals!$J$9:$J$1005679,"Accrued Management Fee")) -> 165061.78 | K10: =SUMIFS(Journals!$L$9:$L$1005679,Journals!$D$9:$D$1005679,"<"&$F$7,Journals!$J$9:$J$1005679,"Accrued Management Fee")-SUMIFS(Journals!$K$9:$K$1005679,Journals!$D$9:$D$1005679,"<"&$F$7,Journals!$J$9:$J$1005679,"Accrued Management Fee") -> 610408.36 | M10: =K10+I10-H10 -> 775470.14
G11: ='Chart of Accounts'!B7 -> Accrued Trustee Fee | H11: =MAX(0,SUMIFS(Journals!$K$9:$K$1005679,Journals!$D$9:$D$1005679,">"&$E$7,Journals!$D$9:$D$1005679,"<"&$E$8,Journals!$J$9:$J$1005679,"accrued trustee fee")-SUMIFS(Journals!$L$9:$L$1005679,Journals!$D$9:$D$1005679,">"&$E$7,Journals!$D$9:$D$1005679,"<"&$E$8,Journals!$J$9:$J$1005679,"accrued trustee fee")) -> 0 | I11: =MAX(0,SUMIFS(Journals!$L$9:$L$1005679,Journals!$D$9:$D$1005679,">"&$E$7,Journals!$D$9:$D$1005679,"<"&$E$8,Journals!$J$9:$J$1005679,"accrued trustee fee")-SUMIFS(Journals!$K$9:$K$1005679,Journals!$D$9:$D$1005679,">"&$E$7,Journals!$D$9:$D$1005679,"<"&$E$8,Journals!$J$9:$J$1005679,"accrued trustee fee")) -> 19610.443 | K11: =SUMIFS(Journals!$L$9:$L$1005679,Journals!$D$9:$D$1005679,"<"&$F$7,Journals!$J$9:$J$1005679,"Accrued Trustee Fee")-SUMIFS(Journals!$K$9:$K$1005679,Journals!$D$9:$D$1005679,"<"&$F$7,Journals!$J$9:$J$1005679,"Accrued Trustee Fee") -> 88416.136 | M11: =K11+I11-H11 -> 108026.58
G12: ='Chart of Accounts'!B8 -> Accrued Custodian Fee | H12: =MAX(0,SUMIFS(Journals!$K$9:$K$1005679,Journals!$D$9:$D$1005679,">"&$E$7,Journals!$D$9:$D$1005679,"<"&$E$8,Journals!$J$9:$J$1005679,"accrued custodian fee")-SUMIFS(Journals!$L$9:$L$1005679,Journals!$D$9:$D$1005679,">"&$E$7,Journals!$D$9:$D$1005679,"<"&$E$8,Journals!$J$9:$J$1005679,"accrued custodian fee")) -> 0 | I12: =MAX(0,SUMIFS(Journals!$L$9:$L$1005679,Journals!$D$9:$D$1005679,">"&$E$7,Journals!$D$9:$D$1005679,"<"&$E$8,Journals!$J$9:$J$1005679,"accrued custodian fee")-SUMIFS(Journals!$K$9:$K$1005679,Journals!$D$9:$D$1005679,">"&$E$7,Journals!$D$9:$D$1005679,"<"&$E$8,Journals!$J$9:$J$1005679,"accrued custodian fee")) -> 0 | K12: =SUMIFS(Journals!$L$9:$L$1005679,Journals!$D$9:$D$1005679,"<"&$F$7,Journals!$J$9:$J$1005679,"Accrued Custodian Fee")-SUMIFS(Journals!$K$9:$K$1005679,Journals!$D$9:$D$1005679,"<"&$F$7,Journals!$J$9:$J$1005679,"Accrued Custodian Fee") -> 0 | M12: =K12+I12-H12 -> 0
G13: ='Chart of Accounts'!B9 -> Accrued BSEC fee | H13: =MAX(0,SUMIFS(Journals!$K$9:$K$1005679,Journals!$D$9:$D$1005679,">"&$E$7,Journals!$D$9:$D$1005679,"<"&$E$8,Journals!$J$9:$J$1005679,"accrued bsec fee")-SUMIFS(Journals!$L$9:$L$1005679,Journals!$D$9:$D$1005679,">"&$E$7,Journals!$D$9:$D$1005679,"<"&$E$8,Journals!$J$9:$J$1005679,"accrued bsec fee")) -> 0 | I13: =MAX(0,SUMIFS(Journals!$L$9:$L$1005679,Journals!$D$9:$D$1005679,">"&$E$7,Journals!$D$9:$D$1005679,"<"&$E$8,Journals!$J$9:$J$1005679,"accrued bsec fee")-SUMIFS(Journals!$K$9:$K$1005679,Journals!$D$9:$D$1005679,">"&$E$7,Journals!$D$9:$D$1005679,"<"&$E$8,Journals!$J$9:$J$1005679,"accrued bsec fee")) -> 0 | K13: =SUMIFS(Journals!$L$9:$L$1005679,Journals!$D$9:$D$1005679,"<"&$F$7,Journals!$J$9:$J$1005679,"accrued bsec fee")-SUMIFS(Journals!$K$9:$K$1005679,Journals!$D$9:$D$1005679,"<"&$F$7,Journals!$J$9:$J$1005679,"accrued bsec fee") -> 0 | M13: =K13+I13-H13 -> 0
G14: ='Chart of Accounts'!B10 -> Accrued Audit Fee | H14: =MAX(0,SUMIFS(Journals!$K$9:$K$1005679,Journals!$D$9:$D$1005679,">"&$E$7,Journals!$D$9:$D$1005679,"<"&$E$8,Journals!$J$9:$J$1005679,"accrued audit fee")-SUMIFS(Journals!$L$9:$L$1005679,Journals!$D$9:$D$1005679,">"&$E$7,Journals!$D$9:$D$1005679,"<"&$E$8,Journals!$J$9:$J$1005679,"accrued audit fee")) -> 0 | I14: =MAX(0,SUMIFS(Journals!$L$9:$L$1005679,Journals!$D$9:$D$1005679,">"&$E$7,Journals!$D$9:$D$1005679,"<"&$E$8,Journals!$J$9:$J$1005679,"accrued audit fee")-SUMIFS(Journals!$K$9:$K$1005679,Journals!$D$9:$D$1005679,">"&$E$7,Journals!$D$9:$D$1005679,"<"&$E$8,Journals!$J$9:$J$1005679,"accrued audit fee")) -> 17250 | K14: =SUMIFS(Journals!$L$9:$L$1005679,Journals!$D$9:$D$1005679,"<"&$F$7,Journals!$J$9:$J$1005679,"accrued audit fee")-SUMIFS(Journals!$K$9:$K$1005679,Journals!$D$9:$D$1005679,"<"&$F$7,Journals!$J$9:$J$1005679,"accrued audit fee") -> 40250 | M14: =K14+I14-H14 -> 57500
G15: ='Chart of Accounts'!B11 -> Accrued CDBL Fee | H15: =MAX(0,SUMIFS(Journals!$K$9:$K$1005679,Journals!$D$9:$D$1005679,">"&$E$7,Journals!$D$9:$D$1005679,"<"&$E$8,Journals!$J$9:$J$1005679,"accrued CDBL fee")-SUMIFS(Journals!$L$9:$L$1005679,Journals!$D$9:$D$1005679,">"&$E$7,Journals!$D$9:$D$1005679,"<"&$E$8,Journals!$J$9:$J$1005679,"accrued CDBL fee")) -> 0 | I15: =MAX(0,SUMIFS(Journals!$L$9:$L$1005679,Journals!$D$9:$D$1005679,">"&$E$7,Journals!$D$9:$D$1005679,"<"&$E$8,Journals!$J$9:$J$1005679,"accrued CDBL fee")-SUMIFS(Journals!$K$9:$K$1005679,Journals!$D$9:$D$1005679,">"&$E$7,Journals!$D$9:$D$1005679,"<"&$E$8,Journals!$J$9:$J$1005679,"accrued CDBL fee")) -> 0 | K15: =SUMIFS(Journals!$L$9:$L$1005679,Journals!$D$9:$D$1005679,"<"&$F$7,Journals!$J$9:$J$1005679,"accrued cdbl fee")-SUMIFS(Journals!$K$9:$K$1005679,Journals!$D$9:$D$1005679,"<"&$F$7,Journals!$J$9:$J$1005679,"accrued cdbl fee") -> 0 | M15: =K15+I15-H15 -> 0
G16: ='Chart of Accounts'!B12 -> Fixed Deposit Receipts (FDR) | H16: =MAX(0,SUMIFS(Journals!$K$9:$K$1005679,Journals!$D$9:$D$1005679,">"&$E$7,Journals!$D$9:$D$1005679,"<"&$E$8,Journals!$J$9:$J$1005679,"Fixed Deposit Receipts (FDR)")-SUMIFS(Journals!$L$9:$L$1005679,Journals!$D$9:$D$1005679,">"&$E$7,Journals!$D$9:$D$1005679,"<"&$E$8,Journals!$J$9:$J$1005679,"Fixed Deposit Receipts (FDR)")) -> 0 | I16: =MAX(0,SUMIFS(Journals!$L$9:$L$1005679,Journals!$D$9:$D$1005679,">"&$E$7,Journals!$D$9:$D$1005679,"<"&$E$8,Journals!$J$9:$J$1005679,"Fixed Deposit Receipts (FDR)")-SUMIFS(Journals!$K$9:$K$1005679,Journals!$D$9:$D$1005679,">"&$E$7,Journals!$D$9:$D$1005679,"<"&$E$8,Journals!$J$9:$J$1005679,"Fixed Deposit Receipts (FDR)")) -> 2060500 | J16: =SUMIFS(Journals!$K$9:$K$1005679,Journals!$D$9:$D$1005679,"<"&$F$7,Journals!$J$9:$J$1005679,"Fixed Deposit Receipts (FDR)")-SUMIFS(Journals!$L$9:$L$1005679,Journals!$D$9:$D$1005679,"<"&$F$7,Journals!$J$9:$J$1005679,"Fixed Deposit Receipts (FDR)") -> 15060500 | L16: =J16+H16-I16 -> 13000000
G17: ='Chart of Accounts'!B13 -> Cash and cash equivalents | H17: =MAX(0,SUMIFS(Journals!$K$9:$K$1005679,Journals!$D$9:$D$1005679,">"&$E$7,Journals!$D$9:$D$1005679,"<"&$E$8,Journals!$J$9:$J$1005679,"Cash and cash equivalents")-SUMIFS(Journals!$L$9:$L$1005679,Journals!$D$9:$D$1005679,">"&$E$7,Journals!$D$9:$D$1005679,"<"&$E$8,Journals!$J$9:$J$1005679,"Cash and cash equivalents")) -> 0 | I17: =MAX(0,SUMIFS(Journals!$L$9:$L$1005679,Journals!$D$9:$D$1005679,">"&$E$7,Journals!$D$9:$D$1005679,"<"&$E$8,Journals!$J$9:$J$1005679,"Cash and cash equivalents")-SUMIFS(Journals!$K$9:$K$1005679,Journals!$D$9:$D$1005679,">"&$E$7,Journals!$D$9:$D$1005679,"<"&$E$8,Journals!$J$9:$J$1005679,"Cash and cash equivalents")) -> 33907914 | J17: =SUMIFS(Journals!$K$9:$K$1005679,Journals!$D$9:$D$1005679,"<"&$F$7,Journals!$J$9:$J$1005679,"Cash and cash equivalents")-SUMIFS(Journals!$L$9:$L$1005679,Journals!$D$9:$D$1005679,"<"&$F$7,Journals!$J$9:$J$1005679,"Cash and cash equivalents") -> 34420156 | L17: =J17+H17-I17 -> 512242.08
G18: ='Chart of Accounts'!B14 -> Unit Capital | H18: =MAX(0,SUMIFS(Journals!$K$9:$K$1005679,Journals!$D$9:$D$1005679,">"&$E$7,Journals!$D$9:$D$1005679,"<"&$E$8,Journals!$J$9:$J$1005679,"unit capital")) -> 12592430 | I18: =MAX(0,SUMIFS(Journals!$L$9:$L$1005679,Journals!$D$9:$D$1005679,">"&$E$7,Journals!$D$9:$D$1005679,"<"&$E$8,Journals!$J$9:$J$1005679,"unit capital")) -> 40652580 | K18: =SUMIFS(Journals!$L$9:$L$1005679,Journals!$D$9:$D$1005679,"<"&$F$7,Journals!$J$9:$J$1005679,"unit capital")-SUMIFS(Journals!$K$9:$K$1005679,Journals!$D$9:$D$1005679,"<"&$F$7,Journals!$J$9:$J$1005679,"unit capital") -> 160875820 | M18: =K18+I18-H18 -> 188935970
G19: ='Chart of Accounts'!B15 -> Unit premium reserve | H19: =MAX(0,SUMIFS(Journals!$K$9:$K$1005679,Journals!$D$9:$D$1005679,">"&$E$7,Journals!$D$9:$D$1005679,"<"&$E$8,Journals!$J$9:$J$1005679,"Unit premium reserve")) -> 2008404 | I19: =MAX(0,SUMIFS(Journals!$L$9:$L$1005679,Journals!$D$9:$D$1005679,">"&$E$7,Journals!$D$9:$D$1005679,"<"&$E$8,Journals!$J$9:$J$1005679,"unit premium reserve")) -> 7019419.9 | K19: =SUMIFS(Journals!$L$9:$L$1005679,Journals!$D$9:$D$1005679,"<"&$F$7,Journals!$J$9:$J$1005679,"unit premium reserve")-SUMIFS(Journals!$K$9:$K$1005679,Journals!$D$9:$D$1005679,"<"&$F$7,Journals!$J$9:$J$1005679,"unit premium reserve") -> -2507109.7 | M19: =K19+I19-H19 -> 2503906.3
G20: ='Chart of Accounts'!B16 -> Interest income | H20: =MAX(0,SUMIFS(Journals!$K$9:$K$1001598,Journals!$D$9:$D$1001598,">"&$E$7,Journals!$D$9:$D$1001598,"<"&$E$8,Journals!$J$9:$J$1001598,"interest income")-SUMIFS(Journals!$L$9:$L$1001598,Journals!$D$9:$D$1001598,">"&$E$7,Journals!$D$9:$D$1001598,"<"&$E$8,Journals!$J$9:$J$1001598,"interest income")) -> 0 | I20: =MAX(0,SUMIFS(Journals!$L$9:$L$1001598,Journals!$D$9:$D$1001598,">"&$E$7,Journals!$D$9:$D$1001598,"<"&$E$8,Journals!$J$9:$J$1001598,"interest income")-SUMIFS(Journals!$K$9:$K$1001598,Journals!$D$9:$D$1001598,">"&$E$7,Journals!$D$9:$D$1001598,"<"&$E$8,Journals!$J$9:$J$1001598,"interest income")) -> 2854862 | O20: =SUMIFS(Journals!$L$9:$L$1005679,Journals!$D$9:$D$1005679,"<"&$F$7,Journals!$J$9:$J$1005679,"interest income")-SUMIFS(Journals!$K$9:$K$1005679,Journals!$D$9:$D$1005679,"<"&$F$7,Journals!$J$9:$J$1005679,"interest income") -> 19089964
G21: Interest Income from FDR | H21: =MAX(0,SUMIFS(Journals!$K$9:$K$1005679,Journals!$D$9:$D$1005679,">"&$E$7,Journals!$D$9:$D$1005679,"<"&$E$8,Journals!$J$9:$J$1005679,"Interest Income from FDR")-SUMIFS(Journals!$L$9:$L$1005679,Journals!$D$9:$D$1005679,">"&$E$7,Journals!$D$9:$D$1005679,"<"&$E$8,Journals!$J$9:$J$1005679,"Interest Income from FDR")) -> 0 | I21: =MAX(0,SUMIFS(Journals!$L$9:$L$1005679,Journals!$D$9:$D$1005679,">"&$E$7,Journals!$D$9:$D$1005679,"<"&$E$8,Journals!$J$9:$J$1005679,"Interest Income from FDR")-SUMIFS(Journals!$K$9:$K$1005679,Journals!$D$9:$D$1005679,">"&$E$7,Journals!$D$9:$D$1005679,"<"&$E$8,Journals!$J$9:$J$1005679,"Interest Income from FDR")) -> 0 | O21: =SUMIFS(Journals!$L$9:$L$1005679,Journals!$D$9:$D$1005679,"<"&$F$7,Journals!$J$9:$J$1005679,"Interest Income from FDR")-SUMIFS(Journals!$K$9:$K$1005679,Journals!$D$9:$D$1005679,"<"&$F$7,Journals!$J$9:$J$1005679,"Interest Income from FDR") -> 0
G22: Interest Income from Renata Pre. Share | H22: =MAX(0,SUMIFS(Journals!$K$9:$K$1005679,Journals!$D$9:$D$1005679,">"&$E$7,Journals!$D$9:$D$1005679,"<"&$E$8,Journals!$J$9:$J$1005679,"Interest Income from Renata Pre. Share")-SUMIFS(Journals!$L$9:$L$1005679,Journals!$D$9:$D$1005679,">"&$E$7,Journals!$D$9:$D$1005679,"<"&$E$8,Journals!$J$9:$J$1005679,"Interest Income from Renata Pre. Share")) -> 0 | I22: =MAX(0,SUMIFS(Journals!$L$9:$L$1005679,Journals!$D$9:$D$1005679,">"&$E$7,Journals!$D$9:$D$1005679,"<"&$E$8,Journals!$J$9:$J$1005679,"Interest Income from Renata Pre. Share")-SUMIFS(Journals!$K$9:$K$1005679,Journals!$D$9:$D$1005679,">"&$E$7,Journals!$D$9:$D$1005679,"<"&$E$8,Journals!$J$9:$J$1005679,"Interest Income from Renata Pre. Share")) -> 402053.57 | O22: =SUMIFS(Journals!$L$9:$L$1005679,Journals!$D$9:$D$1005679,"<"&$F$7,Journals!$J$9:$J$1005679,"Interest Income from Renata Pre. Share")-SUMIFS(Journals!$K$9:$K$1005679,Journals!$D$9:$D$1005679,"<"&$F$7,Journals!$J$9:$J$1005679,"Interest Income from Renata Pre. Share") -> 0
G23: Interest Income from Bank Acc | H23: =MAX(0,SUMIFS(Journals!$K$9:$K$1005679,Journals!$D$9:$D$1005679,">"&$E$7,Journals!$D$9:$D$1005679,"<"&$E$8,Journals!$J$9:$J$1005679,"Interest Income from Bank Acc")-SUMIFS(Journals!$L$9:$L$1005679,Journals!$D$9:$D$1005679,">"&$E$7,Journals!$D$9:$D$1005679,"<"&$E$8,Journals!$J$9:$J$1005679,"Interest Income from Bank Acc")) -> 0 | I23: =MAX(0,SUMIFS(Journals!$L$9:$L$1005679,Journals!$D$9:$D$1005679,">"&$E$7,Journals!$D$9:$D$1005679,"<"&$E$8,Journals!$J$9:$J$1005679,"Interest Income from Bank Acc")-SUMIFS(Journals!$K$9:$K$1005679,Journals!$D$9:$D$1005679,">"&$E$7,Journals!$D$9:$D$1005679,"<"&$E$8,Journals!$J$9:$J$1005679,"Interest Income from Bank Acc")) -> 0 | O23: =SUMIFS(Journals!$L$9:$L$1005679,Journals!$D$9:$D$1005679,"<"&$F$7,Journals!$J$9:$J$1005679,"Interest Income from Bank Acc")-SUMIFS(Journals!$K$9:$K$1005679,Journals!$D$9:$D$1005679,"<"&$F$7,Journals!$J$9:$J$1005679,"Interest Income from Bank Acc") -> 0
G24: Interest Income from T-Bill | H24: =MAX(0,SUMIFS(Journals!$K$9:$K$1005679,Journals!$D$9:$D$1005679,">"&$E$7,Journals!$D$9:$D$1005679,"<"&$E$8,Journals!$J$9:$J$1005679,"Interest Income from T-Bill")-SUMIFS(Journals!$L$9:$L$1005679,Journals!$D$9:$D$1005679,">"&$E$7,Journals!$D$9:$D$1005679,"<"&$E$8,Journals!$J$9:$J$1005679,"Interest Income from T-Bill")) -> 0 | I24: =MAX(0,SUMIFS(Journals!$L$9:$L$1005679,Journals!$D$9:$D$1005679,">"&$E$7,Journals!$D$9:$D$1005679,"<"&$E$8,Journals!$J$9:$J$1005679,"Interest Income from T-Bill")-SUMIFS(Journals!$K$9:$K$1005679,Journals!$D$9:$D$1005679,">"&$E$7,Journals!$D$9:$D$1005679,"<"&$E$8,Journals!$J$9:$J$1005679,"Interest Income from T-Bill")) -> 0 | O24: =SUMIFS(Journals!$L$9:$L$1005679,Journals!$D$9:$D$1005679,"<"&$F$7,Journals!$J$9:$J$1005679,"Interest Income from T-Bill")-SUMIFS(Journals!$K$9:$K$1005679,Journals!$D$9:$D$1005679,"<"&$F$7,Journals!$J$9:$J$1005679,"Interest Income from T-Bill") -> 0
G25: Interest Income from T-Bond | H25: =MAX(0,SUMIFS(Journals!$K$9:$K$1005679,Journals!$D$9:$D$1005679,">"&$E$7,Journals!$D$9:$D$1005679,"<"&$E$8,Journals!$J$9:$J$1005679,"Interest Income from T-Bond")-SUMIFS(Journals!$L$9:$L$1005679,Journals!$D$9:$D$1005679,">"&$E$7,Journals!$D$9:$D$1005679,"<"&$E$8,Journals!$J$9:$J$1005679,"Interest Income from T-Bond")) -> 0 | I25: =MAX(0,SUMIFS(Journals!$L$9:$L$1005679,Journals!$D$9:$D$1005679,">"&$E$7,Journals!$D$9:$D$1005679,"<"&$E$8,Journals!$J$9:$J$1005679,"Interest Income from T-Bond")-SUMIFS(Journals!$K$9:$K$1005679,Journals!$D$9:$D$1005679,">"&$E$7,Journals!$D$9:$D$1005679,"<"&$E$8,Journals!$J$9:$J$1005679,"Interest Income from T-Bond")) -> 1841200 | O25: =SUMIFS(Journals!$L$9:$L$1005679,Journals!$D$9:$D$1005679,"<"&$F$7,Journals!$J$9:$J$1005679,"Interest Income from T-Bond")-SUMIFS(Journals!$K$9:$K$1005679,Journals!$D$9:$D$1005679,"<"&$F$7,Journals!$J$9:$J$1005679,"Interest Income from T-Bond") -> 0
G26: ='Chart of Accounts'!B17 -> Bank charges and excise duties | H26: =MAX(0,SUMIFS(Journals!$K$9:$K$1005679,Journals!$D$9:$D$1005679,">"&$E$7,Journals!$D$9:$D$1005679,"<"&$E$8,Journals!$J$9:$J$1005679,"Bank charges and excise duties")-SUMIFS(Journals!$L$9:$L$1005679,Journals!$D$9:$D$1005679,">"&$E$7,Journals!$D$9:$D$1005679,"<"&$E$8,Journals!$J$9:$J$1005679,"Bank charges and excise duties")) -> 86441.062 | I26: =MAX(0,SUMIFS(Journals!$L$9:$L$1005679,Journals!$D$9:$D$1005679,">"&$E$7,Journals!$D$9:$D$1005679,"<"&$E$8,Journals!$J$9:$J$1005679,"Bank charges and excise duties")-SUMIFS(Journals!$K$9:$K$1005679,Journals!$D$9:$D$1005679,">"&$E$7,Journals!$D$9:$D$1005679,"<"&$E$8,Journals!$J$9:$J$1005679,"Bank charges and excise duties")) -> 0 | N26: =SUMIFS(Journals!$K$9:$K$1005679,Journals!$D$9:$D$1005679,"<"&$F$7,Journals!$J$9:$J$1005679,"Bank charges and excise duties")-SUMIFS(Journals!$L$9:$L$1005679,Journals!$D$9:$D$1005679,"<"&$F$7,Journals!$J$9:$J$1005679,"Bank charges and excise duties") -> 615801.69
G27: ='Chart of Accounts'!B18 -> Brokerage commission | H27: =MAX(0,SUMIFS(Journals!$K$9:$K$1005679,Journals!$D$9:$D$1005679,">"&$E$7,Journals!$D$9:$D$1005679,"<"&$E$8,Journals!$J$9:$J$1005679,"brokerage commission")-SUMIFS(Journals!$L$9:$L$1005679,Journals!$D$9:$D$1005679,">"&$E$7,Journals!$D$9:$D$1005679,"<"&$E$8,Journals!$J$9:$J$1005679,"brokerage commission")) -> 978116.7 | I27: =MAX(0,SUMIFS(Journals!$L$9:$L$1005679,Journals!$D$9:$D$1005679,">"&$E$7,Journals!$D$9:$D$1005679,"<"&$E$8,Journals!$J$9:$J$1005679,"brokerage commission")-SUMIFS(Journals!$K$9:$K$1005679,Journals!$D$9:$D$1005679,">"&$E$7,Journals!$D$9:$D$1005679,"<"&$E$8,Journals!$J$9:$J$1005679,"brokerage commission")) -> 0 | N27: =SUMIFS(Journals!$K$9:$K$1005679,Journals!$D$9:$D$1005679,"<"&$F$7,Journals!$J$9:$J$1005679,"brokerage commission")-SUMIFS(Journals!$L$9:$L$1005679,Journals!$D$9:$D$1005679,"<"&$F$7,Journals!$J$9:$J$1005679,"brokerage commission") -> 1013759.1
G28: ='Chart of Accounts'!B19 -> Unrealized gain on securities | H28: =MAX(0,SUMIFS(Journals!$K$9:$K$1005679,Journals!$D$9:$D$1005679,">"&$E$7,Journals!$D$9:$D$1005679,"<"&$E$8,Journals!$J$9:$J$1005679,"Unrealized gain on securities")-SUMIFS(Journals!$L$9:$L$1005679,Journals!$D$9:$D$1005679,">"&$E$7,Journals!$D$9:$D$1005679,"<"&$E$8,Journals!$J$9:$J$1005679,"Unrealized gain on securities")) -> 0 | I28: =MAX(0,SUMIFS(Journals!$L$9:$L$1005679,Journals!$D$9:$D$1005679,">"&$E$7,Journals!$D$9:$D$1005679,"<"&$E$8,Journals!$J$9:$J$1005679,"Unrealized gain on securities")-SUMIFS(Journals!$K$9:$K$1005679,Journals!$D$9:$D$1005679,">"&$E$7,Journals!$D$9:$D$1005679,"<"&$E$8,Journals!$J$9:$J$1005679,"Unrealized gain on securities")) -> 4306713.4 | O28: =SUMIFS(Journals!$L$9:$L$1005679,Journals!$D$9:$D$1005679,"<"&$F$7,Journals!$J$9:$J$1005679,"unrealized gain on securities")-SUMIFS(Journals!$K$9:$K$1005679,Journals!$D$9:$D$1005679,"<"&$F$7,Journals!$J$9:$J$1005679,"unrealized gain on securities") -> 2616099.2
G29: Unrealized gain on T-Bill | H29: =MAX(0,SUMIFS(Journals!$K$9:$K$1005679,Journals!$D$9:$D$1005679,">"&$E$7,Journals!$D$9:$D$1005679,"<"&$E$8,Journals!$J$9:$J$1005679,"Unrealized gain on T-Bill")-SUMIFS(Journals!$L$9:$L$1005679,Journals!$D$9:$D$1005679,">"&$E$7,Journals!$D$9:$D$1005679,"<"&$E$8,Journals!$J$9:$J$1005679,"Unrealized gain on T-Bill")) -> 0 | I29: =MAX(0,SUMIFS(Journals!$L$9:$L$1005679,Journals!$D$9:$D$1005679,">"&$E$7,Journals!$D$9:$D$1005679,"<"&$E$8,Journals!$J$9:$J$1005679,"Unrealized gain on T-Bill")-SUMIFS(Journals!$K$9:$K$1005679,Journals!$D$9:$D$1005679,">"&$E$7,Journals!$D$9:$D$1005679,"<"&$E$8,Journals!$J$9:$J$1005679,"Unrealized gain on T-Bill")) -> 0 | O29: =SUMIFS(Journals!$L$9:$L$1005679,Journals!$D$9:$D$1005679,"<"&$F$7,Journals!$J$9:$J$1005679,"Unrealized gain on T-Bill")-SUMIFS(Journals!$K$9:$K$1005679,Journals!$D$9:$D$1005679,"<"&$F$7,Journals!$J$9:$J$1005679,"Unrealized gain on T-Bill") -> 0
G30: Unrealized gain on T-Bond | H30: =MAX(0,SUMIFS(Journals!$K$9:$K$1005679,Journals!$D$9:$D$1005679,">"&$E$7,Journals!$D$9:$D$1005679,"<"&$E$8,Journals!$J$9:$J$1005679,"Unrealized gain on T-Bond")-SUMIFS(Journals!$L$9:$L$1005679,Journals!$D$9:$D$1005679,">"&$E$7,Journals!$D$9:$D$1005679,"<"&$E$8,Journals!$J$9:$J$1005679,"Unrealized gain on T-Bond")) -> 178264.59 | I30: =MAX(0,SUMIFS(Journals!$L$9:$L$1005679,Journals!$D$9:$D$1005679,">"&$E$7,Journals!$D$9:$D$1005679,"<"&$E$8,Journals!$J$9:$J$1005679,"Unrealized gain on T-Bond")-SUMIFS(Journals!$K$9:$K$1005679,Journals!$D$9:$D$1005679,">"&$E$7,Journals!$D$9:$D$1005679,"<"&$E$8,Journals!$J$9:$J$1005679,"Unrealized gain on T-Bond")) -> 0 | O30: =SUMIFS(Journals!$L$9:$L$1005679,Journals!$D$9:$D$1005679,"<"&$F$7,Journals!$J$9:$J$1005679,"Unrealized gain on T-Bond")-SUMIFS(Journals!$K$9:$K$1005679,Journals!$D$9:$D$1005679,"<"&$F$7,Journals!$J$9:$J$1005679,"Unrealized gain on T-Bond") -> 178264.59
G31: ='Chart of Accounts'!B22 -> Unrealized loss on securities | H31: =MAX(0,SUMIFS(Journals!$K$9:$K$1005679,Journals!$D$9:$D$1005679,">"&$E$7,Journals!$D$9:$D$1005679,"<"&$E$8,Journals!$J$9:$J$1005679,"Unrealized loss on securities")-SUMIFS(Journals!$L$9:$L$1005679,Journals!$D$9:$D$1005679,">"&$E$7,Journals!$D$9:$D$1005679,"<"&$E$8,Journals!$J$9:$J$1005679,"Unrealized loss on securities")) -> 0 | I31: =MAX(0,SUMIFS(Journals!$L$9:$L$1005679,Journals!$D$9:$D$1005679,">"&$E$7,Journals!$D$9:$D$1005679,"<"&$E$8,Journals!$J$9:$J$1005679,"Unrealized loss on securities")-SUMIFS(Journals!$K$9:$K$1005679,Journals!$D$9:$D$1005679,">"&$E$7,Journals!$D$9:$D$1005679,"<"&$E$8,Journals!$J$9:$J$1005679,"Unrealized loss on securities")) -> 0 | N31: =SUMIFS(Journals!K9:K1005679,Journals!D9:D1005679,"<"&F7,Journals!J9:J1005679,"unrealized loss on securities")-SUMIFS(Journals!L9:L1005679,Journals!D9:D1005679,"<"&F7,Journals!J9:J1005679,"unrealized loss on securities") -> 2262855.3
G32: ='Chart of Accounts'!B23 -> Amortization of preliminary and issue expense | H32: =MAX(0,SUMIFS(Journals!$K$9:$K$1005679,Journals!$D$9:$D$1005679,">"&$E$7,Journals!$D$9:$D$1005679,"<"&$E$8,Journals!$J$9:$J$1005679,"Amortization of preliminary and issue expense")-SUMIFS(Journals!$L$9:$L$1005679,Journals!$D$9:$D$1005679,">"&$E$7,Journals!$D$9:$D$1005679,"<"&$E$8,Journals!$J$9:$J$1005679,"Amortization of preliminary and issue expense")) -> 142464.68 | I32: =MAX(0,SUMIFS(Journals!$L$9:$L$1005679,Journals!$D$9:$D$1005679,">"&$E$7,Journals!$D$9:$D$1005679,"<"&$E$8,Journals!$J$9:$J$1005679,"Amortization of preliminary and issue expense")-SUMIFS(Journals!$K$9:$K$1005679,Journals!$D$9:$D$1005679,">"&$E$7,Journals!$D$9:$D$1005679,"<"&$E$8,Journals!$J$9:$J$1005679,"Amortization of preliminary and issue expense")) -> 0 | N32: =SUMIFS(Journals!$K$9:$K$1005679,Journals!$D$9:$D$1005679,"<"&$F$7,Journals!$J$9:$J$1005679,"Amortization of preliminary and issue expense")-SUMIFS(Journals!$L$9:$L$1005679,Journals!$D$9:$D$1005679,"<"&$F$7,Journals!$J$9:$J$1005679,"Amortization of preliminary and issue expense") -> 412480.37
G33: ='Chart of Accounts'!B24 -> Management Fee | H33: =MAX(0,SUMIFS(Journals!$K$9:$K$1005679,Journals!$D$9:$D$1005679,">"&$E$7,Journals!$D$9:$D$1005679,"<"&$E$8,Journals!$J$9:$J$1005679,"management fee")-SUMIFS(Journals!$L$9:$L$1005679,Journals!$D$9:$D$1005679,">"&$E$7,Journals!$D$9:$D$1005679,"<"&$E$8,Journals!$J$9:$J$1005679,"management fee")) -> 4093753.5 | I33: =MAX(0,SUMIFS(Journals!$L$9:$L$1005679,Journals!$D$9:$D$1005679,">"&$E$7,Journals!$D$9:$D$1005679,"<"&$E$8,Journals!$J$9:$J$1005679,"management fee")-SUMIFS(Journals!$K$9:$K$1005679,Journals!$D$9:$D$1005679,">"&$E$7,Journals!$D$9:$D$1005679,"<"&$E$8,Journals!$J$9:$J$1005679,"management fee")) -> 0 | N33: =SUMIFS(Journals!$K$9:$K$1005679,Journals!$D$9:$D$1005679,"<"&$F$7,Journals!$J$9:$J$1005679,"management fee")-SUMIFS(Journals!$L$9:$L$1005679,Journals!$D$9:$D$1005679,"<"&$F$7,Journals!$J$9:$J$1005679,"management fee") -> 10865705
G34: ='Chart of Accounts'!B25 -> Trustee fee | H34: =MAX(0,SUMIFS(Journals!$K$9:$K$1005679,Journals!$D$9:$D$1005679,">"&$E$7,Journals!$D$9:$D$1005679,"<"&$E$8,Journals!$J$9:$J$1005679,"trustee fee")-SUMIFS(Journals!$L$9:$L$1005679,Journals!$D$9:$D$1005679,">"&$E$7,Journals!$D$9:$D$1005679,"<"&$E$8,Journals!$J$9:$J$1005679,"trustee fee")) -> 192222.02 | I34: =MAX(0,SUMIFS(Journals!$L$9:$L$1005679,Journals!$D$9:$D$1005679,">"&$E$7,Journals!$D$9:$D$1005679,"<"&$E$8,Journals!$J$9:$J$1005679,"trustee fee")-SUMIFS(Journals!$K$9:$K$1005679,Journals!$D$9:$D$1005679,">"&$E$7,Journals!$D$9:$D$1005679,"<"&$E$8,Journals!$J$9:$J$1005679,"trustee fee")) -> 0 | N34: =SUMIFS(Journals!$K$9:$K$1005679,Journals!$D$9:$D$1005679,"<"&$F$7,Journals!$J$9:$J$1005679,"trustee fee")-SUMIFS(Journals!$L$9:$L$1005679,Journals!$D$9:$D$1005679,"<"&$F$7,Journals!$J$9:$J$1005679,"trustee fee") -> 563240.35
G35: ='Chart of Accounts'!B26 -> BSEC Annual Fee | H35: =MAX(0,SUMIFS(Journals!$K$9:$K$1005679,Journals!$D$9:$D$1005679,">"&$E$7,Journals!$D$9:$D$1005679,"<"&$E$8,Journals!$J$9:$J$1005679,"bsec annual fee")-SUMIFS(Journals!$L$9:$L$1005679,Journals!$D$9:$D$1005679,">"&$E$7,Journals!$D$9:$D$1005679,"<"&$E$8,Journals!$J$9:$J$1005679,"bsec annual fee")) -> 180112.35 | I35: =MAX(0,SUMIFS(Journals!$L$9:$L$1005679,Journals!$D$9:$D$1005679,">"&$E$7,Journals!$D$9:$D$1005679,"<"&$E$8,Journals!$J$9:$J$1005679,"bsec annual fee")-SUMIFS(Journals!$K$9:$K$1005679,Journals!$D$9:$D$1005679,">"&$E$7,Journals!$D$9:$D$1005679,"<"&$E$8,Journals!$J$9:$J$1005679,"bsec annual fee")) -> 0 | N35: =SUMIFS(Journals!$K$9:$K$1005679,Journals!$D$9:$D$1005679,"<"&$F$7,Journals!$J$9:$J$1005679,"bsec annual fee")-SUMIFS(Journals!$L$9:$L$1005679,Journals!$D$9:$D$1005679,"<"&$F$7,Journals!$J$9:$J$1005679,"bsec annual fee") -> 578929.83
G36: ='Chart of Accounts'!B27 -> Audit fee | H36: =MAX(0,SUMIFS(Journals!$K$9:$K$1005679,Journals!$D$9:$D$1005679,">"&$E$7,Journals!$D$9:$D$1005679,"<"&$E$8,Journals!$J$9:$J$1005679,"audit fee")-SUMIFS(Journals!$L$9:$L$1005679,Journals!$D$9:$D$1005679,">"&$E$7,Journals!$D$9:$D$1005679,"<"&$E$8,Journals!$J$9:$J$1005679,"audit fee")) -> 57500 | I36: =MAX(0,SUMIFS(Journals!$L$9:$L$1005679,Journals!$D$9:$D$1005679,">"&$E$7,Journals!$D$9:$D$1005679,"<"&$E$8,Journals!$J$9:$J$1005679,"audit fee")-SUMIFS(Journals!$K$9:$K$1005679,Journals!$D$9:$D$1005679,">"&$E$7,Journals!$D$9:$D$1005679,"<"&$E$8,Journals!$J$9:$J$1005679,"audit fee")) -> 0 | N36: =SUMIFS(Journals!$K$9:$K$1005679,Journals!$D$9:$D$1005679,"<"&$F$7,Journals!$J$9:$J$1005679,"audit fee")-SUMIFS(Journals!$L$9:$L$1005679,Journals!$D$9:$D$1005679,"<"&$F$7,Journals!$J$9:$J$1005679,"audit fee") -> 109250
G37: ='Chart of Accounts'!B28 -> CDBL charges | H37: =MAX(0,SUMIFS(Journals!$K$9:$K$1005679,Journals!$D$9:$D$1005679,">"&$E$7,Journals!$D$9:$D$1005679,"<"&$E$8,Journals!$J$9:$J$1005679,"cdbl charges")-SUMIFS(Journals!$L$9:$L$1005679,Journals!$D$9:$D$1005679,">"&$E$7,Journals!$D$9:$D$1005679,"<"&$E$8,Journals!$J$9:$J$1005679,"cdbl charges")) -> 156183.06 | I37: =MAX(0,SUMIFS(Journals!$L$9:$L$1005679,Journals!$D$9:$D$1005679,">"&$E$7,Journals!$D$9:$D$1005679,"<"&$E$8,Journals!$J$9:$J$1005679,"cdbl charges")-SUMIFS(Journals!$K$9:$K$1005679,Journals!$D$9:$D$1005679,">"&$E$7,Journals!$D$9:$D$1005679,"<"&$E$8,Journals!$J$9:$J$1005679,"cdbl charges")) -> 0 | N37: =SUMIFS(Journals!$K$9:$K$1005679,Journals!$D$9:$D$1005679,"<"&$F$7,Journals!$J$9:$J$1005679,"cdbl charges")-SUMIFS(Journals!$L$9:$L$1005679,Journals!$D$9:$D$1005679,"<"&$F$7,Journals!$J$9:$J$1005679,"cdbl charges") -> 195763.37
G38: ='Chart of Accounts'!B29 -> Fair value adjustment | H38: =MAX(0,SUMIFS(Journals!$K$9:$K$1005679,Journals!$D$9:$D$1005679,">"&$E$7,Journals!$D$9:$D$1005679,"<"&$E$8,Journals!$J$9:$J$1005679,"Fair value adjustment")-SUMIFS(Journals!$L$9:$L$1005679,Journals!$D$9:$D$1005679,">"&$E$7,Journals!$D$9:$D$1005679,"<"&$E$8,Journals!$J$9:$J$1005679,"Fair value adjustment")) -> 4306713.4 | I38: =MAX(0,SUMIFS(Journals!$L$9:$L$1005679,Journals!$D$9:$D$1005679,">"&$E$7,Journals!$D$9:$D$1005679,"<"&$E$8,Journals!$J$9:$J$1005679,"fair value adjustment")-SUMIFS(Journals!$K$9:$K$1005679,Journals!$D$9:$D$1005679,">"&$E$7,Journals!$D$9:$D$1005679,"<"&$E$8,Journals!$J$9:$J$1005679,"fair value adjustment")) -> 0 | J38: =MAX(0,SUMIFS(Journals!K9:K1005679,Journals!D9:D1005679,"<"&F7,Journals!J9:J1005679,"fair value adjustment")-SUMIFS(Journals!L9:L1005679,Journals!D9:D1005679,"<"&F7,Journals!J9:J1005679,"fair value adjustment")) -> 353243.92 | K38: =MAX(0,SUMIFS(Journals!L9:L1005679,Journals!D9:D1005679,"<"&F7,Journals!J9:J1005679,"Fair value adjustment")-SUMIFS(Journals!K9:K1005679,Journals!D9:D1005679,"<"&F7,Journals!J9:J1005679,"fair value adjustment")) -> 0 | L38: =MAX(0,H38+J38-K38) -> 4659957.3 | M38: =MAX(0,I38+K38-H38) -> 0
G39: Fair value adjustment T-Bill | H39: =MAX(0,SUMIFS(Journals!$K$9:$K$1011420,Journals!$D$9:$D$1011420,">"&$E$7,Journals!$D$9:$D$1011420,"<"&$E$8,Journals!$J$9:$J$1011420,"Fair value adjustment T-Bill")-SUMIFS(Journals!$L$9:$L$1011420,Journals!$D$9:$D$1011420,">"&$E$7,Journals!$D$9:$D$1011420,"<"&$E$8,Journals!$J$9:$J$1011420,"Fair value adjustment T-Bill")) -> 0 | I39: =MAX(0,SUMIFS(Journals!$L$9:$L$1011420,Journals!$D$9:$D$1011420,">"&$E$7,Journals!$D$9:$D$1011420,"<"&$E$8,Journals!$J$9:$J$1011420,"fair value adjustment T-Bill")-SUMIFS(Journals!$K$9:$K$1011420,Journals!$D$9:$D$1011420,">"&$E$7,Journals!$D$9:$D$1011420,"<"&$E$8,Journals!$J$9:$J$1011420,"fair value adjustment T-Bill")) -> 0 | J39: =MAX(0,SUMIFS(Journals!K9:K1005679,Journals!D9:D1005679,"<"&F7,Journals!J9:J1005679,"fair value adjustment T-Bill")-SUMIFS(Journals!L9:L1005679,Journals!D9:D1005679,"<"&F7,Journals!J9:J1005679,"fair value adjustment T-Bill")) -> 0 | K39: =MAX(0,SUMIFS(Journals!L9:L1005679,Journals!D9:D1005679,"<"&F7,Journals!J9:J1005679,"Fair value adjustment T-Bill")-SUMIFS(Journals!K9:K1005679,Journals!D9:D1005679,"<"&F7,Journals!J9:J1005679,"fair value adjustment T-Bill")) -> 0 | L39: =MAX(0,H39-I39+J39-K39) -> 0 | M39: =MAX(0,I39-H39-J39+K39) -> 0
G40: Fair value adjustment T-Bond | H40: =MAX(0,SUMIFS(Journals!$K$9:$K$1011420,Journals!$D$9:$D$1011420,">"&$E$7,Journals!$D$9:$D$1011420,"<"&$E$8,Journals!$J$9:$J$1011420,"Fair value adjustment T-Bond")-SUMIFS(Journals!$L$9:$L$1011420,Journals!$D$9:$D$1011420,">"&$E$7,Journals!$D$9:$D$1011420,"<"&$E$8,Journals!$J$9:$J$1011420,"Fair value adjustment T-Bond")) -> 0 | I40: =MAX(0,SUMIFS(Journals!$L$9:$L$1011420,Journals!$D$9:$D$1011420,">"&$E$7,Journals!$D$9:$D$1011420,"<"&$E$8,Journals!$J$9:$J$1011420,"fair value adjustment T-Bond")-SUMIFS(Journals!$K$9:$K$1011420,Journals!$D$9:$D$1011420,">"&$E$7,Journals!$D$9:$D$1011420,"<"&$E$8,Journals!$J$9:$J$1011420,"fair value adjustment T-Bond")) -> 178264.59 | J40: =MAX(0,SUMIFS(Journals!K9:K1005679,Journals!D9:D1005679,"<"&F7,Journals!J9:J1005679,"fair value adjustment T-Bond")-SUMIFS(Journals!L9:L1005679,Journals!D9:D1005679,"<"&F7,Journals!J9:J1005679,"fair value adjustment T-Bond")) -> 178264.59 | K40: =MAX(0,SUMIFS(Journals!L9:L1005679,Journals!D9:D1005679,"<"&F7,Journals!J9:J1005679,"Fair value adjustment T-Bond")-SUMIFS(Journals!K9:K1005679,Journals!D9:D1005679,"<"&F7,Journals!J9:J1005679,"fair value adjustment T-Bond")) -> 0 | L40: =MAX(0,H40-I40+J40-K40) -> 0 | M40: =MAX(0,I40-H40-J40+K40) -> 0
G41: ='Chart of Accounts'!B32 -> Interest receivables from FDR | H41: =MAX(0,SUMIFS(Journals!$K$9:$K$1005679,Journals!$D$9:$D$1005679,">"&$E$7,Journals!$D$9:$D$1005679,"<"&$E$8,Journals!$J$9:$J$1005679,"Interest receivables from FDR")-SUMIFS(Journals!$L$9:$L$1005679,Journals!$D$9:$D$1005679,">"&$E$7,Journals!$D$9:$D$1005679,"<"&$E$8,Journals!$J$9:$J$1005679,"Interest receivables from FDR")) -> 0 | I41: =MAX(0,SUMIFS(Journals!$L$9:$L$1005679,Journals!$D$9:$D$1005679,">"&$E$7,Journals!$D$9:$D$1005679,"<"&$E$8,Journals!$J$9:$J$1005679,"Interest receivables from FDR")-SUMIFS(Journals!$K$9:$K$1005679,Journals!$D$9:$D$1005679,">"&$E$7,Journals!$D$9:$D$1005679,"<"&$E$8,Journals!$J$9:$J$1005679,"Interest receivables from FDR")) -> 249658.02 | J41: =SUMIFS(Journals!$K$9:$K$1005679,Journals!$D$9:$D$1005679,"<"&$F$7,Journals!$J$9:$J$1005679,"Interest receivables from FDR")-SUMIFS(Journals!$L$9:$L$1005679,Journals!$D$9:$D$1005679,"<"&$F$7,Journals!$J$9:$J$1005679,"Interest receivables from FDR") -> 434296.91 | L41: =J41+H41-I41 -> 184638.89
G42: Interest receivables from Renata Pre. Share | H42: =MAX(0,SUMIFS(Journals!$K$9:$K$1005679,Journals!$D$9:$D$1005679,">"&$E$7,Journals!$D$9:$D$1005679,"<"&$E$8,Journals!$J$9:$J$1005679,"Interest receivables from Renata Pre. Share")-SUMIFS(Journals!$L$9:$L$1005679,Journals!$D$9:$D$1005679,">"&$E$7,Journals!$D$9:$D$1005679,"<"&$E$8,Journals!$J$9:$J$1005679,"Interest receivables from Renata Pre. Share")) -> 402053.57 | I42: =MAX(0,SUMIFS(Journals!$L$9:$L$1005679,Journals!$D$9:$D$1005679,">"&$E$7,Journals!$D$9:$D$1005679,"<"&$E$8,Journals!$J$9:$J$1005679,"Interest receivables from Renata Pre. Share")-SUMIFS(Journals!$K$9:$K$1005679,Journals!$D$9:$D$1005679,">"&$E$7,Journals!$D$9:$D$1005679,"<"&$E$8,Journals!$J$9:$J$1005679,"Interest receivables from Renata Pre. Share")) -> 0 | J42: =SUMIFS(Journals!$K$9:$K$1005679,Journals!$D$9:$D$1005679,"<"&$F$7,Journals!$J$9:$J$1005679,"Interest receivables from Renata Pre. Share")-SUMIFS(Journals!$L$9:$L$1005679,Journals!$D$9:$D$1005679,"<"&$F$7,Journals!$J$9:$J$1005679,"Interest receivables from Renata Pre. Share") -> 0 | L42: =J42+H42-I42 -> 402053.57
G43: ='Chart of Accounts'!B33 -> Payable to broker | H43: =MAX(0,SUMIFS(Journals!$K$9:$K$1005679,Journals!$D$9:$D$1005679,">"&$E$7,Journals!$D$9:$D$1005679,"<"&$E$8,Journals!$J$9:$J$1005679,"payable to broker")-SUMIFS(Journals!$L$9:$L$1005679,Journals!$D$9:$D$1005679,">"&$E$7,Journals!$D$9:$D$1005679,"<"&$E$8,Journals!$J$9:$J$1005679,"payable to broker")) -> 0 | I43: =MAX(0,SUMIFS(Journals!$L$9:$L$1005679,Journals!$D$9:$D$1005679,">"&$E$7,Journals!$D$9:$D$1005679,"<"&$E$8,Journals!$J$9:$J$1005679,"payable to broker")-SUMIFS(Journals!$K$9:$K$1005679,Journals!$D$9:$D$1005679,">"&$E$7,Journals!$D$9:$D$1005679,"<"&$E$8,Journals!$J$9:$J$1005679,"payable to broker")) -> 377790.15 | K43: =SUMIFS(Journals!$L$9:$L$1005679,Journals!$D$9:$D$1005679,"<"&$F$7,Journals!$J$9:$J$1005679,"payable to broker")-SUMIFS(Journals!$K$9:$K$1005679,Journals!$D$9:$D$1005679,"<"&$F$7,Journals!$J$9:$J$1005679,"payable to broker") -> 0.0029000044 | M43: =K43+I43-H43 -> 377790.15
G44: ='Chart of Accounts'!B34 -> Other operating expenses | H44: =MAX(0,SUMIFS(Journals!$K$9:$K$1005679,Journals!$D$9:$D$1005679,">"&$E$7,Journals!$D$9:$D$1005679,"<"&$E$8,Journals!$J$9:$J$1005679,"OTHER OPERATING EXPENSES")-SUMIFS(Journals!$L$9:$L$1005679,Journals!$D$9:$D$1005679,">"&$E$7,Journals!$D$9:$D$1005679,"<"&$E$8,Journals!$J$9:$J$1005679,"OTHER OPERATING EXPENSES")) -> 85900 | I44: =MAX(0,SUMIFS(Journals!$L$9:$L$1005679,Journals!$D$9:$D$1005679,">"&$E$7,Journals!$D$9:$D$1005679,"<"&$E$8,Journals!$J$9:$J$1005679,"OTHER OPERATING EXPENSES")-SUMIFS(Journals!$K$9:$K$1005679,Journals!$D$9:$D$1005679,">"&$E$7,Journals!$D$9:$D$1005679,"<"&$E$8,Journals!$J$9:$J$1005679,"OTHER OPERATING EXPENSES")) -> 0 | N44: =SUMIFS(Journals!$K$9:$K$1005679,Journals!$D$9:$D$1005679,"<"&$F$7,Journals!$J$9:$J$1005679,"OTHER OPERATING EXPENSES")-SUMIFS(Journals!$L$9:$L$1005679,Journals!$D$9:$D$1005679,"<"&$F$7,Journals!$J$9:$J$1005679,"OTHER OPERATING EXPENSES") -> 318075
G45: ='Chart of Accounts'!B35 -> Dividend income | H45: =MAX(0,SUMIFS(Journals!$K$9:$K$1005679,Journals!$D$9:$D$1005679,">"&$E$7,Journals!$D$9:$D$1005679,"<"&$E$8,Journals!$J$9:$J$1005679,"dividend income")-SUMIFS(Journals!$L$9:$L$1005679,Journals!$D$9:$D$1005679,">"&$E$7,Journals!$D$9:$D$1005679,"<"&$E$8,Journals!$J$9:$J$1005679,"dividend income")) -> 0 | I45: =MAX(0,SUMIFS(Journals!$L$9:$L$1005679,Journals!$D$9:$D$1005679,">"&$E$7,Journals!$D$9:$D$1005679,"<"&$E$8,Journals!$J$9:$J$1005679,"dividend income")-SUMIFS(Journals!$K$9:$K$1005679,Journals!$D$9:$D$1005679,">"&$E$7,Journals!$D$9:$D$1005679,"<"&$E$8,Journals!$J$9:$J$1005679,"dividend income")) -> 6250543.1 | O45: =SUMIFS(Journals!$L$9:$L$1005679,Journals!$D$9:$D$1005679,"<"&$F$7,Journals!$J$9:$J$1005679,"dividend income")-SUMIFS(Journals!$K$9:$K$1005679,Journals!$D$9:$D$1005679,"<"&$F$7,Journals!$J$9:$J$1005679,"dividend income") -> 7587967.7
G46: ='Chart of Accounts'!B36 -> Dividend receivable | H46: =MAX(0,SUMIFS(Journals!$K$9:$K$1005679,Journals!$D$9:$D$1005679,">"&$E$7,Journals!$D$9:$D$1005679,"<"&$E$8,Journals!$J$9:$J$1005679,"dividend receivable")-SUMIFS(Journals!$L$9:$L$1005679,Journals!$D$9:$D$1005679,">"&$E$7,Journals!$D$9:$D$1005679,"<"&$E$8,Journals!$J$9:$J$1005679,"dividend receivable")) -> 301059.6 | I46: =MAX(0,SUMIFS(Journals!$L$9:$L$1005679,Journals!$D$9:$D$1005679,">"&$E$7,Journals!$D$9:$D$1005679,"<"&$E$8,Journals!$J$9:$J$1005679,"dividend receivable")-SUMIFS(Journals!$K$9:$K$1005679,Journals!$D$9:$D$1005679,">"&$E$7,Journals!$D$9:$D$1005679,"<"&$E$8,Journals!$J$9:$J$1005679,"dividend receivable")) -> 0 | J46: =SUMIFS(Journals!$K$9:$K$1005679,Journals!$D$9:$D$1005679,"<"&$F$7,Journals!$J$9:$J$1005679,"dividend receivable")-SUMIFS(Journals!$L$9:$L$1005679,Journals!$D$9:$D$1005679,"<"&$F$7,Journals!$J$9:$J$1005679,"dividend receivable") -> 1040746.4 | L46: =J46+H46-I46 -> 1341806
G47: ='Chart of Accounts'!B37 -> Custodian fee | H47: =MAX(0,SUMIFS(Journals!$K$9:$K$1005679,Journals!$D$9:$D$1005679,">"&$E$7,Journals!$D$9:$D$1005679,"<"&$E$8,Journals!$J$9:$J$1005679,"custodian fee")-SUMIFS(Journals!$L$9:$L$1005679,Journals!$D$9:$D$1005679,">"&$E$7,Journals!$D$9:$D$1005679,"<"&$E$8,Journals!$J$9:$J$1005679,"custodian fee")) -> 128051.13 | N47: =SUMIFS(Journals!$K$9:$K$1005679,Journals!$D$9:$D$1005679,"<"&$F$7,Journals!$J$9:$J$1005679,"custodian fee")-SUMIFS(Journals!$L$9:$L$1005679,Journals!$D$9:$D$1005679,"<"&$F$7,Journals!$J$9:$J$1005679,"custodian fee") -> 358991.1
G48: ='Chart of Accounts'!B38 -> IPO Application | H48: =MAX(0,SUMIFS(Journals!$K$9:$K$1005679,Journals!$D$9:$D$1005679,">"&$E$7,Journals!$D$9:$D$1005679,"<"&$E$8,Journals!$J$9:$J$1005679,"IPO APPLICATION")-SUMIFS(Journals!$L$9:$L$1005679,Journals!$D$9:$D$1005679,">"&$E$7,Journals!$D$9:$D$1005679,"<"&$E$8,Journals!$J$9:$J$1005679,"IPO APPLICATION")) -> 0 | I48: =MAX(0,SUMIFS(Journals!$L$9:$L$1005679,Journals!$D$9:$D$1005679,">"&$E$7,Journals!$D$9:$D$1005679,"<"&$E$8,Journals!$J$9:$J$1005679,"IPO APPLICATION")-SUMIFS(Journals!$K$9:$K$1005679,Journals!$D$9:$D$1005679,">"&$E$7,Journals!$D$9:$D$1005679,"<"&$E$8,Journals!$J$9:$J$1005679,"IPO APPLICATION")) -> 0 | J48: =SUMIFS(Journals!$K$9:$K$1005679,Journals!$D$9:$D$1005679,"<"&$F$7,Journals!$J$9:$J$1005679,"IPO APPLICATION")-SUMIFS(Journals!$L$9:$L$1005679,Journals!$D$9:$D$1005679,"<"&$F$7,Journals!$J$9:$J$1005679,"IPO APPLICATION") -> 0 | L48: =J48+H48-I48 -> 0
G49: ='Chart of Accounts'!B39 -> IPO Application Fee | H49: =MAX(0,SUMIFS(Journals!$K$9:$K$1005679,Journals!$D$9:$D$1005679,">"&$E$7,Journals!$D$9:$D$1005679,"<"&$E$8,Journals!$J$9:$J$1005679,"IPO APPLICATION FEE")-SUMIFS(Journals!$L$9:$L$1005679,Journals!$D$9:$D$1005679,">"&$E$7,Journals!$D$9:$D$1005679,"<"&$E$8,Journals!$J$9:$J$1005679,"IPO APPLICATION FEE")) -> 0 | N49: =SUMIFS(Journals!$K$9:$K$1005679,Journals!$D$9:$D$1005679,"<"&$F$7,Journals!$J$9:$J$1005679,"IPO APPLICATION FEE")-SUMIFS(Journals!$L$9:$L$1005679,Journals!$D$9:$D$1005679,"<"&$F$7,Journals!$J$9:$J$1005679,"IPO APPLICATION FEE") -> 36000
G50: Realized gain | H50: =MAX(0,SUMIFS(Journals!$K$9:$K$1005679,Journals!$D$9:$D$1005679,">"&$E$7,Journals!$D$9:$D$1005679,"<"&$E$8,Journals!$J$9:$J$1005679,"realized gain")-SUMIFS(Journals!$L$9:$L$1005679,Journals!$D$9:$D$1005679,">"&$E$7,Journals!$D$9:$D$1005679,"<"&$E$8,Journals!$J$9:$J$1005679,"realized gain")) -> 0 | I50: =MAX(0,SUMIFS(Journals!$L$9:$L$1005679,Journals!$D$9:$D$1005679,">"&$E$7,Journals!$D$9:$D$1005679,"<"&$E$8,Journals!$J$9:$J$1005679,"realized gain")-SUMIFS(Journals!$K$9:$K$1005679,Journals!$D$9:$D$1005679,">"&$E$7,Journals!$D$9:$D$1005679,"<"&$E$8,Journals!$J$9:$J$1005679,"realized gain")) -> 12035292 | O50: =SUMIFS(Journals!$L$9:$L$1005679,Journals!$D$9:$D$1005679,"<"&$F$7,Journals!$J$9:$J$1005679,"realized gain")-SUMIFS(Journals!$K$9:$K$1005679,Journals!$D$9:$D$1005679,"<"&$F$7,Journals!$J$9:$J$1005679,"realized gain") -> 1411596
G51: Realized gain on T-Bill | H51: =MAX(0,SUMIFS(Journals!$K$9:$K$1005679,Journals!$D$9:$D$1005679,">"&$E$7,Journals!$D$9:$D$1005679,"<"&$E$8,Journals!$J$9:$J$1005679,"Realized gain on T-Bill")-SUMIFS(Journals!$L$9:$L$1005679,Journals!$D$9:$D$1005679,">"&$E$7,Journals!$D$9:$D$1005679,"<"&$E$8,Journals!$J$9:$J$1005679,"Realized gain on T-Bill")) -> 0 | I51: =MAX(0,SUMIFS(Journals!$L$9:$L$1005679,Journals!$D$9:$D$1005679,">"&$E$7,Journals!$D$9:$D$1005679,"<"&$E$8,Journals!$J$9:$J$1005679,"Realized gain on T-Bill")-SUMIFS(Journals!$K$9:$K$1005679,Journals!$D$9:$D$1005679,">"&$E$7,Journals!$D$9:$D$1005679,"<"&$E$8,Journals!$J$9:$J$1005679,"Realized gain on T-Bill")) -> 0 | O51: =SUMIFS(Journals!$L$9:$L$1005679,Journals!$D$9:$D$1005679,"<"&$F$7,Journals!$J$9:$J$1005679,"Realized gain on T-Bill")-SUMIFS(Journals!$K$9:$K$1005679,Journals!$D$9:$D$1005679,"<"&$F$7,Journals!$J$9:$J$1005679,"Realized gain on T-Bill") -> 4268649.2
G52: Realized gain on T-Bond | H52: =MAX(0,SUMIFS(Journals!$K$9:$K$1005679,Journals!$D$9:$D$1005679,">"&$E$7,Journals!$D$9:$D$1005679,"<"&$E$8,Journals!$J$9:$J$1005679,"Realized gain on T-Bill")-SUMIFS(Journals!$L$9:$L$1005679,Journals!$D$9:$D$1005679,">"&$E$7,Journals!$D$9:$D$1005679,"<"&$E$8,Journals!$J$9:$J$1005679,"Realized gain on T-Bill")) -> 0 | I52: =MAX(0,SUMIFS(Journals!$L$9:$L$1005679,Journals!$D$9:$D$1005679,">"&$E$7,Journals!$D$9:$D$1005679,"<"&$E$8,Journals!$J$9:$J$1005679,"Realized gain on T-Bond")-SUMIFS(Journals!$K$9:$K$1005679,Journals!$D$9:$D$1005679,">"&$E$7,Journals!$D$9:$D$1005679,"<"&$E$8,Journals!$J$9:$J$1005679,"Realized gain on T-Bond")) -> 4345089.5 | O52: =SUMIFS(Journals!$L$9:$L$1005679,Journals!$D$9:$D$1005679,"<"&$F$7,Journals!$J$9:$J$1005679,"Realized gain on T-Bond")-SUMIFS(Journals!$K$9:$K$1005679,Journals!$D$9:$D$1005679,"<"&$F$7,Journals!$J$9:$J$1005679,"Realized gain on T-Bond") -> 1161353.8
G53: Receivable from broker | H53: =MAX(0,SUMIFS(Journals!$K$9:$K$1005679,Journals!$D$9:$D$1005679,">"&$E$7,Journals!$D$9:$D$1005679,"<"&$E$8,Journals!$J$9:$J$1005679,"receivable from broker")-SUMIFS(Journals!$L$9:$L$1005679,Journals!$D$9:$D$1005679,">"&$E$7,Journals!$D$9:$D$1005679,"<"&$E$8,Journals!$J$9:$J$1005679,"receivable from broker")) -> 1357722.1 | I53: =MAX(0,SUMIFS(Journals!$L$9:$L$1005679,Journals!$D$9:$D$1005679,">"&$E$7,Journals!$D$9:$D$1005679,"<"&$E$8,Journals!$J$9:$J$1005679,"Receivable from broker")-SUMIFS(Journals!$K$9:$K$1005679,Journals!$D$9:$D$1005679,">"&$E$7,Journals!$D$9:$D$1005679,"<"&$E$8,Journals!$J$9:$J$1005679,"Receivable from broker")) -> 0 | J53: =SUMIFS(Journals!$K$9:$K$1005679,Journals!$D$9:$D$1005679,"<"&$F$7,Journals!$J$9:$J$1005679,"receivable from broker")-SUMIFS(Journals!$L$9:$L$1005679,Journals!$D$9:$D$1005679,"<"&$F$7,Journals!$J$9:$J$1005679,"receivable from broker") -> -1.3213999 | L53: =J53+H53-I53 -> 1357720.8
G54: Dividend Equalization Reserve | H54: =MAX(0,SUMIFS(Journals!$K$9:$K$1005679,Journals!$D$9:$D$1005679,">"&$E$7,Journals!$D$9:$D$1005679,"<"&$E$8,Journals!$J$9:$J$1005679,"dividend equalization reserve")) -> 0 | I54: =MAX(0,SUMIFS(Journals!$L$9:$L$1005679,Journals!$D$9:$D$1005679,">"&$E$7,Journals!$D$9:$D$1005679,"<"&$E$8,Journals!$J$9:$J$1005679,"dividend equalization reserve")) -> 0 | K54: =SUMIFS(Journals!$L$9:$L$1005679,Journals!$D$9:$D$1005679,"<"&$F$7,Journals!$J$9:$J$1005679,"Dividend Equalization Reserve")-SUMIFS(Journals!$K$9:$K$1005679,Journals!$D$9:$D$1005679,"<"&$F$7,Journals!$J$9:$J$1005679,"Dividend Equalization Reserve") -> 0 | L54: =H54 -> 0 | M54: =I54 -> 0
G55: Retained Earnings | H55: =MAX(0,SUMIFS(Journals!$K$9:$K$1005679,Journals!$D$9:$D$1005679,">"&$E$7,Journals!$D$9:$D$1005679,"<"&$E$8,Journals!$J$9:$J$1005679,"retained earnings")-SUMIFS(Journals!$L$9:$L$1005679,Journals!$D$9:$D$1005679,">"&$E$7,Journals!$D$9:$D$1005679,"<"&$E$8,Journals!$J$9:$J$1005679,"retained earnings")) -> 8043791 | I55: =MAX(0,SUMIFS(Journals!$L$9:$L$1005679,Journals!$D$9:$D$1005679,">"&$E$7,Journals!$D$9:$D$1005679,"<"&$E$8,Journals!$J$9:$J$1005679,"retained earnings")-SUMIFS(Journals!$K$9:$K$1005679,Journals!$D$9:$D$1005679,">"&$E$7,Journals!$D$9:$D$1005679,"<"&$E$8,Journals!$J$9:$J$1005679,"retained earnings")) -> 0
G56: Dividend Payable | H56: =MAX(0,SUMIFS(Journals!$K$9:$K$1005679,Journals!$D$9:$D$1005679,">"&$E$7,Journals!$D$9:$D$1005679,"<"&$E$8,Journals!$J$9:$J$1005679,"dividend payable")) -> 8043791 | I56: =MAX(0,SUMIFS(Journals!$L$9:$L$1005679,Journals!$D$9:$D$1005679,">"&$E$7,Journals!$D$9:$D$1005679,"<"&$E$8,Journals!$J$9:$J$1005679,"dividend payable")) -> 8043791 | J56: =SUMIFS(Journals!$K$9:$K$1005679,Journals!$D$9:$D$1005679,"<"&$F$7,Journals!$J$9:$J$1005679,"Dividend Payable") -> 4261889 | K56: =SUMIFS(Journals!$L$9:$L$1005679,Journals!$D$9:$D$1005679,"<"&$F$7,Journals!$J$9:$J$1005679,"Dividend Payable") -> 4261889 | N56: =J56 -> 4261889
G57: Withholding Tax Payable | H57: =MAX(0,SUMIFS(Journals!$K$9:$K$1005679,Journals!$D$9:$D$1005679,">"&$E$7,Journals!$D$9:$D$1005679,"<"&$E$8,Journals!$J$9:$J$1005679,"Withholding Tax Payable")) -> 2118139.2 | I57: =MAX(0,SUMIFS(Journals!$L$9:$L$1005679,Journals!$D$9:$D$1005679,">"&$E$7,Journals!$D$9:$D$1005679,"<"&$E$8,Journals!$J$9:$J$1005679,"Withholding Tax Payable")) -> 1953923.5 | J57: =SUMIFS(Journals!$K$9:$K$1005679,Journals!$D$9:$D$1005679,"<"&$F$7,Journals!$J$9:$J$1005679,"Withholding Tax Payable")-SUMIFS(Journals!$L$9:$L$1005679,Journals!$D$9:$D$1005679,"<"&$F$7,Journals!$J$9:$J$1005679,"Withholding Tax Payable") -> -164215.69 | K57: =SUMIFS(Journals!$L$9:$L$1005679,Journals!$D$9:$D$1005679,"<"&$F$7,Journals!$J$9:$J$1005679,"Withholding Tax Payable")-SUMIFS(Journals!$K$9:$K$1005679,Journals!$D$9:$D$1005679,"<"&$F$7,Journals!$J$9:$J$1005679,"Withholding Tax Payable") -> 164215.69 | M57: =K57+I57-H57 -> 0.0044718808
G58: Withholding Tax Payable for News Paper | H58: =SUMIFS(Journals!$K$9:$K$1005679,Journals!$D$9:$D$1005679,">"&$E$7,Journals!$D$9:$D$1005679,"<"&$E$8,Journals!$J$9:$J$1005679,"Withholding Tax Payable for News Paper") -> 2500 | I58: =MAX(0,SUMIFS(Journals!$L$9:$L$1005679,Journals!$D$9:$D$1005679,">"&$E$7,Journals!$D$9:$D$1005679,"<"&$E$8,Journals!$J$9:$J$1005679,"Withholding Tax Payable for News Paper")) -> 2750 | J58: =SUMIFS(Journals!$K$9:$K$1005679,Journals!$D$9:$D$1005679,"<"&$F$7,Journals!$J$9:$J$1005679,"Withholding Tax Payable for News Paper")-SUMIFS(Journals!$L$9:$L$1005679,Journals!$D$9:$D$1005679,"<"&$F$7,Journals!$J$9:$J$1005679,"Withholding Tax Payable for News Paper") -> -250 | K58: =SUMIFS(Journals!$L$9:$L$1005679,Journals!$D$9:$D$1005679,"<"&$F$7,Journals!$J$9:$J$1005679,"Withholding Tax Payable for News Paper")-SUMIFS(Journals!$K$9:$K$1005679,Journals!$D$9:$D$1005679,"<"&$F$7,Journals!$J$9:$J$1005679,"Withholding Tax Payable for News Paper") -> 250 | M58: =K58+I58-H58 -> 500
G59: Withholding Tax Payable for Telnet | H59: =SUMIFS(Journals!$K$9:$K$1005679,Journals!$D$9:$D$1005679,">"&$E$7,Journals!$D$9:$D$1005679,"<"&$E$8,Journals!$J$9:$J$1005679,"Withholding Tax Payable for Telnet") -> 1575 | I59: =MAX(0,SUMIFS(Journals!$L$9:$L$1005679,Journals!$D$9:$D$1005679,">"&$E$7,Journals!$D$9:$D$1005679,"<"&$E$8,Journals!$J$9:$J$1005679,"Withholding Tax Payable for Telnet")) -> 1650 | J59: =SUMIFS(Journals!$K$9:$K$1005679,Journals!$D$9:$D$1005679,"<"&$F$7,Journals!$J$9:$J$1005679,"Withholding Tax Payable for Telnet")-SUMIFS(Journals!$L$9:$L$1005679,Journals!$D$9:$D$1005679,"<"&$F$7,Journals!$J$9:$J$1005679,"Withholding Tax Payable for Telnet") -> 0 | K59: =SUMIFS(Journals!$L$9:$L$1005679,Journals!$D$9:$D$1005679,"<"&$F$7,Journals!$J$9:$J$1005679,"Withholding Tax Payable for Telnet")-SUMIFS(Journals!$K$9:$K$1005679,Journals!$D$9:$D$1005679,"<"&$F$7,Journals!$J$9:$J$1005679,"Withholding Tax Payable for Telnet") -> 0 | M59: =K59+I59-H59 -> 75
G60: Receivable from FDR | H60: =MAX(0,SUMIFS(Journals!$K$9:$K$1005679,Journals!$D$9:$D$1005679,">"&$E$7,Journals!$D$9:$D$1005679,"<"&$E$8,Journals!$J$9:$J$1005679,"Receivable from FDR")-SUMIFS(Journals!$L$9:$L$1005679,Journals!$D$9:$D$1005679,">"&$E$7,Journals!$D$9:$D$1005679,"<"&$E$8,Journals!$J$9:$J$1005679,"Receivable from FDR")) -> 0 | I60: =MAX(0,SUMIFS(Journals!$L$9:$L$1005679,Journals!$D$9:$D$1005679,">"&$E$7,Journals!$D$9:$D$1005679,"<"&$E$8,Journals!$J$9:$J$1005679,"Receivable from FDR")-SUMIFS(Journals!$K$9:$K$1005679,Journals!$D$9:$D$1005679,">"&$E$7,Journals!$D$9:$D$1005679,"<"&$E$8,Journals!$J$9:$J$1005679,"Receivable from FDR")) -> 0 | J60: =SUMIFS(Journals!$K$9:$K$1005679,Journals!$D$9:$D$1005679,"<"&$F$7,Journals!$J$9:$J$1005679,"Receivable from FDR")-SUMIFS(Journals!$L$9:$L$1005679,Journals!$D$9:$D$1005679,"<"&$F$7,Journals!$J$9:$J$1005679,"Receivable from FDR") -> 0 | L60: =J60+H60-I60 -> 0
G61: Investments in T-Bond | H61: =MAX(0,SUMIFS(Journals!$K$9:$K$1003252,Journals!$D$9:$D$1003252,">"&$E$7,Journals!$D$9:$D$1003252,"<"&$E$8,Journals!$J$9:$J$1003252,"Investments in T-Bond")-SUMIFS(Journals!$L$9:$L$1003252,Journals!$D$9:$D$1003252,">"&$E$7,Journals!$D$9:$D$1003252,"<"&$E$8,Journals!$J$9:$J$1003252,"Investments in T-Bond")) -> 0 | I61: =MAX(0,SUMIFS(Journals!$L$9:$L$1003252,Journals!$D$9:$D$1003252,">"&$E$7,Journals!$D$9:$D$1003252,"<"&$E$8,Journals!$J$9:$J$1003252,"Investments in T-Bond")-SUMIFS(Journals!$K$9:$K$1003252,Journals!$D$9:$D$1003252,">"&$E$7,Journals!$D$9:$D$1003252,"<"&$E$8,Journals!$J$9:$J$1003252,"Investments in T-Bond")) -> 22025793 | J61: =SUMIFS(Journals!$K$9:$K$1003252,Journals!$D$9:$D$1003252,"<"&$F$7,Journals!$J$9:$J$1003252,"Investments in T-Bond")-SUMIFS(Journals!$L$9:$L$1003252,Journals!$D$9:$D$1003252,"<"&$F$7,Journals!$J$9:$J$1003252,"Investments in T-Bond") -> 22025793 | L61: =J61+H61-I61 -> 0
G62: Bond Premium | H62: =SUMIFS(Journals!$K$9:$K$1003252,Journals!$D$9:$D$1003252,">"&$E$7,Journals!$D$9:$D$1003252,"<"&$E$8,Journals!$J$9:$J$1003252,"Bond Premium") -> 0 | I62: =MAX(0,SUMIFS(Journals!$L$9:$L$1003252,Journals!$D$9:$D$1003252,">"&$E$7,Journals!$D$9:$D$1003252,"<"&$E$8,Journals!$J$9:$J$1003252,"Bond Premium")) -> 0 | J62: =SUMIFS(Journals!$K$9:$K$1003252,Journals!$D$9:$D$1003252,"<"&$F$7,Journals!$J$9:$J$1003252,"Bond Premium")-SUMIFS(Journals!$L$9:$L$1003252,Journals!$D$9:$D$1003252,"<"&$F$7,Journals!$J$9:$J$1003252,"Bond Premium") -> 0 | L62: =J62+H62-I62 -> 0
G63: Redemption Receivable | H63: =MAX(0,SUMIFS(Journals!$K$9:$K$1003252,Journals!$D$9:$D$1003252,">"&$E$7,Journals!$D$9:$D$1003252,"<"&$E$8,Journals!$J$9:$J$1003252,"Redemption Receivable")-SUMIFS(Journals!$L$9:$L$1003252,Journals!$D$9:$D$1003252,">"&$E$7,Journals!$D$9:$D$1003252,"<"&$E$8,Journals!$J$9:$J$1003252,"Redemption Receivable")) -> 0 | I63: =MAX(0,SUMIFS(Journals!$L$9:$L$1003252,Journals!$D$9:$D$1003252,">"&$E$7,Journals!$D$9:$D$1003252,"<"&$E$8,Journals!$J$9:$J$1003252,"Redemption Receivable")-SUMIFS(Journals!$K$9:$K$1003252,Journals!$D$9:$D$1003252,">"&$E$7,Journals!$D$9:$D$1003252,"<"&$E$8,Journals!$J$9:$J$1003252,"Redemption Receivable")) -> 0 | J63: =SUMIFS(Journals!$K$9:$K$1003252,Journals!$D$9:$D$1003252,"<"&$F$7,Journals!$J$9:$J$1003252,"Redemption Receivable")-SUMIFS(Journals!$L$9:$L$1003252,Journals!$D$9:$D$1003252,"<"&$F$7,Journals!$J$9:$J$1003252,"Redemption Receivable") -> 0 | L63: =J63+H63-I63 -> 0
G64: Redemption of Investment | H64: =MAX(0,SUMIFS(Journals!$K$9:$K$1003252,Journals!$D$9:$D$1003252,">"&$E$7,Journals!$D$9:$D$1003252,"<"&$E$8,Journals!$J$9:$J$1003252,"Redemption of Investment")-SUMIFS(Journals!$L$9:$L$1003252,Journals!$D$9:$D$1003252,">"&$E$7,Journals!$D$9:$D$1003252,"<"&$E$8,Journals!$J$9:$J$1003252,"Redemption of Investment")) -> 0 | I64: =MAX(0,SUMIFS(Journals!$L$9:$L$1003252,Journals!$D$9:$D$1003252,">"&$E$7,Journals!$D$9:$D$1003252,"<"&$E$8,Journals!$J$9:$J$1003252,"Redemption of Investment")-SUMIFS(Journals!$K$9:$K$1003252,Journals!$D$9:$D$1003252,">"&$E$7,Journals!$D$9:$D$1003252,"<"&$E$8,Journals!$J$9:$J$1003252,"Redemption of Investment")) -> 0
G65: Interest Receivables from Bond | H65: =MAX(0,SUMIFS(Journals!$K$9:$K$1003252,Journals!$D$9:$D$1003252,">"&$E$7,Journals!$D$9:$D$1003252,"<"&$E$8,Journals!$J$9:$J$1003252,"Interest Receivables from Bond")-SUMIFS(Journals!$L$9:$L$1003252,Journals!$D$9:$D$1003252,">"&$E$7,Journals!$D$9:$D$1003252,"<"&$E$8,Journals!$J$9:$J$1003252,"Interest Receivables from Bond")) -> 0 | I65: =MAX(0,SUMIFS(Journals!$L$9:$L$1003252,Journals!$D$9:$D$1003252,">"&$E$7,Journals!$D$9:$D$1003252,"<"&$E$8,Journals!$J$9:$J$1003252,"Interest Receivables from Bond")-SUMIFS(Journals!$K$9:$K$1003252,Journals!$D$9:$D$1003252,">"&$E$7,Journals!$D$9:$D$1003252,"<"&$E$8,Journals!$J$9:$J$1003252,"Interest Receivables from Bond")) -> 0 | J65: =SUMIFS(Journals!$K$9:$K$1003252,Journals!$D$9:$D$1003252,"<"&$F$7,Journals!$J$9:$J$1003252,"Interest Receivables from Bond")-SUMIFS(Journals!$L$9:$L$1003252,Journals!$D$9:$D$1003252,"<"&$F$7,Journals!$J$9:$J$1003252,"Interest Receivables from Bond") -> 0 | L65: =H65+J65-I65 -> 0
G66: Investment in T-Bill | H66: =MAX(0,SUMIFS(Journals!$K$9:$K$1003252,Journals!$D$9:$D$1003252,">"&$E$7,Journals!$D$9:$D$1003252,"<"&$E$8,Journals!$J$9:$J$1003252,"Investment in T-Bill")-SUMIFS(Journals!$L$9:$L$1003252,Journals!$D$9:$D$1003252,">"&$E$7,Journals!$D$9:$D$1003252,"<"&$E$8,Journals!$J$9:$J$1003252,"Investment in T-Bill")) -> 0 | I66: =MAX(0,SUMIFS(Journals!$L$9:$L$1003252,Journals!$D$9:$D$1003252,">"&$E$7,Journals!$D$9:$D$1003252,"<"&$E$8,Journals!$J$9:$J$1003252,"Investment in T-Bill")-SUMIFS(Journals!$K$9:$K$1003252,Journals!$D$9:$D$1003252,">"&$E$7,Journals!$D$9:$D$1003252,"<"&$E$8,Journals!$J$9:$J$1003252,"Investment in T-Bill")) -> 0 | J66: =SUMIFS(Journals!$K$9:$K$1003252,Journals!$D$9:$D$1003252,"<"&$F$7,Journals!$J$9:$J$1003252,"Investment in T-Bill")-SUMIFS(Journals!$L$9:$L$1003252,Journals!$D$9:$D$1003252,"<"&$F$7,Journals!$J$9:$J$1003252,"Investment in T-Bill") -> 0 | L66: =H66+J66-I66 -> 0
G67: Interest Receivables from T-Bill | H67: =MAX(0,SUMIFS(Journals!$K$9:$K$1003252,Journals!$D$9:$D$1003252,">"&$E$7,Journals!$D$9:$D$1003252,"<"&$E$8,Journals!$J$9:$J$1003252,"Interest Receivables from T-Bill")-SUMIFS(Journals!$L$9:$L$1003252,Journals!$D$9:$D$1003252,">"&$E$7,Journals!$D$9:$D$1003252,"<"&$E$8,Journals!$J$9:$J$1003252,"Interest Receivables from T-Bill")) -> 0 | I67: =MAX(0,SUMIFS(Journals!$L$9:$L$1003252,Journals!$D$9:$D$1003252,">"&$E$7,Journals!$D$9:$D$1003252,"<"&$E$8,Journals!$J$9:$J$1003252,"Interest Receivables from T-Bill")-SUMIFS(Journals!$K$9:$K$1003252,Journals!$D$9:$D$1003252,">"&$E$7,Journals!$D$9:$D$1003252,"<"&$E$8,Journals!$J$9:$J$1003252,"Interest Receivables from T-Bill")) -> 0 | J67: =SUMIFS(Journals!$K$9:$K$1003252,Journals!$D$9:$D$1003252,"<"&$F$7,Journals!$J$9:$J$1003252,"Interest Receivables from T-Bill")-SUMIFS(Journals!$L$9:$L$1003252,Journals!$D$9:$D$1003252,"<"&$F$7,Journals!$J$9:$J$1003252,"Interest Receivables from T-Bill") -> 0 | L67: =H67+J67-I67 -> 0

Sheet IS
A1: EKUSH GROWTH FUND
A2: STATEMENT OF PROFIT & LOSS AND OTHER COMPREHENSIVE INCOME
A3: For the period of January 1 to December 31, 2022
A5: Particulars | B5: Notes | C5: January 01 to December 31, 2022 | E5: January 01 to December 31, 2021
C6: Taka | E6: Taka
A8: INCOME
A9: Interest Income | B9: 12 | C9: =SUM('TB-C'!I20:I25) -> 929986.82 | E9: =SUM('TB-P'!I20:I25) -> 5098115.6
A10: Net gain on sale of marketable securities | B10: 13 | C10: =IF('TB-C'!I50>0,'TB-C'!I50,-'TB-C'!H50) -> 11929559 | E10: =IF('TB-P'!I50>0,'TB-P'!I50,-'TB-P'!H50) -> 12035292 | G10: =((C9+C10+C13)-C34)*0.7 -> 7999209.9 | H10: Total Div
A11: Net Gain on Sale of T-Bill | B11: 14 | C11: =IF('TB-C'!I51>0,'TB-C'!I51,-'TB-C'!H51) -> 0 | E11: =IF('TB-P'!I51>0,'TB-P'!I51,-'TB-P'!H51) -> 0
A12: Net Gain on Sale of T-Bond | B12: 15 | C12: =IF('TB-C'!I52>0,'TB-C'!I52,-'TB-C'!H52) -> 0 | E12: =IF('TB-P'!I52>0,'TB-P'!I52,-'TB-P'!H52) -> 4345089.5
A13: Dividend Income | B13: 14 | C13: ='TB-C'!$I$45 -> 365596.5 | E13: ='TB-P'!$I$45 -> 6250543.1 | G13: =G10/C41 -> 0.3835208 | H13: Per Unit Dev
A14: Dividend Reverse | B14: 15 | C14: =-'TB-C'!H45 -> 0 | E14: 0
A15: Unrealized gain/(loss) on securities | B15: 15 | C15: =IF('TB-C'!I38>0,-'TB-C'!I38,'TB-C'!H38) -> 8735993.6 | E15: =IF('TB-P'!$I$38>0,-'TB-P'!$I$38,'TB-P'!$H$38) -> 4306713.4
A16: Unrealized gain/(loss) on T-Bill | B16: 16 | C16: =IF('TB-C'!I39>0,-'TB-C'!I39,'TB-C'!H39) -> 0 | E16: =IF('TB-P'!I39>0,-'TB-P'!I39,'TB-P'!H39) -> 0
A17: Unrealized gain/(loss) on T-Bond | B17: 17 | C17: =IF('TB-C'!I40>0,-'TB-C'!I40,'TB-C'!H40) -> 0 | E17: =IF('TB-P'!I40>0,-'TB-P'!I40,'TB-P'!H40) -> -178264.59
A18: TOTAL | C18: =SUM(C9:C17) -> 21961136 | D18: =SUM(D9:D13) -> 0 | E18: =SUM(E9:E17) -> 31857489
A20: EXPENSES
A21: Management fees | C21: ='TB-C'!$H$33 -> 1183783.6 | E21: ='TB-P'!$H$33 -> 4093753.5
A22: BSEC Annual Fees | C22: ='TB-C'!$H$35 -> 0 | E22: ='TB-P'!$H$35 -> 180112.35
A23: Amortization of preliminary & issue expenses | C23: ='TB-C'!$H$32 -> 32967.033 | E23: ='TB-P'!$H$32 -> 142464.68
A24: CDBL settlement & demat charges | C24: 0 | E24: 0
A25: CDBL Charges | C25: ='TB-C'!$H$37 -> 13947.744 | E25: ='TB-P'!$H$37 -> 156183.06
A26: Trustee Fees | C26: ='TB-C'!$H$34 -> 56977.77 | E26: ='TB-P'!$H$34 -> 192222.02
A27: Custodian Fees | C27: ='TB-C'!$H$47 -> 0 | E27: ='TB-P'!$H$47 -> 128051.13
A28: IPO Application Fees | C28: ='TB-C'!$H$49 -> 0 | E28: ='TB-P'!$H$49 -> 0
A29: Brokerage Commission | C29: ='TB-C'!$H$27 -> 479495.29 | E29: ='TB-P'!$H$27 -> 978116.7
A30: Audit Fees | C30: ='TB-C'!$H$36 -> 0 | E30: ='TB-P'!$H$36 -> 57500
A31: Bank Charge & excise duty | C31: ='TB-C'!$H$26 -> 25803 | E31: ='TB-P'!$H$26 -> 86441.062
A32: Newspaper Publication expense | C32: 0 | E32: 0
A33: Other Operating Expense | C33: ='TB-C'!$H$44 -> 4725 | E33: ='TB-P'!$H$44 -> 85900
A34: TOTAL | C34: =SUM(C21:C33) -> 1797699.5 | D34: =SUM(D21:D33) -> 0 | E34: =SUM(E21:E33) -> 6100744.5
A36: Net Profit For the Period | C36: =C18-C34 -> 20163436 | E36: =E18-E34 -> 25756744
A38: Earnings Per Unit | B38: 16 | C38: =C36/C41 -> 0.96673263 | E38: =E36/E41 -> 1.3632525
A40: These financial statement should be read in conjunction with annexed notes.
A41: No of Units Outstanding | C41: =BS!C50 -> 20857304 | E41: =BS!E50 -> 18893597
A45: Head of Compliance | C45: Managing Director
A46: Ekush Wealth Management Limited | C46: Ekush Wealth Management Limited
A51: Trustee
A52: Shandhani Life Insurance Company Limited
C66: =C41*0.8 -> 16685843
C69: =C36-C15 -> 11427443
C74: =C69-C66 -> -5258400.4

Sheet BS
F1: =C34-C11-C14-C17 -> 2.4840622e+08
A3: EKUSH GROWTH FUND | F3: 2.3777851e+08 | I3: =I4/NAV -> 0.95940556
A4: STATEMENT OF FINANCIAL POSITION | F4: =F3-C10 -> 0.11154503 | I4: 2.5117446e+08 | J4: =TODAY() -> 46106
A5: As on March 31, 2022 | I5: 0
I6: 0
A7: Particulars | B7: Notes | C7: 45016 | E7: 44926
C8: Taka | E8: Taka | I8: =ABS(I10) -> 0
A9: Assets | H9: UG/(UL) | I9: FVA | J9: NAV*
A10: Investment at cost price | C10: ='TB-C'!$L$7 -> 2.3777851e+08 | E10: ='TB-P'!$L$7 -> 2.0327918e+08 | H10: =I4-C10 -> 13395951 | I10: =H10-C11 -> 0 | J10: =C34+I10+I12+I15 -> 2.6180217e+08
A11: fair value adjustment | C11: =IF('TB-C'!$L$38>0,'TB-C'!$L$38,-'TB-C'!$M$38) -> 13395951 | E11: =IF('TB-P'!$L$38>0,'TB-P'!$L$38,-'TB-P'!$M$38) -> 4659957.3 | H11: =J10/C50 -> 12.552062
A12: Investment at Market Price | B12: 1 | C12: =C10+C11 -> 2.5117446e+08 | E12: =E10+E11 -> 2.0793914e+08 | H12: T-Bill | I12: =ABS(I14) -> 0
A13: Investment at cost price T-Bill | C13: ='TB-C'!L66 -> 0 | E13: ='TB-P'!L66 -> 0 | H13: UG/(UL) | I13: FVA
A14: fair value adjustment T-Bill | C14: =IF('TB-C'!$L$39>0,'TB-C'!$L$39,-'TB-C'!$M$39) -> 0 | E14: =IF('TB-P'!$L$39>0,'TB-P'!$L$39,-'TB-P'!$M$39) -> 0 | H14: =I5-C13 -> 0 | I14: =H14-C14 -> 0
A15: Investment in T-Bills | B15: 1 | C15: =C14+C13 -> 0 | E15: =E14+E13 -> 0 | H15: T-Bond | I15: =ABS(I17) -> 0
A16: Investment at cost price T-Bond | C16: ='TB-C'!L61 -> 0 | E16: ='TB-P'!L61 -> 0 | H16: UG/(UL) | I16: FVA
A17: fair value adjustment T-Bond | C17: =IF('TB-C'!$L$40>0,'TB-C'!$L$40,-'TB-C'!$M$40) -> 0 | E17: =IF('TB-P'!$L$40>0,'TB-P'!$L$40,-'TB-P'!$M$40) -> 0 | H17: =I6-C16 -> 0 | I17: =H17-C17 -> 0
A18: Investment in T-Bonds | B18: 1 | C18: =C17+C16 -> 0 | E18: =E17+E16 -> 0
A19: Fixed Deposit Receipts (FDR) | B19: 2 | C19: ='TB-C'!$L$16 -> 4000000 | E19: ='TB-P'!$L$16 -> 13000000
A20: IPO Application | B20: 3 | C20: ='TB-C'!$L$48 -> 0 | E20: ='TB-P'!$L$48 -> 0 | G20: Midland | H20: 0001-1060000119 | I20: 81988.8 | J20: =SUM(I20:I28) -> 2305300.1
A21: Accounts Receivable | B21: 4 | C21: ='TB-C'!L8+SUM('TB-C'!L41:L42)+'TB-C'!$L$46+'TB-C'!$L$53+'TB-C'!H60+'TB-C'!L67 -> 5539453.8 | E21: ='TB-P'!L8+SUM('TB-P'!L41:L42)+'TB-P'!$L$46+'TB-P'!$L$53+'TB-P'!H60+'TB-P'!L67 -> 3296913 | H21: 0001-1090000974 | I21: 1748547 | J21: =J20-C23 -> 0.0099032684
A22: Advance, Deposit & Prepayments | C22: 0 | E22: 0 | G22: BRAC | H22: 1513-205101212001 | I22: 102656.91
A23: Cash & Cash Equivalent | B23: 5 | C23: ='TB-C'!$L$17 -> 2305300.1 | E23: ='TB-P'!$L$17 -> 512242.08 | H23: 2051-012120002 | I23: 183067.45
A24: Preliminary & Issue Expenses | B24: 6 | C24: ='TB-C'!$L$9 -> 412087.91 | E24: ='TB-P'!$L$9 -> 445054.95 | G24: Modhumoti | H24: 1135-12700000002 | I24: 74188.59
A25: Total Assets | C25: =ROUND(SUM(C19:C24)+C12+C15+C18,1) -> 2.634313e+08 | E25: =ROUND(SUM(E19:E24)+E12+E15+E18,1) -> 2.2519335e+08 | G25: SBAC | H25: 2130001431 | I25: 2715.57
G26: MTB | H26: 1310-000147453 | I26: 88488.83
A27: Equity & Liabilities | G27: =E25-E41 -> 0 | H27: 1012-050203825 | I27: 23646.96
A28: Unitholders' Equity | G28: =C25-C41 -> 0 | I28: 0
A29: Unitholders' Equity
A30: Unit Capital | B30: 7 | C30: ='TB-C'!$M$18 -> 208573040 | E30: ='TB-P'!$M$18 -> 188935970
A31: Unit Premium | B31: 8 | C31: ='TB-C'!$M$19 -> 7244346.2 | E31: ='TB-P'!$M$19 -> 2503906.3
A32: Dividend Equalization Reserve | C32: =E!E15 -> 0 | E32: =E!G15 -> 0
A33: Retained Earnings | C33: =E!$D$15 -> 45984785 | E33: =E!D29 -> 32434108
A34: Total Equity | C34: =SUM(C30:C33) -> 2.6180217e+08 | D34: =SUM(D30:D33) -> 0 | E34: =SUM(E30:E33) -> 2.2387398e+08
A35: Current Liabilities
A36: Accounts Payable | C36: ='TB-C'!$M$43+'TB-C'!M57+'TB-C'!M58+'TB-C'!M59 -> 740719.32 | E36: ='TB-P'!$M$43+'TB-P'!M57+'TB-P'!M58+'TB-P'!M59 -> 378365.15
A37: Dividend Payable | C37: ='TB-C'!M56 -> 0
A38: Liability for Expenses | B38: 9 | C38: =SUM('TB-C'!$M$10:$M$15) -> 888410.14 | E38: =SUM('TB-P'!$M$10:$M$15) -> 940996.72
A39: Total Liabilities | C39: =SUM(C36:C38) -> 1629129.5 | D39: =SUM(D36) -> 0 | E39: =SUM(E36:E38) -> 1319361.9
A41: Total Equity and Liabilities | C41: =ROUND(C34+C39,1) -> 2.634313e+08 | D41: =D34+D39 -> 0 | E41: =ROUND(E34+E39,1) -> 2.2519335e+08
A43: Net Asset Value (NAV) | C43: =C34 -> 2.6180217e+08 | E43: =E34 -> 2.2387398e+08
A45: Net Asset Value (NAV) per unit: | C45: =IFERROR(C43/C50,0) -> 12.552062 | E45: =IFERROR(E43/E50,0) -> 11.849199
A46: At Cost | B46: 10 | C46: =IFERROR((C34-C11-C14-C17)/C50,0) -> 11.909795 | E46: =IFERROR((E34-E11)/E50,0) -> 11.602556
A47: At Market Price | B47: 11 | C47: =IFERROR((C34)/(C50),0) -> 12.552062 | E47: =IFERROR((E34)/(E50),0) -> 11.849199 | G47: =C47+0.35 -> 12.902062
A49: These financial statement should be read in conjunction with annexed notes.
A50: No of Units Outstanding | C50: =ROUND(C30/10,0) -> 20857304 | E50: =ROUND(E30/10,0) -> 18893597
A55: Head of Compliance | C55: Managing Director
A56: Ekush Wealth Management Limited | C56: Ekush Wealth Management Limited
A61: Trustee
A62: Shandhani Life Insurance Company Limited

Sheet E
A1: EKUSH GROWTH FUND
A2: STATEMENT OF CHANGES IN EQUITY
A3: For the period from January 1 to December 31, 2022
A6: Particulars | B6: Unit Capital | C6: Unit Premium Reserve | D6: Retained Earnings | E6: Dividend Equalization Reserve | F6: Total Equity
A8: Opening Balance | B8: ='TB-C'!$K$18 -> 188935970 | C8: ='TB-C'!K19 -> 2503906.3 | D8: =SUM('TB-C'!$O$7:$O$218)-SUM('TB-C'!$N$7:$N$218) -> 32434108 | E8: 0 | F8: =SUM(B8:E8) -> 2.2387398e+08
A9: Unit capital raised during the period | B9: ='TB-C'!D18 -> 0 | C9: ='TB-C'!I19 -> 7480353.9 | D9: 0 | E9: 0 | F9: =SUM(B9:E9) -> 7480353.9
A10: Unit surrendered | B10: =-'TB-C'!C18 -> 0 | C10: =-'TB-C'!H19 -> -2739914 | D10: 0 | E10: 0 | F10: =SUM(B10:E10) -> -2739914
A11: Dividend Equalization Reserve | B11: 0 | C11: 0 | D11: =-'TB-C'!M54 -> 0 | E11: ='TB-C'!M54 -> 0 | F11: =SUM(B11:E11) -> 0
A12: Dividend Payable | B12: 0 | C12: 0 | D12: =-'TB-C'!M56 -> 0 | E12: 0 | F12: =SUM(B12:E12) -> 0
A13: Dividend paid during the year | B13: 0 | C13: 0 | D13: =-'TB-C'!H56 -> -6612758.9 | E13: 0 | F13: =SUM(B13:E13) -> -6612758.9
A14: Net profit during the period | B14: 0 | C14: 0 | D14: =IS!$C$36 -> 20163436 | E14: 0 | F14: =SUM(B14:E14) -> 20163436
A15: Ending Balance | B15: =SUM(B8:B14) -> 188935970 | C15: =SUM(C8:C14) -> 7244346.2 | D15: =SUM(D8:D14) -> 45984785 | E15: =SUM(E8:E14) -> 0 | F15: =SUM(F8:F14) -> 2.421651e+08
A18: For the period from January 1 to December 31, 2021
A20: Particulars | B20: Unit Capital | C20: Unit Premium Reserve | D20: Retained Earnings | E20: Dividend Equalization Reserve | F20: Total Equity
A22: Opening Balance | B22: ='TB-P'!$K$18 -> 160875820 | C22: ='TB-P'!K19 -> -2507109.7 | D22: =SUM('TB-P'!$O$7:$O$211)-SUM('TB-P'!$N$7:$N$211) -> 14721154 | E22: ='TB-P'!K54 -> 0 | F22: =SUM(B22:E22) -> 1.7308986e+08
A23: Unit capital raised during the period | B23: ='TB-P'!I18 -> 40652580 | C23: ='TB-P'!I19 -> 7019419.9 | D23: 0 | E23: 0 | F23: =SUM(B23:E23) -> 47672000
A24: Unit surrendered | B24: =-'TB-P'!H18 -> -12592430 | C24: =-'TB-P'!H19 -> -2008404 | D24: 0 | E24: 0 | F24: =SUM(B24:E24) -> -14600834
A25: Dividend Equalization Reserve | B25: 0 | C25: 0 | D25: =-'TB-P'!K54 -> 0 | E25: ='TB-P'!I54 -> 0 | F25: =SUM(B25:E25) -> 0
A26: Dividend Payable | B26: 0 | C26: 0 | D26: ='TB-P'!H56-'TB-P'!I56 -> 0 | E26: 0 | F26: =SUM(B26:E26) -> 0
A27: Dividend paid during the year | B27: 0 | C27: 0 | D27: =-'TB-P'!H56 -> -8043791 | E27: 0 | F27: =SUM(B27:E27) -> -8043791
A28: Net profit during the period | B28: 0 | C28: 0 | D28: =IS!$E$36 -> 25756744 | E28: 0 | F28: =SUM(B28:E28) -> 25756744
A29: Ending Balance | B29: =SUM(B22:B28) -> 188935970 | C29: =SUM(C22:C28) -> 2503906.3 | D29: =SUM(D22:D28) -> 32434108 | E29: =SUM(E22:E28) -> 0 | F29: =SUM(F22:F28) -> 2.2387398e+08
A31: These financial statement should be read in conjunction with annexed notes.
A35: Head of Compliance | C35: Managing Director
A36: Ekush Wealth Management Limited | C36: Ekush Wealth Management Limited
A41: Trustee
A42: Shandhani Life Insurance Company Limited

Sheet CF
A1: EKUSH GROWTH FUND
A2: STATEMENT OF CASH FLOW
A3: For the period from January 01 to December 31, 2022
A5: Particulars | B5: January 01 to December 31, 2022 | D5: January 01 to December 31, 2021
B6: Taka | D6: Taka | G6: BS | H6: =BS!C23 -> 2305300.1 | I6: =BS!E23 -> 512242.08
A8: Cash flows from operating activities: | G8: Difference | H8: =H6-B44 -> -3620314.1 | I8: =D44-BS!E23 -> #REF!
A9: Interest Income | B9: 4773015.5 | D9: ='TB-P'!I20-'TB-P'!H41+'TB-P'!#REF!-'TB-P'!#REF! -> #REF!
A10: Gain on Sale of Share and Securities | B10: =IS!C10 -> 11929559 | D10: =IS!E10 -> 12035292
A11: Gain on Sale of T-Bill | B11: =IS!C11 -> 0
A12: Gain on Sale of T-Bond | B12: =IS!C12 -> 0
A13: Dividend Income | B13: ='TB-C'!I46+('TB-C'!I45-'TB-C'!H46) -> 1707402.5 | D13: ='TB-P'!I46+('TB-P'!I45-'TB-P'!H46) -> 5949483.5
A14: Management Fees | B14: =-'TB-C'!H10 -> -1235848 | D14: ='TB-P'!I10-'TB-P'!H33 -> -3928691.8
A15: Trustee Fees | B15: =-'TB-C'!H11 -> 0 | D15: =-IF('TB-P'!I11='TB-P'!H34,0,IF('TB-P'!I11=0,'TB-P'!H11+'TB-P'!H34,'TB-P'!H34-'TB-P'!I11)) -> -172611.57
A16: BSEC Annual Fee | B16: =-IF('TB-C'!I13='TB-C'!H35,0,IF('TB-C'!I13=0,'TB-C'!H13+'TB-C'!H35,'TB-C'!H35-'TB-C'!H13)) -> 0 | D16: =-IF('TB-P'!I13='TB-P'!H35,0,IF('TB-P'!I13=0,'TB-P'!H13+'TB-P'!H35,'TB-P'!H35-'TB-P'!H13)) -> -180112.35
A17: Brokerage commission | B17: =-IS!$C$29 -> -479495.29 | D17: =-IS!E29 -> -978116.7
A18: Bank Charges & Excise Duty | B18: =-IS!$C$31 -> -25803 | D18: =-IS!E31 -> -86441.062
A19: CDBL Fee | B19: =-IF('TB-C'!I126='TB-C'!H37,0,IF('TB-C'!I15=0,'TB-C'!H15+'TB-C'!H37,'TB-C'!H37-'TB-C'!H15)) -> -13947.744 | D19: =-IF('TB-P'!I127='TB-P'!H37,0,IF('TB-P'!I15=0,'TB-P'!H15+'TB-P'!H37,'TB-P'!H37-'TB-P'!H15)) -> -156183.06
A20: Custodian Fee | B20: =-'TB-C'!H47 -> 0 | D20: =-IF('TB-P'!I12='TB-P'!H47,0,IF('TB-P'!I12=0,'TB-P'!H12+'TB-P'!H47,'TB-P'!H47-'TB-P'!H12)) -> -128051.13
A21: IPO Application Fee | B21: =-'TB-C'!$H$49 -> 0 | D21: =-'TB-P'!$H$49 -> 0
A22: Audit Fee | B22: =-'TB-C'!$H$36-'TB-C'!$H$14+'TB-C'!I14 -> -57500 | D22: =-'TB-P'!H14 -> 0
A23: Other Operating Expense | B23: =-'TB-C'!$H$44 -> -4725 | D23: =-'TB-P'!$H$44 -> -85900
A24: Net Cash Flow from Operating Activities | B24: =SUM(B9:B23) -> 16592658 | C24: =SUM(C9:C18) -> 0 | D24: =SUM(D9:D23) -> #REF!
A26: Cash Flow from Investing Activities:
A27: Net Investment in Shares and securities | B27: =IF('TB-C'!$H$7>0,-'TB-C'!$H$7,'TB-C'!$I$7)+'TB-C'!I43-'TB-C'!H43+'TB-C'!I53-'TB-C'!H53 -> -37944037 | D27: =IF('TB-P'!$H$7>0,-'TB-P'!$H$7,'TB-P'!$I$7)+'TB-P'!$I$43-'TB-P'!$H$53-'TB-P'!H66 -> -1.0436869e+08
A28: Net Investment in T- Bills | B28: ='TB-C'!I66-'TB-C'!H66 -> 0 | D28: 0
A29: Net Investment in T- Bonds | B29: ='TB-C'!I61-'TB-C'!H61 -> 0 | D29: 0
A30: IPO Application | B30: ='TB-C'!I48-'TB-C'!H48 -> 0 | D30: =-'TB-P'!$H$48 -> 0
A31: Investment in FDR | B31: ='TB-C'!I16-'TB-C'!H16 -> 9000000 | D31: =-'TB-C'!J16 -> -13000000
A32: Proceeds from encashment of FDR | B32: ='TB-C'!I60 -> 0 | D32: 0
A33: Preliminary & issue expenses | B33: =-SUMIFS(Journals!$K$9:$K$16452,Journals!$D$9:$D$16452,">"&'TB-C'!$E$7,Journals!$D$9:$D$16452,"<"&'TB-C'!$E$8,Journals!$G$9:$G$16452,"c",Journals!$J$9:$J$16452,"Preliminary & issue expenses") -> 0 | D33: =-'TB-P'!H9-'TB-P'!H32 -> -142464.68
A34: Net Cash from Investing Activities | B34: =SUM(B27:B33) -> -28944037 | C34: =SUM(C27:C33) -> 0 | D34: =SUM(D27:D33) -> -1.1751115e+08
A36: Cash Flow from Financing Activities:
A37: Proceeds from issuance of units | B37: ='TB-C'!I18+'TB-C'!I19 -> 37139544 | D37: ='TB-P'!I18+'TB-P'!I19 -> 47672000
A38: Proceeds made for re-purchase of units | B38: =-('TB-C'!H18+'TB-C'!H19) -> -12762034 | D38: =-'TB-P'!H18-'TB-P'!H19 -> -14600834
A39: Dividend Payment | B39: =-'TB-C'!H56 -> -6612758.9 | D39: =-'TB-C'!J56 -> -12305680
A40: Net Cash from Financing Activities | B40: =SUM(B37:B39) -> 17764751 | C40: =C39 -> 0 | D40: =SUM(D37:D39) -> 20765486
A42: Net Cash Flows | B42: =SUM(B24,B34,B40) -> 5413372.1 | C42: =SUM(C24,C34,C40) -> 0 | D42: =SUM(D24,D34,D40) -> #REF!
A43: Cash & Cash Equivalent at the beginning of the Period | B43: ='TB-C'!J17 -> 512242.08 | D43: ='TB-P'!J17 -> 34420156
A44: Cash & Cash Equivalent at the end of the Period | B44: =B42+B43 -> 5925614.2 | C44: =C42+C43 -> 0 | D44: =D42+D43 -> #REF!
A46: Net Operating Cash Flow per Unit | B46: =B24/B48 -> 0.79553224 | D46: =IFERROR(D24/D48,0) -> 0
A48: No of Units Outstanding | B48: =BS!C50 -> 20857304 | D48: =BS!E50 -> 18893597
A49: These financial statement should be read in conjunction with annexed notes.
A54: Head of Compliance | B54: Managing Director
A55: Ekush Wealth Management Limited | B55: Ekush Wealth Management Limited
A60: Trustee
A61: Shandhani Life Insurance Company Limited

Sheet W C & I
C4: Date | D4: =TODAY() -> 46106
C5: Fund Initiation Day | D5: 43908
C6: Last Day of Accounting Period | D6: 44196
C8: Net Asset Value | D8: =BS!C34 -> 2.6180217e+08
C9: Preliminary & Issue Expenses | D9: 1000000
C10: Fixed Deposit Receipts (FDR):
C11: Institution | D11: Amount | E11: Int. Rate | F11: Monthly Interest | G11: Total Interest | H11: Initiation Date | I11: Tenure (M) | J11: Today | K11: Accrued | L11: Entried | O11: 8000000 | P11: 8000000 | Q11: 6000000 | R11: 6000000 | S11: 8000000 | T11: 8000000 | U11: 5000000 | V11: 5000000 | W11: 5000000 | X11: 8000000 | Y11: 8000000 | AA11: =SUM(O11:Z11) -> 75000000
C12: IDLC | D12: 80000000 | E12: 0.065 | F12: =(D12*E12)/12 -> 433333.33 | G12: =F12*3 -> 1300000 | H12: 44622 | I12: 3 | J12: =MIN(TODAY(),44714) -> 44714 | K12: =G12*((J12-H12)/(30*I12)) -> 1328888.9 | O12: 130000 | P12: 130000 | Q12: 97500 | R12: 97500 | S12: 130000 | T12: 130000 | U12: 81250 | V12: 81250 | W12: 81250 | X12: 130000 | Y12: 130000 | AA12: =SUM(O12:Z12) -> 1218750
C13: IPDC | D13: 40000000 | E13: 0.0655 | F13: =(D13*E13)/12 -> 218333.33 | G13: =F13*3 -> 655000 | H13: 44629 | I13: 3 | J13: =MIN(TODAY(),44720) -> 44720 | K13: =G13*((J13-H13)/(30*I13)) -> 662277.78 | O13: 6500 | P13: 6500 | Q13: 4875 | R13: 4875 | S13: 6500 | T13: 6500 | U13: 4062.5 | V13: 4062.5 | W13: 4062.5 | X13: 6500 | Y13: 6500 | AA13: =SUM(O13:Z13) -> 60937.5
C14: DBH | D14: 5000000 | E14: 0.06 | F14: =(D14*E14)/12 -> 25000 | G14: =F14*3 -> 75000 | H14: 44629 | I14: 3 | J14: =MIN(TODAY(),44720) -> 44720 | K14: =G14*((J14-H14)/(30*I14)) -> 75833.333 | O14: =O11+O12-O13 -> 8123500 | P14: =P11+P12-P13 -> 8123500 | Q14: =Q11+Q12-Q13 -> 6092625 | R14: =R11+R12-R13 -> 6092625 | S14: =S11+S12-S13 -> 8123500 | T14: =T11+T12-T13 -> 8123500 | U14: =U11+U12-U13 -> 5077187.5 | V14: =V11+V12-V13 -> 5077187.5 | ... Y14: =Y11+Y12-Y13 -> 8123500 | AA14: =SUM(O14:Z14) -> 76157812 | AB14: =AA14+SUM(O16:U16)+U17 -> 1.1623969e+08
G15: =SUM(G12:G14) -> 2030000 | K15: =SUM(K12:K14) -> 2067000 | L15: =SUMIFS(Journals!$K:$K,Journals!$J:$J,"Interest Receivables from FDR",Journals!$D:$D,">="&H12,Journals!$D:$D,"<="&J12) -> 2024861.1 | M15: =K15-L15 -> 42138.889
O16: 5000000 | P16: 6000000 | Q16: 6000000 | R16: 6000000 | S16: 7000000 | T16: 5000000 | U16: 5000000
O17: 81875 | P17: 98250 | Q17: 98250 | R17: 98250 | S17: 114625 | T17: 81875 | U17: 81875
O18: PAID | P18: PAID | Q18: PAID | R18: PAID | S18: PAID | T18: PAID
Q28: =SUM(O11:Z11)-Z11 -> 75000000
D31: =SUM(D12:D30) -> 125000000 | G31: =SUM(G12:G30) -> 4060000
C33: Weekly Expenses: | E33: Daily
C34: Preliminary & Issue Expenses | D34: =D9/(52*7) -> 2747.2527 | E34: =D34/7 -> 392.46468
C35: Management Fee | D35: =(IF(NAV<50000001,NAV*2.5%,IF(NAV<250000001,(50000000*2.5%)+(NAV-50000000)*2%,IF(NAV<500000001,(50000000*2.5%)+(200000000*2%)+((NAV-250000000)*1.5%),(50000000*2.5%)+(200000000*2%)+(250000000*1.5%)+((NAV-500000000)*1%)))))/52 -> 104366.01 | E35: =(IF(NAV<50000001,NAV*2.5%,IF(NAV<250000001,(50000000*2.5%)+(NAV-50000000)*2%,IF(NAV<500000001,(50000000*2.5%)+(200000000*2%)+((NAV-250000000)*1.5%),(50000000*2.5%)+(200000000*2%)+(250000000*1.5%)+((NAV-500000000)*1%)))))/365 -> 14868.582 | G35: =50000000*2.5% -> 1250000 | H35: =G35/52 -> 24038.462
C36: Trustee Fee | D36: =BS!C34*0.1%/52 -> 5034.6571 | E36: =BS!C34*0.1%/365 -> 717.26622 | G36: =200000000*2% -> 4000000 | H36: =G36/52 -> 76923.077
C37: BSEC Annual Fee | D37: =MAX(50000,BS!C25*0.1%)*7/('W C & I'!D6-'W C & I'!D5) -> 6402.8441 | H37: =SUM(H35:H36) -> 100961.54
C38: Audit Fee | D38: =30000*7/(D6-D5) -> 729.16667
C39: CDBL Fee | D39: 0

Sheet Bank Interest
C1: Midland | G1: Brac | K1: Modhumoti | M1: SBAC | O1: MTB | Q1: NRB
A2: =TODAY() -> 46106 | B2: Date | C2: 0001-1060000119 | E2: 0001-1090000974 | G2: 1513-205101212001 | I2: 2051-012120002 | K2: 1135-12700000002 | M2: 2130001431 | O2: 1310-000147453 | Q2: 1012-050203825
C3: Amount | D3: Interest | E3: Amount | F3: Interest | G3: Amount | H3: Interest | I3: Amount | J3: Interest | K3: Amount | L3: Interest | M3: Amount | N3: Interest | O3: Amount | P3: Interest | Q3: Amount | R3: Interest
B4: 45474 | C4: 96518.52 | D4: =(C4*7.5%)/360 -> 20.108025 | E4: 26185531 | F4: =(E4*7.5%)/360 -> 5455.3189 | G4: 41250.71 | H4: =(G4*4.5%)/360 -> 5.1563387 | I4: 174968.3 | J4: =(I4*4.5%)/360 -> 21.871037 | K4: 75338.59 | L4: =(K4*6.5%)/360 -> 13.602801 | M4: 3567.32 | N4: =(M4*2.5%)/360 -> 0.24773056 | O4: 92838.69 | P4: =(O4*6.5%)/360 -> 16.762541 | Q4: 7512779.9 | R4: =(Q4*8%)/360 -> 1669.5066
B5: =B4+1 -> 45475 | C5: 111139.67 | D5: =(C5*7.5%)/360 -> 23.154098 | E5: 26179781 | F5: =(E5*7.5%)/360 -> 5454.121 | G5: 41250.71 | H5: =(G5*4.5%)/360 -> 5.1563387 | I5: 174968.3 | J5: =(I5*4.5%)/360 -> 21.871037 | K5: 75338.59 | L5: =(K5*6.5%)/360 -> 13.602801 | M5: 3567.32 | N5: =(M5*2.5%)/360 -> 0.24773056 | O5: 92838.69 | P5: =(O5*6.5%)/360 -> 16.762541 | Q5: 7512779.9 | R5: =(Q5*8%)/360 -> 1669.5066
B6: =B5+1 -> 45476 | C6: 111039.67 | D6: =(C6*7.5%)/360 -> 23.133265 | E6: 20179781 | F6: =(E6*7.5%)/360 -> 4204.121 | G6: 41250.71 | H6: =(G6*4.5%)/360 -> 5.1563387 | I6: 174968.3 | J6: =(I6*4.5%)/360 -> 21.871037 | K6: 75338.59 | L6: =(K6*6.5%)/360 -> 13.602801 | M6: 3567.32 | N6: =(M6*2.5%)/360 -> 0.24773056 | O6: 92838.69 | P6: =(O6*6.5%)/360 -> 16.762541 | Q6: 7512779.9 | R6: =(Q6*8%)/360 -> 1669.5066
B7: =B6+1 -> 45477 | C7: 5111039.7 | D7: =(C7*7.5%)/360 -> 1064.7999 | E7: 23988609 | F7: =(E7*7.5%)/360 -> 4997.6269 | G7: 41250.71 | H7: =(G7*4.5%)/360 -> 5.1563387 | I7: 174968.3 | J7: =(I7*4.5%)/360 -> 21.871037 | K7: 75338.59 | L7: =(K7*6.5%)/360 -> 13.602801 | M7: 3567.32 | N7: =(M7*2.5%)/360 -> 0.24773056 | O7: 92838.69 | P7: =(O7*6.5%)/360 -> 16.762541 | Q7: 7512779.9 | R7: =(Q7*8%)/360 -> 1669.5066
B8: =B7+1 -> 45478 | C8: 5111039.7 | D8: =(C8*7.5%)/360 -> 1064.7999 | E8: 23988609 | F8: =(E8*7.5%)/360 -> 4997.6269 | G8: 41250.71 | H8: =(G8*4.5%)/360 -> 5.1563387 | I8: 174968.3 | J8: =(I8*4.5%)/360 -> 21.871037 | K8: 75338.59 | L8: =(K8*6.5%)/360 -> 13.602801 | M8: 3567.32 | N8: =(M8*2.5%)/360 -> 0.24773056 | O8: 92838.69 | P8: =(O8*6.5%)/360 -> 16.762541 | Q8: 7512779.9 | R8: =(Q8*8%)/360 -> 1669.5066
B9: =B8+1 -> 45479 | C9: 5111039.7 | D9: =(C9*7.5%)/360 -> 1064.7999 | E9: 23988609 | F9: =(E9*7.5%)/360 -> 4997.6269 | G9: 41250.71 | H9: =(G9*4.5%)/360 -> 5.1563387 | I9: 174968.3 | J9: =(I9*4.5%)/360 -> 21.871037 | K9: 75338.59 | L9: =(K9*6.5%)/360 -> 13.602801 | M9: 3567.32 | N9: =(M9*2.5%)/360 -> 0.24773056 | O9: 92838.69 | P9: =(O9*6.5%)/360 -> 16.762541 | Q9: 7512779.9 | R9: =(Q9*8%)/360 -> 1669.5066
B10: =B9+1 -> 45480 | C10: 5111039.7 | D10: =(C10*7.5%)/360 -> 1064.7999 | E10: 23988609 | F10: =(E10*7.5%)/360 -> 4997.6269 | G10: 41250.71 | H10: =(G10*4.5%)/360 -> 5.1563387 | I10: 174968.3 | J10: =(I10*4.5%)/360 -> 21.871037 | K10: 75338.59 | L10: =(K10*6.5%)/360 -> 13.602801 | M10: 3567.32 | N10: =(M10*2.5%)/360 -> 0.24773056 | O10: 92838.69 | P10: =(O10*6.5%)/360 -> 16.762541 | Q10: 7512779.9 | R10: =(Q10*8%)/360 -> 1669.5066
B11: =B10+1 -> 45481 | C11: 5111039.7 | D11: =(C11*7.5%)/360 -> 1064.7999 | E11: 23988609 | F11: =(E11*7.5%)/360 -> 4997.6269 | G11: 41250.71 | H11: =(G11*4.5%)/360 -> 5.1563387 | I11: 174968.3 | J11: =(I11*4.5%)/360 -> 21.871037 | K11: 75338.59 | L11: =(K11*6.5%)/360 -> 13.602801 | M11: 3567.32 | N11: =(M11*2.5%)/360 -> 0.24773056 | O11: 92838.69 | P11: =(O11*6.5%)/360 -> 16.762541 | Q11: 7512779.9 | R11: =(Q11*8%)/360 -> 1669.5066
B12: =B11+1 -> 45482 | C12: 5111039.7 | D12: =(C12*7.5%)/360 -> 1064.7999 | E12: 23702315 | F12: =(E12*7.5%)/360 -> 4937.9823 | G12: 41250.71 | H12: =(G12*4.5%)/360 -> 5.1563387 | I12: 174968.3 | J12: =(I12*4.5%)/360 -> 21.871037 | K12: 75338.59 | L12: =(K12*6.5%)/360 -> 13.602801 | M12: 3567.32 | N12: =(M12*2.5%)/360 -> 0.24773056 | O12: 92838.69 | P12: =(O12*6.5%)/360 -> 16.762541 | Q12: 7512779.9 | R12: =(Q12*8%)/360 -> 1669.5066
B13: =B12+1 -> 45483 | C13: 5111039.7 | D13: =(C13*7.5%)/360 -> 1064.7999 | E13: 23702315 | F13: =(E13*7.5%)/360 -> 4937.9823 | G13: 41250.71 | H13: =(G13*4.5%)/360 -> 5.1563387 | I13: 174968.3 | J13: =(I13*4.5%)/360 -> 21.871037 | K13: 75338.59 | L13: =(K13*6.5%)/360 -> 13.602801 | M13: 3567.32 | N13: =(M13*2.5%)/360 -> 0.24773056 | O13: 92838.69 | P13: =(O13*6.5%)/360 -> 16.762541 | Q13: 7512779.9 | R13: =(Q13*8%)/360 -> 1669.5066
B14: =B13+1 -> 45484 | C14: 3602639.7 | D14: =(C14*7.5%)/360 -> 750.54993 | E14: 24614470 | F14: =(E14*7.5%)/360 -> 5128.0147 | G14: 41250.71 | H14: =(G14*4.5%)/360 -> 5.1563387 | I14: 277458.3 | J14: =(I14*4.5%)/360 -> 34.682288 | K14: 75338.59 | L14: =(K14*6.5%)/360 -> 13.602801 | M14: 3567.32 | N14: =(M14*2.5%)/360 -> 0.24773056 | O14: 92838.69 | P14: =(O14*6.5%)/360 -> 16.762541 | Q14: 7512779.9 | R14: =(Q14*8%)/360 -> 1669.5066
B15: =B14+1 -> 45485 | C15: 3602639.7 | D15: =(C15*7.5%)/360 -> 750.54993 | E15: 24614470 | F15: =(E15*7.5%)/360 -> 5128.0147 | G15: 41250.71 | H15: =(G15*4.5%)/360 -> 5.1563387 | I15: 277458.3 | J15: =(I15*4.5%)/360 -> 34.682288 | K15: 75338.59 | L15: =(K15*6.5%)/360 -> 13.602801 | M15: 3567.32 | N15: =(M15*2.5%)/360 -> 0.24773056 | O15: 92838.69 | P15: =(O15*6.5%)/360 -> 16.762541 | Q15: 7512779.9 | R15: =(Q15*8%)/360 -> 1669.5066
B16: =B15+1 -> 45486 | C16: 3602639.7 | D16: =(C16*7.5%)/360 -> 750.54993 | E16: 24614470 | F16: =(E16*7.5%)/360 -> 5128.0147 | G16: 41250.71 | H16: =(G16*4.5%)/360 -> 5.1563387 | I16: 277458.3 | J16: =(I16*4.5%)/360 -> 34.682288 | K16: 75338.59 | L16: =(K16*6.5%)/360 -> 13.602801 | M16: 3567.32 | N16: =(M16*2.5%)/360 -> 0.24773056 | O16: 92838.69 | P16: =(O16*6.5%)/360 -> 16.762541 | Q16: 7512779.9 | R16: =(Q16*8%)/360 -> 1669.5066
... B184: =B183+1 -> 45654 | C184: 5965364.2 | D184: =(C184*7.5%)/360 -> 1242.7842 | E184: 19387888 | F184: =(E184*7.5%)/360 -> 4039.1433 | G184: 83250.71 | H184: =(G184*4.5%)/360 -> 10.406339 | I184: 115933.39 | J184: =(I184*4.5%)/360 -> 14.491674 | K184: 75352.59 | L184: =(K184*6.5%)/360 -> 13.605329 | M184: 3581.32 | N184: =(M184*2.5%)/360 -> 0.24870278 | O184: 92852.69 | P184: =(O184*6.5%)/360 -> 16.765069 | Q184: 7512779.9 | R184: =(Q184*8%)/360 -> 1669.5066
B189: 45658 | C189: 6050314.2 | D189: =(C189*7.5%)/360 -> 1260.4821 | E189: 19935405 | F189: =(E189*7.5%)/360 -> 4153.2094 | G189: 92720.97 | H189: =(G189*4.5%)/360 -> 11.590121 | I189: 119400.16 | J189: =(I189*4.5%)/360 -> 14.92502 | K189: 74993.59 | L189: =(K189*6.5%)/360 -> 13.540509 | M189: 2677.67 | N189: =(M189*2.5%)/360 -> 0.18594931 | O189: 89319.01 | P189: =(O189*6.5%)/360 -> 16.127043 | Q189: 8324342 | R189: =(Q189*8%)/360 -> 1849.8538
B190: =B189+1 -> 45659 | C190: 6050314.2 | D190: =(C190*7.5%)/360 -> 1260.4821 | E190: 19994718 | F190: =(E190*7.5%)/360 -> 4165.5663 | G190: 92720.97 | H190: =(G190*4.5%)/360 -> 11.590121 | I190: 119400.16 | J190: =(I190*4.5%)/360 -> 14.92502 | K190: 74993.59 | L190: =(K190*6.5%)/360 -> 13.540509 | M190: 2677.67 | N190: =(M190*2.5%)/360 -> 0.18594931 | O190: 89319.01 | P190: =(O190*6.5%)/360 -> 16.127043 | Q190: 8324342 | R190: =(Q190*8%)/360 -> 1849.8538
B191: =B190+1 -> 45660 | C191: 6050314.2 | D191: =(C191*7.5%)/360 -> 1260.4821 | E191: 19994718 | F191: =(E191*7.5%)/360 -> 4165.5663 | G191: 92720.97 | H191: =(G191*4.5%)/360 -> 11.590121 | I191: 119400.16 | J191: =(I191*4.5%)/360 -> 14.92502 | K191: 74993.59 | L191: =(K191*6.5%)/360 -> 13.540509 | M191: 2677.67 | N191: =(M191*2.5%)/360 -> 0.18594931 | O191: 89319.01 | P191: =(O191*6.5%)/360 -> 16.127043 | Q191: 8324342 | R191: =(Q191*8%)/360 -> 1849.8538
B192: =B191+1 -> 45661 | C192: 6050314.2 | D192: =(C192*7.5%)/360 -> 1260.4821 | E192: 19994718 | F192: =(E192*7.5%)/360 -> 4165.5663 | G192: 92720.97 | H192: =(G192*4.5%)/360 -> 11.590121 | I192: 119400.16 | J192: =(I192*4.5%)/360 -> 14.92502 | K192: 74993.59 | L192: =(K192*6.5%)/360 -> 13.540509 | M192: 2677.67 | N192: =(M192*2.5%)/360 -> 0.18594931 | O192: 89319.01 | P192: =(O192*6.5%)/360 -> 16.127043 | Q192: 8324342 | R192: =(Q192*8%)/360 -> 1849.8538
B193: =B192+1 -> 45662 | C193: 6050314.2 | D193: =(C193*7.5%)/360 -> 1260.4821 | E193: 19994718 | F193: =(E193*7.5%)/360 -> 4165.5663 | G193: 92720.97 | H193: =(G193*4.5%)/360 -> 11.590121 | I193: 119400.16 | J193: =(I193*4.5%)/360 -> 14.92502 | K193: 74993.59 | L193: =(K193*6.5%)/360 -> 13.540509 | M193: 2677.67 | N193: =(M193*2.5%)/360 -> 0.18594931 | O193: 89319.01 | P193: =(O193*6.5%)/360 -> 16.127043 | Q193: 8324342 | R193: =(Q193*8%)/360 -> 1849.8538
B194: =B193+1 -> 45663 | C194: 14050314 | D194: =(C194*7.5%)/360 -> 2927.1488 | E194: 19504780 | F194: =(E194*7.5%)/360 -> 4063.4958 | G194: 92720.97 | H194: =(G194*4.5%)/360 -> 11.590121 | I194: 234390.16 | J194: =(I194*4.5%)/360 -> 29.29877 | K194: 74993.59 | L194: =(K194*6.5%)/360 -> 13.540509 | M194: 2677.67 | N194: =(M194*2.5%)/360 -> 0.18594931 | O194: 89319.01 | P194: =(O194*6.5%)/360 -> 16.127043 | Q194: 324242.06 | R194: =(Q194*8%)/360 -> 72.053791
B195: =B194+1 -> 45664 | C195: 4050314.2 | D195: =(C195*7.5%)/360 -> 843.81547 | E195: 29504780 | F195: =(E195*7.5%)/360 -> 6146.8292 | G195: 92720.97 | H195: =(G195*4.5%)/360 -> 11.590121 | I195: 234390.16 | J195: =(I195*4.5%)/360 -> 29.29877 | K195: 74993.59 | L195: =(K195*6.5%)/360 -> 13.540509 | M195: 2677.67 | N195: =(M195*2.5%)/360 -> 0.18594931 | O195: 89319.01 | P195: =(O195*6.5%)/360 -> 16.127043 | Q195: 324242.06 | R195: =(Q195*8%)/360 -> 72.053791
B196: =B195+1 -> 45665 | C196: 4050314.2 | D196: =(C196*7.5%)/360 -> 843.81547 | E196: 28909611 | F196: =(E196*7.5%)/360 -> 6022.8356 | G196: 92720.97 | H196: =(G196*4.5%)/360 -> 11.590121 | I196: 234390.16 | J196: =(I196*4.5%)/360 -> 29.29877 | K196: 74993.59 | L196: =(K196*6.5%)/360 -> 13.540509 | M196: 2677.67 | N196: =(M196*2.5%)/360 -> 0.18594931 | O196: 89319.01 | P196: =(O196*6.5%)/360 -> 16.127043 | Q196: 324242.06 | R196: =(Q196*8%)/360 -> 72.053791
B197: =B196+1 -> 45666 | C197: 4050314.2 | D197: =(C197*7.5%)/360 -> 843.81547 | E197: 28909611 | F197: =(E197*7.5%)/360 -> 6022.8356 | G197: 92720.97 | H197: =(G197*4.5%)/360 -> 11.590121 | I197: 234390.16 | J197: =(I197*4.5%)/360 -> 29.29877 | K197: 74993.59 | L197: =(K197*6.5%)/360 -> 13.540509 | M197: 2677.67 | N197: =(M197*2.5%)/360 -> 0.18594931 | O197: 89319.01 | P197: =(O197*6.5%)/360 -> 16.127043 | Q197: 324242.06 | R197: =(Q197*8%)/360 -> 72.053791
B198: =B197+1 -> 45667 | C198: 4050314.2 | D198: =(C198*7.5%)/360 -> 843.81547 | E198: 28909611 | F198: =(E198*7.5%)/360 -> 6022.8356 | G198: 92720.97 | H198: =(G198*4.5%)/360 -> 11.590121 | I198: 234390.16 | J198: =(I198*4.5%)/360 -> 29.29877 | K198: 74993.59 | L198: =(K198*6.5%)/360 -> 13.540509 | M198: 2677.67 | N198: =(M198*2.5%)/360 -> 0.18594931 | O198: 89319.01 | P198: =(O198*6.5%)/360 -> 16.127043 | Q198: 324242.06 | R198: =(Q198*8%)/360 -> 72.053791
B199: =B198+1 -> 45668 | C199: 4050314.2 | D199: =(C199*7.5%)/360 -> 843.81547 | E199: 28909611 | F199: =(E199*7.5%)/360 -> 6022.8356 | G199: 92720.97 | H199: =(G199*4.5%)/360 -> 11.590121 | I199: 234390.16 | J199: =(I199*4.5%)/360 -> 29.29877 | K199: 74993.59 | L199: =(K199*6.5%)/360 -> 13.540509 | M199: 2677.67 | N199: =(M199*2.5%)/360 -> 0.18594931 | O199: 89319.01 | P199: =(O199*6.5%)/360 -> 16.127043 | Q199: 324242.06 | R199: =(Q199*8%)/360 -> 72.053791
B200: =B199+1 -> 45669 | C200: 4050314.2 | D200: =(C200*7.5%)/360 -> 843.81547 | E200: 28909611 | F200: =(E200*7.5%)/360 -> 6022.8356 | G200: 92720.97 | H200: =(G200*4.5%)/360 -> 11.590121 | I200: 234390.16 | J200: =(I200*4.5%)/360 -> 29.29877 | K200: 74993.59 | L200: =(K200*6.5%)/360 -> 13.540509 | M200: 2677.67 | N200: =(M200*2.5%)/360 -> 0.18594931 | O200: 89319.01 | P200: =(O200*6.5%)/360 -> 16.127043 | Q200: 324242.06 | R200: =(Q200*8%)/360 -> 72.053791
B201: =B200+1 -> 45670 | C201: 4050314.2 | D201: =(C201*7.5%)/360 -> 843.81547 | E201: 28745145 | F201: =(E201*7.5%)/360 -> 5988.5719 | G201: 92720.97 | H201: =(G201*4.5%)/360 -> 11.590121 | I201: 234390.16 | J201: =(I201*4.5%)/360 -> 29.29877 | K201: 74993.59 | L201: =(K201*6.5%)/360 -> 13.540509 | M201: 2677.67 | N201: =(M201*2.5%)/360 -> 0.18594931 | O201: 89319.01 | P201: =(O201*6.5%)/360 -> 16.127043 | Q201: 324242.06 | R201: =(Q201*8%)/360 -> 72.053791
... B307: =B306+1 -> 45776 | C307: 98062.95 | D307: =(C307*7.5%)/360 -> 20.429781 | E307: 8300422.4 | F307: =(E307*7.5%)/360 -> 1729.2547 | G307: 117720.97 | H307: =(G307*4.5%)/360 -> 14.715121 | I307: 176072.51 | J307: =(I307*4.5%)/360 -> 22.009064 | K307: 74993.59 | L307: =(K307*6.5%)/360 -> 13.540509 | M307: 2677.67 | N307: =(M307*2.5%)/360 -> 0.18594931 | O307: 89319.01 | P307: =(O307*6.5%)/360 -> 16.127043 | Q307: 53279.58 | R307: =(Q307*8%)/360 -> 11.839907
B308: =B307+1 -> 45777 | C308: 98062.95 | D308: =(C308*7.5%)/360 -> 20.429781 | E308: 1735884.2 | F308: =(E308*7.5%)/360 -> 361.64254 | G308: 117720.97 | H308: =(G308*4.5%)/360 -> 14.715121 | I308: 176072.51 | J308: =(I308*4.5%)/360 -> 22.009064 | K308: 74993.59 | L308: =(K308*6.5%)/360 -> 13.540509 | M308: 2677.67 | N308: =(M308*2.5%)/360 -> 0.18594931 | O308: 89319.01 | P308: =(O308*6.5%)/360 -> 16.127043 | Q308: =53279.58+5000000 -> 5053279.6 | R308: =(Q308*8%)/360 -> 1122.951
B309: =B308+1 -> 45778 | C309: 98062.95 | D309: =(C309*7.5%)/360 -> 20.429781 | E309: 1735884.2 | F309: =(E309*7.5%)/360 -> 361.64254 | G309: 117720.97 | H309: =(G309*4.5%)/360 -> 14.715121 | I309: 176072.51 | J309: =(I309*4.5%)/360 -> 22.009064 | K309: 74993.59 | L309: =(K309*6.5%)/360 -> 13.540509 | M309: 2677.67 | N309: =(M309*2.5%)/360 -> 0.18594931 | O309: 89319.01 | P309: =(O309*6.5%)/360 -> 16.127043 | Q309: 5053279.6 | R309: =(Q309*8%)/360 -> 1122.951
B310: =B309+1 -> 45779 | C310: 98062.95 | D310: =(C310*7.5%)/360 -> 20.429781 | E310: 1735884.2 | F310: =(E310*7.5%)/360 -> 361.64254 | G310: 117720.97 | H310: =(G310*4.5%)/360 -> 14.715121 | I310: 176072.51 | J310: =(I310*4.5%)/360 -> 22.009064 | K310: 74993.59 | L310: =(K310*6.5%)/360 -> 13.540509 | M310: 2677.67 | N310: =(M310*2.5%)/360 -> 0.18594931 | O310: 89319.01 | P310: =(O310*6.5%)/360 -> 16.127043 | Q310: 5053279.6 | R310: =(Q310*8%)/360 -> 1122.951
B311: =B310+1 -> 45780 | C311: 98062.95 | D311: =(C311*7.5%)/360 -> 20.429781 | E311: 1735884.2 | F311: =(E311*7.5%)/360 -> 361.64254 | G311: 117720.97 | H311: =(G311*4.5%)/360 -> 14.715121 | I311: 176072.51 | J311: =(I311*4.5%)/360 -> 22.009064 | K311: 74993.59 | L311: =(K311*6.5%)/360 -> 13.540509 | M311: 2677.67 | N311: =(M311*2.5%)/360 -> 0.18594931 | O311: 89319.01 | P311: =(O311*6.5%)/360 -> 16.127043 | Q311: 5053279.6 | R311: =(Q311*8%)/360 -> 1122.951
B312: =B311+1 -> 45781 | C312: 123062.95 | D312: =(C312*7.5%)/360 -> 25.638115 | E312: 7462707.2 | F312: =(E312*7.5%)/360 -> 1554.7307 | G312: 117720.97 | H312: =(G312*4.5%)/360 -> 14.715121 | I312: 290180.23 | J312: =(I312*4.5%)/360 -> 36.272529 | K312: 74993.59 | L312: =(K312*6.5%)/360 -> 13.540509 | M312: 2677.67 | N312: =(M312*2.5%)/360 -> 0.18594931 | O312: 89319.01 | P312: =(O312*6.5%)/360 -> 16.127043 | Q312: 5053279.6 | R312: =(Q312*8%)/360 -> 1122.951
B313: =B312+1 -> 45782 | C313: 123062.95 | D313: =(C313*7.5%)/360 -> 25.638115 | E313: 18454115 | F313: =(E313*7.5%)/360 -> 3844.6072 | G313: 117720.97 | H313: =(G313*4.5%)/360 -> 14.715121 | I313: 290180.23 | J313: =(I313*4.5%)/360 -> 36.272529 | K313: 74993.59 | L313: =(K313*6.5%)/360 -> 13.540509 | M313: 2677.67 | N313: =(M313*2.5%)/360 -> 0.18594931 | O313: 89319.01 | P313: =(O313*6.5%)/360 -> 16.127043 | Q313: 5053279.6 | R313: =(Q313*8%)/360 -> 1122.951
B314: =B313+1 -> 45783 | C314: 123062.95 | D314: =(C314*7.5%)/360 -> 25.638115 | E314: 20031975 | F314: =(E314*7.5%)/360 -> 4173.3281 | G314: 117720.97 | H314: =(G314*4.5%)/360 -> 14.715121 | I314: 290180.23 | J314: =(I314*4.5%)/360 -> 36.272529 | K314: 74993.59 | L314: =(K314*6.5%)/360 -> 13.540509 | M314: 2677.67 | N314: =(M314*2.5%)/360 -> 0.18594931 | O314: 89319.01 | P314: =(O314*6.5%)/360 -> 16.127043 | Q314: 5053279.6 | R314: =(Q314*8%)/360 -> 1122.951
B315: =B314+1 -> 45784 | C315: 123062.95 | D315: =(C315*7.5%)/360 -> 25.638115 | E315: 20153340 | F315: =(E315*7.5%)/360 -> 4198.6126 | G315: 117720.97 | H315: =(G315*4.5%)/360 -> 14.715121 | I315: 290180.23 | J315: =(I315*4.5%)/360 -> 36.272529 | K315: 74993.59 | L315: =(K315*6.5%)/360 -> 13.540509 | M315: 2677.67 | N315: =(M315*2.5%)/360 -> 0.18594931 | O315: 89319.01 | P315: =(O315*6.5%)/360 -> 16.127043 | Q315: 5053279.6 | R315: =(Q315*8%)/360 -> 1122.951
B316: =B315+1 -> 45785 | C316: 123062.95 | D316: =(C316*7.5%)/360 -> 25.638115 | E316: 19763924 | F316: =(E316*7.5%)/360 -> 4117.4842 | G316: 117720.97 | H316: =(G316*4.5%)/360 -> 14.715121 | I316: 290180.23 | J316: =(I316*4.5%)/360 -> 36.272529 | K316: 74993.59 | L316: =(K316*6.5%)/360 -> 13.540509 | M316: 2677.67 | N316: =(M316*2.5%)/360 -> 0.18594931 | O316: 89319.01 | P316: =(O316*6.5%)/360 -> 16.127043 | Q316: 5053279.6 | R316: =(Q316*8%)/360 -> 1122.951
B317: =B316+1 -> 45786 | C317: 123062.95 | D317: =(C317*7.5%)/360 -> 25.638115 | E317: 19763924 | F317: =(E317*7.5%)/360 -> 4117.4842 | G317: 117720.97 | H317: =(G317*4.5%)/360 -> 14.715121 | I317: 290180.23 | J317: =(I317*4.5%)/360 -> 36.272529 | K317: 74993.59 | L317: =(K317*6.5%)/360 -> 13.540509 | M317: 2677.67 | N317: =(M317*2.5%)/360 -> 0.18594931 | O317: 89319.01 | P317: =(O317*6.5%)/360 -> 16.127043 | Q317: 5053279.6 | R317: =(Q317*8%)/360 -> 1122.951
B318: =B317+1 -> 45787 | C318: 123062.95 | D318: =(C318*7.5%)/360 -> 25.638115 | E318: 19763924 | F318: =(E318*7.5%)/360 -> 4117.4842 | G318: 117720.97 | H318: =(G318*4.5%)/360 -> 14.715121 | I318: 290180.23 | J318: =(I318*4.5%)/360 -> 36.272529 | K318: 74993.59 | L318: =(K318*6.5%)/360 -> 13.540509 | M318: 2677.67 | N318: =(M318*2.5%)/360 -> 0.18594931 | O318: 89319.01 | P318: =(O318*6.5%)/360 -> 16.127043 | Q318: 5053279.6 | R318: =(Q318*8%)/360 -> 1122.951
B319: =B318+1 -> 45788 | C319: 123062.95 | D319: =(C319*7.5%)/360 -> 25.638115 | E319: 22923083 | F319: =(E319*7.5%)/360 -> 4775.6424 | G319: 117720.97 | H319: =(G319*4.5%)/360 -> 14.715121 | I319: 290180.23 | J319: =(I319*4.5%)/360 -> 36.272529 | K319: 74993.59 | L319: =(K319*6.5%)/360 -> 13.540509 | M319: 2677.67 | N319: =(M319*2.5%)/360 -> 0.18594931 | O319: 89319.01 | P319: =(O319*6.5%)/360 -> 16.127043 | Q319: 5053279.6 | R319: =(Q319*8%)/360 -> 1122.951
B320: =B319+1 -> 45789 | C320: 123062.95 | D320: =(C320*7.5%)/360 -> 25.638115 | E320: 18062067 | F320: =(E320*7.5%)/360 -> 3762.9306 | G320: 117720.97 | H320: =(G320*4.5%)/360 -> 14.715121 | I320: 290180.23 | J320: =(I320*4.5%)/360 -> 36.272529 | K320: 74993.59 | L320: =(K320*6.5%)/360 -> 13.540509 | M320: 2677.67 | N320: =(M320*2.5%)/360 -> 0.18594931 | O320: 89319.01 | P320: =(O320*6.5%)/360 -> 16.127043 | Q320: 5053279.6 | R320: =(Q320*8%)/360 -> 1122.951
... B369: =B368+1 -> 45838 | C369: 76660.24 | D369: =(C369*7.5%)/360 -> 15.970883 | E369: 5667503.2 | F369: =(E369*7.5%)/360 -> 1180.7298 | G369: 709729.97 | H369: =(G369*4.5%)/360 -> 88.716246 | I369: 285264.34 | J369: =(I369*4.5%)/360 -> 35.658043 | K369: 75002.59 | L369: =(K369*6.5%)/360 -> 13.542134 | M369: 2686.67 | N369: =(M369*2.5%)/360 -> 0.18657431 | O369: 89328.01 | P369: =(O369*6.5%)/360 -> 16.128668 | Q369: 53288.58 | R369: =(Q369*8%)/360 -> 11.841907
B370: Total | D370: =SUM(D189:D369) -> 44332.397 | F370: =SUM(F189:F369) -> 388283.61 | H370: =SUM(H189:H369) -> 4325.6926 | J370: =SUM(J189:J369) -> 5106.4691 | L370: =SUM(L189:L369) -> 2450.8403 | N370: =SUM(N189:N369) -> 33.659949 | P370: =SUM(P189:P369) -> 2919.003 | R370: =SUM(R189:R369) -> 250874.3
B372: 45839 | C372: 490106.24 | D372: =(C372*7.5%)/360 -> 102.10547 | E372: 4179493.1 | F372: =(E372*7.5%)/360 -> 870.72773 | G372: 25184.16 | H372: =(G372*4.5%)/360 -> 3.14802 | I372: 84113.66 | J372: =(I372*4.5%)/360 -> 10.514207 | K372: 75002.59 | L372: =(K372*6.5%)/360 -> 13.542134 | M372: 2686.67 | N372: =(M372*2.5%)/360 -> 0.18657431 | O372: 89328.01 | P372: =(O372*6.5%)/360 -> 16.128668 | Q372: 3053279.6 | R372: =(Q372*8%)/360 -> 678.50657
B373: =B372+1 -> 45840 | C373: 376103.93 | D373: =(C373*7.5%)/360 -> 78.354985 | E373: 4687861.7 | F373: =(E373*7.5%)/360 -> 976.63786 | G373: 25184.16 | H373: =(G373*4.5%)/360 -> 3.14802 | I373: 84113.66 | J373: =(I373*4.5%)/360 -> 10.514207 | K373: 75002.59 | L373: =(K373*6.5%)/360 -> 13.542134 | M373: 2686.67 | N373: =(M373*2.5%)/360 -> 0.18657431 | O373: 89328.01 | P373: =(O373*6.5%)/360 -> 16.128668 | Q373: 3053279.6 | R373: =(Q373*8%)/360 -> 678.50657
B374: =B373+1 -> 45841 | C374: 376045.93 | D374: =(C374*7.5%)/360 -> 78.342902 | E374: 13195791 | F374: =(E374*7.5%)/360 -> 2749.1232 | G374: 25184.16 | H374: =(G374*4.5%)/360 -> 3.14802 | I374: 199103.66 | J374: =(I374*4.5%)/360 -> 24.887957 | K374: 75002.59 | L374: =(K374*6.5%)/360 -> 13.542134 | M374: 2686.67 | N374: =(M374*2.5%)/360 -> 0.18657431 | O374: 89328.01 | P374: =(O374*6.5%)/360 -> 16.128668 | Q374: 3053279.6 | R374: =(Q374*8%)/360 -> 678.50657
B375: =B374+1 -> 45842 | C375: 376045.93 | D375: =(C375*7.5%)/360 -> 78.342902 | E375: 13195791 | F375: =(E375*7.5%)/360 -> 2749.1232 | G375: 25184.16 | H375: =(G375*4.5%)/360 -> 3.14802 | I375: 199103.66 | J375: =(I375*4.5%)/360 -> 24.887957 | K375: 75002.59 | L375: =(K375*6.5%)/360 -> 13.542134 | M375: 2686.67 | N375: =(M375*2.5%)/360 -> 0.18657431 | O375: 89328.01 | P375: =(O375*6.5%)/360 -> 16.128668 | Q375: 3053279.6 | R375: =(Q375*8%)/360 -> 678.50657
B376: =B375+1 -> 45843 | C376: 376045.93 | D376: =(C376*7.5%)/360 -> 78.342902 | E376: 13195791 | F376: =(E376*7.5%)/360 -> 2749.1232 | G376: 25184.16 | H376: =(G376*4.5%)/360 -> 3.14802 | I376: 199103.66 | J376: =(I376*4.5%)/360 -> 24.887957 | K376: 75002.59 | L376: =(K376*6.5%)/360 -> 13.542134 | M376: 2686.67 | N376: =(M376*2.5%)/360 -> 0.18657431 | O376: 89328.01 | P376: =(O376*6.5%)/360 -> 16.128668 | Q376: 3053279.6 | R376: =(Q376*8%)/360 -> 678.50657
B377: =B376+1 -> 45844 | C377: 376045.93 | D377: =(C377*7.5%)/360 -> 78.342902 | E377: 13195791 | F377: =(E377*7.5%)/360 -> 2749.1232 | G377: 25184.16 | H377: =(G377*4.5%)/360 -> 3.14802 | I377: 199103.66 | J377: =(I377*4.5%)/360 -> 24.887957 | K377: 75002.59 | L377: =(K377*6.5%)/360 -> 13.542134 | M377: 2686.67 | N377: =(M377*2.5%)/360 -> 0.18657431 | O377: 89328.01 | P377: =(O377*6.5%)/360 -> 16.128668 | Q377: 3053279.6 | R377: =(Q377*8%)/360 -> 678.50657
B378: =B377+1 -> 45845 | C378: 376045.93 | D378: =(C378*7.5%)/360 -> 78.342902 | E378: 16143125 | F378: =(E378*7.5%)/360 -> 3363.1511 | G378: 25184.16 | H378: =(G378*4.5%)/360 -> 3.14802 | I378: 199103.66 | J378: =(I378*4.5%)/360 -> 24.887957 | K378: 75002.59 | L378: =(K378*6.5%)/360 -> 13.542134 | M378: 2686.67 | N378: =(M378*2.5%)/360 -> 0.18657431 | O378: 89328.01 | P378: =(O378*6.5%)/360 -> 16.128668 | Q378: 106400.92 | R378: =(Q378*8%)/360 -> 23.644649
B379: =B378+1 -> 45846 | C379: 376045.93 | D379: =(C379*7.5%)/360 -> 78.342902 | E379: 24479181 | F379: =(E379*7.5%)/360 -> 5099.8294 | G379: 25184.16 | H379: =(G379*4.5%)/360 -> 3.14802 | I379: 199103.66 | J379: =(I379*4.5%)/360 -> 24.887957 | K379: 75002.59 | L379: =(K379*6.5%)/360 -> 13.542134 | M379: 2686.67 | N379: =(M379*2.5%)/360 -> 0.18657431 | O379: 89328.01 | P379: =(O379*6.5%)/360 -> 16.128668 | Q379: 106400.92 | R379: =(Q379*8%)/360 -> 23.644649
B380: =B379+1 -> 45847 | C380: 376045.93 | D380: =(C380*7.5%)/360 -> 78.342902 | E380: 21994317 | F380: =(E380*7.5%)/360 -> 4582.1494 | G380: 25184.16 | H380: =(G380*4.5%)/360 -> 3.14802 | I380: 199103.66 | J380: =(I380*4.5%)/360 -> 24.887957 | K380: 75002.59 | L380: =(K380*6.5%)/360 -> 13.542134 | M380: 2686.67 | N380: =(M380*2.5%)/360 -> 0.18657431 | O380: 89328.01 | P380: =(O380*6.5%)/360 -> 16.128668 | Q380: 106400.92 | R380: =(Q380*8%)/360 -> 23.644649
B381: =B380+1 -> 45848 | C381: 876045.93 | D381: =(C381*7.5%)/360 -> 182.50957 | E381: 21994317 | F381: =(E381*7.5%)/360 -> 4582.1494 | G381: 25184.16 | H381: =(G381*4.5%)/360 -> 3.14802 | I381: 199103.66 | J381: =(I381*4.5%)/360 -> 24.887957 | K381: 75002.59 | L381: =(K381*6.5%)/360 -> 13.542134 | M381: 2686.67 | N381: =(M381*2.5%)/360 -> 0.18657431 | O381: 89328.01 | P381: =(O381*6.5%)/360 -> 16.128668 | Q381: 106400.92 | R381: =(Q381*8%)/360 -> 23.644649
B382: =B381+1 -> 45849 | C382: 876045.93 | D382: =(C382*7.5%)/360 -> 182.50957 | E382: 21994317 | F382: =(E382*7.5%)/360 -> 4582.1494 | G382: 25184.16 | H382: =(G382*4.5%)/360 -> 3.14802 | I382: 199103.66 | J382: =(I382*4.5%)/360 -> 24.887957 | K382: 75002.59 | L382: =(K382*6.5%)/360 -> 13.542134 | M382: 2686.67 | N382: =(M382*2.5%)/360 -> 0.18657431 | O382: 89328.01 | P382: =(O382*6.5%)/360 -> 16.128668 | Q382: 106400.92 | R382: =(Q382*8%)/360 -> 23.644649
B383: =B382+1 -> 45850 | C383: 876045.93 | D383: =(C383*7.5%)/360 -> 182.50957 | E383: 21994317 | F383: =(E383*7.5%)/360 -> 4582.1494 | G383: 25184.16 | H383: =(G383*4.5%)/360 -> 3.14802 | I383: 199103.66 | J383: =(I383*4.5%)/360 -> 24.887957 | K383: 75002.59 | L383: =(K383*6.5%)/360 -> 13.542134 | M383: 2686.67 | N383: =(M383*2.5%)/360 -> 0.18657431 | O383: 89328.01 | P383: =(O383*6.5%)/360 -> 16.128668 | Q383: 106400.92 | R383: =(Q383*8%)/360 -> 23.644649
B384: =B383+1 -> 45851 | C384: 875985.93 | D384: =(C384*7.5%)/360 -> 182.49707 | E384: 18095365 | F384: =(E384*7.5%)/360 -> 3769.8677 | G384: 25184.16 | H384: =(G384*4.5%)/360 -> 3.14802 | I384: 199103.66 | J384: =(I384*4.5%)/360 -> 24.887957 | K384: 75002.59 | L384: =(K384*6.5%)/360 -> 13.542134 | M384: 2686.67 | N384: =(M384*2.5%)/360 -> 0.18657431 | O384: 89328.01 | P384: =(O384*6.5%)/360 -> 16.128668 | Q384: 106400.92 | R384: =(Q384*8%)/360 -> 23.644649
... B525: =B524+1 -> 45992 | C525: 28912.48 | D525: =(C525*7.5%)/360 -> 6.0234333 | E525: 1635742 | F525: =(E525*7.5%)/360 -> 340.77958 | G525: 161226.91 | H525: =(G525*4.5%)/360 -> 20.153364 | I525: 86445.86 | J525: =(I525*4.5%)/360 -> 10.805732 | K525: 74648.59 | L525: =(K525*6.5%)/360 -> 13.478218 | M525: 2696.67 | N525: =(M525*2.5%)/360 -> 0.18726875 | O525: 88905.23 | P525: =(O525*6.5%)/360 -> 16.052333 | Q525: 296575.92 | R525: =(Q525*8%)/360 -> 65.90576
A526: =D526+F526+H526+J526+L526+N526+P526+R526 -> 815.10912 | B526: =B525+1 -> 45993 | C526: 28912.48 | D526: =(C526*7.5%)/360 -> 6.0234333 | E526: 3276014.4 | F526: =(E526*7.5%)/360 -> 682.50301 | G526: 161226.91 | H526: =(G526*4.5%)/360 -> 20.153364 | I526: 86445.86 | J526: =(I526*4.5%)/360 -> 10.805732 | K526: 74648.59 | L526: =(K526*6.5%)/360 -> 13.478218 | M526: 2696.67 | N526: =(M526*2.5%)/360 -> 0.18726875 | O526: 88905.23 | P526: =(O526*6.5%)/360 -> 16.052333 | Q526: 296575.92 | R526: =(Q526*8%)/360 -> 65.90576
A527: =D527+F527+H527+J527+L527+N527+P527+R527 -> 1483.8591 | B527: =B526+1 -> 45994 | C527: 28912.48 | D527: =(C527*7.5%)/360 -> 6.0234333 | E527: 6486014.4 | F527: =(E527*7.5%)/360 -> 1351.253 | G527: 161226.91 | H527: =(G527*4.5%)/360 -> 20.153364 | I527: 86445.86 | J527: =(I527*4.5%)/360 -> 10.805732 | K527: 74648.59 | L527: =(K527*6.5%)/360 -> 13.478218 | M527: 2696.67 | N527: =(M527*2.5%)/360 -> 0.18726875 | O527: 88905.23 | P527: =(O527*6.5%)/360 -> 16.052333 | Q527: 296575.92 | R527: =(Q527*8%)/360 -> 65.90576
A528: =D528+F528+H528+J528+L528+N528+P528+R528 -> 1823.6939 | B528: =B527+1 -> 45995 | C528: 28912.48 | D528: =(C528*7.5%)/360 -> 6.0234333 | E528: 8117221.3 | F528: =(E528*7.5%)/360 -> 1691.0878 | G528: 161226.91 | H528: =(G528*4.5%)/360 -> 20.153364 | I528: 86445.86 | J528: =(I528*4.5%)/360 -> 10.805732 | K528: 74648.59 | L528: =(K528*6.5%)/360 -> 13.478218 | M528: 2696.67 | N528: =(M528*2.5%)/360 -> 0.18726875 | O528: 88905.23 | P528: =(O528*6.5%)/360 -> 16.052333 | Q528: 296575.92 | R528: =(Q528*8%)/360 -> 65.90576
A529: =D529+F529+H529+J529+L529+N529+P529+R529 -> 1899.5456 | B529: =B528+1 -> 45996 | C529: 28912.48 | D529: =(C529*7.5%)/360 -> 6.0234333 | E529: 8481309.5 | F529: =(E529*7.5%)/360 -> 1766.9395 | G529: 161226.91 | H529: =(G529*4.5%)/360 -> 20.153364 | I529: 86445.86 | J529: =(I529*4.5%)/360 -> 10.805732 | K529: 74648.59 | L529: =(K529*6.5%)/360 -> 13.478218 | M529: 2696.67 | N529: =(M529*2.5%)/360 -> 0.18726875 | O529: 88905.23 | P529: =(O529*6.5%)/360 -> 16.052333 | Q529: 296575.92 | R529: =(Q529*8%)/360 -> 65.90576
A530: =D530+F530+H530+J530+L530+N530+P530+R530 -> 1899.5456 | B530: =B529+1 -> 45997 | C530: 28912.48 | D530: =(C530*7.5%)/360 -> 6.0234333 | E530: 8481309.5 | F530: =(E530*7.5%)/360 -> 1766.9395 | G530: 161226.91 | H530: =(G530*4.5%)/360 -> 20.153364 | I530: 86445.86 | J530: =(I530*4.5%)/360 -> 10.805732 | K530: 74648.59 | L530: =(K530*6.5%)/360 -> 13.478218 | M530: 2696.67 | N530: =(M530*2.5%)/360 -> 0.18726875 | O530: 88905.23 | P530: =(O530*6.5%)/360 -> 16.052333 | Q530: 296575.92 | R530: =(Q530*8%)/360 -> 65.90576
A531: =D531+F531+H531+J531+L531+N531+P531+R531 -> 1760.2717 | B531: =B530+1 -> 45998 | C531: 28912.48 | D531: =(C531*7.5%)/360 -> 6.0234333 | E531: 7812794.7 | F531: =(E531*7.5%)/360 -> 1627.6656 | G531: 161226.91 | H531: =(G531*4.5%)/360 -> 20.153364 | I531: 86445.86 | J531: =(I531*4.5%)/360 -> 10.805732 | K531: 74648.59 | L531: =(K531*6.5%)/360 -> 13.478218 | M531: 2696.67 | N531: =(M531*2.5%)/360 -> 0.18726875 | O531: 88905.23 | P531: =(O531*6.5%)/360 -> 16.052333 | Q531: 296575.92 | R531: =(Q531*8%)/360 -> 65.90576
A532: =D532+F532+H532+J532+L532+N532+P532+R532 -> 1567.2914 | B532: =B531+1 -> 45999 | C532: 28912.48 | D532: =(C532*7.5%)/360 -> 6.0234333 | E532: 6863689.2 | F532: =(E532*7.5%)/360 -> 1429.9353 | G532: 199226.91 | H532: =(G532*4.5%)/360 -> 24.903364 | I532: 86445.86 | J532: =(I532*4.5%)/360 -> 10.805732 | K532: 74648.59 | L532: =(K532*6.5%)/360 -> 13.478218 | M532: 2696.67 | N532: =(M532*2.5%)/360 -> 0.18726875 | O532: 88905.23 | P532: =(O532*6.5%)/360 -> 16.052333 | Q532: 296575.92 | R532: =(Q532*8%)/360 -> 65.90576
A533: =D533+F533+H533+J533+L533+N533+P533+R533 -> 1567.2914 | B533: =B532+1 -> 46000 | C533: 28912.48 | D533: =(C533*7.5%)/360 -> 6.0234333 | E533: 6863689.2 | F533: =(E533*7.5%)/360 -> 1429.9353 | G533: 199226.91 | H533: =(G533*4.5%)/360 -> 24.903364 | I533: 86445.86 | J533: =(I533*4.5%)/360 -> 10.805732 | K533: 74648.59 | L533: =(K533*6.5%)/360 -> 13.478218 | M533: 2696.67 | N533: =(M533*2.5%)/360 -> 0.18726875 | O533: 88905.23 | P533: =(O533*6.5%)/360 -> 16.052333 | Q533: 296575.92 | R533: =(Q533*8%)/360 -> 65.90576
A534: =D534+F534+H534+J534+L534+N534+P534+R534 -> 1076.4372 | B534: =B533+1 -> 46001 | C534: 72812.48 | D534: =(C534*7.5%)/360 -> 15.169267 | E534: 4463689.2 | F534: =(E534*7.5%)/360 -> 929.93526 | G534: 199226.91 | H534: =(G534*4.5%)/360 -> 24.903364 | I534: 86445.86 | J534: =(I534*4.5%)/360 -> 10.805732 | K534: 74648.59 | L534: =(K534*6.5%)/360 -> 13.478218 | M534: 2696.67 | N534: =(M534*2.5%)/360 -> 0.18726875 | O534: 88905.23 | P534: =(O534*6.5%)/360 -> 16.052333 | Q534: 296575.92 | R534: =(Q534*8%)/360 -> 65.90576
A535: =D535+F535+H535+J535+L535+N535+P535+R535 -> 1014.9506 | B535: =B534+1 -> 46002 | C535: 72812.48 | D535: =(C535*7.5%)/360 -> 15.169267 | E535: 4165553.6 | F535: =(E535*7.5%)/360 -> 867.82367 | G535: 204226.91 | H535: =(G535*4.5%)/360 -> 25.528364 | I535: 86445.86 | J535: =(I535*4.5%)/360 -> 10.805732 | K535: 74648.59 | L535: =(K535*6.5%)/360 -> 13.478218 | M535: 2696.67 | N535: =(M535*2.5%)/360 -> 0.18726875 | O535: 88905.23 | P535: =(O535*6.5%)/360 -> 16.052333 | Q535: 296575.92 | R535: =(Q535*8%)/360 -> 65.90576
A536: =D536+F536+H536+J536+L536+N536+P536+R536 -> 1014.9506 | B536: =B535+1 -> 46003 | C536: 72812.48 | D536: =(C536*7.5%)/360 -> 15.169267 | E536: 4165553.6 | F536: =(E536*7.5%)/360 -> 867.82367 | G536: 204226.91 | H536: =(G536*4.5%)/360 -> 25.528364 | I536: 86445.86 | J536: =(I536*4.5%)/360 -> 10.805732 | K536: 74648.59 | L536: =(K536*6.5%)/360 -> 13.478218 | M536: 2696.67 | N536: =(M536*2.5%)/360 -> 0.18726875 | O536: 88905.23 | P536: =(O536*6.5%)/360 -> 16.052333 | Q536: 296575.92 | R536: =(Q536*8%)/360 -> 65.90576
A537: =D537+F537+H537+J537+L537+N537+P537+R537 -> 1014.9506 | B537: =B536+1 -> 46004 | C537: 72812.48 | D537: =(C537*7.5%)/360 -> 15.169267 | E537: 4165553.6 | F537: =(E537*7.5%)/360 -> 867.82367 | G537: 204226.91 | H537: =(G537*4.5%)/360 -> 25.528364 | I537: 86445.86 | J537: =(I537*4.5%)/360 -> 10.805732 | K537: 74648.59 | L537: =(K537*6.5%)/360 -> 13.478218 | M537: 2696.67 | N537: =(M537*2.5%)/360 -> 0.18726875 | O537: 88905.23 | P537: =(O537*6.5%)/360 -> 16.052333 | Q537: 296575.92 | R537: =(Q537*8%)/360 -> 65.90576
... A554: =D554+F554+H554+J554+L554+N554+P554+R554 -> 108.70597 | B554: =B553+1 -> 46021 | C554: 1681.56 | D554: =(C554*7.5%)/360 -> 0.350325 | E554: 1280.25 | F554: =(E554*7.5%)/360 -> 0.26671875 | G554: 13276.91 | H554: =(G554*4.5%)/360 -> 1.6596138 | I554: 86445.86 | J554: =(I554*4.5%)/360 -> 10.805732 | K554: 74648.59 | L554: =(K554*6.5%)/360 -> 13.478218 | M554: 2696.67 | N554: =(M554*2.5%)/360 -> 0.18726875 | O554: 88905.23 | P554: =(O554*6.5%)/360 -> 16.052333 | Q554: 296575.92 | R554: =(Q554*8%)/360 -> 65.90576
B555: Total | D555: =SUM(D372:D554) -> 22919.88 | F555: =SUM(F372:F554) -> 157636.86 | H555: =SUM(H372:H554) -> 2338.0593 | J555: =SUM(J372:J554) -> 1834.1927 | L555: =SUM(L372:L554) -> 2471.755 | N555: =SUM(N372:N554) -> 34.213237 | P555: =SUM(P372:P554) -> 2943.8365 | R555: =SUM(R372:R554) -> 11524.515
A557: =D557+F557+H557+J557+L557+N557+P557+R557 -> 188.62645 | B557: 46023 | C557: 13528.56 | D557: =(C557*7.5%)/360 -> 2.81845 | E557: 358769.41 | F557: =(E557*7.5%)/360 -> 74.743627 | G557: 195620.42 | H557: =(G557*2.5%)/360 -> 13.584751 | I557: 86445.86 | J557: =(I557*2.5%)/360 -> 6.0031847 | K557: 74648.59 | L557: =(K557*4.5%)/360 -> 9.3310737 | M557: 2696.67 | N557: =(M557*2.5%)/360 -> 0.18726875 | O557: 88905.23 | P557: =(O557*6.5%)/360 -> 16.052333 | Q557: 296575.92 | R557: =(Q557*8%)/360 -> 65.90576
A558: =D558+F558+H558+J558+L558+N558+P558+R558 -> 188.62645 | B558: =B557+1 -> 46024 | C558: 13528.56 | D558: =(C558*7.5%)/360 -> 2.81845 | E558: 358769.41 | F558: =(E558*7.5%)/360 -> 74.743627 | G558: 86445.86 | H558: =(G558*2.5%)/360 -> 6.0031847 | I558: 195620.42 | J558: =(I558*2.5%)/360 -> 13.584751 | K558: 74648.59 | L558: =(K558*4.5%)/360 -> 9.3310737 | M558: 2696.67 | N558: =(M558*2.5%)/360 -> 0.18726875 | O558: 88905.23 | P558: =(O558*6.5%)/360 -> 16.052333 | Q558: 296575.92 | R558: =(Q558*8%)/360 -> 65.90576
A559: =D559+F559+H559+J559+L559+N559+P559+R559 -> 188.62645 | B559: =B558+1 -> 46025 | C559: 13528.56 | D559: =(C559*7.5%)/360 -> 2.81845 | E559: 358769.41 | F559: =(E559*7.5%)/360 -> 74.743627 | G559: 86445.86 | H559: =(G559*2.5%)/360 -> 6.0031847 | I559: 195620.42 | J559: =(I559*2.5%)/360 -> 13.584751 | K559: 74648.59 | L559: =(K559*4.5%)/360 -> 9.3310737 | M559: 2696.67 | N559: =(M559*2.5%)/360 -> 0.18726875 | O559: 88905.23 | P559: =(O559*6.5%)/360 -> 16.052333 | Q559: 296575.92 | R559: =(Q559*8%)/360 -> 65.90576
A560: =D560+F560+H560+J560+L560+N560+P560+R560 -> 288.3632 | B560: =B559+1 -> 46026 | C560: 13528.56 | D560: =(C560*7.5%)/360 -> 2.81845 | E560: 837505.83 | F560: =(E560*7.5%)/360 -> 174.48038 | G560: 86445.86 | H560: =(G560*2.5%)/360 -> 6.0031847 | I560: 195620.42 | J560: =(I560*2.5%)/360 -> 13.584751 | K560: 74648.59 | L560: =(K560*4.5%)/360 -> 9.3310737 | M560: 2696.67 | N560: =(M560*2.5%)/360 -> 0.18726875 | O560: 88905.23 | P560: =(O560*6.5%)/360 -> 16.052333 | Q560: 296575.92 | R560: =(Q560*8%)/360 -> 65.90576
