Workbook
Name NAV_MKT: [1]LS!$T$1
Name NAV_MKT: [2]LS!$T$1
Name NAV_MKT: LS!$T$1
Name NEW_TCV: [3]Portfolio!$F$38
Name NEW_TMV: [3]Portfolio!$H$38
Name TCV_STOCKS: #REF!
Name TCV_STOCKS: #REF!
Name TCV_STOCKS: #REF!
Name TMV_STOCKS: #REF!
Name TMV_STOCKS: #REF!
Name TMV_STOCKS: #REF!

Sheet DASHBOARD
A1: =LS!Q1+SIP!P1 -> 208573040 | C1: =LS!R1+SIP!Q1 -> 7244346.2
A4: 208565050 | B4: =A1-A4 -> 7990
A5: 7242336.2 | B5: =C1-A5 -> 2010

Sheet INVESTORS
A1: INVESTOR NAME | B1: INVESTOR CODE | C1: TITLE | D1: TYPE OF INVESTOR | E1: LS_TOTAL UNITS BUY | F1: LS_TOTAL UNITS SOLD | G1: LS_TOTAL CURRENT UNITS | H1: LS_TOTAL COST VALUE | I1: LS_TOTAL COST OF UNITS SOLD | J1: LS_TOTAL COST VALUE OF CURRENT UNITS | K1: LS_TOTAL REALIZED GAIN | L1: SIP_TOTAL UNITS BUY | M1: SIP_TOTAL UNITS SOLD | N1: SIP_TOTAL CURRENT UNITS | O1: SIP_TOTAL COST VALUE | P1: SIP_TOTAL COST OF UNITS SOLD | Q1: SIP_TOTAL COST VALUE OF CURRENT UNITS | R1: SIP_TOTAL REALIZED GAIN | S1: TOTAL UNITS BUY | T1: TOTAL UNITS SOLD | U1: BO OPENING BALANCE | V1: LS- BO UNITS SELL | W1: LS- BO UNITS REPURCHASE | X1: SIP- BO UNITS SELL | Y1: SIP- BO UNITS REPURCHASE | Z1: BO UNITS HOLD | AA1: TOTAL CURRENT UNITS | AB1: Column1 | AC1: BO | AD1: TOTAL COST VALUE OF CURRENT INVESTMENT | AE1: LS_WEIGHT | AF1: SIP_WEIGHT | AG1: LS_AVERAGE COST | AH1: SIP_AVERAGE COST | AI1: AVERAGE COST | AJ1: NAV | AK1: TOTAL MARKET VALUE | AL1: LS_TOTAL MARKET VALUE | AM1: SIP_TOTAL MARKET VALUE | AN1: TOTAL SELLABLE UNITS | AO1: MARKET VALUE OF SELLABLE UNITS | AP1: TOTAL REALIZED GAIN | AQ1: TOTAL UNREALIZED GAIN | AR1: TOTAL TAXES | AS1: TOTAL GROSS DIVIDEND | AT1: % of Unit Holding
A2: HARI PADA SAHA | B2: A00002 | C2: Dear Mr. | D2: Individual | E2: =SUMIFS(LS[Unit],LS[Investor ID],INVESTORS_LIST[[#This Row],[INVESTOR CODE]],LS[B/S],"B") -> 74187 | F2: =-SUMIFS(LS[Unit],LS[Investor ID],INVESTORS_LIST[[#This Row],[INVESTOR CODE]],LS[B/S],"S") -> 1 | G2: =IF(INVESTORS_LIST[[#This Row],[LS_TOTAL UNITS BUY]]=0,0,INVESTORS_LIST[[#This Row],[LS_TOTAL UNITS BUY]]-INVESTORS_LIST[[#This Row],[LS_TOTAL UNITS SOLD]]) -> 74186 | H2: =IF(INVESTORS_LIST[[#This Row],[LS_TOTAL UNITS BUY]]=0,0,SUMIFS(LS[Amount],LS[Investor ID],INVESTORS_LIST[[#This Row],[INVESTOR CODE]],LS[B/S],"B")) -> 753785.59 | I2: =IF(INVESTORS_LIST[[#This Row],[LS_TOTAL UNITS SOLD]]=0,0,SUMIFS(LS[Cost of Units Sold],LS[Investor ID],INVESTORS_LIST[[#This Row],[INVESTOR CODE]],LS[B/S],"S")) -> 10.061726 | J2: =IF(INVESTORS_LIST[[#This Row],[LS_TOTAL CURRENT UNITS]]=0,0,INVESTORS_LIST[[#This Row],[LS_TOTAL CURRENT UNITS]]*INVESTORS_LIST[[#This Row],[LS_AVERAGE COST]]) -> 753775.53 | K2: =IF(INVESTORS_LIST[[#This Row],[LS_TOTAL UNITS SOLD]]=0,0,SUMIFS(LS[Realized Gain],LS[Investor ID],INVESTORS_LIST[[#This Row],[INVESTOR CODE]],LS[B/S],"S")) -> -6.7117258 | L2: =SUMIFS(SIP[Unit],SIP[Investor ID],INVESTORS_LIST[[#This Row],[INVESTOR CODE]],SIP[B/S],"B") -> 0 | M2: =-SUMIFS(SIP[Unit],SIP[Investor ID],INVESTORS_LIST[[#This Row],[INVESTOR CODE]],SIP[B/S],"S") -> 0 | N2: =IF(INVESTORS_LIST[[#This Row],[SIP_TOTAL UNITS BUY]]=0,0,INVESTORS_LIST[[#This Row],[SIP_TOTAL UNITS BUY]]-INVESTORS_LIST[[#This Row],[SIP_TOTAL UNITS SOLD]]) -> 0 | O2: =IF(INVESTORS_LIST[[#This Row],[SIP_TOTAL UNITS BUY]]=0,0,SUMIFS(SIP[Amount],SIP[Investor ID],INVESTORS_LIST[[#This Row],[INVESTOR CODE]],SIP[B/S],"B")) -> 0 | P2: =IF(INVESTORS_LIST[[#This Row],[SIP_TOTAL UNITS SOLD]]=0,0,SUMIFS(SIP[Cost of Units Sold],SIP[Investor ID],INVESTORS_LIST[[#This Row],[INVESTOR CODE]],SIP[B/S],"S")) -> 0 | Q2: =IF(INVESTORS_LIST[[#This Row],[SIP_TOTAL CURRENT UNITS]]=0,0,INVESTORS_LIST[[#This Row],[SIP_TOTAL CURRENT UNITS]]*INVESTORS_LIST[[#This Row],[SIP_AVERAGE COST]]) -> 0 | R2: =IF(INVESTORS_LIST[[#This Row],[SIP_TOTAL UNITS SOLD]]=0,0,SUMIFS(SIP[Realized Gain],SIP[Investor ID],INVESTORS_LIST[[#This Row],[INVESTOR CODE]],SIP[B/S],"S")) -> 0 | S2: =INVESTORS_LIST[[#This Row],[LS_TOTAL UNITS BUY]]+INVESTORS_LIST[[#This Row],[SIP_TOTAL UNITS BUY]] -> 74187 | T2: =INVESTORS_LIST[[#This Row],[LS_TOTAL UNITS SOLD]]+INVESTORS_LIST[[#This Row],[SIP_TOTAL UNITS SOLD]] -> 1 | U2: 0 | V2: =SUMIFS(LS[BO UNIT TRANSFER],LS[Investor ID],INVESTORS_LIST[[#This Row],[INVESTOR CODE]],LS[B/S],"B") -> 0 | W2: =SUMIFS(LS[BO UNIT TRANSFER],LS[Investor ID],INVESTORS_LIST[[#This Row],[INVESTOR CODE]],LS[B/S],"S") -> 0 | X2: =SUMIFS(SIP[BO UNIT TRANSFER],SIP[Investor ID],INVESTORS_LIST[[#This Row],[INVESTOR CODE]],SIP[B/S],"S") -> 0 | Y2: =SUMIFS(SIP[BO UNIT TRANSFER],SIP[Investor ID],INVESTORS_LIST[[#This Row],[INVESTOR CODE]],SIP[B/S],"B") -> 0 | Z2: =INVESTORS_LIST[[#This Row],[BO OPENING BALANCE]]+INVESTORS_LIST[[#This Row],[LS- BO UNITS SELL]]+INVESTORS_LIST[[#This Row],[LS- BO UNITS REPURCHASE]]+INVESTORS_LIST[[#This Row],[SIP- BO UNITS REPURCHASE]]-INVESTORS_LIST[[#This Row],[SIP- BO UNITS SELL]] -> 0 | AA2: =INVESTORS_LIST[[#This Row],[TOTAL UNITS BUY]]-INVESTORS_LIST[[#This Row],[TOTAL UNITS SOLD]] -> 74186 | AB2: =INVESTORS_LIST[[#This Row],[TOTAL CURRENT UNITS]]-INVESTORS_LIST[[#This Row],[BO UNITS HOLD]] -> 74186 | AC2: =INDEX([4]!Table_1[BO ID],MATCH(INVESTORS_LIST[[#This Row],[INVESTOR CODE]],[4]!Table_1[INVESTOR CODE],0)) -> #REF! | AD2: =INVESTORS_LIST[[#This Row],[LS_TOTAL COST VALUE OF CURRENT UNITS]]+INVESTORS_LIST[[#This Row],[SIP_TOTAL COST VALUE OF CURRENT UNITS]] -> 753775.53 | AE2: =IF(INVESTORS_LIST[[#This Row],[TOTAL CURRENT UNITS]]=0,0,INVESTORS_LIST[[#This Row],[LS_TOTAL CURRENT UNITS]]/INVESTORS_LIST[[#This Row],[TOTAL CURRENT UNITS]]) -> 1 | AF2: =IF(INVESTORS_LIST[[#This Row],[TOTAL CURRENT UNITS]]=0,0,INVESTORS_LIST[[#This Row],[SIP_TOTAL CURRENT UNITS]]/INVESTORS_LIST[[#This Row],[TOTAL CURRENT UNITS]]) -> 0 | AG2: {=IF(INVESTORS_LIST[[#This Row],[LS_TOTAL UNITS BUY]]>0,INDEX(LS[NAV at Cost (Average)],MATCH(CONCATENATE(COUNTIFS(LS[Investor ID],INVESTORS_LIST[[#This Row],[INVESTOR CODE]]),INVESTORS_LIST[[#This Row],[INVESTOR CODE]]),LS[Unique Code],0),),0)} -> 10.160617 | AH2: {=IF(INVESTORS_LIST[[#This Row],[SIP_TOTAL UNITS BUY]]>0,INDEX(SIP[NAV at Cost (Average)],MATCH(CONCATENATE(COUNTIFS(SIP[Investor ID],INVESTORS_LIST[[#This Row],[INVESTOR CODE]]),INVESTORS_LIST[[#This Row],[INVESTOR CODE]]),SIP[Unique Code],0),),0)} -> 0 | AI2: =IF(INVESTORS_LIST[[#This Row],[TOTAL CURRENT UNITS]]=0,0,(INVESTORS_LIST[[#This Row],[LS_WEIGHT]]*INVESTORS_LIST[[#This Row],[LS_AVERAGE COST]])+(INVESTORS_LIST[[#This Row],[SIP_WEIGHT]]*INVESTORS_LIST[[#This Row],[SIP_AVERAGE COST]])) -> 10.160617 | AJ2: =NAV_MKT -> 12.552 | AK2: =IF(INVESTORS_LIST[[#This Row],[TOTAL CURRENT UNITS]]=0,0,INVESTORS_LIST[[#This Row],[TOTAL CURRENT UNITS]]*INVESTORS_LIST[[#This Row],[NAV]]) -> 931182.67 | AL2: =IF(INVESTORS_LIST[[#This Row],[LS_TOTAL CURRENT UNITS]]=0,0,INVESTORS_LIST[[#This Row],[LS_TOTAL CURRENT UNITS]]*INVESTORS_LIST[[#This Row],[NAV]]) -> 931182.67 | AM2: =IF(INVESTORS_LIST[[#This Row],[SIP_TOTAL CURRENT UNITS]]=0,0,INVESTORS_LIST[[#This Row],[SIP_TOTAL CURRENT UNITS]]*INVESTORS_LIST[[#This Row],[NAV]]) -> 0 | AO2: =IF(INVESTORS_LIST[[#This Row],[TOTAL SELLABLE UNITS]]=0,0,INVESTORS_LIST[[#This Row],[TOTAL SELLABLE UNITS]]*INVESTORS_LIST[[#This Row],[NAV]]) -> 0 | AP2: =INVESTORS_LIST[[#This Row],[LS_TOTAL REALIZED GAIN]]+INVESTORS_LIST[[#This Row],[SIP_TOTAL REALIZED GAIN]] -> -6.7117258 | AQ2: =INVESTORS_LIST[[#This Row],[TOTAL MARKET VALUE]]-INVESTORS_LIST[[#This Row],[TOTAL COST VALUE OF CURRENT INVESTMENT]] -> 177407.14 | AR2: =SUMIFS(DivAndTax[Tax Amount],DivAndTax[Investor ID],INVESTORS_LIST[[#This Row],[INVESTOR CODE]]) -> 11554.19 | AS2: =SUMIFS(DivAndTax[Gross Dividend],DivAndTax[Investor ID],INVESTORS_LIST[[#This Row],[INVESTOR CODE]]) -> 77027.9 | AT2: =IFERROR(INVESTORS_LIST[[#This Row],[TOTAL CURRENT UNITS]]/SUM(INVESTORS_LIST[TOTAL CURRENT UNITS]),0) -> 0.0035568355
A3: EKUSH WEALTH MANAGEMENT LIMITED | B3: A00003 | C3: Dear | D3: Company/Organization | E3: =SUMIFS(LS[Unit],LS[Investor ID],INVESTORS_LIST[[#This Row],[INVESTOR CODE]],LS[B/S],"B") -> 6509076 | F3: =-SUMIFS(LS[Unit],LS[Investor ID],INVESTORS_LIST[[#This Row],[INVESTOR CODE]],LS[B/S],"S") -> 3596507 | G3: =IF(INVESTORS_LIST[[#This Row],[LS_TOTAL UNITS BUY]]=0,0,INVESTORS_LIST[[#This Row],[LS_TOTAL UNITS BUY]]-INVESTORS_LIST[[#This Row],[LS_TOTAL UNITS SOLD]]) -> 2912569 | H3: =IF(INVESTORS_LIST[[#This Row],[LS_TOTAL UNITS BUY]]=0,0,SUMIFS(LS[Amount],LS[Investor ID],INVESTORS_LIST[[#This Row],[INVESTOR CODE]],LS[B/S],"B")) -> 65776233 | I3: =IF(INVESTORS_LIST[[#This Row],[LS_TOTAL UNITS SOLD]]=0,0,SUMIFS(LS[Cost of Units Sold],LS[Investor ID],INVESTORS_LIST[[#This Row],[INVESTOR CODE]],LS[B/S],"S")) -> 35899827 | J3: =IF(INVESTORS_LIST[[#This Row],[LS_TOTAL CURRENT UNITS]]=0,0,INVESTORS_LIST[[#This Row],[LS_TOTAL CURRENT UNITS]]*INVESTORS_LIST[[#This Row],[LS_AVERAGE COST]]) -> 29876406 | K3: =IF(INVESTORS_LIST[[#This Row],[LS_TOTAL UNITS SOLD]]=0,0,SUMIFS(LS[Realized Gain],LS[Investor ID],INVESTORS_LIST[[#This Row],[INVESTOR CODE]],LS[B/S],"S")) -> 150156.26 | L3: =SUMIFS(SIP[Unit],SIP[Investor ID],INVESTORS_LIST[[#This Row],[INVESTOR CODE]],SIP[B/S],"B") -> 0 | M3: =-SUMIFS(SIP[Unit],SIP[Investor ID],INVESTORS_LIST[[#This Row],[INVESTOR CODE]],SIP[B/S],"S") -> 0 | N3: =IF(INVESTORS_LIST[[#This Row],[SIP_TOTAL UNITS BUY]]=0,0,INVESTORS_LIST[[#This Row],[SIP_TOTAL UNITS BUY]]-INVESTORS_LIST[[#This Row],[SIP_TOTAL UNITS SOLD]]) -> 0 | O3: =IF(INVESTORS_LIST[[#This Row],[SIP_TOTAL UNITS BUY]]=0,0,SUMIFS(SIP[Amount],SIP[Investor ID],INVESTORS_LIST[[#This Row],[INVESTOR CODE]],SIP[B/S],"B")) -> 0 | P3: =IF(INVESTORS_LIST[[#This Row],[SIP_TOTAL UNITS SOLD]]=0,0,SUMIFS(SIP[Cost of Units Sold],SIP[Investor ID],INVESTORS_LIST[[#This Row],[INVESTOR CODE]],SIP[B/S],"S")) -> 0 | Q3: =IF(INVESTORS_LIST[[#This Row],[SIP_TOTAL CURRENT UNITS]]=0,0,INVESTORS_LIST[[#This Row],[SIP_TOTAL CURRENT UNITS]]*INVESTORS_LIST[[#This Row],[SIP_AVERAGE COST]]) -> 0 | R3: =IF(INVESTORS_LIST[[#This Row],[SIP_TOTAL UNITS SOLD]]=0,0,SUMIFS(SIP[Realized Gain],SIP[Investor ID],INVESTORS_LIST[[#This Row],[INVESTOR CODE]],SIP[B/S],"S")) -> 0 | S3: =INVESTORS_LIST[[#This Row],[LS_TOTAL UNITS BUY]]+INVESTORS_LIST[[#This Row],[SIP_TOTAL UNITS BUY]] -> 6509076 | T3: =INVESTORS_LIST[[#This Row],[LS_TOTAL UNITS SOLD]]+INVESTORS_LIST[[#This Row],[SIP_TOTAL UNITS SOLD]] -> 3596507 | U3: 672004 | V3: =SUMIFS(LS[BO UNIT TRANSFER],LS[Investor ID],INVESTORS_LIST[[#This Row],[INVESTOR CODE]],LS[B/S],"B") -> 0 | W3: =SUMIFS(LS[BO UNIT TRANSFER],LS[Investor ID],INVESTORS_LIST[[#This Row],[INVESTOR CODE]],LS[B/S],"S") -> 0 | X3: =SUMIFS(SIP[BO UNIT TRANSFER],SIP[Investor ID],INVESTORS_LIST[[#This Row],[INVESTOR CODE]],SIP[B/S],"S") -> 0 | Y3: =SUMIFS(SIP[BO UNIT TRANSFER],SIP[Investor ID],INVESTORS_LIST[[#This Row],[INVESTOR CODE]],SIP[B/S],"B") -> 0 | Z3: =INVESTORS_LIST[[#This Row],[BO OPENING BALANCE]]+INVESTORS_LIST[[#This Row],[LS- BO UNITS SELL]]+INVESTORS_LIST[[#This Row],[LS- BO UNITS REPURCHASE]]+INVESTORS_LIST[[#This Row],[SIP- BO UNITS REPURCHASE]]-INVESTORS_LIST[[#This Row],[SIP- BO UNITS SELL]] -> 672004 | AA3: =INVESTORS_LIST[[#This Row],[TOTAL UNITS BUY]]-INVESTORS_LIST[[#This Row],[TOTAL UNITS SOLD]] -> 2912569 | AB3: =INVESTORS_LIST[[#This Row],[TOTAL CURRENT UNITS]]-INVESTORS_LIST[[#This Row],[BO UNITS HOLD]] -> 2240565 | AC3: =INDEX([4]!Table_1[BO ID],MATCH(INVESTORS_LIST[[#This Row],[INVESTOR CODE]],[4]!Table_1[INVESTOR CODE],0)) -> #REF! | AD3: =INVESTORS_LIST[[#This Row],[LS_TOTAL COST VALUE OF CURRENT UNITS]]+INVESTORS_LIST[[#This Row],[SIP_TOTAL COST VALUE OF CURRENT UNITS]] -> 29876406 | AE3: =IF(INVESTORS_LIST[[#This Row],[TOTAL CURRENT UNITS]]=0,0,INVESTORS_LIST[[#This Row],[LS_TOTAL CURRENT UNITS]]/INVESTORS_LIST[[#This Row],[TOTAL CURRENT UNITS]]) -> 1 | AF3: =IF(INVESTORS_LIST[[#This Row],[TOTAL CURRENT UNITS]]=0,0,INVESTORS_LIST[[#This Row],[SIP_TOTAL CURRENT UNITS]]/INVESTORS_LIST[[#This Row],[TOTAL CURRENT UNITS]]) -> 0 | AG3: {=IF(INVESTORS_LIST[[#This Row],[LS_TOTAL UNITS BUY]]>0,INDEX(LS[NAV at Cost (Average)],MATCH(CONCATENATE(COUNTIFS(LS[Investor ID],INVESTORS_LIST[[#This Row],[INVESTOR CODE]]),INVESTORS_LIST[[#This Row],[INVESTOR CODE]]),LS[Unique Code],0),),0)} -> 10.25775 | AH3: {=IF(INVESTORS_LIST[[#This Row],[SIP_TOTAL UNITS BUY]]>0,INDEX(SIP[NAV at Cost (Average)],MATCH(CONCATENATE(COUNTIFS(SIP[Investor ID],INVESTORS_LIST[[#This Row],[INVESTOR CODE]]),INVESTORS_LIST[[#This Row],[INVESTOR CODE]]),SIP[Unique Code],0),),0)} -> 0 | AI3: =IF(INVESTORS_LIST[[#This Row],[TOTAL CURRENT UNITS]]=0,0,(INVESTORS_LIST[[#This Row],[LS_WEIGHT]]*INVESTORS_LIST[[#This Row],[LS_AVERAGE COST]])+(INVESTORS_LIST[[#This Row],[SIP_WEIGHT]]*INVESTORS_LIST[[#This Row],[SIP_AVERAGE COST]])) -> 10.25775 | AJ3: =NAV_MKT -> 12.552 | AK3: =IF(INVESTORS_LIST[[#This Row],[TOTAL CURRENT UNITS]]=0,0,INVESTORS_LIST[[#This Row],[TOTAL CURRENT UNITS]]*INVESTORS_LIST[[#This Row],[NAV]]) -> 36558566 | AL3: =IF(INVESTORS_LIST[[#This Row],[LS_TOTAL CURRENT UNITS]]=0,0,INVESTORS_LIST[[#This Row],[LS_TOTAL CURRENT UNITS]]*INVESTORS_LIST[[#This Row],[NAV]]) -> 36558566 | AM3: =IF(INVESTORS_LIST[[#This Row],[SIP_TOTAL CURRENT UNITS]]=0,0,INVESTORS_LIST[[#This Row],[SIP_TOTAL CURRENT UNITS]]*INVESTORS_LIST[[#This Row],[NAV]]) -> 0 | AO3: =IF(INVESTORS_LIST[[#This Row],[TOTAL SELLABLE UNITS]]=0,0,INVESTORS_LIST[[#This Row],[TOTAL SELLABLE UNITS]]*INVESTORS_LIST[[#This Row],[NAV]]) -> 0 | AP3: =INVESTORS_LIST[[#This Row],[LS_TOTAL REALIZED GAIN]]+INVESTORS_LIST[[#This Row],[SIP_TOTAL REALIZED GAIN]] -> 150156.26 | AQ3: =INVESTORS_LIST[[#This Row],[TOTAL MARKET VALUE]]-INVESTORS_LIST[[#This Row],[TOTAL COST VALUE OF CURRENT INVESTMENT]] -> 6682160.1 | AR3: =SUMIFS(DivAndTax[Tax Amount],DivAndTax[Investor ID],INVESTORS_LIST[[#This Row],[INVESTOR CODE]]) -> 532968.47 | AS3: =SUMIFS(DivAndTax[Gross Dividend],DivAndTax[Investor ID],INVESTORS_LIST[[#This Row],[INVESTOR CODE]]) -> 2664842.4 | AT3: =IFERROR(INVESTORS_LIST[[#This Row],[TOTAL CURRENT UNITS]]/SUM(INVESTORS_LIST[TOTAL CURRENT UNITS]),0) -> 0.13964264
A4: SADIA AHMED | B4: A00004 | C4: Dear Mrs. | D4: Individual | E4: =SUMIFS(LS[Unit],LS[Investor ID],INVESTORS_LIST[[#This Row],[INVESTOR CODE]],LS[B/S],"B") -> 0 | F4: =-SUMIFS(LS[Unit],LS[Investor ID],INVESTORS_LIST[[#This Row],[INVESTOR CODE]],LS[B/S],"S") -> 0 | G4: =IF(INVESTORS_LIST[[#This Row],[LS_TOTAL UNITS BUY]]=0,0,INVESTORS_LIST[[#This Row],[LS_TOTAL UNITS BUY]]-INVESTORS_LIST[[#This Row],[LS_TOTAL UNITS SOLD]]) -> 0 | H4: =IF(INVESTORS_LIST[[#This Row],[LS_TOTAL UNITS BUY]]=0,0,SUMIFS(LS[Amount],LS[Investor ID],INVESTORS_LIST[[#This Row],[INVESTOR CODE]],LS[B/S],"B")) -> 0 | I4: =IF(INVESTORS_LIST[[#This Row],[LS_TOTAL UNITS SOLD]]=0,0,SUMIFS(LS[Cost of Units Sold],LS[Investor ID],INVESTORS_LIST[[#This Row],[INVESTOR CODE]],LS[B/S],"S")) -> 0 | J4: =IF(INVESTORS_LIST[[#This Row],[LS_TOTAL CURRENT UNITS]]=0,0,INVESTORS_LIST[[#This Row],[LS_TOTAL CURRENT UNITS]]*INVESTORS_LIST[[#This Row],[LS_AVERAGE COST]]) -> 0 | K4: =IF(INVESTORS_LIST[[#This Row],[LS_TOTAL UNITS SOLD]]=0,0,SUMIFS(LS[Realized Gain],LS[Investor ID],INVESTORS_LIST[[#This Row],[INVESTOR CODE]],LS[B/S],"S")) -> 0 | L4: =SUMIFS(SIP[Unit],SIP[Investor ID],INVESTORS_LIST[[#This Row],[INVESTOR CODE]],SIP[B/S],"B") -> 0 | M4: =-SUMIFS(SIP[Unit],SIP[Investor ID],INVESTORS_LIST[[#This Row],[INVESTOR CODE]],SIP[B/S],"S") -> 0 | N4: =IF(INVESTORS_LIST[[#This Row],[SIP_TOTAL UNITS BUY]]=0,0,INVESTORS_LIST[[#This Row],[SIP_TOTAL UNITS BUY]]-INVESTORS_LIST[[#This Row],[SIP_TOTAL UNITS SOLD]]) -> 0 | O4: =IF(INVESTORS_LIST[[#This Row],[SIP_TOTAL UNITS BUY]]=0,0,SUMIFS(SIP[Amount],SIP[Investor ID],INVESTORS_LIST[[#This Row],[INVESTOR CODE]],SIP[B/S],"B")) -> 0 | P4: =IF(INVESTORS_LIST[[#This Row],[SIP_TOTAL UNITS SOLD]]=0,0,SUMIFS(SIP[Cost of Units Sold],SIP[Investor ID],INVESTORS_LIST[[#This Row],[INVESTOR CODE]],SIP[B/S],"S")) -> 0 | Q4: =IF(INVESTORS_LIST[[#This Row],[SIP_TOTAL CURRENT UNITS]]=0,0,INVESTORS_LIST[[#This Row],[SIP_TOTAL CURRENT UNITS]]*INVESTORS_LIST[[#This Row],[SIP_AVERAGE COST]]) -> 0 | R4: =IF(INVESTORS_LIST[[#This Row],[SIP_TOTAL UNITS SOLD]]=0,0,SUMIFS(SIP[Realized Gain],SIP[Investor ID],INVESTORS_LIST[[#This Row],[INVESTOR CODE]],SIP[B/S],"S")) -> 0 | S4: =INVESTORS_LIST[[#This Row],[LS_TOTAL UNITS BUY]]+INVESTORS_LIST[[#This Row],[SIP_TOTAL UNITS BUY]] -> 0 | T4: =INVESTORS_LIST[[#This Row],[LS_TOTAL UNITS SOLD]]+INVESTORS_LIST[[#This Row],[SIP_TOTAL UNITS SOLD]] -> 0 | U4: 0 | V4: =SUMIFS(LS[BO UNIT TRANSFER],LS[Investor ID],INVESTORS_LIST[[#This Row],[INVESTOR CODE]],LS[B/S],"B") -> 0 | W4: =SUMIFS(LS[BO UNIT TRANSFER],LS[Investor ID],INVESTORS_LIST[[#This Row],[INVESTOR CODE]],LS[B/S],"S") -> 0 | X4: =SUMIFS(SIP[BO UNIT TRANSFER],SIP[Investor ID],INVESTORS_LIST[[#This Row],[INVESTOR CODE]],SIP[B/S],"S") -> 0 | Y4: =SUMIFS(SIP[BO UNIT TRANSFER],SIP[Investor ID],INVESTORS_LIST[[#This Row],[INVESTOR CODE]],SIP[B/S],"B") -> 0 | Z4: =INVESTORS_LIST[[#This Row],[BO OPENING BALANCE]]+INVESTORS_LIST[[#This Row],[LS- BO UNITS SELL]]+INVESTORS_LIST[[#This Row],[LS- BO UNITS REPURCHASE]]+INVESTORS_LIST[[#This Row],[SIP- BO UNITS REPURCHASE]]-INVESTORS_LIST[[#This Row],[SIP- BO UNITS SELL]] -> 0 | AA4: =INVESTORS_LIST[[#This Row],[TOTAL UNITS BUY]]-INVESTORS_LIST[[#This Row],[TOTAL UNITS SOLD]] -> 0 | AB4: =INVESTORS_LIST[[#This Row],[TOTAL CURRENT UNITS]]-INVESTORS_LIST[[#This Row],[BO UNITS HOLD]] -> 0 | AC4: =INDEX([4]!Table_1[BO ID],MATCH(INVESTORS_LIST[[#This Row],[INVESTOR CODE]],[4]!Table_1[INVESTOR CODE],0)) -> #REF! | AD4: =INVESTORS_LIST[[#This Row],[LS_TOTAL COST VALUE OF CURRENT UNITS]]+INVESTORS_LIST[[#This Row],[SIP_TOTAL COST VALUE OF CURRENT UNITS]] -> 0 | AE4: =IF(INVESTORS_LIST[[#This Row],[TOTAL CURRENT UNITS]]=0,0,INVESTORS_LIST[[#This Row],[LS_TOTAL CURRENT UNITS]]/INVESTORS_LIST[[#This Row],[TOTAL CURRENT UNITS]]) -> 0 | AF4: =IF(INVESTORS_LIST[[#This Row],[TOTAL CURRENT UNITS]]=0,0,INVESTORS_LIST[[#This Row],[SIP_TOTAL CURRENT UNITS]]/INVESTORS_LIST[[#This Row],[TOTAL CURRENT UNITS]]) -> 0 | AG4: {=IF(INVESTORS_LIST[[#This Row],[LS_TOTAL UNITS BUY]]>0,INDEX(LS[NAV at Cost (Average)],MATCH(CONCATENATE(COUNTIFS(LS[Investor ID],INVESTORS_LIST[[#This Row],[INVESTOR CODE]]),INVESTORS_LIST[[#This Row],[INVESTOR CODE]]),LS[Unique Code],0),),0)} -> 0 | AH4: {=IF(INVESTORS_LIST[[#This Row],[SIP_TOTAL UNITS BUY]]>0,INDEX(SIP[NAV at Cost (Average)],MATCH(CONCATENATE(COUNTIFS(SIP[Investor ID],INVESTORS_LIST[[#This Row],[INVESTOR CODE]]),INVESTORS_LIST[[#This Row],[INVESTOR CODE]]),SIP[Unique Code],0),),0)} -> 0 | AI4: =IF(INVESTORS_LIST[[#This Row],[TOTAL CURRENT UNITS]]=0,0,(INVESTORS_LIST[[#This Row],[LS_WEIGHT]]*INVESTORS_LIST[[#This Row],[LS_AVERAGE COST]])+(INVESTORS_LIST[[#This Row],[SIP_WEIGHT]]*INVESTORS_LIST[[#This Row],[SIP_AVERAGE COST]])) -> 0 | AJ4: =NAV_MKT -> 12.552 | AK4: =IF(INVESTORS_LIST[[#This Row],[TOTAL CURRENT UNITS]]=0,0,INVESTORS_LIST[[#This Row],[TOTAL CURRENT UNITS]]*INVESTORS_LIST[[#This Row],[NAV]]) -> 0 | AL4: =IF(INVESTORS_LIST[[#This Row],[LS_TOTAL CURRENT UNITS]]=0,0,INVESTORS_LIST[[#This Row],[LS_TOTAL CURRENT UNITS]]*INVESTORS_LIST[[#This Row],[NAV]]) -> 0 | AM4: =IF(INVESTORS_LIST[[#This Row],[SIP_TOTAL CURRENT UNITS]]=0,0,INVESTORS_LIST[[#This Row],[SIP_TOTAL CURRENT UNITS]]*INVESTORS_LIST[[#This Row],[NAV]]) -> 0 | AO4: =IF(INVESTORS_LIST[[#This Row],[TOTAL SELLABLE UNITS]]=0,0,INVESTORS_LIST[[#This Row],[TOTAL SELLABLE UNITS]]*INVESTORS_LIST[[#This Row],[NAV]]) -> 0 | AP4: =INVESTORS_LIST[[#This Row],[LS_TOTAL REALIZED GAIN]]+INVESTORS_LIST[[#This Row],[SIP_TOTAL REALIZED GAIN]] -> 0 | AQ4: =INVESTORS_LIST[[#This Row],[TOTAL MARKET VALUE]]-INVESTORS_LIST[[#This Row],[TOTAL COST VALUE OF CURRENT INVESTMENT]] -> 0 | AR4: =SUMIFS(DivAndTax[Tax Amount],DivAndTax[Investor ID],INVESTORS_LIST[[#This Row],[INVESTOR CODE]]) -> 0 | AS4: =SUMIFS(DivAndTax[Gross Dividend],DivAndTax[Investor ID],INVESTORS_LIST[[#This Row],[INVESTOR CODE]]) -> 0 | AT4: =IFERROR(INVESTORS_LIST[[#This Row],[TOTAL CURRENT UNITS]]/SUM(INVESTORS_LIST[TOTAL CURRENT UNITS]),0) -> 0
A5: MORSHEDA MIM | B5: A00005 | C5: Dear Mrs. | D5: Individual | E5: =SUMIFS(LS[Unit],LS[Investor ID],INVESTORS_LIST[[#This Row],[INVESTOR CODE]],LS[B/S],"B") -> 62130 | F5: =-SUMIFS(LS[Unit],LS[Investor ID],INVESTORS_LIST[[#This Row],[INVESTOR CODE]],LS[B/S],"S") -> 62130 | G5: =IF(INVESTORS_LIST[[#This Row],[LS_TOTAL UNITS BUY]]=0,0,INVESTORS_LIST[[#This Row],[LS_TOTAL UNITS BUY]]-INVESTORS_LIST[[#This Row],[LS_TOTAL UNITS SOLD]]) -> 0 | H5: =IF(INVESTORS_LIST[[#This Row],[LS_TOTAL UNITS BUY]]=0,0,SUMIFS(LS[Amount],LS[Investor ID],INVESTORS_LIST[[#This Row],[INVESTOR CODE]],LS[B/S],"B")) -> 655381.42 | I5: =IF(INVESTORS_LIST[[#This Row],[LS_TOTAL UNITS SOLD]]=0,0,SUMIFS(LS[Cost of Units Sold],LS[Investor ID],INVESTORS_LIST[[#This Row],[INVESTOR CODE]],LS[B/S],"S")) -> 655381.42 | J5: =IF(INVESTORS_LIST[[#This Row],[LS_TOTAL CURRENT UNITS]]=0,0,INVESTORS_LIST[[#This Row],[LS_TOTAL CURRENT UNITS]]*INVESTORS_LIST[[#This Row],[LS_AVERAGE COST]]) -> 0 | K5: =IF(INVESTORS_LIST[[#This Row],[LS_TOTAL UNITS SOLD]]=0,0,SUMIFS(LS[Realized Gain],LS[Investor ID],INVESTORS_LIST[[#This Row],[INVESTOR CODE]],LS[B/S],"S")) -> 81418.25 | L5: =SUMIFS(SIP[Unit],SIP[Investor ID],INVESTORS_LIST[[#This Row],[INVESTOR CODE]],SIP[B/S],"B") -> 0 | M5: =-SUMIFS(SIP[Unit],SIP[Investor ID],INVESTORS_LIST[[#This Row],[INVESTOR CODE]],SIP[B/S],"S") -> 0 | N5: =IF(INVESTORS_LIST[[#This Row],[SIP_TOTAL UNITS BUY]]=0,0,INVESTORS_LIST[[#This Row],[SIP_TOTAL UNITS BUY]]-INVESTORS_LIST[[#This Row],[SIP_TOTAL UNITS SOLD]]) -> 0 | O5: =IF(INVESTORS_LIST[[#This Row],[SIP_TOTAL UNITS BUY]]=0,0,SUMIFS(SIP[Amount],SIP[Investor ID],INVESTORS_LIST[[#This Row],[INVESTOR CODE]],SIP[B/S],"B")) -> 0 | P5: =IF(INVESTORS_LIST[[#This Row],[SIP_TOTAL UNITS SOLD]]=0,0,SUMIFS(SIP[Cost of Units Sold],SIP[Investor ID],INVESTORS_LIST[[#This Row],[INVESTOR CODE]],SIP[B/S],"S")) -> 0 | Q5: =IF(INVESTORS_LIST[[#This Row],[SIP_TOTAL CURRENT UNITS]]=0,0,INVESTORS_LIST[[#This Row],[SIP_TOTAL CURRENT UNITS]]*INVESTORS_LIST[[#This Row],[SIP_AVERAGE COST]]) -> 0 | R5: =IF(INVESTORS_LIST[[#This Row],[SIP_TOTAL UNITS SOLD]]=0,0,SUMIFS(SIP[Realized Gain],SIP[Investor ID],INVESTORS_LIST[[#This Row],[INVESTOR CODE]],SIP[B/S],"S")) -> 0 | S5: =INVESTORS_LIST[[#This Row],[LS_TOTAL UNITS BUY]]+INVESTORS_LIST[[#This Row],[SIP_TOTAL UNITS BUY]] -> 62130 | T5: =INVESTORS_LIST[[#This Row],[LS_TOTAL UNITS SOLD]]+INVESTORS_LIST[[#This Row],[SIP_TOTAL UNITS SOLD]] -> 62130 | U5: 0 | V5: =SUMIFS(LS[BO UNIT TRANSFER],LS[Investor ID],INVESTORS_LIST[[#This Row],[INVESTOR CODE]],LS[B/S],"B") -> 0 | W5: =SUMIFS(LS[BO UNIT TRANSFER],LS[Investor ID],INVESTORS_LIST[[#This Row],[INVESTOR CODE]],LS[B/S],"S") -> 0 | X5: =SUMIFS(SIP[BO UNIT TRANSFER],SIP[Investor ID],INVESTORS_LIST[[#This Row],[INVESTOR CODE]],SIP[B/S],"S") -> 0 | Y5: =SUMIFS(SIP[BO UNIT TRANSFER],SIP[Investor ID],INVESTORS_LIST[[#This Row],[INVESTOR CODE]],SIP[B/S],"B") -> 0 | Z5: =INVESTORS_LIST[[#This Row],[BO OPENING BALANCE]]+INVESTORS_LIST[[#This Row],[LS- BO UNITS SELL]]+INVESTORS_LIST[[#This Row],[LS- BO UNITS REPURCHASE]]+INVESTORS_LIST[[#This Row],[SIP- BO UNITS REPURCHASE]]-INVESTORS_LIST[[#This Row],[SIP- BO UNITS SELL]] -> 0 | AA5: =INVESTORS_LIST[[#This Row],[TOTAL UNITS BUY]]-INVESTORS_LIST[[#This Row],[TOTAL UNITS SOLD]] -> 0 | AB5: =INVESTORS_LIST[[#This Row],[TOTAL CURRENT UNITS]]-INVESTORS_LIST[[#This Row],[BO UNITS HOLD]] -> 0 | AC5: =INDEX([4]!Table_1[BO ID],MATCH(INVESTORS_LIST[[#This Row],[INVESTOR CODE]],[4]!Table_1[INVESTOR CODE],0)) -> #REF! | AD5: =INVESTORS_LIST[[#This Row],[LS_TOTAL COST VALUE OF CURRENT UNITS]]+INVESTORS_LIST[[#This Row],[SIP_TOTAL COST VALUE OF CURRENT UNITS]] -> 0 | AE5: =IF(INVESTORS_LIST[[#This Row],[TOTAL CURRENT UNITS]]=0,0,INVESTORS_LIST[[#This Row],[LS_TOTAL CURRENT UNITS]]/INVESTORS_LIST[[#This Row],[TOTAL CURRENT UNITS]]) -> 0 | AF5: =IF(INVESTORS_LIST[[#This Row],[TOTAL CURRENT UNITS]]=0,0,INVESTORS_LIST[[#This Row],[SIP_TOTAL CURRENT UNITS]]/INVESTORS_LIST[[#This Row],[TOTAL CURRENT UNITS]]) -> 0 | AG5: {=IF(INVESTORS_LIST[[#This Row],[LS_TOTAL UNITS BUY]]>0,INDEX(LS[NAV at Cost (Average)],MATCH(CONCATENATE(COUNTIFS(LS[Investor ID],INVESTORS_LIST[[#This Row],[INVESTOR CODE]]),INVESTORS_LIST[[#This Row],[INVESTOR CODE]]),LS[Unique Code],0),),0)} -> 0 | AH5: {=IF(INVESTORS_LIST[[#This Row],[SIP_TOTAL UNITS BUY]]>0,INDEX(SIP[NAV at Cost (Average)],MATCH(CONCATENATE(COUNTIFS(SIP[Investor ID],INVESTORS_LIST[[#This Row],[INVESTOR CODE]]),INVESTORS_LIST[[#This Row],[INVESTOR CODE]]),SIP[Unique Code],0),),0)} -> 0 | AI5: =IF(INVESTORS_LIST[[#This Row],[TOTAL CURRENT UNITS]]=0,0,(INVESTORS_LIST[[#This Row],[LS_WEIGHT]]*INVESTORS_LIST[[#This Row],[LS_AVERAGE COST]])+(INVESTORS_LIST[[#This Row],[SIP_WEIGHT]]*INVESTORS_LIST[[#This Row],[SIP_AVERAGE COST]])) -> 0 | AJ5: =NAV_MKT -> 12.552 | AK5: =IF(INVESTORS_LIST[[#This Row],[TOTAL CURRENT UNITS]]=0,0,INVESTORS_LIST[[#This Row],[TOTAL CURRENT UNITS]]*INVESTORS_LIST[[#This Row],[NAV]]) -> 0 | AL5: =IF(INVESTORS_LIST[[#This Row],[LS_TOTAL CURRENT UNITS]]=0,0,INVESTORS_LIST[[#This Row],[LS_TOTAL CURRENT UNITS]]*INVESTORS_LIST[[#This Row],[NAV]]) -> 0 | AM5: =IF(INVESTORS_LIST[[#This Row],[SIP_TOTAL CURRENT UNITS]]=0,0,INVESTORS_LIST[[#This Row],[SIP_TOTAL CURRENT UNITS]]*INVESTORS_LIST[[#This Row],[NAV]]) -> 0 | AO5: =IF(INVESTORS_LIST[[#This Row],[TOTAL SELLABLE UNITS]]=0,0,INVESTORS_LIST[[#This Row],[TOTAL SELLABLE UNITS]]*INVESTORS_LIST[[#This Row],[NAV]]) -> 0 | AP5: =INVESTORS_LIST[[#This Row],[LS_TOTAL REALIZED GAIN]]+INVESTORS_LIST[[#This Row],[SIP_TOTAL REALIZED GAIN]] -> 81418.25 | AQ5: =INVESTORS_LIST[[#This Row],[TOTAL MARKET VALUE]]-INVESTORS_LIST[[#This Row],[TOTAL COST VALUE OF CURRENT INVESTMENT]] -> 0 | AR5: =SUMIFS(DivAndTax[Tax Amount],DivAndTax[Investor ID],INVESTORS_LIST[[#This Row],[INVESTOR CODE]]) -> 4479.08 | AS5: =SUMIFS(DivAndTax[Gross Dividend],DivAndTax[Investor ID],INVESTORS_LIST[[#This Row],[INVESTOR CODE]]) -> 29860.5 | AT5: =IFERROR(INVESTORS_LIST[[#This Row],[TOTAL CURRENT UNITS]]/SUM(INVESTORS_LIST[TOTAL CURRENT UNITS]),0) -> 0
A6: MD. JAHANGIR ALAM | B6: A00006 | C6: Dear Mr. | D6: Individual | E6: =SUMIFS(LS[Unit],LS[Investor ID],INVESTORS_LIST[[#This Row],[INVESTOR CODE]],LS[B/S],"B") -> 0 | F6: =-SUMIFS(LS[Unit],LS[Investor ID],INVESTORS_LIST[[#This Row],[INVESTOR CODE]],LS[B/S],"S") -> 0 | G6: =IF(INVESTORS_LIST[[#This Row],[LS_TOTAL UNITS BUY]]=0,0,INVESTORS_LIST[[#This Row],[LS_TOTAL UNITS BUY]]-INVESTORS_LIST[[#This Row],[LS_TOTAL UNITS SOLD]]) -> 0 | H6: =IF(INVESTORS_LIST[[#This Row],[LS_TOTAL UNITS BUY]]=0,0,SUMIFS(LS[Amount],LS[Investor ID],INVESTORS_LIST[[#This Row],[INVESTOR CODE]],LS[B/S],"B")) -> 0 | I6: =IF(INVESTORS_LIST[[#This Row],[LS_TOTAL UNITS SOLD]]=0,0,SUMIFS(LS[Cost of Units Sold],LS[Investor ID],INVESTORS_LIST[[#This Row],[INVESTOR CODE]],LS[B/S],"S")) -> 0 | J6: =IF(INVESTORS_LIST[[#This Row],[LS_TOTAL CURRENT UNITS]]=0,0,INVESTORS_LIST[[#This Row],[LS_TOTAL CURRENT UNITS]]*INVESTORS_LIST[[#This Row],[LS_AVERAGE COST]]) -> 0 | K6: =IF(INVESTORS_LIST[[#This Row],[LS_TOTAL UNITS SOLD]]=0,0,SUMIFS(LS[Realized Gain],LS[Investor ID],INVESTORS_LIST[[#This Row],[INVESTOR CODE]],LS[B/S],"S")) -> 0 | L6: =SUMIFS(SIP[Unit],SIP[Investor ID],INVESTORS_LIST[[#This Row],[INVESTOR CODE]],SIP[B/S],"B") -> 0 | M6: =-SUMIFS(SIP[Unit],SIP[Investor ID],INVESTORS_LIST[[#This Row],[INVESTOR CODE]],SIP[B/S],"S") -> 0 | N6: =IF(INVESTORS_LIST[[#This Row],[SIP_TOTAL UNITS BUY]]=0,0,INVESTORS_LIST[[#This Row],[SIP_TOTAL UNITS BUY]]-INVESTORS_LIST[[#This Row],[SIP_TOTAL UNITS SOLD]]) -> 0 | O6: =IF(INVESTORS_LIST[[#This Row],[SIP_TOTAL UNITS BUY]]=0,0,SUMIFS(SIP[Amount],SIP[Investor ID],INVESTORS_LIST[[#This Row],[INVESTOR CODE]],SIP[B/S],"B")) -> 0 | P6: =IF(INVESTORS_LIST[[#This Row],[SIP_TOTAL UNITS SOLD]]=0,0,SUMIFS(SIP[Cost of Units Sold],SIP[Investor ID],INVESTORS_LIST[[#This Row],[INVESTOR CODE]],SIP[B/S],"S")) -> 0 | Q6: =IF(INVESTORS_LIST[[#This Row],[SIP_TOTAL CURRENT UNITS]]=0,0,INVESTORS_LIST[[#This Row],[SIP_TOTAL CURRENT UNITS]]*INVESTORS_LIST[[#This Row],[SIP_AVERAGE COST]]) -> 0 | R6: =IF(INVESTORS_LIST[[#This Row],[SIP_TOTAL UNITS SOLD]]=0,0,SUMIFS(SIP[Realized Gain],SIP[Investor ID],INVESTORS_LIST[[#This Row],[INVESTOR CODE]],SIP[B/S],"S")) -> 0 | S6: =INVESTORS_LIST[[#This Row],[LS_TOTAL UNITS BUY]]+INVESTORS_LIST[[#This Row],[SIP_TOTAL UNITS BUY]] -> 0 | T6: =INVESTORS_LIST[[#This Row],[LS_TOTAL UNITS SOLD]]+INVESTORS_LIST[[#This Row],[SIP_TOTAL UNITS SOLD]] -> 0 | U6: 0 | V6: =SUMIFS(LS[BO UNIT TRANSFER],LS[Investor ID],INVESTORS_LIST[[#This Row],[INVESTOR CODE]],LS[B/S],"B") -> 0 | W6: =SUMIFS(LS[BO UNIT TRANSFER],LS[Investor ID],INVESTORS_LIST[[#This Row],[INVESTOR CODE]],LS[B/S],"S") -> 0 | X6: =SUMIFS(SIP[BO UNIT TRANSFER],SIP[Investor ID],INVESTORS_LIST[[#This Row],[INVESTOR CODE]],SIP[B/S],"S") -> 0 | Y6: =SUMIFS(SIP[BO UNIT TRANSFER],SIP[Investor ID],INVESTORS_LIST[[#This Row],[INVESTOR CODE]],SIP[B/S],"B") -> 0 | Z6: =INVESTORS_LIST[[#This Row],[BO OPENING BALANCE]]+INVESTORS_LIST[[#This Row],[LS- BO UNITS SELL]]+INVESTORS_LIST[[#This Row],[LS- BO UNITS REPURCHASE]]+INVESTORS_LIST[[#This Row],[SIP- BO UNITS REPURCHASE]]-INVESTORS_LIST[[#This Row],[SIP- BO UNITS SELL]] -> 0 | AA6: =INVESTORS_LIST[[#This Row],[TOTAL UNITS BUY]]-INVESTORS_LIST[[#This Row],[TOTAL UNITS SOLD]] -> 0 | AB6: =INVESTORS_LIST[[#This Row],[TOTAL CURRENT UNITS]]-INVESTORS_LIST[[#This Row],[BO UNITS HOLD]] -> 0 | AC6: =INDEX([4]!Table_1[BO ID],MATCH(INVESTORS_LIST[[#This Row],[INVESTOR CODE]],[4]!Table_1[INVESTOR CODE],0)) -> #REF! | AD6: =INVESTORS_LIST[[#This Row],[LS_TOTAL COST VALUE OF CURRENT UNITS]]+INVESTORS_LIST[[#This Row],[SIP_TOTAL COST VALUE OF CURRENT UNITS]] -> 0 | AE6: =IF(INVESTORS_LIST[[#This Row],[TOTAL CURRENT UNITS]]=0,0,INVESTORS_LIST[[#This Row],[LS_TOTAL CURRENT UNITS]]/INVESTORS_LIST[[#This Row],[TOTAL CURRENT UNITS]]) -> 0 | AF6: =IF(INVESTORS_LIST[[#This Row],[TOTAL CURRENT UNITS]]=0,0,INVESTORS_LIST[[#This Row],[SIP_TOTAL CURRENT UNITS]]/INVESTORS_LIST[[#This Row],[TOTAL CURRENT UNITS]]) -> 0 | AG6: {=IF(INVESTORS_LIST[[#This Row],[LS_TOTAL UNITS BUY]]>0,INDEX(LS[NAV at Cost (Average)],MATCH(CONCATENATE(COUNTIFS(LS[Investor ID],INVESTORS_LIST[[#This Row],[INVESTOR CODE]]),INVESTORS_LIST[[#This Row],[INVESTOR CODE]]),LS[Unique Code],0),),0)} -> 0 | AH6: {=IF(INVESTORS_LIST[[#This Row],[SIP_TOTAL UNITS BUY]]>0,INDEX(SIP[NAV at Cost (Average)],MATCH(CONCATENATE(COUNTIFS(SIP[Investor ID],INVESTORS_LIST[[#This Row],[INVESTOR CODE]]),INVESTORS_LIST[[#This Row],[INVESTOR CODE]]),SIP[Unique Code],0),),0)} -> 0 | AI6: =IF(INVESTORS_LIST[[#This Row],[TOTAL CURRENT UNITS]]=0,0,(INVESTORS_LIST[[#This Row],[LS_WEIGHT]]*INVESTORS_LIST[[#This Row],[LS_AVERAGE COST]])+(INVESTORS_LIST[[#This Row],[SIP_WEIGHT]]*INVESTORS_LIST[[#This Row],[SIP_AVERAGE COST]])) -> 0 | AJ6: =NAV_MKT -> 12.552 | AK6: =IF(INVESTORS_LIST[[#This Row],[TOTAL CURRENT UNITS]]=0,0,INVESTORS_LIST[[#This Row],[TOTAL CURRENT UNITS]]*INVESTORS_LIST[[#This Row],[NAV]]) -> 0 | AL6: =IF(INVESTORS_LIST[[#This Row],[LS_TOTAL CURRENT UNITS]]=0,0,INVESTORS_LIST[[#This Row],[LS_TOTAL CURRENT UNITS]]*INVESTORS_LIST[[#This Row],[NAV]]) -> 0 | AM6: =IF(INVESTORS_LIST[[#This Row],[SIP_TOTAL CURRENT UNITS]]=0,0,INVESTORS_LIST[[#This Row],[SIP_TOTAL CURRENT UNITS]]*INVESTORS_LIST[[#This Row],[NAV]]) -> 0 | AO6: =IF(INVESTORS_LIST[[#This Row],[TOTAL SELLABLE UNITS]]=0,0,INVESTORS_LIST[[#This Row],[TOTAL SELLABLE UNITS]]*INVESTORS_LIST[[#This Row],[NAV]]) -> 0 | AP6: =INVESTORS_LIST[[#This Row],[LS_TOTAL REALIZED GAIN]]+INVESTORS_LIST[[#This Row],[SIP_TOTAL REALIZED GAIN]] -> 0 | AQ6: =INVESTORS_LIST[[#This Row],[TOTAL MARKET VALUE]]-INVESTORS_LIST[[#This Row],[TOTAL COST VALUE OF CURRENT INVESTMENT]] -> 0 | AR6: =SUMIFS(DivAndTax[Tax Amount],DivAndTax[Investor ID],INVESTORS_LIST[[#This Row],[INVESTOR CODE]]) -> 0 | AS6: =SUMIFS(DivAndTax[Gross Dividend],DivAndTax[Investor ID],INVESTORS_LIST[[#This Row],[INVESTOR CODE]]) -> 0 | AT6: =IFERROR(INVESTORS_LIST[[#This Row],[TOTAL CURRENT UNITS]]/SUM(INVESTORS_LIST[TOTAL CURRENT UNITS]),0) -> 0
A7: BISWAS ARIFUR RAHMAN | B7: A00007 | C7: Dear Mr. | D7: Individual | E7: =SUMIFS(LS[Unit],LS[Investor ID],INVESTORS_LIST[[#This Row],[INVESTOR CODE]],LS[B/S],"B") -> 20000 | F7: =-SUMIFS(LS[Unit],LS[Investor ID],INVESTORS_LIST[[#This Row],[INVESTOR CODE]],LS[B/S],"S") -> 20000 | G7: =IF(INVESTORS_LIST[[#This Row],[LS_TOTAL UNITS BUY]]=0,0,INVESTORS_LIST[[#This Row],[LS_TOTAL UNITS BUY]]-INVESTORS_LIST[[#This Row],[LS_TOTAL UNITS SOLD]]) -> 0 | H7: =IF(INVESTORS_LIST[[#This Row],[LS_TOTAL UNITS BUY]]=0,0,SUMIFS(LS[Amount],LS[Investor ID],INVESTORS_LIST[[#This Row],[INVESTOR CODE]],LS[B/S],"B")) -> 200000 | I7: =IF(INVESTORS_LIST[[#This Row],[LS_TOTAL UNITS SOLD]]=0,0,SUMIFS(LS[Cost of Units Sold],LS[Investor ID],INVESTORS_LIST[[#This Row],[INVESTOR CODE]],LS[B/S],"S")) -> 200000 | J7: =IF(INVESTORS_LIST[[#This Row],[LS_TOTAL CURRENT UNITS]]=0,0,INVESTORS_LIST[[#This Row],[LS_TOTAL CURRENT UNITS]]*INVESTORS_LIST[[#This Row],[LS_AVERAGE COST]]) -> 0 | K7: =IF(INVESTORS_LIST[[#This Row],[LS_TOTAL UNITS SOLD]]=0,0,SUMIFS(LS[Realized Gain],LS[Investor ID],INVESTORS_LIST[[#This Row],[INVESTOR CODE]],LS[B/S],"S")) -> -1000 | L7: =SUMIFS(SIP[Unit],SIP[Investor ID],INVESTORS_LIST[[#This Row],[INVESTOR CODE]],SIP[B/S],"B") -> 0 | M7: =-SUMIFS(SIP[Unit],SIP[Investor ID],INVESTORS_LIST[[#This Row],[INVESTOR CODE]],SIP[B/S],"S") -> 0 | N7: =IF(INVESTORS_LIST[[#This Row],[SIP_TOTAL UNITS BUY]]=0,0,INVESTORS_LIST[[#This Row],[SIP_TOTAL UNITS BUY]]-INVESTORS_LIST[[#This Row],[SIP_TOTAL UNITS SOLD]]) -> 0 | O7: =IF(INVESTORS_LIST[[#This Row],[SIP_TOTAL UNITS BUY]]=0,0,SUMIFS(SIP[Amount],SIP[Investor ID],INVESTORS_LIST[[#This Row],[INVESTOR CODE]],SIP[B/S],"B")) -> 0 | P7: =IF(INVESTORS_LIST[[#This Row],[SIP_TOTAL UNITS SOLD]]=0,0,SUMIFS(SIP[Cost of Units Sold],SIP[Investor ID],INVESTORS_LIST[[#This Row],[INVESTOR CODE]],SIP[B/S],"S")) -> 0 | Q7: =IF(INVESTORS_LIST[[#This Row],[SIP_TOTAL CURRENT UNITS]]=0,0,INVESTORS_LIST[[#This Row],[SIP_TOTAL CURRENT UNITS]]*INVESTORS_LIST[[#This Row],[SIP_AVERAGE COST]]) -> 0 | R7: =IF(INVESTORS_LIST[[#This Row],[SIP_TOTAL UNITS SOLD]]=0,0,SUMIFS(SIP[Realized Gain],SIP[Investor ID],INVESTORS_LIST[[#This Row],[INVESTOR CODE]],SIP[B/S],"S")) -> 0 | S7: =INVESTORS_LIST[[#This Row],[LS_TOTAL UNITS BUY]]+INVESTORS_LIST[[#This Row],[SIP_TOTAL UNITS BUY]] -> 20000 | T7: =INVESTORS_LIST[[#This Row],[LS_TOTAL UNITS SOLD]]+INVESTORS_LIST[[#This Row],[SIP_TOTAL UNITS SOLD]] -> 20000 | U7: 0 | V7: =SUMIFS(LS[BO UNIT TRANSFER],LS[Investor ID],INVESTORS_LIST[[#This Row],[INVESTOR CODE]],LS[B/S],"B") -> 0 | W7: =SUMIFS(LS[BO UNIT TRANSFER],LS[Investor ID],INVESTORS_LIST[[#This Row],[INVESTOR CODE]],LS[B/S],"S") -> 0 | X7: =SUMIFS(SIP[BO UNIT TRANSFER],SIP[Investor ID],INVESTORS_LIST[[#This Row],[INVESTOR CODE]],SIP[B/S],"S") -> 0 | Y7: =SUMIFS(SIP[BO UNIT TRANSFER],SIP[Investor ID],INVESTORS_LIST[[#This Row],[INVESTOR CODE]],SIP[B/S],"B") -> 0 | Z7: =INVESTORS_LIST[[#This Row],[BO OPENING BALANCE]]+INVESTORS_LIST[[#This Row],[LS- BO UNITS SELL]]+INVESTORS_LIST[[#This Row],[LS- BO UNITS REPURCHASE]]+INVESTORS_LIST[[#This Row],[SIP- BO UNITS REPURCHASE]]-INVESTORS_LIST[[#This Row],[SIP- BO UNITS SELL]] -> 0 | AA7: =INVESTORS_LIST[[#This Row],[TOTAL UNITS BUY]]-INVESTORS_LIST[[#This Row],[TOTAL UNITS SOLD]] -> 0 | AB7: =INVESTORS_LIST[[#This Row],[TOTAL CURRENT UNITS]]-INVESTORS_LIST[[#This Row],[BO UNITS HOLD]] -> 0 | AC7: =INDEX([4]!Table_1[BO ID],MATCH(INVESTORS_LIST[[#This Row],[INVESTOR CODE]],[4]!Table_1[INVESTOR CODE],0)) -> #REF! | AD7: =INVESTORS_LIST[[#This Row],[LS_TOTAL COST VALUE OF CURRENT UNITS]]+INVESTORS_LIST[[#This Row],[SIP_TOTAL COST VALUE OF CURRENT UNITS]] -> 0 | AE7: =IF(INVESTORS_LIST[[#This Row],[TOTAL CURRENT UNITS]]=0,0,INVESTORS_LIST[[#This Row],[LS_TOTAL CURRENT UNITS]]/INVESTORS_LIST[[#This Row],[TOTAL CURRENT UNITS]]) -> 0 | AF7: =IF(INVESTORS_LIST[[#This Row],[TOTAL CURRENT UNITS]]=0,0,INVESTORS_LIST[[#This Row],[SIP_TOTAL CURRENT UNITS]]/INVESTORS_LIST[[#This Row],[TOTAL CURRENT UNITS]]) -> 0 | AG7: {=IF(INVESTORS_LIST[[#This Row],[LS_TOTAL UNITS BUY]]>0,INDEX(LS[NAV at Cost (Average)],MATCH(CONCATENATE(COUNTIFS(LS[Investor ID],INVESTORS_LIST[[#This Row],[INVESTOR CODE]]),INVESTORS_LIST[[#This Row],[INVESTOR CODE]]),LS[Unique Code],0),),0)} -> 0 | AH7: {=IF(INVESTORS_LIST[[#This Row],[SIP_TOTAL UNITS BUY]]>0,INDEX(SIP[NAV at Cost (Average)],MATCH(CONCATENATE(COUNTIFS(SIP[Investor ID],INVESTORS_LIST[[#This Row],[INVESTOR CODE]]),INVESTORS_LIST[[#This Row],[INVESTOR CODE]]),SIP[Unique Code],0),),0)} -> 0 | AI7: =IF(INVESTORS_LIST[[#This Row],[TOTAL CURRENT UNITS]]=0,0,(INVESTORS_LIST[[#This Row],[LS_WEIGHT]]*INVESTORS_LIST[[#This Row],[LS_AVERAGE COST]])+(INVESTORS_LIST[[#This Row],[SIP_WEIGHT]]*INVESTORS_LIST[[#This Row],[SIP_AVERAGE COST]])) -> 0 | AJ7: =NAV_MKT -> 12.552 | AK7: =IF(INVESTORS_LIST[[#This Row],[TOTAL CURRENT UNITS]]=0,0,INVESTORS_LIST[[#This Row],[TOTAL CURRENT UNITS]]*INVESTORS_LIST[[#This Row],[NAV]]) -> 0 | AL7: =IF(INVESTORS_LIST[[#This Row],[LS_TOTAL CURRENT UNITS]]=0,0,INVESTORS_LIST[[#This Row],[LS_TOTAL CURRENT UNITS]]*INVESTORS_LIST[[#This Row],[NAV]]) -> 0 | AM7: =IF(INVESTORS_LIST[[#This Row],[SIP_TOTAL CURRENT UNITS]]=0,0,INVESTORS_LIST[[#This Row],[SIP_TOTAL CURRENT UNITS]]*INVESTORS_LIST[[#This Row],[NAV]]) -> 0 | AO7: =IF(INVESTORS_LIST[[#This Row],[TOTAL SELLABLE UNITS]]=0,0,INVESTORS_LIST[[#This Row],[TOTAL SELLABLE UNITS]]*INVESTORS_LIST[[#This Row],[NAV]]) -> 0 | AP7: =INVESTORS_LIST[[#This Row],[LS_TOTAL REALIZED GAIN]]+INVESTORS_LIST[[#This Row],[SIP_TOTAL REALIZED GAIN]] -> -1000 | AQ7: =INVESTORS_LIST[[#This Row],[TOTAL MARKET VALUE]]-INVESTORS_LIST[[#This Row],[TOTAL COST VALUE OF CURRENT INVESTMENT]] -> 0 | AR7: =SUMIFS(DivAndTax[Tax Amount],DivAndTax[Investor ID],INVESTORS_LIST[[#This Row],[INVESTOR CODE]]) -> 0 | AS7: =SUMIFS(DivAndTax[Gross Dividend],DivAndTax[Investor ID],INVESTORS_LIST[[#This Row],[INVESTOR CODE]]) -> 0 | AT7: =IFERROR(INVESTORS_LIST[[#This Row],[TOTAL CURRENT UNITS]]/SUM(INVESTORS_LIST[TOTAL CURRENT UNITS]),0) -> 0
A8: JEWEL SAHA | B8: A00008 | C8: Dear Mr. | D8: Individual | E8: =SUMIFS(LS[Unit],LS[Investor ID],INVESTORS_LIST[[#This Row],[INVESTOR CODE]],LS[B/S],"B") -> 0 | F8: =-SUMIFS(LS[Unit],LS[Investor ID],INVESTORS_LIST[[#This Row],[INVESTOR CODE]],LS[B/S],"S") -> 0 | G8: =IF(INVESTORS_LIST[[#This Row],[LS_TOTAL UNITS BUY]]=0,0,INVESTORS_LIST[[#This Row],[LS_TOTAL UNITS BUY]]-INVESTORS_LIST[[#This Row],[LS_TOTAL UNITS SOLD]]) -> 0 | H8: =IF(INVESTORS_LIST[[#This Row],[LS_TOTAL UNITS BUY]]=0,0,SUMIFS(LS[Amount],LS[Investor ID],INVESTORS_LIST[[#This Row],[INVESTOR CODE]],LS[B/S],"B")) -> 0 | I8: =IF(INVESTORS_LIST[[#This Row],[LS_TOTAL UNITS SOLD]]=0,0,SUMIFS(LS[Cost of Units Sold],LS[Investor ID],INVESTORS_LIST[[#This Row],[INVESTOR CODE]],LS[B/S],"S")) -> 0 | J8: =IF(INVESTORS_LIST[[#This Row],[LS_TOTAL CURRENT UNITS]]=0,0,INVESTORS_LIST[[#This Row],[LS_TOTAL CURRENT UNITS]]*INVESTORS_LIST[[#This Row],[LS_AVERAGE COST]]) -> 0 | K8: =IF(INVESTORS_LIST[[#This Row],[LS_TOTAL UNITS SOLD]]=0,0,SUMIFS(LS[Realized Gain],LS[Investor ID],INVESTORS_LIST[[#This Row],[INVESTOR CODE]],LS[B/S],"S")) -> 0 | L8: =SUMIFS(SIP[Unit],SIP[Investor ID],INVESTORS_LIST[[#This Row],[INVESTOR CODE]],SIP[B/S],"B") -> 0 | M8: =-SUMIFS(SIP[Unit],SIP[Investor ID],INVESTORS_LIST[[#This Row],[INVESTOR CODE]],SIP[B/S],"S") -> 0 | N8: =IF(INVESTORS_LIST[[#This Row],[SIP_TOTAL UNITS BUY]]=0,0,INVESTORS_LIST[[#This Row],[SIP_TOTAL UNITS BUY]]-INVESTORS_LIST[[#This Row],[SIP_TOTAL UNITS SOLD]]) -> 0 | O8: =IF(INVESTORS_LIST[[#This Row],[SIP_TOTAL UNITS BUY]]=0,0,SUMIFS(SIP[Amount],SIP[Investor ID],INVESTORS_LIST[[#This Row],[INVESTOR CODE]],SIP[B/S],"B")) -> 0 | P8: =IF(INVESTORS_LIST[[#This Row],[SIP_TOTAL UNITS SOLD]]=0,0,SUMIFS(SIP[Cost of Units Sold],SIP[Investor ID],INVESTORS_LIST[[#This Row],[INVESTOR CODE]],SIP[B/S],"S")) -> 0 | Q8: =IF(INVESTORS_LIST[[#This Row],[SIP_TOTAL CURRENT UNITS]]=0,0,INVESTORS_LIST[[#This Row],[SIP_TOTAL CURRENT UNITS]]*INVESTORS_LIST[[#This Row],[SIP_AVERAGE COST]]) -> 0 | R8: =IF(INVESTORS_LIST[[#This Row],[SIP_TOTAL UNITS SOLD]]=0,0,SUMIFS(SIP[Realized Gain],SIP[Investor ID],INVESTORS_LIST[[#This Row],[INVESTOR CODE]],SIP[B/S],"S")) -> 0 | S8: =INVESTORS_LIST[[#This Row],[LS_TOTAL UNITS BUY]]+INVESTORS_LIST[[#This Row],[SIP_TOTAL UNITS BUY]] -> 0 | T8: =INVESTORS_LIST[[#This Row],[LS_TOTAL UNITS SOLD]]+INVESTORS_LIST[[#This Row],[SIP_TOTAL UNITS SOLD]] -> 0 | U8: 0 | V8: =SUMIFS(LS[BO UNIT TRANSFER],LS[Investor ID],INVESTORS_LIST[[#This Row],[INVESTOR CODE]],LS[B/S],"B") -> 0 | W8: =SUMIFS(LS[BO UNIT TRANSFER],LS[Investor ID],INVESTORS_LIST[[#This Row],[INVESTOR CODE]],LS[B/S],"S") -> 0 | X8: =SUMIFS(SIP[BO UNIT TRANSFER],SIP[Investor ID],INVESTORS_LIST[[#This Row],[INVESTOR CODE]],SIP[B/S],"S") -> 0 | Y8: =SUMIFS(SIP[BO UNIT TRANSFER],SIP[Investor ID],INVESTORS_LIST[[#This Row],[INVESTOR CODE]],SIP[B/S],"B") -> 0 | Z8: =INVESTORS_LIST[[#This Row],[BO OPENING BALANCE]]+INVESTORS_LIST[[#This Row],[LS- BO UNITS SELL]]+INVESTORS_LIST[[#This Row],[LS- BO UNITS REPURCHASE]]+INVESTORS_LIST[[#This Row],[SIP- BO UNITS REPURCHASE]]-INVESTORS_LIST[[#This Row],[SIP- BO UNITS SELL]] -> 0 | AA8: =INVESTORS_LIST[[#This Row],[TOTAL UNITS BUY]]-INVESTORS_LIST[[#This Row],[TOTAL UNITS SOLD]] -> 0 | AB8: =INVESTORS_LIST[[#This Row],[TOTAL CURRENT UNITS]]-INVESTORS_LIST[[#This Row],[BO UNITS HOLD]] -> 0 | AC8: =INDEX([4]!Table_1[BO ID],MATCH(INVESTORS_LIST[[#This Row],[INVESTOR CODE]],[4]!Table_1[INVESTOR CODE],0)) -> #REF! | AD8: =INVESTORS_LIST[[#This Row],[LS_TOTAL COST VALUE OF CURRENT UNITS]]+INVESTORS_LIST[[#This Row],[SIP_TOTAL COST VALUE OF CURRENT UNITS]] -> 0 | AE8: =IF(INVESTORS_LIST[[#This Row],[TOTAL CURRENT UNITS]]=0,0,INVESTORS_LIST[[#This Row],[LS_TOTAL CURRENT UNITS]]/INVESTORS_LIST[[#This Row],[TOTAL CURRENT UNITS]]) -> 0 | AF8: =IF(INVESTORS_LIST[[#This Row],[TOTAL CURRENT UNITS]]=0,0,INVESTORS_LIST[[#This Row],[SIP_TOTAL CURRENT UNITS]]/INVESTORS_LIST[[#This Row],[TOTAL CURRENT UNITS]]) -> 0 | AG8: {=IF(INVESTORS_LIST[[#This Row],[LS_TOTAL UNITS BUY]]>0,INDEX(LS[NAV at Cost (Average)],MATCH(CONCATENATE(COUNTIFS(LS[Investor ID],INVESTORS_LIST[[#This Row],[INVESTOR CODE]]),INVESTORS_LIST[[#This Row],[INVESTOR CODE]]),LS[Unique Code],0),),0)} -> 0 | AH8: {=IF(INVESTORS_LIST[[#This Row],[SIP_TOTAL UNITS BUY]]>0,INDEX(SIP[NAV at Cost (Average)],MATCH(CONCATENATE(COUNTIFS(SIP[Investor ID],INVESTORS_LIST[[#This Row],[INVESTOR CODE]]),INVESTORS_LIST[[#This Row],[INVESTOR CODE]]),SIP[Unique Code],0),),0)} -> 0 | AI8: =IF(INVESTORS_LIST[[#This Row],[TOTAL CURRENT UNITS]]=0,0,(INVESTORS_LIST[[#This Row],[LS_WEIGHT]]*INVESTORS_LIST[[#This Row],[LS_AVERAGE COST]])+(INVESTORS_LIST[[#This Row],[SIP_WEIGHT]]*INVESTORS_LIST[[#This Row],[SIP_AVERAGE COST]])) -> 0 | AJ8: =NAV_MKT -> 12.552 | AK8: =IF(INVESTORS_LIST[[#This Row],[TOTAL CURRENT UNITS]]=0,0,INVESTORS_LIST[[#This Row],[TOTAL CURRENT UNITS]]*INVESTORS_LIST[[#This Row],[NAV]]) -> 0 | AL8: =IF(INVESTORS_LIST[[#This Row],[LS_TOTAL CURRENT UNITS]]=0,0,INVESTORS_LIST[[#This Row],[LS_TOTAL CURRENT UNITS]]*INVESTORS_LIST[[#This Row],[NAV]]) -> 0 | AM8: =IF(INVESTORS_LIST[[#This Row],[SIP_TOTAL CURRENT UNITS]]=0,0,INVESTORS_LIST[[#This Row],[SIP_TOTAL CURRENT UNITS]]*INVESTORS_LIST[[#This Row],[NAV]]) -> 0 | AO8: =IF(INVESTORS_LIST[[#This Row],[TOTAL SELLABLE UNITS]]=0,0,INVESTORS_LIST[[#This Row],[TOTAL SELLABLE UNITS]]*INVESTORS_LIST[[#This Row],[NAV]]) -> 0 | AP8: =INVESTORS_LIST[[#This Row],[LS_TOTAL REALIZED GAIN]]+INVESTORS_LIST[[#This Row],[SIP_TOTAL REALIZED GAIN]] -> 0 | AQ8: =INVESTORS_LIST[[#This Row],[TOTAL MARKET VALUE]]-INVESTORS_LIST[[#This Row],[TOTAL COST VALUE OF CURRENT INVESTMENT]] -> 0 | AR8: =SUMIFS(DivAndTax[Tax Amount],DivAndTax[Investor ID],INVESTORS_LIST[[#This Row],[INVESTOR CODE]]) -> 0 | AS8: =SUMIFS(DivAndTax[Gross Dividend],DivAndTax[Investor ID],INVESTORS_LIST[[#This Row],[INVESTOR CODE]]) -> 0 | AT8: =IFERROR(INVESTORS_LIST[[#This Row],[TOTAL CURRENT UNITS]]/SUM(INVESTORS_LIST[TOTAL CURRENT UNITS]),0) -> 0
A9: SHIBBIR AHMED | B9: A00009 | C9: Dear Mr. | D9: Individual | E9: =SUMIFS(LS[Unit],LS[Investor ID],INVESTORS_LIST[[#This Row],[INVESTOR CODE]],LS[B/S],"B") -> 0 | F9: =-SUMIFS(LS[Unit],LS[Investor ID],INVESTORS_LIST[[#This Row],[INVESTOR CODE]],LS[B/S],"S") -> 0 | G9: =IF(INVESTORS_LIST[[#This Row],[LS_TOTAL UNITS BUY]]=0,0,INVESTORS_LIST[[#This Row],[LS_TOTAL UNITS BUY]]-INVESTORS_LIST[[#This Row],[LS_TOTAL UNITS SOLD]]) -> 0 | H9: =IF(INVESTORS_LIST[[#This Row],[LS_TOTAL UNITS BUY]]=0,0,SUMIFS(LS[Amount],LS[Investor ID],INVESTORS_LIST[[#This Row],[INVESTOR CODE]],LS[B/S],"B")) -> 0 | I9: =IF(INVESTORS_LIST[[#This Row],[LS_TOTAL UNITS SOLD]]=0,0,SUMIFS(LS[Cost of Units Sold],LS[Investor ID],INVESTORS_LIST[[#This Row],[INVESTOR CODE]],LS[B/S],"S")) -> 0 | J9: =IF(INVESTORS_LIST[[#This Row],[LS_TOTAL CURRENT UNITS]]=0,0,INVESTORS_LIST[[#This Row],[LS_TOTAL CURRENT UNITS]]*INVESTORS_LIST[[#This Row],[LS_AVERAGE COST]]) -> 0 | K9: =IF(INVESTORS_LIST[[#This Row],[LS_TOTAL UNITS SOLD]]=0,0,SUMIFS(LS[Realized Gain],LS[Investor ID],INVESTORS_LIST[[#This Row],[INVESTOR CODE]],LS[B/S],"S")) -> 0 | L9: =SUMIFS(SIP[Unit],SIP[Investor ID],INVESTORS_LIST[[#This Row],[INVESTOR CODE]],SIP[B/S],"B") -> 0 | M9: =-SUMIFS(SIP[Unit],SIP[Investor ID],INVESTORS_LIST[[#This Row],[INVESTOR CODE]],SIP[B/S],"S") -> 0 | N9: =IF(INVESTORS_LIST[[#This Row],[SIP_TOTAL UNITS BUY]]=0,0,INVESTORS_LIST[[#This Row],[SIP_TOTAL UNITS BUY]]-INVESTORS_LIST[[#This Row],[SIP_TOTAL UNITS SOLD]]) -> 0 | O9: =IF(INVESTORS_LIST[[#This Row],[SIP_TOTAL UNITS BUY]]=0,0,SUMIFS(SIP[Amount],SIP[Investor ID],INVESTORS_LIST[[#This Row],[INVESTOR CODE]],SIP[B/S],"B")) -> 0 | P9: =IF(INVESTORS_LIST[[#This Row],[SIP_TOTAL UNITS SOLD]]=0,0,SUMIFS(SIP[Cost of Units Sold],SIP[Investor ID],INVESTORS_LIST[[#This Row],[INVESTOR CODE]],SIP[B/S],"S")) -> 0 | Q9: =IF(INVESTORS_LIST[[#This Row],[SIP_TOTAL CURRENT UNITS]]=0,0,INVESTORS_LIST[[#This Row],[SIP_TOTAL CURRENT UNITS]]*INVESTORS_LIST[[#This Row],[SIP_AVERAGE COST]]) -> 0 | R9: =IF(INVESTORS_LIST[[#This Row],[SIP_TOTAL UNITS SOLD]]=0,0,SUMIFS(SIP[Realized Gain],SIP[Investor ID],INVESTORS_LIST[[#This Row],[INVESTOR CODE]],SIP[B/S],"S")) -> 0 | S9: =INVESTORS_LIST[[#This Row],[LS_TOTAL UNITS BUY]]+INVESTORS_LIST[[#This Row],[SIP_TOTAL UNITS BUY]] -> 0 | T9: =INVESTORS_LIST[[#This Row],[LS_TOTAL UNITS SOLD]]+INVESTORS_LIST[[#This Row],[SIP_TOTAL UNITS SOLD]] -> 0 | U9: 0 | V9: =SUMIFS(LS[BO UNIT TRANSFER],LS[Investor ID],INVESTORS_LIST[[#This Row],[INVESTOR CODE]],LS[B/S],"B") -> 0 | W9: =SUMIFS(LS[BO UNIT TRANSFER],LS[Investor ID],INVESTORS_LIST[[#This Row],[INVESTOR CODE]],LS[B/S],"S") -> 0 | X9: =SUMIFS(SIP[BO UNIT TRANSFER],SIP[Investor ID],INVESTORS_LIST[[#This Row],[INVESTOR CODE]],SIP[B/S],"S") -> 0 | Y9: =SUMIFS(SIP[BO UNIT TRANSFER],SIP[Investor ID],INVESTORS_LIST[[#This Row],[INVESTOR CODE]],SIP[B/S],"B") -> 0 | Z9: =INVESTORS_LIST[[#This Row],[BO OPENING BALANCE]]+INVESTORS_LIST[[#This Row],[LS- BO UNITS SELL]]+INVESTORS_LIST[[#This Row],[LS- BO UNITS REPURCHASE]]+INVESTORS_LIST[[#This Row],[SIP- BO UNITS REPURCHASE]]-INVESTORS_LIST[[#This Row],[SIP- BO UNITS SELL]] -> 0 | AA9: =INVESTORS_LIST[[#This Row],[TOTAL UNITS BUY]]-INVESTORS_LIST[[#This Row],[TOTAL UNITS SOLD]] -> 0 | AB9: =INVESTORS_LIST[[#This Row],[TOTAL CURRENT UNITS]]-INVESTORS_LIST[[#This Row],[BO UNITS HOLD]] -> 0 | AC9: =INDEX([4]!Table_1[BO ID],MATCH(INVESTORS_LIST[[#This Row],[INVESTOR CODE]],[4]!Table_1[INVESTOR CODE],0)) -> #REF! | AD9: =INVESTORS_LIST[[#This Row],[LS_TOTAL COST VALUE OF CURRENT UNITS]]+INVESTORS_LIST[[#This Row],[SIP_TOTAL COST VALUE OF CURRENT UNITS]] -> 0 | AE9: =IF(INVESTORS_LIST[[#This Row],[TOTAL CURRENT UNITS]]=0,0,INVESTORS_LIST[[#This Row],[LS_TOTAL CURRENT UNITS]]/INVESTORS_LIST[[#This Row],[TOTAL CURRENT UNITS]]) -> 0 | AF9: =IF(INVESTORS_LIST[[#This Row],[TOTAL CURRENT UNITS]]=0,0,INVESTORS_LIST[[#This Row],[SIP_TOTAL CURRENT UNITS]]/INVESTORS_LIST[[#This Row],[TOTAL CURRENT UNITS]]) -> 0 | AG9: {=IF(INVESTORS_LIST[[#This Row],[LS_TOTAL UNITS BUY]]>0,INDEX(LS[NAV at Cost (Average)],MATCH(CONCATENATE(COUNTIFS(LS[Investor ID],INVESTORS_LIST[[#This Row],[INVESTOR CODE]]),INVESTORS_LIST[[#This Row],[INVESTOR CODE]]),LS[Unique Code],0),),0)} -> 0 | AH9: {=IF(INVESTORS_LIST[[#This Row],[SIP_TOTAL UNITS BUY]]>0,INDEX(SIP[NAV at Cost (Average)],MATCH(CONCATENATE(COUNTIFS(SIP[Investor ID],INVESTORS_LIST[[#This Row],[INVESTOR CODE]]),INVESTORS_LIST[[#This Row],[INVESTOR CODE]]),SIP[Unique Code],0),),0)} -> 0 | AI9: =IF(INVESTORS_LIST[[#This Row],[TOTAL CURRENT UNITS]]=0,0,(INVESTORS_LIST[[#This Row],[LS_WEIGHT]]*INVESTORS_LIST[[#This Row],[LS_AVERAGE COST]])+(INVESTORS_LIST[[#This Row],[SIP_WEIGHT]]*INVESTORS_LIST[[#This Row],[SIP_AVERAGE COST]])) -> 0 | AJ9: =NAV_MKT -> 12.552 | AK9: =IF(INVESTORS_LIST[[#This Row],[TOTAL CURRENT UNITS]]=0,0,INVESTORS_LIST[[#This Row],[TOTAL CURRENT UNITS]]*INVESTORS_LIST[[#This Row],[NAV]]) -> 0 | AL9: =IF(INVESTORS_LIST[[#This Row],[LS_TOTAL CURRENT UNITS]]=0,0,INVESTORS_LIST[[#This Row],[LS_TOTAL CURRENT UNITS]]*INVESTORS_LIST[[#This Row],[NAV]]) -> 0 | AM9: =IF(INVESTORS_LIST[[#This Row],[SIP_TOTAL CURRENT UNITS]]=0,0,INVESTORS_LIST[[#This Row],[SIP_TOTAL CURRENT UNITS]]*INVESTORS_LIST[[#This Row],[NAV]]) -> 0 | AO9: =IF(INVESTORS_LIST[[#This Row],[TOTAL SELLABLE UNITS]]=0,0,INVESTORS_LIST[[#This Row],[TOTAL SELLABLE UNITS]]*INVESTORS_LIST[[#This Row],[NAV]]) -> 0 | AP9: =INVESTORS_LIST[[#This Row],[LS_TOTAL REALIZED GAIN]]+INVESTORS_LIST[[#This Row],[SIP_TOTAL REALIZED GAIN]] -> 0 | AQ9: =INVESTORS_LIST[[#This Row],[TOTAL MARKET VALUE]]-INVESTORS_LIST[[#This Row],[TOTAL COST VALUE OF CURRENT INVESTMENT]] -> 0 | AR9: =SUMIFS(DivAndTax[Tax Amount],DivAndTax[Investor ID],INVESTORS_LIST[[#This Row],[INVESTOR CODE]]) -> 0 | AS9: =SUMIFS(DivAndTax[Gross Dividend],DivAndTax[Investor ID],INVESTORS_LIST[[#This Row],[INVESTOR CODE]]) -> 0 | AT9: =IFERROR(INVESTORS_LIST[[#This Row],[TOTAL CURRENT UNITS]]/SUM(INVESTORS_LIST[TOTAL CURRENT UNITS]),0) -> 0
A10: SHYAMAL KRISHNA SAHA | B10: A00010 | C10: Dear Mr. | D10: Individual | E10: =SUMIFS(LS[Unit],LS[Investor ID],INVESTORS_LIST[[#This Row],[INVESTOR CODE]],LS[B/S],"B") -> 50000 | F10: =-SUMIFS(LS[Unit],LS[Investor ID],INVESTORS_LIST[[#This Row],[INVESTOR CODE]],LS[B/S],"S") -> 50000 | G10: =IF(INVESTORS_LIST[[#This Row],[LS_TOTAL UNITS BUY]]=0,0,INVESTORS_LIST[[#This Row],[LS_TOTAL UNITS BUY]]-INVESTORS_LIST[[#This Row],[LS_TOTAL UNITS SOLD]]) -> 0 | H10: =IF(INVESTORS_LIST[[#This Row],[LS_TOTAL UNITS BUY]]=0,0,SUMIFS(LS[Amount],LS[Investor ID],INVESTORS_LIST[[#This Row],[INVESTOR CODE]],LS[B/S],"B")) -> 500000 | I10: =IF(INVESTORS_LIST[[#This Row],[LS_TOTAL UNITS SOLD]]=0,0,SUMIFS(LS[Cost of Units Sold],LS[Investor ID],INVESTORS_LIST[[#This Row],[INVESTOR CODE]],LS[B/S],"S")) -> 500000 | J10: =IF(INVESTORS_LIST[[#This Row],[LS_TOTAL CURRENT UNITS]]=0,0,INVESTORS_LIST[[#This Row],[LS_TOTAL CURRENT UNITS]]*INVESTORS_LIST[[#This Row],[LS_AVERAGE COST]]) -> 0 | K10: =IF(INVESTORS_LIST[[#This Row],[LS_TOTAL UNITS SOLD]]=0,0,SUMIFS(LS[Realized Gain],LS[Investor ID],INVESTORS_LIST[[#This Row],[INVESTOR CODE]],LS[B/S],"S")) -> 1000 | L10: =SUMIFS(SIP[Unit],SIP[Investor ID],INVESTORS_LIST[[#This Row],[INVESTOR CODE]],SIP[B/S],"B") -> 0 | M10: =-SUMIFS(SIP[Unit],SIP[Investor ID],INVESTORS_LIST[[#This Row],[INVESTOR CODE]],SIP[B/S],"S") -> 0 | N10: =IF(INVESTORS_LIST[[#This Row],[SIP_TOTAL UNITS BUY]]=0,0,INVESTORS_LIST[[#This Row],[SIP_TOTAL UNITS BUY]]-INVESTORS_LIST[[#This Row],[SIP_TOTAL UNITS SOLD]]) -> 0 | O10: =IF(INVESTORS_LIST[[#This Row],[SIP_TOTAL UNITS BUY]]=0,0,SUMIFS(SIP[Amount],SIP[Investor ID],INVESTORS_LIST[[#This Row],[INVESTOR CODE]],SIP[B/S],"B")) -> 0 | P10: =IF(INVESTORS_LIST[[#This Row],[SIP_TOTAL UNITS SOLD]]=0,0,SUMIFS(SIP[Cost of Units Sold],SIP[Investor ID],INVESTORS_LIST[[#This Row],[INVESTOR CODE]],SIP[B/S],"S")) -> 0 | Q10: =IF(INVESTORS_LIST[[#This Row],[SIP_TOTAL CURRENT UNITS]]=0,0,INVESTORS_LIST[[#This Row],[SIP_TOTAL CURRENT UNITS]]*INVESTORS_LIST[[#This Row],[SIP_AVERAGE COST]]) -> 0 | R10: =IF(INVESTORS_LIST[[#This Row],[SIP_TOTAL UNITS SOLD]]=0,0,SUMIFS(SIP[Realized Gain],SIP[Investor ID],INVESTORS_LIST[[#This Row],[INVESTOR CODE]],SIP[B/S],"S")) -> 0 | S10: =INVESTORS_LIST[[#This Row],[LS_TOTAL UNITS BUY]]+INVESTORS_LIST[[#This Row],[SIP_TOTAL UNITS BUY]] -> 50000 | T10: =INVESTORS_LIST[[#This Row],[LS_TOTAL UNITS SOLD]]+INVESTORS_LIST[[#This Row],[SIP_TOTAL UNITS SOLD]] -> 50000 | U10: 50000 | V10: =SUMIFS(LS[BO UNIT TRANSFER],LS[Investor ID],INVESTORS_LIST[[#This Row],[INVESTOR CODE]],LS[B/S],"B") -> 0 | W10: =SUMIFS(LS[BO UNIT TRANSFER],LS[Investor ID],INVESTORS_LIST[[#This Row],[INVESTOR CODE]],LS[B/S],"S") -> 0 | X10: =SUMIFS(SIP[BO UNIT TRANSFER],SIP[Investor ID],INVESTORS_LIST[[#This Row],[INVESTOR CODE]],SIP[B/S],"S") -> 0 | Y10: =SUMIFS(SIP[BO UNIT TRANSFER],SIP[Investor ID],INVESTORS_LIST[[#This Row],[INVESTOR CODE]],SIP[B/S],"B") -> 0 | Z10: =INVESTORS_LIST[[#This Row],[BO OPENING BALANCE]]+INVESTORS_LIST[[#This Row],[LS- BO UNITS SELL]]+INVESTORS_LIST[[#This Row],[LS- BO UNITS REPURCHASE]]+INVESTORS_LIST[[#This Row],[SIP- BO UNITS REPURCHASE]]-INVESTORS_LIST[[#This Row],[SIP- BO UNITS SELL]] -> 50000 | AA10: =INVESTORS_LIST[[#This Row],[TOTAL UNITS BUY]]-INVESTORS_LIST[[#This Row],[TOTAL UNITS SOLD]] -> 0 | AB10: =INVESTORS_LIST[[#This Row],[TOTAL CURRENT UNITS]]-INVESTORS_LIST[[#This Row],[BO UNITS HOLD]] -> -50000 | AC10: =INDEX([4]!Table_1[BO ID],MATCH(INVESTORS_LIST[[#This Row],[INVESTOR CODE]],[4]!Table_1[INVESTOR CODE],0)) -> #REF! | AD10: =INVESTORS_LIST[[#This Row],[LS_TOTAL COST VALUE OF CURRENT UNITS]]+INVESTORS_LIST[[#This Row],[SIP_TOTAL COST VALUE OF CURRENT UNITS]] -> 0 | AE10: =IF(INVESTORS_LIST[[#This Row],[TOTAL CURRENT UNITS]]=0,0,INVESTORS_LIST[[#This Row],[LS_TOTAL CURRENT UNITS]]/INVESTORS_LIST[[#This Row],[TOTAL CURRENT UNITS]]) -> 0 | AF10: =IF(INVESTORS_LIST[[#This Row],[TOTAL CURRENT UNITS]]=0,0,INVESTORS_LIST[[#This Row],[SIP_TOTAL CURRENT UNITS]]/INVESTORS_LIST[[#This Row],[TOTAL CURRENT UNITS]]) -> 0 | AG10: {=IF(INVESTORS_LIST[[#This Row],[LS_TOTAL UNITS BUY]]>0,INDEX(LS[NAV at Cost (Average)],MATCH(CONCATENATE(COUNTIFS(LS[Investor ID],INVESTORS_LIST[[#This Row],[INVESTOR CODE]]),INVESTORS_LIST[[#This Row],[INVESTOR CODE]]),LS[Unique Code],0),),0)} -> 0 | AH10: {=IF(INVESTORS_LIST[[#This Row],[SIP_TOTAL UNITS BUY]]>0,INDEX(SIP[NAV at Cost (Average)],MATCH(CONCATENATE(COUNTIFS(SIP[Investor ID],INVESTORS_LIST[[#This Row],[INVESTOR CODE]]),INVESTORS_LIST[[#This Row],[INVESTOR CODE]]),SIP[Unique Code],0),),0)} -> 0 | AI10: =IF(INVESTORS_LIST[[#This Row],[TOTAL CURRENT UNITS]]=0,0,(INVESTORS_LIST[[#This Row],[LS_WEIGHT]]*INVESTORS_LIST[[#This Row],[LS_AVERAGE COST]])+(INVESTORS_LIST[[#This Row],[SIP_WEIGHT]]*INVESTORS_LIST[[#This Row],[SIP_AVERAGE COST]])) -> 0 | AJ10: =NAV_MKT -> 12.552 | AK10: =IF(INVESTORS_LIST[[#This Row],[TOTAL CURRENT UNITS]]=0,0,INVESTORS_LIST[[#This Row],[TOTAL CURRENT UNITS]]*INVESTORS_LIST[[#This Row],[NAV]]) -> 0 | AL10: =IF(INVESTORS_LIST[[#This Row],[LS_TOTAL CURRENT UNITS]]=0,0,INVESTORS_LIST[[#This Row],[LS_TOTAL CURRENT UNITS]]*INVESTORS_LIST[[#This Row],[NAV]]) -> 0 | AM10: =IF(INVESTORS_LIST[[#This Row],[SIP_TOTAL CURRENT UNITS]]=0,0,INVESTORS_LIST[[#This Row],[SIP_TOTAL CURRENT UNITS]]*INVESTORS_LIST[[#This Row],[NAV]]) -> 0 | AO10: =IF(INVESTORS_LIST[[#This Row],[TOTAL SELLABLE UNITS]]=0,0,INVESTORS_LIST[[#This Row],[TOTAL SELLABLE UNITS]]*INVESTORS_LIST[[#This Row],[NAV]]) -> 0 | AP10: =INVESTORS_LIST[[#This Row],[LS_TOTAL REALIZED GAIN]]+INVESTORS_LIST[[#This Row],[SIP_TOTAL REALIZED GAIN]] -> 1000 | AQ10: =INVESTORS_LIST[[#This Row],[TOTAL MARKET VALUE]]-INVESTORS_LIST[[#This Row],[TOTAL COST VALUE OF CURRENT INVESTMENT]] -> 0 | AR10: =SUMIFS(DivAndTax[Tax Amount],DivAndTax[Investor ID],INVESTORS_LIST[[#This Row],[INVESTOR CODE]]) -> 0 | AS10: =SUMIFS(DivAndTax[Gross Dividend],DivAndTax[Investor ID],INVESTORS_LIST[[#This Row],[INVESTOR CODE]]) -> 0 | AT10: =IFERROR(INVESTORS_LIST[[#This Row],[TOTAL CURRENT UNITS]]/SUM(INVESTORS_LIST[TOTAL CURRENT UNITS]),0) -> 0
A11: NASRIN AKHTER | B11: A00011 | C11: Dear Ms. | D11: Individual | E11: =SUMIFS(LS[Unit],LS[Investor ID],INVESTORS_LIST[[#This Row],[INVESTOR CODE]],LS[B/S],"B") -> 0 | F11: =-SUMIFS(LS[Unit],LS[Investor ID],INVESTORS_LIST[[#This Row],[INVESTOR CODE]],LS[B/S],"S") -> 0 | G11: =IF(INVESTORS_LIST[[#This Row],[LS_TOTAL UNITS BUY]]=0,0,INVESTORS_LIST[[#This Row],[LS_TOTAL UNITS BUY]]-INVESTORS_LIST[[#This Row],[LS_TOTAL UNITS SOLD]]) -> 0 | H11: =IF(INVESTORS_LIST[[#This Row],[LS_TOTAL UNITS BUY]]=0,0,SUMIFS(LS[Amount],LS[Investor ID],INVESTORS_LIST[[#This Row],[INVESTOR CODE]],LS[B/S],"B")) -> 0 | I11: =IF(INVESTORS_LIST[[#This Row],[LS_TOTAL UNITS SOLD]]=0,0,SUMIFS(LS[Cost of Units Sold],LS[Investor ID],INVESTORS_LIST[[#This Row],[INVESTOR CODE]],LS[B/S],"S")) -> 0 | J11: =IF(INVESTORS_LIST[[#This Row],[LS_TOTAL CURRENT UNITS]]=0,0,INVESTORS_LIST[[#This Row],[LS_TOTAL CURRENT UNITS]]*INVESTORS_LIST[[#This Row],[LS_AVERAGE COST]]) -> 0 | K11: =IF(INVESTORS_LIST[[#This Row],[LS_TOTAL UNITS SOLD]]=0,0,SUMIFS(LS[Realized Gain],LS[Investor ID],INVESTORS_LIST[[#This Row],[INVESTOR CODE]],LS[B/S],"S")) -> 0 | L11: =SUMIFS(SIP[Unit],SIP[Investor ID],INVESTORS_LIST[[#This Row],[INVESTOR CODE]],SIP[B/S],"B") -> 0 | M11: =-SUMIFS(SIP[Unit],SIP[Investor ID],INVESTORS_LIST[[#This Row],[INVESTOR CODE]],SIP[B/S],"S") -> 0 | N11: =IF(INVESTORS_LIST[[#This Row],[SIP_TOTAL UNITS BUY]]=0,0,INVESTORS_LIST[[#This Row],[SIP_TOTAL UNITS BUY]]-INVESTORS_LIST[[#This Row],[SIP_TOTAL UNITS SOLD]]) -> 0 | O11: =IF(INVESTORS_LIST[[#This Row],[SIP_TOTAL UNITS BUY]]=0,0,SUMIFS(SIP[Amount],SIP[Investor ID],INVESTORS_LIST[[#This Row],[INVESTOR CODE]],SIP[B/S],"B")) -> 0 | P11: =IF(INVESTORS_LIST[[#This Row],[SIP_TOTAL UNITS SOLD]]=0,0,SUMIFS(SIP[Cost of Units Sold],SIP[Investor ID],INVESTORS_LIST[[#This Row],[INVESTOR CODE]],SIP[B/S],"S")) -> 0 | Q11: =IF(INVESTORS_LIST[[#This Row],[SIP_TOTAL CURRENT UNITS]]=0,0,INVESTORS_LIST[[#This Row],[SIP_TOTAL CURRENT UNITS]]*INVESTORS_LIST[[#This Row],[SIP_AVERAGE COST]]) -> 0 | R11: =IF(INVESTORS_LIST[[#This Row],[SIP_TOTAL UNITS SOLD]]=0,0,SUMIFS(SIP[Realized Gain],SIP[Investor ID],INVESTORS_LIST[[#This Row],[INVESTOR CODE]],SIP[B/S],"S")) -> 0 | S11: =INVESTORS_LIST[[#This Row],[LS_TOTAL UNITS BUY]]+INVESTORS_LIST[[#This Row],[SIP_TOTAL UNITS BUY]] -> 0 | T11: =INVESTORS_LIST[[#This Row],[LS_TOTAL UNITS SOLD]]+INVESTORS_LIST[[#This Row],[SIP_TOTAL UNITS SOLD]] -> 0 | U11: 0 | V11: =SUMIFS(LS[BO UNIT TRANSFER],LS[Investor ID],INVESTORS_LIST[[#This Row],[INVESTOR CODE]],LS[B/S],"B") -> 0 | W11: =SUMIFS(LS[BO UNIT TRANSFER],LS[Investor ID],INVESTORS_LIST[[#This Row],[INVESTOR CODE]],LS[B/S],"S") -> 0 | X11: =SUMIFS(SIP[BO UNIT TRANSFER],SIP[Investor ID],INVESTORS_LIST[[#This Row],[INVESTOR CODE]],SIP[B/S],"S") -> 0 | Y11: =SUMIFS(SIP[BO UNIT TRANSFER],SIP[Investor ID],INVESTORS_LIST[[#This Row],[INVESTOR CODE]],SIP[B/S],"B") -> 0 | Z11: =INVESTORS_LIST[[#This Row],[BO OPENING BALANCE]]+INVESTORS_LIST[[#This Row],[LS- BO UNITS SELL]]+INVESTORS_LIST[[#This Row],[LS- BO UNITS REPURCHASE]]+INVESTORS_LIST[[#This Row],[SIP- BO UNITS REPURCHASE]]-INVESTORS_LIST[[#This Row],[SIP- BO UNITS SELL]] -> 0 | AA11: =INVESTORS_LIST[[#This Row],[TOTAL UNITS BUY]]-INVESTORS_LIST[[#This Row],[TOTAL UNITS SOLD]] -> 0 | AB11: =INVESTORS_LIST[[#This Row],[TOTAL CURRENT UNITS]]-INVESTORS_LIST[[#This Row],[BO UNITS HOLD]] -> 0 | AC11: =INDEX([4]!Table_1[BO ID],MATCH(INVESTORS_LIST[[#This Row],[INVESTOR CODE]],[4]!Table_1[INVESTOR CODE],0)) -> #REF! | AD11: =INVESTORS_LIST[[#This Row],[LS_TOTAL COST VALUE OF CURRENT UNITS]]+INVESTORS_LIST[[#This Row],[SIP_TOTAL COST VALUE OF CURRENT UNITS]] -> 0 | AE11: =IF(INVESTORS_LIST[[#This Row],[TOTAL CURRENT UNITS]]=0,0,INVESTORS_LIST[[#This Row],[LS_TOTAL CURRENT UNITS]]/INVESTORS_LIST[[#This Row],[TOTAL CURRENT UNITS]]) -> 0 | AF11: =IF(INVESTORS_LIST[[#This Row],[TOTAL CURRENT UNITS]]=0,0,INVESTORS_LIST[[#This Row],[SIP_TOTAL CURRENT UNITS]]/INVESTORS_LIST[[#This Row],[TOTAL CURRENT UNITS]]) -> 0 | AG11: {=IF(INVESTORS_LIST[[#This Row],[LS_TOTAL UNITS BUY]]>0,INDEX(LS[NAV at Cost (Average)],MATCH(CONCATENATE(COUNTIFS(LS[Investor ID],INVESTORS_LIST[[#This Row],[INVESTOR CODE]]),INVESTORS_LIST[[#This Row],[INVESTOR CODE]]),LS[Unique Code],0),),0)} -> 0 | AH11: {=IF(INVESTORS_LIST[[#This Row],[SIP_TOTAL UNITS BUY]]>0,INDEX(SIP[NAV at Cost (Average)],MATCH(CONCATENATE(COUNTIFS(SIP[Investor ID],INVESTORS_LIST[[#This Row],[INVESTOR CODE]]),INVESTORS_LIST[[#This Row],[INVESTOR CODE]]),SIP[Unique Code],0),),0)} -> 0 | AI11: =IF(INVESTORS_LIST[[#This Row],[TOTAL CURRENT UNITS]]=0,0,(INVESTORS_LIST[[#This Row],[LS_WEIGHT]]*INVESTORS_LIST[[#This Row],[LS_AVERAGE COST]])+(INVESTORS_LIST[[#This Row],[SIP_WEIGHT]]*INVESTORS_LIST[[#This Row],[SIP_AVERAGE COST]])) -> 0 | AJ11: =NAV_MKT -> 12.552 | AK11: =IF(INVESTORS_LIST[[#This Row],[TOTAL CURRENT UNITS]]=0,0,INVESTORS_LIST[[#This Row],[TOTAL CURRENT UNITS]]*INVESTORS_LIST[[#This Row],[NAV]]) -> 0 | AL11: =IF(INVESTORS_LIST[[#This Row],[LS_TOTAL CURRENT UNITS]]=0,0,INVESTORS_LIST[[#This Row],[LS_TOTAL CURRENT UNITS]]*INVESTORS_LIST[[#This Row],[NAV]]) -> 0 | AM11: =IF(INVESTORS_LIST[[#This Row],[SIP_TOTAL CURRENT UNITS]]=0,0,INVESTORS_LIST[[#This Row],[SIP_TOTAL CURRENT UNITS]]*INVESTORS_LIST[[#This Row],[NAV]]) -> 0 | AO11: =IF(INVESTORS_LIST[[#This Row],[TOTAL SELLABLE UNITS]]=0,0,INVESTORS_LIST[[#This Row],[TOTAL SELLABLE UNITS]]*INVESTORS_LIST[[#This Row],[NAV]]) -> 0 | AP11: =INVESTORS_LIST[[#This Row],[LS_TOTAL REALIZED GAIN]]+INVESTORS_LIST[[#This Row],[SIP_TOTAL REALIZED GAIN]] -> 0 | AQ11: =INVESTORS_LIST[[#This Row],[TOTAL MARKET VALUE]]-INVESTORS_LIST[[#This Row],[TOTAL COST VALUE OF CURRENT INVESTMENT]] -> 0 | AR11: =SUMIFS(DivAndTax[Tax Amount],DivAndTax[Investor ID],INVESTORS_LIST[[#This Row],[INVESTOR CODE]]) -> 0 | AS11: =SUMIFS(DivAndTax[Gross Dividend],DivAndTax[Investor ID],INVESTORS_LIST[[#This Row],[INVESTOR CODE]]) -> 0 | AT11: =IFERROR(INVESTORS_LIST[[#This Row],[TOTAL CURRENT UNITS]]/SUM(INVESTORS_LIST[TOTAL CURRENT UNITS]),0) -> 0
A12: MRINMOY GHOSH | B12: A00012 | C12: Dear Mr. | D12: Individual | E12: =SUMIFS(LS[Unit],LS[Investor ID],INVESTORS_LIST[[#This Row],[INVESTOR CODE]],LS[B/S],"B") -> 0 | F12: =-SUMIFS(LS[Unit],LS[Investor ID],INVESTORS_LIST[[#This Row],[INVESTOR CODE]],LS[B/S],"S") -> 0 | G12: =IF(INVESTORS_LIST[[#This Row],[LS_TOTAL UNITS BUY]]=0,0,INVESTORS_LIST[[#This Row],[LS_TOTAL UNITS BUY]]-INVESTORS_LIST[[#This Row],[LS_TOTAL UNITS SOLD]]) -> 0 | H12: =IF(INVESTORS_LIST[[#This Row],[LS_TOTAL UNITS BUY]]=0,0,SUMIFS(LS[Amount],LS[Investor ID],INVESTORS_LIST[[#This Row],[INVESTOR CODE]],LS[B/S],"B")) -> 0 | I12: =IF(INVESTORS_LIST[[#This Row],[LS_TOTAL UNITS SOLD]]=0,0,SUMIFS(LS[Cost of Units Sold],LS[Investor ID],INVESTORS_LIST[[#This Row],[INVESTOR CODE]],LS[B/S],"S")) -> 0 | J12: =IF(INVESTORS_LIST[[#This Row],[LS_TOTAL CURRENT UNITS]]=0,0,INVESTORS_LIST[[#This Row],[LS_TOTAL CURRENT UNITS]]*INVESTORS_LIST[[#This Row],[LS_AVERAGE COST]]) -> 0 | K12: =IF(INVESTORS_LIST[[#This Row],[LS_TOTAL UNITS SOLD]]=0,0,SUMIFS(LS[Realized Gain],LS[Investor ID],INVESTORS_LIST[[#This Row],[INVESTOR CODE]],LS[B/S],"S")) -> 0 | L12: =SUMIFS(SIP[Unit],SIP[Investor ID],INVESTORS_LIST[[#This Row],[INVESTOR CODE]],SIP[B/S],"B") -> 0 | M12: =-SUMIFS(SIP[Unit],SIP[Investor ID],INVESTORS_LIST[[#This Row],[INVESTOR CODE]],SIP[B/S],"S") -> 0 | N12: =IF(INVESTORS_LIST[[#This Row],[SIP_TOTAL UNITS BUY]]=0,0,INVESTORS_LIST[[#This Row],[SIP_TOTAL UNITS BUY]]-INVESTORS_LIST[[#This Row],[SIP_TOTAL UNITS SOLD]]) -> 0 | O12: =IF(INVESTORS_LIST[[#This Row],[SIP_TOTAL UNITS BUY]]=0,0,SUMIFS(SIP[Amount],SIP[Investor ID],INVESTORS_LIST[[#This Row],[INVESTOR CODE]],SIP[B/S],"B")) -> 0 | P12: =IF(INVESTORS_LIST[[#This Row],[SIP_TOTAL UNITS SOLD]]=0,0,SUMIFS(SIP[Cost of Units Sold],SIP[Investor ID],INVESTORS_LIST[[#This Row],[INVESTOR CODE]],SIP[B/S],"S")) -> 0 | Q12: =IF(INVESTORS_LIST[[#This Row],[SIP_TOTAL CURRENT UNITS]]=0,0,INVESTORS_LIST[[#This Row],[SIP_TOTAL CURRENT UNITS]]*INVESTORS_LIST[[#This Row],[SIP_AVERAGE COST]]) -> 0 | R12: =IF(INVESTORS_LIST[[#This Row],[SIP_TOTAL UNITS SOLD]]=0,0,SUMIFS(SIP[Realized Gain],SIP[Investor ID],INVESTORS_LIST[[#This Row],[INVESTOR CODE]],SIP[B/S],"S")) -> 0 | S12: =INVESTORS_LIST[[#This Row],[LS_TOTAL UNITS BUY]]+INVESTORS_LIST[[#This Row],[SIP_TOTAL UNITS BUY]] -> 0 | T12: =INVESTORS_LIST[[#This Row],[LS_TOTAL UNITS SOLD]]+INVESTORS_LIST[[#This Row],[SIP_TOTAL UNITS SOLD]] -> 0 | U12: 0 | V12: =SUMIFS(LS[BO UNIT TRANSFER],LS[Investor ID],INVESTORS_LIST[[#This Row],[INVESTOR CODE]],LS[B/S],"B") -> 0 | W12: =SUMIFS(LS[BO UNIT TRANSFER],LS[Investor ID],INVESTORS_LIST[[#This Row],[INVESTOR CODE]],LS[B/S],"S") -> 0 | X12: =SUMIFS(SIP[BO UNIT TRANSFER],SIP[Investor ID],INVESTORS_LIST[[#This Row],[INVESTOR CODE]],SIP[B/S],"S") -> 0 | Y12: =SUMIFS(SIP[BO UNIT TRANSFER],SIP[Investor ID],INVESTORS_LIST[[#This Row],[INVESTOR CODE]],SIP[B/S],"B") -> 0 | Z12: =INVESTORS_LIST[[#This Row],[BO OPENING BALANCE]]+INVESTORS_LIST[[#This Row],[LS- BO UNITS SELL]]+INVESTORS_LIST[[#This Row],[LS- BO UNITS REPURCHASE]]+INVESTORS_LIST[[#This Row],[SIP- BO UNITS REPURCHASE]]-INVESTORS_LIST[[#This Row],[SIP- BO UNITS SELL]] -> 0 | AA12: =INVESTORS_LIST[[#This Row],[TOTAL UNITS BUY]]-INVESTORS_LIST[[#This Row],[TOTAL UNITS SOLD]] -> 0 | AB12: =INVESTORS_LIST[[#This Row],[TOTAL CURRENT UNITS]]-INVESTORS_LIST[[#This Row],[BO UNITS HOLD]] -> 0 | AC12: =INDEX([4]!Table_1[BO ID],MATCH(INVESTORS_LIST[[#This Row],[INVESTOR CODE]],[4]!Table_1[INVESTOR CODE],0)) -> #REF! | AD12: =INVESTORS_LIST[[#This Row],[LS_TOTAL COST VALUE OF CURRENT UNITS]]+INVESTORS_LIST[[#This Row],[SIP_TOTAL COST VALUE OF CURRENT UNITS]] -> 0 | AE12: =IF(INVESTORS_LIST[[#This Row],[TOTAL CURRENT UNITS]]=0,0,INVESTORS_LIST[[#This Row],[LS_TOTAL CURRENT UNITS]]/INVESTORS_LIST[[#This Row],[TOTAL CURRENT UNITS]]) -> 0 | AF12: =IF(INVESTORS_LIST[[#This Row],[TOTAL CURRENT UNITS]]=0,0,INVESTORS_LIST[[#This Row],[SIP_TOTAL CURRENT UNITS]]/INVESTORS_LIST[[#This Row],[TOTAL CURRENT UNITS]]) -> 0 | AG12: {=IF(INVESTORS_LIST[[#This Row],[LS_TOTAL UNITS BUY]]>0,INDEX(LS[NAV at Cost (Average)],MATCH(CONCATENATE(COUNTIFS(LS[Investor ID],INVESTORS_LIST[[#This Row],[INVESTOR CODE]]),INVESTORS_LIST[[#This Row],[INVESTOR CODE]]),LS[Unique Code],0),),0)} -> 0 | AH12: {=IF(INVESTORS_LIST[[#This Row],[SIP_TOTAL UNITS BUY]]>0,INDEX(SIP[NAV at Cost (Average)],MATCH(CONCATENATE(COUNTIFS(SIP[Investor ID],INVESTORS_LIST[[#This Row],[INVESTOR CODE]]),INVESTORS_LIST[[#This Row],[INVESTOR CODE]]),SIP[Unique Code],0),),0)} -> 0 | AI12: =IF(INVESTORS_LIST[[#This Row],[TOTAL CURRENT UNITS]]=0,0,(INVESTORS_LIST[[#This Row],[LS_WEIGHT]]*INVESTORS_LIST[[#This Row],[LS_AVERAGE COST]])+(INVESTORS_LIST[[#This Row],[SIP_WEIGHT]]*INVESTORS_LIST[[#This Row],[SIP_AVERAGE COST]])) -> 0 | AJ12: =NAV_MKT -> 12.552 | AK12: =IF(INVESTORS_LIST[[#This Row],[TOTAL CURRENT UNITS]]=0,0,INVESTORS_LIST[[#This Row],[TOTAL CURRENT UNITS]]*INVESTORS_LIST[[#This Row],[NAV]]) -> 0 | AL12: =IF(INVESTORS_LIST[[#This Row],[LS_TOTAL CURRENT UNITS]]=0,0,INVESTORS_LIST[[#This Row],[LS_TOTAL CURRENT UNITS]]*INVESTORS_LIST[[#This Row],[NAV]]) -> 0 | AM12: =IF(INVESTORS_LIST[[#This Row],[SIP_TOTAL CURRENT UNITS]]=0,0,INVESTORS_LIST[[#This Row],[SIP_TOTAL CURRENT UNITS]]*INVESTORS_LIST[[#This Row],[NAV]]) -> 0 | AO12: =IF(INVESTORS_LIST[[#This Row],[TOTAL SELLABLE UNITS]]=0,0,INVESTORS_LIST[[#This Row],[TOTAL SELLABLE UNITS]]*INVESTORS_LIST[[#This Row],[NAV]]) -> 0 | AP12: =INVESTORS_LIST[[#This Row],[LS_TOTAL REALIZED GAIN]]+INVESTORS_LIST[[#This Row],[SIP_TOTAL REALIZED GAIN]] -> 0 | AQ12: =INVESTORS_LIST[[#This Row],[TOTAL MARKET VALUE]]-INVESTORS_LIST[[#This Row],[TOTAL COST VALUE OF CURRENT INVESTMENT]] -> 0 | AR12: =SUMIFS(DivAndTax[Tax Amount],DivAndTax[Investor ID],INVESTORS_LIST[[#This Row],[INVESTOR CODE]]) -> 0 | AS12: =SUMIFS(DivAndTax[Gross Dividend],DivAndTax[Investor ID],INVESTORS_LIST[[#This Row],[INVESTOR CODE]]) -> 0 | AT12: =IFERROR(INVESTORS_LIST[[#This Row],[TOTAL CURRENT UNITS]]/SUM(INVESTORS_LIST[TOTAL CURRENT UNITS]),0) -> 0
A13: MOHAMMAD NAZMUL HOSSAIN | B13: A00013 | C13: Dear Mr. | D13: Individual | E13: =SUMIFS(LS[Unit],LS[Investor ID],INVESTORS_LIST[[#This Row],[INVESTOR CODE]],LS[B/S],"B") -> 0 | F13: =-SUMIFS(LS[Unit],LS[Investor ID],INVESTORS_LIST[[#This Row],[INVESTOR CODE]],LS[B/S],"S") -> 0 | G13: =IF(INVESTORS_LIST[[#This Row],[LS_TOTAL UNITS BUY]]=0,0,INVESTORS_LIST[[#This Row],[LS_TOTAL UNITS BUY]]-INVESTORS_LIST[[#This Row],[LS_TOTAL UNITS SOLD]]) -> 0 | H13: =IF(INVESTORS_LIST[[#This Row],[LS_TOTAL UNITS BUY]]=0,0,SUMIFS(LS[Amount],LS[Investor ID],INVESTORS_LIST[[#This Row],[INVESTOR CODE]],LS[B/S],"B")) -> 0 | I13: =IF(INVESTORS_LIST[[#This Row],[LS_TOTAL UNITS SOLD]]=0,0,SUMIFS(LS[Cost of Units Sold],LS[Investor ID],INVESTORS_LIST[[#This Row],[INVESTOR CODE]],LS[B/S],"S")) -> 0 | J13: =IF(INVESTORS_LIST[[#This Row],[LS_TOTAL CURRENT UNITS]]=0,0,INVESTORS_LIST[[#This Row],[LS_TOTAL CURRENT UNITS]]*INVESTORS_LIST[[#This Row],[LS_AVERAGE COST]]) -> 0 | K13: =IF(INVESTORS_LIST[[#This Row],[LS_TOTAL UNITS SOLD]]=0,0,SUMIFS(LS[Realized Gain],LS[Investor ID],INVESTORS_LIST[[#This Row],[INVESTOR CODE]],LS[B/S],"S")) -> 0 | L13: =SUMIFS(SIP[Unit],SIP[Investor ID],INVESTORS_LIST[[#This Row],[INVESTOR CODE]],SIP[B/S],"B") -> 0 | M13: =-SUMIFS(SIP[Unit],SIP[Investor ID],INVESTORS_LIST[[#This Row],[INVESTOR CODE]],SIP[B/S],"S") -> 0 | N13: =IF(INVESTORS_LIST[[#This Row],[SIP_TOTAL UNITS BUY]]=0,0,INVESTORS_LIST[[#This Row],[SIP_TOTAL UNITS BUY]]-INVESTORS_LIST[[#This Row],[SIP_TOTAL UNITS SOLD]]) -> 0 | O13: =IF(INVESTORS_LIST[[#This Row],[SIP_TOTAL UNITS BUY]]=0,0,SUMIFS(SIP[Amount],SIP[Investor ID],INVESTORS_LIST[[#This Row],[INVESTOR CODE]],SIP[B/S],"B")) -> 0 | P13: =IF(INVESTORS_LIST[[#This Row],[SIP_TOTAL UNITS SOLD]]=0,0,SUMIFS(SIP[Cost of Units Sold],SIP[Investor ID],INVESTORS_LIST[[#This Row],[INVESTOR CODE]],SIP[B/S],"S")) -> 0 | Q13: =IF(INVESTORS_LIST[[#This Row],[SIP_TOTAL CURRENT UNITS]]=0,0,INVESTORS_LIST[[#This Row],[SIP_TOTAL CURRENT UNITS]]*INVESTORS_LIST[[#This Row],[SIP_AVERAGE COST]]) -> 0 | R13: =IF(INVESTORS_LIST[[#This Row],[SIP_TOTAL UNITS SOLD]]=0,0,SUMIFS(SIP[Realized Gain],SIP[Investor ID],INVESTORS_LIST[[#This Row],[INVESTOR CODE]],SIP[B/S],"S")) -> 0 | S13: =INVESTORS_LIST[[#This Row],[LS_TOTAL UNITS BUY]]+INVESTORS_LIST[[#This Row],[SIP_TOTAL UNITS BUY]] -> 0 | T13: =INVESTORS_LIST[[#This Row],[LS_TOTAL UNITS SOLD]]+INVESTORS_LIST[[#This Row],[SIP_TOTAL UNITS SOLD]] -> 0 | U13: 0 | V13: =SUMIFS(LS[BO UNIT TRANSFER],LS[Investor ID],INVESTORS_LIST[[#This Row],[INVESTOR CODE]],LS[B/S],"B") -> 0 | W13: =SUMIFS(LS[BO UNIT TRANSFER],LS[Investor ID],INVESTORS_LIST[[#This Row],[INVESTOR CODE]],LS[B/S],"S") -> 0 | X13: =SUMIFS(SIP[BO UNIT TRANSFER],SIP[Investor ID],INVESTORS_LIST[[#This Row],[INVESTOR CODE]],SIP[B/S],"S") -> 0 | Y13: =SUMIFS(SIP[BO UNIT TRANSFER],SIP[Investor ID],INVESTORS_LIST[[#This Row],[INVESTOR CODE]],SIP[B/S],"B") -> 0 | Z13: =INVESTORS_LIST[[#This Row],[BO OPENING BALANCE]]+INVESTORS_LIST[[#This Row],[LS- BO UNITS SELL]]+INVESTORS_LIST[[#This Row],[LS- BO UNITS REPURCHASE]]+INVESTORS_LIST[[#This Row],[SIP- BO UNITS REPURCHASE]]-INVESTORS_LIST[[#This Row],[SIP- BO UNITS SELL]] -> 0 | AA13: =INVESTORS_LIST[[#This Row],[TOTAL UNITS BUY]]-INVESTORS_LIST[[#This Row],[TOTAL UNITS SOLD]] -> 0 | AB13: =INVESTORS_LIST[[#This Row],[TOTAL CURRENT UNITS]]-INVESTORS_LIST[[#This Row],[BO UNITS HOLD]] -> 0 | AC13: =INDEX([4]!Table_1[BO ID],MATCH(INVESTORS_LIST[[#This Row],[INVESTOR CODE]],[4]!Table_1[INVESTOR CODE],0)) -> #REF! | AD13: =INVESTORS_LIST[[#This Row],[LS_TOTAL COST VALUE OF CURRENT UNITS]]+INVESTORS_LIST[[#This Row],[SIP_TOTAL COST VALUE OF CURRENT UNITS]] -> 0 | AE13: =IF(INVESTORS_LIST[[#This Row],[TOTAL CURRENT UNITS]]=0,0,INVESTORS_LIST[[#This Row],[LS_TOTAL CURRENT UNITS]]/INVESTORS_LIST[[#This Row],[TOTAL CURRENT UNITS]]) -> 0 | AF13: =IF(INVESTORS_LIST[[#This Row],[TOTAL CURRENT UNITS]]=0,0,INVESTORS_LIST[[#This Row],[SIP_TOTAL CURRENT UNITS]]/INVESTORS_LIST[[#This Row],[TOTAL CURRENT UNITS]]) -> 0 | AG13: {=IF(INVESTORS_LIST[[#This Row],[LS_TOTAL UNITS BUY]]>0,INDEX(LS[NAV at Cost (Average)],MATCH(CONCATENATE(COUNTIFS(LS[Investor ID],INVESTORS_LIST[[#This Row],[INVESTOR CODE]]),INVESTORS_LIST[[#This Row],[INVESTOR CODE]]),LS[Unique Code],0),),0)} -> 0 | AH13: {=IF(INVESTORS_LIST[[#This Row],[SIP_TOTAL UNITS BUY]]>0,INDEX(SIP[NAV at Cost (Average)],MATCH(CONCATENATE(COUNTIFS(SIP[Investor ID],INVESTORS_LIST[[#This Row],[INVESTOR CODE]]),INVESTORS_LIST[[#This Row],[INVESTOR CODE]]),SIP[Unique Code],0),),0)} -> 0 | AI13: =IF(INVESTORS_LIST[[#This Row],[TOTAL CURRENT UNITS]]=0,0,(INVESTORS_LIST[[#This Row],[LS_WEIGHT]]*INVESTORS_LIST[[#This Row],[LS_AVERAGE COST]])+(INVESTORS_LIST[[#This Row],[SIP_WEIGHT]]*INVESTORS_LIST[[#This Row],[SIP_AVERAGE COST]])) -> 0 | AJ13: =NAV_MKT -> 12.552 | AK13: =IF(INVESTORS_LIST[[#This Row],[TOTAL CURRENT UNITS]]=0,0,INVESTORS_LIST[[#This Row],[TOTAL CURRENT UNITS]]*INVESTORS_LIST[[#This Row],[NAV]]) -> 0 | AL13: =IF(INVESTORS_LIST[[#This Row],[LS_TOTAL CURRENT UNITS]]=0,0,INVESTORS_LIST[[#This Row],[LS_TOTAL CURRENT UNITS]]*INVESTORS_LIST[[#This Row],[NAV]]) -> 0 | AM13: =IF(INVESTORS_LIST[[#This Row],[SIP_TOTAL CURRENT UNITS]]=0,0,INVESTORS_LIST[[#This Row],[SIP_TOTAL CURRENT UNITS]]*INVESTORS_LIST[[#This Row],[NAV]]) -> 0 | AO13: =IF(INVESTORS_LIST[[#This Row],[TOTAL SELLABLE UNITS]]=0,0,INVESTORS_LIST[[#This Row],[TOTAL SELLABLE UNITS]]*INVESTORS_LIST[[#This Row],[NAV]]) -> 0 | AP13: =INVESTORS_LIST[[#This Row],[LS_TOTAL REALIZED GAIN]]+INVESTORS_LIST[[#This Row],[SIP_TOTAL REALIZED GAIN]] -> 0 | AQ13: =INVESTORS_LIST[[#This Row],[TOTAL MARKET VALUE]]-INVESTORS_LIST[[#This Row],[TOTAL COST VALUE OF CURRENT INVESTMENT]] -> 0 | AR13: =SUMIFS(DivAndTax[Tax Amount],DivAndTax[Investor ID],INVESTORS_LIST[[#This Row],[INVESTOR CODE]]) -> 0 | AS13: =SUMIFS(DivAndTax[Gross Dividend],DivAndTax[Investor ID],INVESTORS_LIST[[#This Row],[INVESTOR CODE]]) -> 0 | AT13: =IFERROR(INVESTORS_LIST[[#This Row],[TOTAL CURRENT UNITS]]/SUM(INVESTORS_LIST[TOTAL CURRENT UNITS]),0) -> 0
... A641: FAISAL RAHMAN | B641: A00639 | C641: Dear Mr. | D641: Individual | E641: =SUMIFS(LS[Unit],LS[Investor ID],INVESTORS_LIST[[#This Row],[INVESTOR CODE]],LS[B/S],"B") -> 0 | F641: =-SUMIFS(LS[Unit],LS[Investor ID],INVESTORS_LIST[[#This Row],[INVESTOR CODE]],LS[B/S],"S") -> 0 | G641: =IF(INVESTORS_LIST[[#This Row],[LS_TOTAL UNITS BUY]]=0,0,INVESTORS_LIST[[#This Row],[LS_TOTAL UNITS BUY]]-INVESTORS_LIST[[#This Row],[LS_TOTAL UNITS SOLD]]) -> 0 | H641: =IF(INVESTORS_LIST[[#This Row],[LS_TOTAL UNITS BUY]]=0,0,SUMIFS(LS[Amount],LS[Investor ID],INVESTORS_LIST[[#This Row],[INVESTOR CODE]],LS[B/S],"B")) -> 0 | I641: =IF(INVESTORS_LIST[[#This Row],[LS_TOTAL UNITS SOLD]]=0,0,SUMIFS(LS[Cost of Units Sold],LS[Investor ID],INVESTORS_LIST[[#This Row],[INVESTOR CODE]],LS[B/S],"S")) -> 0 | J641: =IF(INVESTORS_LIST[[#This Row],[LS_TOTAL CURRENT UNITS]]=0,0,INVESTORS_LIST[[#This Row],[LS_TOTAL CURRENT UNITS]]*INVESTORS_LIST[[#This Row],[LS_AVERAGE COST]]) -> 0 | K641: =IF(INVESTORS_LIST[[#This Row],[LS_TOTAL UNITS SOLD]]=0,0,SUMIFS(LS[Realized Gain],LS[Investor ID],INVESTORS_LIST[[#This Row],[INVESTOR CODE]],LS[B/S],"S")) -> 0 | L641: =SUMIFS(SIP[Unit],SIP[Investor ID],INVESTORS_LIST[[#This Row],[INVESTOR CODE]],SIP[B/S],"B") -> 0 | M641: =-SUMIFS(SIP[Unit],SIP[Investor ID],INVESTORS_LIST[[#This Row],[INVESTOR CODE]],SIP[B/S],"S") -> 0 | N641: =IF(INVESTORS_LIST[[#This Row],[SIP_TOTAL UNITS BUY]]=0,0,INVESTORS_LIST[[#This Row],[SIP_TOTAL UNITS BUY]]-INVESTORS_LIST[[#This Row],[SIP_TOTAL UNITS SOLD]]) -> 0 | O641: =IF(INVESTORS_LIST[[#This Row],[SIP_TOTAL UNITS BUY]]=0,0,SUMIFS(SIP[Amount],SIP[Investor ID],INVESTORS_LIST[[#This Row],[INVESTOR CODE]],SIP[B/S],"B")) -> 0 | P641: =IF(INVESTORS_LIST[[#This Row],[SIP_TOTAL UNITS SOLD]]=0,0,SUMIFS(SIP[Cost of Units Sold],SIP[Investor ID],INVESTORS_LIST[[#This Row],[INVESTOR CODE]],SIP[B/S],"S")) -> 0 | Q641: =IF(INVESTORS_LIST[[#This Row],[SIP_TOTAL CURRENT UNITS]]=0,0,INVESTORS_LIST[[#This Row],[SIP_TOTAL CURRENT UNITS]]*INVESTORS_LIST[[#This Row],[SIP_AVERAGE COST]]) -> 0 | R641: =IF(INVESTORS_LIST[[#This Row],[SIP_TOTAL UNITS SOLD]]=0,0,SUMIFS(SIP[Realized Gain],SIP[Investor ID],INVESTORS_LIST[[#This Row],[INVESTOR CODE]],SIP[B/S],"S")) -> 0 | S641: =INVESTORS_LIST[[#This Row],[LS_TOTAL UNITS BUY]]+INVESTORS_LIST[[#This Row],[SIP_TOTAL UNITS BUY]] -> 0 | T641: =INVESTORS_LIST[[#This Row],[LS_TOTAL UNITS SOLD]]+INVESTORS_LIST[[#This Row],[SIP_TOTAL UNITS SOLD]] -> 0 | U641: 0 | V641: =SUMIFS(LS[BO UNIT TRANSFER],LS[Investor ID],INVESTORS_LIST[[#This Row],[INVESTOR CODE]],LS[B/S],"B") -> 0 | W641: =SUMIFS(LS[BO UNIT TRANSFER],LS[Investor ID],INVESTORS_LIST[[#This Row],[INVESTOR CODE]],LS[B/S],"S") -> 0 | X641: =SUMIFS(SIP[BO UNIT TRANSFER],SIP[Investor ID],INVESTORS_LIST[[#This Row],[INVESTOR CODE]],SIP[B/S],"S") -> 0 | Y641: =SUMIFS(SIP[BO UNIT TRANSFER],SIP[Investor ID],INVESTORS_LIST[[#This Row],[INVESTOR CODE]],SIP[B/S],"B") -> 0 | Z641: =INVESTORS_LIST[[#This Row],[BO OPENING BALANCE]]+INVESTORS_LIST[[#This Row],[LS- BO UNITS SELL]]+INVESTORS_LIST[[#This Row],[LS- BO UNITS REPURCHASE]]+INVESTORS_LIST[[#This Row],[SIP- BO UNITS REPURCHASE]]-INVESTORS_LIST[[#This Row],[SIP- BO UNITS SELL]] -> 0 | AA641: =INVESTORS_LIST[[#This Row],[TOTAL UNITS BUY]]-INVESTORS_LIST[[#This Row],[TOTAL UNITS SOLD]] -> 0 | AB641: =INVESTORS_LIST[[#This Row],[TOTAL CURRENT UNITS]]-INVESTORS_LIST[[#This Row],[BO UNITS HOLD]] -> 0 | AC641: =INDEX([4]!Table_1[BO ID],MATCH(INVESTORS_LIST[[#This Row],[INVESTOR CODE]],[4]!Table_1[INVESTOR CODE],0)) -> #REF! | AD641: =INVESTORS_LIST[[#This Row],[LS_TOTAL COST VALUE OF CURRENT UNITS]]+INVESTORS_LIST[[#This Row],[SIP_TOTAL COST VALUE OF CURRENT UNITS]] -> 0 | AE641: =IF(INVESTORS_LIST[[#This Row],[TOTAL CURRENT UNITS]]=0,0,INVESTORS_LIST[[#This Row],[LS_TOTAL CURRENT UNITS]]/INVESTORS_LIST[[#This Row],[TOTAL CURRENT UNITS]]) -> 0 | AF641: =IF(INVESTORS_LIST[[#This Row],[TOTAL CURRENT UNITS]]=0,0,INVESTORS_LIST[[#This Row],[SIP_TOTAL CURRENT UNITS]]/INVESTORS_LIST[[#This Row],[TOTAL CURRENT UNITS]]) -> 0 | AG641: {=IF(INVESTORS_LIST[[#This Row],[LS_TOTAL UNITS BUY]]>0,INDEX(LS[NAV at Cost (Average)],MATCH(CONCATENATE(COUNTIFS(LS[Investor ID],INVESTORS_LIST[[#This Row],[INVESTOR CODE]]),INVESTORS_LIST[[#This Row],[INVESTOR CODE]]),LS[Unique Code],0),),0)} -> 0 | AH641: {=IF(INVESTORS_LIST[[#This Row],[SIP_TOTAL UNITS BUY]]>0,INDEX(SIP[NAV at Cost (Average)],MATCH(CONCATENATE(COUNTIFS(SIP[Investor ID],INVESTORS_LIST[[#This Row],[INVESTOR CODE]]),INVESTORS_LIST[[#This Row],[INVESTOR CODE]]),SIP[Unique Code],0),),0)} -> 0 | AI641: =IF(INVESTORS_LIST[[#This Row],[TOTAL CURRENT UNITS]]=0,0,(INVESTORS_LIST[[#This Row],[LS_WEIGHT]]*INVESTORS_LIST[[#This Row],[LS_AVERAGE COST]])+(INVESTORS_LIST[[#This Row],[SIP_WEIGHT]]*INVESTORS_LIST[[#This Row],[SIP_AVERAGE COST]])) -> 0 | AJ641: =NAV_MKT -> 12.552 | AK641: =IF(INVESTORS_LIST[[#This Row],[TOTAL CURRENT UNITS]]=0,0,INVESTORS_LIST[[#This Row],[TOTAL CURRENT UNITS]]*INVESTORS_LIST[[#This Row],[NAV]]) -> 0 | AL641: =IF(INVESTORS_LIST[[#This Row],[LS_TOTAL CURRENT UNITS]]=0,0,INVESTORS_LIST[[#This Row],[LS_TOTAL CURRENT UNITS]]*INVESTORS_LIST[[#This Row],[NAV]]) -> 0 | AM641: =IF(INVESTORS_LIST[[#This Row],[SIP_TOTAL CURRENT UNITS]]=0,0,INVESTORS_LIST[[#This Row],[SIP_TOTAL CURRENT UNITS]]*INVESTORS_LIST[[#This Row],[NAV]]) -> 0 | AO641: =IF(INVESTORS_LIST[[#This Row],[TOTAL SELLABLE UNITS]]=0,0,INVESTORS_LIST[[#This Row],[TOTAL SELLABLE UNITS]]*INVESTORS_LIST[[#This Row],[NAV]]) -> 0 | AP641: =INVESTORS_LIST[[#This Row],[LS_TOTAL REALIZED GAIN]]+INVESTORS_LIST[[#This Row],[SIP_TOTAL REALIZED GAIN]] -> 0 | AQ641: =INVESTORS_LIST[[#This Row],[TOTAL MARKET VALUE]]-INVESTORS_LIST[[#This Row],[TOTAL COST VALUE OF CURRENT INVESTMENT]] -> 0 | AR641: =SUMIFS(DivAndTax[Tax Amount],DivAndTax[Investor ID],INVESTORS_LIST[[#This Row],[INVESTOR CODE]]) -> 0 | AS641: =SUMIFS(DivAndTax[Gross Dividend],DivAndTax[Investor ID],INVESTORS_LIST[[#This Row],[INVESTOR CODE]]) -> 0 | AT641: =IFERROR(INVESTORS_LIST[[#This Row],[TOTAL CURRENT UNITS]]/SUM(INVESTORS_LIST[TOTAL CURRENT UNITS]),0) -> 0
B642: A00640 | E642: =SUMIFS(LS[Unit],LS[Investor ID],INVESTORS_LIST[[#This Row],[INVESTOR CODE]],LS[B/S],"B") -> 0 | F642: =-SUMIFS(LS[Unit],LS[Investor ID],INVESTORS_LIST[[#This Row],[INVESTOR CODE]],LS[B/S],"S") -> 0 | G642: =IF(INVESTORS_LIST[[#This Row],[LS_TOTAL UNITS BUY]]=0,0,INVESTORS_LIST[[#This Row],[LS_TOTAL UNITS BUY]]-INVESTORS_LIST[[#This Row],[LS_TOTAL UNITS SOLD]]) -> 0 | H642: =IF(INVESTORS_LIST[[#This Row],[LS_TOTAL UNITS BUY]]=0,0,SUMIFS(LS[Amount],LS[Investor ID],INVESTORS_LIST[[#This Row],[INVESTOR CODE]],LS[B/S],"B")) -> 0 | I642: =IF(INVESTORS_LIST[[#This Row],[LS_TOTAL UNITS SOLD]]=0,0,SUMIFS(LS[Cost of Units Sold],LS[Investor ID],INVESTORS_LIST[[#This Row],[INVESTOR CODE]],LS[B/S],"S")) -> 0 | J642: =IF(INVESTORS_LIST[[#This Row],[LS_TOTAL CURRENT UNITS]]=0,0,INVESTORS_LIST[[#This Row],[LS_TOTAL CURRENT UNITS]]*INVESTORS_LIST[[#This Row],[LS_AVERAGE COST]]) -> 0 | K642: =IF(INVESTORS_LIST[[#This Row],[LS_TOTAL UNITS SOLD]]=0,0,SUMIFS(LS[Realized Gain],LS[Investor ID],INVESTORS_LIST[[#This Row],[INVESTOR CODE]],LS[B/S],"S")) -> 0 | L642: =SUMIFS(SIP[Unit],SIP[Investor ID],INVESTORS_LIST[[#This Row],[INVESTOR CODE]],SIP[B/S],"B") -> 0 | M642: =-SUMIFS(SIP[Unit],SIP[Investor ID],INVESTORS_LIST[[#This Row],[INVESTOR CODE]],SIP[B/S],"S") -> 0 | N642: =IF(INVESTORS_LIST[[#This Row],[SIP_TOTAL UNITS BUY]]=0,0,INVESTORS_LIST[[#This Row],[SIP_TOTAL UNITS BUY]]-INVESTORS_LIST[[#This Row],[SIP_TOTAL UNITS SOLD]]) -> 0 | O642: =IF(INVESTORS_LIST[[#This Row],[SIP_TOTAL UNITS BUY]]=0,0,SUMIFS(SIP[Amount],SIP[Investor ID],INVESTORS_LIST[[#This Row],[INVESTOR CODE]],SIP[B/S],"B")) -> 0 | P642: =IF(INVESTORS_LIST[[#This Row],[SIP_TOTAL UNITS SOLD]]=0,0,SUMIFS(SIP[Cost of Units Sold],SIP[Investor ID],INVESTORS_LIST[[#This Row],[INVESTOR CODE]],SIP[B/S],"S")) -> 0 | Q642: =IF(INVESTORS_LIST[[#This Row],[SIP_TOTAL CURRENT UNITS]]=0,0,INVESTORS_LIST[[#This Row],[SIP_TOTAL CURRENT UNITS]]*INVESTORS_LIST[[#This Row],[SIP_AVERAGE COST]]) -> 0 | R642: =IF(INVESTORS_LIST[[#This Row],[SIP_TOTAL UNITS SOLD]]=0,0,SUMIFS(SIP[Realized Gain],SIP[Investor ID],INVESTORS_LIST[[#This Row],[INVESTOR CODE]],SIP[B/S],"S")) -> 0 | S642: =INVESTORS_LIST[[#This Row],[LS_TOTAL UNITS BUY]]+INVESTORS_LIST[[#This Row],[SIP_TOTAL UNITS BUY]] -> 0 | T642: =INVESTORS_LIST[[#This Row],[LS_TOTAL UNITS SOLD]]+INVESTORS_LIST[[#This Row],[SIP_TOTAL UNITS SOLD]] -> 0 | U642: 0 | V642: =SUMIFS(LS[BO UNIT TRANSFER],LS[Investor ID],INVESTORS_LIST[[#This Row],[INVESTOR CODE]],LS[B/S],"B") -> 0 | W642: =SUMIFS(LS[BO UNIT TRANSFER],LS[Investor ID],INVESTORS_LIST[[#This Row],[INVESTOR CODE]],LS[B/S],"S") -> 0 | X642: =SUMIFS(SIP[BO UNIT TRANSFER],SIP[Investor ID],INVESTORS_LIST[[#This Row],[INVESTOR CODE]],SIP[B/S],"S") -> 0 | Y642: =SUMIFS(SIP[BO UNIT TRANSFER],SIP[Investor ID],INVESTORS_LIST[[#This Row],[INVESTOR CODE]],SIP[B/S],"B") -> 0 | Z642: =INVESTORS_LIST[[#This Row],[BO OPENING BALANCE]]+INVESTORS_LIST[[#This Row],[LS- BO UNITS SELL]]+INVESTORS_LIST[[#This Row],[LS- BO UNITS REPURCHASE]]+INVESTORS_LIST[[#This Row],[SIP- BO UNITS REPURCHASE]]-INVESTORS_LIST[[#This Row],[SIP- BO UNITS SELL]] -> 0 | AA642: =INVESTORS_LIST[[#This Row],[TOTAL UNITS BUY]]-INVESTORS_LIST[[#This Row],[TOTAL UNITS SOLD]] -> 0 | AB642: =INVESTORS_LIST[[#This Row],[TOTAL CURRENT UNITS]]-INVESTORS_LIST[[#This Row],[BO UNITS HOLD]] -> 0 | AC642: =INDEX([4]!Table_1[BO ID],MATCH(INVESTORS_LIST[[#This Row],[INVESTOR CODE]],[4]!Table_1[INVESTOR CODE],0)) -> #REF! | AD642: =INVESTORS_LIST[[#This Row],[LS_TOTAL COST VALUE OF CURRENT UNITS]]+INVESTORS_LIST[[#This Row],[SIP_TOTAL COST VALUE OF CURRENT UNITS]] -> 0 | AE642: =IF(INVESTORS_LIST[[#This Row],[TOTAL CURRENT UNITS]]=0,0,INVESTORS_LIST[[#This Row],[LS_TOTAL CURRENT UNITS]]/INVESTORS_LIST[[#This Row],[TOTAL CURRENT UNITS]]) -> 0 | AF642: =IF(INVESTORS_LIST[[#This Row],[TOTAL CURRENT UNITS]]=0,0,INVESTORS_LIST[[#This Row],[SIP_TOTAL CURRENT UNITS]]/INVESTORS_LIST[[#This Row],[TOTAL CURRENT UNITS]]) -> 0 | AG642: {=IF(INVESTORS_LIST[[#This Row],[LS_TOTAL UNITS BUY]]>0,INDEX(LS[NAV at Cost (Average)],MATCH(CONCATENATE(COUNTIFS(LS[Investor ID],INVESTORS_LIST[[#This Row],[INVESTOR CODE]]),INVESTORS_LIST[[#This Row],[INVESTOR CODE]]),LS[Unique Code],0),),0)} -> 0 | AH642: {=IF(INVESTORS_LIST[[#This Row],[SIP_TOTAL UNITS BUY]]>0,INDEX(SIP[NAV at Cost (Average)],MATCH(CONCATENATE(COUNTIFS(SIP[Investor ID],INVESTORS_LIST[[#This Row],[INVESTOR CODE]]),INVESTORS_LIST[[#This Row],[INVESTOR CODE]]),SIP[Unique Code],0),),0)} -> 0 | AI642: =IF(INVESTORS_LIST[[#This Row],[TOTAL CURRENT UNITS]]=0,0,(INVESTORS_LIST[[#This Row],[LS_WEIGHT]]*INVESTORS_LIST[[#This Row],[LS_AVERAGE COST]])+(INVESTORS_LIST[[#This Row],[SIP_WEIGHT]]*INVESTORS_LIST[[#This Row],[SIP_AVERAGE COST]])) -> 0 | AJ642: =NAV_MKT -> 12.552 | AK642: =IF(INVESTORS_LIST[[#This Row],[TOTAL CURRENT UNITS]]=0,0,INVESTORS_LIST[[#This Row],[TOTAL CURRENT UNITS]]*INVESTORS_LIST[[#This Row],[NAV]]) -> 0 | AL642: =IF(INVESTORS_LIST[[#This Row],[LS_TOTAL CURRENT UNITS]]=0,0,INVESTORS_LIST[[#This Row],[LS_TOTAL CURRENT UNITS]]*INVESTORS_LIST[[#This Row],[NAV]]) -> 0 | AM642: =IF(INVESTORS_LIST[[#This Row],[SIP_TOTAL CURRENT UNITS]]=0,0,INVESTORS_LIST[[#This Row],[SIP_TOTAL CURRENT UNITS]]*INVESTORS_LIST[[#This Row],[NAV]]) -> 0 | AO642: =IF(INVESTORS_LIST[[#This Row],[TOTAL SELLABLE UNITS]]=0,0,INVESTORS_LIST[[#This Row],[TOTAL SELLABLE UNITS]]*INVESTORS_LIST[[#This Row],[NAV]]) -> 0 | AP642: =INVESTORS_LIST[[#This Row],[LS_TOTAL REALIZED GAIN]]+INVESTORS_LIST[[#This Row],[SIP_TOTAL REALIZED GAIN]] -> 0 | AQ642: =INVESTORS_LIST[[#This Row],[TOTAL MARKET VALUE]]-INVESTORS_LIST[[#This Row],[TOTAL COST VALUE OF CURRENT INVESTMENT]] -> 0 | AR642: =SUMIFS(DivAndTax[Tax Amount],DivAndTax[Investor ID],INVESTORS_LIST[[#This Row],[INVESTOR CODE]]) -> 0 | AS642: =SUMIFS(DivAndTax[Gross Dividend],DivAndTax[Investor ID],INVESTORS_LIST[[#This Row],[INVESTOR CODE]]) -> 0 | AT642: =IFERROR(INVESTORS_LIST[[#This Row],[TOTAL CURRENT UNITS]]/SUM(INVESTORS_LIST[TOTAL CURRENT UNITS]),0) -> 0
A643: MD. KAMRUL HASAN | B643: A00641 | C643: Dear Mr. | D643: Individual | E643: =SUMIFS(LS[Unit],LS[Investor ID],INVESTORS_LIST[[#This Row],[INVESTOR CODE]],LS[B/S],"B") -> 13830 | F643: =-SUMIFS(LS[Unit],LS[Investor ID],INVESTORS_LIST[[#This Row],[INVESTOR CODE]],LS[B/S],"S") -> 13830 | G643: =IF(INVESTORS_LIST[[#This Row],[LS_TOTAL UNITS BUY]]=0,0,INVESTORS_LIST[[#This Row],[LS_TOTAL UNITS BUY]]-INVESTORS_LIST[[#This Row],[LS_TOTAL UNITS SOLD]]) -> 0 | H643: =IF(INVESTORS_LIST[[#This Row],[LS_TOTAL UNITS BUY]]=0,0,SUMIFS(LS[Amount],LS[Investor ID],INVESTORS_LIST[[#This Row],[INVESTOR CODE]],LS[B/S],"B")) -> 150000 | I643: =IF(INVESTORS_LIST[[#This Row],[LS_TOTAL UNITS SOLD]]=0,0,SUMIFS(LS[Cost of Units Sold],LS[Investor ID],INVESTORS_LIST[[#This Row],[INVESTOR CODE]],LS[B/S],"S")) -> 150000 | J643: =IF(INVESTORS_LIST[[#This Row],[LS_TOTAL CURRENT UNITS]]=0,0,INVESTORS_LIST[[#This Row],[LS_TOTAL CURRENT UNITS]]*INVESTORS_LIST[[#This Row],[LS_AVERAGE COST]]) -> 0 | K643: =IF(INVESTORS_LIST[[#This Row],[LS_TOTAL UNITS SOLD]]=0,0,SUMIFS(LS[Realized Gain],LS[Investor ID],INVESTORS_LIST[[#This Row],[INVESTOR CODE]],LS[B/S],"S")) -> 20662.2 | L643: =SUMIFS(SIP[Unit],SIP[Investor ID],INVESTORS_LIST[[#This Row],[INVESTOR CODE]],SIP[B/S],"B") -> 0 | M643: =-SUMIFS(SIP[Unit],SIP[Investor ID],INVESTORS_LIST[[#This Row],[INVESTOR CODE]],SIP[B/S],"S") -> 0 | N643: =IF(INVESTORS_LIST[[#This Row],[SIP_TOTAL UNITS BUY]]=0,0,INVESTORS_LIST[[#This Row],[SIP_TOTAL UNITS BUY]]-INVESTORS_LIST[[#This Row],[SIP_TOTAL UNITS SOLD]]) -> 0 | O643: =IF(INVESTORS_LIST[[#This Row],[SIP_TOTAL UNITS BUY]]=0,0,SUMIFS(SIP[Amount],SIP[Investor ID],INVESTORS_LIST[[#This Row],[INVESTOR CODE]],SIP[B/S],"B")) -> 0 | P643: =IF(INVESTORS_LIST[[#This Row],[SIP_TOTAL UNITS SOLD]]=0,0,SUMIFS(SIP[Cost of Units Sold],SIP[Investor ID],INVESTORS_LIST[[#This Row],[INVESTOR CODE]],SIP[B/S],"S")) -> 0 | Q643: =IF(INVESTORS_LIST[[#This Row],[SIP_TOTAL CURRENT UNITS]]=0,0,INVESTORS_LIST[[#This Row],[SIP_TOTAL CURRENT UNITS]]*INVESTORS_LIST[[#This Row],[SIP_AVERAGE COST]]) -> 0 | R643: =IF(INVESTORS_LIST[[#This Row],[SIP_TOTAL UNITS SOLD]]=0,0,SUMIFS(SIP[Realized Gain],SIP[Investor ID],INVESTORS_LIST[[#This Row],[INVESTOR CODE]],SIP[B/S],"S")) -> 0 | S643: =INVESTORS_LIST[[#This Row],[LS_TOTAL UNITS BUY]]+INVESTORS_LIST[[#This Row],[SIP_TOTAL UNITS BUY]] -> 13830 | T643: =INVESTORS_LIST[[#This Row],[LS_TOTAL UNITS SOLD]]+INVESTORS_LIST[[#This Row],[SIP_TOTAL UNITS SOLD]] -> 13830 | U643: 0 | V643: =SUMIFS(LS[BO UNIT TRANSFER],LS[Investor ID],INVESTORS_LIST[[#This Row],[INVESTOR CODE]],LS[B/S],"B") -> 0 | W643: =SUMIFS(LS[BO UNIT TRANSFER],LS[Investor ID],INVESTORS_LIST[[#This Row],[INVESTOR CODE]],LS[B/S],"S") -> 0 | X643: =SUMIFS(SIP[BO UNIT TRANSFER],SIP[Investor ID],INVESTORS_LIST[[#This Row],[INVESTOR CODE]],SIP[B/S],"S") -> 0 | Y643: =SUMIFS(SIP[BO UNIT TRANSFER],SIP[Investor ID],INVESTORS_LIST[[#This Row],[INVESTOR CODE]],SIP[B/S],"B") -> 0 | Z643: =INVESTORS_LIST[[#This Row],[BO OPENING BALANCE]]+INVESTORS_LIST[[#This Row],[LS- BO UNITS SELL]]+INVESTORS_LIST[[#This Row],[LS- BO UNITS REPURCHASE]]+INVESTORS_LIST[[#This Row],[SIP- BO UNITS REPURCHASE]]-INVESTORS_LIST[[#This Row],[SIP- BO UNITS SELL]] -> 0 | AA643: =INVESTORS_LIST[[#This Row],[TOTAL UNITS BUY]]-INVESTORS_LIST[[#This Row],[TOTAL UNITS SOLD]] -> 0 | AB643: =INVESTORS_LIST[[#This Row],[TOTAL CURRENT UNITS]]-INVESTORS_LIST[[#This Row],[BO UNITS HOLD]] -> 0 | AC643: =INDEX([4]!Table_1[BO ID],MATCH(INVESTORS_LIST[[#This Row],[INVESTOR CODE]],[4]!Table_1[INVESTOR CODE],0)) -> #REF! | AD643: =INVESTORS_LIST[[#This Row],[LS_TOTAL COST VALUE OF CURRENT UNITS]]+INVESTORS_LIST[[#This Row],[SIP_TOTAL COST VALUE OF CURRENT UNITS]] -> 0 | AE643: =IF(INVESTORS_LIST[[#This Row],[TOTAL CURRENT UNITS]]=0,0,INVESTORS_LIST[[#This Row],[LS_TOTAL CURRENT UNITS]]/INVESTORS_LIST[[#This Row],[TOTAL CURRENT UNITS]]) -> 0 | AF643: =IF(INVESTORS_LIST[[#This Row],[TOTAL CURRENT UNITS]]=0,0,INVESTORS_LIST[[#This Row],[SIP_TOTAL CURRENT UNITS]]/INVESTORS_LIST[[#This Row],[TOTAL CURRENT UNITS]]) -> 0 | AG643: {=IF(INVESTORS_LIST[[#This Row],[LS_TOTAL UNITS BUY]]>0,INDEX(LS[NAV at Cost (Average)],MATCH(CONCATENATE(COUNTIFS(LS[Investor ID],INVESTORS_LIST[[#This Row],[INVESTOR CODE]]),INVESTORS_LIST[[#This Row],[INVESTOR CODE]]),LS[Unique Code],0),),0)} -> 0 | AH643: {=IF(INVESTORS_LIST[[#This Row],[SIP_TOTAL UNITS BUY]]>0,INDEX(SIP[NAV at Cost (Average)],MATCH(CONCATENATE(COUNTIFS(SIP[Investor ID],INVESTORS_LIST[[#This Row],[INVESTOR CODE]]),INVESTORS_LIST[[#This Row],[INVESTOR CODE]]),SIP[Unique Code],0),),0)} -> 0 | AI643: =IF(INVESTORS_LIST[[#This Row],[TOTAL CURRENT UNITS]]=0,0,(INVESTORS_LIST[[#This Row],[LS_WEIGHT]]*INVESTORS_LIST[[#This Row],[LS_AVERAGE COST]])+(INVESTORS_LIST[[#This Row],[SIP_WEIGHT]]*INVESTORS_LIST[[#This Row],[SIP_AVERAGE COST]])) -> 0 | AJ643: =NAV_MKT -> 12.552 | AK643: =IF(INVESTORS_LIST[[#This Row],[TOTAL CURRENT UNITS]]=0,0,INVESTORS_LIST[[#This Row],[TOTAL CURRENT UNITS]]*INVESTORS_LIST[[#This Row],[NAV]]) -> 0 | AL643: =IF(INVESTORS_LIST[[#This Row],[LS_TOTAL CURRENT UNITS]]=0,0,INVESTORS_LIST[[#This Row],[LS_TOTAL CURRENT UNITS]]*INVESTORS_LIST[[#This Row],[NAV]]) -> 0 | AM643: =IF(INVESTORS_LIST[[#This Row],[SIP_TOTAL CURRENT UNITS]]=0,0,INVESTORS_LIST[[#This Row],[SIP_TOTAL CURRENT UNITS]]*INVESTORS_LIST[[#This Row],[NAV]]) -> 0 | AO643: =IF(INVESTORS_LIST[[#This Row],[TOTAL SELLABLE UNITS]]=0,0,INVESTORS_LIST[[#This Row],[TOTAL SELLABLE UNITS]]*INVESTORS_LIST[[#This Row],[NAV]]) -> 0 | AP643: =INVESTORS_LIST[[#This Row],[LS_TOTAL REALIZED GAIN]]+INVESTORS_LIST[[#This Row],[SIP_TOTAL REALIZED GAIN]] -> 20662.2 | AQ643: =INVESTORS_LIST[[#This Row],[TOTAL MARKET VALUE]]-INVESTORS_LIST[[#This Row],[TOTAL COST VALUE OF CURRENT INVESTMENT]] -> 0 | AR643: =SUMIFS(DivAndTax[Tax Amount],DivAndTax[Investor ID],INVESTORS_LIST[[#This Row],[INVESTOR CODE]]) -> 0 | AS643: =SUMIFS(DivAndTax[Gross Dividend],DivAndTax[Investor ID],INVESTORS_LIST[[#This Row],[INVESTOR CODE]]) -> 0 | AT643: =IFERROR(INVESTORS_LIST[[#This Row],[TOTAL CURRENT UNITS]]/SUM(INVESTORS_LIST[TOTAL CURRENT UNITS]),0) -> 0
A644: PUJA GHOSH | B644: A00642 | C644: Dear Ms. | D644: Individual | E644: =SUMIFS(LS[Unit],LS[Investor ID],INVESTORS_LIST[[#This Row],[INVESTOR CODE]],LS[B/S],"B") -> 32670 | F644: =-SUMIFS(LS[Unit],LS[Investor ID],INVESTORS_LIST[[#This Row],[INVESTOR CODE]],LS[B/S],"S") -> 25013 | G644: =IF(INVESTORS_LIST[[#This Row],[LS_TOTAL UNITS BUY]]=0,0,INVESTORS_LIST[[#This Row],[LS_TOTAL UNITS BUY]]-INVESTORS_LIST[[#This Row],[LS_TOTAL UNITS SOLD]]) -> 7657 | H644: =IF(INVESTORS_LIST[[#This Row],[LS_TOTAL UNITS BUY]]=0,0,SUMIFS(LS[Amount],LS[Investor ID],INVESTORS_LIST[[#This Row],[INVESTOR CODE]],LS[B/S],"B")) -> 376110.65 | I644: =IF(INVESTORS_LIST[[#This Row],[LS_TOTAL UNITS SOLD]]=0,0,SUMIFS(LS[Cost of Units Sold],LS[Investor ID],INVESTORS_LIST[[#This Row],[INVESTOR CODE]],LS[B/S],"S")) -> 285000 | J644: =IF(INVESTORS_LIST[[#This Row],[LS_TOTAL CURRENT UNITS]]=0,0,INVESTORS_LIST[[#This Row],[LS_TOTAL CURRENT UNITS]]*INVESTORS_LIST[[#This Row],[LS_AVERAGE COST]]) -> 91110.65 | K644: =IF(INVESTORS_LIST[[#This Row],[LS_TOTAL UNITS SOLD]]=0,0,SUMIFS(LS[Realized Gain],LS[Investor ID],INVESTORS_LIST[[#This Row],[INVESTOR CODE]],LS[B/S],"S")) -> 11629.17 | L644: =SUMIFS(SIP[Unit],SIP[Investor ID],INVESTORS_LIST[[#This Row],[INVESTOR CODE]],SIP[B/S],"B") -> 0 | M644: =-SUMIFS(SIP[Unit],SIP[Investor ID],INVESTORS_LIST[[#This Row],[INVESTOR CODE]],SIP[B/S],"S") -> 0 | N644: =IF(INVESTORS_LIST[[#This Row],[SIP_TOTAL UNITS BUY]]=0,0,INVESTORS_LIST[[#This Row],[SIP_TOTAL UNITS BUY]]-INVESTORS_LIST[[#This Row],[SIP_TOTAL UNITS SOLD]]) -> 0 | O644: =IF(INVESTORS_LIST[[#This Row],[SIP_TOTAL UNITS BUY]]=0,0,SUMIFS(SIP[Amount],SIP[Investor ID],INVESTORS_LIST[[#This Row],[INVESTOR CODE]],SIP[B/S],"B")) -> 0 | P644: =IF(INVESTORS_LIST[[#This Row],[SIP_TOTAL UNITS SOLD]]=0,0,SUMIFS(SIP[Cost of Units Sold],SIP[Investor ID],INVESTORS_LIST[[#This Row],[INVESTOR CODE]],SIP[B/S],"S")) -> 0 | Q644: =IF(INVESTORS_LIST[[#This Row],[SIP_TOTAL CURRENT UNITS]]=0,0,INVESTORS_LIST[[#This Row],[SIP_TOTAL CURRENT UNITS]]*INVESTORS_LIST[[#This Row],[SIP_AVERAGE COST]]) -> 0 | R644: =IF(INVESTORS_LIST[[#This Row],[SIP_TOTAL UNITS SOLD]]=0,0,SUMIFS(SIP[Realized Gain],SIP[Investor ID],INVESTORS_LIST[[#This Row],[INVESTOR CODE]],SIP[B/S],"S")) -> 0 | S644: =INVESTORS_LIST[[#This Row],[LS_TOTAL UNITS BUY]]+INVESTORS_LIST[[#This Row],[SIP_TOTAL UNITS BUY]] -> 32670 | T644: =INVESTORS_LIST[[#This Row],[LS_TOTAL UNITS SOLD]]+INVESTORS_LIST[[#This Row],[SIP_TOTAL UNITS SOLD]] -> 25013 | U644: 0 | V644: =SUMIFS(LS[BO UNIT TRANSFER],LS[Investor ID],INVESTORS_LIST[[#This Row],[INVESTOR CODE]],LS[B/S],"B") -> 0 | W644: =SUMIFS(LS[BO UNIT TRANSFER],LS[Investor ID],INVESTORS_LIST[[#This Row],[INVESTOR CODE]],LS[B/S],"S") -> 0 | X644: =SUMIFS(SIP[BO UNIT TRANSFER],SIP[Investor ID],INVESTORS_LIST[[#This Row],[INVESTOR CODE]],SIP[B/S],"S") -> 0 | Y644: =SUMIFS(SIP[BO UNIT TRANSFER],SIP[Investor ID],INVESTORS_LIST[[#This Row],[INVESTOR CODE]],SIP[B/S],"B") -> 0 | Z644: =INVESTORS_LIST[[#This Row],[BO OPENING BALANCE]]+INVESTORS_LIST[[#This Row],[LS- BO UNITS SELL]]+INVESTORS_LIST[[#This Row],[LS- BO UNITS REPURCHASE]]+INVESTORS_LIST[[#This Row],[SIP- BO UNITS REPURCHASE]]-INVESTORS_LIST[[#This Row],[SIP- BO UNITS SELL]] -> 0 | AA644: =INVESTORS_LIST[[#This Row],[TOTAL UNITS BUY]]-INVESTORS_LIST[[#This Row],[TOTAL UNITS SOLD]] -> 7657 | AB644: =INVESTORS_LIST[[#This Row],[TOTAL CURRENT UNITS]]-INVESTORS_LIST[[#This Row],[BO UNITS HOLD]] -> 7657 | AC644: =INDEX([4]!Table_1[BO ID],MATCH(INVESTORS_LIST[[#This Row],[INVESTOR CODE]],[4]!Table_1[INVESTOR CODE],0)) -> #REF! | AD644: =INVESTORS_LIST[[#This Row],[LS_TOTAL COST VALUE OF CURRENT UNITS]]+INVESTORS_LIST[[#This Row],[SIP_TOTAL COST VALUE OF CURRENT UNITS]] -> 91110.65 | AE644: =IF(INVESTORS_LIST[[#This Row],[TOTAL CURRENT UNITS]]=0,0,INVESTORS_LIST[[#This Row],[LS_TOTAL CURRENT UNITS]]/INVESTORS_LIST[[#This Row],[TOTAL CURRENT UNITS]]) -> 1 | AF644: =IF(INVESTORS_LIST[[#This Row],[TOTAL CURRENT UNITS]]=0,0,INVESTORS_LIST[[#This Row],[SIP_TOTAL CURRENT UNITS]]/INVESTORS_LIST[[#This Row],[TOTAL CURRENT UNITS]]) -> 0 | AG644: {=IF(INVESTORS_LIST[[#This Row],[LS_TOTAL UNITS BUY]]>0,INDEX(LS[NAV at Cost (Average)],MATCH(CONCATENATE(COUNTIFS(LS[Investor ID],INVESTORS_LIST[[#This Row],[INVESTOR CODE]]),INVESTORS_LIST[[#This Row],[INVESTOR CODE]]),LS[Unique Code],0),),0)} -> 11.899001 | AH644: {=IF(INVESTORS_LIST[[#This Row],[SIP_TOTAL UNITS BUY]]>0,INDEX(SIP[NAV at Cost (Average)],MATCH(CONCATENATE(COUNTIFS(SIP[Investor ID],INVESTORS_LIST[[#This Row],[INVESTOR CODE]]),INVESTORS_LIST[[#This Row],[INVESTOR CODE]]),SIP[Unique Code],0),),0)} -> 0 | AI644: =IF(INVESTORS_LIST[[#This Row],[TOTAL CURRENT UNITS]]=0,0,(INVESTORS_LIST[[#This Row],[LS_WEIGHT]]*INVESTORS_LIST[[#This Row],[LS_AVERAGE COST]])+(INVESTORS_LIST[[#This Row],[SIP_WEIGHT]]*INVESTORS_LIST[[#This Row],[SIP_AVERAGE COST]])) -> 11.899001 | AJ644: =NAV_MKT -> 12.552 | AK644: =IF(INVESTORS_LIST[[#This Row],[TOTAL CURRENT UNITS]]=0,0,INVESTORS_LIST[[#This Row],[TOTAL CURRENT UNITS]]*INVESTORS_LIST[[#This Row],[NAV]]) -> 96110.664 | AL644: =IF(INVESTORS_LIST[[#This Row],[LS_TOTAL CURRENT UNITS]]=0,0,INVESTORS_LIST[[#This Row],[LS_TOTAL CURRENT UNITS]]*INVESTORS_LIST[[#This Row],[NAV]]) -> 96110.664 | AM644: =IF(INVESTORS_LIST[[#This Row],[SIP_TOTAL CURRENT UNITS]]=0,0,INVESTORS_LIST[[#This Row],[SIP_TOTAL CURRENT UNITS]]*INVESTORS_LIST[[#This Row],[NAV]]) -> 0 | AO644: =IF(INVESTORS_LIST[[#This Row],[TOTAL SELLABLE UNITS]]=0,0,INVESTORS_LIST[[#This Row],[TOTAL SELLABLE UNITS]]*INVESTORS_LIST[[#This Row],[NAV]]) -> 0 | AP644: =INVESTORS_LIST[[#This Row],[LS_TOTAL REALIZED GAIN]]+INVESTORS_LIST[[#This Row],[SIP_TOTAL REALIZED GAIN]] -> 11629.17 | AQ644: =INVESTORS_LIST[[#This Row],[TOTAL MARKET VALUE]]-INVESTORS_LIST[[#This Row],[TOTAL COST VALUE OF CURRENT INVESTMENT]] -> 5000.014 | AR644: =SUMIFS(DivAndTax[Tax Amount],DivAndTax[Investor ID],INVESTORS_LIST[[#This Row],[INVESTOR CODE]]) -> 391.6 | AS644: =SUMIFS(DivAndTax[Gross Dividend],DivAndTax[Investor ID],INVESTORS_LIST[[#This Row],[INVESTOR CODE]]) -> 2610.65 | AT644: =IFERROR(INVESTORS_LIST[[#This Row],[TOTAL CURRENT UNITS]]/SUM(INVESTORS_LIST[TOTAL CURRENT UNITS]),0) -> 0.0003671136
A645: MOHAMMED NURUNNABI BHUIYAN | B645: A00643 | C645: Dear Mr. | D645: Individual | E645: =SUMIFS(LS[Unit],LS[Investor ID],INVESTORS_LIST[[#This Row],[INVESTOR CODE]],LS[B/S],"B") -> 0 | F645: =-SUMIFS(LS[Unit],LS[Investor ID],INVESTORS_LIST[[#This Row],[INVESTOR CODE]],LS[B/S],"S") -> 0 | G645: =IF(INVESTORS_LIST[[#This Row],[LS_TOTAL UNITS BUY]]=0,0,INVESTORS_LIST[[#This Row],[LS_TOTAL UNITS BUY]]-INVESTORS_LIST[[#This Row],[LS_TOTAL UNITS SOLD]]) -> 0 | H645: =IF(INVESTORS_LIST[[#This Row],[LS_TOTAL UNITS BUY]]=0,0,SUMIFS(LS[Amount],LS[Investor ID],INVESTORS_LIST[[#This Row],[INVESTOR CODE]],LS[B/S],"B")) -> 0 | I645: =IF(INVESTORS_LIST[[#This Row],[LS_TOTAL UNITS SOLD]]=0,0,SUMIFS(LS[Cost of Units Sold],LS[Investor ID],INVESTORS_LIST[[#This Row],[INVESTOR CODE]],LS[B/S],"S")) -> 0 | J645: =IF(INVESTORS_LIST[[#This Row],[LS_TOTAL CURRENT UNITS]]=0,0,INVESTORS_LIST[[#This Row],[LS_TOTAL CURRENT UNITS]]*INVESTORS_LIST[[#This Row],[LS_AVERAGE COST]]) -> 0 | K645: =IF(INVESTORS_LIST[[#This Row],[LS_TOTAL UNITS SOLD]]=0,0,SUMIFS(LS[Realized Gain],LS[Investor ID],INVESTORS_LIST[[#This Row],[INVESTOR CODE]],LS[B/S],"S")) -> 0 | L645: =SUMIFS(SIP[Unit],SIP[Investor ID],INVESTORS_LIST[[#This Row],[INVESTOR CODE]],SIP[B/S],"B") -> 0 | M645: =-SUMIFS(SIP[Unit],SIP[Investor ID],INVESTORS_LIST[[#This Row],[INVESTOR CODE]],SIP[B/S],"S") -> 0 | N645: =IF(INVESTORS_LIST[[#This Row],[SIP_TOTAL UNITS BUY]]=0,0,INVESTORS_LIST[[#This Row],[SIP_TOTAL UNITS BUY]]-INVESTORS_LIST[[#This Row],[SIP_TOTAL UNITS SOLD]]) -> 0 | O645: =IF(INVESTORS_LIST[[#This Row],[SIP_TOTAL UNITS BUY]]=0,0,SUMIFS(SIP[Amount],SIP[Investor ID],INVESTORS_LIST[[#This Row],[INVESTOR CODE]],SIP[B/S],"B")) -> 0 | P645: =IF(INVESTORS_LIST[[#This Row],[SIP_TOTAL UNITS SOLD]]=0,0,SUMIFS(SIP[Cost of Units Sold],SIP[Investor ID],INVESTORS_LIST[[#This Row],[INVESTOR CODE]],SIP[B/S],"S")) -> 0 | Q645: =IF(INVESTORS_LIST[[#This Row],[SIP_TOTAL CURRENT UNITS]]=0,0,INVESTORS_LIST[[#This Row],[SIP_TOTAL CURRENT UNITS]]*INVESTORS_LIST[[#This Row],[SIP_AVERAGE COST]]) -> 0 | R645: =IF(INVESTORS_LIST[[#This Row],[SIP_TOTAL UNITS SOLD]]=0,0,SUMIFS(SIP[Realized Gain],SIP[Investor ID],INVESTORS_LIST[[#This Row],[INVESTOR CODE]],SIP[B/S],"S")) -> 0 | S645: =INVESTORS_LIST[[#This Row],[LS_TOTAL UNITS BUY]]+INVESTORS_LIST[[#This Row],[SIP_TOTAL UNITS BUY]] -> 0 | T645: =INVESTORS_LIST[[#This Row],[LS_TOTAL UNITS SOLD]]+INVESTORS_LIST[[#This Row],[SIP_TOTAL UNITS SOLD]] -> 0 | U645: 0 | V645: =SUMIFS(LS[BO UNIT TRANSFER],LS[Investor ID],INVESTORS_LIST[[#This Row],[INVESTOR CODE]],LS[B/S],"B") -> 0 | W645: =SUMIFS(LS[BO UNIT TRANSFER],LS[Investor ID],INVESTORS_LIST[[#This Row],[INVESTOR CODE]],LS[B/S],"S") -> 0 | X645: =SUMIFS(SIP[BO UNIT TRANSFER],SIP[Investor ID],INVESTORS_LIST[[#This Row],[INVESTOR CODE]],SIP[B/S],"S") -> 0 | Y645: =SUMIFS(SIP[BO UNIT TRANSFER],SIP[Investor ID],INVESTORS_LIST[[#This Row],[INVESTOR CODE]],SIP[B/S],"B") -> 0 | Z645: =INVESTORS_LIST[[#This Row],[BO OPENING BALANCE]]+INVESTORS_LIST[[#This Row],[LS- BO UNITS SELL]]+INVESTORS_LIST[[#This Row],[LS- BO UNITS REPURCHASE]]+INVESTORS_LIST[[#This Row],[SIP- BO UNITS REPURCHASE]]-INVESTORS_LIST[[#This Row],[SIP- BO UNITS SELL]] -> 0 | AA645: =INVESTORS_LIST[[#This Row],[TOTAL UNITS BUY]]-INVESTORS_LIST[[#This Row],[TOTAL UNITS SOLD]] -> 0 | AB645: =INVESTORS_LIST[[#This Row],[TOTAL CURRENT UNITS]]-INVESTORS_LIST[[#This Row],[BO UNITS HOLD]] -> 0 | AC645: =INDEX([4]!Table_1[BO ID],MATCH(INVESTORS_LIST[[#This Row],[INVESTOR CODE]],[4]!Table_1[INVESTOR CODE],0)) -> #REF! | AD645: =INVESTORS_LIST[[#This Row],[LS_TOTAL COST VALUE OF CURRENT UNITS]]+INVESTORS_LIST[[#This Row],[SIP_TOTAL COST VALUE OF CURRENT UNITS]] -> 0 | AE645: =IF(INVESTORS_LIST[[#This Row],[TOTAL CURRENT UNITS]]=0,0,INVESTORS_LIST[[#This Row],[LS_TOTAL CURRENT UNITS]]/INVESTORS_LIST[[#This Row],[TOTAL CURRENT UNITS]]) -> 0 | AF645: =IF(INVESTORS_LIST[[#This Row],[TOTAL CURRENT UNITS]]=0,0,INVESTORS_LIST[[#This Row],[SIP_TOTAL CURRENT UNITS]]/INVESTORS_LIST[[#This Row],[TOTAL CURRENT UNITS]]) -> 0 | AG645: {=IF(INVESTORS_LIST[[#This Row],[LS_TOTAL UNITS BUY]]>0,INDEX(LS[NAV at Cost (Average)],MATCH(CONCATENATE(COUNTIFS(LS[Investor ID],INVESTORS_LIST[[#This Row],[INVESTOR CODE]]),INVESTORS_LIST[[#This Row],[INVESTOR CODE]]),LS[Unique Code],0),),0)} -> 0 | AH645: {=IF(INVESTORS_LIST[[#This Row],[SIP_TOTAL UNITS BUY]]>0,INDEX(SIP[NAV at Cost (Average)],MATCH(CONCATENATE(COUNTIFS(SIP[Investor ID],INVESTORS_LIST[[#This Row],[INVESTOR CODE]]),INVESTORS_LIST[[#This Row],[INVESTOR CODE]]),SIP[Unique Code],0),),0)} -> 0 | AI645: =IF(INVESTORS_LIST[[#This Row],[TOTAL CURRENT UNITS]]=0,0,(INVESTORS_LIST[[#This Row],[LS_WEIGHT]]*INVESTORS_LIST[[#This Row],[LS_AVERAGE COST]])+(INVESTORS_LIST[[#This Row],[SIP_WEIGHT]]*INVESTORS_LIST[[#This Row],[SIP_AVERAGE COST]])) -> 0 | AJ645: =NAV_MKT -> 12.552 | AK645: =IF(INVESTORS_LIST[[#This Row],[TOTAL CURRENT UNITS]]=0,0,INVESTORS_LIST[[#This Row],[TOTAL CURRENT UNITS]]*INVESTORS_LIST[[#This Row],[NAV]]) -> 0 | AL645: =IF(INVESTORS_LIST[[#This Row],[LS_TOTAL CURRENT UNITS]]=0,0,INVESTORS_LIST[[#This Row],[LS_TOTAL CURRENT UNITS]]*INVESTORS_LIST[[#This Row],[NAV]]) -> 0 | AM645: =IF(INVESTORS_LIST[[#This Row],[SIP_TOTAL CURRENT UNITS]]=0,0,INVESTORS_LIST[[#This Row],[SIP_TOTAL CURRENT UNITS]]*INVESTORS_LIST[[#This Row],[NAV]]) -> 0 | AO645: =IF(INVESTORS_LIST[[#This Row],[TOTAL SELLABLE UNITS]]=0,0,INVESTORS_LIST[[#This Row],[TOTAL SELLABLE UNITS]]*INVESTORS_LIST[[#This Row],[NAV]]) -> 0 | AP645: =INVESTORS_LIST[[#This Row],[LS_TOTAL REALIZED GAIN]]+INVESTORS_LIST[[#This Row],[SIP_TOTAL REALIZED GAIN]] -> 0 | AQ645: =INVESTORS_LIST[[#This Row],[TOTAL MARKET VALUE]]-INVESTORS_LIST[[#This Row],[TOTAL COST VALUE OF CURRENT INVESTMENT]] -> 0 | AR645: =SUMIFS(DivAndTax[Tax Amount],DivAndTax[Investor ID],INVESTORS_LIST[[#This Row],[INVESTOR CODE]]) -> 0 | AS645: =SUMIFS(DivAndTax[Gross Dividend],DivAndTax[Investor ID],INVESTORS_LIST[[#This Row],[INVESTOR CODE]]) -> 0 | AT645: =IFERROR(INVESTORS_LIST[[#This Row],[TOTAL CURRENT UNITS]]/SUM(INVESTORS_LIST[TOTAL CURRENT UNITS]),0) -> 0
A646: ANONYA CHOWDHURY HIYA | B646: A00644 | C646: Dear Ms. | D646: Individual | E646: =SUMIFS(LS[Unit],LS[Investor ID],INVESTORS_LIST[[#This Row],[INVESTOR CODE]],LS[B/S],"B") -> 0 | F646: =-SUMIFS(LS[Unit],LS[Investor ID],INVESTORS_LIST[[#This Row],[INVESTOR CODE]],LS[B/S],"S") -> 0 | G646: =IF(INVESTORS_LIST[[#This Row],[LS_TOTAL UNITS BUY]]=0,0,INVESTORS_LIST[[#This Row],[LS_TOTAL UNITS BUY]]-INVESTORS_LIST[[#This Row],[LS_TOTAL UNITS SOLD]]) -> 0 | H646: =IF(INVESTORS_LIST[[#This Row],[LS_TOTAL UNITS BUY]]=0,0,SUMIFS(LS[Amount],LS[Investor ID],INVESTORS_LIST[[#This Row],[INVESTOR CODE]],LS[B/S],"B")) -> 0 | I646: =IF(INVESTORS_LIST[[#This Row],[LS_TOTAL UNITS SOLD]]=0,0,SUMIFS(LS[Cost of Units Sold],LS[Investor ID],INVESTORS_LIST[[#This Row],[INVESTOR CODE]],LS[B/S],"S")) -> 0 | J646: =IF(INVESTORS_LIST[[#This Row],[LS_TOTAL CURRENT UNITS]]=0,0,INVESTORS_LIST[[#This Row],[LS_TOTAL CURRENT UNITS]]*INVESTORS_LIST[[#This Row],[LS_AVERAGE COST]]) -> 0 | K646: =IF(INVESTORS_LIST[[#This Row],[LS_TOTAL UNITS SOLD]]=0,0,SUMIFS(LS[Realized Gain],LS[Investor ID],INVESTORS_LIST[[#This Row],[INVESTOR CODE]],LS[B/S],"S")) -> 0 | L646: =SUMIFS(SIP[Unit],SIP[Investor ID],INVESTORS_LIST[[#This Row],[INVESTOR CODE]],SIP[B/S],"B") -> 0 | M646: =-SUMIFS(SIP[Unit],SIP[Investor ID],INVESTORS_LIST[[#This Row],[INVESTOR CODE]],SIP[B/S],"S") -> 0 | N646: =IF(INVESTORS_LIST[[#This Row],[SIP_TOTAL UNITS BUY]]=0,0,INVESTORS_LIST[[#This Row],[SIP_TOTAL UNITS BUY]]-INVESTORS_LIST[[#This Row],[SIP_TOTAL UNITS SOLD]]) -> 0 | O646: =IF(INVESTORS_LIST[[#This Row],[SIP_TOTAL UNITS BUY]]=0,0,SUMIFS(SIP[Amount],SIP[Investor ID],INVESTORS_LIST[[#This Row],[INVESTOR CODE]],SIP[B/S],"B")) -> 0 | P646: =IF(INVESTORS_LIST[[#This Row],[SIP_TOTAL UNITS SOLD]]=0,0,SUMIFS(SIP[Cost of Units Sold],SIP[Investor ID],INVESTORS_LIST[[#This Row],[INVESTOR CODE]],SIP[B/S],"S")) -> 0 | Q646: =IF(INVESTORS_LIST[[#This Row],[SIP_TOTAL CURRENT UNITS]]=0,0,INVESTORS_LIST[[#This Row],[SIP_TOTAL CURRENT UNITS]]*INVESTORS_LIST[[#This Row],[SIP_AVERAGE COST]]) -> 0 | R646: =IF(INVESTORS_LIST[[#This Row],[SIP_TOTAL UNITS SOLD]]=0,0,SUMIFS(SIP[Realized Gain],SIP[Investor ID],INVESTORS_LIST[[#This Row],[INVESTOR CODE]],SIP[B/S],"S")) -> 0 | S646: =INVESTORS_LIST[[#This Row],[LS_TOTAL UNITS BUY]]+INVESTORS_LIST[[#This Row],[SIP_TOTAL UNITS BUY]] -> 0 | T646: =INVESTORS_LIST[[#This Row],[LS_TOTAL UNITS SOLD]]+INVESTORS_LIST[[#This Row],[SIP_TOTAL UNITS SOLD]] -> 0 | U646: 0 | V646: =SUMIFS(LS[BO UNIT TRANSFER],LS[Investor ID],INVESTORS_LIST[[#This Row],[INVESTOR CODE]],LS[B/S],"B") -> 0 | W646: =SUMIFS(LS[BO UNIT TRANSFER],LS[Investor ID],INVESTORS_LIST[[#This Row],[INVESTOR CODE]],LS[B/S],"S") -> 0 | X646: =SUMIFS(SIP[BO UNIT TRANSFER],SIP[Investor ID],INVESTORS_LIST[[#This Row],[INVESTOR CODE]],SIP[B/S],"S") -> 0 | Y646: =SUMIFS(SIP[BO UNIT TRANSFER],SIP[Investor ID],INVESTORS_LIST[[#This Row],[INVESTOR CODE]],SIP[B/S],"B") -> 0 | Z646: =INVESTORS_LIST[[#This Row],[BO OPENING BALANCE]]+INVESTORS_LIST[[#This Row],[LS- BO UNITS SELL]]+INVESTORS_LIST[[#This Row],[LS- BO UNITS REPURCHASE]]+INVESTORS_LIST[[#This Row],[SIP- BO UNITS REPURCHASE]]-INVESTORS_LIST[[#This Row],[SIP- BO UNITS SELL]] -> 0 | AA646: =INVESTORS_LIST[[#This Row],[TOTAL UNITS BUY]]-INVESTORS_LIST[[#This Row],[TOTAL UNITS SOLD]] -> 0 | AB646: =INVESTORS_LIST[[#This Row],[TOTAL CURRENT UNITS]]-INVESTORS_LIST[[#This Row],[BO UNITS HOLD]] -> 0 | AC646: =INDEX([4]!Table_1[BO ID],MATCH(INVESTORS_LIST[[#This Row],[INVESTOR CODE]],[4]!Table_1[INVESTOR CODE],0)) -> #REF! | AD646: =INVESTORS_LIST[[#This Row],[LS_TOTAL COST VALUE OF CURRENT UNITS]]+INVESTORS_LIST[[#This Row],[SIP_TOTAL COST VALUE OF CURRENT UNITS]] -> 0 | AE646: =IF(INVESTORS_LIST[[#This Row],[TOTAL CURRENT UNITS]]=0,0,INVESTORS_LIST[[#This Row],[LS_TOTAL CURRENT UNITS]]/INVESTORS_LIST[[#This Row],[TOTAL CURRENT UNITS]]) -> 0 | AF646: =IF(INVESTORS_LIST[[#This Row],[TOTAL CURRENT UNITS]]=0,0,INVESTORS_LIST[[#This Row],[SIP_TOTAL CURRENT UNITS]]/INVESTORS_LIST[[#This Row],[TOTAL CURRENT UNITS]]) -> 0 | AG646: {=IF(INVESTORS_LIST[[#This Row],[LS_TOTAL UNITS BUY]]>0,INDEX(LS[NAV at Cost (Average)],MATCH(CONCATENATE(COUNTIFS(LS[Investor ID],INVESTORS_LIST[[#This Row],[INVESTOR CODE]]),INVESTORS_LIST[[#This Row],[INVESTOR CODE]]),LS[Unique Code],0),),0)} -> 0 | AH646: {=IF(INVESTORS_LIST[[#This Row],[SIP_TOTAL UNITS BUY]]>0,INDEX(SIP[NAV at Cost (Average)],MATCH(CONCATENATE(COUNTIFS(SIP[Investor ID],INVESTORS_LIST[[#This Row],[INVESTOR CODE]]),INVESTORS_LIST[[#This Row],[INVESTOR CODE]]),SIP[Unique Code],0),),0)} -> 0 | AI646: =IF(INVESTORS_LIST[[#This Row],[TOTAL CURRENT UNITS]]=0,0,(INVESTORS_LIST[[#This Row],[LS_WEIGHT]]*INVESTORS_LIST[[#This Row],[LS_AVERAGE COST]])+(INVESTORS_LIST[[#This Row],[SIP_WEIGHT]]*INVESTORS_LIST[[#This Row],[SIP_AVERAGE COST]])) -> 0 | AJ646: =NAV_MKT -> 12.552 | AK646: =IF(INVESTORS_LIST[[#This Row],[TOTAL CURRENT UNITS]]=0,0,INVESTORS_LIST[[#This Row],[TOTAL CURRENT UNITS]]*INVESTORS_LIST[[#This Row],[NAV]]) -> 0 | AL646: =IF(INVESTORS_LIST[[#This Row],[LS_TOTAL CURRENT UNITS]]=0,0,INVESTORS_LIST[[#This Row],[LS_TOTAL CURRENT UNITS]]*INVESTORS_LIST[[#This Row],[NAV]]) -> 0 | AM646: =IF(INVESTORS_LIST[[#This Row],[SIP_TOTAL CURRENT UNITS]]=0,0,INVESTORS_LIST[[#This Row],[SIP_TOTAL CURRENT UNITS]]*INVESTORS_LIST[[#This Row],[NAV]]) -> 0 | AO646: =IF(INVESTORS_LIST[[#This Row],[TOTAL SELLABLE UNITS]]=0,0,INVESTORS_LIST[[#This Row],[TOTAL SELLABLE UNITS]]*INVESTORS_LIST[[#This Row],[NAV]]) -> 0 | AP646: =INVESTORS_LIST[[#This Row],[LS_TOTAL REALIZED GAIN]]+INVESTORS_LIST[[#This Row],[SIP_TOTAL REALIZED GAIN]] -> 0 | AQ646: =INVESTORS_LIST[[#This Row],[TOTAL MARKET VALUE]]-INVESTORS_LIST[[#This Row],[TOTAL COST VALUE OF CURRENT INVESTMENT]] -> 0 | AR646: =SUMIFS(DivAndTax[Tax Amount],DivAndTax[Investor ID],INVESTORS_LIST[[#This Row],[INVESTOR CODE]]) -> 0 | AS646: =SUMIFS(DivAndTax[Gross Dividend],DivAndTax[Investor ID],INVESTORS_LIST[[#This Row],[INVESTOR CODE]]) -> 0 | AT646: =IFERROR(INVESTORS_LIST[[#This Row],[TOTAL CURRENT UNITS]]/SUM(INVESTORS_LIST[TOTAL CURRENT UNITS]),0) -> 0
A647: S.M. AFZAL REZA | B647: A00645 | C647: Dear Mr. | D647: Individual | E647: =SUMIFS(LS[Unit],LS[Investor ID],INVESTORS_LIST[[#This Row],[INVESTOR CODE]],LS[B/S],"B") -> 0 | F647: =-SUMIFS(LS[Unit],LS[Investor ID],INVESTORS_LIST[[#This Row],[INVESTOR CODE]],LS[B/S],"S") -> 0 | G647: =IF(INVESTORS_LIST[[#This Row],[LS_TOTAL UNITS BUY]]=0,0,INVESTORS_LIST[[#This Row],[LS_TOTAL UNITS BUY]]-INVESTORS_LIST[[#This Row],[LS_TOTAL UNITS SOLD]]) -> 0 | H647: =IF(INVESTORS_LIST[[#This Row],[LS_TOTAL UNITS BUY]]=0,0,SUMIFS(LS[Amount],LS[Investor ID],INVESTORS_LIST[[#This Row],[INVESTOR CODE]],LS[B/S],"B")) -> 0 | I647: =IF(INVESTORS_LIST[[#This Row],[LS_TOTAL UNITS SOLD]]=0,0,SUMIFS(LS[Cost of Units Sold],LS[Investor ID],INVESTORS_LIST[[#This Row],[INVESTOR CODE]],LS[B/S],"S")) -> 0 | J647: =IF(INVESTORS_LIST[[#This Row],[LS_TOTAL CURRENT UNITS]]=0,0,INVESTORS_LIST[[#This Row],[LS_TOTAL CURRENT UNITS]]*INVESTORS_LIST[[#This Row],[LS_AVERAGE COST]]) -> 0 | K647: =IF(INVESTORS_LIST[[#This Row],[LS_TOTAL UNITS SOLD]]=0,0,SUMIFS(LS[Realized Gain],LS[Investor ID],INVESTORS_LIST[[#This Row],[INVESTOR CODE]],LS[B/S],"S")) -> 0 | L647: =SUMIFS(SIP[Unit],SIP[Investor ID],INVESTORS_LIST[[#This Row],[INVESTOR CODE]],SIP[B/S],"B") -> 0 | M647: =-SUMIFS(SIP[Unit],SIP[Investor ID],INVESTORS_LIST[[#This Row],[INVESTOR CODE]],SIP[B/S],"S") -> 0 | N647: =IF(INVESTORS_LIST[[#This Row],[SIP_TOTAL UNITS BUY]]=0,0,INVESTORS_LIST[[#This Row],[SIP_TOTAL UNITS BUY]]-INVESTORS_LIST[[#This Row],[SIP_TOTAL UNITS SOLD]]) -> 0 | O647: =IF(INVESTORS_LIST[[#This Row],[SIP_TOTAL UNITS BUY]]=0,0,SUMIFS(SIP[Amount],SIP[Investor ID],INVESTORS_LIST[[#This Row],[INVESTOR CODE]],SIP[B/S],"B")) -> 0 | P647: =IF(INVESTORS_LIST[[#This Row],[SIP_TOTAL UNITS SOLD]]=0,0,SUMIFS(SIP[Cost of Units Sold],SIP[Investor ID],INVESTORS_LIST[[#This Row],[INVESTOR CODE]],SIP[B/S],"S")) -> 0 | Q647: =IF(INVESTORS_LIST[[#This Row],[SIP_TOTAL CURRENT UNITS]]=0,0,INVESTORS_LIST[[#This Row],[SIP_TOTAL CURRENT UNITS]]*INVESTORS_LIST[[#This Row],[SIP_AVERAGE COST]]) -> 0 | R647: =IF(INVESTORS_LIST[[#This Row],[SIP_TOTAL UNITS SOLD]]=0,0,SUMIFS(SIP[Realized Gain],SIP[Investor ID],INVESTORS_LIST[[#This Row],[INVESTOR CODE]],SIP[B/S],"S")) -> 0 | S647: =INVESTORS_LIST[[#This Row],[LS_TOTAL UNITS BUY]]+INVESTORS_LIST[[#This Row],[SIP_TOTAL UNITS BUY]] -> 0 | T647: =INVESTORS_LIST[[#This Row],[LS_TOTAL UNITS SOLD]]+INVESTORS_LIST[[#This Row],[SIP_TOTAL UNITS SOLD]] -> 0 | U647: 0 | V647: =SUMIFS(LS[BO UNIT TRANSFER],LS[Investor ID],INVESTORS_LIST[[#This Row],[INVESTOR CODE]],LS[B/S],"B") -> 0 | W647: =SUMIFS(LS[BO UNIT TRANSFER],LS[Investor ID],INVESTORS_LIST[[#This Row],[INVESTOR CODE]],LS[B/S],"S") -> 0 | X647: =SUMIFS(SIP[BO UNIT TRANSFER],SIP[Investor ID],INVESTORS_LIST[[#This Row],[INVESTOR CODE]],SIP[B/S],"S") -> 0 | Y647: =SUMIFS(SIP[BO UNIT TRANSFER],SIP[Investor ID],INVESTORS_LIST[[#This Row],[INVESTOR CODE]],SIP[B/S],"B") -> 0 | Z647: =INVESTORS_LIST[[#This Row],[BO OPENING BALANCE]]+INVESTORS_LIST[[#This Row],[LS- BO UNITS SELL]]+INVESTORS_LIST[[#This Row],[LS- BO UNITS REPURCHASE]]+INVESTORS_LIST[[#This Row],[SIP- BO UNITS REPURCHASE]]-INVESTORS_LIST[[#This Row],[SIP- BO UNITS SELL]] -> 0 | AA647: =INVESTORS_LIST[[#This Row],[TOTAL UNITS BUY]]-INVESTORS_LIST[[#This Row],[TOTAL UNITS SOLD]] -> 0 | AB647: =INVESTORS_LIST[[#This Row],[TOTAL CURRENT UNITS]]-INVESTORS_LIST[[#This Row],[BO UNITS HOLD]] -> 0 | AC647: =INDEX([4]!Table_1[BO ID],MATCH(INVESTORS_LIST[[#This Row],[INVESTOR CODE]],[4]!Table_1[INVESTOR CODE],0)) -> #REF! | AD647: =INVESTORS_LIST[[#This Row],[LS_TOTAL COST VALUE OF CURRENT UNITS]]+INVESTORS_LIST[[#This Row],[SIP_TOTAL COST VALUE OF CURRENT UNITS]] -> 0 | AE647: =IF(INVESTORS_LIST[[#This Row],[TOTAL CURRENT UNITS]]=0,0,INVESTORS_LIST[[#This Row],[LS_TOTAL CURRENT UNITS]]/INVESTORS_LIST[[#This Row],[TOTAL CURRENT UNITS]]) -> 0 | AF647: =IF(INVESTORS_LIST[[#This Row],[TOTAL CURRENT UNITS]]=0,0,INVESTORS_LIST[[#This Row],[SIP_TOTAL CURRENT UNITS]]/INVESTORS_LIST[[#This Row],[TOTAL CURRENT UNITS]]) -> 0 | AG647: {=IF(INVESTORS_LIST[[#This Row],[LS_TOTAL UNITS BUY]]>0,INDEX(LS[NAV at Cost (Average)],MATCH(CONCATENATE(COUNTIFS(LS[Investor ID],INVESTORS_LIST[[#This Row],[INVESTOR CODE]]),INVESTORS_LIST[[#This Row],[INVESTOR CODE]]),LS[Unique Code],0),),0)} -> 0 | AH647: {=IF(INVESTORS_LIST[[#This Row],[SIP_TOTAL UNITS BUY]]>0,INDEX(SIP[NAV at Cost (Average)],MATCH(CONCATENATE(COUNTIFS(SIP[Investor ID],INVESTORS_LIST[[#This Row],[INVESTOR CODE]]),INVESTORS_LIST[[#This Row],[INVESTOR CODE]]),SIP[Unique Code],0),),0)} -> 0 | AI647: =IF(INVESTORS_LIST[[#This Row],[TOTAL CURRENT UNITS]]=0,0,(INVESTORS_LIST[[#This Row],[LS_WEIGHT]]*INVESTORS_LIST[[#This Row],[LS_AVERAGE COST]])+(INVESTORS_LIST[[#This Row],[SIP_WEIGHT]]*INVESTORS_LIST[[#This Row],[SIP_AVERAGE COST]])) -> 0 | AJ647: =NAV_MKT -> 12.552 | AK647: =IF(INVESTORS_LIST[[#This Row],[TOTAL CURRENT UNITS]]=0,0,INVESTORS_LIST[[#This Row],[TOTAL CURRENT UNITS]]*INVESTORS_LIST[[#This Row],[NAV]]) -> 0 | AL647: =IF(INVESTORS_LIST[[#This Row],[LS_TOTAL CURRENT UNITS]]=0,0,INVESTORS_LIST[[#This Row],[LS_TOTAL CURRENT UNITS]]*INVESTORS_LIST[[#This Row],[NAV]]) -> 0 | AM647: =IF(INVESTORS_LIST[[#This Row],[SIP_TOTAL CURRENT UNITS]]=0,0,INVESTORS_LIST[[#This Row],[SIP_TOTAL CURRENT UNITS]]*INVESTORS_LIST[[#This Row],[NAV]]) -> 0 | AO647: =IF(INVESTORS_LIST[[#This Row],[TOTAL SELLABLE UNITS]]=0,0,INVESTORS_LIST[[#This Row],[TOTAL SELLABLE UNITS]]*INVESTORS_LIST[[#This Row],[NAV]]) -> 0 | AP647: =INVESTORS_LIST[[#This Row],[LS_TOTAL REALIZED GAIN]]+INVESTORS_LIST[[#This Row],[SIP_TOTAL REALIZED GAIN]] -> 0 | AQ647: =INVESTORS_LIST[[#This Row],[TOTAL MARKET VALUE]]-INVESTORS_LIST[[#This Row],[TOTAL COST VALUE OF CURRENT INVESTMENT]] -> 0 | AR647: =SUMIFS(DivAndTax[Tax Amount],DivAndTax[Investor ID],INVESTORS_LIST[[#This Row],[INVESTOR CODE]]) -> 0 | AS647: =SUMIFS(DivAndTax[Gross Dividend],DivAndTax[Investor ID],INVESTORS_LIST[[#This Row],[INVESTOR CODE]]) -> 0 | AT647: =IFERROR(INVESTORS_LIST[[#This Row],[TOTAL CURRENT UNITS]]/SUM(INVESTORS_LIST[TOTAL CURRENT UNITS]),0) -> 0
A648: RAHNUMA SANJANA & AROORA SAMEERA CHOWDHURY | B648: A00646 | C648: Dear Ms. | D648: Individual | E648: =SUMIFS(LS[Unit],LS[Investor ID],INVESTORS_LIST[[#This Row],[INVESTOR CODE]],LS[B/S],"B") -> 0 | F648: =-SUMIFS(LS[Unit],LS[Investor ID],INVESTORS_LIST[[#This Row],[INVESTOR CODE]],LS[B/S],"S") -> 0 | G648: =IF(INVESTORS_LIST[[#This Row],[LS_TOTAL UNITS BUY]]=0,0,INVESTORS_LIST[[#This Row],[LS_TOTAL UNITS BUY]]-INVESTORS_LIST[[#This Row],[LS_TOTAL UNITS SOLD]]) -> 0 | H648: =IF(INVESTORS_LIST[[#This Row],[LS_TOTAL UNITS BUY]]=0,0,SUMIFS(LS[Amount],LS[Investor ID],INVESTORS_LIST[[#This Row],[INVESTOR CODE]],LS[B/S],"B")) -> 0 | I648: =IF(INVESTORS_LIST[[#This Row],[LS_TOTAL UNITS SOLD]]=0,0,SUMIFS(LS[Cost of Units Sold],LS[Investor ID],INVESTORS_LIST[[#This Row],[INVESTOR CODE]],LS[B/S],"S")) -> 0 | J648: =IF(INVESTORS_LIST[[#This Row],[LS_TOTAL CURRENT UNITS]]=0,0,INVESTORS_LIST[[#This Row],[LS_TOTAL CURRENT UNITS]]*INVESTORS_LIST[[#This Row],[LS_AVERAGE COST]]) -> 0 | K648: =IF(INVESTORS_LIST[[#This Row],[LS_TOTAL UNITS SOLD]]=0,0,SUMIFS(LS[Realized Gain],LS[Investor ID],INVESTORS_LIST[[#This Row],[INVESTOR CODE]],LS[B/S],"S")) -> 0 | L648: =SUMIFS(SIP[Unit],SIP[Investor ID],INVESTORS_LIST[[#This Row],[INVESTOR CODE]],SIP[B/S],"B") -> 0 | M648: =-SUMIFS(SIP[Unit],SIP[Investor ID],INVESTORS_LIST[[#This Row],[INVESTOR CODE]],SIP[B/S],"S") -> 0 | N648: =IF(INVESTORS_LIST[[#This Row],[SIP_TOTAL UNITS BUY]]=0,0,INVESTORS_LIST[[#This Row],[SIP_TOTAL UNITS BUY]]-INVESTORS_LIST[[#This Row],[SIP_TOTAL UNITS SOLD]]) -> 0 | O648: =IF(INVESTORS_LIST[[#This Row],[SIP_TOTAL UNITS BUY]]=0,0,SUMIFS(SIP[Amount],SIP[Investor ID],INVESTORS_LIST[[#This Row],[INVESTOR CODE]],SIP[B/S],"B")) -> 0 | P648: =IF(INVESTORS_LIST[[#This Row],[SIP_TOTAL UNITS SOLD]]=0,0,SUMIFS(SIP[Cost of Units Sold],SIP[Investor ID],INVESTORS_LIST[[#This Row],[INVESTOR CODE]],SIP[B/S],"S")) -> 0 | Q648: =IF(INVESTORS_LIST[[#This Row],[SIP_TOTAL CURRENT UNITS]]=0,0,INVESTORS_LIST[[#This Row],[SIP_TOTAL CURRENT UNITS]]*INVESTORS_LIST[[#This Row],[SIP_AVERAGE COST]]) -> 0 | R648: =IF(INVESTORS_LIST[[#This Row],[SIP_TOTAL UNITS SOLD]]=0,0,SUMIFS(SIP[Realized Gain],SIP[Investor ID],INVESTORS_LIST[[#This Row],[INVESTOR CODE]],SIP[B/S],"S")) -> 0 | S648: =INVESTORS_LIST[[#This Row],[LS_TOTAL UNITS BUY]]+INVESTORS_LIST[[#This Row],[SIP_TOTAL UNITS BUY]] -> 0 | T648: =INVESTORS_LIST[[#This Row],[LS_TOTAL UNITS SOLD]]+INVESTORS_LIST[[#This Row],[SIP_TOTAL UNITS SOLD]] -> 0 | U648: 0 | V648: =SUMIFS(LS[BO UNIT TRANSFER],LS[Investor ID],INVESTORS_LIST[[#This Row],[INVESTOR CODE]],LS[B/S],"B") -> 0 | W648: =SUMIFS(LS[BO UNIT TRANSFER],LS[Investor ID],INVESTORS_LIST[[#This Row],[INVESTOR CODE]],LS[B/S],"S") -> 0 | X648: =SUMIFS(SIP[BO UNIT TRANSFER],SIP[Investor ID],INVESTORS_LIST[[#This Row],[INVESTOR CODE]],SIP[B/S],"S") -> 0 | Y648: =SUMIFS(SIP[BO UNIT TRANSFER],SIP[Investor ID],INVESTORS_LIST[[#This Row],[INVESTOR CODE]],SIP[B/S],"B") -> 0 | Z648: =INVESTORS_LIST[[#This Row],[BO OPENING BALANCE]]+INVESTORS_LIST[[#This Row],[LS- BO UNITS SELL]]+INVESTORS_LIST[[#This Row],[LS- BO UNITS REPURCHASE]]+INVESTORS_LIST[[#This Row],[SIP- BO UNITS REPURCHASE]]-INVESTORS_LIST[[#This Row],[SIP- BO UNITS SELL]] -> 0 | AA648: =INVESTORS_LIST[[#This Row],[TOTAL UNITS BUY]]-INVESTORS_LIST[[#This Row],[TOTAL UNITS SOLD]] -> 0 | AB648: =INVESTORS_LIST[[#This Row],[TOTAL CURRENT UNITS]]-INVESTORS_LIST[[#This Row],[BO UNITS HOLD]] -> 0 | AC648: =INDEX([4]!Table_1[BO ID],MATCH(INVESTORS_LIST[[#This Row],[INVESTOR CODE]],[4]!Table_1[INVESTOR CODE],0)) -> #REF! | AD648: =INVESTORS_LIST[[#This Row],[LS_TOTAL COST VALUE OF CURRENT UNITS]]+INVESTORS_LIST[[#This Row],[SIP_TOTAL COST VALUE OF CURRENT UNITS]] -> 0 | AE648: =IF(INVESTORS_LIST[[#This Row],[TOTAL CURRENT UNITS]]=0,0,INVESTORS_LIST[[#This Row],[LS_TOTAL CURRENT UNITS]]/INVESTORS_LIST[[#This Row],[TOTAL CURRENT UNITS]]) -> 0 | AF648: =IF(INVESTORS_LIST[[#This Row],[TOTAL CURRENT UNITS]]=0,0,INVESTORS_LIST[[#This Row],[SIP_TOTAL CURRENT UNITS]]/INVESTORS_LIST[[#This Row],[TOTAL CURRENT UNITS]]) -> 0 | AG648: {=IF(INVESTORS_LIST[[#This Row],[LS_TOTAL UNITS BUY]]>0,INDEX(LS[NAV at Cost (Average)],MATCH(CONCATENATE(COUNTIFS(LS[Investor ID],INVESTORS_LIST[[#This Row],[INVESTOR CODE]]),INVESTORS_LIST[[#This Row],[INVESTOR CODE]]),LS[Unique Code],0),),0)} -> 0 | AH648: {=IF(INVESTORS_LIST[[#This Row],[SIP_TOTAL UNITS BUY]]>0,INDEX(SIP[NAV at Cost (Average)],MATCH(CONCATENATE(COUNTIFS(SIP[Investor ID],INVESTORS_LIST[[#This Row],[INVESTOR CODE]]),INVESTORS_LIST[[#This Row],[INVESTOR CODE]]),SIP[Unique Code],0),),0)} -> 0 | AI648: =IF(INVESTORS_LIST[[#This Row],[TOTAL CURRENT UNITS]]=0,0,(INVESTORS_LIST[[#This Row],[LS_WEIGHT]]*INVESTORS_LIST[[#This Row],[LS_AVERAGE COST]])+(INVESTORS_LIST[[#This Row],[SIP_WEIGHT]]*INVESTORS_LIST[[#This Row],[SIP_AVERAGE COST]])) -> 0 | AJ648: =NAV_MKT -> 12.552 | AK648: =IF(INVESTORS_LIST[[#This Row],[TOTAL CURRENT UNITS]]=0,0,INVESTORS_LIST[[#This Row],[TOTAL CURRENT UNITS]]*INVESTORS_LIST[[#This Row],[NAV]]) -> 0 | AL648: =IF(INVESTORS_LIST[[#This Row],[LS_TOTAL CURRENT UNITS]]=0,0,INVESTORS_LIST[[#This Row],[LS_TOTAL CURRENT UNITS]]*INVESTORS_LIST[[#This Row],[NAV]]) -> 0 | AM648: =IF(INVESTORS_LIST[[#This Row],[SIP_TOTAL CURRENT UNITS]]=0,0,INVESTORS_LIST[[#This Row],[SIP_TOTAL CURRENT UNITS]]*INVESTORS_LIST[[#This Row],[NAV]]) -> 0 | AO648: =IF(INVESTORS_LIST[[#This Row],[TOTAL SELLABLE UNITS]]=0,0,INVESTORS_LIST[[#This Row],[TOTAL SELLABLE UNITS]]*INVESTORS_LIST[[#This Row],[NAV]]) -> 0 | AP648: =INVESTORS_LIST[[#This Row],[LS_TOTAL REALIZED GAIN]]+INVESTORS_LIST[[#This Row],[SIP_TOTAL REALIZED GAIN]] -> 0 | AQ648: =INVESTORS_LIST[[#This Row],[TOTAL MARKET VALUE]]-INVESTORS_LIST[[#This Row],[TOTAL COST VALUE OF CURRENT INVESTMENT]] -> 0 | AR648: =SUMIFS(DivAndTax[Tax Amount],DivAndTax[Investor ID],INVESTORS_LIST[[#This Row],[INVESTOR CODE]]) -> 0 | AS648: =SUMIFS(DivAndTax[Gross Dividend],DivAndTax[Investor ID],INVESTORS_LIST[[#This Row],[INVESTOR CODE]]) -> 0 | AT648: =IFERROR(INVESTORS_LIST[[#This Row],[TOTAL CURRENT UNITS]]/SUM(INVESTORS_LIST[TOTAL CURRENT UNITS]),0) -> 0
A649: SUKANTA SAHA | B649: A00647 | C649: Dear Ms. | D649: Individual | E649: =SUMIFS(LS[Unit],LS[Investor ID],INVESTORS_LIST[[#This Row],[INVESTOR CODE]],LS[B/S],"B") -> 0 | F649: =-SUMIFS(LS[Unit],LS[Investor ID],INVESTORS_LIST[[#This Row],[INVESTOR CODE]],LS[B/S],"S") -> 0 | G649: =IF(INVESTORS_LIST[[#This Row],[LS_TOTAL UNITS BUY]]=0,0,INVESTORS_LIST[[#This Row],[LS_TOTAL UNITS BUY]]-INVESTORS_LIST[[#This Row],[LS_TOTAL UNITS SOLD]]) -> 0 | H649: =IF(INVESTORS_LIST[[#This Row],[LS_TOTAL UNITS BUY]]=0,0,SUMIFS(LS[Amount],LS[Investor ID],INVESTORS_LIST[[#This Row],[INVESTOR CODE]],LS[B/S],"B")) -> 0 | I649: =IF(INVESTORS_LIST[[#This Row],[LS_TOTAL UNITS SOLD]]=0,0,SUMIFS(LS[Cost of Units Sold],LS[Investor ID],INVESTORS_LIST[[#This Row],[INVESTOR CODE]],LS[B/S],"S")) -> 0 | J649: =IF(INVESTORS_LIST[[#This Row],[LS_TOTAL CURRENT UNITS]]=0,0,INVESTORS_LIST[[#This Row],[LS_TOTAL CURRENT UNITS]]*INVESTORS_LIST[[#This Row],[LS_AVERAGE COST]]) -> 0 | K649: =IF(INVESTORS_LIST[[#This Row],[LS_TOTAL UNITS SOLD]]=0,0,SUMIFS(LS[Realized Gain],LS[Investor ID],INVESTORS_LIST[[#This Row],[INVESTOR CODE]],LS[B/S],"S")) -> 0 | L649: =SUMIFS(SIP[Unit],SIP[Investor ID],INVESTORS_LIST[[#This Row],[INVESTOR CODE]],SIP[B/S],"B") -> 0 | M649: =-SUMIFS(SIP[Unit],SIP[Investor ID],INVESTORS_LIST[[#This Row],[INVESTOR CODE]],SIP[B/S],"S") -> 0 | N649: =IF(INVESTORS_LIST[[#This Row],[SIP_TOTAL UNITS BUY]]=0,0,INVESTORS_LIST[[#This Row],[SIP_TOTAL UNITS BUY]]-INVESTORS_LIST[[#This Row],[SIP_TOTAL UNITS SOLD]]) -> 0 | O649: =IF(INVESTORS_LIST[[#This Row],[SIP_TOTAL UNITS BUY]]=0,0,SUMIFS(SIP[Amount],SIP[Investor ID],INVESTORS_LIST[[#This Row],[INVESTOR CODE]],SIP[B/S],"B")) -> 0 | P649: =IF(INVESTORS_LIST[[#This Row],[SIP_TOTAL UNITS SOLD]]=0,0,SUMIFS(SIP[Cost of Units Sold],SIP[Investor ID],INVESTORS_LIST[[#This Row],[INVESTOR CODE]],SIP[B/S],"S")) -> 0 | Q649: =IF(INVESTORS_LIST[[#This Row],[SIP_TOTAL CURRENT UNITS]]=0,0,INVESTORS_LIST[[#This Row],[SIP_TOTAL CURRENT UNITS]]*INVESTORS_LIST[[#This Row],[SIP_AVERAGE COST]]) -> 0 | R649: =IF(INVESTORS_LIST[[#This Row],[SIP_TOTAL UNITS SOLD]]=0,0,SUMIFS(SIP[Realized Gain],SIP[Investor ID],INVESTORS_LIST[[#This Row],[INVESTOR CODE]],SIP[B/S],"S")) -> 0 | S649: =INVESTORS_LIST[[#This Row],[LS_TOTAL UNITS BUY]]+INVESTORS_LIST[[#This Row],[SIP_TOTAL UNITS BUY]] -> 0 | T649: =INVESTORS_LIST[[#This Row],[LS_TOTAL UNITS SOLD]]+INVESTORS_LIST[[#This Row],[SIP_TOTAL UNITS SOLD]] -> 0 | U649: 0 | V649: =SUMIFS(LS[BO UNIT TRANSFER],LS[Investor ID],INVESTORS_LIST[[#This Row],[INVESTOR CODE]],LS[B/S],"B") -> 0 | W649: =SUMIFS(LS[BO UNIT TRANSFER],LS[Investor ID],INVESTORS_LIST[[#This Row],[INVESTOR CODE]],LS[B/S],"S") -> 0 | X649: =SUMIFS(SIP[BO UNIT TRANSFER],SIP[Investor ID],INVESTORS_LIST[[#This Row],[INVESTOR CODE]],SIP[B/S],"S") -> 0 | Y649: =SUMIFS(SIP[BO UNIT TRANSFER],SIP[Investor ID],INVESTORS_LIST[[#This Row],[INVESTOR CODE]],SIP[B/S],"B") -> 0 | Z649: =INVESTORS_LIST[[#This Row],[BO OPENING BALANCE]]+INVESTORS_LIST[[#This Row],[LS- BO UNITS SELL]]+INVESTORS_LIST[[#This Row],[LS- BO UNITS REPURCHASE]]+INVESTORS_LIST[[#This Row],[SIP- BO UNITS REPURCHASE]]-INVESTORS_LIST[[#This Row],[SIP- BO UNITS SELL]] -> 0 | AA649: =INVESTORS_LIST[[#This Row],[TOTAL UNITS BUY]]-INVESTORS_LIST[[#This Row],[TOTAL UNITS SOLD]] -> 0 | AB649: =INVESTORS_LIST[[#This Row],[TOTAL CURRENT UNITS]]-INVESTORS_LIST[[#This Row],[BO UNITS HOLD]] -> 0 | AC649: =INDEX([4]!Table_1[BO ID],MATCH(INVESTORS_LIST[[#This Row],[INVESTOR CODE]],[4]!Table_1[INVESTOR CODE],0)) -> #REF! | AD649: =INVESTORS_LIST[[#This Row],[LS_TOTAL COST VALUE OF CURRENT UNITS]]+INVESTORS_LIST[[#This Row],[SIP_TOTAL COST VALUE OF CURRENT UNITS]] -> 0 | AE649: =IF(INVESTORS_LIST[[#This Row],[TOTAL CURRENT UNITS]]=0,0,INVESTORS_LIST[[#This Row],[LS_TOTAL CURRENT UNITS]]/INVESTORS_LIST[[#This Row],[TOTAL CURRENT UNITS]]) -> 0 | AF649: =IF(INVESTORS_LIST[[#This Row],[TOTAL CURRENT UNITS]]=0,0,INVESTORS_LIST[[#This Row],[SIP_TOTAL CURRENT UNITS]]/INVESTORS_LIST[[#This Row],[TOTAL CURRENT UNITS]]) -> 0 | AG649: {=IF(INVESTORS_LIST[[#This Row],[LS_TOTAL UNITS BUY]]>0,INDEX(LS[NAV at Cost (Average)],MATCH(CONCATENATE(COUNTIFS(LS[Investor ID],INVESTORS_LIST[[#This Row],[INVESTOR CODE]]),INVESTORS_LIST[[#This Row],[INVESTOR CODE]]),LS[Unique Code],0),),0)} -> 0 | AH649: {=IF(INVESTORS_LIST[[#This Row],[SIP_TOTAL UNITS BUY]]>0,INDEX(SIP[NAV at Cost (Average)],MATCH(CONCATENATE(COUNTIFS(SIP[Investor ID],INVESTORS_LIST[[#This Row],[INVESTOR CODE]]),INVESTORS_LIST[[#This Row],[INVESTOR CODE]]),SIP[Unique Code],0),),0)} -> 0 | AI649: =IF(INVESTORS_LIST[[#This Row],[TOTAL CURRENT UNITS]]=0,0,(INVESTORS_LIST[[#This Row],[LS_WEIGHT]]*INVESTORS_LIST[[#This Row],[LS_AVERAGE COST]])+(INVESTORS_LIST[[#This Row],[SIP_WEIGHT]]*INVESTORS_LIST[[#This Row],[SIP_AVERAGE COST]])) -> 0 | AJ649: =NAV_MKT -> 12.552 | AK649: =IF(INVESTORS_LIST[[#This Row],[TOTAL CURRENT UNITS]]=0,0,INVESTORS_LIST[[#This Row],[TOTAL CURRENT UNITS]]*INVESTORS_LIST[[#This Row],[NAV]]) -> 0 | AL649: =IF(INVESTORS_LIST[[#This Row],[LS_TOTAL CURRENT UNITS]]=0,0,INVESTORS_LIST[[#This Row],[LS_TOTAL CURRENT UNITS]]*INVESTORS_LIST[[#This Row],[NAV]]) -> 0 | AM649: =IF(INVESTORS_LIST[[#This Row],[SIP_TOTAL CURRENT UNITS]]=0,0,INVESTORS_LIST[[#This Row],[SIP_TOTAL CURRENT UNITS]]*INVESTORS_LIST[[#This Row],[NAV]]) -> 0 | AO649: =IF(INVESTORS_LIST[[#This Row],[TOTAL SELLABLE UNITS]]=0,0,INVESTORS_LIST[[#This Row],[TOTAL SELLABLE UNITS]]*INVESTORS_LIST[[#This Row],[NAV]]) -> 0 | AP649: =INVESTORS_LIST[[#This Row],[LS_TOTAL REALIZED GAIN]]+INVESTORS_LIST[[#This Row],[SIP_TOTAL REALIZED GAIN]] -> 0 | AQ649: =INVESTORS_LIST[[#This Row],[TOTAL MARKET VALUE]]-INVESTORS_LIST[[#This Row],[TOTAL COST VALUE OF CURRENT INVESTMENT]] -> 0 | AR649: =SUMIFS(DivAndTax[Tax Amount],DivAndTax[Investor ID],INVESTORS_LIST[[#This Row],[INVESTOR CODE]]) -> 0 | AS649: =SUMIFS(DivAndTax[Gross Dividend],DivAndTax[Investor ID],INVESTORS_LIST[[#This Row],[INVESTOR CODE]]) -> 0 | AT649: =IFERROR(INVESTORS_LIST[[#This Row],[TOTAL CURRENT UNITS]]/SUM(INVESTORS_LIST[TOTAL CURRENT UNITS]),0) -> 0
A650: K. M. ROHAN AHMED | B650: A00648 | C650: Dear Mr. | D650: Individual | E650: =SUMIFS(LS[Unit],LS[Investor ID],INVESTORS_LIST[[#This Row],[INVESTOR CODE]],LS[B/S],"B") -> 0 | F650: =-SUMIFS(LS[Unit],LS[Investor ID],INVESTORS_LIST[[#This Row],[INVESTOR CODE]],LS[B/S],"S") -> 0 | G650: =IF(INVESTORS_LIST[[#This Row],[LS_TOTAL UNITS BUY]]=0,0,INVESTORS_LIST[[#This Row],[LS_TOTAL UNITS BUY]]-INVESTORS_LIST[[#This Row],[LS_TOTAL UNITS SOLD]]) -> 0 | H650: =IF(INVESTORS_LIST[[#This Row],[LS_TOTAL UNITS BUY]]=0,0,SUMIFS(LS[Amount],LS[Investor ID],INVESTORS_LIST[[#This Row],[INVESTOR CODE]],LS[B/S],"B")) -> 0 | I650: =IF(INVESTORS_LIST[[#This Row],[LS_TOTAL UNITS SOLD]]=0,0,SUMIFS(LS[Cost of Units Sold],LS[Investor ID],INVESTORS_LIST[[#This Row],[INVESTOR CODE]],LS[B/S],"S")) -> 0 | J650: =IF(INVESTORS_LIST[[#This Row],[LS_TOTAL CURRENT UNITS]]=0,0,INVESTORS_LIST[[#This Row],[LS_TOTAL CURRENT UNITS]]*INVESTORS_LIST[[#This Row],[LS_AVERAGE COST]]) -> 0 | K650: =IF(INVESTORS_LIST[[#This Row],[LS_TOTAL UNITS SOLD]]=0,0,SUMIFS(LS[Realized Gain],LS[Investor ID],INVESTORS_LIST[[#This Row],[INVESTOR CODE]],LS[B/S],"S")) -> 0 | L650: =SUMIFS(SIP[Unit],SIP[Investor ID],INVESTORS_LIST[[#This Row],[INVESTOR CODE]],SIP[B/S],"B") -> 0 | M650: =-SUMIFS(SIP[Unit],SIP[Investor ID],INVESTORS_LIST[[#This Row],[INVESTOR CODE]],SIP[B/S],"S") -> 0 | N650: =IF(INVESTORS_LIST[[#This Row],[SIP_TOTAL UNITS BUY]]=0,0,INVESTORS_LIST[[#This Row],[SIP_TOTAL UNITS BUY]]-INVESTORS_LIST[[#This Row],[SIP_TOTAL UNITS SOLD]]) -> 0 | O650: =IF(INVESTORS_LIST[[#This Row],[SIP_TOTAL UNITS BUY]]=0,0,SUMIFS(SIP[Amount],SIP[Investor ID],INVESTORS_LIST[[#This Row],[INVESTOR CODE]],SIP[B/S],"B")) -> 0 | P650: =IF(INVESTORS_LIST[[#This Row],[SIP_TOTAL UNITS SOLD]]=0,0,SUMIFS(SIP[Cost of Units Sold],SIP[Investor ID],INVESTORS_LIST[[#This Row],[INVESTOR CODE]],SIP[B/S],"S")) -> 0 | Q650: =IF(INVESTORS_LIST[[#This Row],[SIP_TOTAL CURRENT UNITS]]=0,0,INVESTORS_LIST[[#This Row],[SIP_TOTAL CURRENT UNITS]]*INVESTORS_LIST[[#This Row],[SIP_AVERAGE COST]]) -> 0 | R650: =IF(INVESTORS_LIST[[#This Row],[SIP_TOTAL UNITS SOLD]]=0,0,SUMIFS(SIP[Realized Gain],SIP[Investor ID],INVESTORS_LIST[[#This Row],[INVESTOR CODE]],SIP[B/S],"S")) -> 0 | S650: =INVESTORS_LIST[[#This Row],[LS_TOTAL UNITS BUY]]+INVESTORS_LIST[[#This Row],[SIP_TOTAL UNITS BUY]] -> 0 | T650: =INVESTORS_LIST[[#This Row],[LS_TOTAL UNITS SOLD]]+INVESTORS_LIST[[#This Row],[SIP_TOTAL UNITS SOLD]] -> 0 | U650: 0 | V650: =SUMIFS(LS[BO UNIT TRANSFER],LS[Investor ID],INVESTORS_LIST[[#This Row],[INVESTOR CODE]],LS[B/S],"B") -> 0 | W650: =SUMIFS(LS[BO UNIT TRANSFER],LS[Investor ID],INVESTORS_LIST[[#This Row],[INVESTOR CODE]],LS[B/S],"S") -> 0 | X650: =SUMIFS(SIP[BO UNIT TRANSFER],SIP[Investor ID],INVESTORS_LIST[[#This Row],[INVESTOR CODE]],SIP[B/S],"S") -> 0 | Y650: =SUMIFS(SIP[BO UNIT TRANSFER],SIP[Investor ID],INVESTORS_LIST[[#This Row],[INVESTOR CODE]],SIP[B/S],"B") -> 0 | Z650: =INVESTORS_LIST[[#This Row],[BO OPENING BALANCE]]+INVESTORS_LIST[[#This Row],[LS- BO UNITS SELL]]+INVESTORS_LIST[[#This Row],[LS- BO UNITS REPURCHASE]]+INVESTORS_LIST[[#This Row],[SIP- BO UNITS REPURCHASE]]-INVESTORS_LIST[[#This Row],[SIP- BO UNITS SELL]] -> 0 | AA650: =INVESTORS_LIST[[#This Row],[TOTAL UNITS BUY]]-INVESTORS_LIST[[#This Row],[TOTAL UNITS SOLD]] -> 0 | AB650: =INVESTORS_LIST[[#This Row],[TOTAL CURRENT UNITS]]-INVESTORS_LIST[[#This Row],[BO UNITS HOLD]] -> 0 | AC650: =INDEX([4]!Table_1[BO ID],MATCH(INVESTORS_LIST[[#This Row],[INVESTOR CODE]],[4]!Table_1[INVESTOR CODE],0)) -> #REF! | AD650: =INVESTORS_LIST[[#This Row],[LS_TOTAL COST VALUE OF CURRENT UNITS]]+INVESTORS_LIST[[#This Row],[SIP_TOTAL COST VALUE OF CURRENT UNITS]] -> 0 | AE650: =IF(INVESTORS_LIST[[#This Row],[TOTAL CURRENT UNITS]]=0,0,INVESTORS_LIST[[#This Row],[LS_TOTAL CURRENT UNITS]]/INVESTORS_LIST[[#This Row],[TOTAL CURRENT UNITS]]) -> 0 | AF650: =IF(INVESTORS_LIST[[#This Row],[TOTAL CURRENT UNITS]]=0,0,INVESTORS_LIST[[#This Row],[SIP_TOTAL CURRENT UNITS]]/INVESTORS_LIST[[#This Row],[TOTAL CURRENT UNITS]]) -> 0 | AG650: {=IF(INVESTORS_LIST[[#This Row],[LS_TOTAL UNITS BUY]]>0,INDEX(LS[NAV at Cost (Average)],MATCH(CONCATENATE(COUNTIFS(LS[Investor ID],INVESTORS_LIST[[#This Row],[INVESTOR CODE]]),INVESTORS_LIST[[#This Row],[INVESTOR CODE]]),LS[Unique Code],0),),0)} -> 0 | AH650: {=IF(INVESTORS_LIST[[#This Row],[SIP_TOTAL UNITS BUY]]>0,INDEX(SIP[NAV at Cost (Average)],MATCH(CONCATENATE(COUNTIFS(SIP[Investor ID],INVESTORS_LIST[[#This Row],[INVESTOR CODE]]),INVESTORS_LIST[[#This Row],[INVESTOR CODE]]),SIP[Unique Code],0),),0)} -> 0 | AI650: =IF(INVESTORS_LIST[[#This Row],[TOTAL CURRENT UNITS]]=0,0,(INVESTORS_LIST[[#This Row],[LS_WEIGHT]]*INVESTORS_LIST[[#This Row],[LS_AVERAGE COST]])+(INVESTORS_LIST[[#This Row],[SIP_WEIGHT]]*INVESTORS_LIST[[#This Row],[SIP_AVERAGE COST]])) -> 0 | AJ650: =NAV_MKT -> 12.552 | AK650: =IF(INVESTORS_LIST[[#This Row],[TOTAL CURRENT UNITS]]=0,0,INVESTORS_LIST[[#This Row],[TOTAL CURRENT UNITS]]*INVESTORS_LIST[[#This Row],[NAV]]) -> 0 | AL650: =IF(INVESTORS_LIST[[#This Row],[LS_TOTAL CURRENT UNITS]]=0,0,INVESTORS_LIST[[#This Row],[LS_TOTAL CURRENT UNITS]]*INVESTORS_LIST[[#This Row],[NAV]]) -> 0 | AM650: =IF(INVESTORS_LIST[[#This Row],[SIP_TOTAL CURRENT UNITS]]=0,0,INVESTORS_LIST[[#This Row],[SIP_TOTAL CURRENT UNITS]]*INVESTORS_LIST[[#This Row],[NAV]]) -> 0 | AO650: =IF(INVESTORS_LIST[[#This Row],[TOTAL SELLABLE UNITS]]=0,0,INVESTORS_LIST[[#This Row],[TOTAL SELLABLE UNITS]]*INVESTORS_LIST[[#This Row],[NAV]]) -> 0 | AP650: =INVESTORS_LIST[[#This Row],[LS_TOTAL REALIZED GAIN]]+INVESTORS_LIST[[#This Row],[SIP_TOTAL REALIZED GAIN]] -> 0 | AQ650: =INVESTORS_LIST[[#This Row],[TOTAL MARKET VALUE]]-INVESTORS_LIST[[#This Row],[TOTAL COST VALUE OF CURRENT INVESTMENT]] -> 0 | AR650: =SUMIFS(DivAndTax[Tax Amount],DivAndTax[Investor ID],INVESTORS_LIST[[#This Row],[INVESTOR CODE]]) -> 0 | AS650: =SUMIFS(DivAndTax[Gross Dividend],DivAndTax[Investor ID],INVESTORS_LIST[[#This Row],[INVESTOR CODE]]) -> 0 | AT650: =IFERROR(INVESTORS_LIST[[#This Row],[TOTAL CURRENT UNITS]]/SUM(INVESTORS_LIST[TOTAL CURRENT UNITS]),0) -> 0
A651: AZAM KHAN | B651: A00649 | C651: Dear Mr. | D651: Individual | E651: =SUMIFS(LS[Unit],LS[Investor ID],INVESTORS_LIST[[#This Row],[INVESTOR CODE]],LS[B/S],"B") -> 0 | F651: =-SUMIFS(LS[Unit],LS[Investor ID],INVESTORS_LIST[[#This Row],[INVESTOR CODE]],LS[B/S],"S") -> 0 | G651: =IF(INVESTORS_LIST[[#This Row],[LS_TOTAL UNITS BUY]]=0,0,INVESTORS_LIST[[#This Row],[LS_TOTAL UNITS BUY]]-INVESTORS_LIST[[#This Row],[LS_TOTAL UNITS SOLD]]) -> 0 | H651: =IF(INVESTORS_LIST[[#This Row],[LS_TOTAL UNITS BUY]]=0,0,SUMIFS(LS[Amount],LS[Investor ID],INVESTORS_LIST[[#This Row],[INVESTOR CODE]],LS[B/S],"B")) -> 0 | I651: =IF(INVESTORS_LIST[[#This Row],[LS_TOTAL UNITS SOLD]]=0,0,SUMIFS(LS[Cost of Units Sold],LS[Investor ID],INVESTORS_LIST[[#This Row],[INVESTOR CODE]],LS[B/S],"S")) -> 0 | J651: =IF(INVESTORS_LIST[[#This Row],[LS_TOTAL CURRENT UNITS]]=0,0,INVESTORS_LIST[[#This Row],[LS_TOTAL CURRENT UNITS]]*INVESTORS_LIST[[#This Row],[LS_AVERAGE COST]]) -> 0 | K651: =IF(INVESTORS_LIST[[#This Row],[LS_TOTAL UNITS SOLD]]=0,0,SUMIFS(LS[Realized Gain],LS[Investor ID],INVESTORS_LIST[[#This Row],[INVESTOR CODE]],LS[B/S],"S")) -> 0 | L651: =SUMIFS(SIP[Unit],SIP[Investor ID],INVESTORS_LIST[[#This Row],[INVESTOR CODE]],SIP[B/S],"B") -> 0 | M651: =-SUMIFS(SIP[Unit],SIP[Investor ID],INVESTORS_LIST[[#This Row],[INVESTOR CODE]],SIP[B/S],"S") -> 0 | N651: =IF(INVESTORS_LIST[[#This Row],[SIP_TOTAL UNITS BUY]]=0,0,INVESTORS_LIST[[#This Row],[SIP_TOTAL UNITS BUY]]-INVESTORS_LIST[[#This Row],[SIP_TOTAL UNITS SOLD]]) -> 0 | O651: =IF(INVESTORS_LIST[[#This Row],[SIP_TOTAL UNITS BUY]]=0,0,SUMIFS(SIP[Amount],SIP[Investor ID],INVESTORS_LIST[[#This Row],[INVESTOR CODE]],SIP[B/S],"B")) -> 0 | P651: =IF(INVESTORS_LIST[[#This Row],[SIP_TOTAL UNITS SOLD]]=0,0,SUMIFS(SIP[Cost of Units Sold],SIP[Investor ID],INVESTORS_LIST[[#This Row],[INVESTOR CODE]],SIP[B/S],"S")) -> 0 | Q651: =IF(INVESTORS_LIST[[#This Row],[SIP_TOTAL CURRENT UNITS]]=0,0,INVESTORS_LIST[[#This Row],[SIP_TOTAL CURRENT UNITS]]*INVESTORS_LIST[[#This Row],[SIP_AVERAGE COST]]) -> 0 | R651: =IF(INVESTORS_LIST[[#This Row],[SIP_TOTAL UNITS SOLD]]=0,0,SUMIFS(SIP[Realized Gain],SIP[Investor ID],INVESTORS_LIST[[#This Row],[INVESTOR CODE]],SIP[B/S],"S")) -> 0 | S651: =INVESTORS_LIST[[#This Row],[LS_TOTAL UNITS BUY]]+INVESTORS_LIST[[#This Row],[SIP_TOTAL UNITS BUY]] -> 0 | T651: =INVESTORS_LIST[[#This Row],[LS_TOTAL UNITS SOLD]]+INVESTORS_LIST[[#This Row],[SIP_TOTAL UNITS SOLD]] -> 0 | U651: 0 | V651: =SUMIFS(LS[BO UNIT TRANSFER],LS[Investor ID],INVESTORS_LIST[[#This Row],[INVESTOR CODE]],LS[B/S],"B") -> 0 | W651: =SUMIFS(LS[BO UNIT TRANSFER],LS[Investor ID],INVESTORS_LIST[[#This Row],[INVESTOR CODE]],LS[B/S],"S") -> 0 | X651: =SUMIFS(SIP[BO UNIT TRANSFER],SIP[Investor ID],INVESTORS_LIST[[#This Row],[INVESTOR CODE]],SIP[B/S],"S") -> 0 | Y651: =SUMIFS(SIP[BO UNIT TRANSFER],SIP[Investor ID],INVESTORS_LIST[[#This Row],[INVESTOR CODE]],SIP[B/S],"B") -> 0 | Z651: =INVESTORS_LIST[[#This Row],[BO OPENING BALANCE]]+INVESTORS_LIST[[#This Row],[LS- BO UNITS SELL]]+INVESTORS_LIST[[#This Row],[LS- BO UNITS REPURCHASE]]+INVESTORS_LIST[[#This Row],[SIP- BO UNITS REPURCHASE]]-INVESTORS_LIST[[#This Row],[SIP- BO UNITS SELL]] -> 0 | AA651: =INVESTORS_LIST[[#This Row],[TOTAL UNITS BUY]]-INVESTORS_LIST[[#This Row],[TOTAL UNITS SOLD]] -> 0 | AB651: =INVESTORS_LIST[[#This Row],[TOTAL CURRENT UNITS]]-INVESTORS_LIST[[#This Row],[BO UNITS HOLD]] -> 0 | AC651: =INDEX([4]!Table_1[BO ID],MATCH(INVESTORS_LIST[[#This Row],[INVESTOR CODE]],[4]!Table_1[INVESTOR CODE],0)) -> #REF! | AD651: =INVESTORS_LIST[[#This Row],[LS_TOTAL COST VALUE OF CURRENT UNITS]]+INVESTORS_LIST[[#This Row],[SIP_TOTAL COST VALUE OF CURRENT UNITS]] -> 0 | AE651: =IF(INVESTORS_LIST[[#This Row],[TOTAL CURRENT UNITS]]=0,0,INVESTORS_LIST[[#This Row],[LS_TOTAL CURRENT UNITS]]/INVESTORS_LIST[[#This Row],[TOTAL CURRENT UNITS]]) -> 0 | AF651: =IF(INVESTORS_LIST[[#This Row],[TOTAL CURRENT UNITS]]=0,0,INVESTORS_LIST[[#This Row],[SIP_TOTAL CURRENT UNITS]]/INVESTORS_LIST[[#This Row],[TOTAL CURRENT UNITS]]) -> 0 | AG651: {=IF(INVESTORS_LIST[[#This Row],[LS_TOTAL UNITS BUY]]>0,INDEX(LS[NAV at Cost (Average)],MATCH(CONCATENATE(COUNTIFS(LS[Investor ID],INVESTORS_LIST[[#This Row],[INVESTOR CODE]]),INVESTORS_LIST[[#This Row],[INVESTOR CODE]]),LS[Unique Code],0),),0)} -> 0 | AH651: {=IF(INVESTORS_LIST[[#This Row],[SIP_TOTAL UNITS BUY]]>0,INDEX(SIP[NAV at Cost (Average)],MATCH(CONCATENATE(COUNTIFS(SIP[Investor ID],INVESTORS_LIST[[#This Row],[INVESTOR CODE]]),INVESTORS_LIST[[#This Row],[INVESTOR CODE]]),SIP[Unique Code],0),),0)} -> 0 | AI651: =IF(INVESTORS_LIST[[#This Row],[TOTAL CURRENT UNITS]]=0,0,(INVESTORS_LIST[[#This Row],[LS_WEIGHT]]*INVESTORS_LIST[[#This Row],[LS_AVERAGE COST]])+(INVESTORS_LIST[[#This Row],[SIP_WEIGHT]]*INVESTORS_LIST[[#This Row],[SIP_AVERAGE COST]])) -> 0 | AJ651: =NAV_MKT -> 12.552 | AK651: =IF(INVESTORS_LIST[[#This Row],[TOTAL CURRENT UNITS]]=0,0,INVESTORS_LIST[[#This Row],[TOTAL CURRENT UNITS]]*INVESTORS_LIST[[#This Row],[NAV]]) -> 0 | AL651: =IF(INVESTORS_LIST[[#This Row],[LS_TOTAL CURRENT UNITS]]=0,0,INVESTORS_LIST[[#This Row],[LS_TOTAL CURRENT UNITS]]*INVESTORS_LIST[[#This Row],[NAV]]) -> 0 | AM651: =IF(INVESTORS_LIST[[#This Row],[SIP_TOTAL CURRENT UNITS]]=0,0,INVESTORS_LIST[[#This Row],[SIP_TOTAL CURRENT UNITS]]*INVESTORS_LIST[[#This Row],[NAV]]) -> 0 | AO651: =IF(INVESTORS_LIST[[#This Row],[TOTAL SELLABLE UNITS]]=0,0,INVESTORS_LIST[[#This Row],[TOTAL SELLABLE UNITS]]*INVESTORS_LIST[[#This Row],[NAV]]) -> 0 | AP651: =INVESTORS_LIST[[#This Row],[LS_TOTAL REALIZED GAIN]]+INVESTORS_LIST[[#This Row],[SIP_TOTAL REALIZED GAIN]] -> 0 | AQ651: =INVESTORS_LIST[[#This Row],[TOTAL MARKET VALUE]]-INVESTORS_LIST[[#This Row],[TOTAL COST VALUE OF CURRENT INVESTMENT]] -> 0 | AR651: =SUMIFS(DivAndTax[Tax Amount],DivAndTax[Investor ID],INVESTORS_LIST[[#This Row],[INVESTOR CODE]]) -> 0 | AS651: =SUMIFS(DivAndTax[Gross Dividend],DivAndTax[Investor ID],INVESTORS_LIST[[#This Row],[INVESTOR CODE]]) -> 0 | AT651: =IFERROR(INVESTORS_LIST[[#This Row],[TOTAL CURRENT UNITS]]/SUM(INVESTORS_LIST[TOTAL CURRENT UNITS]),0) -> 0
A652: MD. MITHU HOWLADER | B652: A00650 | C652: Dear Mr. | D652: Individual | E652: =SUMIFS(LS[Unit],LS[Investor ID],INVESTORS_LIST[[#This Row],[INVESTOR CODE]],LS[B/S],"B") -> 413652 | F652: =-SUMIFS(LS[Unit],LS[Investor ID],INVESTORS_LIST[[#This Row],[INVESTOR CODE]],LS[B/S],"S") -> 0 | G652: =IF(INVESTORS_LIST[[#This Row],[LS_TOTAL UNITS BUY]]=0,0,INVESTORS_LIST[[#This Row],[LS_TOTAL UNITS BUY]]-INVESTORS_LIST[[#This Row],[LS_TOTAL UNITS SOLD]]) -> 413652 | H652: =IF(INVESTORS_LIST[[#This Row],[LS_TOTAL UNITS BUY]]=0,0,SUMIFS(LS[Amount],LS[Investor ID],INVESTORS_LIST[[#This Row],[INVESTOR CODE]],LS[B/S],"B")) -> 5000000 | I652: =IF(INVESTORS_LIST[[#This Row],[LS_TOTAL UNITS SOLD]]=0,0,SUMIFS(LS[Cost of Units Sold],LS[Investor ID],INVESTORS_LIST[[#This Row],[INVESTOR CODE]],LS[B/S],"S")) -> 0 | J652: =IF(INVESTORS_LIST[[#This Row],[LS_TOTAL CURRENT UNITS]]=0,0,INVESTORS_LIST[[#This Row],[LS_TOTAL CURRENT UNITS]]*INVESTORS_LIST[[#This Row],[LS_AVERAGE COST]]) -> 5000000 | K652: =IF(INVESTORS_LIST[[#This Row],[LS_TOTAL UNITS SOLD]]=0,0,SUMIFS(LS[Realized Gain],LS[Investor ID],INVESTORS_LIST[[#This Row],[INVESTOR CODE]],LS[B/S],"S")) -> 0 | L652: =SUMIFS(SIP[Unit],SIP[Investor ID],INVESTORS_LIST[[#This Row],[INVESTOR CODE]],SIP[B/S],"B") -> 0 | M652: =-SUMIFS(SIP[Unit],SIP[Investor ID],INVESTORS_LIST[[#This Row],[INVESTOR CODE]],SIP[B/S],"S") -> 0 | N652: =IF(INVESTORS_LIST[[#This Row],[SIP_TOTAL UNITS BUY]]=0,0,INVESTORS_LIST[[#This Row],[SIP_TOTAL UNITS BUY]]-INVESTORS_LIST[[#This Row],[SIP_TOTAL UNITS SOLD]]) -> 0 | O652: =IF(INVESTORS_LIST[[#This Row],[SIP_TOTAL UNITS BUY]]=0,0,SUMIFS(SIP[Amount],SIP[Investor ID],INVESTORS_LIST[[#This Row],[INVESTOR CODE]],SIP[B/S],"B")) -> 0 | P652: =IF(INVESTORS_LIST[[#This Row],[SIP_TOTAL UNITS SOLD]]=0,0,SUMIFS(SIP[Cost of Units Sold],SIP[Investor ID],INVESTORS_LIST[[#This Row],[INVESTOR CODE]],SIP[B/S],"S")) -> 0 | Q652: =IF(INVESTORS_LIST[[#This Row],[SIP_TOTAL CURRENT UNITS]]=0,0,INVESTORS_LIST[[#This Row],[SIP_TOTAL CURRENT UNITS]]*INVESTORS_LIST[[#This Row],[SIP_AVERAGE COST]]) -> 0 | R652: =IF(INVESTORS_LIST[[#This Row],[SIP_TOTAL UNITS SOLD]]=0,0,SUMIFS(SIP[Realized Gain],SIP[Investor ID],INVESTORS_LIST[[#This Row],[INVESTOR CODE]],SIP[B/S],"S")) -> 0 | S652: =INVESTORS_LIST[[#This Row],[LS_TOTAL UNITS BUY]]+INVESTORS_LIST[[#This Row],[SIP_TOTAL UNITS BUY]] -> 413652 | T652: =INVESTORS_LIST[[#This Row],[LS_TOTAL UNITS SOLD]]+INVESTORS_LIST[[#This Row],[SIP_TOTAL UNITS SOLD]] -> 0 | U652: 0 | V652: =SUMIFS(LS[BO UNIT TRANSFER],LS[Investor ID],INVESTORS_LIST[[#This Row],[INVESTOR CODE]],LS[B/S],"B") -> 413652 | W652: =SUMIFS(LS[BO UNIT TRANSFER],LS[Investor ID],INVESTORS_LIST[[#This Row],[INVESTOR CODE]],LS[B/S],"S") -> 0 | X652: =SUMIFS(SIP[BO UNIT TRANSFER],SIP[Investor ID],INVESTORS_LIST[[#This Row],[INVESTOR CODE]],SIP[B/S],"S") -> 0 | Y652: =SUMIFS(SIP[BO UNIT TRANSFER],SIP[Investor ID],INVESTORS_LIST[[#This Row],[INVESTOR CODE]],SIP[B/S],"B") -> 0 | Z652: =INVESTORS_LIST[[#This Row],[BO OPENING BALANCE]]+INVESTORS_LIST[[#This Row],[LS- BO UNITS SELL]]+INVESTORS_LIST[[#This Row],[LS- BO UNITS REPURCHASE]]+INVESTORS_LIST[[#This Row],[SIP- BO UNITS REPURCHASE]]-INVESTORS_LIST[[#This Row],[SIP- BO UNITS SELL]] -> 413652 | AA652: =INVESTORS_LIST[[#This Row],[TOTAL UNITS BUY]]-INVESTORS_LIST[[#This Row],[TOTAL UNITS SOLD]] -> 413652 | AB652: =INVESTORS_LIST[[#This Row],[TOTAL CURRENT UNITS]]-INVESTORS_LIST[[#This Row],[BO UNITS HOLD]] -> 0 | AC652: =INDEX([4]!Table_1[BO ID],MATCH(INVESTORS_LIST[[#This Row],[INVESTOR CODE]],[4]!Table_1[INVESTOR CODE],0)) -> #REF! | AD652: =INVESTORS_LIST[[#This Row],[LS_TOTAL COST VALUE OF CURRENT UNITS]]+INVESTORS_LIST[[#This Row],[SIP_TOTAL COST VALUE OF CURRENT UNITS]] -> 5000000 | AE652: =IF(INVESTORS_LIST[[#This Row],[TOTAL CURRENT UNITS]]=0,0,INVESTORS_LIST[[#This Row],[LS_TOTAL CURRENT UNITS]]/INVESTORS_LIST[[#This Row],[TOTAL CURRENT UNITS]]) -> 1 | AF652: =IF(INVESTORS_LIST[[#This Row],[TOTAL CURRENT UNITS]]=0,0,INVESTORS_LIST[[#This Row],[SIP_TOTAL CURRENT UNITS]]/INVESTORS_LIST[[#This Row],[TOTAL CURRENT UNITS]]) -> 0 | AG652: {=IF(INVESTORS_LIST[[#This Row],[LS_TOTAL UNITS BUY]]>0,INDEX(LS[NAV at Cost (Average)],MATCH(CONCATENATE(COUNTIFS(LS[Investor ID],INVESTORS_LIST[[#This Row],[INVESTOR CODE]]),INVESTORS_LIST[[#This Row],[INVESTOR CODE]]),LS[Unique Code],0),),0)} -> 12.087455 | AH652: {=IF(INVESTORS_LIST[[#This Row],[SIP_TOTAL UNITS BUY]]>0,INDEX(SIP[NAV at Cost (Average)],MATCH(CONCATENATE(COUNTIFS(SIP[Investor ID],INVESTORS_LIST[[#This Row],[INVESTOR CODE]]),INVESTORS_LIST[[#This Row],[INVESTOR CODE]]),SIP[Unique Code],0),),0)} -> 0 | AI652: =IF(INVESTORS_LIST[[#This Row],[TOTAL CURRENT UNITS]]=0,0,(INVESTORS_LIST[[#This Row],[LS_WEIGHT]]*INVESTORS_LIST[[#This Row],[LS_AVERAGE COST]])+(INVESTORS_LIST[[#This Row],[SIP_WEIGHT]]*INVESTORS_LIST[[#This Row],[SIP_AVERAGE COST]])) -> 12.087455 | AJ652: =NAV_MKT -> 12.552 | AK652: =IF(INVESTORS_LIST[[#This Row],[TOTAL CURRENT UNITS]]=0,0,INVESTORS_LIST[[#This Row],[TOTAL CURRENT UNITS]]*INVESTORS_LIST[[#This Row],[NAV]]) -> 5192159.9 | AL652: =IF(INVESTORS_LIST[[#This Row],[LS_TOTAL CURRENT UNITS]]=0,0,INVESTORS_LIST[[#This Row],[LS_TOTAL CURRENT UNITS]]*INVESTORS_LIST[[#This Row],[NAV]]) -> 5192159.9 | AM652: =IF(INVESTORS_LIST[[#This Row],[SIP_TOTAL CURRENT UNITS]]=0,0,INVESTORS_LIST[[#This Row],[SIP_TOTAL CURRENT UNITS]]*INVESTORS_LIST[[#This Row],[NAV]]) -> 0 | AO652: =IF(INVESTORS_LIST[[#This Row],[TOTAL SELLABLE UNITS]]=0,0,INVESTORS_LIST[[#This Row],[TOTAL SELLABLE UNITS]]*INVESTORS_LIST[[#This Row],[NAV]]) -> 0 | AP652: =INVESTORS_LIST[[#This Row],[LS_TOTAL REALIZED GAIN]]+INVESTORS_LIST[[#This Row],[SIP_TOTAL REALIZED GAIN]] -> 0 | AQ652: =INVESTORS_LIST[[#This Row],[TOTAL MARKET VALUE]]-INVESTORS_LIST[[#This Row],[TOTAL COST VALUE OF CURRENT INVESTMENT]] -> 192159.9 | AR652: =SUMIFS(DivAndTax[Tax Amount],DivAndTax[Investor ID],INVESTORS_LIST[[#This Row],[INVESTOR CODE]]) -> 0 | AS652: =SUMIFS(DivAndTax[Gross Dividend],DivAndTax[Investor ID],INVESTORS_LIST[[#This Row],[INVESTOR CODE]]) -> 0 | AT652: =IFERROR(INVESTORS_LIST[[#This Row],[TOTAL CURRENT UNITS]]/SUM(INVESTORS_LIST[TOTAL CURRENT UNITS]),0) -> 0.019832477
A653: ANJUMAN ARA BEGUM POLY | B653: A00651 | C653: Dear Ms. | D653: Individual | E653: =SUMIFS(LS[Unit],LS[Investor ID],INVESTORS_LIST[[#This Row],[INVESTOR CODE]],LS[B/S],"B") -> 0 | F653: =-SUMIFS(LS[Unit],LS[Investor ID],INVESTORS_LIST[[#This Row],[INVESTOR CODE]],LS[B/S],"S") -> 0 | G653: =IF(INVESTORS_LIST[[#This Row],[LS_TOTAL UNITS BUY]]=0,0,INVESTORS_LIST[[#This Row],[LS_TOTAL UNITS BUY]]-INVESTORS_LIST[[#This Row],[LS_TOTAL UNITS SOLD]]) -> 0 | H653: =IF(INVESTORS_LIST[[#This Row],[LS_TOTAL UNITS BUY]]=0,0,SUMIFS(LS[Amount],LS[Investor ID],INVESTORS_LIST[[#This Row],[INVESTOR CODE]],LS[B/S],"B")) -> 0 | I653: =IF(INVESTORS_LIST[[#This Row],[LS_TOTAL UNITS SOLD]]=0,0,SUMIFS(LS[Cost of Units Sold],LS[Investor ID],INVESTORS_LIST[[#This Row],[INVESTOR CODE]],LS[B/S],"S")) -> 0 | J653: =IF(INVESTORS_LIST[[#This Row],[LS_TOTAL CURRENT UNITS]]=0,0,INVESTORS_LIST[[#This Row],[LS_TOTAL CURRENT UNITS]]*INVESTORS_LIST[[#This Row],[LS_AVERAGE COST]]) -> 0 | K653: =IF(INVESTORS_LIST[[#This Row],[LS_TOTAL UNITS SOLD]]=0,0,SUMIFS(LS[Realized Gain],LS[Investor ID],INVESTORS_LIST[[#This Row],[INVESTOR CODE]],LS[B/S],"S")) -> 0 | L653: =SUMIFS(SIP[Unit],SIP[Investor ID],INVESTORS_LIST[[#This Row],[INVESTOR CODE]],SIP[B/S],"B") -> 0 | M653: =-SUMIFS(SIP[Unit],SIP[Investor ID],INVESTORS_LIST[[#This Row],[INVESTOR CODE]],SIP[B/S],"S") -> 0 | N653: =IF(INVESTORS_LIST[[#This Row],[SIP_TOTAL UNITS BUY]]=0,0,INVESTORS_LIST[[#This Row],[SIP_TOTAL UNITS BUY]]-INVESTORS_LIST[[#This Row],[SIP_TOTAL UNITS SOLD]]) -> 0 | O653: =IF(INVESTORS_LIST[[#This Row],[SIP_TOTAL UNITS BUY]]=0,0,SUMIFS(SIP[Amount],SIP[Investor ID],INVESTORS_LIST[[#This Row],[INVESTOR CODE]],SIP[B/S],"B")) -> 0 | P653: =IF(INVESTORS_LIST[[#This Row],[SIP_TOTAL UNITS SOLD]]=0,0,SUMIFS(SIP[Cost of Units Sold],SIP[Investor ID],INVESTORS_LIST[[#This Row],[INVESTOR CODE]],SIP[B/S],"S")) -> 0 | Q653: =IF(INVESTORS_LIST[[#This Row],[SIP_TOTAL CURRENT UNITS]]=0,0,INVESTORS_LIST[[#This Row],[SIP_TOTAL CURRENT UNITS]]*INVESTORS_LIST[[#This Row],[SIP_AVERAGE COST]]) -> 0 | R653: =IF(INVESTORS_LIST[[#This Row],[SIP_TOTAL UNITS SOLD]]=0,0,SUMIFS(SIP[Realized Gain],SIP[Investor ID],INVESTORS_LIST[[#This Row],[INVESTOR CODE]],SIP[B/S],"S")) -> 0 | S653: =INVESTORS_LIST[[#This Row],[LS_TOTAL UNITS BUY]]+INVESTORS_LIST[[#This Row],[SIP_TOTAL UNITS BUY]] -> 0 | T653: =INVESTORS_LIST[[#This Row],[LS_TOTAL UNITS SOLD]]+INVESTORS_LIST[[#This Row],[SIP_TOTAL UNITS SOLD]] -> 0 | U653: 0 | V653: =SUMIFS(LS[BO UNIT TRANSFER],LS[Investor ID],INVESTORS_LIST[[#This Row],[INVESTOR CODE]],LS[B/S],"B") -> 0 | W653: =SUMIFS(LS[BO UNIT TRANSFER],LS[Investor ID],INVESTORS_LIST[[#This Row],[INVESTOR CODE]],LS[B/S],"S") -> 0 | X653: =SUMIFS(SIP[BO UNIT TRANSFER],SIP[Investor ID],INVESTORS_LIST[[#This Row],[INVESTOR CODE]],SIP[B/S],"S") -> 0 | Y653: =SUMIFS(SIP[BO UNIT TRANSFER],SIP[Investor ID],INVESTORS_LIST[[#This Row],[INVESTOR CODE]],SIP[B/S],"B") -> 0 | Z653: =INVESTORS_LIST[[#This Row],[BO OPENING BALANCE]]+INVESTORS_LIST[[#This Row],[LS- BO UNITS SELL]]+INVESTORS_LIST[[#This Row],[LS- BO UNITS REPURCHASE]]+INVESTORS_LIST[[#This Row],[SIP- BO UNITS REPURCHASE]]-INVESTORS_LIST[[#This Row],[SIP- BO UNITS SELL]] -> 0 | AA653: =INVESTORS_LIST[[#This Row],[TOTAL UNITS BUY]]-INVESTORS_LIST[[#This Row],[TOTAL UNITS SOLD]] -> 0 | AB653: =INVESTORS_LIST[[#This Row],[TOTAL CURRENT UNITS]]-INVESTORS_LIST[[#This Row],[BO UNITS HOLD]] -> 0 | AC653: =INDEX([4]!Table_1[BO ID],MATCH(INVESTORS_LIST[[#This Row],[INVESTOR CODE]],[4]!Table_1[INVESTOR CODE],0)) -> #REF! | AD653: =INVESTORS_LIST[[#This Row],[LS_TOTAL COST VALUE OF CURRENT UNITS]]+INVESTORS_LIST[[#This Row],[SIP_TOTAL COST VALUE OF CURRENT UNITS]] -> 0 | AE653: =IF(INVESTORS_LIST[[#This Row],[TOTAL CURRENT UNITS]]=0,0,INVESTORS_LIST[[#This Row],[LS_TOTAL CURRENT UNITS]]/INVESTORS_LIST[[#This Row],[TOTAL CURRENT UNITS]]) -> 0 | AF653: =IF(INVESTORS_LIST[[#This Row],[TOTAL CURRENT UNITS]]=0,0,INVESTORS_LIST[[#This Row],[SIP_TOTAL CURRENT UNITS]]/INVESTORS_LIST[[#This Row],[TOTAL CURRENT UNITS]]) -> 0 | AG653: {=IF(INVESTORS_LIST[[#This Row],[LS_TOTAL UNITS BUY]]>0,INDEX(LS[NAV at Cost (Average)],MATCH(CONCATENATE(COUNTIFS(LS[Investor ID],INVESTORS_LIST[[#This Row],[INVESTOR CODE]]),INVESTORS_LIST[[#This Row],[INVESTOR CODE]]),LS[Unique Code],0),),0)} -> 0 | AH653: {=IF(INVESTORS_LIST[[#This Row],[SIP_TOTAL UNITS BUY]]>0,INDEX(SIP[NAV at Cost (Average)],MATCH(CONCATENATE(COUNTIFS(SIP[Investor ID],INVESTORS_LIST[[#This Row],[INVESTOR CODE]]),INVESTORS_LIST[[#This Row],[INVESTOR CODE]]),SIP[Unique Code],0),),0)} -> 0 | AI653: =IF(INVESTORS_LIST[[#This Row],[TOTAL CURRENT UNITS]]=0,0,(INVESTORS_LIST[[#This Row],[LS_WEIGHT]]*INVESTORS_LIST[[#This Row],[LS_AVERAGE COST]])+(INVESTORS_LIST[[#This Row],[SIP_WEIGHT]]*INVESTORS_LIST[[#This Row],[SIP_AVERAGE COST]])) -> 0 | AJ653: =NAV_MKT -> 12.552 | AK653: =IF(INVESTORS_LIST[[#This Row],[TOTAL CURRENT UNITS]]=0,0,INVESTORS_LIST[[#This Row],[TOTAL CURRENT UNITS]]*INVESTORS_LIST[[#This Row],[NAV]]) -> 0 | AL653: =IF(INVESTORS_LIST[[#This Row],[LS_TOTAL CURRENT UNITS]]=0,0,INVESTORS_LIST[[#This Row],[LS_TOTAL CURRENT UNITS]]*INVESTORS_LIST[[#This Row],[NAV]]) -> 0 | AM653: =IF(INVESTORS_LIST[[#This Row],[SIP_TOTAL CURRENT UNITS]]=0,0,INVESTORS_LIST[[#This Row],[SIP_TOTAL CURRENT UNITS]]*INVESTORS_LIST[[#This Row],[NAV]]) -> 0 | AO653: =IF(INVESTORS_LIST[[#This Row],[TOTAL SELLABLE UNITS]]=0,0,INVESTORS_LIST[[#This Row],[TOTAL SELLABLE UNITS]]*INVESTORS_LIST[[#This Row],[NAV]]) -> 0 | AP653: =INVESTORS_LIST[[#This Row],[LS_TOTAL REALIZED GAIN]]+INVESTORS_LIST[[#This Row],[SIP_TOTAL REALIZED GAIN]] -> 0 | AQ653: =INVESTORS_LIST[[#This Row],[TOTAL MARKET VALUE]]-INVESTORS_LIST[[#This Row],[TOTAL COST VALUE OF CURRENT INVESTMENT]] -> 0 | AR653: =SUMIFS(DivAndTax[Tax Amount],DivAndTax[Investor ID],INVESTORS_LIST[[#This Row],[INVESTOR CODE]]) -> 0 | AS653: =SUMIFS(DivAndTax[Gross Dividend],DivAndTax[Investor ID],INVESTORS_LIST[[#This Row],[INVESTOR CODE]]) -> 0 | AT653: =IFERROR(INVESTORS_LIST[[#This Row],[TOTAL CURRENT UNITS]]/SUM(INVESTORS_LIST[TOTAL CURRENT UNITS]),0) -> 0
A654: NASREEN BEGUM | B654: A00652 | C654: Dear Ms. | D654: Individual | E654: =SUMIFS(LS[Unit],LS[Investor ID],INVESTORS_LIST[[#This Row],[INVESTOR CODE]],LS[B/S],"B") -> 0 | F654: =-SUMIFS(LS[Unit],LS[Investor ID],INVESTORS_LIST[[#This Row],[INVESTOR CODE]],LS[B/S],"S") -> 0 | G654: =IF(INVESTORS_LIST[[#This Row],[LS_TOTAL UNITS BUY]]=0,0,INVESTORS_LIST[[#This Row],[LS_TOTAL UNITS BUY]]-INVESTORS_LIST[[#This Row],[LS_TOTAL UNITS SOLD]]) -> 0 | H654: =IF(INVESTORS_LIST[[#This Row],[LS_TOTAL UNITS BUY]]=0,0,SUMIFS(LS[Amount],LS[Investor ID],INVESTORS_LIST[[#This Row],[INVESTOR CODE]],LS[B/S],"B")) -> 0 | I654: =IF(INVESTORS_LIST[[#This Row],[LS_TOTAL UNITS SOLD]]=0,0,SUMIFS(LS[Cost of Units Sold],LS[Investor ID],INVESTORS_LIST[[#This Row],[INVESTOR CODE]],LS[B/S],"S")) -> 0 | J654: =IF(INVESTORS_LIST[[#This Row],[LS_TOTAL CURRENT UNITS]]=0,0,INVESTORS_LIST[[#This Row],[LS_TOTAL CURRENT UNITS]]*INVESTORS_LIST[[#This Row],[LS_AVERAGE COST]]) -> 0 | K654: =IF(INVESTORS_LIST[[#This Row],[LS_TOTAL UNITS SOLD]]=0,0,SUMIFS(LS[Realized Gain],LS[Investor ID],INVESTORS_LIST[[#This Row],[INVESTOR CODE]],LS[B/S],"S")) -> 0 | L654: =SUMIFS(SIP[Unit],SIP[Investor ID],INVESTORS_LIST[[#This Row],[INVESTOR CODE]],SIP[B/S],"B") -> 0 | M654: =-SUMIFS(SIP[Unit],SIP[Investor ID],INVESTORS_LIST[[#This Row],[INVESTOR CODE]],SIP[B/S],"S") -> 0 | N654: =IF(INVESTORS_LIST[[#This Row],[SIP_TOTAL UNITS BUY]]=0,0,INVESTORS_LIST[[#This Row],[SIP_TOTAL UNITS BUY]]-INVESTORS_LIST[[#This Row],[SIP_TOTAL UNITS SOLD]]) -> 0 | O654: =IF(INVESTORS_LIST[[#This Row],[SIP_TOTAL UNITS BUY]]=0,0,SUMIFS(SIP[Amount],SIP[Investor ID],INVESTORS_LIST[[#This Row],[INVESTOR CODE]],SIP[B/S],"B")) -> 0 | P654: =IF(INVESTORS_LIST[[#This Row],[SIP_TOTAL UNITS SOLD]]=0,0,SUMIFS(SIP[Cost of Units Sold],SIP[Investor ID],INVESTORS_LIST[[#This Row],[INVESTOR CODE]],SIP[B/S],"S")) -> 0 | Q654: =IF(INVESTORS_LIST[[#This Row],[SIP_TOTAL CURRENT UNITS]]=0,0,INVESTORS_LIST[[#This Row],[SIP_TOTAL CURRENT UNITS]]*INVESTORS_LIST[[#This Row],[SIP_AVERAGE COST]]) -> 0 | R654: =IF(INVESTORS_LIST[[#This Row],[SIP_TOTAL UNITS SOLD]]=0,0,SUMIFS(SIP[Realized Gain],SIP[Investor ID],INVESTORS_LIST[[#This Row],[INVESTOR CODE]],SIP[B/S],"S")) -> 0 | S654: =INVESTORS_LIST[[#This Row],[LS_TOTAL UNITS BUY]]+INVESTORS_LIST[[#This Row],[SIP_TOTAL UNITS BUY]] -> 0 | T654: =INVESTORS_LIST[[#This Row],[LS_TOTAL UNITS SOLD]]+INVESTORS_LIST[[#This Row],[SIP_TOTAL UNITS SOLD]] -> 0 | U654: 0 | V654: =SUMIFS(LS[BO UNIT TRANSFER],LS[Investor ID],INVESTORS_LIST[[#This Row],[INVESTOR CODE]],LS[B/S],"B") -> 0 | W654: =SUMIFS(LS[BO UNIT TRANSFER],LS[Investor ID],INVESTORS_LIST[[#This Row],[INVESTOR CODE]],LS[B/S],"S") -> 0 | X654: =SUMIFS(SIP[BO UNIT TRANSFER],SIP[Investor ID],INVESTORS_LIST[[#This Row],[INVESTOR CODE]],SIP[B/S],"S") -> 0 | Y654: =SUMIFS(SIP[BO UNIT TRANSFER],SIP[Investor ID],INVESTORS_LIST[[#This Row],[INVESTOR CODE]],SIP[B/S],"B") -> 0 | Z654: =INVESTORS_LIST[[#This Row],[BO OPENING BALANCE]]+INVESTORS_LIST[[#This Row],[LS- BO UNITS SELL]]+INVESTORS_LIST[[#This Row],[LS- BO UNITS REPURCHASE]]+INVESTORS_LIST[[#This Row],[SIP- BO UNITS REPURCHASE]]-INVESTORS_LIST[[#This Row],[SIP- BO UNITS SELL]] -> 0 | AA654: =INVESTORS_LIST[[#This Row],[TOTAL UNITS BUY]]-INVESTORS_LIST[[#This Row],[TOTAL UNITS SOLD]] -> 0 | AB654: =INVESTORS_LIST[[#This Row],[TOTAL CURRENT UNITS]]-INVESTORS_LIST[[#This Row],[BO UNITS HOLD]] -> 0 | AC654: =INDEX([4]!Table_1[BO ID],MATCH(INVESTORS_LIST[[#This Row],[INVESTOR CODE]],[4]!Table_1[INVESTOR CODE],0)) -> #REF! | AD654: =INVESTORS_LIST[[#This Row],[LS_TOTAL COST VALUE OF CURRENT UNITS]]+INVESTORS_LIST[[#This Row],[SIP_TOTAL COST VALUE OF CURRENT UNITS]] -> 0 | AE654: =IF(INVESTORS_LIST[[#This Row],[TOTAL CURRENT UNITS]]=0,0,INVESTORS_LIST[[#This Row],[LS_TOTAL CURRENT UNITS]]/INVESTORS_LIST[[#This Row],[TOTAL CURRENT UNITS]]) -> 0 | AF654: =IF(INVESTORS_LIST[[#This Row],[TOTAL CURRENT UNITS]]=0,0,INVESTORS_LIST[[#This Row],[SIP_TOTAL CURRENT UNITS]]/INVESTORS_LIST[[#This Row],[TOTAL CURRENT UNITS]]) -> 0 | AG654: {=IF(INVESTORS_LIST[[#This Row],[LS_TOTAL UNITS BUY]]>0,INDEX(LS[NAV at Cost (Average)],MATCH(CONCATENATE(COUNTIFS(LS[Investor ID],INVESTORS_LIST[[#This Row],[INVESTOR CODE]]),INVESTORS_LIST[[#This Row],[INVESTOR CODE]]),LS[Unique Code],0),),0)} -> 0 | AH654: {=IF(INVESTORS_LIST[[#This Row],[SIP_TOTAL UNITS BUY]]>0,INDEX(SIP[NAV at Cost (Average)],MATCH(CONCATENATE(COUNTIFS(SIP[Investor ID],INVESTORS_LIST[[#This Row],[INVESTOR CODE]]),INVESTORS_LIST[[#This Row],[INVESTOR CODE]]),SIP[Unique Code],0),),0)} -> 0 | AI654: =IF(INVESTORS_LIST[[#This Row],[TOTAL CURRENT UNITS]]=0,0,(INVESTORS_LIST[[#This Row],[LS_WEIGHT]]*INVESTORS_LIST[[#This Row],[LS_AVERAGE COST]])+(INVESTORS_LIST[[#This Row],[SIP_WEIGHT]]*INVESTORS_LIST[[#This Row],[SIP_AVERAGE COST]])) -> 0 | AJ654: =NAV_MKT -> 12.552 | AK654: =IF(INVESTORS_LIST[[#This Row],[TOTAL CURRENT UNITS]]=0,0,INVESTORS_LIST[[#This Row],[TOTAL CURRENT UNITS]]*INVESTORS_LIST[[#This Row],[NAV]]) -> 0 | AL654: =IF(INVESTORS_LIST[[#This Row],[LS_TOTAL CURRENT UNITS]]=0,0,INVESTORS_LIST[[#This Row],[LS_TOTAL CURRENT UNITS]]*INVESTORS_LIST[[#This Row],[NAV]]) -> 0 | AM654: =IF(INVESTORS_LIST[[#This Row],[SIP_TOTAL CURRENT UNITS]]=0,0,INVESTORS_LIST[[#This Row],[SIP_TOTAL CURRENT UNITS]]*INVESTORS_LIST[[#This Row],[NAV]]) -> 0 | AO654: =IF(INVESTORS_LIST[[#This Row],[TOTAL SELLABLE UNITS]]=0,0,INVESTORS_LIST[[#This Row],[TOTAL SELLABLE UNITS]]*INVESTORS_LIST[[#This Row],[NAV]]) -> 0 | AP654: =INVESTORS_LIST[[#This Row],[LS_TOTAL REALIZED GAIN]]+INVESTORS_LIST[[#This Row],[SIP_TOTAL REALIZED GAIN]] -> 0 | AQ654: =INVESTORS_LIST[[#This Row],[TOTAL MARKET VALUE]]-INVESTORS_LIST[[#This Row],[TOTAL COST VALUE OF CURRENT INVESTMENT]] -> 0 | AR654: =SUMIFS(DivAndTax[Tax Amount],DivAndTax[Investor ID],INVESTORS_LIST[[#This Row],[INVESTOR CODE]]) -> 0 | AS654: =SUMIFS(DivAndTax[Gross Dividend],DivAndTax[Investor ID],INVESTORS_LIST[[#This Row],[INVESTOR CODE]]) -> 0 | AT654: =IFERROR(INVESTORS_LIST[[#This Row],[TOTAL CURRENT UNITS]]/SUM(INVESTORS_LIST[TOTAL CURRENT UNITS]),0) -> 0
... A708: AL-FARABI AKASH | B708: BR0002 | C708: Dear Mr. | D708: Individual | E708: =SUMIFS(LS[Unit],LS[Investor ID],INVESTORS_LIST[[#This Row],[INVESTOR CODE]],LS[B/S],"B") -> 0 | F708: =-SUMIFS(LS[Unit],LS[Investor ID],INVESTORS_LIST[[#This Row],[INVESTOR CODE]],LS[B/S],"S") -> 0 | G708: =IF(INVESTORS_LIST[[#This Row],[LS_TOTAL UNITS BUY]]=0,0,INVESTORS_LIST[[#This Row],[LS_TOTAL UNITS BUY]]-INVESTORS_LIST[[#This Row],[LS_TOTAL UNITS SOLD]]) -> 0 | H708: =IF(INVESTORS_LIST[[#This Row],[LS_TOTAL UNITS BUY]]=0,0,SUMIFS(LS[Amount],LS[Investor ID],INVESTORS_LIST[[#This Row],[INVESTOR CODE]],LS[B/S],"B")) -> 0 | I708: =IF(INVESTORS_LIST[[#This Row],[LS_TOTAL UNITS SOLD]]=0,0,SUMIFS(LS[Cost of Units Sold],LS[Investor ID],INVESTORS_LIST[[#This Row],[INVESTOR CODE]],LS[B/S],"S")) -> 0 | J708: =IF(INVESTORS_LIST[[#This Row],[LS_TOTAL CURRENT UNITS]]=0,0,INVESTORS_LIST[[#This Row],[LS_TOTAL CURRENT UNITS]]*INVESTORS_LIST[[#This Row],[LS_AVERAGE COST]]) -> 0 | K708: =IF(INVESTORS_LIST[[#This Row],[LS_TOTAL UNITS SOLD]]=0,0,SUMIFS(LS[Realized Gain],LS[Investor ID],INVESTORS_LIST[[#This Row],[INVESTOR CODE]],LS[B/S],"S")) -> 0 | L708: =SUMIFS(SIP[Unit],SIP[Investor ID],INVESTORS_LIST[[#This Row],[INVESTOR CODE]],SIP[B/S],"B") -> 151 | M708: =-SUMIFS(SIP[Unit],SIP[Investor ID],INVESTORS_LIST[[#This Row],[INVESTOR CODE]],SIP[B/S],"S") -> 0 | N708: =IF(INVESTORS_LIST[[#This Row],[SIP_TOTAL UNITS BUY]]=0,0,INVESTORS_LIST[[#This Row],[SIP_TOTAL UNITS BUY]]-INVESTORS_LIST[[#This Row],[SIP_TOTAL UNITS SOLD]]) -> 151 | O708: =IF(INVESTORS_LIST[[#This Row],[SIP_TOTAL UNITS BUY]]=0,0,SUMIFS(SIP[Amount],SIP[Investor ID],INVESTORS_LIST[[#This Row],[INVESTOR CODE]],SIP[B/S],"B")) -> 2000 | P708: =IF(INVESTORS_LIST[[#This Row],[SIP_TOTAL UNITS SOLD]]=0,0,SUMIFS(SIP[Cost of Units Sold],SIP[Investor ID],INVESTORS_LIST[[#This Row],[INVESTOR CODE]],SIP[B/S],"S")) -> 0 | Q708: =IF(INVESTORS_LIST[[#This Row],[SIP_TOTAL CURRENT UNITS]]=0,0,INVESTORS_LIST[[#This Row],[SIP_TOTAL CURRENT UNITS]]*INVESTORS_LIST[[#This Row],[SIP_AVERAGE COST]]) -> 2000 | R708: =IF(INVESTORS_LIST[[#This Row],[SIP_TOTAL UNITS SOLD]]=0,0,SUMIFS(SIP[Realized Gain],SIP[Investor ID],INVESTORS_LIST[[#This Row],[INVESTOR CODE]],SIP[B/S],"S")) -> 0 | S708: =INVESTORS_LIST[[#This Row],[LS_TOTAL UNITS BUY]]+INVESTORS_LIST[[#This Row],[SIP_TOTAL UNITS BUY]] -> 151 | T708: =INVESTORS_LIST[[#This Row],[LS_TOTAL UNITS SOLD]]+INVESTORS_LIST[[#This Row],[SIP_TOTAL UNITS SOLD]] -> 0 | U708: 0 | V708: =SUMIFS(LS[BO UNIT TRANSFER],LS[Investor ID],INVESTORS_LIST[[#This Row],[INVESTOR CODE]],LS[B/S],"B") -> 0 | W708: =SUMIFS(LS[BO UNIT TRANSFER],LS[Investor ID],INVESTORS_LIST[[#This Row],[INVESTOR CODE]],LS[B/S],"S") -> 0 | X708: =SUMIFS(SIP[BO UNIT TRANSFER],SIP[Investor ID],INVESTORS_LIST[[#This Row],[INVESTOR CODE]],SIP[B/S],"S") -> 0 | Y708: =SUMIFS(SIP[BO UNIT TRANSFER],SIP[Investor ID],INVESTORS_LIST[[#This Row],[INVESTOR CODE]],SIP[B/S],"B") -> 80 | Z708: =INVESTORS_LIST[[#This Row],[BO OPENING BALANCE]]+INVESTORS_LIST[[#This Row],[LS- BO UNITS SELL]]+INVESTORS_LIST[[#This Row],[LS- BO UNITS REPURCHASE]]+INVESTORS_LIST[[#This Row],[SIP- BO UNITS REPURCHASE]]-INVESTORS_LIST[[#This Row],[SIP- BO UNITS SELL]] -> 80 | AA708: =INVESTORS_LIST[[#This Row],[TOTAL UNITS BUY]]-INVESTORS_LIST[[#This Row],[TOTAL UNITS SOLD]] -> 151 | AB708: =INVESTORS_LIST[[#This Row],[TOTAL CURRENT UNITS]]-INVESTORS_LIST[[#This Row],[BO UNITS HOLD]] -> 71 | AC708: =INDEX([4]!Table_1[BO ID],MATCH(INVESTORS_LIST[[#This Row],[INVESTOR CODE]],[4]!Table_1[INVESTOR CODE],0)) -> #REF! | AD708: =INVESTORS_LIST[[#This Row],[LS_TOTAL COST VALUE OF CURRENT UNITS]]+INVESTORS_LIST[[#This Row],[SIP_TOTAL COST VALUE OF CURRENT UNITS]] -> 2000 | AE708: =IF(INVESTORS_LIST[[#This Row],[TOTAL CURRENT UNITS]]=0,0,INVESTORS_LIST[[#This Row],[LS_TOTAL CURRENT UNITS]]/INVESTORS_LIST[[#This Row],[TOTAL CURRENT UNITS]]) -> 0 | AF708: =IF(INVESTORS_LIST[[#This Row],[TOTAL CURRENT UNITS]]=0,0,INVESTORS_LIST[[#This Row],[SIP_TOTAL CURRENT UNITS]]/INVESTORS_LIST[[#This Row],[TOTAL CURRENT UNITS]]) -> 1 | AG708: {=IF(INVESTORS_LIST[[#This Row],[LS_TOTAL UNITS BUY]]>0,INDEX(LS[NAV at Cost (Average)],MATCH(CONCATENATE(COUNTIFS(LS[Investor ID],INVESTORS_LIST[[#This Row],[INVESTOR CODE]]),INVESTORS_LIST[[#This Row],[INVESTOR CODE]]),LS[Unique Code],0),),0)} -> 0 | AH708: {=IF(INVESTORS_LIST[[#This Row],[SIP_TOTAL UNITS BUY]]>0,INDEX(SIP[NAV at Cost (Average)],MATCH(CONCATENATE(COUNTIFS(SIP[Investor ID],INVESTORS_LIST[[#This Row],[INVESTOR CODE]]),INVESTORS_LIST[[#This Row],[INVESTOR CODE]]),SIP[Unique Code],0),),0)} -> 13.245033 | AI708: =IF(INVESTORS_LIST[[#This Row],[TOTAL CURRENT UNITS]]=0,0,(INVESTORS_LIST[[#This Row],[LS_WEIGHT]]*INVESTORS_LIST[[#This Row],[LS_AVERAGE COST]])+(INVESTORS_LIST[[#This Row],[SIP_WEIGHT]]*INVESTORS_LIST[[#This Row],[SIP_AVERAGE COST]])) -> 13.245033 | AJ708: =NAV_MKT -> 12.552 | AK708: =IF(INVESTORS_LIST[[#This Row],[TOTAL CURRENT UNITS]]=0,0,INVESTORS_LIST[[#This Row],[TOTAL CURRENT UNITS]]*INVESTORS_LIST[[#This Row],[NAV]]) -> 1895.352 | AL708: =IF(INVESTORS_LIST[[#This Row],[LS_TOTAL CURRENT UNITS]]=0,0,INVESTORS_LIST[[#This Row],[LS_TOTAL CURRENT UNITS]]*INVESTORS_LIST[[#This Row],[NAV]]) -> 0 | AM708: =IF(INVESTORS_LIST[[#This Row],[SIP_TOTAL CURRENT UNITS]]=0,0,INVESTORS_LIST[[#This Row],[SIP_TOTAL CURRENT UNITS]]*INVESTORS_LIST[[#This Row],[NAV]]) -> 1895.352 | AO708: =IF(INVESTORS_LIST[[#This Row],[TOTAL SELLABLE UNITS]]=0,0,INVESTORS_LIST[[#This Row],[TOTAL SELLABLE UNITS]]*INVESTORS_LIST[[#This Row],[NAV]]) -> 0 | AP708: =INVESTORS_LIST[[#This Row],[LS_TOTAL REALIZED GAIN]]+INVESTORS_LIST[[#This Row],[SIP_TOTAL REALIZED GAIN]] -> 0 | AQ708: =INVESTORS_LIST[[#This Row],[TOTAL MARKET VALUE]]-INVESTORS_LIST[[#This Row],[TOTAL COST VALUE OF CURRENT INVESTMENT]] -> -104.648 | AR708: =SUMIFS(DivAndTax[Tax Amount],DivAndTax[Investor ID],INVESTORS_LIST[[#This Row],[INVESTOR CODE]]) -> 0 | AS708: =SUMIFS(DivAndTax[Gross Dividend],DivAndTax[Investor ID],INVESTORS_LIST[[#This Row],[INVESTOR CODE]]) -> 0 | AT708: =IFERROR(INVESTORS_LIST[[#This Row],[TOTAL CURRENT UNITS]]/SUM(INVESTORS_LIST[TOTAL CURRENT UNITS]),0) -> 7.2396701e-06
A709: KHADIZA PARVIN | B709: A00696 | C709: Dear Ms. | D709: Individual | E709: =SUMIFS(LS[Unit],LS[Investor ID],INVESTORS_LIST[[#This Row],[INVESTOR CODE]],LS[B/S],"B") -> 0 | F709: =-SUMIFS(LS[Unit],LS[Investor ID],INVESTORS_LIST[[#This Row],[INVESTOR CODE]],LS[B/S],"S") -> 0 | G709: =IF(INVESTORS_LIST[[#This Row],[LS_TOTAL UNITS BUY]]=0,0,INVESTORS_LIST[[#This Row],[LS_TOTAL UNITS BUY]]-INVESTORS_LIST[[#This Row],[LS_TOTAL UNITS SOLD]]) -> 0 | H709: =IF(INVESTORS_LIST[[#This Row],[LS_TOTAL UNITS BUY]]=0,0,SUMIFS(LS[Amount],LS[Investor ID],INVESTORS_LIST[[#This Row],[INVESTOR CODE]],LS[B/S],"B")) -> 0 | I709: =IF(INVESTORS_LIST[[#This Row],[LS_TOTAL UNITS SOLD]]=0,0,SUMIFS(LS[Cost of Units Sold],LS[Investor ID],INVESTORS_LIST[[#This Row],[INVESTOR CODE]],LS[B/S],"S")) -> 0 | J709: =IF(INVESTORS_LIST[[#This Row],[LS_TOTAL CURRENT UNITS]]=0,0,INVESTORS_LIST[[#This Row],[LS_TOTAL CURRENT UNITS]]*INVESTORS_LIST[[#This Row],[LS_AVERAGE COST]]) -> 0 | K709: =IF(INVESTORS_LIST[[#This Row],[LS_TOTAL UNITS SOLD]]=0,0,SUMIFS(LS[Realized Gain],LS[Investor ID],INVESTORS_LIST[[#This Row],[INVESTOR CODE]],LS[B/S],"S")) -> 0 | L709: =SUMIFS(SIP[Unit],SIP[Investor ID],INVESTORS_LIST[[#This Row],[INVESTOR CODE]],SIP[B/S],"B") -> 759 | M709: =-SUMIFS(SIP[Unit],SIP[Investor ID],INVESTORS_LIST[[#This Row],[INVESTOR CODE]],SIP[B/S],"S") -> 0 | N709: =IF(INVESTORS_LIST[[#This Row],[SIP_TOTAL UNITS BUY]]=0,0,INVESTORS_LIST[[#This Row],[SIP_TOTAL UNITS BUY]]-INVESTORS_LIST[[#This Row],[SIP_TOTAL UNITS SOLD]]) -> 759 | O709: =IF(INVESTORS_LIST[[#This Row],[SIP_TOTAL UNITS BUY]]=0,0,SUMIFS(SIP[Amount],SIP[Investor ID],INVESTORS_LIST[[#This Row],[INVESTOR CODE]],SIP[B/S],"B")) -> 10000 | P709: =IF(INVESTORS_LIST[[#This Row],[SIP_TOTAL UNITS SOLD]]=0,0,SUMIFS(SIP[Cost of Units Sold],SIP[Investor ID],INVESTORS_LIST[[#This Row],[INVESTOR CODE]],SIP[B/S],"S")) -> 0 | Q709: =IF(INVESTORS_LIST[[#This Row],[SIP_TOTAL CURRENT UNITS]]=0,0,INVESTORS_LIST[[#This Row],[SIP_TOTAL CURRENT UNITS]]*INVESTORS_LIST[[#This Row],[SIP_AVERAGE COST]]) -> 10000 | R709: =IF(INVESTORS_LIST[[#This Row],[SIP_TOTAL UNITS SOLD]]=0,0,SUMIFS(SIP[Realized Gain],SIP[Investor ID],INVESTORS_LIST[[#This Row],[INVESTOR CODE]],SIP[B/S],"S")) -> 0 | S709: =INVESTORS_LIST[[#This Row],[LS_TOTAL UNITS BUY]]+INVESTORS_LIST[[#This Row],[SIP_TOTAL UNITS BUY]] -> 759 | T709: =INVESTORS_LIST[[#This Row],[LS_TOTAL UNITS SOLD]]+INVESTORS_LIST[[#This Row],[SIP_TOTAL UNITS SOLD]] -> 0 | V709: =SUMIFS(LS[BO UNIT TRANSFER],LS[Investor ID],INVESTORS_LIST[[#This Row],[INVESTOR CODE]],LS[B/S],"B") -> 0 | W709: =SUMIFS(LS[BO UNIT TRANSFER],LS[Investor ID],INVESTORS_LIST[[#This Row],[INVESTOR CODE]],LS[B/S],"S") -> 0 | X709: =SUMIFS(SIP[BO UNIT TRANSFER],SIP[Investor ID],INVESTORS_LIST[[#This Row],[INVESTOR CODE]],SIP[B/S],"S") -> 0 | Y709: =SUMIFS(SIP[BO UNIT TRANSFER],SIP[Investor ID],INVESTORS_LIST[[#This Row],[INVESTOR CODE]],SIP[B/S],"B") -> 0 | Z709: =INVESTORS_LIST[[#This Row],[BO OPENING BALANCE]]+INVESTORS_LIST[[#This Row],[LS- BO UNITS SELL]]+INVESTORS_LIST[[#This Row],[LS- BO UNITS REPURCHASE]]+INVESTORS_LIST[[#This Row],[SIP- BO UNITS REPURCHASE]]-INVESTORS_LIST[[#This Row],[SIP- BO UNITS SELL]] -> 0 | AA709: =INVESTORS_LIST[[#This Row],[TOTAL UNITS BUY]]-INVESTORS_LIST[[#This Row],[TOTAL UNITS SOLD]] -> 759 | AB709: =INVESTORS_LIST[[#This Row],[TOTAL CURRENT UNITS]]-INVESTORS_LIST[[#This Row],[BO UNITS HOLD]] -> 759 | AC709: =INDEX([4]!Table_1[BO ID],MATCH(INVESTORS_LIST[[#This Row],[INVESTOR CODE]],[4]!Table_1[INVESTOR CODE],0)) -> #REF! | AD709: =INVESTORS_LIST[[#This Row],[LS_TOTAL COST VALUE OF CURRENT UNITS]]+INVESTORS_LIST[[#This Row],[SIP_TOTAL COST VALUE OF CURRENT UNITS]] -> 10000 | AE709: =IF(INVESTORS_LIST[[#This Row],[TOTAL CURRENT UNITS]]=0,0,INVESTORS_LIST[[#This Row],[LS_TOTAL CURRENT UNITS]]/INVESTORS_LIST[[#This Row],[TOTAL CURRENT UNITS]]) -> 0 | AF709: =IF(INVESTORS_LIST[[#This Row],[TOTAL CURRENT UNITS]]=0,0,INVESTORS_LIST[[#This Row],[SIP_TOTAL CURRENT UNITS]]/INVESTORS_LIST[[#This Row],[TOTAL CURRENT UNITS]]) -> 1 | AG709: {=IF(INVESTORS_LIST[[#This Row],[LS_TOTAL UNITS BUY]]>0,INDEX(LS[NAV at Cost (Average)],MATCH(CONCATENATE(COUNTIFS(LS[Investor ID],INVESTORS_LIST[[#This Row],[INVESTOR CODE]]),INVESTORS_LIST[[#This Row],[INVESTOR CODE]]),LS[Unique Code],0),),0)} -> 0 | AH709: {=IF(INVESTORS_LIST[[#This Row],[SIP_TOTAL UNITS BUY]]>0,INDEX(SIP[NAV at Cost (Average)],MATCH(CONCATENATE(COUNTIFS(SIP[Investor ID],INVESTORS_LIST[[#This Row],[INVESTOR CODE]]),INVESTORS_LIST[[#This Row],[INVESTOR CODE]]),SIP[Unique Code],0),),0)} -> 13.175231 | AI709: =IF(INVESTORS_LIST[[#This Row],[TOTAL CURRENT UNITS]]=0,0,(INVESTORS_LIST[[#This Row],[LS_WEIGHT]]*INVESTORS_LIST[[#This Row],[LS_AVERAGE COST]])+(INVESTORS_LIST[[#This Row],[SIP_WEIGHT]]*INVESTORS_LIST[[#This Row],[SIP_AVERAGE COST]])) -> 13.175231 | AJ709: =NAV_MKT -> 12.552 | AK709: =IF(INVESTORS_LIST[[#This Row],[TOTAL CURRENT UNITS]]=0,0,INVESTORS_LIST[[#This Row],[TOTAL CURRENT UNITS]]*INVESTORS_LIST[[#This Row],[NAV]]) -> 9526.968 | AL709: =IF(INVESTORS_LIST[[#This Row],[LS_TOTAL CURRENT UNITS]]=0,0,INVESTORS_LIST[[#This Row],[LS_TOTAL CURRENT UNITS]]*INVESTORS_LIST[[#This Row],[NAV]]) -> 0 | AM709: =IF(INVESTORS_LIST[[#This Row],[SIP_TOTAL CURRENT UNITS]]=0,0,INVESTORS_LIST[[#This Row],[SIP_TOTAL CURRENT UNITS]]*INVESTORS_LIST[[#This Row],[NAV]]) -> 9526.968 | AO709: =IF(INVESTORS_LIST[[#This Row],[TOTAL SELLABLE UNITS]]=0,0,INVESTORS_LIST[[#This Row],[TOTAL SELLABLE UNITS]]*INVESTORS_LIST[[#This Row],[NAV]]) -> 0 | AP709: =INVESTORS_LIST[[#This Row],[LS_TOTAL REALIZED GAIN]]+INVESTORS_LIST[[#This Row],[SIP_TOTAL REALIZED GAIN]] -> 0 | AQ709: =INVESTORS_LIST[[#This Row],[TOTAL MARKET VALUE]]-INVESTORS_LIST[[#This Row],[TOTAL COST VALUE OF CURRENT INVESTMENT]] -> -473.032 | AR709: =SUMIFS(DivAndTax[Tax Amount],DivAndTax[Investor ID],INVESTORS_LIST[[#This Row],[INVESTOR CODE]]) -> 0 | AS709: =SUMIFS(DivAndTax[Gross Dividend],DivAndTax[Investor ID],INVESTORS_LIST[[#This Row],[INVESTOR CODE]]) -> 0 | AT709: =IFERROR(INVESTORS_LIST[[#This Row],[TOTAL CURRENT UNITS]]/SUM(INVESTORS_LIST[TOTAL CURRENT UNITS]),0) -> 3.639013e-05
A710: MD. RAKIBUL ALOM | B710: A00697 | C710: Dear Mr. | D710: Individual | E710: =SUMIFS(LS[Unit],LS[Investor ID],INVESTORS_LIST[[#This Row],[INVESTOR CODE]],LS[B/S],"B") -> 0 | F710: =-SUMIFS(LS[Unit],LS[Investor ID],INVESTORS_LIST[[#This Row],[INVESTOR CODE]],LS[B/S],"S") -> 0 | G710: =IF(INVESTORS_LIST[[#This Row],[LS_TOTAL UNITS BUY]]=0,0,INVESTORS_LIST[[#This Row],[LS_TOTAL UNITS BUY]]-INVESTORS_LIST[[#This Row],[LS_TOTAL UNITS SOLD]]) -> 0 | H710: =IF(INVESTORS_LIST[[#This Row],[LS_TOTAL UNITS BUY]]=0,0,SUMIFS(LS[Amount],LS[Investor ID],INVESTORS_LIST[[#This Row],[INVESTOR CODE]],LS[B/S],"B")) -> 0 | I710: =IF(INVESTORS_LIST[[#This Row],[LS_TOTAL UNITS SOLD]]=0,0,SUMIFS(LS[Cost of Units Sold],LS[Investor ID],INVESTORS_LIST[[#This Row],[INVESTOR CODE]],LS[B/S],"S")) -> 0 | J710: =IF(INVESTORS_LIST[[#This Row],[LS_TOTAL CURRENT UNITS]]=0,0,INVESTORS_LIST[[#This Row],[LS_TOTAL CURRENT UNITS]]*INVESTORS_LIST[[#This Row],[LS_AVERAGE COST]]) -> 0 | K710: =IF(INVESTORS_LIST[[#This Row],[LS_TOTAL UNITS SOLD]]=0,0,SUMIFS(LS[Realized Gain],LS[Investor ID],INVESTORS_LIST[[#This Row],[INVESTOR CODE]],LS[B/S],"S")) -> 0 | L710: =SUMIFS(SIP[Unit],SIP[Investor ID],INVESTORS_LIST[[#This Row],[INVESTOR CODE]],SIP[B/S],"B") -> 0 | M710: =-SUMIFS(SIP[Unit],SIP[Investor ID],INVESTORS_LIST[[#This Row],[INVESTOR CODE]],SIP[B/S],"S") -> 0 | N710: =IF(INVESTORS_LIST[[#This Row],[SIP_TOTAL UNITS BUY]]=0,0,INVESTORS_LIST[[#This Row],[SIP_TOTAL UNITS BUY]]-INVESTORS_LIST[[#This Row],[SIP_TOTAL UNITS SOLD]]) -> 0 | O710: =IF(INVESTORS_LIST[[#This Row],[SIP_TOTAL UNITS BUY]]=0,0,SUMIFS(SIP[Amount],SIP[Investor ID],INVESTORS_LIST[[#This Row],[INVESTOR CODE]],SIP[B/S],"B")) -> 0 | P710: =IF(INVESTORS_LIST[[#This Row],[SIP_TOTAL UNITS SOLD]]=0,0,SUMIFS(SIP[Cost of Units Sold],SIP[Investor ID],INVESTORS_LIST[[#This Row],[INVESTOR CODE]],SIP[B/S],"S")) -> 0 | Q710: =IF(INVESTORS_LIST[[#This Row],[SIP_TOTAL CURRENT UNITS]]=0,0,INVESTORS_LIST[[#This Row],[SIP_TOTAL CURRENT UNITS]]*INVESTORS_LIST[[#This Row],[SIP_AVERAGE COST]]) -> 0 | R710: =IF(INVESTORS_LIST[[#This Row],[SIP_TOTAL UNITS SOLD]]=0,0,SUMIFS(SIP[Realized Gain],SIP[Investor ID],INVESTORS_LIST[[#This Row],[INVESTOR CODE]],SIP[B/S],"S")) -> 0 | S710: =INVESTORS_LIST[[#This Row],[LS_TOTAL UNITS BUY]]+INVESTORS_LIST[[#This Row],[SIP_TOTAL UNITS BUY]] -> 0 | T710: =INVESTORS_LIST[[#This Row],[LS_TOTAL UNITS SOLD]]+INVESTORS_LIST[[#This Row],[SIP_TOTAL UNITS SOLD]] -> 0 | V710: =SUMIFS(LS[BO UNIT TRANSFER],LS[Investor ID],INVESTORS_LIST[[#This Row],[INVESTOR CODE]],LS[B/S],"B") -> 0 | W710: =SUMIFS(LS[BO UNIT TRANSFER],LS[Investor ID],INVESTORS_LIST[[#This Row],[INVESTOR CODE]],LS[B/S],"S") -> 0 | X710: =SUMIFS(SIP[BO UNIT TRANSFER],SIP[Investor ID],INVESTORS_LIST[[#This Row],[INVESTOR CODE]],SIP[B/S],"S") -> 0 | Y710: =SUMIFS(SIP[BO UNIT TRANSFER],SIP[Investor ID],INVESTORS_LIST[[#This Row],[INVESTOR CODE]],SIP[B/S],"B") -> 0 | Z710: =INVESTORS_LIST[[#This Row],[BO OPENING BALANCE]]+INVESTORS_LIST[[#This Row],[LS- BO UNITS SELL]]+INVESTORS_LIST[[#This Row],[LS- BO UNITS REPURCHASE]]+INVESTORS_LIST[[#This Row],[SIP- BO UNITS REPURCHASE]]-INVESTORS_LIST[[#This Row],[SIP- BO UNITS SELL]] -> 0 | AA710: =INVESTORS_LIST[[#This Row],[TOTAL UNITS BUY]]-INVESTORS_LIST[[#This Row],[TOTAL UNITS SOLD]] -> 0 | AB710: =INVESTORS_LIST[[#This Row],[TOTAL CURRENT UNITS]]-INVESTORS_LIST[[#This Row],[BO UNITS HOLD]] -> 0 | AC710: =INDEX([4]!Table_1[BO ID],MATCH(INVESTORS_LIST[[#This Row],[INVESTOR CODE]],[4]!Table_1[INVESTOR CODE],0)) -> #REF! | AD710: =INVESTORS_LIST[[#This Row],[LS_TOTAL COST VALUE OF CURRENT UNITS]]+INVESTORS_LIST[[#This Row],[SIP_TOTAL COST VALUE OF CURRENT UNITS]] -> 0 | AE710: =IF(INVESTORS_LIST[[#This Row],[TOTAL CURRENT UNITS]]=0,0,INVESTORS_LIST[[#This Row],[LS_TOTAL CURRENT UNITS]]/INVESTORS_LIST[[#This Row],[TOTAL CURRENT UNITS]]) -> 0 | AF710: =IF(INVESTORS_LIST[[#This Row],[TOTAL CURRENT UNITS]]=0,0,INVESTORS_LIST[[#This Row],[SIP_TOTAL CURRENT UNITS]]/INVESTORS_LIST[[#This Row],[TOTAL CURRENT UNITS]]) -> 0 | AG710: {=IF(INVESTORS_LIST[[#This Row],[LS_TOTAL UNITS BUY]]>0,INDEX(LS[NAV at Cost (Average)],MATCH(CONCATENATE(COUNTIFS(LS[Investor ID],INVESTORS_LIST[[#This Row],[INVESTOR CODE]]),INVESTORS_LIST[[#This Row],[INVESTOR CODE]]),LS[Unique Code],0),),0)} -> 0 | AH710: {=IF(INVESTORS_LIST[[#This Row],[SIP_TOTAL UNITS BUY]]>0,INDEX(SIP[NAV at Cost (Average)],MATCH(CONCATENATE(COUNTIFS(SIP[Investor ID],INVESTORS_LIST[[#This Row],[INVESTOR CODE]]),INVESTORS_LIST[[#This Row],[INVESTOR CODE]]),SIP[Unique Code],0),),0)} -> 0 | AI710: =IF(INVESTORS_LIST[[#This Row],[TOTAL CURRENT UNITS]]=0,0,(INVESTORS_LIST[[#This Row],[LS_WEIGHT]]*INVESTORS_LIST[[#This Row],[LS_AVERAGE COST]])+(INVESTORS_LIST[[#This Row],[SIP_WEIGHT]]*INVESTORS_LIST[[#This Row],[SIP_AVERAGE COST]])) -> 0 | AJ710: =NAV_MKT -> 12.552 | AK710: =IF(INVESTORS_LIST[[#This Row],[TOTAL CURRENT UNITS]]=0,0,INVESTORS_LIST[[#This Row],[TOTAL CURRENT UNITS]]*INVESTORS_LIST[[#This Row],[NAV]]) -> 0 | AL710: =IF(INVESTORS_LIST[[#This Row],[LS_TOTAL CURRENT UNITS]]=0,0,INVESTORS_LIST[[#This Row],[LS_TOTAL CURRENT UNITS]]*INVESTORS_LIST[[#This Row],[NAV]]) -> 0 | AM710: =IF(INVESTORS_LIST[[#This Row],[SIP_TOTAL CURRENT UNITS]]=0,0,INVESTORS_LIST[[#This Row],[SIP_TOTAL CURRENT UNITS]]*INVESTORS_LIST[[#This Row],[NAV]]) -> 0 | AO710: =IF(INVESTORS_LIST[[#This Row],[TOTAL SELLABLE UNITS]]=0,0,INVESTORS_LIST[[#This Row],[TOTAL SELLABLE UNITS]]*INVESTORS_LIST[[#This Row],[NAV]]) -> 0 | AP710: =INVESTORS_LIST[[#This Row],[LS_TOTAL REALIZED GAIN]]+INVESTORS_LIST[[#This Row],[SIP_TOTAL REALIZED GAIN]] -> 0 | AQ710: =INVESTORS_LIST[[#This Row],[TOTAL MARKET VALUE]]-INVESTORS_LIST[[#This Row],[TOTAL COST VALUE OF CURRENT INVESTMENT]] -> 0 | AR710: =SUMIFS(DivAndTax[Tax Amount],DivAndTax[Investor ID],INVESTORS_LIST[[#This Row],[INVESTOR CODE]]) -> 0 | AS710: =SUMIFS(DivAndTax[Gross Dividend],DivAndTax[Investor ID],INVESTORS_LIST[[#This Row],[INVESTOR CODE]]) -> 0 | AT710: =IFERROR(INVESTORS_LIST[[#This Row],[TOTAL CURRENT UNITS]]/SUM(INVESTORS_LIST[TOTAL CURRENT UNITS]),0) -> 0
A711: AKID AQTAB ZAMAN | B711: A00698 | C711: Dear Mr. | D711: Individual | E711: =SUMIFS(LS[Unit],LS[Investor ID],INVESTORS_LIST[[#This Row],[INVESTOR CODE]],LS[B/S],"B") -> 7784 | F711: =-SUMIFS(LS[Unit],LS[Investor ID],INVESTORS_LIST[[#This Row],[INVESTOR CODE]],LS[B/S],"S") -> 0 | G711: =IF(INVESTORS_LIST[[#This Row],[LS_TOTAL UNITS BUY]]=0,0,INVESTORS_LIST[[#This Row],[LS_TOTAL UNITS BUY]]-INVESTORS_LIST[[#This Row],[LS_TOTAL UNITS SOLD]]) -> 7784 | H711: =IF(INVESTORS_LIST[[#This Row],[LS_TOTAL UNITS BUY]]=0,0,SUMIFS(LS[Amount],LS[Investor ID],INVESTORS_LIST[[#This Row],[INVESTOR CODE]],LS[B/S],"B")) -> 100000 | I711: =IF(INVESTORS_LIST[[#This Row],[LS_TOTAL UNITS SOLD]]=0,0,SUMIFS(LS[Cost of Units Sold],LS[Investor ID],INVESTORS_LIST[[#This Row],[INVESTOR CODE]],LS[B/S],"S")) -> 0 | J711: =IF(INVESTORS_LIST[[#This Row],[LS_TOTAL CURRENT UNITS]]=0,0,INVESTORS_LIST[[#This Row],[LS_TOTAL CURRENT UNITS]]*INVESTORS_LIST[[#This Row],[LS_AVERAGE COST]]) -> 100000 | K711: =IF(INVESTORS_LIST[[#This Row],[LS_TOTAL UNITS SOLD]]=0,0,SUMIFS(LS[Realized Gain],LS[Investor ID],INVESTORS_LIST[[#This Row],[INVESTOR CODE]],LS[B/S],"S")) -> 0 | L711: =SUMIFS(SIP[Unit],SIP[Investor ID],INVESTORS_LIST[[#This Row],[INVESTOR CODE]],SIP[B/S],"B") -> 0 | M711: =-SUMIFS(SIP[Unit],SIP[Investor ID],INVESTORS_LIST[[#This Row],[INVESTOR CODE]],SIP[B/S],"S") -> 0 | N711: =IF(INVESTORS_LIST[[#This Row],[SIP_TOTAL UNITS BUY]]=0,0,INVESTORS_LIST[[#This Row],[SIP_TOTAL UNITS BUY]]-INVESTORS_LIST[[#This Row],[SIP_TOTAL UNITS SOLD]]) -> 0 | O711: =IF(INVESTORS_LIST[[#This Row],[SIP_TOTAL UNITS BUY]]=0,0,SUMIFS(SIP[Amount],SIP[Investor ID],INVESTORS_LIST[[#This Row],[INVESTOR CODE]],SIP[B/S],"B")) -> 0 | P711: =IF(INVESTORS_LIST[[#This Row],[SIP_TOTAL UNITS SOLD]]=0,0,SUMIFS(SIP[Cost of Units Sold],SIP[Investor ID],INVESTORS_LIST[[#This Row],[INVESTOR CODE]],SIP[B/S],"S")) -> 0 | Q711: =IF(INVESTORS_LIST[[#This Row],[SIP_TOTAL CURRENT UNITS]]=0,0,INVESTORS_LIST[[#This Row],[SIP_TOTAL CURRENT UNITS]]*INVESTORS_LIST[[#This Row],[SIP_AVERAGE COST]]) -> 0 | R711: =IF(INVESTORS_LIST[[#This Row],[SIP_TOTAL UNITS SOLD]]=0,0,SUMIFS(SIP[Realized Gain],SIP[Investor ID],INVESTORS_LIST[[#This Row],[INVESTOR CODE]],SIP[B/S],"S")) -> 0 | S711: =INVESTORS_LIST[[#This Row],[LS_TOTAL UNITS BUY]]+INVESTORS_LIST[[#This Row],[SIP_TOTAL UNITS BUY]] -> 7784 | T711: =INVESTORS_LIST[[#This Row],[LS_TOTAL UNITS SOLD]]+INVESTORS_LIST[[#This Row],[SIP_TOTAL UNITS SOLD]] -> 0 | V711: =SUMIFS(LS[BO UNIT TRANSFER],LS[Investor ID],INVESTORS_LIST[[#This Row],[INVESTOR CODE]],LS[B/S],"B") -> 0 | W711: =SUMIFS(LS[BO UNIT TRANSFER],LS[Investor ID],INVESTORS_LIST[[#This Row],[INVESTOR CODE]],LS[B/S],"S") -> 0 | X711: =SUMIFS(SIP[BO UNIT TRANSFER],SIP[Investor ID],INVESTORS_LIST[[#This Row],[INVESTOR CODE]],SIP[B/S],"S") -> 0 | Y711: =SUMIFS(SIP[BO UNIT TRANSFER],SIP[Investor ID],INVESTORS_LIST[[#This Row],[INVESTOR CODE]],SIP[B/S],"B") -> 0 | Z711: =INVESTORS_LIST[[#This Row],[BO OPENING BALANCE]]+INVESTORS_LIST[[#This Row],[LS- BO UNITS SELL]]+INVESTORS_LIST[[#This Row],[LS- BO UNITS REPURCHASE]]+INVESTORS_LIST[[#This Row],[SIP- BO UNITS REPURCHASE]]-INVESTORS_LIST[[#This Row],[SIP- BO UNITS SELL]] -> 0 | AA711: =INVESTORS_LIST[[#This Row],[TOTAL UNITS BUY]]-INVESTORS_LIST[[#This Row],[TOTAL UNITS SOLD]] -> 7784 | AB711: =INVESTORS_LIST[[#This Row],[TOTAL CURRENT UNITS]]-INVESTORS_LIST[[#This Row],[BO UNITS HOLD]] -> 7784 | AC711: =INDEX([4]!Table_1[BO ID],MATCH(INVESTORS_LIST[[#This Row],[INVESTOR CODE]],[4]!Table_1[INVESTOR CODE],0)) -> #REF! | AD711: =INVESTORS_LIST[[#This Row],[LS_TOTAL COST VALUE OF CURRENT UNITS]]+INVESTORS_LIST[[#This Row],[SIP_TOTAL COST VALUE OF CURRENT UNITS]] -> 100000 | AE711: =IF(INVESTORS_LIST[[#This Row],[TOTAL CURRENT UNITS]]=0,0,INVESTORS_LIST[[#This Row],[LS_TOTAL CURRENT UNITS]]/INVESTORS_LIST[[#This Row],[TOTAL CURRENT UNITS]]) -> 1 | AF711: =IF(INVESTORS_LIST[[#This Row],[TOTAL CURRENT UNITS]]=0,0,INVESTORS_LIST[[#This Row],[SIP_TOTAL CURRENT UNITS]]/INVESTORS_LIST[[#This Row],[TOTAL CURRENT UNITS]]) -> 0 | AG711: {=IF(INVESTORS_LIST[[#This Row],[LS_TOTAL UNITS BUY]]>0,INDEX(LS[NAV at Cost (Average)],MATCH(CONCATENATE(COUNTIFS(LS[Investor ID],INVESTORS_LIST[[#This Row],[INVESTOR CODE]]),INVESTORS_LIST[[#This Row],[INVESTOR CODE]]),LS[Unique Code],0),),0)} -> 12.846865 | AH711: {=IF(INVESTORS_LIST[[#This Row],[SIP_TOTAL UNITS BUY]]>0,INDEX(SIP[NAV at Cost (Average)],MATCH(CONCATENATE(COUNTIFS(SIP[Investor ID],INVESTORS_LIST[[#This Row],[INVESTOR CODE]]),INVESTORS_LIST[[#This Row],[INVESTOR CODE]]),SIP[Unique Code],0),),0)} -> 0 | AI711: =IF(INVESTORS_LIST[[#This Row],[TOTAL CURRENT UNITS]]=0,0,(INVESTORS_LIST[[#This Row],[LS_WEIGHT]]*INVESTORS_LIST[[#This Row],[LS_AVERAGE COST]])+(INVESTORS_LIST[[#This Row],[SIP_WEIGHT]]*INVESTORS_LIST[[#This Row],[SIP_AVERAGE COST]])) -> 12.846865 | AJ711: =NAV_MKT -> 12.552 | AK711: =IF(INVESTORS_LIST[[#This Row],[TOTAL CURRENT UNITS]]=0,0,INVESTORS_LIST[[#This Row],[TOTAL CURRENT UNITS]]*INVESTORS_LIST[[#This Row],[NAV]]) -> 97704.768 | AL711: =IF(INVESTORS_LIST[[#This Row],[LS_TOTAL CURRENT UNITS]]=0,0,INVESTORS_LIST[[#This Row],[LS_TOTAL CURRENT UNITS]]*INVESTORS_LIST[[#This Row],[NAV]]) -> 97704.768 | AM711: =IF(INVESTORS_LIST[[#This Row],[SIP_TOTAL CURRENT UNITS]]=0,0,INVESTORS_LIST[[#This Row],[SIP_TOTAL CURRENT UNITS]]*INVESTORS_LIST[[#This Row],[NAV]]) -> 0 | AO711: =IF(INVESTORS_LIST[[#This Row],[TOTAL SELLABLE UNITS]]=0,0,INVESTORS_LIST[[#This Row],[TOTAL SELLABLE UNITS]]*INVESTORS_LIST[[#This Row],[NAV]]) -> 0 | AP711: =INVESTORS_LIST[[#This Row],[LS_TOTAL REALIZED GAIN]]+INVESTORS_LIST[[#This Row],[SIP_TOTAL REALIZED GAIN]] -> 0 | AQ711: =INVESTORS_LIST[[#This Row],[TOTAL MARKET VALUE]]-INVESTORS_LIST[[#This Row],[TOTAL COST VALUE OF CURRENT INVESTMENT]] -> -2295.232 | AR711: =SUMIFS(DivAndTax[Tax Amount],DivAndTax[Investor ID],INVESTORS_LIST[[#This Row],[INVESTOR CODE]]) -> 0 | AS711: =SUMIFS(DivAndTax[Gross Dividend],DivAndTax[Investor ID],INVESTORS_LIST[[#This Row],[INVESTOR CODE]]) -> 0 | AT711: =IFERROR(INVESTORS_LIST[[#This Row],[TOTAL CURRENT UNITS]]/SUM(INVESTORS_LIST[TOTAL CURRENT UNITS]),0) -> 0.0003732026
A712: ALBIN AHAMED | B712: BR0003 | C712: Dear Mr. | D712: Individual | E712: =SUMIFS(LS[Unit],LS[Investor ID],INVESTORS_LIST[[#This Row],[INVESTOR CODE]],LS[B/S],"B") -> 0 | F712: =-SUMIFS(LS[Unit],LS[Investor ID],INVESTORS_LIST[[#This Row],[INVESTOR CODE]],LS[B/S],"S") -> 0 | G712: =IF(INVESTORS_LIST[[#This Row],[LS_TOTAL UNITS BUY]]=0,0,INVESTORS_LIST[[#This Row],[LS_TOTAL UNITS BUY]]-INVESTORS_LIST[[#This Row],[LS_TOTAL UNITS SOLD]]) -> 0 | H712: =IF(INVESTORS_LIST[[#This Row],[LS_TOTAL UNITS BUY]]=0,0,SUMIFS(LS[Amount],LS[Investor ID],INVESTORS_LIST[[#This Row],[INVESTOR CODE]],LS[B/S],"B")) -> 0 | I712: =IF(INVESTORS_LIST[[#This Row],[LS_TOTAL UNITS SOLD]]=0,0,SUMIFS(LS[Cost of Units Sold],LS[Investor ID],INVESTORS_LIST[[#This Row],[INVESTOR CODE]],LS[B/S],"S")) -> 0 | J712: =IF(INVESTORS_LIST[[#This Row],[LS_TOTAL CURRENT UNITS]]=0,0,INVESTORS_LIST[[#This Row],[LS_TOTAL CURRENT UNITS]]*INVESTORS_LIST[[#This Row],[LS_AVERAGE COST]]) -> 0 | K712: =IF(INVESTORS_LIST[[#This Row],[LS_TOTAL UNITS SOLD]]=0,0,SUMIFS(LS[Realized Gain],LS[Investor ID],INVESTORS_LIST[[#This Row],[INVESTOR CODE]],LS[B/S],"S")) -> 0 | L712: =SUMIFS(SIP[Unit],SIP[Investor ID],INVESTORS_LIST[[#This Row],[INVESTOR CODE]],SIP[B/S],"B") -> 155 | M712: =-SUMIFS(SIP[Unit],SIP[Investor ID],INVESTORS_LIST[[#This Row],[INVESTOR CODE]],SIP[B/S],"S") -> 0 | N712: =IF(INVESTORS_LIST[[#This Row],[SIP_TOTAL UNITS BUY]]=0,0,INVESTORS_LIST[[#This Row],[SIP_TOTAL UNITS BUY]]-INVESTORS_LIST[[#This Row],[SIP_TOTAL UNITS SOLD]]) -> 155 | O712: =IF(INVESTORS_LIST[[#This Row],[SIP_TOTAL UNITS BUY]]=0,0,SUMIFS(SIP[Amount],SIP[Investor ID],INVESTORS_LIST[[#This Row],[INVESTOR CODE]],SIP[B/S],"B")) -> 2000 | P712: =IF(INVESTORS_LIST[[#This Row],[SIP_TOTAL UNITS SOLD]]=0,0,SUMIFS(SIP[Cost of Units Sold],SIP[Investor ID],INVESTORS_LIST[[#This Row],[INVESTOR CODE]],SIP[B/S],"S")) -> 0 | Q712: =IF(INVESTORS_LIST[[#This Row],[SIP_TOTAL CURRENT UNITS]]=0,0,INVESTORS_LIST[[#This Row],[SIP_TOTAL CURRENT UNITS]]*INVESTORS_LIST[[#This Row],[SIP_AVERAGE COST]]) -> 2000 | R712: =IF(INVESTORS_LIST[[#This Row],[SIP_TOTAL UNITS SOLD]]=0,0,SUMIFS(SIP[Realized Gain],SIP[Investor ID],INVESTORS_LIST[[#This Row],[INVESTOR CODE]],SIP[B/S],"S")) -> 0 | S712: =INVESTORS_LIST[[#This Row],[LS_TOTAL UNITS BUY]]+INVESTORS_LIST[[#This Row],[SIP_TOTAL UNITS BUY]] -> 155 | T712: =INVESTORS_LIST[[#This Row],[LS_TOTAL UNITS SOLD]]+INVESTORS_LIST[[#This Row],[SIP_TOTAL UNITS SOLD]] -> 0 | V712: =SUMIFS(LS[BO UNIT TRANSFER],LS[Investor ID],INVESTORS_LIST[[#This Row],[INVESTOR CODE]],LS[B/S],"B") -> 0 | W712: =SUMIFS(LS[BO UNIT TRANSFER],LS[Investor ID],INVESTORS_LIST[[#This Row],[INVESTOR CODE]],LS[B/S],"S") -> 0 | X712: =SUMIFS(SIP[BO UNIT TRANSFER],SIP[Investor ID],INVESTORS_LIST[[#This Row],[INVESTOR CODE]],SIP[B/S],"S") -> 0 | Y712: =SUMIFS(SIP[BO UNIT TRANSFER],SIP[Investor ID],INVESTORS_LIST[[#This Row],[INVESTOR CODE]],SIP[B/S],"B") -> 77 | Z712: =INVESTORS_LIST[[#This Row],[BO OPENING BALANCE]]+INVESTORS_LIST[[#This Row],[LS- BO UNITS SELL]]+INVESTORS_LIST[[#This Row],[LS- BO UNITS REPURCHASE]]+INVESTORS_LIST[[#This Row],[SIP- BO UNITS REPURCHASE]]-INVESTORS_LIST[[#This Row],[SIP- BO UNITS SELL]] -> 77 | AA712: =INVESTORS_LIST[[#This Row],[TOTAL UNITS BUY]]-INVESTORS_LIST[[#This Row],[TOTAL UNITS SOLD]] -> 155 | AB712: =INVESTORS_LIST[[#This Row],[TOTAL CURRENT UNITS]]-INVESTORS_LIST[[#This Row],[BO UNITS HOLD]] -> 78 | AC712: =INDEX([4]!Table_1[BO ID],MATCH(INVESTORS_LIST[[#This Row],[INVESTOR CODE]],[4]!Table_1[INVESTOR CODE],0)) -> #REF! | AD712: =INVESTORS_LIST[[#This Row],[LS_TOTAL COST VALUE OF CURRENT UNITS]]+INVESTORS_LIST[[#This Row],[SIP_TOTAL COST VALUE OF CURRENT UNITS]] -> 2000 | AE712: =IF(INVESTORS_LIST[[#This Row],[TOTAL CURRENT UNITS]]=0,0,INVESTORS_LIST[[#This Row],[LS_TOTAL CURRENT UNITS]]/INVESTORS_LIST[[#This Row],[TOTAL CURRENT UNITS]]) -> 0 | AF712: =IF(INVESTORS_LIST[[#This Row],[TOTAL CURRENT UNITS]]=0,0,INVESTORS_LIST[[#This Row],[SIP_TOTAL CURRENT UNITS]]/INVESTORS_LIST[[#This Row],[TOTAL CURRENT UNITS]]) -> 1 | AG712: {=IF(INVESTORS_LIST[[#This Row],[LS_TOTAL UNITS BUY]]>0,INDEX(LS[NAV at Cost (Average)],MATCH(CONCATENATE(COUNTIFS(LS[Investor ID],INVESTORS_LIST[[#This Row],[INVESTOR CODE]]),INVESTORS_LIST[[#This Row],[INVESTOR CODE]]),LS[Unique Code],0),),0)} -> 0 | AH712: {=IF(INVESTORS_LIST[[#This Row],[SIP_TOTAL UNITS BUY]]>0,INDEX(SIP[NAV at Cost (Average)],MATCH(CONCATENATE(COUNTIFS(SIP[Investor ID],INVESTORS_LIST[[#This Row],[INVESTOR CODE]]),INVESTORS_LIST[[#This Row],[INVESTOR CODE]]),SIP[Unique Code],0),),0)} -> 12.903226 | AI712: =IF(INVESTORS_LIST[[#This Row],[TOTAL CURRENT UNITS]]=0,0,(INVESTORS_LIST[[#This Row],[LS_WEIGHT]]*INVESTORS_LIST[[#This Row],[LS_AVERAGE COST]])+(INVESTORS_LIST[[#This Row],[SIP_WEIGHT]]*INVESTORS_LIST[[#This Row],[SIP_AVERAGE COST]])) -> 12.903226 | AJ712: =NAV_MKT -> 12.552 | AK712: =IF(INVESTORS_LIST[[#This Row],[TOTAL CURRENT UNITS]]=0,0,INVESTORS_LIST[[#This Row],[TOTAL CURRENT UNITS]]*INVESTORS_LIST[[#This Row],[NAV]]) -> 1945.56 | AL712: =IF(INVESTORS_LIST[[#This Row],[LS_TOTAL CURRENT UNITS]]=0,0,INVESTORS_LIST[[#This Row],[LS_TOTAL CURRENT UNITS]]*INVESTORS_LIST[[#This Row],[NAV]]) -> 0 | AM712: =IF(INVESTORS_LIST[[#This Row],[SIP_TOTAL CURRENT UNITS]]=0,0,INVESTORS_LIST[[#This Row],[SIP_TOTAL CURRENT UNITS]]*INVESTORS_LIST[[#This Row],[NAV]]) -> 1945.56 | AO712: =IF(INVESTORS_LIST[[#This Row],[TOTAL SELLABLE UNITS]]=0,0,INVESTORS_LIST[[#This Row],[TOTAL SELLABLE UNITS]]*INVESTORS_LIST[[#This Row],[NAV]]) -> 0 | AP712: =INVESTORS_LIST[[#This Row],[LS_TOTAL REALIZED GAIN]]+INVESTORS_LIST[[#This Row],[SIP_TOTAL REALIZED GAIN]] -> 0 | AQ712: =INVESTORS_LIST[[#This Row],[TOTAL MARKET VALUE]]-INVESTORS_LIST[[#This Row],[TOTAL COST VALUE OF CURRENT INVESTMENT]] -> -54.44 | AR712: =SUMIFS(DivAndTax[Tax Amount],DivAndTax[Investor ID],INVESTORS_LIST[[#This Row],[INVESTOR CODE]]) -> 0 | AS712: =SUMIFS(DivAndTax[Gross Dividend],DivAndTax[Investor ID],INVESTORS_LIST[[#This Row],[INVESTOR CODE]]) -> 0 | AT712: =IFERROR(INVESTORS_LIST[[#This Row],[TOTAL CURRENT UNITS]]/SUM(INVESTORS_LIST[TOTAL CURRENT UNITS]),0) -> 7.4314494e-06
A713: A.K.M. FAHIM MASHROOR | B713: A00699 | C713: Dear Mr. | D713: Individual | E713: =SUMIFS(LS[Unit],LS[Investor ID],INVESTORS_LIST[[#This Row],[INVESTOR CODE]],LS[B/S],"B") -> 0 | F713: =-SUMIFS(LS[Unit],LS[Investor ID],INVESTORS_LIST[[#This Row],[INVESTOR CODE]],LS[B/S],"S") -> 0 | G713: =IF(INVESTORS_LIST[[#This Row],[LS_TOTAL UNITS BUY]]=0,0,INVESTORS_LIST[[#This Row],[LS_TOTAL UNITS BUY]]-INVESTORS_LIST[[#This Row],[LS_TOTAL UNITS SOLD]]) -> 0 | H713: =IF(INVESTORS_LIST[[#This Row],[LS_TOTAL UNITS BUY]]=0,0,SUMIFS(LS[Amount],LS[Investor ID],INVESTORS_LIST[[#This Row],[INVESTOR CODE]],LS[B/S],"B")) -> 0 | I713: =IF(INVESTORS_LIST[[#This Row],[LS_TOTAL UNITS SOLD]]=0,0,SUMIFS(LS[Cost of Units Sold],LS[Investor ID],INVESTORS_LIST[[#This Row],[INVESTOR CODE]],LS[B/S],"S")) -> 0 | J713: =IF(INVESTORS_LIST[[#This Row],[LS_TOTAL CURRENT UNITS]]=0,0,INVESTORS_LIST[[#This Row],[LS_TOTAL CURRENT UNITS]]*INVESTORS_LIST[[#This Row],[LS_AVERAGE COST]]) -> 0 | K713: =IF(INVESTORS_LIST[[#This Row],[LS_TOTAL UNITS SOLD]]=0,0,SUMIFS(LS[Realized Gain],LS[Investor ID],INVESTORS_LIST[[#This Row],[INVESTOR CODE]],LS[B/S],"S")) -> 0 | L713: =SUMIFS(SIP[Unit],SIP[Investor ID],INVESTORS_LIST[[#This Row],[INVESTOR CODE]],SIP[B/S],"B") -> 0 | M713: =-SUMIFS(SIP[Unit],SIP[Investor ID],INVESTORS_LIST[[#This Row],[INVESTOR CODE]],SIP[B/S],"S") -> 0 | N713: =IF(INVESTORS_LIST[[#This Row],[SIP_TOTAL UNITS BUY]]=0,0,INVESTORS_LIST[[#This Row],[SIP_TOTAL UNITS BUY]]-INVESTORS_LIST[[#This Row],[SIP_TOTAL UNITS SOLD]]) -> 0 | O713: =IF(INVESTORS_LIST[[#This Row],[SIP_TOTAL UNITS BUY]]=0,0,SUMIFS(SIP[Amount],SIP[Investor ID],INVESTORS_LIST[[#This Row],[INVESTOR CODE]],SIP[B/S],"B")) -> 0 | P713: =IF(INVESTORS_LIST[[#This Row],[SIP_TOTAL UNITS SOLD]]=0,0,SUMIFS(SIP[Cost of Units Sold],SIP[Investor ID],INVESTORS_LIST[[#This Row],[INVESTOR CODE]],SIP[B/S],"S")) -> 0 | Q713: =IF(INVESTORS_LIST[[#This Row],[SIP_TOTAL CURRENT UNITS]]=0,0,INVESTORS_LIST[[#This Row],[SIP_TOTAL CURRENT UNITS]]*INVESTORS_LIST[[#This Row],[SIP_AVERAGE COST]]) -> 0 | R713: =IF(INVESTORS_LIST[[#This Row],[SIP_TOTAL UNITS SOLD]]=0,0,SUMIFS(SIP[Realized Gain],SIP[Investor ID],INVESTORS_LIST[[#This Row],[INVESTOR CODE]],SIP[B/S],"S")) -> 0 | S713: =INVESTORS_LIST[[#This Row],[LS_TOTAL UNITS BUY]]+INVESTORS_LIST[[#This Row],[SIP_TOTAL UNITS BUY]] -> 0 | T713: =INVESTORS_LIST[[#This Row],[LS_TOTAL UNITS SOLD]]+INVESTORS_LIST[[#This Row],[SIP_TOTAL UNITS SOLD]] -> 0 | V713: =SUMIFS(LS[BO UNIT TRANSFER],LS[Investor ID],INVESTORS_LIST[[#This Row],[INVESTOR CODE]],LS[B/S],"B") -> 0 | W713: =SUMIFS(LS[BO UNIT TRANSFER],LS[Investor ID],INVESTORS_LIST[[#This Row],[INVESTOR CODE]],LS[B/S],"S") -> 0 | X713: =SUMIFS(SIP[BO UNIT TRANSFER],SIP[Investor ID],INVESTORS_LIST[[#This Row],[INVESTOR CODE]],SIP[B/S],"S") -> 0 | Y713: =SUMIFS(SIP[BO UNIT TRANSFER],SIP[Investor ID],INVESTORS_LIST[[#This Row],[INVESTOR CODE]],SIP[B/S],"B") -> 0 | Z713: =INVESTORS_LIST[[#This Row],[BO OPENING BALANCE]]+INVESTORS_LIST[[#This Row],[LS- BO UNITS SELL]]+INVESTORS_LIST[[#This Row],[LS- BO UNITS REPURCHASE]]+INVESTORS_LIST[[#This Row],[SIP- BO UNITS REPURCHASE]]-INVESTORS_LIST[[#This Row],[SIP- BO UNITS SELL]] -> 0 | AA713: =INVESTORS_LIST[[#This Row],[TOTAL UNITS BUY]]-INVESTORS_LIST[[#This Row],[TOTAL UNITS SOLD]] -> 0 | AB713: =INVESTORS_LIST[[#This Row],[TOTAL CURRENT UNITS]]-INVESTORS_LIST[[#This Row],[BO UNITS HOLD]] -> 0 | AC713: =INDEX([4]!Table_1[BO ID],MATCH(INVESTORS_LIST[[#This Row],[INVESTOR CODE]],[4]!Table_1[INVESTOR CODE],0)) -> #REF! | AD713: =INVESTORS_LIST[[#This Row],[LS_TOTAL COST VALUE OF CURRENT UNITS]]+INVESTORS_LIST[[#This Row],[SIP_TOTAL COST VALUE OF CURRENT UNITS]] -> 0 | AE713: =IF(INVESTORS_LIST[[#This Row],[TOTAL CURRENT UNITS]]=0,0,INVESTORS_LIST[[#This Row],[LS_TOTAL CURRENT UNITS]]/INVESTORS_LIST[[#This Row],[TOTAL CURRENT UNITS]]) -> 0 | AF713: =IF(INVESTORS_LIST[[#This Row],[TOTAL CURRENT UNITS]]=0,0,INVESTORS_LIST[[#This Row],[SIP_TOTAL CURRENT UNITS]]/INVESTORS_LIST[[#This Row],[TOTAL CURRENT UNITS]]) -> 0 | AG713: {=IF(INVESTORS_LIST[[#This Row],[LS_TOTAL UNITS BUY]]>0,INDEX(LS[NAV at Cost (Average)],MATCH(CONCATENATE(COUNTIFS(LS[Investor ID],INVESTORS_LIST[[#This Row],[INVESTOR CODE]]),INVESTORS_LIST[[#This Row],[INVESTOR CODE]]),LS[Unique Code],0),),0)} -> 0 | AH713: {=IF(INVESTORS_LIST[[#This Row],[SIP_TOTAL UNITS BUY]]>0,INDEX(SIP[NAV at Cost (Average)],MATCH(CONCATENATE(COUNTIFS(SIP[Investor ID],INVESTORS_LIST[[#This Row],[INVESTOR CODE]]),INVESTORS_LIST[[#This Row],[INVESTOR CODE]]),SIP[Unique Code],0),),0)} -> 0 | AI713: =IF(INVESTORS_LIST[[#This Row],[TOTAL CURRENT UNITS]]=0,0,(INVESTORS_LIST[[#This Row],[LS_WEIGHT]]*INVESTORS_LIST[[#This Row],[LS_AVERAGE COST]])+(INVESTORS_LIST[[#This Row],[SIP_WEIGHT]]*INVESTORS_LIST[[#This Row],[SIP_AVERAGE COST]])) -> 0 | AJ713: =NAV_MKT -> 12.552 | AK713: =IF(INVESTORS_LIST[[#This Row],[TOTAL CURRENT UNITS]]=0,0,INVESTORS_LIST[[#This Row],[TOTAL CURRENT UNITS]]*INVESTORS_LIST[[#This Row],[NAV]]) -> 0 | AL713: =IF(INVESTORS_LIST[[#This Row],[LS_TOTAL CURRENT UNITS]]=0,0,INVESTORS_LIST[[#This Row],[LS_TOTAL CURRENT UNITS]]*INVESTORS_LIST[[#This Row],[NAV]]) -> 0 | AM713: =IF(INVESTORS_LIST[[#This Row],[SIP_TOTAL CURRENT UNITS]]=0,0,INVESTORS_LIST[[#This Row],[SIP_TOTAL CURRENT UNITS]]*INVESTORS_LIST[[#This Row],[NAV]]) -> 0 | AO713: =IF(INVESTORS_LIST[[#This Row],[TOTAL SELLABLE UNITS]]=0,0,INVESTORS_LIST[[#This Row],[TOTAL SELLABLE UNITS]]*INVESTORS_LIST[[#This Row],[NAV]]) -> 0 | AP713: =INVESTORS_LIST[[#This Row],[LS_TOTAL REALIZED GAIN]]+INVESTORS_LIST[[#This Row],[SIP_TOTAL REALIZED GAIN]] -> 0 | AQ713: =INVESTORS_LIST[[#This Row],[TOTAL MARKET VALUE]]-INVESTORS_LIST[[#This Row],[TOTAL COST VALUE OF CURRENT INVESTMENT]] -> 0 | AR713: =SUMIFS(DivAndTax[Tax Amount],DivAndTax[Investor ID],INVESTORS_LIST[[#This Row],[INVESTOR CODE]]) -> 0 | AS713: =SUMIFS(DivAndTax[Gross Dividend],DivAndTax[Investor ID],INVESTORS_LIST[[#This Row],[INVESTOR CODE]]) -> 0 | AT713: =IFERROR(INVESTORS_LIST[[#This Row],[TOTAL CURRENT UNITS]]/SUM(INVESTORS_LIST[TOTAL CURRENT UNITS]),0) -> 0
