Workbook
Name NAV_MKT: [1]LS!$T$1
Name NAV_MKT: LS!$S$1
Name NEW_TCV: [2]Portfolio!$F$38
Name NEW_TMV: [2]Portfolio!$H$38
Name TCV_STOCKS: #REF!
Name TMV_STOCKS: #REF!
Name TMV_STOCKS: #REF!

Sheet DASHBOARD
A1: =LS!P1+SIP!P1 -> 411925950 | C1: =LS!Q1+SIP!Q1 -> 23036942
A4: 411925950 | B4: =A1-A4 -> 0
A5: 23036942 | B5: =A5-C1 -> 0.53209996

Sheet INVESTORS
A1: INVESTOR NAME | B1: INVESTOR CODE | C1: Title | D1: TYPE OF INVESTOR | E1: LS_TOTAL UNITS BUY | F1: LS_TOTAL UNITS SOLD | G1: LS_TOTAL CURRENT UNITS | H1: LS_TOTAL COST VALUE | I1: LS_TOTAL COST OF UNITS SOLD | J1: LS_TOTAL COST VALUE OF CURRENT UNITS | K1: LS_TOTAL REALIZED GAIN | L1: SIP_TOTAL UNITS BUY | M1: SIP_TOTAL UNITS SOLD | N1: SIP_TOTAL CURRENT UNITS | O1: SIP_TOTAL COST VALUE | P1: SIP_TOTAL COST OF UNITS SOLD | Q1: SIP_TOTAL COST VALUE OF CURRENT UNITS | R1: SIP_TOTAL REALIZED GAIN | S1: TOTAL UNITS BUY | T1: TOTAL UNITS SOLD | U1: BO OPENING BALANCE | V1: BO LS UNITS SELL | W1: BO SIP UNITS SELL | X1: BO LS UNITS REPURCHASE | Y1: BO SIP UNITS REPURCHASE | Z1: BO UNITS HOLD | AA1: TOTAL CURRENT UNITS | AB1: mismatch | AC1: BO ID | AD1: Column3 | AE1: Column4 | AF1: Column2 | AG1: Column1 | AH1: Column12 | AI1: TOTAL COST VALUE OF CURRENT INVESTMENT | AJ1: LS_WEIGHT | AK1: SIP_WEIGHT | AL1: LS_AVERAGE COST | AM1: SIP_AVERAGE COST | AN1: AVERAGE COST | AO1: NAV | AP1: TOTAL MARKET VALUE | AQ1: LS_TOTAL MARKET VALUE | AR1: SIP_TOTAL MARKET VALUE | AS1: TOTAL SELLABLE UNITS | AT1: MARKET VALUE OF SELLABLE UNITS | AU1: TOTAL REALIZED GAIN | AV1: TOTAL UNREALIZED GAIN | AW1: % of Units Hold
A2: HARI PADA SAHA | B2: A00002 | C2: Dear Mr. | D2: Individual | E2: =SUMIFS(LS[Unit],LS[Investor ID],INVESTORS_LIST[[#This Row],[INVESTOR CODE]],LS[B/S],"B") -> 0 | F2: =-SUMIFS(LS[Unit],LS[Investor ID],INVESTORS_LIST[[#This Row],[INVESTOR CODE]],LS[B/S],"S") -> 0 | G2: =IF(INVESTORS_LIST[[#This Row],[LS_TOTAL UNITS BUY]]=0,0,INVESTORS_LIST[[#This Row],[LS_TOTAL UNITS BUY]]-INVESTORS_LIST[[#This Row],[LS_TOTAL UNITS SOLD]]) -> 0 | H2: =IF(INVESTORS_LIST[[#This Row],[LS_TOTAL UNITS BUY]]=0,0,SUMIFS(LS[Amount],LS[Investor ID],INVESTORS_LIST[[#This Row],[INVESTOR CODE]],LS[B/S],"B")) -> 0 | I2: =IF(INVESTORS_LIST[[#This Row],[LS_TOTAL UNITS SOLD]]=0,0,SUMIFS(LS[Cost of Units Sold],LS[Investor ID],INVESTORS_LIST[[#This Row],[INVESTOR CODE]],LS[B/S],"S")) -> 0 | J2: =IF(INVESTORS_LIST[[#This Row],[LS_TOTAL CURRENT UNITS]]=0,0,INVESTORS_LIST[[#This Row],[LS_TOTAL CURRENT UNITS]]*INVESTORS_LIST[[#This Row],[LS_AVERAGE COST]]) -> 0 | K2: =IF(INVESTORS_LIST[[#This Row],[LS_TOTAL UNITS SOLD]]=0,0,SUMIFS(LS[Realized Gain],LS[Investor ID],INVESTORS_LIST[[#This Row],[INVESTOR CODE]],LS[B/S],"S")) -> 0 | L2: =SUMIFS(SIP[Unit],SIP[Investor ID],INVESTORS_LIST[[#This Row],[INVESTOR CODE]],SIP[B/S],"B") -> 0 | M2: =-SUMIFS(SIP[Unit],SIP[Investor ID],INVESTORS_LIST[[#This Row],[INVESTOR CODE]],SIP[B/S],"S") -> 0 | N2: =IF(INVESTORS_LIST[[#This Row],[SIP_TOTAL UNITS BUY]]=0,0,INVESTORS_LIST[[#This Row],[SIP_TOTAL UNITS BUY]]-INVESTORS_LIST[[#This Row],[SIP_TOTAL UNITS SOLD]]) -> 0 | O2: =IF(INVESTORS_LIST[[#This Row],[SIP_TOTAL UNITS BUY]]=0,0,SUMIFS(SIP[Amount],SIP[Investor ID],INVESTORS_LIST[[#This Row],[INVESTOR CODE]],SIP[B/S],"B")) -> 0 | P2: =IF(INVESTORS_LIST[[#This Row],[SIP_TOTAL UNITS SOLD]]=0,0,SUMIFS(SIP[Cost of Units Sold],SIP[Investor ID],INVESTORS_LIST[[#This Row],[INVESTOR CODE]],SIP[B/S],"S")) -> 0 | Q2: =IF(INVESTORS_LIST[[#This Row],[SIP_TOTAL CURRENT UNITS]]=0,0,INVESTORS_LIST[[#This Row],[SIP_TOTAL CURRENT UNITS]]*INVESTORS_LIST[[#This Row],[SIP_AVERAGE COST]]) -> 0 | R2: =IF(INVESTORS_LIST[[#This Row],[SIP_TOTAL UNITS SOLD]]=0,0,SUMIFS(SIP[Realized Gain],SIP[Investor ID],INVESTORS_LIST[[#This Row],[INVESTOR CODE]],SIP[B/S],"S")) -> 0 | S2: =INVESTORS_LIST[[#This Row],[LS_TOTAL UNITS BUY]]+INVESTORS_LIST[[#This Row],[SIP_TOTAL UNITS BUY]] -> 0 | T2: =INVESTORS_LIST[[#This Row],[LS_TOTAL UNITS SOLD]]+INVESTORS_LIST[[#This Row],[SIP_TOTAL UNITS SOLD]] -> 0 | V2: =SUMIFS(LS[BO UNIT TRANSFER],LS[Investor ID],INVESTORS_LIST[[#This Row],[INVESTOR CODE]],LS[B/S],"B") -> 0 | W2: =SUMIFS(SIP[BO UNIT TRANSFER],SIP[Investor ID],INVESTORS_LIST[[#This Row],[INVESTOR CODE]],SIP[B/S],"B") -> 0 | X2: =SUMIFS(LS[BO UNIT TRANSFER],LS[Investor ID],INVESTORS_LIST[[#This Row],[INVESTOR CODE]],LS[B/S],"S") -> 0 | Y2: =SUMIFS(SIP[BO UNIT TRANSFER],SIP[Investor ID],INVESTORS_LIST[[#This Row],[INVESTOR CODE]],SIP[B/S],"S") -> 0 | Z2: =SUM(INVESTORS_LIST[[#This Row],[BO OPENING BALANCE]:[BO SIP UNITS REPURCHASE]]) -> 0 | AA2: =INVESTORS_LIST[[#This Row],[TOTAL UNITS BUY]]-INVESTORS_LIST[[#This Row],[TOTAL UNITS SOLD]] -> 0 | AB2: =INVESTORS_LIST[[#This Row],[TOTAL CURRENT UNITS]]-INVESTORS_LIST[[#This Row],[BO UNITS HOLD]] -> 0 | AC2: =INDEX([3]!Table_1[BO ID],MATCH(INVESTORS_LIST[[#This Row],[INVESTOR CODE]],[3]!Table_1[INVESTOR CODE],0)) -> #REF! | AD2: =INDEX([3]!Table_1[Brokerage Name2],MATCH(INVESTORS_LIST[[#This Row],[INVESTOR CODE]],[3]!Table_1[INVESTOR CODE],0)) -> #REF! | AE2: =MID(INVESTORS_LIST[[#This Row],[BO ID]],4,5) -> #REF! | AF2: =MID(INVESTORS_LIST[[#This Row],[BO ID]],2,7) -> #REF! | AG2: =MID(INVESTORS_LIST[[#This Row],[BO ID]],9,7) -> #REF! | AH2: =RIGHT(INVESTORS_LIST[[#This Row],[BO ID]],1) -> #REF! | AI2: =INVESTORS_LIST[[#This Row],[LS_TOTAL COST VALUE OF CURRENT UNITS]]+INVESTORS_LIST[[#This Row],[SIP_TOTAL COST VALUE OF CURRENT UNITS]] -> 0 | AJ2: =IF(INVESTORS_LIST[[#This Row],[TOTAL CURRENT UNITS]]=0,0,INVESTORS_LIST[[#This Row],[LS_TOTAL CURRENT UNITS]]/INVESTORS_LIST[[#This Row],[TOTAL CURRENT UNITS]]) -> 0 | AK2: =IF(INVESTORS_LIST[[#This Row],[TOTAL CURRENT UNITS]]=0,0,INVESTORS_LIST[[#This Row],[SIP_TOTAL CURRENT UNITS]]/INVESTORS_LIST[[#This Row],[TOTAL CURRENT UNITS]]) -> 0 | AL2: {=IF(INVESTORS_LIST[[#This Row],[LS_TOTAL UNITS BUY]]>0,INDEX(LS[NAV at Cost (Average)],MATCH(CONCATENATE(COUNTIFS(LS[Investor ID],INVESTORS_LIST[[#This Row],[INVESTOR CODE]]),INVESTORS_LIST[[#This Row],[INVESTOR CODE]]),LS[Unique Code],0),),0)} -> 0 | AM2: {=IF(INVESTORS_LIST[[#This Row],[SIP_TOTAL UNITS BUY]]>0,INDEX(SIP[NAV at Cost (Average)],MATCH(CONCATENATE(COUNTIFS(SIP[Investor ID],INVESTORS_LIST[[#This Row],[INVESTOR CODE]]),INVESTORS_LIST[[#This Row],[INVESTOR CODE]]),SIP[Unique Code],0),),0)} -> 0 | AN2: =IF(INVESTORS_LIST[[#This Row],[TOTAL CURRENT UNITS]]=0,0,(INVESTORS_LIST[[#This Row],[LS_WEIGHT]]*INVESTORS_LIST[[#This Row],[LS_AVERAGE COST]])+(INVESTORS_LIST[[#This Row],[SIP_WEIGHT]]*INVESTORS_LIST[[#This Row],[SIP_AVERAGE COST]])) -> 0 | AO2: =NAV_MKT -> 14.224 | AP2: =IF(INVESTORS_LIST[[#This Row],[TOTAL CURRENT UNITS]]=0,0,INVESTORS_LIST[[#This Row],[TOTAL CURRENT UNITS]]*INVESTORS_LIST[[#This Row],[NAV]]) -> 0 | AQ2: =IF(INVESTORS_LIST[[#This Row],[LS_TOTAL CURRENT UNITS]]=0,0,INVESTORS_LIST[[#This Row],[LS_TOTAL CURRENT UNITS]]*INVESTORS_LIST[[#This Row],[NAV]]) -> 0 | AR2: =IF(INVESTORS_LIST[[#This Row],[SIP_TOTAL CURRENT UNITS]]=0,0,INVESTORS_LIST[[#This Row],[SIP_TOTAL CURRENT UNITS]]*INVESTORS_LIST[[#This Row],[NAV]]) -> 0 | AS2: =INVESTORS_LIST[[#This Row],[TOTAL CURRENT UNITS]] -> 0 | AT2: =IF(INVESTORS_LIST[[#This Row],[TOTAL SELLABLE UNITS]]=0,0,INVESTORS_LIST[[#This Row],[TOTAL SELLABLE UNITS]]*INVESTORS_LIST[[#This Row],[NAV]]) -> 0 | AU2: =INVESTORS_LIST[[#This Row],[LS_TOTAL REALIZED GAIN]]+INVESTORS_LIST[[#This Row],[SIP_TOTAL REALIZED GAIN]] -> 0 | AV2: =INVESTORS_LIST[[#This Row],[TOTAL MARKET VALUE]]-INVESTORS_LIST[[#This Row],[TOTAL COST VALUE OF CURRENT INVESTMENT]] -> 0 | AW2: =IFERROR(INVESTORS_LIST[[#This Row],[TOTAL CURRENT UNITS]]/SUM(INVESTORS_LIST[TOTAL CURRENT UNITS]),0) -> 0
A3: EKUSH WEALTH MANAGEMENT LIMITED | B3: A00003 | C3: Dear | D3: Company/Organization | E3: =SUMIFS(LS[Unit],LS[Investor ID],INVESTORS_LIST[[#This Row],[INVESTOR CODE]],LS[B/S],"B") -> 4293158 | F3: =-SUMIFS(LS[Unit],LS[Investor ID],INVESTORS_LIST[[#This Row],[INVESTOR CODE]],LS[B/S],"S") -> 4043106 | G3: =IF(INVESTORS_LIST[[#This Row],[LS_TOTAL UNITS BUY]]=0,0,INVESTORS_LIST[[#This Row],[LS_TOTAL UNITS BUY]]-INVESTORS_LIST[[#This Row],[LS_TOTAL UNITS SOLD]]) -> 250052 | H3: =IF(INVESTORS_LIST[[#This Row],[LS_TOTAL UNITS BUY]]=0,0,SUMIFS(LS[Amount],LS[Investor ID],INVESTORS_LIST[[#This Row],[INVESTOR CODE]],LS[B/S],"B")) -> 45874500 | I3: =IF(INVESTORS_LIST[[#This Row],[LS_TOTAL UNITS SOLD]]=0,0,SUMIFS(LS[Cost of Units Sold],LS[Investor ID],INVESTORS_LIST[[#This Row],[INVESTOR CODE]],LS[B/S],"S")) -> 42680200 | J3: =IF(INVESTORS_LIST[[#This Row],[LS_TOTAL CURRENT UNITS]]=0,0,INVESTORS_LIST[[#This Row],[LS_TOTAL CURRENT UNITS]]*INVESTORS_LIST[[#This Row],[LS_AVERAGE COST]]) -> 3194299.8 | K3: =IF(INVESTORS_LIST[[#This Row],[LS_TOTAL UNITS SOLD]]=0,0,SUMIFS(LS[Realized Gain],LS[Investor ID],INVESTORS_LIST[[#This Row],[INVESTOR CODE]],LS[B/S],"S")) -> 3169268 | L3: =SUMIFS(SIP[Unit],SIP[Investor ID],INVESTORS_LIST[[#This Row],[INVESTOR CODE]],SIP[B/S],"B") -> 0 | M3: =-SUMIFS(SIP[Unit],SIP[Investor ID],INVESTORS_LIST[[#This Row],[INVESTOR CODE]],SIP[B/S],"S") -> 0 | N3: =IF(INVESTORS_LIST[[#This Row],[SIP_TOTAL UNITS BUY]]=0,0,INVESTORS_LIST[[#This Row],[SIP_TOTAL UNITS BUY]]-INVESTORS_LIST[[#This Row],[SIP_TOTAL UNITS SOLD]]) -> 0 | O3: =IF(INVESTORS_LIST[[#This Row],[SIP_TOTAL UNITS BUY]]=0,0,SUMIFS(SIP[Amount],SIP[Investor ID],INVESTORS_LIST[[#This Row],[INVESTOR CODE]],SIP[B/S],"B")) -> 0 | P3: =IF(INVESTORS_LIST[[#This Row],[SIP_TOTAL UNITS SOLD]]=0,0,SUMIFS(SIP[Cost of Units Sold],SIP[Investor ID],INVESTORS_LIST[[#This Row],[INVESTOR CODE]],SIP[B/S],"S")) -> 0 | Q3: =IF(INVESTORS_LIST[[#This Row],[SIP_TOTAL CURRENT UNITS]]=0,0,INVESTORS_LIST[[#This Row],[SIP_TOTAL CURRENT UNITS]]*INVESTORS_LIST[[#This Row],[SIP_AVERAGE COST]]) -> 0 | R3: =IF(INVESTORS_LIST[[#This Row],[SIP_TOTAL UNITS SOLD]]=0,0,SUMIFS(SIP[Realized Gain],SIP[Investor ID],INVESTORS_LIST[[#This Row],[INVESTOR CODE]],SIP[B/S],"S")) -> 0 | S3: =INVESTORS_LIST[[#This Row],[LS_TOTAL UNITS BUY]]+INVESTORS_LIST[[#This Row],[SIP_TOTAL UNITS BUY]] -> 4293158 | T3: =INVESTORS_LIST[[#This Row],[LS_TOTAL UNITS SOLD]]+INVESTORS_LIST[[#This Row],[SIP_TOTAL UNITS SOLD]] -> 4043106 | U3: 500052 | V3: =SUMIFS(LS[BO UNIT TRANSFER],LS[Investor ID],INVESTORS_LIST[[#This Row],[INVESTOR CODE]],LS[B/S],"B") -> 0 | W3: =SUMIFS(SIP[BO UNIT TRANSFER],SIP[Investor ID],INVESTORS_LIST[[#This Row],[INVESTOR CODE]],SIP[B/S],"B") -> 0 | X3: =SUMIFS(LS[BO UNIT TRANSFER],LS[Investor ID],INVESTORS_LIST[[#This Row],[INVESTOR CODE]],LS[B/S],"S") -> 0 | Y3: =SUMIFS(SIP[BO UNIT TRANSFER],SIP[Investor ID],INVESTORS_LIST[[#This Row],[INVESTOR CODE]],SIP[B/S],"S") -> 0 | Z3: =SUM(INVESTORS_LIST[[#This Row],[BO OPENING BALANCE]:[BO SIP UNITS REPURCHASE]]) -> 500052 | AA3: =INVESTORS_LIST[[#This Row],[TOTAL UNITS BUY]]-INVESTORS_LIST[[#This Row],[TOTAL UNITS SOLD]] -> 250052 | AB3: =INVESTORS_LIST[[#This Row],[TOTAL CURRENT UNITS]]-INVESTORS_LIST[[#This Row],[BO UNITS HOLD]] -> -250000 | AC3: =INDEX([3]!Table_1[BO ID],MATCH(INVESTORS_LIST[[#This Row],[INVESTOR CODE]],[3]!Table_1[INVESTOR CODE],0)) -> #REF! | AD3: =INDEX([3]!Table_1[Brokerage Name2],MATCH(INVESTORS_LIST[[#This Row],[INVESTOR CODE]],[3]!Table_1[INVESTOR CODE],0)) -> #REF! | AE3: =MID(INVESTORS_LIST[[#This Row],[BO ID]],4,5) -> #REF! | AF3: =MID(INVESTORS_LIST[[#This Row],[BO ID]],2,7) -> #REF! | AG3: =MID(INVESTORS_LIST[[#This Row],[BO ID]],9,7) -> #REF! | AH3: =RIGHT(INVESTORS_LIST[[#This Row],[BO ID]],1) -> #REF! | AI3: =INVESTORS_LIST[[#This Row],[LS_TOTAL COST VALUE OF CURRENT UNITS]]+INVESTORS_LIST[[#This Row],[SIP_TOTAL COST VALUE OF CURRENT UNITS]] -> 3194299.8 | AJ3: =IF(INVESTORS_LIST[[#This Row],[TOTAL CURRENT UNITS]]=0,0,INVESTORS_LIST[[#This Row],[LS_TOTAL CURRENT UNITS]]/INVESTORS_LIST[[#This Row],[TOTAL CURRENT UNITS]]) -> 1 | AK3: =IF(INVESTORS_LIST[[#This Row],[TOTAL CURRENT UNITS]]=0,0,INVESTORS_LIST[[#This Row],[SIP_TOTAL CURRENT UNITS]]/INVESTORS_LIST[[#This Row],[TOTAL CURRENT UNITS]]) -> 0 | AL3: {=IF(INVESTORS_LIST[[#This Row],[LS_TOTAL UNITS BUY]]>0,INDEX(LS[NAV at Cost (Average)],MATCH(CONCATENATE(COUNTIFS(LS[Investor ID],INVESTORS_LIST[[#This Row],[INVESTOR CODE]]),INVESTORS_LIST[[#This Row],[INVESTOR CODE]]),LS[Unique Code],0),),0)} -> 12.774542 | AM3: {=IF(INVESTORS_LIST[[#This Row],[SIP_TOTAL UNITS BUY]]>0,INDEX(SIP[NAV at Cost (Average)],MATCH(CONCATENATE(COUNTIFS(SIP[Investor ID],INVESTORS_LIST[[#This Row],[INVESTOR CODE]]),INVESTORS_LIST[[#This Row],[INVESTOR CODE]]),SIP[Unique Code],0),),0)} -> 0 | AN3: =IF(INVESTORS_LIST[[#This Row],[TOTAL CURRENT UNITS]]=0,0,(INVESTORS_LIST[[#This Row],[LS_WEIGHT]]*INVESTORS_LIST[[#This Row],[LS_AVERAGE COST]])+(INVESTORS_LIST[[#This Row],[SIP_WEIGHT]]*INVESTORS_LIST[[#This Row],[SIP_AVERAGE COST]])) -> 12.774542 | AO3: =NAV_MKT -> 14.224 | AP3: =IF(INVESTORS_LIST[[#This Row],[TOTAL CURRENT UNITS]]=0,0,INVESTORS_LIST[[#This Row],[TOTAL CURRENT UNITS]]*INVESTORS_LIST[[#This Row],[NAV]]) -> 3556739.6 | AQ3: =IF(INVESTORS_LIST[[#This Row],[LS_TOTAL CURRENT UNITS]]=0,0,INVESTORS_LIST[[#This Row],[LS_TOTAL CURRENT UNITS]]*INVESTORS_LIST[[#This Row],[NAV]]) -> 3556739.6 | AR3: =IF(INVESTORS_LIST[[#This Row],[SIP_TOTAL CURRENT UNITS]]=0,0,INVESTORS_LIST[[#This Row],[SIP_TOTAL CURRENT UNITS]]*INVESTORS_LIST[[#This Row],[NAV]]) -> 0 | AS3: =INVESTORS_LIST[[#This Row],[TOTAL CURRENT UNITS]] -> 250052 | AT3: =IF(INVESTORS_LIST[[#This Row],[TOTAL SELLABLE UNITS]]=0,0,INVESTORS_LIST[[#This Row],[TOTAL SELLABLE UNITS]]*INVESTORS_LIST[[#This Row],[NAV]]) -> 3556739.6 | AU3: =INVESTORS_LIST[[#This Row],[LS_TOTAL REALIZED GAIN]]+INVESTORS_LIST[[#This Row],[SIP_TOTAL REALIZED GAIN]] -> 3169268 | AV3: =INVESTORS_LIST[[#This Row],[TOTAL MARKET VALUE]]-INVESTORS_LIST[[#This Row],[TOTAL COST VALUE OF CURRENT INVESTMENT]] -> 362439.86 | AW3: =IFERROR(INVESTORS_LIST[[#This Row],[TOTAL CURRENT UNITS]]/SUM(INVESTORS_LIST[TOTAL CURRENT UNITS]),0) -> 0.0060703143
A4: SADIA AHMED | B4: A00004 | C4: Dear Mrs. | D4: Individual | E4: =SUMIFS(LS[Unit],LS[Investor ID],INVESTORS_LIST[[#This Row],[INVESTOR CODE]],LS[B/S],"B") -> 0 | F4: =-SUMIFS(LS[Unit],LS[Investor ID],INVESTORS_LIST[[#This Row],[INVESTOR CODE]],LS[B/S],"S") -> 0 | G4: =IF(INVESTORS_LIST[[#This Row],[LS_TOTAL UNITS BUY]]=0,0,INVESTORS_LIST[[#This Row],[LS_TOTAL UNITS BUY]]-INVESTORS_LIST[[#This Row],[LS_TOTAL UNITS SOLD]]) -> 0 | H4: =IF(INVESTORS_LIST[[#This Row],[LS_TOTAL UNITS BUY]]=0,0,SUMIFS(LS[Amount],LS[Investor ID],INVESTORS_LIST[[#This Row],[INVESTOR CODE]],LS[B/S],"B")) -> 0 | I4: =IF(INVESTORS_LIST[[#This Row],[LS_TOTAL UNITS SOLD]]=0,0,SUMIFS(LS[Cost of Units Sold],LS[Investor ID],INVESTORS_LIST[[#This Row],[INVESTOR CODE]],LS[B/S],"S")) -> 0 | J4: =IF(INVESTORS_LIST[[#This Row],[LS_TOTAL CURRENT UNITS]]=0,0,INVESTORS_LIST[[#This Row],[LS_TOTAL CURRENT UNITS]]*INVESTORS_LIST[[#This Row],[LS_AVERAGE COST]]) -> 0 | K4: =IF(INVESTORS_LIST[[#This Row],[LS_TOTAL UNITS SOLD]]=0,0,SUMIFS(LS[Realized Gain],LS[Investor ID],INVESTORS_LIST[[#This Row],[INVESTOR CODE]],LS[B/S],"S")) -> 0 | L4: =SUMIFS(SIP[Unit],SIP[Investor ID],INVESTORS_LIST[[#This Row],[INVESTOR CODE]],SIP[B/S],"B") -> 0 | M4: =-SUMIFS(SIP[Unit],SIP[Investor ID],INVESTORS_LIST[[#This Row],[INVESTOR CODE]],SIP[B/S],"S") -> 0 | N4: =IF(INVESTORS_LIST[[#This Row],[SIP_TOTAL UNITS BUY]]=0,0,INVESTORS_LIST[[#This Row],[SIP_TOTAL UNITS BUY]]-INVESTORS_LIST[[#This Row],[SIP_TOTAL UNITS SOLD]]) -> 0 | O4: =IF(INVESTORS_LIST[[#This Row],[SIP_TOTAL UNITS BUY]]=0,0,SUMIFS(SIP[Amount],SIP[Investor ID],INVESTORS_LIST[[#This Row],[INVESTOR CODE]],SIP[B/S],"B")) -> 0 | P4: =IF(INVESTORS_LIST[[#This Row],[SIP_TOTAL UNITS SOLD]]=0,0,SUMIFS(SIP[Cost of Units Sold],SIP[Investor ID],INVESTORS_LIST[[#This Row],[INVESTOR CODE]],SIP[B/S],"S")) -> 0 | Q4: =IF(INVESTORS_LIST[[#This Row],[SIP_TOTAL CURRENT UNITS]]=0,0,INVESTORS_LIST[[#This Row],[SIP_TOTAL CURRENT UNITS]]*INVESTORS_LIST[[#This Row],[SIP_AVERAGE COST]]) -> 0 | R4: =IF(INVESTORS_LIST[[#This Row],[SIP_TOTAL UNITS SOLD]]=0,0,SUMIFS(SIP[Realized Gain],SIP[Investor ID],INVESTORS_LIST[[#This Row],[INVESTOR CODE]],SIP[B/S],"S")) -> 0 | S4: =INVESTORS_LIST[[#This Row],[LS_TOTAL UNITS BUY]]+INVESTORS_LIST[[#This Row],[SIP_TOTAL UNITS BUY]] -> 0 | T4: =INVESTORS_LIST[[#This Row],[LS_TOTAL UNITS SOLD]]+INVESTORS_LIST[[#This Row],[SIP_TOTAL UNITS SOLD]] -> 0 | V4: =SUMIFS(LS[BO UNIT TRANSFER],LS[Investor ID],INVESTORS_LIST[[#This Row],[INVESTOR CODE]],LS[B/S],"B") -> 0 | W4: =SUMIFS(SIP[BO UNIT TRANSFER],SIP[Investor ID],INVESTORS_LIST[[#This Row],[INVESTOR CODE]],SIP[B/S],"B") -> 0 | X4: =SUMIFS(LS[BO UNIT TRANSFER],LS[Investor ID],INVESTORS_LIST[[#This Row],[INVESTOR CODE]],LS[B/S],"S") -> 0 | Y4: =SUMIFS(SIP[BO UNIT TRANSFER],SIP[Investor ID],INVESTORS_LIST[[#This Row],[INVESTOR CODE]],SIP[B/S],"S") -> 0 | Z4: =SUM(INVESTORS_LIST[[#This Row],[BO OPENING BALANCE]:[BO SIP UNITS REPURCHASE]]) -> 0 | AA4: =INVESTORS_LIST[[#This Row],[TOTAL UNITS BUY]]-INVESTORS_LIST[[#This Row],[TOTAL UNITS SOLD]] -> 0 | AB4: =INVESTORS_LIST[[#This Row],[TOTAL CURRENT UNITS]]-INVESTORS_LIST[[#This Row],[BO UNITS HOLD]] -> 0 | AC4: =INDEX([3]!Table_1[BO ID],MATCH(INVESTORS_LIST[[#This Row],[INVESTOR CODE]],[3]!Table_1[INVESTOR CODE],0)) -> #REF! | AD4: =INDEX([3]!Table_1[Brokerage Name2],MATCH(INVESTORS_LIST[[#This Row],[INVESTOR CODE]],[3]!Table_1[INVESTOR CODE],0)) -> #REF! | AE4: =MID(INVESTORS_LIST[[#This Row],[BO ID]],4,5) -> #REF! | AF4: =MID(INVESTORS_LIST[[#This Row],[BO ID]],2,7) -> #REF! | AG4: =MID(INVESTORS_LIST[[#This Row],[BO ID]],9,7) -> #REF! | AH4: =RIGHT(INVESTORS_LIST[[#This Row],[BO ID]],1) -> #REF! | AI4: =INVESTORS_LIST[[#This Row],[LS_TOTAL COST VALUE OF CURRENT UNITS]]+INVESTORS_LIST[[#This Row],[SIP_TOTAL COST VALUE OF CURRENT UNITS]] -> 0 | AJ4: =IF(INVESTORS_LIST[[#This Row],[TOTAL CURRENT UNITS]]=0,0,INVESTORS_LIST[[#This Row],[LS_TOTAL CURRENT UNITS]]/INVESTORS_LIST[[#This Row],[TOTAL CURRENT UNITS]]) -> 0 | AK4: =IF(INVESTORS_LIST[[#This Row],[TOTAL CURRENT UNITS]]=0,0,INVESTORS_LIST[[#This Row],[SIP_TOTAL CURRENT UNITS]]/INVESTORS_LIST[[#This Row],[TOTAL CURRENT UNITS]]) -> 0 | AL4: {=IF(INVESTORS_LIST[[#This Row],[LS_TOTAL UNITS BUY]]>0,INDEX(LS[NAV at Cost (Average)],MATCH(CONCATENATE(COUNTIFS(LS[Investor ID],INVESTORS_LIST[[#This Row],[INVESTOR CODE]]),INVESTORS_LIST[[#This Row],[INVESTOR CODE]]),LS[Unique Code],0),),0)} -> 0 | AM4: {=IF(INVESTORS_LIST[[#This Row],[SIP_TOTAL UNITS BUY]]>0,INDEX(SIP[NAV at Cost (Average)],MATCH(CONCATENATE(COUNTIFS(SIP[Investor ID],INVESTORS_LIST[[#This Row],[INVESTOR CODE]]),INVESTORS_LIST[[#This Row],[INVESTOR CODE]]),SIP[Unique Code],0),),0)} -> 0 | AN4: =IF(INVESTORS_LIST[[#This Row],[TOTAL CURRENT UNITS]]=0,0,(INVESTORS_LIST[[#This Row],[LS_WEIGHT]]*INVESTORS_LIST[[#This Row],[LS_AVERAGE COST]])+(INVESTORS_LIST[[#This Row],[SIP_WEIGHT]]*INVESTORS_LIST[[#This Row],[SIP_AVERAGE COST]])) -> 0 | AO4: =NAV_MKT -> 14.224 | AP4: =IF(INVESTORS_LIST[[#This Row],[TOTAL CURRENT UNITS]]=0,0,INVESTORS_LIST[[#This Row],[TOTAL CURRENT UNITS]]*INVESTORS_LIST[[#This Row],[NAV]]) -> 0 | AQ4: =IF(INVESTORS_LIST[[#This Row],[LS_TOTAL CURRENT UNITS]]=0,0,INVESTORS_LIST[[#This Row],[LS_TOTAL CURRENT UNITS]]*INVESTORS_LIST[[#This Row],[NAV]]) -> 0 | AR4: =IF(INVESTORS_LIST[[#This Row],[SIP_TOTAL CURRENT UNITS]]=0,0,INVESTORS_LIST[[#This Row],[SIP_TOTAL CURRENT UNITS]]*INVESTORS_LIST[[#This Row],[NAV]]) -> 0 | AS4: =INVESTORS_LIST[[#This Row],[TOTAL CURRENT UNITS]] -> 0 | AT4: =IF(INVESTORS_LIST[[#This Row],[TOTAL SELLABLE UNITS]]=0,0,INVESTORS_LIST[[#This Row],[TOTAL SELLABLE UNITS]]*INVESTORS_LIST[[#This Row],[NAV]]) -> 0 | AU4: =INVESTORS_LIST[[#This Row],[LS_TOTAL REALIZED GAIN]]+INVESTORS_LIST[[#This Row],[SIP_TOTAL REALIZED GAIN]] -> 0 | AV4: =INVESTORS_LIST[[#This Row],[TOTAL MARKET VALUE]]-INVESTORS_LIST[[#This Row],[TOTAL COST VALUE OF CURRENT INVESTMENT]] -> 0 | AW4: =IFERROR(INVESTORS_LIST[[#This Row],[TOTAL CURRENT UNITS]]/SUM(INVESTORS_LIST[TOTAL CURRENT UNITS]),0) -> 0
A5: MORSHEDA MIM | B5: A00005 | C5: Dear Mrs. | D5: Individual | E5: =SUMIFS(LS[Unit],LS[Investor ID],INVESTORS_LIST[[#This Row],[INVESTOR CODE]],LS[B/S],"B") -> 94661 | F5: =-SUMIFS(LS[Unit],LS[Investor ID],INVESTORS_LIST[[#This Row],[INVESTOR CODE]],LS[B/S],"S") -> 94661 | G5: =IF(INVESTORS_LIST[[#This Row],[LS_TOTAL UNITS BUY]]=0,0,INVESTORS_LIST[[#This Row],[LS_TOTAL UNITS BUY]]-INVESTORS_LIST[[#This Row],[LS_TOTAL UNITS SOLD]]) -> 0 | H5: =IF(INVESTORS_LIST[[#This Row],[LS_TOTAL UNITS BUY]]=0,0,SUMIFS(LS[Amount],LS[Investor ID],INVESTORS_LIST[[#This Row],[INVESTOR CODE]],LS[B/S],"B")) -> 1000000 | I5: =IF(INVESTORS_LIST[[#This Row],[LS_TOTAL UNITS SOLD]]=0,0,SUMIFS(LS[Cost of Units Sold],LS[Investor ID],INVESTORS_LIST[[#This Row],[INVESTOR CODE]],LS[B/S],"S")) -> 1000000 | J5: =IF(INVESTORS_LIST[[#This Row],[LS_TOTAL CURRENT UNITS]]=0,0,INVESTORS_LIST[[#This Row],[LS_TOTAL CURRENT UNITS]]*INVESTORS_LIST[[#This Row],[LS_AVERAGE COST]]) -> 0 | K5: =IF(INVESTORS_LIST[[#This Row],[LS_TOTAL UNITS SOLD]]=0,0,SUMIFS(LS[Realized Gain],LS[Investor ID],INVESTORS_LIST[[#This Row],[INVESTOR CODE]],LS[B/S],"S")) -> 49736.91 | L5: =SUMIFS(SIP[Unit],SIP[Investor ID],INVESTORS_LIST[[#This Row],[INVESTOR CODE]],SIP[B/S],"B") -> 0 | M5: =-SUMIFS(SIP[Unit],SIP[Investor ID],INVESTORS_LIST[[#This Row],[INVESTOR CODE]],SIP[B/S],"S") -> 0 | N5: =IF(INVESTORS_LIST[[#This Row],[SIP_TOTAL UNITS BUY]]=0,0,INVESTORS_LIST[[#This Row],[SIP_TOTAL UNITS BUY]]-INVESTORS_LIST[[#This Row],[SIP_TOTAL UNITS SOLD]]) -> 0 | O5: =IF(INVESTORS_LIST[[#This Row],[SIP_TOTAL UNITS BUY]]=0,0,SUMIFS(SIP[Amount],SIP[Investor ID],INVESTORS_LIST[[#This Row],[INVESTOR CODE]],SIP[B/S],"B")) -> 0 | P5: =IF(INVESTORS_LIST[[#This Row],[SIP_TOTAL UNITS SOLD]]=0,0,SUMIFS(SIP[Cost of Units Sold],SIP[Investor ID],INVESTORS_LIST[[#This Row],[INVESTOR CODE]],SIP[B/S],"S")) -> 0 | Q5: =IF(INVESTORS_LIST[[#This Row],[SIP_TOTAL CURRENT UNITS]]=0,0,INVESTORS_LIST[[#This Row],[SIP_TOTAL CURRENT UNITS]]*INVESTORS_LIST[[#This Row],[SIP_AVERAGE COST]]) -> 0 | R5: =IF(INVESTORS_LIST[[#This Row],[SIP_TOTAL UNITS SOLD]]=0,0,SUMIFS(SIP[Realized Gain],SIP[Investor ID],INVESTORS_LIST[[#This Row],[INVESTOR CODE]],SIP[B/S],"S")) -> 0 | S5: =INVESTORS_LIST[[#This Row],[LS_TOTAL UNITS BUY]]+INVESTORS_LIST[[#This Row],[SIP_TOTAL UNITS BUY]] -> 94661 | T5: =INVESTORS_LIST[[#This Row],[LS_TOTAL UNITS SOLD]]+INVESTORS_LIST[[#This Row],[SIP_TOTAL UNITS SOLD]] -> 94661 | U5: 47468 | V5: =SUMIFS(LS[BO UNIT TRANSFER],LS[Investor ID],INVESTORS_LIST[[#This Row],[INVESTOR CODE]],LS[B/S],"B") -> 0 | W5: =SUMIFS(SIP[BO UNIT TRANSFER],SIP[Investor ID],INVESTORS_LIST[[#This Row],[INVESTOR CODE]],SIP[B/S],"B") -> 0 | X5: =SUMIFS(LS[BO UNIT TRANSFER],LS[Investor ID],INVESTORS_LIST[[#This Row],[INVESTOR CODE]],LS[B/S],"S") -> 0 | Y5: =SUMIFS(SIP[BO UNIT TRANSFER],SIP[Investor ID],INVESTORS_LIST[[#This Row],[INVESTOR CODE]],SIP[B/S],"S") -> 0 | Z5: =SUM(INVESTORS_LIST[[#This Row],[BO OPENING BALANCE]:[BO SIP UNITS REPURCHASE]]) -> 47468 | AA5: =INVESTORS_LIST[[#This Row],[TOTAL UNITS BUY]]-INVESTORS_LIST[[#This Row],[TOTAL UNITS SOLD]] -> 0 | AB5: =INVESTORS_LIST[[#This Row],[TOTAL CURRENT UNITS]]-INVESTORS_LIST[[#This Row],[BO UNITS HOLD]] -> -47468 | AC5: =INDEX([3]!Table_1[BO ID],MATCH(INVESTORS_LIST[[#This Row],[INVESTOR CODE]],[3]!Table_1[INVESTOR CODE],0)) -> #REF! | AD5: =INDEX([3]!Table_1[Brokerage Name2],MATCH(INVESTORS_LIST[[#This Row],[INVESTOR CODE]],[3]!Table_1[INVESTOR CODE],0)) -> #REF! | AE5: =MID(INVESTORS_LIST[[#This Row],[BO ID]],4,5) -> #REF! | AF5: =MID(INVESTORS_LIST[[#This Row],[BO ID]],2,7) -> #REF! | AG5: =MID(INVESTORS_LIST[[#This Row],[BO ID]],9,7) -> #REF! | AH5: =RIGHT(INVESTORS_LIST[[#This Row],[BO ID]],1) -> #REF! | AI5: =INVESTORS_LIST[[#This Row],[LS_TOTAL COST VALUE OF CURRENT UNITS]]+INVESTORS_LIST[[#This Row],[SIP_TOTAL COST VALUE OF CURRENT UNITS]] -> 0 | AJ5: =IF(INVESTORS_LIST[[#This Row],[TOTAL CURRENT UNITS]]=0,0,INVESTORS_LIST[[#This Row],[LS_TOTAL CURRENT UNITS]]/INVESTORS_LIST[[#This Row],[TOTAL CURRENT UNITS]]) -> 0 | AK5: =IF(INVESTORS_LIST[[#This Row],[TOTAL CURRENT UNITS]]=0,0,INVESTORS_LIST[[#This Row],[SIP_TOTAL CURRENT UNITS]]/INVESTORS_LIST[[#This Row],[TOTAL CURRENT UNITS]]) -> 0 | AL5: {=IF(INVESTORS_LIST[[#This Row],[LS_TOTAL UNITS BUY]]>0,INDEX(LS[NAV at Cost (Average)],MATCH(CONCATENATE(COUNTIFS(LS[Investor ID],INVESTORS_LIST[[#This Row],[INVESTOR CODE]]),INVESTORS_LIST[[#This Row],[INVESTOR CODE]]),LS[Unique Code],0),),0)} -> 0 | AM5: {=IF(INVESTORS_LIST[[#This Row],[SIP_TOTAL UNITS BUY]]>0,INDEX(SIP[NAV at Cost (Average)],MATCH(CONCATENATE(COUNTIFS(SIP[Investor ID],INVESTORS_LIST[[#This Row],[INVESTOR CODE]]),INVESTORS_LIST[[#This Row],[INVESTOR CODE]]),SIP[Unique Code],0),),0)} -> 0 | AN5: =IF(INVESTORS_LIST[[#This Row],[TOTAL CURRENT UNITS]]=0,0,(INVESTORS_LIST[[#This Row],[LS_WEIGHT]]*INVESTORS_LIST[[#This Row],[LS_AVERAGE COST]])+(INVESTORS_LIST[[#This Row],[SIP_WEIGHT]]*INVESTORS_LIST[[#This Row],[SIP_AVERAGE COST]])) -> 0 | AO5: =NAV_MKT -> 14.224 | AP5: =IF(INVESTORS_LIST[[#This Row],[TOTAL CURRENT UNITS]]=0,0,INVESTORS_LIST[[#This Row],[TOTAL CURRENT UNITS]]*INVESTORS_LIST[[#This Row],[NAV]]) -> 0 | AQ5: =IF(INVESTORS_LIST[[#This Row],[LS_TOTAL CURRENT UNITS]]=0,0,INVESTORS_LIST[[#This Row],[LS_TOTAL CURRENT UNITS]]*INVESTORS_LIST[[#This Row],[NAV]]) -> 0 | AR5: =IF(INVESTORS_LIST[[#This Row],[SIP_TOTAL CURRENT UNITS]]=0,0,INVESTORS_LIST[[#This Row],[SIP_TOTAL CURRENT UNITS]]*INVESTORS_LIST[[#This Row],[NAV]]) -> 0 | AS5: =INVESTORS_LIST[[#This Row],[TOTAL CURRENT UNITS]] -> 0 | AT5: =IF(INVESTORS_LIST[[#This Row],[TOTAL SELLABLE UNITS]]=0,0,INVESTORS_LIST[[#This Row],[TOTAL SELLABLE UNITS]]*INVESTORS_LIST[[#This Row],[NAV]]) -> 0 | AU5: =INVESTORS_LIST[[#This Row],[LS_TOTAL REALIZED GAIN]]+INVESTORS_LIST[[#This Row],[SIP_TOTAL REALIZED GAIN]] -> 49736.91 | AV5: =INVESTORS_LIST[[#This Row],[TOTAL MARKET VALUE]]-INVESTORS_LIST[[#This Row],[TOTAL COST VALUE OF CURRENT INVESTMENT]] -> 0 | AW5: =IFERROR(INVESTORS_LIST[[#This Row],[TOTAL CURRENT UNITS]]/SUM(INVESTORS_LIST[TOTAL CURRENT UNITS]),0) -> 0
A6: MD. JAHANGIR ALAM | B6: A00006 | C6: Dear Mr. | D6: Individual | E6: =SUMIFS(LS[Unit],LS[Investor ID],INVESTORS_LIST[[#This Row],[INVESTOR CODE]],LS[B/S],"B") -> 0 | F6: =-SUMIFS(LS[Unit],LS[Investor ID],INVESTORS_LIST[[#This Row],[INVESTOR CODE]],LS[B/S],"S") -> 0 | G6: =IF(INVESTORS_LIST[[#This Row],[LS_TOTAL UNITS BUY]]=0,0,INVESTORS_LIST[[#This Row],[LS_TOTAL UNITS BUY]]-INVESTORS_LIST[[#This Row],[LS_TOTAL UNITS SOLD]]) -> 0 | H6: =IF(INVESTORS_LIST[[#This Row],[LS_TOTAL UNITS BUY]]=0,0,SUMIFS(LS[Amount],LS[Investor ID],INVESTORS_LIST[[#This Row],[INVESTOR CODE]],LS[B/S],"B")) -> 0 | I6: =IF(INVESTORS_LIST[[#This Row],[LS_TOTAL UNITS SOLD]]=0,0,SUMIFS(LS[Cost of Units Sold],LS[Investor ID],INVESTORS_LIST[[#This Row],[INVESTOR CODE]],LS[B/S],"S")) -> 0 | J6: =IF(INVESTORS_LIST[[#This Row],[LS_TOTAL CURRENT UNITS]]=0,0,INVESTORS_LIST[[#This Row],[LS_TOTAL CURRENT UNITS]]*INVESTORS_LIST[[#This Row],[LS_AVERAGE COST]]) -> 0 | K6: =IF(INVESTORS_LIST[[#This Row],[LS_TOTAL UNITS SOLD]]=0,0,SUMIFS(LS[Realized Gain],LS[Investor ID],INVESTORS_LIST[[#This Row],[INVESTOR CODE]],LS[B/S],"S")) -> 0 | L6: =SUMIFS(SIP[Unit],SIP[Investor ID],INVESTORS_LIST[[#This Row],[INVESTOR CODE]],SIP[B/S],"B") -> 0 | M6: =-SUMIFS(SIP[Unit],SIP[Investor ID],INVESTORS_LIST[[#This Row],[INVESTOR CODE]],SIP[B/S],"S") -> 0 | N6: =IF(INVESTORS_LIST[[#This Row],[SIP_TOTAL UNITS BUY]]=0,0,INVESTORS_LIST[[#This Row],[SIP_TOTAL UNITS BUY]]-INVESTORS_LIST[[#This Row],[SIP_TOTAL UNITS SOLD]]) -> 0 | O6: =IF(INVESTORS_LIST[[#This Row],[SIP_TOTAL UNITS BUY]]=0,0,SUMIFS(SIP[Amount],SIP[Investor ID],INVESTORS_LIST[[#This Row],[INVESTOR CODE]],SIP[B/S],"B")) -> 0 | P6: =IF(INVESTORS_LIST[[#This Row],[SIP_TOTAL UNITS SOLD]]=0,0,SUMIFS(SIP[Cost of Units Sold],SIP[Investor ID],INVESTORS_LIST[[#This Row],[INVESTOR CODE]],SIP[B/S],"S")) -> 0 | Q6: =IF(INVESTORS_LIST[[#This Row],[SIP_TOTAL CURRENT UNITS]]=0,0,INVESTORS_LIST[[#This Row],[SIP_TOTAL CURRENT UNITS]]*INVESTORS_LIST[[#This Row],[SIP_AVERAGE COST]]) -> 0 | R6: =IF(INVESTORS_LIST[[#This Row],[SIP_TOTAL UNITS SOLD]]=0,0,SUMIFS(SIP[Realized Gain],SIP[Investor ID],INVESTORS_LIST[[#This Row],[INVESTOR CODE]],SIP[B/S],"S")) -> 0 | S6: =INVESTORS_LIST[[#This Row],[LS_TOTAL UNITS BUY]]+INVESTORS_LIST[[#This Row],[SIP_TOTAL UNITS BUY]] -> 0 | T6: =INVESTORS_LIST[[#This Row],[LS_TOTAL UNITS SOLD]]+INVESTORS_LIST[[#This Row],[SIP_TOTAL UNITS SOLD]] -> 0 | V6: =SUMIFS(LS[BO UNIT TRANSFER],LS[Investor ID],INVESTORS_LIST[[#This Row],[INVESTOR CODE]],LS[B/S],"B") -> 0 | W6: =SUMIFS(SIP[BO UNIT TRANSFER],SIP[Investor ID],INVESTORS_LIST[[#This Row],[INVESTOR CODE]],SIP[B/S],"B") -> 0 | X6: =SUMIFS(LS[BO UNIT TRANSFER],LS[Investor ID],INVESTORS_LIST[[#This Row],[INVESTOR CODE]],LS[B/S],"S") -> 0 | Y6: =SUMIFS(SIP[BO UNIT TRANSFER],SIP[Investor ID],INVESTORS_LIST[[#This Row],[INVESTOR CODE]],SIP[B/S],"S") -> 0 | Z6: =SUM(INVESTORS_LIST[[#This Row],[BO OPENING BALANCE]:[BO SIP UNITS REPURCHASE]]) -> 0 | AA6: =INVESTORS_LIST[[#This Row],[TOTAL UNITS BUY]]-INVESTORS_LIST[[#This Row],[TOTAL UNITS SOLD]] -> 0 | AB6: =INVESTORS_LIST[[#This Row],[TOTAL CURRENT UNITS]]-INVESTORS_LIST[[#This Row],[BO UNITS HOLD]] -> 0 | AC6: =INDEX([3]!Table_1[BO ID],MATCH(INVESTORS_LIST[[#This Row],[INVESTOR CODE]],[3]!Table_1[INVESTOR CODE],0)) -> #REF! | AD6: =INDEX([3]!Table_1[Brokerage Name2],MATCH(INVESTORS_LIST[[#This Row],[INVESTOR CODE]],[3]!Table_1[INVESTOR CODE],0)) -> #REF! | AE6: =MID(INVESTORS_LIST[[#This Row],[BO ID]],4,5) -> #REF! | AF6: =MID(INVESTORS_LIST[[#This Row],[BO ID]],2,7) -> #REF! | AG6: =MID(INVESTORS_LIST[[#This Row],[BO ID]],9,7) -> #REF! | AH6: =RIGHT(INVESTORS_LIST[[#This Row],[BO ID]],1) -> #REF! | AI6: =INVESTORS_LIST[[#This Row],[LS_TOTAL COST VALUE OF CURRENT UNITS]]+INVESTORS_LIST[[#This Row],[SIP_TOTAL COST VALUE OF CURRENT UNITS]] -> 0 | AJ6: =IF(INVESTORS_LIST[[#This Row],[TOTAL CURRENT UNITS]]=0,0,INVESTORS_LIST[[#This Row],[LS_TOTAL CURRENT UNITS]]/INVESTORS_LIST[[#This Row],[TOTAL CURRENT UNITS]]) -> 0 | AK6: =IF(INVESTORS_LIST[[#This Row],[TOTAL CURRENT UNITS]]=0,0,INVESTORS_LIST[[#This Row],[SIP_TOTAL CURRENT UNITS]]/INVESTORS_LIST[[#This Row],[TOTAL CURRENT UNITS]]) -> 0 | AL6: {=IF(INVESTORS_LIST[[#This Row],[LS_TOTAL UNITS BUY]]>0,INDEX(LS[NAV at Cost (Average)],MATCH(CONCATENATE(COUNTIFS(LS[Investor ID],INVESTORS_LIST[[#This Row],[INVESTOR CODE]]),INVESTORS_LIST[[#This Row],[INVESTOR CODE]]),LS[Unique Code],0),),0)} -> 0 | AM6: {=IF(INVESTORS_LIST[[#This Row],[SIP_TOTAL UNITS BUY]]>0,INDEX(SIP[NAV at Cost (Average)],MATCH(CONCATENATE(COUNTIFS(SIP[Investor ID],INVESTORS_LIST[[#This Row],[INVESTOR CODE]]),INVESTORS_LIST[[#This Row],[INVESTOR CODE]]),SIP[Unique Code],0),),0)} -> 0 | AN6: =IF(INVESTORS_LIST[[#This Row],[TOTAL CURRENT UNITS]]=0,0,(INVESTORS_LIST[[#This Row],[LS_WEIGHT]]*INVESTORS_LIST[[#This Row],[LS_AVERAGE COST]])+(INVESTORS_LIST[[#This Row],[SIP_WEIGHT]]*INVESTORS_LIST[[#This Row],[SIP_AVERAGE COST]])) -> 0 | AO6: =NAV_MKT -> 14.224 | AP6: =IF(INVESTORS_LIST[[#This Row],[TOTAL CURRENT UNITS]]=0,0,INVESTORS_LIST[[#This Row],[TOTAL CURRENT UNITS]]*INVESTORS_LIST[[#This Row],[NAV]]) -> 0 | AQ6: =IF(INVESTORS_LIST[[#This Row],[LS_TOTAL CURRENT UNITS]]=0,0,INVESTORS_LIST[[#This Row],[LS_TOTAL CURRENT UNITS]]*INVESTORS_LIST[[#This Row],[NAV]]) -> 0 | AR6: =IF(INVESTORS_LIST[[#This Row],[SIP_TOTAL CURRENT UNITS]]=0,0,INVESTORS_LIST[[#This Row],[SIP_TOTAL CURRENT UNITS]]*INVESTORS_LIST[[#This Row],[NAV]]) -> 0 | AS6: =INVESTORS_LIST[[#This Row],[TOTAL CURRENT UNITS]] -> 0 | AT6: =IF(INVESTORS_LIST[[#This Row],[TOTAL SELLABLE UNITS]]=0,0,INVESTORS_LIST[[#This Row],[TOTAL SELLABLE UNITS]]*INVESTORS_LIST[[#This Row],[NAV]]) -> 0 | AU6: =INVESTORS_LIST[[#This Row],[LS_TOTAL REALIZED GAIN]]+INVESTORS_LIST[[#This Row],[SIP_TOTAL REALIZED GAIN]] -> 0 | AV6: =INVESTORS_LIST[[#This Row],[TOTAL MARKET VALUE]]-INVESTORS_LIST[[#This Row],[TOTAL COST VALUE OF CURRENT INVESTMENT]] -> 0 | AW6: =IFERROR(INVESTORS_LIST[[#This Row],[TOTAL CURRENT UNITS]]/SUM(INVESTORS_LIST[TOTAL CURRENT UNITS]),0) -> 0
A7: BISWAS ARIFUR RAHMAN | B7: A00007 | C7: Dear Mr. | D7: Individual | E7: =SUMIFS(LS[Unit],LS[Investor ID],INVESTORS_LIST[[#This Row],[INVESTOR CODE]],LS[B/S],"B") -> 0 | F7: =-SUMIFS(LS[Unit],LS[Investor ID],INVESTORS_LIST[[#This Row],[INVESTOR CODE]],LS[B/S],"S") -> 0 | G7: =IF(INVESTORS_LIST[[#This Row],[LS_TOTAL UNITS BUY]]=0,0,INVESTORS_LIST[[#This Row],[LS_TOTAL UNITS BUY]]-INVESTORS_LIST[[#This Row],[LS_TOTAL UNITS SOLD]]) -> 0 | H7: =IF(INVESTORS_LIST[[#This Row],[LS_TOTAL UNITS BUY]]=0,0,SUMIFS(LS[Amount],LS[Investor ID],INVESTORS_LIST[[#This Row],[INVESTOR CODE]],LS[B/S],"B")) -> 0 | I7: =IF(INVESTORS_LIST[[#This Row],[LS_TOTAL UNITS SOLD]]=0,0,SUMIFS(LS[Cost of Units Sold],LS[Investor ID],INVESTORS_LIST[[#This Row],[INVESTOR CODE]],LS[B/S],"S")) -> 0 | J7: =IF(INVESTORS_LIST[[#This Row],[LS_TOTAL CURRENT UNITS]]=0,0,INVESTORS_LIST[[#This Row],[LS_TOTAL CURRENT UNITS]]*INVESTORS_LIST[[#This Row],[LS_AVERAGE COST]]) -> 0 | K7: =IF(INVESTORS_LIST[[#This Row],[LS_TOTAL UNITS SOLD]]=0,0,SUMIFS(LS[Realized Gain],LS[Investor ID],INVESTORS_LIST[[#This Row],[INVESTOR CODE]],LS[B/S],"S")) -> 0 | L7: =SUMIFS(SIP[Unit],SIP[Investor ID],INVESTORS_LIST[[#This Row],[INVESTOR CODE]],SIP[B/S],"B") -> 0 | M7: =-SUMIFS(SIP[Unit],SIP[Investor ID],INVESTORS_LIST[[#This Row],[INVESTOR CODE]],SIP[B/S],"S") -> 0 | N7: =IF(INVESTORS_LIST[[#This Row],[SIP_TOTAL UNITS BUY]]=0,0,INVESTORS_LIST[[#This Row],[SIP_TOTAL UNITS BUY]]-INVESTORS_LIST[[#This Row],[SIP_TOTAL UNITS SOLD]]) -> 0 | O7: =IF(INVESTORS_LIST[[#This Row],[SIP_TOTAL UNITS BUY]]=0,0,SUMIFS(SIP[Amount],SIP[Investor ID],INVESTORS_LIST[[#This Row],[INVESTOR CODE]],SIP[B/S],"B")) -> 0 | P7: =IF(INVESTORS_LIST[[#This Row],[SIP_TOTAL UNITS SOLD]]=0,0,SUMIFS(SIP[Cost of Units Sold],SIP[Investor ID],INVESTORS_LIST[[#This Row],[INVESTOR CODE]],SIP[B/S],"S")) -> 0 | Q7: =IF(INVESTORS_LIST[[#This Row],[SIP_TOTAL CURRENT UNITS]]=0,0,INVESTORS_LIST[[#This Row],[SIP_TOTAL CURRENT UNITS]]*INVESTORS_LIST[[#This Row],[SIP_AVERAGE COST]]) -> 0 | R7: =IF(INVESTORS_LIST[[#This Row],[SIP_TOTAL UNITS SOLD]]=0,0,SUMIFS(SIP[Realized Gain],SIP[Investor ID],INVESTORS_LIST[[#This Row],[INVESTOR CODE]],SIP[B/S],"S")) -> 0 | S7: =INVESTORS_LIST[[#This Row],[LS_TOTAL UNITS BUY]]+INVESTORS_LIST[[#This Row],[SIP_TOTAL UNITS BUY]] -> 0 | T7: =INVESTORS_LIST[[#This Row],[LS_TOTAL UNITS SOLD]]+INVESTORS_LIST[[#This Row],[SIP_TOTAL UNITS SOLD]] -> 0 | V7: =SUMIFS(LS[BO UNIT TRANSFER],LS[Investor ID],INVESTORS_LIST[[#This Row],[INVESTOR CODE]],LS[B/S],"B") -> 0 | W7: =SUMIFS(SIP[BO UNIT TRANSFER],SIP[Investor ID],INVESTORS_LIST[[#This Row],[INVESTOR CODE]],SIP[B/S],"B") -> 0 | X7: =SUMIFS(LS[BO UNIT TRANSFER],LS[Investor ID],INVESTORS_LIST[[#This Row],[INVESTOR CODE]],LS[B/S],"S") -> 0 | Y7: =SUMIFS(SIP[BO UNIT TRANSFER],SIP[Investor ID],INVESTORS_LIST[[#This Row],[INVESTOR CODE]],SIP[B/S],"S") -> 0 | Z7: =SUM(INVESTORS_LIST[[#This Row],[BO OPENING BALANCE]:[BO SIP UNITS REPURCHASE]]) -> 0 | AA7: =INVESTORS_LIST[[#This Row],[TOTAL UNITS BUY]]-INVESTORS_LIST[[#This Row],[TOTAL UNITS SOLD]] -> 0 | AB7: =INVESTORS_LIST[[#This Row],[TOTAL CURRENT UNITS]]-INVESTORS_LIST[[#This Row],[BO UNITS HOLD]] -> 0 | AC7: =INDEX([3]!Table_1[BO ID],MATCH(INVESTORS_LIST[[#This Row],[INVESTOR CODE]],[3]!Table_1[INVESTOR CODE],0)) -> #REF! | AD7: =INDEX([3]!Table_1[Brokerage Name2],MATCH(INVESTORS_LIST[[#This Row],[INVESTOR CODE]],[3]!Table_1[INVESTOR CODE],0)) -> #REF! | AE7: =MID(INVESTORS_LIST[[#This Row],[BO ID]],4,5) -> #REF! | AF7: =MID(INVESTORS_LIST[[#This Row],[BO ID]],2,7) -> #REF! | AG7: =MID(INVESTORS_LIST[[#This Row],[BO ID]],9,7) -> #REF! | AH7: =RIGHT(INVESTORS_LIST[[#This Row],[BO ID]],1) -> #REF! | AI7: =INVESTORS_LIST[[#This Row],[LS_TOTAL COST VALUE OF CURRENT UNITS]]+INVESTORS_LIST[[#This Row],[SIP_TOTAL COST VALUE OF CURRENT UNITS]] -> 0 | AJ7: =IF(INVESTORS_LIST[[#This Row],[TOTAL CURRENT UNITS]]=0,0,INVESTORS_LIST[[#This Row],[LS_TOTAL CURRENT UNITS]]/INVESTORS_LIST[[#This Row],[TOTAL CURRENT UNITS]]) -> 0 | AK7: =IF(INVESTORS_LIST[[#This Row],[TOTAL CURRENT UNITS]]=0,0,INVESTORS_LIST[[#This Row],[SIP_TOTAL CURRENT UNITS]]/INVESTORS_LIST[[#This Row],[TOTAL CURRENT UNITS]]) -> 0 | AL7: {=IF(INVESTORS_LIST[[#This Row],[LS_TOTAL UNITS BUY]]>0,INDEX(LS[NAV at Cost (Average)],MATCH(CONCATENATE(COUNTIFS(LS[Investor ID],INVESTORS_LIST[[#This Row],[INVESTOR CODE]]),INVESTORS_LIST[[#This Row],[INVESTOR CODE]]),LS[Unique Code],0),),0)} -> 0 | AM7: {=IF(INVESTORS_LIST[[#This Row],[SIP_TOTAL UNITS BUY]]>0,INDEX(SIP[NAV at Cost (Average)],MATCH(CONCATENATE(COUNTIFS(SIP[Investor ID],INVESTORS_LIST[[#This Row],[INVESTOR CODE]]),INVESTORS_LIST[[#This Row],[INVESTOR CODE]]),SIP[Unique Code],0),),0)} -> 0 | AN7: =IF(INVESTORS_LIST[[#This Row],[TOTAL CURRENT UNITS]]=0,0,(INVESTORS_LIST[[#This Row],[LS_WEIGHT]]*INVESTORS_LIST[[#This Row],[LS_AVERAGE COST]])+(INVESTORS_LIST[[#This Row],[SIP_WEIGHT]]*INVESTORS_LIST[[#This Row],[SIP_AVERAGE COST]])) -> 0 | AO7: =NAV_MKT -> 14.224 | AP7: =IF(INVESTORS_LIST[[#This Row],[TOTAL CURRENT UNITS]]=0,0,INVESTORS_LIST[[#This Row],[TOTAL CURRENT UNITS]]*INVESTORS_LIST[[#This Row],[NAV]]) -> 0 | AQ7: =IF(INVESTORS_LIST[[#This Row],[LS_TOTAL CURRENT UNITS]]=0,0,INVESTORS_LIST[[#This Row],[LS_TOTAL CURRENT UNITS]]*INVESTORS_LIST[[#This Row],[NAV]]) -> 0 | AR7: =IF(INVESTORS_LIST[[#This Row],[SIP_TOTAL CURRENT UNITS]]=0,0,INVESTORS_LIST[[#This Row],[SIP_TOTAL CURRENT UNITS]]*INVESTORS_LIST[[#This Row],[NAV]]) -> 0 | AS7: =INVESTORS_LIST[[#This Row],[TOTAL CURRENT UNITS]] -> 0 | AT7: =IF(INVESTORS_LIST[[#This Row],[TOTAL SELLABLE UNITS]]=0,0,INVESTORS_LIST[[#This Row],[TOTAL SELLABLE UNITS]]*INVESTORS_LIST[[#This Row],[NAV]]) -> 0 | AU7: =INVESTORS_LIST[[#This Row],[LS_TOTAL REALIZED GAIN]]+INVESTORS_LIST[[#This Row],[SIP_TOTAL REALIZED GAIN]] -> 0 | AV7: =INVESTORS_LIST[[#This Row],[TOTAL MARKET VALUE]]-INVESTORS_LIST[[#This Row],[TOTAL COST VALUE OF CURRENT INVESTMENT]] -> 0 | AW7: =IFERROR(INVESTORS_LIST[[#This Row],[TOTAL CURRENT UNITS]]/SUM(INVESTORS_LIST[TOTAL CURRENT UNITS]),0) -> 0
A8: JEWEL SAHA | B8: A00008 | C8: Dear Mr. | D8: Individual | E8: =SUMIFS(LS[Unit],LS[Investor ID],INVESTORS_LIST[[#This Row],[INVESTOR CODE]],LS[B/S],"B") -> 0 | F8: =-SUMIFS(LS[Unit],LS[Investor ID],INVESTORS_LIST[[#This Row],[INVESTOR CODE]],LS[B/S],"S") -> 0 | G8: =IF(INVESTORS_LIST[[#This Row],[LS_TOTAL UNITS BUY]]=0,0,INVESTORS_LIST[[#This Row],[LS_TOTAL UNITS BUY]]-INVESTORS_LIST[[#This Row],[LS_TOTAL UNITS SOLD]]) -> 0 | H8: =IF(INVESTORS_LIST[[#This Row],[LS_TOTAL UNITS BUY]]=0,0,SUMIFS(LS[Amount],LS[Investor ID],INVESTORS_LIST[[#This Row],[INVESTOR CODE]],LS[B/S],"B")) -> 0 | I8: =IF(INVESTORS_LIST[[#This Row],[LS_TOTAL UNITS SOLD]]=0,0,SUMIFS(LS[Cost of Units Sold],LS[Investor ID],INVESTORS_LIST[[#This Row],[INVESTOR CODE]],LS[B/S],"S")) -> 0 | J8: =IF(INVESTORS_LIST[[#This Row],[LS_TOTAL CURRENT UNITS]]=0,0,INVESTORS_LIST[[#This Row],[LS_TOTAL CURRENT UNITS]]*INVESTORS_LIST[[#This Row],[LS_AVERAGE COST]]) -> 0 | K8: =IF(INVESTORS_LIST[[#This Row],[LS_TOTAL UNITS SOLD]]=0,0,SUMIFS(LS[Realized Gain],LS[Investor ID],INVESTORS_LIST[[#This Row],[INVESTOR CODE]],LS[B/S],"S")) -> 0 | L8: =SUMIFS(SIP[Unit],SIP[Investor ID],INVESTORS_LIST[[#This Row],[INVESTOR CODE]],SIP[B/S],"B") -> 0 | M8: =-SUMIFS(SIP[Unit],SIP[Investor ID],INVESTORS_LIST[[#This Row],[INVESTOR CODE]],SIP[B/S],"S") -> 0 | N8: =IF(INVESTORS_LIST[[#This Row],[SIP_TOTAL UNITS BUY]]=0,0,INVESTORS_LIST[[#This Row],[SIP_TOTAL UNITS BUY]]-INVESTORS_LIST[[#This Row],[SIP_TOTAL UNITS SOLD]]) -> 0 | O8: =IF(INVESTORS_LIST[[#This Row],[SIP_TOTAL UNITS BUY]]=0,0,SUMIFS(SIP[Amount],SIP[Investor ID],INVESTORS_LIST[[#This Row],[INVESTOR CODE]],SIP[B/S],"B")) -> 0 | P8: =IF(INVESTORS_LIST[[#This Row],[SIP_TOTAL UNITS SOLD]]=0,0,SUMIFS(SIP[Cost of Units Sold],SIP[Investor ID],INVESTORS_LIST[[#This Row],[INVESTOR CODE]],SIP[B/S],"S")) -> 0 | Q8: =IF(INVESTORS_LIST[[#This Row],[SIP_TOTAL CURRENT UNITS]]=0,0,INVESTORS_LIST[[#This Row],[SIP_TOTAL CURRENT UNITS]]*INVESTORS_LIST[[#This Row],[SIP_AVERAGE COST]]) -> 0 | R8: =IF(INVESTORS_LIST[[#This Row],[SIP_TOTAL UNITS SOLD]]=0,0,SUMIFS(SIP[Realized Gain],SIP[Investor ID],INVESTORS_LIST[[#This Row],[INVESTOR CODE]],SIP[B/S],"S")) -> 0 | S8: =INVESTORS_LIST[[#This Row],[LS_TOTAL UNITS BUY]]+INVESTORS_LIST[[#This Row],[SIP_TOTAL UNITS BUY]] -> 0 | T8: =INVESTORS_LIST[[#This Row],[LS_TOTAL UNITS SOLD]]+INVESTORS_LIST[[#This Row],[SIP_TOTAL UNITS SOLD]] -> 0 | V8: =SUMIFS(LS[BO UNIT TRANSFER],LS[Investor ID],INVESTORS_LIST[[#This Row],[INVESTOR CODE]],LS[B/S],"B") -> 0 | W8: =SUMIFS(SIP[BO UNIT TRANSFER],SIP[Investor ID],INVESTORS_LIST[[#This Row],[INVESTOR CODE]],SIP[B/S],"B") -> 0 | X8: =SUMIFS(LS[BO UNIT TRANSFER],LS[Investor ID],INVESTORS_LIST[[#This Row],[INVESTOR CODE]],LS[B/S],"S") -> 0 | Y8: =SUMIFS(SIP[BO UNIT TRANSFER],SIP[Investor ID],INVESTORS_LIST[[#This Row],[INVESTOR CODE]],SIP[B/S],"S") -> 0 | Z8: =SUM(INVESTORS_LIST[[#This Row],[BO OPENING BALANCE]:[BO SIP UNITS REPURCHASE]]) -> 0 | AA8: =INVESTORS_LIST[[#This Row],[TOTAL UNITS BUY]]-INVESTORS_LIST[[#This Row],[TOTAL UNITS SOLD]] -> 0 | AB8: =INVESTORS_LIST[[#This Row],[TOTAL CURRENT UNITS]]-INVESTORS_LIST[[#This Row],[BO UNITS HOLD]] -> 0 | AC8: =INDEX([3]!Table_1[BO ID],MATCH(INVESTORS_LIST[[#This Row],[INVESTOR CODE]],[3]!Table_1[INVESTOR CODE],0)) -> #REF! | AD8: =INDEX([3]!Table_1[Brokerage Name2],MATCH(INVESTORS_LIST[[#This Row],[INVESTOR CODE]],[3]!Table_1[INVESTOR CODE],0)) -> #REF! | AE8: =MID(INVESTORS_LIST[[#This Row],[BO ID]],4,5) -> #REF! | AF8: =MID(INVESTORS_LIST[[#This Row],[BO ID]],2,7) -> #REF! | AG8: =MID(INVESTORS_LIST[[#This Row],[BO ID]],9,7) -> #REF! | AH8: =RIGHT(INVESTORS_LIST[[#This Row],[BO ID]],1) -> #REF! | AI8: =INVESTORS_LIST[[#This Row],[LS_TOTAL COST VALUE OF CURRENT UNITS]]+INVESTORS_LIST[[#This Row],[SIP_TOTAL COST VALUE OF CURRENT UNITS]] -> 0 | AJ8: =IF(INVESTORS_LIST[[#This Row],[TOTAL CURRENT UNITS]]=0,0,INVESTORS_LIST[[#This Row],[LS_TOTAL CURRENT UNITS]]/INVESTORS_LIST[[#This Row],[TOTAL CURRENT UNITS]]) -> 0 | AK8: =IF(INVESTORS_LIST[[#This Row],[TOTAL CURRENT UNITS]]=0,0,INVESTORS_LIST[[#This Row],[SIP_TOTAL CURRENT UNITS]]/INVESTORS_LIST[[#This Row],[TOTAL CURRENT UNITS]]) -> 0 | AL8: {=IF(INVESTORS_LIST[[#This Row],[LS_TOTAL UNITS BUY]]>0,INDEX(LS[NAV at Cost (Average)],MATCH(CONCATENATE(COUNTIFS(LS[Investor ID],INVESTORS_LIST[[#This Row],[INVESTOR CODE]]),INVESTORS_LIST[[#This Row],[INVESTOR CODE]]),LS[Unique Code],0),),0)} -> 0 | AM8: {=IF(INVESTORS_LIST[[#This Row],[SIP_TOTAL UNITS BUY]]>0,INDEX(SIP[NAV at Cost (Average)],MATCH(CONCATENATE(COUNTIFS(SIP[Investor ID],INVESTORS_LIST[[#This Row],[INVESTOR CODE]]),INVESTORS_LIST[[#This Row],[INVESTOR CODE]]),SIP[Unique Code],0),),0)} -> 0 | AN8: =IF(INVESTORS_LIST[[#This Row],[TOTAL CURRENT UNITS]]=0,0,(INVESTORS_LIST[[#This Row],[LS_WEIGHT]]*INVESTORS_LIST[[#This Row],[LS_AVERAGE COST]])+(INVESTORS_LIST[[#This Row],[SIP_WEIGHT]]*INVESTORS_LIST[[#This Row],[SIP_AVERAGE COST]])) -> 0 | AO8: =NAV_MKT -> 14.224 | AP8: =IF(INVESTORS_LIST[[#This Row],[TOTAL CURRENT UNITS]]=0,0,INVESTORS_LIST[[#This Row],[TOTAL CURRENT UNITS]]*INVESTORS_LIST[[#This Row],[NAV]]) -> 0 | AQ8: =IF(INVESTORS_LIST[[#This Row],[LS_TOTAL CURRENT UNITS]]=0,0,INVESTORS_LIST[[#This Row],[LS_TOTAL CURRENT UNITS]]*INVESTORS_LIST[[#This Row],[NAV]]) -> 0 | AR8: =IF(INVESTORS_LIST[[#This Row],[SIP_TOTAL CURRENT UNITS]]=0,0,INVESTORS_LIST[[#This Row],[SIP_TOTAL CURRENT UNITS]]*INVESTORS_LIST[[#This Row],[NAV]]) -> 0 | AS8: =INVESTORS_LIST[[#This Row],[TOTAL CURRENT UNITS]] -> 0 | AT8: =IF(INVESTORS_LIST[[#This Row],[TOTAL SELLABLE UNITS]]=0,0,INVESTORS_LIST[[#This Row],[TOTAL SELLABLE UNITS]]*INVESTORS_LIST[[#This Row],[NAV]]) -> 0 | AU8: =INVESTORS_LIST[[#This Row],[LS_TOTAL REALIZED GAIN]]+INVESTORS_LIST[[#This Row],[SIP_TOTAL REALIZED GAIN]] -> 0 | AV8: =INVESTORS_LIST[[#This Row],[TOTAL MARKET VALUE]]-INVESTORS_LIST[[#This Row],[TOTAL COST VALUE OF CURRENT INVESTMENT]] -> 0 | AW8: =IFERROR(INVESTORS_LIST[[#This Row],[TOTAL CURRENT UNITS]]/SUM(INVESTORS_LIST[TOTAL CURRENT UNITS]),0) -> 0
A9: SHIBBIR AHMED | B9: A00009 | C9: Dear Mr. | D9: Individual | E9: =SUMIFS(LS[Unit],LS[Investor ID],INVESTORS_LIST[[#This Row],[INVESTOR CODE]],LS[B/S],"B") -> 0 | F9: =-SUMIFS(LS[Unit],LS[Investor ID],INVESTORS_LIST[[#This Row],[INVESTOR CODE]],LS[B/S],"S") -> 0 | G9: =IF(INVESTORS_LIST[[#This Row],[LS_TOTAL UNITS BUY]]=0,0,INVESTORS_LIST[[#This Row],[LS_TOTAL UNITS BUY]]-INVESTORS_LIST[[#This Row],[LS_TOTAL UNITS SOLD]]) -> 0 | H9: =IF(INVESTORS_LIST[[#This Row],[LS_TOTAL UNITS BUY]]=0,0,SUMIFS(LS[Amount],LS[Investor ID],INVESTORS_LIST[[#This Row],[INVESTOR CODE]],LS[B/S],"B")) -> 0 | I9: =IF(INVESTORS_LIST[[#This Row],[LS_TOTAL UNITS SOLD]]=0,0,SUMIFS(LS[Cost of Units Sold],LS[Investor ID],INVESTORS_LIST[[#This Row],[INVESTOR CODE]],LS[B/S],"S")) -> 0 | J9: =IF(INVESTORS_LIST[[#This Row],[LS_TOTAL CURRENT UNITS]]=0,0,INVESTORS_LIST[[#This Row],[LS_TOTAL CURRENT UNITS]]*INVESTORS_LIST[[#This Row],[LS_AVERAGE COST]]) -> 0 | K9: =IF(INVESTORS_LIST[[#This Row],[LS_TOTAL UNITS SOLD]]=0,0,SUMIFS(LS[Realized Gain],LS[Investor ID],INVESTORS_LIST[[#This Row],[INVESTOR CODE]],LS[B/S],"S")) -> 0 | L9: =SUMIFS(SIP[Unit],SIP[Investor ID],INVESTORS_LIST[[#This Row],[INVESTOR CODE]],SIP[B/S],"B") -> 0 | M9: =-SUMIFS(SIP[Unit],SIP[Investor ID],INVESTORS_LIST[[#This Row],[INVESTOR CODE]],SIP[B/S],"S") -> 0 | N9: =IF(INVESTORS_LIST[[#This Row],[SIP_TOTAL UNITS BUY]]=0,0,INVESTORS_LIST[[#This Row],[SIP_TOTAL UNITS BUY]]-INVESTORS_LIST[[#This Row],[SIP_TOTAL UNITS SOLD]]) -> 0 | O9: =IF(INVESTORS_LIST[[#This Row],[SIP_TOTAL UNITS BUY]]=0,0,SUMIFS(SIP[Amount],SIP[Investor ID],INVESTORS_LIST[[#This Row],[INVESTOR CODE]],SIP[B/S],"B")) -> 0 | P9: =IF(INVESTORS_LIST[[#This Row],[SIP_TOTAL UNITS SOLD]]=0,0,SUMIFS(SIP[Cost of Units Sold],SIP[Investor ID],INVESTORS_LIST[[#This Row],[INVESTOR CODE]],SIP[B/S],"S")) -> 0 | Q9: =IF(INVESTORS_LIST[[#This Row],[SIP_TOTAL CURRENT UNITS]]=0,0,INVESTORS_LIST[[#This Row],[SIP_TOTAL CURRENT UNITS]]*INVESTORS_LIST[[#This Row],[SIP_AVERAGE COST]]) -> 0 | R9: =IF(INVESTORS_LIST[[#This Row],[SIP_TOTAL UNITS SOLD]]=0,0,SUMIFS(SIP[Realized Gain],SIP[Investor ID],INVESTORS_LIST[[#This Row],[INVESTOR CODE]],SIP[B/S],"S")) -> 0 | S9: =INVESTORS_LIST[[#This Row],[LS_TOTAL UNITS BUY]]+INVESTORS_LIST[[#This Row],[SIP_TOTAL UNITS BUY]] -> 0 | T9: =INVESTORS_LIST[[#This Row],[LS_TOTAL UNITS SOLD]]+INVESTORS_LIST[[#This Row],[SIP_TOTAL UNITS SOLD]] -> 0 | V9: =SUMIFS(LS[BO UNIT TRANSFER],LS[Investor ID],INVESTORS_LIST[[#This Row],[INVESTOR CODE]],LS[B/S],"B") -> 0 | W9: =SUMIFS(SIP[BO UNIT TRANSFER],SIP[Investor ID],INVESTORS_LIST[[#This Row],[INVESTOR CODE]],SIP[B/S],"B") -> 0 | X9: =SUMIFS(LS[BO UNIT TRANSFER],LS[Investor ID],INVESTORS_LIST[[#This Row],[INVESTOR CODE]],LS[B/S],"S") -> 0 | Y9: =SUMIFS(SIP[BO UNIT TRANSFER],SIP[Investor ID],INVESTORS_LIST[[#This Row],[INVESTOR CODE]],SIP[B/S],"S") -> 0 | Z9: =SUM(INVESTORS_LIST[[#This Row],[BO OPENING BALANCE]:[BO SIP UNITS REPURCHASE]]) -> 0 | AA9: =INVESTORS_LIST[[#This Row],[TOTAL UNITS BUY]]-INVESTORS_LIST[[#This Row],[TOTAL UNITS SOLD]] -> 0 | AB9: =INVESTORS_LIST[[#This Row],[TOTAL CURRENT UNITS]]-INVESTORS_LIST[[#This Row],[BO UNITS HOLD]] -> 0 | AC9: =INDEX([3]!Table_1[BO ID],MATCH(INVESTORS_LIST[[#This Row],[INVESTOR CODE]],[3]!Table_1[INVESTOR CODE],0)) -> #REF! | AD9: =INDEX([3]!Table_1[Brokerage Name2],MATCH(INVESTORS_LIST[[#This Row],[INVESTOR CODE]],[3]!Table_1[INVESTOR CODE],0)) -> #REF! | AE9: =MID(INVESTORS_LIST[[#This Row],[BO ID]],4,5) -> #REF! | AF9: =MID(INVESTORS_LIST[[#This Row],[BO ID]],2,7) -> #REF! | AG9: =MID(INVESTORS_LIST[[#This Row],[BO ID]],9,7) -> #REF! | AH9: =RIGHT(INVESTORS_LIST[[#This Row],[BO ID]],1) -> #REF! | AI9: =INVESTORS_LIST[[#This Row],[LS_TOTAL COST VALUE OF CURRENT UNITS]]+INVESTORS_LIST[[#This Row],[SIP_TOTAL COST VALUE OF CURRENT UNITS]] -> 0 | AJ9: =IF(INVESTORS_LIST[[#This Row],[TOTAL CURRENT UNITS]]=0,0,INVESTORS_LIST[[#This Row],[LS_TOTAL CURRENT UNITS]]/INVESTORS_LIST[[#This Row],[TOTAL CURRENT UNITS]]) -> 0 | AK9: =IF(INVESTORS_LIST[[#This Row],[TOTAL CURRENT UNITS]]=0,0,INVESTORS_LIST[[#This Row],[SIP_TOTAL CURRENT UNITS]]/INVESTORS_LIST[[#This Row],[TOTAL CURRENT UNITS]]) -> 0 | AL9: {=IF(INVESTORS_LIST[[#This Row],[LS_TOTAL UNITS BUY]]>0,INDEX(LS[NAV at Cost (Average)],MATCH(CONCATENATE(COUNTIFS(LS[Investor ID],INVESTORS_LIST[[#This Row],[INVESTOR CODE]]),INVESTORS_LIST[[#This Row],[INVESTOR CODE]]),LS[Unique Code],0),),0)} -> 0 | AM9: {=IF(INVESTORS_LIST[[#This Row],[SIP_TOTAL UNITS BUY]]>0,INDEX(SIP[NAV at Cost (Average)],MATCH(CONCATENATE(COUNTIFS(SIP[Investor ID],INVESTORS_LIST[[#This Row],[INVESTOR CODE]]),INVESTORS_LIST[[#This Row],[INVESTOR CODE]]),SIP[Unique Code],0),),0)} -> 0 | AN9: =IF(INVESTORS_LIST[[#This Row],[TOTAL CURRENT UNITS]]=0,0,(INVESTORS_LIST[[#This Row],[LS_WEIGHT]]*INVESTORS_LIST[[#This Row],[LS_AVERAGE COST]])+(INVESTORS_LIST[[#This Row],[SIP_WEIGHT]]*INVESTORS_LIST[[#This Row],[SIP_AVERAGE COST]])) -> 0 | AO9: =NAV_MKT -> 14.224 | AP9: =IF(INVESTORS_LIST[[#This Row],[TOTAL CURRENT UNITS]]=0,0,INVESTORS_LIST[[#This Row],[TOTAL CURRENT UNITS]]*INVESTORS_LIST[[#This Row],[NAV]]) -> 0 | AQ9: =IF(INVESTORS_LIST[[#This Row],[LS_TOTAL CURRENT UNITS]]=0,0,INVESTORS_LIST[[#This Row],[LS_TOTAL CURRENT UNITS]]*INVESTORS_LIST[[#This Row],[NAV]]) -> 0 | AR9: =IF(INVESTORS_LIST[[#This Row],[SIP_TOTAL CURRENT UNITS]]=0,0,INVESTORS_LIST[[#This Row],[SIP_TOTAL CURRENT UNITS]]*INVESTORS_LIST[[#This Row],[NAV]]) -> 0 | AS9: =INVESTORS_LIST[[#This Row],[TOTAL CURRENT UNITS]] -> 0 | AT9: =IF(INVESTORS_LIST[[#This Row],[TOTAL SELLABLE UNITS]]=0,0,INVESTORS_LIST[[#This Row],[TOTAL SELLABLE UNITS]]*INVESTORS_LIST[[#This Row],[NAV]]) -> 0 | AU9: =INVESTORS_LIST[[#This Row],[LS_TOTAL REALIZED GAIN]]+INVESTORS_LIST[[#This Row],[SIP_TOTAL REALIZED GAIN]] -> 0 | AV9: =INVESTORS_LIST[[#This Row],[TOTAL MARKET VALUE]]-INVESTORS_LIST[[#This Row],[TOTAL COST VALUE OF CURRENT INVESTMENT]] -> 0 | AW9: =IFERROR(INVESTORS_LIST[[#This Row],[TOTAL CURRENT UNITS]]/SUM(INVESTORS_LIST[TOTAL CURRENT UNITS]),0) -> 0
A10: SHYAMAL KRISHNA SAHA | B10: A00010 | C10: Dear Mr. | D10: Individual | E10: =SUMIFS(LS[Unit],LS[Investor ID],INVESTORS_LIST[[#This Row],[INVESTOR CODE]],LS[B/S],"B") -> 0 | F10: =-SUMIFS(LS[Unit],LS[Investor ID],INVESTORS_LIST[[#This Row],[INVESTOR CODE]],LS[B/S],"S") -> 0 | G10: =IF(INVESTORS_LIST[[#This Row],[LS_TOTAL UNITS BUY]]=0,0,INVESTORS_LIST[[#This Row],[LS_TOTAL UNITS BUY]]-INVESTORS_LIST[[#This Row],[LS_TOTAL UNITS SOLD]]) -> 0 | H10: =IF(INVESTORS_LIST[[#This Row],[LS_TOTAL UNITS BUY]]=0,0,SUMIFS(LS[Amount],LS[Investor ID],INVESTORS_LIST[[#This Row],[INVESTOR CODE]],LS[B/S],"B")) -> 0 | I10: =IF(INVESTORS_LIST[[#This Row],[LS_TOTAL UNITS SOLD]]=0,0,SUMIFS(LS[Cost of Units Sold],LS[Investor ID],INVESTORS_LIST[[#This Row],[INVESTOR CODE]],LS[B/S],"S")) -> 0 | J10: =IF(INVESTORS_LIST[[#This Row],[LS_TOTAL CURRENT UNITS]]=0,0,INVESTORS_LIST[[#This Row],[LS_TOTAL CURRENT UNITS]]*INVESTORS_LIST[[#This Row],[LS_AVERAGE COST]]) -> 0 | K10: =IF(INVESTORS_LIST[[#This Row],[LS_TOTAL UNITS SOLD]]=0,0,SUMIFS(LS[Realized Gain],LS[Investor ID],INVESTORS_LIST[[#This Row],[INVESTOR CODE]],LS[B/S],"S")) -> 0 | L10: =SUMIFS(SIP[Unit],SIP[Investor ID],INVESTORS_LIST[[#This Row],[INVESTOR CODE]],SIP[B/S],"B") -> 0 | M10: =-SUMIFS(SIP[Unit],SIP[Investor ID],INVESTORS_LIST[[#This Row],[INVESTOR CODE]],SIP[B/S],"S") -> 0 | N10: =IF(INVESTORS_LIST[[#This Row],[SIP_TOTAL UNITS BUY]]=0,0,INVESTORS_LIST[[#This Row],[SIP_TOTAL UNITS BUY]]-INVESTORS_LIST[[#This Row],[SIP_TOTAL UNITS SOLD]]) -> 0 | O10: =IF(INVESTORS_LIST[[#This Row],[SIP_TOTAL UNITS BUY]]=0,0,SUMIFS(SIP[Amount],SIP[Investor ID],INVESTORS_LIST[[#This Row],[INVESTOR CODE]],SIP[B/S],"B")) -> 0 | P10: =IF(INVESTORS_LIST[[#This Row],[SIP_TOTAL UNITS SOLD]]=0,0,SUMIFS(SIP[Cost of Units Sold],SIP[Investor ID],INVESTORS_LIST[[#This Row],[INVESTOR CODE]],SIP[B/S],"S")) -> 0 | Q10: =IF(INVESTORS_LIST[[#This Row],[SIP_TOTAL CURRENT UNITS]]=0,0,INVESTORS_LIST[[#This Row],[SIP_TOTAL CURRENT UNITS]]*INVESTORS_LIST[[#This Row],[SIP_AVERAGE COST]]) -> 0 | R10: =IF(INVESTORS_LIST[[#This Row],[SIP_TOTAL UNITS SOLD]]=0,0,SUMIFS(SIP[Realized Gain],SIP[Investor ID],INVESTORS_LIST[[#This Row],[INVESTOR CODE]],SIP[B/S],"S")) -> 0 | S10: =INVESTORS_LIST[[#This Row],[LS_TOTAL UNITS BUY]]+INVESTORS_LIST[[#This Row],[SIP_TOTAL UNITS BUY]] -> 0 | T10: =INVESTORS_LIST[[#This Row],[LS_TOTAL UNITS SOLD]]+INVESTORS_LIST[[#This Row],[SIP_TOTAL UNITS SOLD]] -> 0 | V10: =SUMIFS(LS[BO UNIT TRANSFER],LS[Investor ID],INVESTORS_LIST[[#This Row],[INVESTOR CODE]],LS[B/S],"B") -> 0 | W10: =SUMIFS(SIP[BO UNIT TRANSFER],SIP[Investor ID],INVESTORS_LIST[[#This Row],[INVESTOR CODE]],SIP[B/S],"B") -> 0 | X10: =SUMIFS(LS[BO UNIT TRANSFER],LS[Investor ID],INVESTORS_LIST[[#This Row],[INVESTOR CODE]],LS[B/S],"S") -> 0 | Y10: =SUMIFS(SIP[BO UNIT TRANSFER],SIP[Investor ID],INVESTORS_LIST[[#This Row],[INVESTOR CODE]],SIP[B/S],"S") -> 0 | Z10: =SUM(INVESTORS_LIST[[#This Row],[BO OPENING BALANCE]:[BO SIP UNITS REPURCHASE]]) -> 0 | AA10: =INVESTORS_LIST[[#This Row],[TOTAL UNITS BUY]]-INVESTORS_LIST[[#This Row],[TOTAL UNITS SOLD]] -> 0 | AB10: =INVESTORS_LIST[[#This Row],[TOTAL CURRENT UNITS]]-INVESTORS_LIST[[#This Row],[BO UNITS HOLD]] -> 0 | AC10: =INDEX([3]!Table_1[BO ID],MATCH(INVESTORS_LIST[[#This Row],[INVESTOR CODE]],[3]!Table_1[INVESTOR CODE],0)) -> #REF! | AD10: =INDEX([3]!Table_1[Brokerage Name2],MATCH(INVESTORS_LIST[[#This Row],[INVESTOR CODE]],[3]!Table_1[INVESTOR CODE],0)) -> #REF! | AE10: =MID(INVESTORS_LIST[[#This Row],[BO ID]],4,5) -> #REF! | AF10: =MID(INVESTORS_LIST[[#This Row],[BO ID]],2,7) -> #REF! | AG10: =MID(INVESTORS_LIST[[#This Row],[BO ID]],9,7) -> #REF! | AH10: =RIGHT(INVESTORS_LIST[[#This Row],[BO ID]],1) -> #REF! | AI10: =INVESTORS_LIST[[#This Row],[LS_TOTAL COST VALUE OF CURRENT UNITS]]+INVESTORS_LIST[[#This Row],[SIP_TOTAL COST VALUE OF CURRENT UNITS]] -> 0 | AJ10: =IF(INVESTORS_LIST[[#This Row],[TOTAL CURRENT UNITS]]=0,0,INVESTORS_LIST[[#This Row],[LS_TOTAL CURRENT UNITS]]/INVESTORS_LIST[[#This Row],[TOTAL CURRENT UNITS]]) -> 0 | AK10: =IF(INVESTORS_LIST[[#This Row],[TOTAL CURRENT UNITS]]=0,0,INVESTORS_LIST[[#This Row],[SIP_TOTAL CURRENT UNITS]]/INVESTORS_LIST[[#This Row],[TOTAL CURRENT UNITS]]) -> 0 | AL10: {=IF(INVESTORS_LIST[[#This Row],[LS_TOTAL UNITS BUY]]>0,INDEX(LS[NAV at Cost (Average)],MATCH(CONCATENATE(COUNTIFS(LS[Investor ID],INVESTORS_LIST[[#This Row],[INVESTOR CODE]]),INVESTORS_LIST[[#This Row],[INVESTOR CODE]]),LS[Unique Code],0),),0)} -> 0 | AM10: {=IF(INVESTORS_LIST[[#This Row],[SIP_TOTAL UNITS BUY]]>0,INDEX(SIP[NAV at Cost (Average)],MATCH(CONCATENATE(COUNTIFS(SIP[Investor ID],INVESTORS_LIST[[#This Row],[INVESTOR CODE]]),INVESTORS_LIST[[#This Row],[INVESTOR CODE]]),SIP[Unique Code],0),),0)} -> 0 | AN10: =IF(INVESTORS_LIST[[#This Row],[TOTAL CURRENT UNITS]]=0,0,(INVESTORS_LIST[[#This Row],[LS_WEIGHT]]*INVESTORS_LIST[[#This Row],[LS_AVERAGE COST]])+(INVESTORS_LIST[[#This Row],[SIP_WEIGHT]]*INVESTORS_LIST[[#This Row],[SIP_AVERAGE COST]])) -> 0 | AO10: =NAV_MKT -> 14.224 | AP10: =IF(INVESTORS_LIST[[#This Row],[TOTAL CURRENT UNITS]]=0,0,INVESTORS_LIST[[#This Row],[TOTAL CURRENT UNITS]]*INVESTORS_LIST[[#This Row],[NAV]]) -> 0 | AQ10: =IF(INVESTORS_LIST[[#This Row],[LS_TOTAL CURRENT UNITS]]=0,0,INVESTORS_LIST[[#This Row],[LS_TOTAL CURRENT UNITS]]*INVESTORS_LIST[[#This Row],[NAV]]) -> 0 | AR10: =IF(INVESTORS_LIST[[#This Row],[SIP_TOTAL CURRENT UNITS]]=0,0,INVESTORS_LIST[[#This Row],[SIP_TOTAL CURRENT UNITS]]*INVESTORS_LIST[[#This Row],[NAV]]) -> 0 | AS10: =INVESTORS_LIST[[#This Row],[TOTAL CURRENT UNITS]] -> 0 | AT10: =IF(INVESTORS_LIST[[#This Row],[TOTAL SELLABLE UNITS]]=0,0,INVESTORS_LIST[[#This Row],[TOTAL SELLABLE UNITS]]*INVESTORS_LIST[[#This Row],[NAV]]) -> 0 | AU10: =INVESTORS_LIST[[#This Row],[LS_TOTAL REALIZED GAIN]]+INVESTORS_LIST[[#This Row],[SIP_TOTAL REALIZED GAIN]] -> 0 | AV10: =INVESTORS_LIST[[#This Row],[TOTAL MARKET VALUE]]-INVESTORS_LIST[[#This Row],[TOTAL COST VALUE OF CURRENT INVESTMENT]] -> 0 | AW10: =IFERROR(INVESTORS_LIST[[#This Row],[TOTAL CURRENT UNITS]]/SUM(INVESTORS_LIST[TOTAL CURRENT UNITS]),0) -> 0
A11: NASRIN AKHTER | B11: A00011 | C11: Dear Ms. | D11: Individual | E11: =SUMIFS(LS[Unit],LS[Investor ID],INVESTORS_LIST[[#This Row],[INVESTOR CODE]],LS[B/S],"B") -> 0 | F11: =-SUMIFS(LS[Unit],LS[Investor ID],INVESTORS_LIST[[#This Row],[INVESTOR CODE]],LS[B/S],"S") -> 0 | G11: =IF(INVESTORS_LIST[[#This Row],[LS_TOTAL UNITS BUY]]=0,0,INVESTORS_LIST[[#This Row],[LS_TOTAL UNITS BUY]]-INVESTORS_LIST[[#This Row],[LS_TOTAL UNITS SOLD]]) -> 0 | H11: =IF(INVESTORS_LIST[[#This Row],[LS_TOTAL UNITS BUY]]=0,0,SUMIFS(LS[Amount],LS[Investor ID],INVESTORS_LIST[[#This Row],[INVESTOR CODE]],LS[B/S],"B")) -> 0 | I11: =IF(INVESTORS_LIST[[#This Row],[LS_TOTAL UNITS SOLD]]=0,0,SUMIFS(LS[Cost of Units Sold],LS[Investor ID],INVESTORS_LIST[[#This Row],[INVESTOR CODE]],LS[B/S],"S")) -> 0 | J11: =IF(INVESTORS_LIST[[#This Row],[LS_TOTAL CURRENT UNITS]]=0,0,INVESTORS_LIST[[#This Row],[LS_TOTAL CURRENT UNITS]]*INVESTORS_LIST[[#This Row],[LS_AVERAGE COST]]) -> 0 | K11: =IF(INVESTORS_LIST[[#This Row],[LS_TOTAL UNITS SOLD]]=0,0,SUMIFS(LS[Realized Gain],LS[Investor ID],INVESTORS_LIST[[#This Row],[INVESTOR CODE]],LS[B/S],"S")) -> 0 | L11: =SUMIFS(SIP[Unit],SIP[Investor ID],INVESTORS_LIST[[#This Row],[INVESTOR CODE]],SIP[B/S],"B") -> 0 | M11: =-SUMIFS(SIP[Unit],SIP[Investor ID],INVESTORS_LIST[[#This Row],[INVESTOR CODE]],SIP[B/S],"S") -> 0 | N11: =IF(INVESTORS_LIST[[#This Row],[SIP_TOTAL UNITS BUY]]=0,0,INVESTORS_LIST[[#This Row],[SIP_TOTAL UNITS BUY]]-INVESTORS_LIST[[#This Row],[SIP_TOTAL UNITS SOLD]]) -> 0 | O11: =IF(INVESTORS_LIST[[#This Row],[SIP_TOTAL UNITS BUY]]=0,0,SUMIFS(SIP[Amount],SIP[Investor ID],INVESTORS_LIST[[#This Row],[INVESTOR CODE]],SIP[B/S],"B")) -> 0 | P11: =IF(INVESTORS_LIST[[#This Row],[SIP_TOTAL UNITS SOLD]]=0,0,SUMIFS(SIP[Cost of Units Sold],SIP[Investor ID],INVESTORS_LIST[[#This Row],[INVESTOR CODE]],SIP[B/S],"S")) -> 0 | Q11: =IF(INVESTORS_LIST[[#This Row],[SIP_TOTAL CURRENT UNITS]]=0,0,INVESTORS_LIST[[#This Row],[SIP_TOTAL CURRENT UNITS]]*INVESTORS_LIST[[#This Row],[SIP_AVERAGE COST]]) -> 0 | R11: =IF(INVESTORS_LIST[[#This Row],[SIP_TOTAL UNITS SOLD]]=0,0,SUMIFS(SIP[Realized Gain],SIP[Investor ID],INVESTORS_LIST[[#This Row],[INVESTOR CODE]],SIP[B/S],"S")) -> 0 | S11: =INVESTORS_LIST[[#This Row],[LS_TOTAL UNITS BUY]]+INVESTORS_LIST[[#This Row],[SIP_TOTAL UNITS BUY]] -> 0 | T11: =INVESTORS_LIST[[#This Row],[LS_TOTAL UNITS SOLD]]+INVESTORS_LIST[[#This Row],[SIP_TOTAL UNITS SOLD]] -> 0 | V11: =SUMIFS(LS[BO UNIT TRANSFER],LS[Investor ID],INVESTORS_LIST[[#This Row],[INVESTOR CODE]],LS[B/S],"B") -> 0 | W11: =SUMIFS(SIP[BO UNIT TRANSFER],SIP[Investor ID],INVESTORS_LIST[[#This Row],[INVESTOR CODE]],SIP[B/S],"B") -> 0 | X11: =SUMIFS(LS[BO UNIT TRANSFER],LS[Investor ID],INVESTORS_LIST[[#This Row],[INVESTOR CODE]],LS[B/S],"S") -> 0 | Y11: =SUMIFS(SIP[BO UNIT TRANSFER],SIP[Investor ID],INVESTORS_LIST[[#This Row],[INVESTOR CODE]],SIP[B/S],"S") -> 0 | Z11: =SUM(INVESTORS_LIST[[#This Row],[BO OPENING BALANCE]:[BO SIP UNITS REPURCHASE]]) -> 0 | AA11: =INVESTORS_LIST[[#This Row],[TOTAL UNITS BUY]]-INVESTORS_LIST[[#This Row],[TOTAL UNITS SOLD]] -> 0 | AB11: =INVESTORS_LIST[[#This Row],[TOTAL CURRENT UNITS]]-INVESTORS_LIST[[#This Row],[BO UNITS HOLD]] -> 0 | AC11: =INDEX([3]!Table_1[BO ID],MATCH(INVESTORS_LIST[[#This Row],[INVESTOR CODE]],[3]!Table_1[INVESTOR CODE],0)) -> #REF! | AD11: =INDEX([3]!Table_1[Brokerage Name2],MATCH(INVESTORS_LIST[[#This Row],[INVESTOR CODE]],[3]!Table_1[INVESTOR CODE],0)) -> #REF! | AE11: =MID(INVESTORS_LIST[[#This Row],[BO ID]],4,5) -> #REF! | AF11: =MID(INVESTORS_LIST[[#This Row],[BO ID]],2,7) -> #REF! | AG11: =MID(INVESTORS_LIST[[#This Row],[BO ID]],9,7) -> #REF! | AH11: =RIGHT(INVESTORS_LIST[[#This Row],[BO ID]],1) -> #REF! | AI11: =INVESTORS_LIST[[#This Row],[LS_TOTAL COST VALUE OF CURRENT UNITS]]+INVESTORS_LIST[[#This Row],[SIP_TOTAL COST VALUE OF CURRENT UNITS]] -> 0 | AJ11: =IF(INVESTORS_LIST[[#This Row],[TOTAL CURRENT UNITS]]=0,0,INVESTORS_LIST[[#This Row],[LS_TOTAL CURRENT UNITS]]/INVESTORS_LIST[[#This Row],[TOTAL CURRENT UNITS]]) -> 0 | AK11: =IF(INVESTORS_LIST[[#This Row],[TOTAL CURRENT UNITS]]=0,0,INVESTORS_LIST[[#This Row],[SIP_TOTAL CURRENT UNITS]]/INVESTORS_LIST[[#This Row],[TOTAL CURRENT UNITS]]) -> 0 | AL11: {=IF(INVESTORS_LIST[[#This Row],[LS_TOTAL UNITS BUY]]>0,INDEX(LS[NAV at Cost (Average)],MATCH(CONCATENATE(COUNTIFS(LS[Investor ID],INVESTORS_LIST[[#This Row],[INVESTOR CODE]]),INVESTORS_LIST[[#This Row],[INVESTOR CODE]]),LS[Unique Code],0),),0)} -> 0 | AM11: {=IF(INVESTORS_LIST[[#This Row],[SIP_TOTAL UNITS BUY]]>0,INDEX(SIP[NAV at Cost (Average)],MATCH(CONCATENATE(COUNTIFS(SIP[Investor ID],INVESTORS_LIST[[#This Row],[INVESTOR CODE]]),INVESTORS_LIST[[#This Row],[INVESTOR CODE]]),SIP[Unique Code],0),),0)} -> 0 | AN11: =IF(INVESTORS_LIST[[#This Row],[TOTAL CURRENT UNITS]]=0,0,(INVESTORS_LIST[[#This Row],[LS_WEIGHT]]*INVESTORS_LIST[[#This Row],[LS_AVERAGE COST]])+(INVESTORS_LIST[[#This Row],[SIP_WEIGHT]]*INVESTORS_LIST[[#This Row],[SIP_AVERAGE COST]])) -> 0 | AO11: =NAV_MKT -> 14.224 | AP11: =IF(INVESTORS_LIST[[#This Row],[TOTAL CURRENT UNITS]]=0,0,INVESTORS_LIST[[#This Row],[TOTAL CURRENT UNITS]]*INVESTORS_LIST[[#This Row],[NAV]]) -> 0 | AQ11: =IF(INVESTORS_LIST[[#This Row],[LS_TOTAL CURRENT UNITS]]=0,0,INVESTORS_LIST[[#This Row],[LS_TOTAL CURRENT UNITS]]*INVESTORS_LIST[[#This Row],[NAV]]) -> 0 | AR11: =IF(INVESTORS_LIST[[#This Row],[SIP_TOTAL CURRENT UNITS]]=0,0,INVESTORS_LIST[[#This Row],[SIP_TOTAL CURRENT UNITS]]*INVESTORS_LIST[[#This Row],[NAV]]) -> 0 | AS11: =INVESTORS_LIST[[#This Row],[TOTAL CURRENT UNITS]] -> 0 | AT11: =IF(INVESTORS_LIST[[#This Row],[TOTAL SELLABLE UNITS]]=0,0,INVESTORS_LIST[[#This Row],[TOTAL SELLABLE UNITS]]*INVESTORS_LIST[[#This Row],[NAV]]) -> 0 | AU11: =INVESTORS_LIST[[#This Row],[LS_TOTAL REALIZED GAIN]]+INVESTORS_LIST[[#This Row],[SIP_TOTAL REALIZED GAIN]] -> 0 | AV11: =INVESTORS_LIST[[#This Row],[TOTAL MARKET VALUE]]-INVESTORS_LIST[[#This Row],[TOTAL COST VALUE OF CURRENT INVESTMENT]] -> 0 | AW11: =IFERROR(INVESTORS_LIST[[#This Row],[TOTAL CURRENT UNITS]]/SUM(INVESTORS_LIST[TOTAL CURRENT UNITS]),0) -> 0
A12: MRINMOY GHOSH | B12: A00012 | C12: Dear Mr. | D12: Individual | E12: =SUMIFS(LS[Unit],LS[Investor ID],INVESTORS_LIST[[#This Row],[INVESTOR CODE]],LS[B/S],"B") -> 0 | F12: =-SUMIFS(LS[Unit],LS[Investor ID],INVESTORS_LIST[[#This Row],[INVESTOR CODE]],LS[B/S],"S") -> 0 | G12: =IF(INVESTORS_LIST[[#This Row],[LS_TOTAL UNITS BUY]]=0,0,INVESTORS_LIST[[#This Row],[LS_TOTAL UNITS BUY]]-INVESTORS_LIST[[#This Row],[LS_TOTAL UNITS SOLD]]) -> 0 | H12: =IF(INVESTORS_LIST[[#This Row],[LS_TOTAL UNITS BUY]]=0,0,SUMIFS(LS[Amount],LS[Investor ID],INVESTORS_LIST[[#This Row],[INVESTOR CODE]],LS[B/S],"B")) -> 0 | I12: =IF(INVESTORS_LIST[[#This Row],[LS_TOTAL UNITS SOLD]]=0,0,SUMIFS(LS[Cost of Units Sold],LS[Investor ID],INVESTORS_LIST[[#This Row],[INVESTOR CODE]],LS[B/S],"S")) -> 0 | J12: =IF(INVESTORS_LIST[[#This Row],[LS_TOTAL CURRENT UNITS]]=0,0,INVESTORS_LIST[[#This Row],[LS_TOTAL CURRENT UNITS]]*INVESTORS_LIST[[#This Row],[LS_AVERAGE COST]]) -> 0 | K12: =IF(INVESTORS_LIST[[#This Row],[LS_TOTAL UNITS SOLD]]=0,0,SUMIFS(LS[Realized Gain],LS[Investor ID],INVESTORS_LIST[[#This Row],[INVESTOR CODE]],LS[B/S],"S")) -> 0 | L12: =SUMIFS(SIP[Unit],SIP[Investor ID],INVESTORS_LIST[[#This Row],[INVESTOR CODE]],SIP[B/S],"B") -> 17492 | M12: =-SUMIFS(SIP[Unit],SIP[Investor ID],INVESTORS_LIST[[#This Row],[INVESTOR CODE]],SIP[B/S],"S") -> 17492 | N12: =IF(INVESTORS_LIST[[#This Row],[SIP_TOTAL UNITS BUY]]=0,0,INVESTORS_LIST[[#This Row],[SIP_TOTAL UNITS BUY]]-INVESTORS_LIST[[#This Row],[SIP_TOTAL UNITS SOLD]]) -> 0 | O12: =IF(INVESTORS_LIST[[#This Row],[SIP_TOTAL UNITS BUY]]=0,0,SUMIFS(SIP[Amount],SIP[Investor ID],INVESTORS_LIST[[#This Row],[INVESTOR CODE]],SIP[B/S],"B")) -> 200000 | P12: =IF(INVESTORS_LIST[[#This Row],[SIP_TOTAL UNITS SOLD]]=0,0,SUMIFS(SIP[Cost of Units Sold],SIP[Investor ID],INVESTORS_LIST[[#This Row],[INVESTOR CODE]],SIP[B/S],"S")) -> 200000 | Q12: =IF(INVESTORS_LIST[[#This Row],[SIP_TOTAL CURRENT UNITS]]=0,0,INVESTORS_LIST[[#This Row],[SIP_TOTAL CURRENT UNITS]]*INVESTORS_LIST[[#This Row],[SIP_AVERAGE COST]]) -> 0 | R12: =IF(INVESTORS_LIST[[#This Row],[SIP_TOTAL UNITS SOLD]]=0,0,SUMIFS(SIP[Realized Gain],SIP[Investor ID],INVESTORS_LIST[[#This Row],[INVESTOR CODE]],SIP[B/S],"S")) -> 7909.63 | S12: =INVESTORS_LIST[[#This Row],[LS_TOTAL UNITS BUY]]+INVESTORS_LIST[[#This Row],[SIP_TOTAL UNITS BUY]] -> 17492 | T12: =INVESTORS_LIST[[#This Row],[LS_TOTAL UNITS SOLD]]+INVESTORS_LIST[[#This Row],[SIP_TOTAL UNITS SOLD]] -> 17492 | V12: =SUMIFS(LS[BO UNIT TRANSFER],LS[Investor ID],INVESTORS_LIST[[#This Row],[INVESTOR CODE]],LS[B/S],"B") -> 0 | W12: =SUMIFS(SIP[BO UNIT TRANSFER],SIP[Investor ID],INVESTORS_LIST[[#This Row],[INVESTOR CODE]],SIP[B/S],"B") -> 0 | X12: =SUMIFS(LS[BO UNIT TRANSFER],LS[Investor ID],INVESTORS_LIST[[#This Row],[INVESTOR CODE]],LS[B/S],"S") -> 0 | Y12: =SUMIFS(SIP[BO UNIT TRANSFER],SIP[Investor ID],INVESTORS_LIST[[#This Row],[INVESTOR CODE]],SIP[B/S],"S") -> 0 | Z12: =SUM(INVESTORS_LIST[[#This Row],[BO OPENING BALANCE]:[BO SIP UNITS REPURCHASE]]) -> 0 | AA12: =INVESTORS_LIST[[#This Row],[TOTAL UNITS BUY]]-INVESTORS_LIST[[#This Row],[TOTAL UNITS SOLD]] -> 0 | AB12: =INVESTORS_LIST[[#This Row],[TOTAL CURRENT UNITS]]-INVESTORS_LIST[[#This Row],[BO UNITS HOLD]] -> 0 | AC12: =INDEX([3]!Table_1[BO ID],MATCH(INVESTORS_LIST[[#This Row],[INVESTOR CODE]],[3]!Table_1[INVESTOR CODE],0)) -> #REF! | AD12: =INDEX([3]!Table_1[Brokerage Name2],MATCH(INVESTORS_LIST[[#This Row],[INVESTOR CODE]],[3]!Table_1[INVESTOR CODE],0)) -> #REF! | AE12: =MID(INVESTORS_LIST[[#This Row],[BO ID]],4,5) -> #REF! | AF12: =MID(INVESTORS_LIST[[#This Row],[BO ID]],2,7) -> #REF! | AG12: =MID(INVESTORS_LIST[[#This Row],[BO ID]],9,7) -> #REF! | AH12: =RIGHT(INVESTORS_LIST[[#This Row],[BO ID]],1) -> #REF! | AI12: =INVESTORS_LIST[[#This Row],[LS_TOTAL COST VALUE OF CURRENT UNITS]]+INVESTORS_LIST[[#This Row],[SIP_TOTAL COST VALUE OF CURRENT UNITS]] -> 0 | AJ12: =IF(INVESTORS_LIST[[#This Row],[TOTAL CURRENT UNITS]]=0,0,INVESTORS_LIST[[#This Row],[LS_TOTAL CURRENT UNITS]]/INVESTORS_LIST[[#This Row],[TOTAL CURRENT UNITS]]) -> 0 | AK12: =IF(INVESTORS_LIST[[#This Row],[TOTAL CURRENT UNITS]]=0,0,INVESTORS_LIST[[#This Row],[SIP_TOTAL CURRENT UNITS]]/INVESTORS_LIST[[#This Row],[TOTAL CURRENT UNITS]]) -> 0 | AL12: {=IF(INVESTORS_LIST[[#This Row],[LS_TOTAL UNITS BUY]]>0,INDEX(LS[NAV at Cost (Average)],MATCH(CONCATENATE(COUNTIFS(LS[Investor ID],INVESTORS_LIST[[#This Row],[INVESTOR CODE]]),INVESTORS_LIST[[#This Row],[INVESTOR CODE]]),LS[Unique Code],0),),0)} -> 0 | AM12: {=IF(INVESTORS_LIST[[#This Row],[SIP_TOTAL UNITS BUY]]>0,INDEX(SIP[NAV at Cost (Average)],MATCH(CONCATENATE(COUNTIFS(SIP[Investor ID],INVESTORS_LIST[[#This Row],[INVESTOR CODE]]),INVESTORS_LIST[[#This Row],[INVESTOR CODE]]),SIP[Unique Code],0),),0)} -> 0 | AN12: =IF(INVESTORS_LIST[[#This Row],[TOTAL CURRENT UNITS]]=0,0,(INVESTORS_LIST[[#This Row],[LS_WEIGHT]]*INVESTORS_LIST[[#This Row],[LS_AVERAGE COST]])+(INVESTORS_LIST[[#This Row],[SIP_WEIGHT]]*INVESTORS_LIST[[#This Row],[SIP_AVERAGE COST]])) -> 0 | AO12: =NAV_MKT -> 14.224 | AP12: =IF(INVESTORS_LIST[[#This Row],[TOTAL CURRENT UNITS]]=0,0,INVESTORS_LIST[[#This Row],[TOTAL CURRENT UNITS]]*INVESTORS_LIST[[#This Row],[NAV]]) -> 0 | AQ12: =IF(INVESTORS_LIST[[#This Row],[LS_TOTAL CURRENT UNITS]]=0,0,INVESTORS_LIST[[#This Row],[LS_TOTAL CURRENT UNITS]]*INVESTORS_LIST[[#This Row],[NAV]]) -> 0 | AR12: =IF(INVESTORS_LIST[[#This Row],[SIP_TOTAL CURRENT UNITS]]=0,0,INVESTORS_LIST[[#This Row],[SIP_TOTAL CURRENT UNITS]]*INVESTORS_LIST[[#This Row],[NAV]]) -> 0 | AS12: =INVESTORS_LIST[[#This Row],[TOTAL CURRENT UNITS]] -> 0 | AT12: =IF(INVESTORS_LIST[[#This Row],[TOTAL SELLABLE UNITS]]=0,0,INVESTORS_LIST[[#This Row],[TOTAL SELLABLE UNITS]]*INVESTORS_LIST[[#This Row],[NAV]]) -> 0 | AU12: =INVESTORS_LIST[[#This Row],[LS_TOTAL REALIZED GAIN]]+INVESTORS_LIST[[#This Row],[SIP_TOTAL REALIZED GAIN]] -> 7909.63 | AV12: =INVESTORS_LIST[[#This Row],[TOTAL MARKET VALUE]]-INVESTORS_LIST[[#This Row],[TOTAL COST VALUE OF CURRENT INVESTMENT]] -> 0 | AW12: =IFERROR(INVESTORS_LIST[[#This Row],[TOTAL CURRENT UNITS]]/SUM(INVESTORS_LIST[TOTAL CURRENT UNITS]),0) -> 0 | AY12: =AY3*NAV_MKT -> 0
A13: MOHAMMAD NAZMUL HOSSAIN | B13: A00013 | C13: Dear Mr. | D13: Individual | E13: =SUMIFS(LS[Unit],LS[Investor ID],INVESTORS_LIST[[#This Row],[INVESTOR CODE]],LS[B/S],"B") -> 0 | F13: =-SUMIFS(LS[Unit],LS[Investor ID],INVESTORS_LIST[[#This Row],[INVESTOR CODE]],LS[B/S],"S") -> 0 | G13: =IF(INVESTORS_LIST[[#This Row],[LS_TOTAL UNITS BUY]]=0,0,INVESTORS_LIST[[#This Row],[LS_TOTAL UNITS BUY]]-INVESTORS_LIST[[#This Row],[LS_TOTAL UNITS SOLD]]) -> 0 | H13: =IF(INVESTORS_LIST[[#This Row],[LS_TOTAL UNITS BUY]]=0,0,SUMIFS(LS[Amount],LS[Investor ID],INVESTORS_LIST[[#This Row],[INVESTOR CODE]],LS[B/S],"B")) -> 0 | I13: =IF(INVESTORS_LIST[[#This Row],[LS_TOTAL UNITS SOLD]]=0,0,SUMIFS(LS[Cost of Units Sold],LS[Investor ID],INVESTORS_LIST[[#This Row],[INVESTOR CODE]],LS[B/S],"S")) -> 0 | J13: =IF(INVESTORS_LIST[[#This Row],[LS_TOTAL CURRENT UNITS]]=0,0,INVESTORS_LIST[[#This Row],[LS_TOTAL CURRENT UNITS]]*INVESTORS_LIST[[#This Row],[LS_AVERAGE COST]]) -> 0 | K13: =IF(INVESTORS_LIST[[#This Row],[LS_TOTAL UNITS SOLD]]=0,0,SUMIFS(LS[Realized Gain],LS[Investor ID],INVESTORS_LIST[[#This Row],[INVESTOR CODE]],LS[B/S],"S")) -> 0 | L13: =SUMIFS(SIP[Unit],SIP[Investor ID],INVESTORS_LIST[[#This Row],[INVESTOR CODE]],SIP[B/S],"B") -> 0 | M13: =-SUMIFS(SIP[Unit],SIP[Investor ID],INVESTORS_LIST[[#This Row],[INVESTOR CODE]],SIP[B/S],"S") -> 0 | N13: =IF(INVESTORS_LIST[[#This Row],[SIP_TOTAL UNITS BUY]]=0,0,INVESTORS_LIST[[#This Row],[SIP_TOTAL UNITS BUY]]-INVESTORS_LIST[[#This Row],[SIP_TOTAL UNITS SOLD]]) -> 0 | O13: =IF(INVESTORS_LIST[[#This Row],[SIP_TOTAL UNITS BUY]]=0,0,SUMIFS(SIP[Amount],SIP[Investor ID],INVESTORS_LIST[[#This Row],[INVESTOR CODE]],SIP[B/S],"B")) -> 0 | P13: =IF(INVESTORS_LIST[[#This Row],[SIP_TOTAL UNITS SOLD]]=0,0,SUMIFS(SIP[Cost of Units Sold],SIP[Investor ID],INVESTORS_LIST[[#This Row],[INVESTOR CODE]],SIP[B/S],"S")) -> 0 | Q13: =IF(INVESTORS_LIST[[#This Row],[SIP_TOTAL CURRENT UNITS]]=0,0,INVESTORS_LIST[[#This Row],[SIP_TOTAL CURRENT UNITS]]*INVESTORS_LIST[[#This Row],[SIP_AVERAGE COST]]) -> 0 | R13: =IF(INVESTORS_LIST[[#This Row],[SIP_TOTAL UNITS SOLD]]=0,0,SUMIFS(SIP[Realized Gain],SIP[Investor ID],INVESTORS_LIST[[#This Row],[INVESTOR CODE]],SIP[B/S],"S")) -> 0 | S13: =INVESTORS_LIST[[#This Row],[LS_TOTAL UNITS BUY]]+INVESTORS_LIST[[#This Row],[SIP_TOTAL UNITS BUY]] -> 0 | T13: =INVESTORS_LIST[[#This Row],[LS_TOTAL UNITS SOLD]]+INVESTORS_LIST[[#This Row],[SIP_TOTAL UNITS SOLD]] -> 0 | V13: =SUMIFS(LS[BO UNIT TRANSFER],LS[Investor ID],INVESTORS_LIST[[#This Row],[INVESTOR CODE]],LS[B/S],"B") -> 0 | W13: =SUMIFS(SIP[BO UNIT TRANSFER],SIP[Investor ID],INVESTORS_LIST[[#This Row],[INVESTOR CODE]],SIP[B/S],"B") -> 0 | X13: =SUMIFS(LS[BO UNIT TRANSFER],LS[Investor ID],INVESTORS_LIST[[#This Row],[INVESTOR CODE]],LS[B/S],"S") -> 0 | Y13: =SUMIFS(SIP[BO UNIT TRANSFER],SIP[Investor ID],INVESTORS_LIST[[#This Row],[INVESTOR CODE]],SIP[B/S],"S") -> 0 | Z13: =SUM(INVESTORS_LIST[[#This Row],[BO OPENING BALANCE]:[BO SIP UNITS REPURCHASE]]) -> 0 | AA13: =INVESTORS_LIST[[#This Row],[TOTAL UNITS BUY]]-INVESTORS_LIST[[#This Row],[TOTAL UNITS SOLD]] -> 0 | AB13: =INVESTORS_LIST[[#This Row],[TOTAL CURRENT UNITS]]-INVESTORS_LIST[[#This Row],[BO UNITS HOLD]] -> 0 | AC13: =INDEX([3]!Table_1[BO ID],MATCH(INVESTORS_LIST[[#This Row],[INVESTOR CODE]],[3]!Table_1[INVESTOR CODE],0)) -> #REF! | AD13: =INDEX([3]!Table_1[Brokerage Name2],MATCH(INVESTORS_LIST[[#This Row],[INVESTOR CODE]],[3]!Table_1[INVESTOR CODE],0)) -> #REF! | AE13: =MID(INVESTORS_LIST[[#This Row],[BO ID]],4,5) -> #REF! | AF13: =MID(INVESTORS_LIST[[#This Row],[BO ID]],2,7) -> #REF! | AG13: =MID(INVESTORS_LIST[[#This Row],[BO ID]],9,7) -> #REF! | AH13: =RIGHT(INVESTORS_LIST[[#This Row],[BO ID]],1) -> #REF! | AI13: =INVESTORS_LIST[[#This Row],[LS_TOTAL COST VALUE OF CURRENT UNITS]]+INVESTORS_LIST[[#This Row],[SIP_TOTAL COST VALUE OF CURRENT UNITS]] -> 0 | AJ13: =IF(INVESTORS_LIST[[#This Row],[TOTAL CURRENT UNITS]]=0,0,INVESTORS_LIST[[#This Row],[LS_TOTAL CURRENT UNITS]]/INVESTORS_LIST[[#This Row],[TOTAL CURRENT UNITS]]) -> 0 | AK13: =IF(INVESTORS_LIST[[#This Row],[TOTAL CURRENT UNITS]]=0,0,INVESTORS_LIST[[#This Row],[SIP_TOTAL CURRENT UNITS]]/INVESTORS_LIST[[#This Row],[TOTAL CURRENT UNITS]]) -> 0 | AL13: {=IF(INVESTORS_LIST[[#This Row],[LS_TOTAL UNITS BUY]]>0,INDEX(LS[NAV at Cost (Average)],MATCH(CONCATENATE(COUNTIFS(LS[Investor ID],INVESTORS_LIST[[#This Row],[INVESTOR CODE]]),INVESTORS_LIST[[#This Row],[INVESTOR CODE]]),LS[Unique Code],0),),0)} -> 0 | AM13: {=IF(INVESTORS_LIST[[#This Row],[SIP_TOTAL UNITS BUY]]>0,INDEX(SIP[NAV at Cost (Average)],MATCH(CONCATENATE(COUNTIFS(SIP[Investor ID],INVESTORS_LIST[[#This Row],[INVESTOR CODE]]),INVESTORS_LIST[[#This Row],[INVESTOR CODE]]),SIP[Unique Code],0),),0)} -> 0 | AN13: =IF(INVESTORS_LIST[[#This Row],[TOTAL CURRENT UNITS]]=0,0,(INVESTORS_LIST[[#This Row],[LS_WEIGHT]]*INVESTORS_LIST[[#This Row],[LS_AVERAGE COST]])+(INVESTORS_LIST[[#This Row],[SIP_WEIGHT]]*INVESTORS_LIST[[#This Row],[SIP_AVERAGE COST]])) -> 0 | AO13: =NAV_MKT -> 14.224 | AP13: =IF(INVESTORS_LIST[[#This Row],[TOTAL CURRENT UNITS]]=0,0,INVESTORS_LIST[[#This Row],[TOTAL CURRENT UNITS]]*INVESTORS_LIST[[#This Row],[NAV]]) -> 0 | AQ13: =IF(INVESTORS_LIST[[#This Row],[LS_TOTAL CURRENT UNITS]]=0,0,INVESTORS_LIST[[#This Row],[LS_TOTAL CURRENT UNITS]]*INVESTORS_LIST[[#This Row],[NAV]]) -> 0 | AR13: =IF(INVESTORS_LIST[[#This Row],[SIP_TOTAL CURRENT UNITS]]=0,0,INVESTORS_LIST[[#This Row],[SIP_TOTAL CURRENT UNITS]]*INVESTORS_LIST[[#This Row],[NAV]]) -> 0 | AS13: =INVESTORS_LIST[[#This Row],[TOTAL CURRENT UNITS]] -> 0 | AT13: =IF(INVESTORS_LIST[[#This Row],[TOTAL SELLABLE UNITS]]=0,0,INVESTORS_LIST[[#This Row],[TOTAL SELLABLE UNITS]]*INVESTORS_LIST[[#This Row],[NAV]]) -> 0 | AU13: =INVESTORS_LIST[[#This Row],[LS_TOTAL REALIZED GAIN]]+INVESTORS_LIST[[#This Row],[SIP_TOTAL REALIZED GAIN]] -> 0 | AV13: =INVESTORS_LIST[[#This Row],[TOTAL MARKET VALUE]]-INVESTORS_LIST[[#This Row],[TOTAL COST VALUE OF CURRENT INVESTMENT]] -> 0 | AW13: =IFERROR(INVESTORS_LIST[[#This Row],[TOTAL CURRENT UNITS]]/SUM(INVESTORS_LIST[TOTAL CURRENT UNITS]),0) -> 0
A14: ANJANA SAHA | B14: A00014 | C14: Dear Mrs. | D14: Individual | E14: =SUMIFS(LS[Unit],LS[Investor ID],INVESTORS_LIST[[#This Row],[INVESTOR CODE]],LS[B/S],"B") -> 381782 | F14: =-SUMIFS(LS[Unit],LS[Investor ID],INVESTORS_LIST[[#This Row],[INVESTOR CODE]],LS[B/S],"S") -> 381782 | G14: =IF(INVESTORS_LIST[[#This Row],[LS_TOTAL UNITS BUY]]=0,0,INVESTORS_LIST[[#This Row],[LS_TOTAL UNITS BUY]]-INVESTORS_LIST[[#This Row],[LS_TOTAL UNITS SOLD]]) -> 0 | H14: =IF(INVESTORS_LIST[[#This Row],[LS_TOTAL UNITS BUY]]=0,0,SUMIFS(LS[Amount],LS[Investor ID],INVESTORS_LIST[[#This Row],[INVESTOR CODE]],LS[B/S],"B")) -> 4000000 | I14: =IF(INVESTORS_LIST[[#This Row],[LS_TOTAL UNITS SOLD]]=0,0,SUMIFS(LS[Cost of Units Sold],LS[Investor ID],INVESTORS_LIST[[#This Row],[INVESTOR CODE]],LS[B/S],"S")) -> 4000000 | J14: =IF(INVESTORS_LIST[[#This Row],[LS_TOTAL CURRENT UNITS]]=0,0,INVESTORS_LIST[[#This Row],[LS_TOTAL CURRENT UNITS]]*INVESTORS_LIST[[#This Row],[LS_AVERAGE COST]]) -> 0 | K14: =IF(INVESTORS_LIST[[#This Row],[LS_TOTAL UNITS SOLD]]=0,0,SUMIFS(LS[Realized Gain],LS[Investor ID],INVESTORS_LIST[[#This Row],[INVESTOR CODE]],LS[B/S],"S")) -> 563032.84 | L14: =SUMIFS(SIP[Unit],SIP[Investor ID],INVESTORS_LIST[[#This Row],[INVESTOR CODE]],SIP[B/S],"B") -> 0 | M14: =-SUMIFS(SIP[Unit],SIP[Investor ID],INVESTORS_LIST[[#This Row],[INVESTOR CODE]],SIP[B/S],"S") -> 0 | N14: =IF(INVESTORS_LIST[[#This Row],[SIP_TOTAL UNITS BUY]]=0,0,INVESTORS_LIST[[#This Row],[SIP_TOTAL UNITS BUY]]-INVESTORS_LIST[[#This Row],[SIP_TOTAL UNITS SOLD]]) -> 0 | O14: =IF(INVESTORS_LIST[[#This Row],[SIP_TOTAL UNITS BUY]]=0,0,SUMIFS(SIP[Amount],SIP[Investor ID],INVESTORS_LIST[[#This Row],[INVESTOR CODE]],SIP[B/S],"B")) -> 0 | P14: =IF(INVESTORS_LIST[[#This Row],[SIP_TOTAL UNITS SOLD]]=0,0,SUMIFS(SIP[Cost of Units Sold],SIP[Investor ID],INVESTORS_LIST[[#This Row],[INVESTOR CODE]],SIP[B/S],"S")) -> 0 | Q14: =IF(INVESTORS_LIST[[#This Row],[SIP_TOTAL CURRENT UNITS]]=0,0,INVESTORS_LIST[[#This Row],[SIP_TOTAL CURRENT UNITS]]*INVESTORS_LIST[[#This Row],[SIP_AVERAGE COST]]) -> 0 | R14: =IF(INVESTORS_LIST[[#This Row],[SIP_TOTAL UNITS SOLD]]=0,0,SUMIFS(SIP[Realized Gain],SIP[Investor ID],INVESTORS_LIST[[#This Row],[INVESTOR CODE]],SIP[B/S],"S")) -> 0 | S14: =INVESTORS_LIST[[#This Row],[LS_TOTAL UNITS BUY]]+INVESTORS_LIST[[#This Row],[SIP_TOTAL UNITS BUY]] -> 381782 | T14: =INVESTORS_LIST[[#This Row],[LS_TOTAL UNITS SOLD]]+INVESTORS_LIST[[#This Row],[SIP_TOTAL UNITS SOLD]] -> 381782 | V14: =SUMIFS(LS[BO UNIT TRANSFER],LS[Investor ID],INVESTORS_LIST[[#This Row],[INVESTOR CODE]],LS[B/S],"B") -> 0 | W14: =SUMIFS(SIP[BO UNIT TRANSFER],SIP[Investor ID],INVESTORS_LIST[[#This Row],[INVESTOR CODE]],SIP[B/S],"B") -> 0 | X14: =SUMIFS(LS[BO UNIT TRANSFER],LS[Investor ID],INVESTORS_LIST[[#This Row],[INVESTOR CODE]],LS[B/S],"S") -> 0 | Y14: =SUMIFS(SIP[BO UNIT TRANSFER],SIP[Investor ID],INVESTORS_LIST[[#This Row],[INVESTOR CODE]],SIP[B/S],"S") -> 0 | Z14: =SUM(INVESTORS_LIST[[#This Row],[BO OPENING BALANCE]:[BO SIP UNITS REPURCHASE]]) -> 0 | AA14: =INVESTORS_LIST[[#This Row],[TOTAL UNITS BUY]]-INVESTORS_LIST[[#This Row],[TOTAL UNITS SOLD]] -> 0 | AB14: =INVESTORS_LIST[[#This Row],[TOTAL CURRENT UNITS]]-INVESTORS_LIST[[#This Row],[BO UNITS HOLD]] -> 0 | AC14: =INDEX([3]!Table_1[BO ID],MATCH(INVESTORS_LIST[[#This Row],[INVESTOR CODE]],[3]!Table_1[INVESTOR CODE],0)) -> #REF! | AD14: =INDEX([3]!Table_1[Brokerage Name2],MATCH(INVESTORS_LIST[[#This Row],[INVESTOR CODE]],[3]!Table_1[INVESTOR CODE],0)) -> #REF! | AE14: =MID(INVESTORS_LIST[[#This Row],[BO ID]],4,5) -> #REF! | AF14: =MID(INVESTORS_LIST[[#This Row],[BO ID]],2,7) -> #REF! | AG14: =MID(INVESTORS_LIST[[#This Row],[BO ID]],9,7) -> #REF! | AH14: =RIGHT(INVESTORS_LIST[[#This Row],[BO ID]],1) -> #REF! | AI14: =INVESTORS_LIST[[#This Row],[LS_TOTAL COST VALUE OF CURRENT UNITS]]+INVESTORS_LIST[[#This Row],[SIP_TOTAL COST VALUE OF CURRENT UNITS]] -> 0 | AJ14: =IF(INVESTORS_LIST[[#This Row],[TOTAL CURRENT UNITS]]=0,0,INVESTORS_LIST[[#This Row],[LS_TOTAL CURRENT UNITS]]/INVESTORS_LIST[[#This Row],[TOTAL CURRENT UNITS]]) -> 0 | AK14: =IF(INVESTORS_LIST[[#This Row],[TOTAL CURRENT UNITS]]=0,0,INVESTORS_LIST[[#This Row],[SIP_TOTAL CURRENT UNITS]]/INVESTORS_LIST[[#This Row],[TOTAL CURRENT UNITS]]) -> 0 | AL14: {=IF(INVESTORS_LIST[[#This Row],[LS_TOTAL UNITS BUY]]>0,INDEX(LS[NAV at Cost (Average)],MATCH(CONCATENATE(COUNTIFS(LS[Investor ID],INVESTORS_LIST[[#This Row],[INVESTOR CODE]]),INVESTORS_LIST[[#This Row],[INVESTOR CODE]]),LS[Unique Code],0),),0)} -> 0 | AM14: {=IF(INVESTORS_LIST[[#This Row],[SIP_TOTAL UNITS BUY]]>0,INDEX(SIP[NAV at Cost (Average)],MATCH(CONCATENATE(COUNTIFS(SIP[Investor ID],INVESTORS_LIST[[#This Row],[INVESTOR CODE]]),INVESTORS_LIST[[#This Row],[INVESTOR CODE]]),SIP[Unique Code],0),),0)} -> 0 | AN14: =IF(INVESTORS_LIST[[#This Row],[TOTAL CURRENT UNITS]]=0,0,(INVESTORS_LIST[[#This Row],[LS_WEIGHT]]*INVESTORS_LIST[[#This Row],[LS_AVERAGE COST]])+(INVESTORS_LIST[[#This Row],[SIP_WEIGHT]]*INVESTORS_LIST[[#This Row],[SIP_AVERAGE COST]])) -> 0 | AO14: =NAV_MKT -> 14.224 | AP14: =IF(INVESTORS_LIST[[#This Row],[TOTAL CURRENT UNITS]]=0,0,INVESTORS_LIST[[#This Row],[TOTAL CURRENT UNITS]]*INVESTORS_LIST[[#This Row],[NAV]]) -> 0 | AQ14: =IF(INVESTORS_LIST[[#This Row],[LS_TOTAL CURRENT UNITS]]=0,0,INVESTORS_LIST[[#This Row],[LS_TOTAL CURRENT UNITS]]*INVESTORS_LIST[[#This Row],[NAV]]) -> 0 | AR14: =IF(INVESTORS_LIST[[#This Row],[SIP_TOTAL CURRENT UNITS]]=0,0,INVESTORS_LIST[[#This Row],[SIP_TOTAL CURRENT UNITS]]*INVESTORS_LIST[[#This Row],[NAV]]) -> 0 | AS14: =INVESTORS_LIST[[#This Row],[TOTAL CURRENT UNITS]] -> 0 | AT14: =IF(INVESTORS_LIST[[#This Row],[TOTAL SELLABLE UNITS]]=0,0,INVESTORS_LIST[[#This Row],[TOTAL SELLABLE UNITS]]*INVESTORS_LIST[[#This Row],[NAV]]) -> 0 | AU14: =INVESTORS_LIST[[#This Row],[LS_TOTAL REALIZED GAIN]]+INVESTORS_LIST[[#This Row],[SIP_TOTAL REALIZED GAIN]] -> 563032.84 | AV14: =INVESTORS_LIST[[#This Row],[TOTAL MARKET VALUE]]-INVESTORS_LIST[[#This Row],[TOTAL COST VALUE OF CURRENT INVESTMENT]] -> 0 | AW14: =IFERROR(INVESTORS_LIST[[#This Row],[TOTAL CURRENT UNITS]]/SUM(INVESTORS_LIST[TOTAL CURRENT UNITS]),0) -> 0
A15: ABDUL HAI BHUYAN | B15: A00015 | C15: Dear Mr. | D15: Individual | E15: =SUMIFS(LS[Unit],LS[Investor ID],INVESTORS_LIST[[#This Row],[INVESTOR CODE]],LS[B/S],"B") -> 0 | F15: =-SUMIFS(LS[Unit],LS[Investor ID],INVESTORS_LIST[[#This Row],[INVESTOR CODE]],LS[B/S],"S") -> 0 | G15: =IF(INVESTORS_LIST[[#This Row],[LS_TOTAL UNITS BUY]]=0,0,INVESTORS_LIST[[#This Row],[LS_TOTAL UNITS BUY]]-INVESTORS_LIST[[#This Row],[LS_TOTAL UNITS SOLD]]) -> 0 | H15: =IF(INVESTORS_LIST[[#This Row],[LS_TOTAL UNITS BUY]]=0,0,SUMIFS(LS[Amount],LS[Investor ID],INVESTORS_LIST[[#This Row],[INVESTOR CODE]],LS[B/S],"B")) -> 0 | I15: =IF(INVESTORS_LIST[[#This Row],[LS_TOTAL UNITS SOLD]]=0,0,SUMIFS(LS[Cost of Units Sold],LS[Investor ID],INVESTORS_LIST[[#This Row],[INVESTOR CODE]],LS[B/S],"S")) -> 0 | J15: =IF(INVESTORS_LIST[[#This Row],[LS_TOTAL CURRENT UNITS]]=0,0,INVESTORS_LIST[[#This Row],[LS_TOTAL CURRENT UNITS]]*INVESTORS_LIST[[#This Row],[LS_AVERAGE COST]]) -> 0 | K15: =IF(INVESTORS_LIST[[#This Row],[LS_TOTAL UNITS SOLD]]=0,0,SUMIFS(LS[Realized Gain],LS[Investor ID],INVESTORS_LIST[[#This Row],[INVESTOR CODE]],LS[B/S],"S")) -> 0 | L15: =SUMIFS(SIP[Unit],SIP[Investor ID],INVESTORS_LIST[[#This Row],[INVESTOR CODE]],SIP[B/S],"B") -> 0 | M15: =-SUMIFS(SIP[Unit],SIP[Investor ID],INVESTORS_LIST[[#This Row],[INVESTOR CODE]],SIP[B/S],"S") -> 0 | N15: =IF(INVESTORS_LIST[[#This Row],[SIP_TOTAL UNITS BUY]]=0,0,INVESTORS_LIST[[#This Row],[SIP_TOTAL UNITS BUY]]-INVESTORS_LIST[[#This Row],[SIP_TOTAL UNITS SOLD]]) -> 0 | O15: =IF(INVESTORS_LIST[[#This Row],[SIP_TOTAL UNITS BUY]]=0,0,SUMIFS(SIP[Amount],SIP[Investor ID],INVESTORS_LIST[[#This Row],[INVESTOR CODE]],SIP[B/S],"B")) -> 0 | P15: =IF(INVESTORS_LIST[[#This Row],[SIP_TOTAL UNITS SOLD]]=0,0,SUMIFS(SIP[Cost of Units Sold],SIP[Investor ID],INVESTORS_LIST[[#This Row],[INVESTOR CODE]],SIP[B/S],"S")) -> 0 | Q15: =IF(INVESTORS_LIST[[#This Row],[SIP_TOTAL CURRENT UNITS]]=0,0,INVESTORS_LIST[[#This Row],[SIP_TOTAL CURRENT UNITS]]*INVESTORS_LIST[[#This Row],[SIP_AVERAGE COST]]) -> 0 | R15: =IF(INVESTORS_LIST[[#This Row],[SIP_TOTAL UNITS SOLD]]=0,0,SUMIFS(SIP[Realized Gain],SIP[Investor ID],INVESTORS_LIST[[#This Row],[INVESTOR CODE]],SIP[B/S],"S")) -> 0 | S15: =INVESTORS_LIST[[#This Row],[LS_TOTAL UNITS BUY]]+INVESTORS_LIST[[#This Row],[SIP_TOTAL UNITS BUY]] -> 0 | T15: =INVESTORS_LIST[[#This Row],[LS_TOTAL UNITS SOLD]]+INVESTORS_LIST[[#This Row],[SIP_TOTAL UNITS SOLD]] -> 0 | V15: =SUMIFS(LS[BO UNIT TRANSFER],LS[Investor ID],INVESTORS_LIST[[#This Row],[INVESTOR CODE]],LS[B/S],"B") -> 0 | W15: =SUMIFS(SIP[BO UNIT TRANSFER],SIP[Investor ID],INVESTORS_LIST[[#This Row],[INVESTOR CODE]],SIP[B/S],"B") -> 0 | X15: =SUMIFS(LS[BO UNIT TRANSFER],LS[Investor ID],INVESTORS_LIST[[#This Row],[INVESTOR CODE]],LS[B/S],"S") -> 0 | Y15: =SUMIFS(SIP[BO UNIT TRANSFER],SIP[Investor ID],INVESTORS_LIST[[#This Row],[INVESTOR CODE]],SIP[B/S],"S") -> 0 | Z15: =SUM(INVESTORS_LIST[[#This Row],[BO OPENING BALANCE]:[BO SIP UNITS REPURCHASE]]) -> 0 | AA15: =INVESTORS_LIST[[#This Row],[TOTAL UNITS BUY]]-INVESTORS_LIST[[#This Row],[TOTAL UNITS SOLD]] -> 0 | AB15: =INVESTORS_LIST[[#This Row],[TOTAL CURRENT UNITS]]-INVESTORS_LIST[[#This Row],[BO UNITS HOLD]] -> 0 | AC15: =INDEX([3]!Table_1[BO ID],MATCH(INVESTORS_LIST[[#This Row],[INVESTOR CODE]],[3]!Table_1[INVESTOR CODE],0)) -> #REF! | AD15: =INDEX([3]!Table_1[Brokerage Name2],MATCH(INVESTORS_LIST[[#This Row],[INVESTOR CODE]],[3]!Table_1[INVESTOR CODE],0)) -> #REF! | AE15: =MID(INVESTORS_LIST[[#This Row],[BO ID]],4,5) -> #REF! | AF15: =MID(INVESTORS_LIST[[#This Row],[BO ID]],2,7) -> #REF! | AG15: =MID(INVESTORS_LIST[[#This Row],[BO ID]],9,7) -> #REF! | AH15: =RIGHT(INVESTORS_LIST[[#This Row],[BO ID]],1) -> #REF! | AI15: =INVESTORS_LIST[[#This Row],[LS_TOTAL COST VALUE OF CURRENT UNITS]]+INVESTORS_LIST[[#This Row],[SIP_TOTAL COST VALUE OF CURRENT UNITS]] -> 0 | AJ15: =IF(INVESTORS_LIST[[#This Row],[TOTAL CURRENT UNITS]]=0,0,INVESTORS_LIST[[#This Row],[LS_TOTAL CURRENT UNITS]]/INVESTORS_LIST[[#This Row],[TOTAL CURRENT UNITS]]) -> 0 | AK15: =IF(INVESTORS_LIST[[#This Row],[TOTAL CURRENT UNITS]]=0,0,INVESTORS_LIST[[#This Row],[SIP_TOTAL CURRENT UNITS]]/INVESTORS_LIST[[#This Row],[TOTAL CURRENT UNITS]]) -> 0 | AL15: {=IF(INVESTORS_LIST[[#This Row],[LS_TOTAL UNITS BUY]]>0,INDEX(LS[NAV at Cost (Average)],MATCH(CONCATENATE(COUNTIFS(LS[Investor ID],INVESTORS_LIST[[#This Row],[INVESTOR CODE]]),INVESTORS_LIST[[#This Row],[INVESTOR CODE]]),LS[Unique Code],0),),0)} -> 0 | AM15: {=IF(INVESTORS_LIST[[#This Row],[SIP_TOTAL UNITS BUY]]>0,INDEX(SIP[NAV at Cost (Average)],MATCH(CONCATENATE(COUNTIFS(SIP[Investor ID],INVESTORS_LIST[[#This Row],[INVESTOR CODE]]),INVESTORS_LIST[[#This Row],[INVESTOR CODE]]),SIP[Unique Code],0),),0)} -> 0 | AN15: =IF(INVESTORS_LIST[[#This Row],[TOTAL CURRENT UNITS]]=0,0,(INVESTORS_LIST[[#This Row],[LS_WEIGHT]]*INVESTORS_LIST[[#This Row],[LS_AVERAGE COST]])+(INVESTORS_LIST[[#This Row],[SIP_WEIGHT]]*INVESTORS_LIST[[#This Row],[SIP_AVERAGE COST]])) -> 0 | AO15: =NAV_MKT -> 14.224 | AP15: =IF(INVESTORS_LIST[[#This Row],[TOTAL CURRENT UNITS]]=0,0,INVESTORS_LIST[[#This Row],[TOTAL CURRENT UNITS]]*INVESTORS_LIST[[#This Row],[NAV]]) -> 0 | AQ15: =IF(INVESTORS_LIST[[#This Row],[LS_TOTAL CURRENT UNITS]]=0,0,INVESTORS_LIST[[#This Row],[LS_TOTAL CURRENT UNITS]]*INVESTORS_LIST[[#This Row],[NAV]]) -> 0 | AR15: =IF(INVESTORS_LIST[[#This Row],[SIP_TOTAL CURRENT UNITS]]=0,0,INVESTORS_LIST[[#This Row],[SIP_TOTAL CURRENT UNITS]]*INVESTORS_LIST[[#This Row],[NAV]]) -> 0 | AS15: =INVESTORS_LIST[[#This Row],[TOTAL CURRENT UNITS]] -> 0 | AT15: =IF(INVESTORS_LIST[[#This Row],[TOTAL SELLABLE UNITS]]=0,0,INVESTORS_LIST[[#This Row],[TOTAL SELLABLE UNITS]]*INVESTORS_LIST[[#This Row],[NAV]]) -> 0 | AU15: =INVESTORS_LIST[[#This Row],[LS_TOTAL REALIZED GAIN]]+INVESTORS_LIST[[#This Row],[SIP_TOTAL REALIZED GAIN]] -> 0 | AV15: =INVESTORS_LIST[[#This Row],[TOTAL MARKET VALUE]]-INVESTORS_LIST[[#This Row],[TOTAL COST VALUE OF CURRENT INVESTMENT]] -> 0 | AW15: =IFERROR(INVESTORS_LIST[[#This Row],[TOTAL CURRENT UNITS]]/SUM(INVESTORS_LIST[TOTAL CURRENT UNITS]),0) -> 0
A16: ALI IMAM | B16: A00016 | C16: Dear Mr. | D16: Individual | E16: =SUMIFS(LS[Unit],LS[Investor ID],INVESTORS_LIST[[#This Row],[INVESTOR CODE]],LS[B/S],"B") -> 0 | F16: =-SUMIFS(LS[Unit],LS[Investor ID],INVESTORS_LIST[[#This Row],[INVESTOR CODE]],LS[B/S],"S") -> 0 | G16: =IF(INVESTORS_LIST[[#This Row],[LS_TOTAL UNITS BUY]]=0,0,INVESTORS_LIST[[#This Row],[LS_TOTAL UNITS BUY]]-INVESTORS_LIST[[#This Row],[LS_TOTAL UNITS SOLD]]) -> 0 | H16: =IF(INVESTORS_LIST[[#This Row],[LS_TOTAL UNITS BUY]]=0,0,SUMIFS(LS[Amount],LS[Investor ID],INVESTORS_LIST[[#This Row],[INVESTOR CODE]],LS[B/S],"B")) -> 0 | I16: =IF(INVESTORS_LIST[[#This Row],[LS_TOTAL UNITS SOLD]]=0,0,SUMIFS(LS[Cost of Units Sold],LS[Investor ID],INVESTORS_LIST[[#This Row],[INVESTOR CODE]],LS[B/S],"S")) -> 0 | J16: =IF(INVESTORS_LIST[[#This Row],[LS_TOTAL CURRENT UNITS]]=0,0,INVESTORS_LIST[[#This Row],[LS_TOTAL CURRENT UNITS]]*INVESTORS_LIST[[#This Row],[LS_AVERAGE COST]]) -> 0 | K16: =IF(INVESTORS_LIST[[#This Row],[LS_TOTAL UNITS SOLD]]=0,0,SUMIFS(LS[Realized Gain],LS[Investor ID],INVESTORS_LIST[[#This Row],[INVESTOR CODE]],LS[B/S],"S")) -> 0 | L16: =SUMIFS(SIP[Unit],SIP[Investor ID],INVESTORS_LIST[[#This Row],[INVESTOR CODE]],SIP[B/S],"B") -> 0 | M16: =-SUMIFS(SIP[Unit],SIP[Investor ID],INVESTORS_LIST[[#This Row],[INVESTOR CODE]],SIP[B/S],"S") -> 0 | N16: =IF(INVESTORS_LIST[[#This Row],[SIP_TOTAL UNITS BUY]]=0,0,INVESTORS_LIST[[#This Row],[SIP_TOTAL UNITS BUY]]-INVESTORS_LIST[[#This Row],[SIP_TOTAL UNITS SOLD]]) -> 0 | O16: =IF(INVESTORS_LIST[[#This Row],[SIP_TOTAL UNITS BUY]]=0,0,SUMIFS(SIP[Amount],SIP[Investor ID],INVESTORS_LIST[[#This Row],[INVESTOR CODE]],SIP[B/S],"B")) -> 0 | P16: =IF(INVESTORS_LIST[[#This Row],[SIP_TOTAL UNITS SOLD]]=0,0,SUMIFS(SIP[Cost of Units Sold],SIP[Investor ID],INVESTORS_LIST[[#This Row],[INVESTOR CODE]],SIP[B/S],"S")) -> 0 | Q16: =IF(INVESTORS_LIST[[#This Row],[SIP_TOTAL CURRENT UNITS]]=0,0,INVESTORS_LIST[[#This Row],[SIP_TOTAL CURRENT UNITS]]*INVESTORS_LIST[[#This Row],[SIP_AVERAGE COST]]) -> 0 | R16: =IF(INVESTORS_LIST[[#This Row],[SIP_TOTAL UNITS SOLD]]=0,0,SUMIFS(SIP[Realized Gain],SIP[Investor ID],INVESTORS_LIST[[#This Row],[INVESTOR CODE]],SIP[B/S],"S")) -> 0 | S16: =INVESTORS_LIST[[#This Row],[LS_TOTAL UNITS BUY]]+INVESTORS_LIST[[#This Row],[SIP_TOTAL UNITS BUY]] -> 0 | T16: =INVESTORS_LIST[[#This Row],[LS_TOTAL UNITS SOLD]]+INVESTORS_LIST[[#This Row],[SIP_TOTAL UNITS SOLD]] -> 0 | V16: =SUMIFS(LS[BO UNIT TRANSFER],LS[Investor ID],INVESTORS_LIST[[#This Row],[INVESTOR CODE]],LS[B/S],"B") -> 0 | W16: =SUMIFS(SIP[BO UNIT TRANSFER],SIP[Investor ID],INVESTORS_LIST[[#This Row],[INVESTOR CODE]],SIP[B/S],"B") -> 0 | X16: =SUMIFS(LS[BO UNIT TRANSFER],LS[Investor ID],INVESTORS_LIST[[#This Row],[INVESTOR CODE]],LS[B/S],"S") -> 0 | Y16: =SUMIFS(SIP[BO UNIT TRANSFER],SIP[Investor ID],INVESTORS_LIST[[#This Row],[INVESTOR CODE]],SIP[B/S],"S") -> 0 | Z16: =SUM(INVESTORS_LIST[[#This Row],[BO OPENING BALANCE]:[BO SIP UNITS REPURCHASE]]) -> 0 | AA16: =INVESTORS_LIST[[#This Row],[TOTAL UNITS BUY]]-INVESTORS_LIST[[#This Row],[TOTAL UNITS SOLD]] -> 0 | AB16: =INVESTORS_LIST[[#This Row],[TOTAL CURRENT UNITS]]-INVESTORS_LIST[[#This Row],[BO UNITS HOLD]] -> 0 | AC16: =INDEX([3]!Table_1[BO ID],MATCH(INVESTORS_LIST[[#This Row],[INVESTOR CODE]],[3]!Table_1[INVESTOR CODE],0)) -> #REF! | AD16: =INDEX([3]!Table_1[Brokerage Name2],MATCH(INVESTORS_LIST[[#This Row],[INVESTOR CODE]],[3]!Table_1[INVESTOR CODE],0)) -> #REF! | AE16: =MID(INVESTORS_LIST[[#This Row],[BO ID]],4,5) -> #REF! | AF16: =MID(INVESTORS_LIST[[#This Row],[BO ID]],2,7) -> #REF! | AG16: =MID(INVESTORS_LIST[[#This Row],[BO ID]],9,7) -> #REF! | AH16: =RIGHT(INVESTORS_LIST[[#This Row],[BO ID]],1) -> #REF! | AI16: =INVESTORS_LIST[[#This Row],[LS_TOTAL COST VALUE OF CURRENT UNITS]]+INVESTORS_LIST[[#This Row],[SIP_TOTAL COST VALUE OF CURRENT UNITS]] -> 0 | AJ16: =IF(INVESTORS_LIST[[#This Row],[TOTAL CURRENT UNITS]]=0,0,INVESTORS_LIST[[#This Row],[LS_TOTAL CURRENT UNITS]]/INVESTORS_LIST[[#This Row],[TOTAL CURRENT UNITS]]) -> 0 | AK16: =IF(INVESTORS_LIST[[#This Row],[TOTAL CURRENT UNITS]]=0,0,INVESTORS_LIST[[#This Row],[SIP_TOTAL CURRENT UNITS]]/INVESTORS_LIST[[#This Row],[TOTAL CURRENT UNITS]]) -> 0 | AL16: {=IF(INVESTORS_LIST[[#This Row],[LS_TOTAL UNITS BUY]]>0,INDEX(LS[NAV at Cost (Average)],MATCH(CONCATENATE(COUNTIFS(LS[Investor ID],INVESTORS_LIST[[#This Row],[INVESTOR CODE]]),INVESTORS_LIST[[#This Row],[INVESTOR CODE]]),LS[Unique Code],0),),0)} -> 0 | AM16: {=IF(INVESTORS_LIST[[#This Row],[SIP_TOTAL UNITS BUY]]>0,INDEX(SIP[NAV at Cost (Average)],MATCH(CONCATENATE(COUNTIFS(SIP[Investor ID],INVESTORS_LIST[[#This Row],[INVESTOR CODE]]),INVESTORS_LIST[[#This Row],[INVESTOR CODE]]),SIP[Unique Code],0),),0)} -> 0 | AN16: =IF(INVESTORS_LIST[[#This Row],[TOTAL CURRENT UNITS]]=0,0,(INVESTORS_LIST[[#This Row],[LS_WEIGHT]]*INVESTORS_LIST[[#This Row],[LS_AVERAGE COST]])+(INVESTORS_LIST[[#This Row],[SIP_WEIGHT]]*INVESTORS_LIST[[#This Row],[SIP_AVERAGE COST]])) -> 0 | AO16: =NAV_MKT -> 14.224 | AP16: =IF(INVESTORS_LIST[[#This Row],[TOTAL CURRENT UNITS]]=0,0,INVESTORS_LIST[[#This Row],[TOTAL CURRENT UNITS]]*INVESTORS_LIST[[#This Row],[NAV]]) -> 0 | AQ16: =IF(INVESTORS_LIST[[#This Row],[LS_TOTAL CURRENT UNITS]]=0,0,INVESTORS_LIST[[#This Row],[LS_TOTAL CURRENT UNITS]]*INVESTORS_LIST[[#This Row],[NAV]]) -> 0 | AR16: =IF(INVESTORS_LIST[[#This Row],[SIP_TOTAL CURRENT UNITS]]=0,0,INVESTORS_LIST[[#This Row],[SIP_TOTAL CURRENT UNITS]]*INVESTORS_LIST[[#This Row],[NAV]]) -> 0 | AS16: =INVESTORS_LIST[[#This Row],[TOTAL CURRENT UNITS]] -> 0 | AT16: =IF(INVESTORS_LIST[[#This Row],[TOTAL SELLABLE UNITS]]=0,0,INVESTORS_LIST[[#This Row],[TOTAL SELLABLE UNITS]]*INVESTORS_LIST[[#This Row],[NAV]]) -> 0 | AU16: =INVESTORS_LIST[[#This Row],[LS_TOTAL REALIZED GAIN]]+INVESTORS_LIST[[#This Row],[SIP_TOTAL REALIZED GAIN]] -> 0 | AV16: =INVESTORS_LIST[[#This Row],[TOTAL MARKET VALUE]]-INVESTORS_LIST[[#This Row],[TOTAL COST VALUE OF CURRENT INVESTMENT]] -> 0 | AW16: =IFERROR(INVESTORS_LIST[[#This Row],[TOTAL CURRENT UNITS]]/SUM(INVESTORS_LIST[TOTAL CURRENT UNITS]),0) -> 0
A17: UCIL EMPLOYEES' PROVIDENT FUND | B17: A00017 | C17: Dear | D17: Providend Fund | E17: =SUMIFS(LS[Unit],LS[Investor ID],INVESTORS_LIST[[#This Row],[INVESTOR CODE]],LS[B/S],"B") -> 0 | F17: =-SUMIFS(LS[Unit],LS[Investor ID],INVESTORS_LIST[[#This Row],[INVESTOR CODE]],LS[B/S],"S") -> 0 | G17: =IF(INVESTORS_LIST[[#This Row],[LS_TOTAL UNITS BUY]]=0,0,INVESTORS_LIST[[#This Row],[LS_TOTAL UNITS BUY]]-INVESTORS_LIST[[#This Row],[LS_TOTAL UNITS SOLD]]) -> 0 | H17: =IF(INVESTORS_LIST[[#This Row],[LS_TOTAL UNITS BUY]]=0,0,SUMIFS(LS[Amount],LS[Investor ID],INVESTORS_LIST[[#This Row],[INVESTOR CODE]],LS[B/S],"B")) -> 0 | I17: =IF(INVESTORS_LIST[[#This Row],[LS_TOTAL UNITS SOLD]]=0,0,SUMIFS(LS[Cost of Units Sold],LS[Investor ID],INVESTORS_LIST[[#This Row],[INVESTOR CODE]],LS[B/S],"S")) -> 0 | J17: =IF(INVESTORS_LIST[[#This Row],[LS_TOTAL CURRENT UNITS]]=0,0,INVESTORS_LIST[[#This Row],[LS_TOTAL CURRENT UNITS]]*INVESTORS_LIST[[#This Row],[LS_AVERAGE COST]]) -> 0 | K17: =IF(INVESTORS_LIST[[#This Row],[LS_TOTAL UNITS SOLD]]=0,0,SUMIFS(LS[Realized Gain],LS[Investor ID],INVESTORS_LIST[[#This Row],[INVESTOR CODE]],LS[B/S],"S")) -> 0 | L17: =SUMIFS(SIP[Unit],SIP[Investor ID],INVESTORS_LIST[[#This Row],[INVESTOR CODE]],SIP[B/S],"B") -> 0 | M17: =-SUMIFS(SIP[Unit],SIP[Investor ID],INVESTORS_LIST[[#This Row],[INVESTOR CODE]],SIP[B/S],"S") -> 0 | N17: =IF(INVESTORS_LIST[[#This Row],[SIP_TOTAL UNITS BUY]]=0,0,INVESTORS_LIST[[#This Row],[SIP_TOTAL UNITS BUY]]-INVESTORS_LIST[[#This Row],[SIP_TOTAL UNITS SOLD]]) -> 0 | O17: =IF(INVESTORS_LIST[[#This Row],[SIP_TOTAL UNITS BUY]]=0,0,SUMIFS(SIP[Amount],SIP[Investor ID],INVESTORS_LIST[[#This Row],[INVESTOR CODE]],SIP[B/S],"B")) -> 0 | P17: =IF(INVESTORS_LIST[[#This Row],[SIP_TOTAL UNITS SOLD]]=0,0,SUMIFS(SIP[Cost of Units Sold],SIP[Investor ID],INVESTORS_LIST[[#This Row],[INVESTOR CODE]],SIP[B/S],"S")) -> 0 | Q17: =IF(INVESTORS_LIST[[#This Row],[SIP_TOTAL CURRENT UNITS]]=0,0,INVESTORS_LIST[[#This Row],[SIP_TOTAL CURRENT UNITS]]*INVESTORS_LIST[[#This Row],[SIP_AVERAGE COST]]) -> 0 | R17: =IF(INVESTORS_LIST[[#This Row],[SIP_TOTAL UNITS SOLD]]=0,0,SUMIFS(SIP[Realized Gain],SIP[Investor ID],INVESTORS_LIST[[#This Row],[INVESTOR CODE]],SIP[B/S],"S")) -> 0 | S17: =INVESTORS_LIST[[#This Row],[LS_TOTAL UNITS BUY]]+INVESTORS_LIST[[#This Row],[SIP_TOTAL UNITS BUY]] -> 0 | T17: =INVESTORS_LIST[[#This Row],[LS_TOTAL UNITS SOLD]]+INVESTORS_LIST[[#This Row],[SIP_TOTAL UNITS SOLD]] -> 0 | V17: =SUMIFS(LS[BO UNIT TRANSFER],LS[Investor ID],INVESTORS_LIST[[#This Row],[INVESTOR CODE]],LS[B/S],"B") -> 0 | W17: =SUMIFS(SIP[BO UNIT TRANSFER],SIP[Investor ID],INVESTORS_LIST[[#This Row],[INVESTOR CODE]],SIP[B/S],"B") -> 0 | X17: =SUMIFS(LS[BO UNIT TRANSFER],LS[Investor ID],INVESTORS_LIST[[#This Row],[INVESTOR CODE]],LS[B/S],"S") -> 0 | Y17: =SUMIFS(SIP[BO UNIT TRANSFER],SIP[Investor ID],INVESTORS_LIST[[#This Row],[INVESTOR CODE]],SIP[B/S],"S") -> 0 | Z17: =SUM(INVESTORS_LIST[[#This Row],[BO OPENING BALANCE]:[BO SIP UNITS REPURCHASE]]) -> 0 | AA17: =INVESTORS_LIST[[#This Row],[TOTAL UNITS BUY]]-INVESTORS_LIST[[#This Row],[TOTAL UNITS SOLD]] -> 0 | AB17: =INVESTORS_LIST[[#This Row],[TOTAL CURRENT UNITS]]-INVESTORS_LIST[[#This Row],[BO UNITS HOLD]] -> 0 | AC17: =INDEX([3]!Table_1[BO ID],MATCH(INVESTORS_LIST[[#This Row],[INVESTOR CODE]],[3]!Table_1[INVESTOR CODE],0)) -> #REF! | AD17: =INDEX([3]!Table_1[Brokerage Name2],MATCH(INVESTORS_LIST[[#This Row],[INVESTOR CODE]],[3]!Table_1[INVESTOR CODE],0)) -> #REF! | AE17: =MID(INVESTORS_LIST[[#This Row],[BO ID]],4,5) -> #REF! | AF17: =MID(INVESTORS_LIST[[#This Row],[BO ID]],2,7) -> #REF! | AG17: =MID(INVESTORS_LIST[[#This Row],[BO ID]],9,7) -> #REF! | AH17: =RIGHT(INVESTORS_LIST[[#This Row],[BO ID]],1) -> #REF! | AI17: =INVESTORS_LIST[[#This Row],[LS_TOTAL COST VALUE OF CURRENT UNITS]]+INVESTORS_LIST[[#This Row],[SIP_TOTAL COST VALUE OF CURRENT UNITS]] -> 0 | AJ17: =IF(INVESTORS_LIST[[#This Row],[TOTAL CURRENT UNITS]]=0,0,INVESTORS_LIST[[#This Row],[LS_TOTAL CURRENT UNITS]]/INVESTORS_LIST[[#This Row],[TOTAL CURRENT UNITS]]) -> 0 | AK17: =IF(INVESTORS_LIST[[#This Row],[TOTAL CURRENT UNITS]]=0,0,INVESTORS_LIST[[#This Row],[SIP_TOTAL CURRENT UNITS]]/INVESTORS_LIST[[#This Row],[TOTAL CURRENT UNITS]]) -> 0 | AL17: {=IF(INVESTORS_LIST[[#This Row],[LS_TOTAL UNITS BUY]]>0,INDEX(LS[NAV at Cost (Average)],MATCH(CONCATENATE(COUNTIFS(LS[Investor ID],INVESTORS_LIST[[#This Row],[INVESTOR CODE]]),INVESTORS_LIST[[#This Row],[INVESTOR CODE]]),LS[Unique Code],0),),0)} -> 0 | AM17: {=IF(INVESTORS_LIST[[#This Row],[SIP_TOTAL UNITS BUY]]>0,INDEX(SIP[NAV at Cost (Average)],MATCH(CONCATENATE(COUNTIFS(SIP[Investor ID],INVESTORS_LIST[[#This Row],[INVESTOR CODE]]),INVESTORS_LIST[[#This Row],[INVESTOR CODE]]),SIP[Unique Code],0),),0)} -> 0 | AN17: =IF(INVESTORS_LIST[[#This Row],[TOTAL CURRENT UNITS]]=0,0,(INVESTORS_LIST[[#This Row],[LS_WEIGHT]]*INVESTORS_LIST[[#This Row],[LS_AVERAGE COST]])+(INVESTORS_LIST[[#This Row],[SIP_WEIGHT]]*INVESTORS_LIST[[#This Row],[SIP_AVERAGE COST]])) -> 0 | AO17: =NAV_MKT -> 14.224 | AP17: =IF(INVESTORS_LIST[[#This Row],[TOTAL CURRENT UNITS]]=0,0,INVESTORS_LIST[[#This Row],[TOTAL CURRENT UNITS]]*INVESTORS_LIST[[#This Row],[NAV]]) -> 0 | AQ17: =IF(INVESTORS_LIST[[#This Row],[LS_TOTAL CURRENT UNITS]]=0,0,INVESTORS_LIST[[#This Row],[LS_TOTAL CURRENT UNITS]]*INVESTORS_LIST[[#This Row],[NAV]]) -> 0 | AR17: =IF(INVESTORS_LIST[[#This Row],[SIP_TOTAL CURRENT UNITS]]=0,0,INVESTORS_LIST[[#This Row],[SIP_TOTAL CURRENT UNITS]]*INVESTORS_LIST[[#This Row],[NAV]]) -> 0 | AS17: =INVESTORS_LIST[[#This Row],[TOTAL CURRENT UNITS]] -> 0 | AT17: =IF(INVESTORS_LIST[[#This Row],[TOTAL SELLABLE UNITS]]=0,0,INVESTORS_LIST[[#This Row],[TOTAL SELLABLE UNITS]]*INVESTORS_LIST[[#This Row],[NAV]]) -> 0 | AU17: =INVESTORS_LIST[[#This Row],[LS_TOTAL REALIZED GAIN]]+INVESTORS_LIST[[#This Row],[SIP_TOTAL REALIZED GAIN]] -> 0 | AV17: =INVESTORS_LIST[[#This Row],[TOTAL MARKET VALUE]]-INVESTORS_LIST[[#This Row],[TOTAL COST VALUE OF CURRENT INVESTMENT]] -> 0 | AW17: =IFERROR(INVESTORS_LIST[[#This Row],[TOTAL CURRENT UNITS]]/SUM(INVESTORS_LIST[TOTAL CURRENT UNITS]),0) -> 0
A18: MD. ZAKIR HOSSEN | B18: A00018 | C18: Dear Mr. | D18: Individual | E18: =SUMIFS(LS[Unit],LS[Investor ID],INVESTORS_LIST[[#This Row],[INVESTOR CODE]],LS[B/S],"B") -> 80000 | F18: =-SUMIFS(LS[Unit],LS[Investor ID],INVESTORS_LIST[[#This Row],[INVESTOR CODE]],LS[B/S],"S") -> 80000 | G18: =IF(INVESTORS_LIST[[#This Row],[LS_TOTAL UNITS BUY]]=0,0,INVESTORS_LIST[[#This Row],[LS_TOTAL UNITS BUY]]-INVESTORS_LIST[[#This Row],[LS_TOTAL UNITS SOLD]]) -> 0 | H18: =IF(INVESTORS_LIST[[#This Row],[LS_TOTAL UNITS BUY]]=0,0,SUMIFS(LS[Amount],LS[Investor ID],INVESTORS_LIST[[#This Row],[INVESTOR CODE]],LS[B/S],"B")) -> 800000 | I18: =IF(INVESTORS_LIST[[#This Row],[LS_TOTAL UNITS SOLD]]=0,0,SUMIFS(LS[Cost of Units Sold],LS[Investor ID],INVESTORS_LIST[[#This Row],[INVESTOR CODE]],LS[B/S],"S")) -> 800000 | J18: =IF(INVESTORS_LIST[[#This Row],[LS_TOTAL CURRENT UNITS]]=0,0,INVESTORS_LIST[[#This Row],[LS_TOTAL CURRENT UNITS]]*INVESTORS_LIST[[#This Row],[LS_AVERAGE COST]]) -> 0 | K18: =IF(INVESTORS_LIST[[#This Row],[LS_TOTAL UNITS SOLD]]=0,0,SUMIFS(LS[Realized Gain],LS[Investor ID],INVESTORS_LIST[[#This Row],[INVESTOR CODE]],LS[B/S],"S")) -> 211920 | L18: =SUMIFS(SIP[Unit],SIP[Investor ID],INVESTORS_LIST[[#This Row],[INVESTOR CODE]],SIP[B/S],"B") -> 0 | M18: =-SUMIFS(SIP[Unit],SIP[Investor ID],INVESTORS_LIST[[#This Row],[INVESTOR CODE]],SIP[B/S],"S") -> 0 | N18: =IF(INVESTORS_LIST[[#This Row],[SIP_TOTAL UNITS BUY]]=0,0,INVESTORS_LIST[[#This Row],[SIP_TOTAL UNITS BUY]]-INVESTORS_LIST[[#This Row],[SIP_TOTAL UNITS SOLD]]) -> 0 | O18: =IF(INVESTORS_LIST[[#This Row],[SIP_TOTAL UNITS BUY]]=0,0,SUMIFS(SIP[Amount],SIP[Investor ID],INVESTORS_LIST[[#This Row],[INVESTOR CODE]],SIP[B/S],"B")) -> 0 | P18: =IF(INVESTORS_LIST[[#This Row],[SIP_TOTAL UNITS SOLD]]=0,0,SUMIFS(SIP[Cost of Units Sold],SIP[Investor ID],INVESTORS_LIST[[#This Row],[INVESTOR CODE]],SIP[B/S],"S")) -> 0 | Q18: =IF(INVESTORS_LIST[[#This Row],[SIP_TOTAL CURRENT UNITS]]=0,0,INVESTORS_LIST[[#This Row],[SIP_TOTAL CURRENT UNITS]]*INVESTORS_LIST[[#This Row],[SIP_AVERAGE COST]]) -> 0 | R18: =IF(INVESTORS_LIST[[#This Row],[SIP_TOTAL UNITS SOLD]]=0,0,SUMIFS(SIP[Realized Gain],SIP[Investor ID],INVESTORS_LIST[[#This Row],[INVESTOR CODE]],SIP[B/S],"S")) -> 0 | S18: =INVESTORS_LIST[[#This Row],[LS_TOTAL UNITS BUY]]+INVESTORS_LIST[[#This Row],[SIP_TOTAL UNITS BUY]] -> 80000 | T18: =INVESTORS_LIST[[#This Row],[LS_TOTAL UNITS SOLD]]+INVESTORS_LIST[[#This Row],[SIP_TOTAL UNITS SOLD]] -> 80000 | V18: =SUMIFS(LS[BO UNIT TRANSFER],LS[Investor ID],INVESTORS_LIST[[#This Row],[INVESTOR CODE]],LS[B/S],"B") -> 0 | W18: =SUMIFS(SIP[BO UNIT TRANSFER],SIP[Investor ID],INVESTORS_LIST[[#This Row],[INVESTOR CODE]],SIP[B/S],"B") -> 0 | X18: =SUMIFS(LS[BO UNIT TRANSFER],LS[Investor ID],INVESTORS_LIST[[#This Row],[INVESTOR CODE]],LS[B/S],"S") -> 0 | Y18: =SUMIFS(SIP[BO UNIT TRANSFER],SIP[Investor ID],INVESTORS_LIST[[#This Row],[INVESTOR CODE]],SIP[B/S],"S") -> 0 | Z18: =SUM(INVESTORS_LIST[[#This Row],[BO OPENING BALANCE]:[BO SIP UNITS REPURCHASE]]) -> 0 | AA18: =INVESTORS_LIST[[#This Row],[TOTAL UNITS BUY]]-INVESTORS_LIST[[#This Row],[TOTAL UNITS SOLD]] -> 0 | AB18: =INVESTORS_LIST[[#This Row],[TOTAL CURRENT UNITS]]-INVESTORS_LIST[[#This Row],[BO UNITS HOLD]] -> 0 | AC18: =INDEX([3]!Table_1[BO ID],MATCH(INVESTORS_LIST[[#This Row],[INVESTOR CODE]],[3]!Table_1[INVESTOR CODE],0)) -> #REF! | AD18: =INDEX([3]!Table_1[Brokerage Name2],MATCH(INVESTORS_LIST[[#This Row],[INVESTOR CODE]],[3]!Table_1[INVESTOR CODE],0)) -> #REF! | AE18: =MID(INVESTORS_LIST[[#This Row],[BO ID]],4,5) -> #REF! | AF18: =MID(INVESTORS_LIST[[#This Row],[BO ID]],2,7) -> #REF! | AG18: =MID(INVESTORS_LIST[[#This Row],[BO ID]],9,7) -> #REF! | AH18: =RIGHT(INVESTORS_LIST[[#This Row],[BO ID]],1) -> #REF! | AI18: =INVESTORS_LIST[[#This Row],[LS_TOTAL COST VALUE OF CURRENT UNITS]]+INVESTORS_LIST[[#This Row],[SIP_TOTAL COST VALUE OF CURRENT UNITS]] -> 0 | AJ18: =IF(INVESTORS_LIST[[#This Row],[TOTAL CURRENT UNITS]]=0,0,INVESTORS_LIST[[#This Row],[LS_TOTAL CURRENT UNITS]]/INVESTORS_LIST[[#This Row],[TOTAL CURRENT UNITS]]) -> 0 | AK18: =IF(INVESTORS_LIST[[#This Row],[TOTAL CURRENT UNITS]]=0,0,INVESTORS_LIST[[#This Row],[SIP_TOTAL CURRENT UNITS]]/INVESTORS_LIST[[#This Row],[TOTAL CURRENT UNITS]]) -> 0 | AL18: {=IF(INVESTORS_LIST[[#This Row],[LS_TOTAL UNITS BUY]]>0,INDEX(LS[NAV at Cost (Average)],MATCH(CONCATENATE(COUNTIFS(LS[Investor ID],INVESTORS_LIST[[#This Row],[INVESTOR CODE]]),INVESTORS_LIST[[#This Row],[INVESTOR CODE]]),LS[Unique Code],0),),0)} -> 0 | AM18: {=IF(INVESTORS_LIST[[#This Row],[SIP_TOTAL UNITS BUY]]>0,INDEX(SIP[NAV at Cost (Average)],MATCH(CONCATENATE(COUNTIFS(SIP[Investor ID],INVESTORS_LIST[[#This Row],[INVESTOR CODE]]),INVESTORS_LIST[[#This Row],[INVESTOR CODE]]),SIP[Unique Code],0),),0)} -> 0 | AN18: =IF(INVESTORS_LIST[[#This Row],[TOTAL CURRENT UNITS]]=0,0,(INVESTORS_LIST[[#This Row],[LS_WEIGHT]]*INVESTORS_LIST[[#This Row],[LS_AVERAGE COST]])+(INVESTORS_LIST[[#This Row],[SIP_WEIGHT]]*INVESTORS_LIST[[#This Row],[SIP_AVERAGE COST]])) -> 0 | AO18: =NAV_MKT -> 14.224 | AP18: =IF(INVESTORS_LIST[[#This Row],[TOTAL CURRENT UNITS]]=0,0,INVESTORS_LIST[[#This Row],[TOTAL CURRENT UNITS]]*INVESTORS_LIST[[#This Row],[NAV]]) -> 0 | AQ18: =IF(INVESTORS_LIST[[#This Row],[LS_TOTAL CURRENT UNITS]]=0,0,INVESTORS_LIST[[#This Row],[LS_TOTAL CURRENT UNITS]]*INVESTORS_LIST[[#This Row],[NAV]]) -> 0 | AR18: =IF(INVESTORS_LIST[[#This Row],[SIP_TOTAL CURRENT UNITS]]=0,0,INVESTORS_LIST[[#This Row],[SIP_TOTAL CURRENT UNITS]]*INVESTORS_LIST[[#This Row],[NAV]]) -> 0 | AS18: =INVESTORS_LIST[[#This Row],[TOTAL CURRENT UNITS]] -> 0 | AT18: =IF(INVESTORS_LIST[[#This Row],[TOTAL SELLABLE UNITS]]=0,0,INVESTORS_LIST[[#This Row],[TOTAL SELLABLE UNITS]]*INVESTORS_LIST[[#This Row],[NAV]]) -> 0 | AU18: =INVESTORS_LIST[[#This Row],[LS_TOTAL REALIZED GAIN]]+INVESTORS_LIST[[#This Row],[SIP_TOTAL REALIZED GAIN]] -> 211920 | AV18: =INVESTORS_LIST[[#This Row],[TOTAL MARKET VALUE]]-INVESTORS_LIST[[#This Row],[TOTAL COST VALUE OF CURRENT INVESTMENT]] -> 0 | AW18: =IFERROR(INVESTORS_LIST[[#This Row],[TOTAL CURRENT UNITS]]/SUM(INVESTORS_LIST[TOTAL CURRENT UNITS]),0) -> 0
A19: TANIZA MAZED | B19: A00019 | C19: Dear Mrs. | D19: Individual | E19: =SUMIFS(LS[Unit],LS[Investor ID],INVESTORS_LIST[[#This Row],[INVESTOR CODE]],LS[B/S],"B") -> 339497 | F19: =-SUMIFS(LS[Unit],LS[Investor ID],INVESTORS_LIST[[#This Row],[INVESTOR CODE]],LS[B/S],"S") -> 152812 | G19: =IF(INVESTORS_LIST[[#This Row],[LS_TOTAL UNITS BUY]]=0,0,INVESTORS_LIST[[#This Row],[LS_TOTAL UNITS BUY]]-INVESTORS_LIST[[#This Row],[LS_TOTAL UNITS SOLD]]) -> 186685 | H19: =IF(INVESTORS_LIST[[#This Row],[LS_TOTAL UNITS BUY]]=0,0,SUMIFS(LS[Amount],LS[Investor ID],INVESTORS_LIST[[#This Row],[INVESTOR CODE]],LS[B/S],"B")) -> 3800000 | I19: =IF(INVESTORS_LIST[[#This Row],[LS_TOTAL UNITS SOLD]]=0,0,SUMIFS(LS[Cost of Units Sold],LS[Investor ID],INVESTORS_LIST[[#This Row],[INVESTOR CODE]],LS[B/S],"S")) -> 1710429.3 | J19: =IF(INVESTORS_LIST[[#This Row],[LS_TOTAL CURRENT UNITS]]=0,0,INVESTORS_LIST[[#This Row],[LS_TOTAL CURRENT UNITS]]*INVESTORS_LIST[[#This Row],[LS_AVERAGE COST]]) -> 2089570.7 | K19: =IF(INVESTORS_LIST[[#This Row],[LS_TOTAL UNITS SOLD]]=0,0,SUMIFS(LS[Realized Gain],LS[Investor ID],INVESTORS_LIST[[#This Row],[INVESTOR CODE]],LS[B/S],"S")) -> 289570.75 | L19: =SUMIFS(SIP[Unit],SIP[Investor ID],INVESTORS_LIST[[#This Row],[INVESTOR CODE]],SIP[B/S],"B") -> 0 | M19: =-SUMIFS(SIP[Unit],SIP[Investor ID],INVESTORS_LIST[[#This Row],[INVESTOR CODE]],SIP[B/S],"S") -> 0 | N19: =IF(INVESTORS_LIST[[#This Row],[SIP_TOTAL UNITS BUY]]=0,0,INVESTORS_LIST[[#This Row],[SIP_TOTAL UNITS BUY]]-INVESTORS_LIST[[#This Row],[SIP_TOTAL UNITS SOLD]]) -> 0 | O19: =IF(INVESTORS_LIST[[#This Row],[SIP_TOTAL UNITS BUY]]=0,0,SUMIFS(SIP[Amount],SIP[Investor ID],INVESTORS_LIST[[#This Row],[INVESTOR CODE]],SIP[B/S],"B")) -> 0 | P19: =IF(INVESTORS_LIST[[#This Row],[SIP_TOTAL UNITS SOLD]]=0,0,SUMIFS(SIP[Cost of Units Sold],SIP[Investor ID],INVESTORS_LIST[[#This Row],[INVESTOR CODE]],SIP[B/S],"S")) -> 0 | Q19: =IF(INVESTORS_LIST[[#This Row],[SIP_TOTAL CURRENT UNITS]]=0,0,INVESTORS_LIST[[#This Row],[SIP_TOTAL CURRENT UNITS]]*INVESTORS_LIST[[#This Row],[SIP_AVERAGE COST]]) -> 0 | R19: =IF(INVESTORS_LIST[[#This Row],[SIP_TOTAL UNITS SOLD]]=0,0,SUMIFS(SIP[Realized Gain],SIP[Investor ID],INVESTORS_LIST[[#This Row],[INVESTOR CODE]],SIP[B/S],"S")) -> 0 | S19: =INVESTORS_LIST[[#This Row],[LS_TOTAL UNITS BUY]]+INVESTORS_LIST[[#This Row],[SIP_TOTAL UNITS BUY]] -> 339497 | T19: =INVESTORS_LIST[[#This Row],[LS_TOTAL UNITS SOLD]]+INVESTORS_LIST[[#This Row],[SIP_TOTAL UNITS SOLD]] -> 152812 | U19: 339497 | V19: =SUMIFS(LS[BO UNIT TRANSFER],LS[Investor ID],INVESTORS_LIST[[#This Row],[INVESTOR CODE]],LS[B/S],"B") -> 0 | W19: =SUMIFS(SIP[BO UNIT TRANSFER],SIP[Investor ID],INVESTORS_LIST[[#This Row],[INVESTOR CODE]],SIP[B/S],"B") -> 0 | X19: =SUMIFS(LS[BO UNIT TRANSFER],LS[Investor ID],INVESTORS_LIST[[#This Row],[INVESTOR CODE]],LS[B/S],"S") -> 0 | Y19: =SUMIFS(SIP[BO UNIT TRANSFER],SIP[Investor ID],INVESTORS_LIST[[#This Row],[INVESTOR CODE]],SIP[B/S],"S") -> 0 | Z19: =SUM(INVESTORS_LIST[[#This Row],[BO OPENING BALANCE]:[BO SIP UNITS REPURCHASE]]) -> 339497 | AA19: =INVESTORS_LIST[[#This Row],[TOTAL UNITS BUY]]-INVESTORS_LIST[[#This Row],[TOTAL UNITS SOLD]] -> 186685 | AB19: =INVESTORS_LIST[[#This Row],[TOTAL CURRENT UNITS]]-INVESTORS_LIST[[#This Row],[BO UNITS HOLD]] -> -152812 | AC19: =INDEX([3]!Table_1[BO ID],MATCH(INVESTORS_LIST[[#This Row],[INVESTOR CODE]],[3]!Table_1[INVESTOR CODE],0)) -> #REF! | AD19: =INDEX([3]!Table_1[Brokerage Name2],MATCH(INVESTORS_LIST[[#This Row],[INVESTOR CODE]],[3]!Table_1[INVESTOR CODE],0)) -> #REF! | AE19: =MID(INVESTORS_LIST[[#This Row],[BO ID]],4,5) -> #REF! | AF19: =MID(INVESTORS_LIST[[#This Row],[BO ID]],2,7) -> #REF! | AG19: =MID(INVESTORS_LIST[[#This Row],[BO ID]],9,7) -> #REF! | AH19: =RIGHT(INVESTORS_LIST[[#This Row],[BO ID]],1) -> #REF! | AI19: =INVESTORS_LIST[[#This Row],[LS_TOTAL COST VALUE OF CURRENT UNITS]]+INVESTORS_LIST[[#This Row],[SIP_TOTAL COST VALUE OF CURRENT UNITS]] -> 2089570.7 | AJ19: =IF(INVESTORS_LIST[[#This Row],[TOTAL CURRENT UNITS]]=0,0,INVESTORS_LIST[[#This Row],[LS_TOTAL CURRENT UNITS]]/INVESTORS_LIST[[#This Row],[TOTAL CURRENT UNITS]]) -> 1 | AK19: =IF(INVESTORS_LIST[[#This Row],[TOTAL CURRENT UNITS]]=0,0,INVESTORS_LIST[[#This Row],[SIP_TOTAL CURRENT UNITS]]/INVESTORS_LIST[[#This Row],[TOTAL CURRENT UNITS]]) -> 0 | AL19: {=IF(INVESTORS_LIST[[#This Row],[LS_TOTAL UNITS BUY]]>0,INDEX(LS[NAV at Cost (Average)],MATCH(CONCATENATE(COUNTIFS(LS[Investor ID],INVESTORS_LIST[[#This Row],[INVESTOR CODE]]),INVESTORS_LIST[[#This Row],[INVESTOR CODE]]),LS[Unique Code],0),),0)} -> 11.19303 | AM19: {=IF(INVESTORS_LIST[[#This Row],[SIP_TOTAL UNITS BUY]]>0,INDEX(SIP[NAV at Cost (Average)],MATCH(CONCATENATE(COUNTIFS(SIP[Investor ID],INVESTORS_LIST[[#This Row],[INVESTOR CODE]]),INVESTORS_LIST[[#This Row],[INVESTOR CODE]]),SIP[Unique Code],0),),0)} -> 0 | AN19: =IF(INVESTORS_LIST[[#This Row],[TOTAL CURRENT UNITS]]=0,0,(INVESTORS_LIST[[#This Row],[LS_WEIGHT]]*INVESTORS_LIST[[#This Row],[LS_AVERAGE COST]])+(INVESTORS_LIST[[#This Row],[SIP_WEIGHT]]*INVESTORS_LIST[[#This Row],[SIP_AVERAGE COST]])) -> 11.19303 | AO19: =NAV_MKT -> 14.224 | AP19: =IF(INVESTORS_LIST[[#This Row],[TOTAL CURRENT UNITS]]=0,0,INVESTORS_LIST[[#This Row],[TOTAL CURRENT UNITS]]*INVESTORS_LIST[[#This Row],[NAV]]) -> 2655407.4 | AQ19: =IF(INVESTORS_LIST[[#This Row],[LS_TOTAL CURRENT UNITS]]=0,0,INVESTORS_LIST[[#This Row],[LS_TOTAL CURRENT UNITS]]*INVESTORS_LIST[[#This Row],[NAV]]) -> 2655407.4 | AR19: =IF(INVESTORS_LIST[[#This Row],[SIP_TOTAL CURRENT UNITS]]=0,0,INVESTORS_LIST[[#This Row],[SIP_TOTAL CURRENT UNITS]]*INVESTORS_LIST[[#This Row],[NAV]]) -> 0 | AS19: =INVESTORS_LIST[[#This Row],[TOTAL CURRENT UNITS]] -> 186685 | AT19: =IF(INVESTORS_LIST[[#This Row],[TOTAL SELLABLE UNITS]]=0,0,INVESTORS_LIST[[#This Row],[TOTAL SELLABLE UNITS]]*INVESTORS_LIST[[#This Row],[NAV]]) -> 2655407.4 | AU19: =INVESTORS_LIST[[#This Row],[LS_TOTAL REALIZED GAIN]]+INVESTORS_LIST[[#This Row],[SIP_TOTAL REALIZED GAIN]] -> 289570.75 | AV19: =INVESTORS_LIST[[#This Row],[TOTAL MARKET VALUE]]-INVESTORS_LIST[[#This Row],[TOTAL COST VALUE OF CURRENT INVESTMENT]] -> 565836.69 | AW19: =IFERROR(INVESTORS_LIST[[#This Row],[TOTAL CURRENT UNITS]]/SUM(INVESTORS_LIST[TOTAL CURRENT UNITS]),0) -> 0.0045320039
A20: MRIDUL KUMAR DEY | B20: A00020 | C20: Dear Mr. | D20: Individual | E20: =SUMIFS(LS[Unit],LS[Investor ID],INVESTORS_LIST[[#This Row],[INVESTOR CODE]],LS[B/S],"B") -> 0 | F20: =-SUMIFS(LS[Unit],LS[Investor ID],INVESTORS_LIST[[#This Row],[INVESTOR CODE]],LS[B/S],"S") -> 0 | G20: =IF(INVESTORS_LIST[[#This Row],[LS_TOTAL UNITS BUY]]=0,0,INVESTORS_LIST[[#This Row],[LS_TOTAL UNITS BUY]]-INVESTORS_LIST[[#This Row],[LS_TOTAL UNITS SOLD]]) -> 0 | H20: =IF(INVESTORS_LIST[[#This Row],[LS_TOTAL UNITS BUY]]=0,0,SUMIFS(LS[Amount],LS[Investor ID],INVESTORS_LIST[[#This Row],[INVESTOR CODE]],LS[B/S],"B")) -> 0 | I20: =IF(INVESTORS_LIST[[#This Row],[LS_TOTAL UNITS SOLD]]=0,0,SUMIFS(LS[Cost of Units Sold],LS[Investor ID],INVESTORS_LIST[[#This Row],[INVESTOR CODE]],LS[B/S],"S")) -> 0 | J20: =IF(INVESTORS_LIST[[#This Row],[LS_TOTAL CURRENT UNITS]]=0,0,INVESTORS_LIST[[#This Row],[LS_TOTAL CURRENT UNITS]]*INVESTORS_LIST[[#This Row],[LS_AVERAGE COST]]) -> 0 | K20: =IF(INVESTORS_LIST[[#This Row],[LS_TOTAL UNITS SOLD]]=0,0,SUMIFS(LS[Realized Gain],LS[Investor ID],INVESTORS_LIST[[#This Row],[INVESTOR CODE]],LS[B/S],"S")) -> 0 | L20: =SUMIFS(SIP[Unit],SIP[Investor ID],INVESTORS_LIST[[#This Row],[INVESTOR CODE]],SIP[B/S],"B") -> 0 | M20: =-SUMIFS(SIP[Unit],SIP[Investor ID],INVESTORS_LIST[[#This Row],[INVESTOR CODE]],SIP[B/S],"S") -> 0 | N20: =IF(INVESTORS_LIST[[#This Row],[SIP_TOTAL UNITS BUY]]=0,0,INVESTORS_LIST[[#This Row],[SIP_TOTAL UNITS BUY]]-INVESTORS_LIST[[#This Row],[SIP_TOTAL UNITS SOLD]]) -> 0 | O20: =IF(INVESTORS_LIST[[#This Row],[SIP_TOTAL UNITS BUY]]=0,0,SUMIFS(SIP[Amount],SIP[Investor ID],INVESTORS_LIST[[#This Row],[INVESTOR CODE]],SIP[B/S],"B")) -> 0 | P20: =IF(INVESTORS_LIST[[#This Row],[SIP_TOTAL UNITS SOLD]]=0,0,SUMIFS(SIP[Cost of Units Sold],SIP[Investor ID],INVESTORS_LIST[[#This Row],[INVESTOR CODE]],SIP[B/S],"S")) -> 0 | Q20: =IF(INVESTORS_LIST[[#This Row],[SIP_TOTAL CURRENT UNITS]]=0,0,INVESTORS_LIST[[#This Row],[SIP_TOTAL CURRENT UNITS]]*INVESTORS_LIST[[#This Row],[SIP_AVERAGE COST]]) -> 0 | R20: =IF(INVESTORS_LIST[[#This Row],[SIP_TOTAL UNITS SOLD]]=0,0,SUMIFS(SIP[Realized Gain],SIP[Investor ID],INVESTORS_LIST[[#This Row],[INVESTOR CODE]],SIP[B/S],"S")) -> 0 | S20: =INVESTORS_LIST[[#This Row],[LS_TOTAL UNITS BUY]]+INVESTORS_LIST[[#This Row],[SIP_TOTAL UNITS BUY]] -> 0 | T20: =INVESTORS_LIST[[#This Row],[LS_TOTAL UNITS SOLD]]+INVESTORS_LIST[[#This Row],[SIP_TOTAL UNITS SOLD]] -> 0 | V20: =SUMIFS(LS[BO UNIT TRANSFER],LS[Investor ID],INVESTORS_LIST[[#This Row],[INVESTOR CODE]],LS[B/S],"B") -> 0 | W20: =SUMIFS(SIP[BO UNIT TRANSFER],SIP[Investor ID],INVESTORS_LIST[[#This Row],[INVESTOR CODE]],SIP[B/S],"B") -> 0 | X20: =SUMIFS(LS[BO UNIT TRANSFER],LS[Investor ID],INVESTORS_LIST[[#This Row],[INVESTOR CODE]],LS[B/S],"S") -> 0 | Y20: =SUMIFS(SIP[BO UNIT TRANSFER],SIP[Investor ID],INVESTORS_LIST[[#This Row],[INVESTOR CODE]],SIP[B/S],"S") -> 0 | Z20: =SUM(INVESTORS_LIST[[#This Row],[BO OPENING BALANCE]:[BO SIP UNITS REPURCHASE]]) -> 0 | AA20: =INVESTORS_LIST[[#This Row],[TOTAL UNITS BUY]]-INVESTORS_LIST[[#This Row],[TOTAL UNITS SOLD]] -> 0 | AB20: =INVESTORS_LIST[[#This Row],[TOTAL CURRENT UNITS]]-INVESTORS_LIST[[#This Row],[BO UNITS HOLD]] -> 0 | AC20: =INDEX([3]!Table_1[BO ID],MATCH(INVESTORS_LIST[[#This Row],[INVESTOR CODE]],[3]!Table_1[INVESTOR CODE],0)) -> #REF! | AD20: =INDEX([3]!Table_1[Brokerage Name2],MATCH(INVESTORS_LIST[[#This Row],[INVESTOR CODE]],[3]!Table_1[INVESTOR CODE],0)) -> #REF! | AE20: =MID(INVESTORS_LIST[[#This Row],[BO ID]],4,5) -> #REF! | AF20: =MID(INVESTORS_LIST[[#This Row],[BO ID]],2,7) -> #REF! | AG20: =MID(INVESTORS_LIST[[#This Row],[BO ID]],9,7) -> #REF! | AH20: =RIGHT(INVESTORS_LIST[[#This Row],[BO ID]],1) -> #REF! | AI20: =INVESTORS_LIST[[#This Row],[LS_TOTAL COST VALUE OF CURRENT UNITS]]+INVESTORS_LIST[[#This Row],[SIP_TOTAL COST VALUE OF CURRENT UNITS]] -> 0 | AJ20: =IF(INVESTORS_LIST[[#This Row],[TOTAL CURRENT UNITS]]=0,0,INVESTORS_LIST[[#This Row],[LS_TOTAL CURRENT UNITS]]/INVESTORS_LIST[[#This Row],[TOTAL CURRENT UNITS]]) -> 0 | AK20: =IF(INVESTORS_LIST[[#This Row],[TOTAL CURRENT UNITS]]=0,0,INVESTORS_LIST[[#This Row],[SIP_TOTAL CURRENT UNITS]]/INVESTORS_LIST[[#This Row],[TOTAL CURRENT UNITS]]) -> 0 | AL20: {=IF(INVESTORS_LIST[[#This Row],[LS_TOTAL UNITS BUY]]>0,INDEX(LS[NAV at Cost (Average)],MATCH(CONCATENATE(COUNTIFS(LS[Investor ID],INVESTORS_LIST[[#This Row],[INVESTOR CODE]]),INVESTORS_LIST[[#This Row],[INVESTOR CODE]]),LS[Unique Code],0),),0)} -> 0 | AM20: {=IF(INVESTORS_LIST[[#This Row],[SIP_TOTAL UNITS BUY]]>0,INDEX(SIP[NAV at Cost (Average)],MATCH(CONCATENATE(COUNTIFS(SIP[Investor ID],INVESTORS_LIST[[#This Row],[INVESTOR CODE]]),INVESTORS_LIST[[#This Row],[INVESTOR CODE]]),SIP[Unique Code],0),),0)} -> 0 | AN20: =IF(INVESTORS_LIST[[#This Row],[TOTAL CURRENT UNITS]]=0,0,(INVESTORS_LIST[[#This Row],[LS_WEIGHT]]*INVESTORS_LIST[[#This Row],[LS_AVERAGE COST]])+(INVESTORS_LIST[[#This Row],[SIP_WEIGHT]]*INVESTORS_LIST[[#This Row],[SIP_AVERAGE COST]])) -> 0 | AO20: =NAV_MKT -> 14.224 | AP20: =IF(INVESTORS_LIST[[#This Row],[TOTAL CURRENT UNITS]]=0,0,INVESTORS_LIST[[#This Row],[TOTAL CURRENT UNITS]]*INVESTORS_LIST[[#This Row],[NAV]]) -> 0 | AQ20: =IF(INVESTORS_LIST[[#This Row],[LS_TOTAL CURRENT UNITS]]=0,0,INVESTORS_LIST[[#This Row],[LS_TOTAL CURRENT UNITS]]*INVESTORS_LIST[[#This Row],[NAV]]) -> 0 | AR20: =IF(INVESTORS_LIST[[#This Row],[SIP_TOTAL CURRENT UNITS]]=0,0,INVESTORS_LIST[[#This Row],[SIP_TOTAL CURRENT UNITS]]*INVESTORS_LIST[[#This Row],[NAV]]) -> 0 | AS20: =INVESTORS_LIST[[#This Row],[TOTAL CURRENT UNITS]] -> 0 | AT20: =IF(INVESTORS_LIST[[#This Row],[TOTAL SELLABLE UNITS]]=0,0,INVESTORS_LIST[[#This Row],[TOTAL SELLABLE UNITS]]*INVESTORS_LIST[[#This Row],[NAV]]) -> 0 | AU20: =INVESTORS_LIST[[#This Row],[LS_TOTAL REALIZED GAIN]]+INVESTORS_LIST[[#This Row],[SIP_TOTAL REALIZED GAIN]] -> 0 | AV20: =INVESTORS_LIST[[#This Row],[TOTAL MARKET VALUE]]-INVESTORS_LIST[[#This Row],[TOTAL COST VALUE OF CURRENT INVESTMENT]] -> 0 | AW20: =IFERROR(INVESTORS_LIST[[#This Row],[TOTAL CURRENT UNITS]]/SUM(INVESTORS_LIST[TOTAL CURRENT UNITS]),0) -> 0
A21: MAMUNUR RASHID | B21: A00021 | C21: Dear Mr. | D21: Individual | E21: =SUMIFS(LS[Unit],LS[Investor ID],INVESTORS_LIST[[#This Row],[INVESTOR CODE]],LS[B/S],"B") -> 0 | F21: =-SUMIFS(LS[Unit],LS[Investor ID],INVESTORS_LIST[[#This Row],[INVESTOR CODE]],LS[B/S],"S") -> 0 | G21: =IF(INVESTORS_LIST[[#This Row],[LS_TOTAL UNITS BUY]]=0,0,INVESTORS_LIST[[#This Row],[LS_TOTAL UNITS BUY]]-INVESTORS_LIST[[#This Row],[LS_TOTAL UNITS SOLD]]) -> 0 | H21: =IF(INVESTORS_LIST[[#This Row],[LS_TOTAL UNITS BUY]]=0,0,SUMIFS(LS[Amount],LS[Investor ID],INVESTORS_LIST[[#This Row],[INVESTOR CODE]],LS[B/S],"B")) -> 0 | I21: =IF(INVESTORS_LIST[[#This Row],[LS_TOTAL UNITS SOLD]]=0,0,SUMIFS(LS[Cost of Units Sold],LS[Investor ID],INVESTORS_LIST[[#This Row],[INVESTOR CODE]],LS[B/S],"S")) -> 0 | J21: =IF(INVESTORS_LIST[[#This Row],[LS_TOTAL CURRENT UNITS]]=0,0,INVESTORS_LIST[[#This Row],[LS_TOTAL CURRENT UNITS]]*INVESTORS_LIST[[#This Row],[LS_AVERAGE COST]]) -> 0 | K21: =IF(INVESTORS_LIST[[#This Row],[LS_TOTAL UNITS SOLD]]=0,0,SUMIFS(LS[Realized Gain],LS[Investor ID],INVESTORS_LIST[[#This Row],[INVESTOR CODE]],LS[B/S],"S")) -> 0 | L21: =SUMIFS(SIP[Unit],SIP[Investor ID],INVESTORS_LIST[[#This Row],[INVESTOR CODE]],SIP[B/S],"B") -> 0 | M21: =-SUMIFS(SIP[Unit],SIP[Investor ID],INVESTORS_LIST[[#This Row],[INVESTOR CODE]],SIP[B/S],"S") -> 0 | N21: =IF(INVESTORS_LIST[[#This Row],[SIP_TOTAL UNITS BUY]]=0,0,INVESTORS_LIST[[#This Row],[SIP_TOTAL UNITS BUY]]-INVESTORS_LIST[[#This Row],[SIP_TOTAL UNITS SOLD]]) -> 0 | O21: =IF(INVESTORS_LIST[[#This Row],[SIP_TOTAL UNITS BUY]]=0,0,SUMIFS(SIP[Amount],SIP[Investor ID],INVESTORS_LIST[[#This Row],[INVESTOR CODE]],SIP[B/S],"B")) -> 0 | P21: =IF(INVESTORS_LIST[[#This Row],[SIP_TOTAL UNITS SOLD]]=0,0,SUMIFS(SIP[Cost of Units Sold],SIP[Investor ID],INVESTORS_LIST[[#This Row],[INVESTOR CODE]],SIP[B/S],"S")) -> 0 | Q21: =IF(INVESTORS_LIST[[#This Row],[SIP_TOTAL CURRENT UNITS]]=0,0,INVESTORS_LIST[[#This Row],[SIP_TOTAL CURRENT UNITS]]*INVESTORS_LIST[[#This Row],[SIP_AVERAGE COST]]) -> 0 | R21: =IF(INVESTORS_LIST[[#This Row],[SIP_TOTAL UNITS SOLD]]=0,0,SUMIFS(SIP[Realized Gain],SIP[Investor ID],INVESTORS_LIST[[#This Row],[INVESTOR CODE]],SIP[B/S],"S")) -> 0 | S21: =INVESTORS_LIST[[#This Row],[LS_TOTAL UNITS BUY]]+INVESTORS_LIST[[#This Row],[SIP_TOTAL UNITS BUY]] -> 0 | T21: =INVESTORS_LIST[[#This Row],[LS_TOTAL UNITS SOLD]]+INVESTORS_LIST[[#This Row],[SIP_TOTAL UNITS SOLD]] -> 0 | V21: =SUMIFS(LS[BO UNIT TRANSFER],LS[Investor ID],INVESTORS_LIST[[#This Row],[INVESTOR CODE]],LS[B/S],"B") -> 0 | W21: =SUMIFS(SIP[BO UNIT TRANSFER],SIP[Investor ID],INVESTORS_LIST[[#This Row],[INVESTOR CODE]],SIP[B/S],"B") -> 0 | X21: =SUMIFS(LS[BO UNIT TRANSFER],LS[Investor ID],INVESTORS_LIST[[#This Row],[INVESTOR CODE]],LS[B/S],"S") -> 0 | Y21: =SUMIFS(SIP[BO UNIT TRANSFER],SIP[Investor ID],INVESTORS_LIST[[#This Row],[INVESTOR CODE]],SIP[B/S],"S") -> 0 | Z21: =SUM(INVESTORS_LIST[[#This Row],[BO OPENING BALANCE]:[BO SIP UNITS REPURCHASE]]) -> 0 | AA21: =INVESTORS_LIST[[#This Row],[TOTAL UNITS BUY]]-INVESTORS_LIST[[#This Row],[TOTAL UNITS SOLD]] -> 0 | AB21: =INVESTORS_LIST[[#This Row],[TOTAL CURRENT UNITS]]-INVESTORS_LIST[[#This Row],[BO UNITS HOLD]] -> 0 | AC21: =INDEX([3]!Table_1[BO ID],MATCH(INVESTORS_LIST[[#This Row],[INVESTOR CODE]],[3]!Table_1[INVESTOR CODE],0)) -> #REF! | AD21: =INDEX([3]!Table_1[Brokerage Name2],MATCH(INVESTORS_LIST[[#This Row],[INVESTOR CODE]],[3]!Table_1[INVESTOR CODE],0)) -> #REF! | AE21: =MID(INVESTORS_LIST[[#This Row],[BO ID]],4,5) -> #REF! | AF21: =MID(INVESTORS_LIST[[#This Row],[BO ID]],2,7) -> #REF! | AG21: =MID(INVESTORS_LIST[[#This Row],[BO ID]],9,7) -> #REF! | AH21: =RIGHT(INVESTORS_LIST[[#This Row],[BO ID]],1) -> #REF! | AI21: =INVESTORS_LIST[[#This Row],[LS_TOTAL COST VALUE OF CURRENT UNITS]]+INVESTORS_LIST[[#This Row],[SIP_TOTAL COST VALUE OF CURRENT UNITS]] -> 0 | AJ21: =IF(INVESTORS_LIST[[#This Row],[TOTAL CURRENT UNITS]]=0,0,INVESTORS_LIST[[#This Row],[LS_TOTAL CURRENT UNITS]]/INVESTORS_LIST[[#This Row],[TOTAL CURRENT UNITS]]) -> 0 | AK21: =IF(INVESTORS_LIST[[#This Row],[TOTAL CURRENT UNITS]]=0,0,INVESTORS_LIST[[#This Row],[SIP_TOTAL CURRENT UNITS]]/INVESTORS_LIST[[#This Row],[TOTAL CURRENT UNITS]]) -> 0 | AL21: {=IF(INVESTORS_LIST[[#This Row],[LS_TOTAL UNITS BUY]]>0,INDEX(LS[NAV at Cost (Average)],MATCH(CONCATENATE(COUNTIFS(LS[Investor ID],INVESTORS_LIST[[#This Row],[INVESTOR CODE]]),INVESTORS_LIST[[#This Row],[INVESTOR CODE]]),LS[Unique Code],0),),0)} -> 0 | AM21: {=IF(INVESTORS_LIST[[#This Row],[SIP_TOTAL UNITS BUY]]>0,INDEX(SIP[NAV at Cost (Average)],MATCH(CONCATENATE(COUNTIFS(SIP[Investor ID],INVESTORS_LIST[[#This Row],[INVESTOR CODE]]),INVESTORS_LIST[[#This Row],[INVESTOR CODE]]),SIP[Unique Code],0),),0)} -> 0 | AN21: =IF(INVESTORS_LIST[[#This Row],[TOTAL CURRENT UNITS]]=0,0,(INVESTORS_LIST[[#This Row],[LS_WEIGHT]]*INVESTORS_LIST[[#This Row],[LS_AVERAGE COST]])+(INVESTORS_LIST[[#This Row],[SIP_WEIGHT]]*INVESTORS_LIST[[#This Row],[SIP_AVERAGE COST]])) -> 0 | AO21: =NAV_MKT -> 14.224 | AP21: =IF(INVESTORS_LIST[[#This Row],[TOTAL CURRENT UNITS]]=0,0,INVESTORS_LIST[[#This Row],[TOTAL CURRENT UNITS]]*INVESTORS_LIST[[#This Row],[NAV]]) -> 0 | AQ21: =IF(INVESTORS_LIST[[#This Row],[LS_TOTAL CURRENT UNITS]]=0,0,INVESTORS_LIST[[#This Row],[LS_TOTAL CURRENT UNITS]]*INVESTORS_LIST[[#This Row],[NAV]]) -> 0 | AR21: =IF(INVESTORS_LIST[[#This Row],[SIP_TOTAL CURRENT UNITS]]=0,0,INVESTORS_LIST[[#This Row],[SIP_TOTAL CURRENT UNITS]]*INVESTORS_LIST[[#This Row],[NAV]]) -> 0 | AS21: =INVESTORS_LIST[[#This Row],[TOTAL CURRENT UNITS]] -> 0 | AT21: =IF(INVESTORS_LIST[[#This Row],[TOTAL SELLABLE UNITS]]=0,0,INVESTORS_LIST[[#This Row],[TOTAL SELLABLE UNITS]]*INVESTORS_LIST[[#This Row],[NAV]]) -> 0 | AU21: =INVESTORS_LIST[[#This Row],[LS_TOTAL REALIZED GAIN]]+INVESTORS_LIST[[#This Row],[SIP_TOTAL REALIZED GAIN]] -> 0 | AV21: =INVESTORS_LIST[[#This Row],[TOTAL MARKET VALUE]]-INVESTORS_LIST[[#This Row],[TOTAL COST VALUE OF CURRENT INVESTMENT]] -> 0 | AW21: =IFERROR(INVESTORS_LIST[[#This Row],[TOTAL CURRENT UNITS]]/SUM(INVESTORS_LIST[TOTAL CURRENT UNITS]),0) -> 0
A22: MINHAJ UDDIN | B22: A00022 | C22: Dear Mr. | D22: Individual | E22: =SUMIFS(LS[Unit],LS[Investor ID],INVESTORS_LIST[[#This Row],[INVESTOR CODE]],LS[B/S],"B") -> 85000 | F22: =-SUMIFS(LS[Unit],LS[Investor ID],INVESTORS_LIST[[#This Row],[INVESTOR CODE]],LS[B/S],"S") -> 85000 | G22: =IF(INVESTORS_LIST[[#This Row],[LS_TOTAL UNITS BUY]]=0,0,INVESTORS_LIST[[#This Row],[LS_TOTAL UNITS BUY]]-INVESTORS_LIST[[#This Row],[LS_TOTAL UNITS SOLD]]) -> 0 | H22: =IF(INVESTORS_LIST[[#This Row],[LS_TOTAL UNITS BUY]]=0,0,SUMIFS(LS[Amount],LS[Investor ID],INVESTORS_LIST[[#This Row],[INVESTOR CODE]],LS[B/S],"B")) -> 850000 | I22: =IF(INVESTORS_LIST[[#This Row],[LS_TOTAL UNITS SOLD]]=0,0,SUMIFS(LS[Cost of Units Sold],LS[Investor ID],INVESTORS_LIST[[#This Row],[INVESTOR CODE]],LS[B/S],"S")) -> 850000 | J22: =IF(INVESTORS_LIST[[#This Row],[LS_TOTAL CURRENT UNITS]]=0,0,INVESTORS_LIST[[#This Row],[LS_TOTAL CURRENT UNITS]]*INVESTORS_LIST[[#This Row],[LS_AVERAGE COST]]) -> 0 | K22: =IF(INVESTORS_LIST[[#This Row],[LS_TOTAL UNITS SOLD]]=0,0,SUMIFS(LS[Realized Gain],LS[Investor ID],INVESTORS_LIST[[#This Row],[INVESTOR CODE]],LS[B/S],"S")) -> 42330 | L22: =SUMIFS(SIP[Unit],SIP[Investor ID],INVESTORS_LIST[[#This Row],[INVESTOR CODE]],SIP[B/S],"B") -> 0 | M22: =-SUMIFS(SIP[Unit],SIP[Investor ID],INVESTORS_LIST[[#This Row],[INVESTOR CODE]],SIP[B/S],"S") -> 0 | N22: =IF(INVESTORS_LIST[[#This Row],[SIP_TOTAL UNITS BUY]]=0,0,INVESTORS_LIST[[#This Row],[SIP_TOTAL UNITS BUY]]-INVESTORS_LIST[[#This Row],[SIP_TOTAL UNITS SOLD]]) -> 0 | O22: =IF(INVESTORS_LIST[[#This Row],[SIP_TOTAL UNITS BUY]]=0,0,SUMIFS(SIP[Amount],SIP[Investor ID],INVESTORS_LIST[[#This Row],[INVESTOR CODE]],SIP[B/S],"B")) -> 0 | P22: =IF(INVESTORS_LIST[[#This Row],[SIP_TOTAL UNITS SOLD]]=0,0,SUMIFS(SIP[Cost of Units Sold],SIP[Investor ID],INVESTORS_LIST[[#This Row],[INVESTOR CODE]],SIP[B/S],"S")) -> 0 | Q22: =IF(INVESTORS_LIST[[#This Row],[SIP_TOTAL CURRENT UNITS]]=0,0,INVESTORS_LIST[[#This Row],[SIP_TOTAL CURRENT UNITS]]*INVESTORS_LIST[[#This Row],[SIP_AVERAGE COST]]) -> 0 | R22: =IF(INVESTORS_LIST[[#This Row],[SIP_TOTAL UNITS SOLD]]=0,0,SUMIFS(SIP[Realized Gain],SIP[Investor ID],INVESTORS_LIST[[#This Row],[INVESTOR CODE]],SIP[B/S],"S")) -> 0 | S22: =INVESTORS_LIST[[#This Row],[LS_TOTAL UNITS BUY]]+INVESTORS_LIST[[#This Row],[SIP_TOTAL UNITS BUY]] -> 85000 | T22: =INVESTORS_LIST[[#This Row],[LS_TOTAL UNITS SOLD]]+INVESTORS_LIST[[#This Row],[SIP_TOTAL UNITS SOLD]] -> 85000 | V22: =SUMIFS(LS[BO UNIT TRANSFER],LS[Investor ID],INVESTORS_LIST[[#This Row],[INVESTOR CODE]],LS[B/S],"B") -> 0 | W22: =SUMIFS(SIP[BO UNIT TRANSFER],SIP[Investor ID],INVESTORS_LIST[[#This Row],[INVESTOR CODE]],SIP[B/S],"B") -> 0 | X22: =SUMIFS(LS[BO UNIT TRANSFER],LS[Investor ID],INVESTORS_LIST[[#This Row],[INVESTOR CODE]],LS[B/S],"S") -> 0 | Y22: =SUMIFS(SIP[BO UNIT TRANSFER],SIP[Investor ID],INVESTORS_LIST[[#This Row],[INVESTOR CODE]],SIP[B/S],"S") -> 0 | Z22: =SUM(INVESTORS_LIST[[#This Row],[BO OPENING BALANCE]:[BO SIP UNITS REPURCHASE]]) -> 0 | AA22: =INVESTORS_LIST[[#This Row],[TOTAL UNITS BUY]]-INVESTORS_LIST[[#This Row],[TOTAL UNITS SOLD]] -> 0 | AB22: =INVESTORS_LIST[[#This Row],[TOTAL CURRENT UNITS]]-INVESTORS_LIST[[#This Row],[BO UNITS HOLD]] -> 0 | AC22: =INDEX([3]!Table_1[BO ID],MATCH(INVESTORS_LIST[[#This Row],[INVESTOR CODE]],[3]!Table_1[INVESTOR CODE],0)) -> #REF! | AD22: =INDEX([3]!Table_1[Brokerage Name2],MATCH(INVESTORS_LIST[[#This Row],[INVESTOR CODE]],[3]!Table_1[INVESTOR CODE],0)) -> #REF! | AE22: =MID(INVESTORS_LIST[[#This Row],[BO ID]],4,5) -> #REF! | AF22: =MID(INVESTORS_LIST[[#This Row],[BO ID]],2,7) -> #REF! | AG22: =MID(INVESTORS_LIST[[#This Row],[BO ID]],9,7) -> #REF! | AH22: =RIGHT(INVESTORS_LIST[[#This Row],[BO ID]],1) -> #REF! | AI22: =INVESTORS_LIST[[#This Row],[LS_TOTAL COST VALUE OF CURRENT UNITS]]+INVESTORS_LIST[[#This Row],[SIP_TOTAL COST VALUE OF CURRENT UNITS]] -> 0 | AJ22: =IF(INVESTORS_LIST[[#This Row],[TOTAL CURRENT UNITS]]=0,0,INVESTORS_LIST[[#This Row],[LS_TOTAL CURRENT UNITS]]/INVESTORS_LIST[[#This Row],[TOTAL CURRENT UNITS]]) -> 0 | AK22: =IF(INVESTORS_LIST[[#This Row],[TOTAL CURRENT UNITS]]=0,0,INVESTORS_LIST[[#This Row],[SIP_TOTAL CURRENT UNITS]]/INVESTORS_LIST[[#This Row],[TOTAL CURRENT UNITS]]) -> 0 | AL22: {=IF(INVESTORS_LIST[[#This Row],[LS_TOTAL UNITS BUY]]>0,INDEX(LS[NAV at Cost (Average)],MATCH(CONCATENATE(COUNTIFS(LS[Investor ID],INVESTORS_LIST[[#This Row],[INVESTOR CODE]]),INVESTORS_LIST[[#This Row],[INVESTOR CODE]]),LS[Unique Code],0),),0)} -> 0 | AM22: {=IF(INVESTORS_LIST[[#This Row],[SIP_TOTAL UNITS BUY]]>0,INDEX(SIP[NAV at Cost (Average)],MATCH(CONCATENATE(COUNTIFS(SIP[Investor ID],INVESTORS_LIST[[#This Row],[INVESTOR CODE]]),INVESTORS_LIST[[#This Row],[INVESTOR CODE]]),SIP[Unique Code],0),),0)} -> 0 | AN22: =IF(INVESTORS_LIST[[#This Row],[TOTAL CURRENT UNITS]]=0,0,(INVESTORS_LIST[[#This Row],[LS_WEIGHT]]*INVESTORS_LIST[[#This Row],[LS_AVERAGE COST]])+(INVESTORS_LIST[[#This Row],[SIP_WEIGHT]]*INVESTORS_LIST[[#This Row],[SIP_AVERAGE COST]])) -> 0 | AO22: =NAV_MKT -> 14.224 | AP22: =IF(INVESTORS_LIST[[#This Row],[TOTAL CURRENT UNITS]]=0,0,INVESTORS_LIST[[#This Row],[TOTAL CURRENT UNITS]]*INVESTORS_LIST[[#This Row],[NAV]]) -> 0 | AQ22: =IF(INVESTORS_LIST[[#This Row],[LS_TOTAL CURRENT UNITS]]=0,0,INVESTORS_LIST[[#This Row],[LS_TOTAL CURRENT UNITS]]*INVESTORS_LIST[[#This Row],[NAV]]) -> 0 | AR22: =IF(INVESTORS_LIST[[#This Row],[SIP_TOTAL CURRENT UNITS]]=0,0,INVESTORS_LIST[[#This Row],[SIP_TOTAL CURRENT UNITS]]*INVESTORS_LIST[[#This Row],[NAV]]) -> 0 | AS22: =INVESTORS_LIST[[#This Row],[TOTAL CURRENT UNITS]] -> 0 | AT22: =IF(INVESTORS_LIST[[#This Row],[TOTAL SELLABLE UNITS]]=0,0,INVESTORS_LIST[[#This Row],[TOTAL SELLABLE UNITS]]*INVESTORS_LIST[[#This Row],[NAV]]) -> 0 | AU22: =INVESTORS_LIST[[#This Row],[LS_TOTAL REALIZED GAIN]]+INVESTORS_LIST[[#This Row],[SIP_TOTAL REALIZED GAIN]] -> 42330 | AV22: =INVESTORS_LIST[[#This Row],[TOTAL MARKET VALUE]]-INVESTORS_LIST[[#This Row],[TOTAL COST VALUE OF CURRENT INVESTMENT]] -> 0 | AW22: =IFERROR(INVESTORS_LIST[[#This Row],[TOTAL CURRENT UNITS]]/SUM(INVESTORS_LIST[TOTAL CURRENT UNITS]),0) -> 0
A23: CRAB EMPLOYEES PROVIDENT FUND | B23: A00023 | C23: Dear | D23: Providend Fund | E23: =SUMIFS(LS[Unit],LS[Investor ID],INVESTORS_LIST[[#This Row],[INVESTOR CODE]],LS[B/S],"B") -> 0 | F23: =-SUMIFS(LS[Unit],LS[Investor ID],INVESTORS_LIST[[#This Row],[INVESTOR CODE]],LS[B/S],"S") -> 0 | G23: =IF(INVESTORS_LIST[[#This Row],[LS_TOTAL UNITS BUY]]=0,0,INVESTORS_LIST[[#This Row],[LS_TOTAL UNITS BUY]]-INVESTORS_LIST[[#This Row],[LS_TOTAL UNITS SOLD]]) -> 0 | H23: =IF(INVESTORS_LIST[[#This Row],[LS_TOTAL UNITS BUY]]=0,0,SUMIFS(LS[Amount],LS[Investor ID],INVESTORS_LIST[[#This Row],[INVESTOR CODE]],LS[B/S],"B")) -> 0 | I23: =IF(INVESTORS_LIST[[#This Row],[LS_TOTAL UNITS SOLD]]=0,0,SUMIFS(LS[Cost of Units Sold],LS[Investor ID],INVESTORS_LIST[[#This Row],[INVESTOR CODE]],LS[B/S],"S")) -> 0 | J23: =IF(INVESTORS_LIST[[#This Row],[LS_TOTAL CURRENT UNITS]]=0,0,INVESTORS_LIST[[#This Row],[LS_TOTAL CURRENT UNITS]]*INVESTORS_LIST[[#This Row],[LS_AVERAGE COST]]) -> 0 | K23: =IF(INVESTORS_LIST[[#This Row],[LS_TOTAL UNITS SOLD]]=0,0,SUMIFS(LS[Realized Gain],LS[Investor ID],INVESTORS_LIST[[#This Row],[INVESTOR CODE]],LS[B/S],"S")) -> 0 | L23: =SUMIFS(SIP[Unit],SIP[Investor ID],INVESTORS_LIST[[#This Row],[INVESTOR CODE]],SIP[B/S],"B") -> 0 | M23: =-SUMIFS(SIP[Unit],SIP[Investor ID],INVESTORS_LIST[[#This Row],[INVESTOR CODE]],SIP[B/S],"S") -> 0 | N23: =IF(INVESTORS_LIST[[#This Row],[SIP_TOTAL UNITS BUY]]=0,0,INVESTORS_LIST[[#This Row],[SIP_TOTAL UNITS BUY]]-INVESTORS_LIST[[#This Row],[SIP_TOTAL UNITS SOLD]]) -> 0 | O23: =IF(INVESTORS_LIST[[#This Row],[SIP_TOTAL UNITS BUY]]=0,0,SUMIFS(SIP[Amount],SIP[Investor ID],INVESTORS_LIST[[#This Row],[INVESTOR CODE]],SIP[B/S],"B")) -> 0 | P23: =IF(INVESTORS_LIST[[#This Row],[SIP_TOTAL UNITS SOLD]]=0,0,SUMIFS(SIP[Cost of Units Sold],SIP[Investor ID],INVESTORS_LIST[[#This Row],[INVESTOR CODE]],SIP[B/S],"S")) -> 0 | Q23: =IF(INVESTORS_LIST[[#This Row],[SIP_TOTAL CURRENT UNITS]]=0,0,INVESTORS_LIST[[#This Row],[SIP_TOTAL CURRENT UNITS]]*INVESTORS_LIST[[#This Row],[SIP_AVERAGE COST]]) -> 0 | R23: =IF(INVESTORS_LIST[[#This Row],[SIP_TOTAL UNITS SOLD]]=0,0,SUMIFS(SIP[Realized Gain],SIP[Investor ID],INVESTORS_LIST[[#This Row],[INVESTOR CODE]],SIP[B/S],"S")) -> 0 | S23: =INVESTORS_LIST[[#This Row],[LS_TOTAL UNITS BUY]]+INVESTORS_LIST[[#This Row],[SIP_TOTAL UNITS BUY]] -> 0 | T23: =INVESTORS_LIST[[#This Row],[LS_TOTAL UNITS SOLD]]+INVESTORS_LIST[[#This Row],[SIP_TOTAL UNITS SOLD]] -> 0 | V23: =SUMIFS(LS[BO UNIT TRANSFER],LS[Investor ID],INVESTORS_LIST[[#This Row],[INVESTOR CODE]],LS[B/S],"B") -> 0 | W23: =SUMIFS(SIP[BO UNIT TRANSFER],SIP[Investor ID],INVESTORS_LIST[[#This Row],[INVESTOR CODE]],SIP[B/S],"B") -> 0 | X23: =SUMIFS(LS[BO UNIT TRANSFER],LS[Investor ID],INVESTORS_LIST[[#This Row],[INVESTOR CODE]],LS[B/S],"S") -> 0 | Y23: =SUMIFS(SIP[BO UNIT TRANSFER],SIP[Investor ID],INVESTORS_LIST[[#This Row],[INVESTOR CODE]],SIP[B/S],"S") -> 0 | Z23: =SUM(INVESTORS_LIST[[#This Row],[BO OPENING BALANCE]:[BO SIP UNITS REPURCHASE]]) -> 0 | AA23: =INVESTORS_LIST[[#This Row],[TOTAL UNITS BUY]]-INVESTORS_LIST[[#This Row],[TOTAL UNITS SOLD]] -> 0 | AB23: =INVESTORS_LIST[[#This Row],[TOTAL CURRENT UNITS]]-INVESTORS_LIST[[#This Row],[BO UNITS HOLD]] -> 0 | AC23: =INDEX([3]!Table_1[BO ID],MATCH(INVESTORS_LIST[[#This Row],[INVESTOR CODE]],[3]!Table_1[INVESTOR CODE],0)) -> #REF! | AD23: =INDEX([3]!Table_1[Brokerage Name2],MATCH(INVESTORS_LIST[[#This Row],[INVESTOR CODE]],[3]!Table_1[INVESTOR CODE],0)) -> #REF! | AE23: =MID(INVESTORS_LIST[[#This Row],[BO ID]],4,5) -> #REF! | AF23: =MID(INVESTORS_LIST[[#This Row],[BO ID]],2,7) -> #REF! | AG23: =MID(INVESTORS_LIST[[#This Row],[BO ID]],9,7) -> #REF! | AH23: =RIGHT(INVESTORS_LIST[[#This Row],[BO ID]],1) -> #REF! | AI23: =INVESTORS_LIST[[#This Row],[LS_TOTAL COST VALUE OF CURRENT UNITS]]+INVESTORS_LIST[[#This Row],[SIP_TOTAL COST VALUE OF CURRENT UNITS]] -> 0 | AJ23: =IF(INVESTORS_LIST[[#This Row],[TOTAL CURRENT UNITS]]=0,0,INVESTORS_LIST[[#This Row],[LS_TOTAL CURRENT UNITS]]/INVESTORS_LIST[[#This Row],[TOTAL CURRENT UNITS]]) -> 0 | AK23: =IF(INVESTORS_LIST[[#This Row],[TOTAL CURRENT UNITS]]=0,0,INVESTORS_LIST[[#This Row],[SIP_TOTAL CURRENT UNITS]]/INVESTORS_LIST[[#This Row],[TOTAL CURRENT UNITS]]) -> 0 | AL23: {=IF(INVESTORS_LIST[[#This Row],[LS_TOTAL UNITS BUY]]>0,INDEX(LS[NAV at Cost (Average)],MATCH(CONCATENATE(COUNTIFS(LS[Investor ID],INVESTORS_LIST[[#This Row],[INVESTOR CODE]]),INVESTORS_LIST[[#This Row],[INVESTOR CODE]]),LS[Unique Code],0),),0)} -> 0 | AM23: {=IF(INVESTORS_LIST[[#This Row],[SIP_TOTAL UNITS BUY]]>0,INDEX(SIP[NAV at Cost (Average)],MATCH(CONCATENATE(COUNTIFS(SIP[Investor ID],INVESTORS_LIST[[#This Row],[INVESTOR CODE]]),INVESTORS_LIST[[#This Row],[INVESTOR CODE]]),SIP[Unique Code],0),),0)} -> 0 | AN23: =IF(INVESTORS_LIST[[#This Row],[TOTAL CURRENT UNITS]]=0,0,(INVESTORS_LIST[[#This Row],[LS_WEIGHT]]*INVESTORS_LIST[[#This Row],[LS_AVERAGE COST]])+(INVESTORS_LIST[[#This Row],[SIP_WEIGHT]]*INVESTORS_LIST[[#This Row],[SIP_AVERAGE COST]])) -> 0 | AO23: =NAV_MKT -> 14.224 | AP23: =IF(INVESTORS_LIST[[#This Row],[TOTAL CURRENT UNITS]]=0,0,INVESTORS_LIST[[#This Row],[TOTAL CURRENT UNITS]]*INVESTORS_LIST[[#This Row],[NAV]]) -> 0 | AQ23: =IF(INVESTORS_LIST[[#This Row],[LS_TOTAL CURRENT UNITS]]=0,0,INVESTORS_LIST[[#This Row],[LS_TOTAL CURRENT UNITS]]*INVESTORS_LIST[[#This Row],[NAV]]) -> 0 | AR23: =IF(INVESTORS_LIST[[#This Row],[SIP_TOTAL CURRENT UNITS]]=0,0,INVESTORS_LIST[[#This Row],[SIP_TOTAL CURRENT UNITS]]*INVESTORS_LIST[[#This Row],[NAV]]) -> 0 | AS23: =INVESTORS_LIST[[#This Row],[TOTAL CURRENT UNITS]] -> 0 | AT23: =IF(INVESTORS_LIST[[#This Row],[TOTAL SELLABLE UNITS]]=0,0,INVESTORS_LIST[[#This Row],[TOTAL SELLABLE UNITS]]*INVESTORS_LIST[[#This Row],[NAV]]) -> 0 | AU23: =INVESTORS_LIST[[#This Row],[LS_TOTAL REALIZED GAIN]]+INVESTORS_LIST[[#This Row],[SIP_TOTAL REALIZED GAIN]] -> 0 | AV23: =INVESTORS_LIST[[#This Row],[TOTAL MARKET VALUE]]-INVESTORS_LIST[[#This Row],[TOTAL COST VALUE OF CURRENT INVESTMENT]] -> 0 | AW23: =IFERROR(INVESTORS_LIST[[#This Row],[TOTAL CURRENT UNITS]]/SUM(INVESTORS_LIST[TOTAL CURRENT UNITS]),0) -> 0
A24: CRAB EMPLOYEES GRATUITY FUND | B24: A00024 | C24: Dear | D24: Gratuity Fund | E24: =SUMIFS(LS[Unit],LS[Investor ID],INVESTORS_LIST[[#This Row],[INVESTOR CODE]],LS[B/S],"B") -> 0 | F24: =-SUMIFS(LS[Unit],LS[Investor ID],INVESTORS_LIST[[#This Row],[INVESTOR CODE]],LS[B/S],"S") -> 0 | G24: =IF(INVESTORS_LIST[[#This Row],[LS_TOTAL UNITS BUY]]=0,0,INVESTORS_LIST[[#This Row],[LS_TOTAL UNITS BUY]]-INVESTORS_LIST[[#This Row],[LS_TOTAL UNITS SOLD]]) -> 0 | H24: =IF(INVESTORS_LIST[[#This Row],[LS_TOTAL UNITS BUY]]=0,0,SUMIFS(LS[Amount],LS[Investor ID],INVESTORS_LIST[[#This Row],[INVESTOR CODE]],LS[B/S],"B")) -> 0 | I24: =IF(INVESTORS_LIST[[#This Row],[LS_TOTAL UNITS SOLD]]=0,0,SUMIFS(LS[Cost of Units Sold],LS[Investor ID],INVESTORS_LIST[[#This Row],[INVESTOR CODE]],LS[B/S],"S")) -> 0 | J24: =IF(INVESTORS_LIST[[#This Row],[LS_TOTAL CURRENT UNITS]]=0,0,INVESTORS_LIST[[#This Row],[LS_TOTAL CURRENT UNITS]]*INVESTORS_LIST[[#This Row],[LS_AVERAGE COST]]) -> 0 | K24: =IF(INVESTORS_LIST[[#This Row],[LS_TOTAL UNITS SOLD]]=0,0,SUMIFS(LS[Realized Gain],LS[Investor ID],INVESTORS_LIST[[#This Row],[INVESTOR CODE]],LS[B/S],"S")) -> 0 | L24: =SUMIFS(SIP[Unit],SIP[Investor ID],INVESTORS_LIST[[#This Row],[INVESTOR CODE]],SIP[B/S],"B") -> 0 | M24: =-SUMIFS(SIP[Unit],SIP[Investor ID],INVESTORS_LIST[[#This Row],[INVESTOR CODE]],SIP[B/S],"S") -> 0 | N24: =IF(INVESTORS_LIST[[#This Row],[SIP_TOTAL UNITS BUY]]=0,0,INVESTORS_LIST[[#This Row],[SIP_TOTAL UNITS BUY]]-INVESTORS_LIST[[#This Row],[SIP_TOTAL UNITS SOLD]]) -> 0 | O24: =IF(INVESTORS_LIST[[#This Row],[SIP_TOTAL UNITS BUY]]=0,0,SUMIFS(SIP[Amount],SIP[Investor ID],INVESTORS_LIST[[#This Row],[INVESTOR CODE]],SIP[B/S],"B")) -> 0 | P24: =IF(INVESTORS_LIST[[#This Row],[SIP_TOTAL UNITS SOLD]]=0,0,SUMIFS(SIP[Cost of Units Sold],SIP[Investor ID],INVESTORS_LIST[[#This Row],[INVESTOR CODE]],SIP[B/S],"S")) -> 0 | Q24: =IF(INVESTORS_LIST[[#This Row],[SIP_TOTAL CURRENT UNITS]]=0,0,INVESTORS_LIST[[#This Row],[SIP_TOTAL CURRENT UNITS]]*INVESTORS_LIST[[#This Row],[SIP_AVERAGE COST]]) -> 0 | R24: =IF(INVESTORS_LIST[[#This Row],[SIP_TOTAL UNITS SOLD]]=0,0,SUMIFS(SIP[Realized Gain],SIP[Investor ID],INVESTORS_LIST[[#This Row],[INVESTOR CODE]],SIP[B/S],"S")) -> 0 | S24: =INVESTORS_LIST[[#This Row],[LS_TOTAL UNITS BUY]]+INVESTORS_LIST[[#This Row],[SIP_TOTAL UNITS BUY]] -> 0 | T24: =INVESTORS_LIST[[#This Row],[LS_TOTAL UNITS SOLD]]+INVESTORS_LIST[[#This Row],[SIP_TOTAL UNITS SOLD]] -> 0 | V24: =SUMIFS(LS[BO UNIT TRANSFER],LS[Investor ID],INVESTORS_LIST[[#This Row],[INVESTOR CODE]],LS[B/S],"B") -> 0 | W24: =SUMIFS(SIP[BO UNIT TRANSFER],SIP[Investor ID],INVESTORS_LIST[[#This Row],[INVESTOR CODE]],SIP[B/S],"B") -> 0 | X24: =SUMIFS(LS[BO UNIT TRANSFER],LS[Investor ID],INVESTORS_LIST[[#This Row],[INVESTOR CODE]],LS[B/S],"S") -> 0 | Y24: =SUMIFS(SIP[BO UNIT TRANSFER],SIP[Investor ID],INVESTORS_LIST[[#This Row],[INVESTOR CODE]],SIP[B/S],"S") -> 0 | Z24: =SUM(INVESTORS_LIST[[#This Row],[BO OPENING BALANCE]:[BO SIP UNITS REPURCHASE]]) -> 0 | AA24: =INVESTORS_LIST[[#This Row],[TOTAL UNITS BUY]]-INVESTORS_LIST[[#This Row],[TOTAL UNITS SOLD]] -> 0 | AB24: =INVESTORS_LIST[[#This Row],[TOTAL CURRENT UNITS]]-INVESTORS_LIST[[#This Row],[BO UNITS HOLD]] -> 0 | AC24: =INDEX([3]!Table_1[BO ID],MATCH(INVESTORS_LIST[[#This Row],[INVESTOR CODE]],[3]!Table_1[INVESTOR CODE],0)) -> #REF! | AD24: =INDEX([3]!Table_1[Brokerage Name2],MATCH(INVESTORS_LIST[[#This Row],[INVESTOR CODE]],[3]!Table_1[INVESTOR CODE],0)) -> #REF! | AE24: =MID(INVESTORS_LIST[[#This Row],[BO ID]],4,5) -> #REF! | AF24: =MID(INVESTORS_LIST[[#This Row],[BO ID]],2,7) -> #REF! | AG24: =MID(INVESTORS_LIST[[#This Row],[BO ID]],9,7) -> #REF! | AH24: =RIGHT(INVESTORS_LIST[[#This Row],[BO ID]],1) -> #REF! | AI24: =INVESTORS_LIST[[#This Row],[LS_TOTAL COST VALUE OF CURRENT UNITS]]+INVESTORS_LIST[[#This Row],[SIP_TOTAL COST VALUE OF CURRENT UNITS]] -> 0 | AJ24: =IF(INVESTORS_LIST[[#This Row],[TOTAL CURRENT UNITS]]=0,0,INVESTORS_LIST[[#This Row],[LS_TOTAL CURRENT UNITS]]/INVESTORS_LIST[[#This Row],[TOTAL CURRENT UNITS]]) -> 0 | AK24: =IF(INVESTORS_LIST[[#This Row],[TOTAL CURRENT UNITS]]=0,0,INVESTORS_LIST[[#This Row],[SIP_TOTAL CURRENT UNITS]]/INVESTORS_LIST[[#This Row],[TOTAL CURRENT UNITS]]) -> 0 | AL24: {=IF(INVESTORS_LIST[[#This Row],[LS_TOTAL UNITS BUY]]>0,INDEX(LS[NAV at Cost (Average)],MATCH(CONCATENATE(COUNTIFS(LS[Investor ID],INVESTORS_LIST[[#This Row],[INVESTOR CODE]]),INVESTORS_LIST[[#This Row],[INVESTOR CODE]]),LS[Unique Code],0),),0)} -> 0 | AM24: {=IF(INVESTORS_LIST[[#This Row],[SIP_TOTAL UNITS BUY]]>0,INDEX(SIP[NAV at Cost (Average)],MATCH(CONCATENATE(COUNTIFS(SIP[Investor ID],INVESTORS_LIST[[#This Row],[INVESTOR CODE]]),INVESTORS_LIST[[#This Row],[INVESTOR CODE]]),SIP[Unique Code],0),),0)} -> 0 | AN24: =IF(INVESTORS_LIST[[#This Row],[TOTAL CURRENT UNITS]]=0,0,(INVESTORS_LIST[[#This Row],[LS_WEIGHT]]*INVESTORS_LIST[[#This Row],[LS_AVERAGE COST]])+(INVESTORS_LIST[[#This Row],[SIP_WEIGHT]]*INVESTORS_LIST[[#This Row],[SIP_AVERAGE COST]])) -> 0 | AO24: =NAV_MKT -> 14.224 | AP24: =IF(INVESTORS_LIST[[#This Row],[TOTAL CURRENT UNITS]]=0,0,INVESTORS_LIST[[#This Row],[TOTAL CURRENT UNITS]]*INVESTORS_LIST[[#This Row],[NAV]]) -> 0 | AQ24: =IF(INVESTORS_LIST[[#This Row],[LS_TOTAL CURRENT UNITS]]=0,0,INVESTORS_LIST[[#This Row],[LS_TOTAL CURRENT UNITS]]*INVESTORS_LIST[[#This Row],[NAV]]) -> 0 | AR24: =IF(INVESTORS_LIST[[#This Row],[SIP_TOTAL CURRENT UNITS]]=0,0,INVESTORS_LIST[[#This Row],[SIP_TOTAL CURRENT UNITS]]*INVESTORS_LIST[[#This Row],[NAV]]) -> 0 | AS24: =INVESTORS_LIST[[#This Row],[TOTAL CURRENT UNITS]] -> 0 | AT24: =IF(INVESTORS_LIST[[#This Row],[TOTAL SELLABLE UNITS]]=0,0,INVESTORS_LIST[[#This Row],[TOTAL SELLABLE UNITS]]*INVESTORS_LIST[[#This Row],[NAV]]) -> 0 | AU24: =INVESTORS_LIST[[#This Row],[LS_TOTAL REALIZED GAIN]]+INVESTORS_LIST[[#This Row],[SIP_TOTAL REALIZED GAIN]] -> 0 | AV24: =INVESTORS_LIST[[#This Row],[TOTAL MARKET VALUE]]-INVESTORS_LIST[[#This Row],[TOTAL COST VALUE OF CURRENT INVESTMENT]] -> 0 | AW24: =IFERROR(INVESTORS_LIST[[#This Row],[TOTAL CURRENT UNITS]]/SUM(INVESTORS_LIST[TOTAL CURRENT UNITS]),0) -> 0
A25: MD. BADI-UZ-ZAMAN | B25: A00025 | C25: Dear Mr. | D25: Individual | E25: =SUMIFS(LS[Unit],LS[Investor ID],INVESTORS_LIST[[#This Row],[INVESTOR CODE]],LS[B/S],"B") -> 0 | F25: =-SUMIFS(LS[Unit],LS[Investor ID],INVESTORS_LIST[[#This Row],[INVESTOR CODE]],LS[B/S],"S") -> 0 | G25: =IF(INVESTORS_LIST[[#This Row],[LS_TOTAL UNITS BUY]]=0,0,INVESTORS_LIST[[#This Row],[LS_TOTAL UNITS BUY]]-INVESTORS_LIST[[#This Row],[LS_TOTAL UNITS SOLD]]) -> 0 | H25: =IF(INVESTORS_LIST[[#This Row],[LS_TOTAL UNITS BUY]]=0,0,SUMIFS(LS[Amount],LS[Investor ID],INVESTORS_LIST[[#This Row],[INVESTOR CODE]],LS[B/S],"B")) -> 0 | I25: =IF(INVESTORS_LIST[[#This Row],[LS_TOTAL UNITS SOLD]]=0,0,SUMIFS(LS[Cost of Units Sold],LS[Investor ID],INVESTORS_LIST[[#This Row],[INVESTOR CODE]],LS[B/S],"S")) -> 0 | J25: =IF(INVESTORS_LIST[[#This Row],[LS_TOTAL CURRENT UNITS]]=0,0,INVESTORS_LIST[[#This Row],[LS_TOTAL CURRENT UNITS]]*INVESTORS_LIST[[#This Row],[LS_AVERAGE COST]]) -> 0 | K25: =IF(INVESTORS_LIST[[#This Row],[LS_TOTAL UNITS SOLD]]=0,0,SUMIFS(LS[Realized Gain],LS[Investor ID],INVESTORS_LIST[[#This Row],[INVESTOR CODE]],LS[B/S],"S")) -> 0 | L25: =SUMIFS(SIP[Unit],SIP[Investor ID],INVESTORS_LIST[[#This Row],[INVESTOR CODE]],SIP[B/S],"B") -> 0 | M25: =-SUMIFS(SIP[Unit],SIP[Investor ID],INVESTORS_LIST[[#This Row],[INVESTOR CODE]],SIP[B/S],"S") -> 0 | N25: =IF(INVESTORS_LIST[[#This Row],[SIP_TOTAL UNITS BUY]]=0,0,INVESTORS_LIST[[#This Row],[SIP_TOTAL UNITS BUY]]-INVESTORS_LIST[[#This Row],[SIP_TOTAL UNITS SOLD]]) -> 0 | O25: =IF(INVESTORS_LIST[[#This Row],[SIP_TOTAL UNITS BUY]]=0,0,SUMIFS(SIP[Amount],SIP[Investor ID],INVESTORS_LIST[[#This Row],[INVESTOR CODE]],SIP[B/S],"B")) -> 0 | P25: =IF(INVESTORS_LIST[[#This Row],[SIP_TOTAL UNITS SOLD]]=0,0,SUMIFS(SIP[Cost of Units Sold],SIP[Investor ID],INVESTORS_LIST[[#This Row],[INVESTOR CODE]],SIP[B/S],"S")) -> 0 | Q25: =IF(INVESTORS_LIST[[#This Row],[SIP_TOTAL CURRENT UNITS]]=0,0,INVESTORS_LIST[[#This Row],[SIP_TOTAL CURRENT UNITS]]*INVESTORS_LIST[[#This Row],[SIP_AVERAGE COST]]) -> 0 | R25: =IF(INVESTORS_LIST[[#This Row],[SIP_TOTAL UNITS SOLD]]=0,0,SUMIFS(SIP[Realized Gain],SIP[Investor ID],INVESTORS_LIST[[#This Row],[INVESTOR CODE]],SIP[B/S],"S")) -> 0 | S25: =INVESTORS_LIST[[#This Row],[LS_TOTAL UNITS BUY]]+INVESTORS_LIST[[#This Row],[SIP_TOTAL UNITS BUY]] -> 0 | T25: =INVESTORS_LIST[[#This Row],[LS_TOTAL UNITS SOLD]]+INVESTORS_LIST[[#This Row],[SIP_TOTAL UNITS SOLD]] -> 0 | V25: =SUMIFS(LS[BO UNIT TRANSFER],LS[Investor ID],INVESTORS_LIST[[#This Row],[INVESTOR CODE]],LS[B/S],"B") -> 0 | W25: =SUMIFS(SIP[BO UNIT TRANSFER],SIP[Investor ID],INVESTORS_LIST[[#This Row],[INVESTOR CODE]],SIP[B/S],"B") -> 0 | X25: =SUMIFS(LS[BO UNIT TRANSFER],LS[Investor ID],INVESTORS_LIST[[#This Row],[INVESTOR CODE]],LS[B/S],"S") -> 0 | Y25: =SUMIFS(SIP[BO UNIT TRANSFER],SIP[Investor ID],INVESTORS_LIST[[#This Row],[INVESTOR CODE]],SIP[B/S],"S") -> 0 | Z25: =SUM(INVESTORS_LIST[[#This Row],[BO OPENING BALANCE]:[BO SIP UNITS REPURCHASE]]) -> 0 | AA25: =INVESTORS_LIST[[#This Row],[TOTAL UNITS BUY]]-INVESTORS_LIST[[#This Row],[TOTAL UNITS SOLD]] -> 0 | AB25: =INVESTORS_LIST[[#This Row],[TOTAL CURRENT UNITS]]-INVESTORS_LIST[[#This Row],[BO UNITS HOLD]] -> 0 | AC25: =INDEX([3]!Table_1[BO ID],MATCH(INVESTORS_LIST[[#This Row],[INVESTOR CODE]],[3]!Table_1[INVESTOR CODE],0)) -> #REF! | AD25: =INDEX([3]!Table_1[Brokerage Name2],MATCH(INVESTORS_LIST[[#This Row],[INVESTOR CODE]],[3]!Table_1[INVESTOR CODE],0)) -> #REF! | AE25: =MID(INVESTORS_LIST[[#This Row],[BO ID]],4,5) -> #REF! | AF25: =MID(INVESTORS_LIST[[#This Row],[BO ID]],2,7) -> #REF! | AG25: =MID(INVESTORS_LIST[[#This Row],[BO ID]],9,7) -> #REF! | AH25: =RIGHT(INVESTORS_LIST[[#This Row],[BO ID]],1) -> #REF! | AI25: =INVESTORS_LIST[[#This Row],[LS_TOTAL COST VALUE OF CURRENT UNITS]]+INVESTORS_LIST[[#This Row],[SIP_TOTAL COST VALUE OF CURRENT UNITS]] -> 0 | AJ25: =IF(INVESTORS_LIST[[#This Row],[TOTAL CURRENT UNITS]]=0,0,INVESTORS_LIST[[#This Row],[LS_TOTAL CURRENT UNITS]]/INVESTORS_LIST[[#This Row],[TOTAL CURRENT UNITS]]) -> 0 | AK25: =IF(INVESTORS_LIST[[#This Row],[TOTAL CURRENT UNITS]]=0,0,INVESTORS_LIST[[#This Row],[SIP_TOTAL CURRENT UNITS]]/INVESTORS_LIST[[#This Row],[TOTAL CURRENT UNITS]]) -> 0 | AL25: {=IF(INVESTORS_LIST[[#This Row],[LS_TOTAL UNITS BUY]]>0,INDEX(LS[NAV at Cost (Average)],MATCH(CONCATENATE(COUNTIFS(LS[Investor ID],INVESTORS_LIST[[#This Row],[INVESTOR CODE]]),INVESTORS_LIST[[#This Row],[INVESTOR CODE]]),LS[Unique Code],0),),0)} -> 0 | AM25: {=IF(INVESTORS_LIST[[#This Row],[SIP_TOTAL UNITS BUY]]>0,INDEX(SIP[NAV at Cost (Average)],MATCH(CONCATENATE(COUNTIFS(SIP[Investor ID],INVESTORS_LIST[[#This Row],[INVESTOR CODE]]),INVESTORS_LIST[[#This Row],[INVESTOR CODE]]),SIP[Unique Code],0),),0)} -> 0 | AN25: =IF(INVESTORS_LIST[[#This Row],[TOTAL CURRENT UNITS]]=0,0,(INVESTORS_LIST[[#This Row],[LS_WEIGHT]]*INVESTORS_LIST[[#This Row],[LS_AVERAGE COST]])+(INVESTORS_LIST[[#This Row],[SIP_WEIGHT]]*INVESTORS_LIST[[#This Row],[SIP_AVERAGE COST]])) -> 0 | AO25: =NAV_MKT -> 14.224 | AP25: =IF(INVESTORS_LIST[[#This Row],[TOTAL CURRENT UNITS]]=0,0,INVESTORS_LIST[[#This Row],[TOTAL CURRENT UNITS]]*INVESTORS_LIST[[#This Row],[NAV]]) -> 0 | AQ25: =IF(INVESTORS_LIST[[#This Row],[LS_TOTAL CURRENT UNITS]]=0,0,INVESTORS_LIST[[#This Row],[LS_TOTAL CURRENT UNITS]]*INVESTORS_LIST[[#This Row],[NAV]]) -> 0 | AR25: =IF(INVESTORS_LIST[[#This Row],[SIP_TOTAL CURRENT UNITS]]=0,0,INVESTORS_LIST[[#This Row],[SIP_TOTAL CURRENT UNITS]]*INVESTORS_LIST[[#This Row],[NAV]]) -> 0 | AS25: =INVESTORS_LIST[[#This Row],[TOTAL CURRENT UNITS]] -> 0 | AT25: =IF(INVESTORS_LIST[[#This Row],[TOTAL SELLABLE UNITS]]=0,0,INVESTORS_LIST[[#This Row],[TOTAL SELLABLE UNITS]]*INVESTORS_LIST[[#This Row],[NAV]]) -> 0 | AU25: =INVESTORS_LIST[[#This Row],[LS_TOTAL REALIZED GAIN]]+INVESTORS_LIST[[#This Row],[SIP_TOTAL REALIZED GAIN]] -> 0 | AV25: =INVESTORS_LIST[[#This Row],[TOTAL MARKET VALUE]]-INVESTORS_LIST[[#This Row],[TOTAL COST VALUE OF CURRENT INVESTMENT]] -> 0 | AW25: =IFERROR(INVESTORS_LIST[[#This Row],[TOTAL CURRENT UNITS]]/SUM(INVESTORS_LIST[TOTAL CURRENT UNITS]),0) -> 0
A26: FAHMIDA HAQUE | B26: A00026 | C26: Dear Mrs. | D26: Individual | E26: =SUMIFS(LS[Unit],LS[Investor ID],INVESTORS_LIST[[#This Row],[INVESTOR CODE]],LS[B/S],"B") -> 0 | F26: =-SUMIFS(LS[Unit],LS[Investor ID],INVESTORS_LIST[[#This Row],[INVESTOR CODE]],LS[B/S],"S") -> 0 | G26: =IF(INVESTORS_LIST[[#This Row],[LS_TOTAL UNITS BUY]]=0,0,INVESTORS_LIST[[#This Row],[LS_TOTAL UNITS BUY]]-INVESTORS_LIST[[#This Row],[LS_TOTAL UNITS SOLD]]) -> 0 | H26: =IF(INVESTORS_LIST[[#This Row],[LS_TOTAL UNITS BUY]]=0,0,SUMIFS(LS[Amount],LS[Investor ID],INVESTORS_LIST[[#This Row],[INVESTOR CODE]],LS[B/S],"B")) -> 0 | I26: =IF(INVESTORS_LIST[[#This Row],[LS_TOTAL UNITS SOLD]]=0,0,SUMIFS(LS[Cost of Units Sold],LS[Investor ID],INVESTORS_LIST[[#This Row],[INVESTOR CODE]],LS[B/S],"S")) -> 0 | J26: =IF(INVESTORS_LIST[[#This Row],[LS_TOTAL CURRENT UNITS]]=0,0,INVESTORS_LIST[[#This Row],[LS_TOTAL CURRENT UNITS]]*INVESTORS_LIST[[#This Row],[LS_AVERAGE COST]]) -> 0 | K26: =IF(INVESTORS_LIST[[#This Row],[LS_TOTAL UNITS SOLD]]=0,0,SUMIFS(LS[Realized Gain],LS[Investor ID],INVESTORS_LIST[[#This Row],[INVESTOR CODE]],LS[B/S],"S")) -> 0 | L26: =SUMIFS(SIP[Unit],SIP[Investor ID],INVESTORS_LIST[[#This Row],[INVESTOR CODE]],SIP[B/S],"B") -> 0 | M26: =-SUMIFS(SIP[Unit],SIP[Investor ID],INVESTORS_LIST[[#This Row],[INVESTOR CODE]],SIP[B/S],"S") -> 0 | N26: =IF(INVESTORS_LIST[[#This Row],[SIP_TOTAL UNITS BUY]]=0,0,INVESTORS_LIST[[#This Row],[SIP_TOTAL UNITS BUY]]-INVESTORS_LIST[[#This Row],[SIP_TOTAL UNITS SOLD]]) -> 0 | O26: =IF(INVESTORS_LIST[[#This Row],[SIP_TOTAL UNITS BUY]]=0,0,SUMIFS(SIP[Amount],SIP[Investor ID],INVESTORS_LIST[[#This Row],[INVESTOR CODE]],SIP[B/S],"B")) -> 0 | P26: =IF(INVESTORS_LIST[[#This Row],[SIP_TOTAL UNITS SOLD]]=0,0,SUMIFS(SIP[Cost of Units Sold],SIP[Investor ID],INVESTORS_LIST[[#This Row],[INVESTOR CODE]],SIP[B/S],"S")) -> 0 | Q26: =IF(INVESTORS_LIST[[#This Row],[SIP_TOTAL CURRENT UNITS]]=0,0,INVESTORS_LIST[[#This Row],[SIP_TOTAL CURRENT UNITS]]*INVESTORS_LIST[[#This Row],[SIP_AVERAGE COST]]) -> 0 | R26: =IF(INVESTORS_LIST[[#This Row],[SIP_TOTAL UNITS SOLD]]=0,0,SUMIFS(SIP[Realized Gain],SIP[Investor ID],INVESTORS_LIST[[#This Row],[INVESTOR CODE]],SIP[B/S],"S")) -> 0 | S26: =INVESTORS_LIST[[#This Row],[LS_TOTAL UNITS BUY]]+INVESTORS_LIST[[#This Row],[SIP_TOTAL UNITS BUY]] -> 0 | T26: =INVESTORS_LIST[[#This Row],[LS_TOTAL UNITS SOLD]]+INVESTORS_LIST[[#This Row],[SIP_TOTAL UNITS SOLD]] -> 0 | V26: =SUMIFS(LS[BO UNIT TRANSFER],LS[Investor ID],INVESTORS_LIST[[#This Row],[INVESTOR CODE]],LS[B/S],"B") -> 0 | W26: =SUMIFS(SIP[BO UNIT TRANSFER],SIP[Investor ID],INVESTORS_LIST[[#This Row],[INVESTOR CODE]],SIP[B/S],"B") -> 0 | X26: =SUMIFS(LS[BO UNIT TRANSFER],LS[Investor ID],INVESTORS_LIST[[#This Row],[INVESTOR CODE]],LS[B/S],"S") -> 0 | Y26: =SUMIFS(SIP[BO UNIT TRANSFER],SIP[Investor ID],INVESTORS_LIST[[#This Row],[INVESTOR CODE]],SIP[B/S],"S") -> 0 | Z26: =SUM(INVESTORS_LIST[[#This Row],[BO OPENING BALANCE]:[BO SIP UNITS REPURCHASE]]) -> 0 | AA26: =INVESTORS_LIST[[#This Row],[TOTAL UNITS BUY]]-INVESTORS_LIST[[#This Row],[TOTAL UNITS SOLD]] -> 0 | AB26: =INVESTORS_LIST[[#This Row],[TOTAL CURRENT UNITS]]-INVESTORS_LIST[[#This Row],[BO UNITS HOLD]] -> 0 | AC26: =INDEX([3]!Table_1[BO ID],MATCH(INVESTORS_LIST[[#This Row],[INVESTOR CODE]],[3]!Table_1[INVESTOR CODE],0)) -> #REF! | AD26: =INDEX([3]!Table_1[Brokerage Name2],MATCH(INVESTORS_LIST[[#This Row],[INVESTOR CODE]],[3]!Table_1[INVESTOR CODE],0)) -> #REF! | AE26: =MID(INVESTORS_LIST[[#This Row],[BO ID]],4,5) -> #REF! | AF26: =MID(INVESTORS_LIST[[#This Row],[BO ID]],2,7) -> #REF! | AG26: =MID(INVESTORS_LIST[[#This Row],[BO ID]],9,7) -> #REF! | AH26: =RIGHT(INVESTORS_LIST[[#This Row],[BO ID]],1) -> #REF! | AI26: =INVESTORS_LIST[[#This Row],[LS_TOTAL COST VALUE OF CURRENT UNITS]]+INVESTORS_LIST[[#This Row],[SIP_TOTAL COST VALUE OF CURRENT UNITS]] -> 0 | AJ26: =IF(INVESTORS_LIST[[#This Row],[TOTAL CURRENT UNITS]]=0,0,INVESTORS_LIST[[#This Row],[LS_TOTAL CURRENT UNITS]]/INVESTORS_LIST[[#This Row],[TOTAL CURRENT UNITS]]) -> 0 | AK26: =IF(INVESTORS_LIST[[#This Row],[TOTAL CURRENT UNITS]]=0,0,INVESTORS_LIST[[#This Row],[SIP_TOTAL CURRENT UNITS]]/INVESTORS_LIST[[#This Row],[TOTAL CURRENT UNITS]]) -> 0 | AL26: {=IF(INVESTORS_LIST[[#This Row],[LS_TOTAL UNITS BUY]]>0,INDEX(LS[NAV at Cost (Average)],MATCH(CONCATENATE(COUNTIFS(LS[Investor ID],INVESTORS_LIST[[#This Row],[INVESTOR CODE]]),INVESTORS_LIST[[#This Row],[INVESTOR CODE]]),LS[Unique Code],0),),0)} -> 0 | AM26: {=IF(INVESTORS_LIST[[#This Row],[SIP_TOTAL UNITS BUY]]>0,INDEX(SIP[NAV at Cost (Average)],MATCH(CONCATENATE(COUNTIFS(SIP[Investor ID],INVESTORS_LIST[[#This Row],[INVESTOR CODE]]),INVESTORS_LIST[[#This Row],[INVESTOR CODE]]),SIP[Unique Code],0),),0)} -> 0 | AN26: =IF(INVESTORS_LIST[[#This Row],[TOTAL CURRENT UNITS]]=0,0,(INVESTORS_LIST[[#This Row],[LS_WEIGHT]]*INVESTORS_LIST[[#This Row],[LS_AVERAGE COST]])+(INVESTORS_LIST[[#This Row],[SIP_WEIGHT]]*INVESTORS_LIST[[#This Row],[SIP_AVERAGE COST]])) -> 0 | AO26: =NAV_MKT -> 14.224 | AP26: =IF(INVESTORS_LIST[[#This Row],[TOTAL CURRENT UNITS]]=0,0,INVESTORS_LIST[[#This Row],[TOTAL CURRENT UNITS]]*INVESTORS_LIST[[#This Row],[NAV]]) -> 0 | AQ26: =IF(INVESTORS_LIST[[#This Row],[LS_TOTAL CURRENT UNITS]]=0,0,INVESTORS_LIST[[#This Row],[LS_TOTAL CURRENT UNITS]]*INVESTORS_LIST[[#This Row],[NAV]]) -> 0 | AR26: =IF(INVESTORS_LIST[[#This Row],[SIP_TOTAL CURRENT UNITS]]=0,0,INVESTORS_LIST[[#This Row],[SIP_TOTAL CURRENT UNITS]]*INVESTORS_LIST[[#This Row],[NAV]]) -> 0 | AS26: =INVESTORS_LIST[[#This Row],[TOTAL CURRENT UNITS]] -> 0 | AT26: =IF(INVESTORS_LIST[[#This Row],[TOTAL SELLABLE UNITS]]=0,0,INVESTORS_LIST[[#This Row],[TOTAL SELLABLE UNITS]]*INVESTORS_LIST[[#This Row],[NAV]]) -> 0 | AU26: =INVESTORS_LIST[[#This Row],[LS_TOTAL REALIZED GAIN]]+INVESTORS_LIST[[#This Row],[SIP_TOTAL REALIZED GAIN]] -> 0 | AV26: =INVESTORS_LIST[[#This Row],[TOTAL MARKET VALUE]]-INVESTORS_LIST[[#This Row],[TOTAL COST VALUE OF CURRENT INVESTMENT]] -> 0 | AW26: =IFERROR(INVESTORS_LIST[[#This Row],[TOTAL CURRENT UNITS]]/SUM(INVESTORS_LIST[TOTAL CURRENT UNITS]),0) -> 0
A27: MD. SHAHIDUL ISLAM | B27: A00027 | C27: Dear Mr. | D27: Individual | E27: =SUMIFS(LS[Unit],LS[Investor ID],INVESTORS_LIST[[#This Row],[INVESTOR CODE]],LS[B/S],"B") -> 50000 | F27: =-SUMIFS(LS[Unit],LS[Investor ID],INVESTORS_LIST[[#This Row],[INVESTOR CODE]],LS[B/S],"S") -> 50000 | G27: =IF(INVESTORS_LIST[[#This Row],[LS_TOTAL UNITS BUY]]=0,0,INVESTORS_LIST[[#This Row],[LS_TOTAL UNITS BUY]]-INVESTORS_LIST[[#This Row],[LS_TOTAL UNITS SOLD]]) -> 0 | H27: =IF(INVESTORS_LIST[[#This Row],[LS_TOTAL UNITS BUY]]=0,0,SUMIFS(LS[Amount],LS[Investor ID],INVESTORS_LIST[[#This Row],[INVESTOR CODE]],LS[B/S],"B")) -> 500000 | I27: =IF(INVESTORS_LIST[[#This Row],[LS_TOTAL UNITS SOLD]]=0,0,SUMIFS(LS[Cost of Units Sold],LS[Investor ID],INVESTORS_LIST[[#This Row],[INVESTOR CODE]],LS[B/S],"S")) -> 500000 | J27: =IF(INVESTORS_LIST[[#This Row],[LS_TOTAL CURRENT UNITS]]=0,0,INVESTORS_LIST[[#This Row],[LS_TOTAL CURRENT UNITS]]*INVESTORS_LIST[[#This Row],[LS_AVERAGE COST]]) -> 0 | K27: =IF(INVESTORS_LIST[[#This Row],[LS_TOTAL UNITS SOLD]]=0,0,SUMIFS(LS[Realized Gain],LS[Investor ID],INVESTORS_LIST[[#This Row],[INVESTOR CODE]],LS[B/S],"S")) -> 2850 | L27: =SUMIFS(SIP[Unit],SIP[Investor ID],INVESTORS_LIST[[#This Row],[INVESTOR CODE]],SIP[B/S],"B") -> 0 | M27: =-SUMIFS(SIP[Unit],SIP[Investor ID],INVESTORS_LIST[[#This Row],[INVESTOR CODE]],SIP[B/S],"S") -> 0 | N27: =IF(INVESTORS_LIST[[#This Row],[SIP_TOTAL UNITS BUY]]=0,0,INVESTORS_LIST[[#This Row],[SIP_TOTAL UNITS BUY]]-INVESTORS_LIST[[#This Row],[SIP_TOTAL UNITS SOLD]]) -> 0 | O27: =IF(INVESTORS_LIST[[#This Row],[SIP_TOTAL UNITS BUY]]=0,0,SUMIFS(SIP[Amount],SIP[Investor ID],INVESTORS_LIST[[#This Row],[INVESTOR CODE]],SIP[B/S],"B")) -> 0 | P27: =IF(INVESTORS_LIST[[#This Row],[SIP_TOTAL UNITS SOLD]]=0,0,SUMIFS(SIP[Cost of Units Sold],SIP[Investor ID],INVESTORS_LIST[[#This Row],[INVESTOR CODE]],SIP[B/S],"S")) -> 0 | Q27: =IF(INVESTORS_LIST[[#This Row],[SIP_TOTAL CURRENT UNITS]]=0,0,INVESTORS_LIST[[#This Row],[SIP_TOTAL CURRENT UNITS]]*INVESTORS_LIST[[#This Row],[SIP_AVERAGE COST]]) -> 0 | R27: =IF(INVESTORS_LIST[[#This Row],[SIP_TOTAL UNITS SOLD]]=0,0,SUMIFS(SIP[Realized Gain],SIP[Investor ID],INVESTORS_LIST[[#This Row],[INVESTOR CODE]],SIP[B/S],"S")) -> 0 | S27: =INVESTORS_LIST[[#This Row],[LS_TOTAL UNITS BUY]]+INVESTORS_LIST[[#This Row],[SIP_TOTAL UNITS BUY]] -> 50000 | T27: =INVESTORS_LIST[[#This Row],[LS_TOTAL UNITS SOLD]]+INVESTORS_LIST[[#This Row],[SIP_TOTAL UNITS SOLD]] -> 50000 | V27: =SUMIFS(LS[BO UNIT TRANSFER],LS[Investor ID],INVESTORS_LIST[[#This Row],[INVESTOR CODE]],LS[B/S],"B") -> 0 | W27: =SUMIFS(SIP[BO UNIT TRANSFER],SIP[Investor ID],INVESTORS_LIST[[#This Row],[INVESTOR CODE]],SIP[B/S],"B") -> 0 | X27: =SUMIFS(LS[BO UNIT TRANSFER],LS[Investor ID],INVESTORS_LIST[[#This Row],[INVESTOR CODE]],LS[B/S],"S") -> 0 | Y27: =SUMIFS(SIP[BO UNIT TRANSFER],SIP[Investor ID],INVESTORS_LIST[[#This Row],[INVESTOR CODE]],SIP[B/S],"S") -> 0 | Z27: =SUM(INVESTORS_LIST[[#This Row],[BO OPENING BALANCE]:[BO SIP UNITS REPURCHASE]]) -> 0 | AA27: =INVESTORS_LIST[[#This Row],[TOTAL UNITS BUY]]-INVESTORS_LIST[[#This Row],[TOTAL UNITS SOLD]] -> 0 | AB27: =INVESTORS_LIST[[#This Row],[TOTAL CURRENT UNITS]]-INVESTORS_LIST[[#This Row],[BO UNITS HOLD]] -> 0 | AC27: =INDEX([3]!Table_1[BO ID],MATCH(INVESTORS_LIST[[#This Row],[INVESTOR CODE]],[3]!Table_1[INVESTOR CODE],0)) -> #REF! | AD27: =INDEX([3]!Table_1[Brokerage Name2],MATCH(INVESTORS_LIST[[#This Row],[INVESTOR CODE]],[3]!Table_1[INVESTOR CODE],0)) -> #REF! | AE27: =MID(INVESTORS_LIST[[#This Row],[BO ID]],4,5) -> #REF! | AF27: =MID(INVESTORS_LIST[[#This Row],[BO ID]],2,7) -> #REF! | AG27: =MID(INVESTORS_LIST[[#This Row],[BO ID]],9,7) -> #REF! | AH27: =RIGHT(INVESTORS_LIST[[#This Row],[BO ID]],1) -> #REF! | AI27: =INVESTORS_LIST[[#This Row],[LS_TOTAL COST VALUE OF CURRENT UNITS]]+INVESTORS_LIST[[#This Row],[SIP_TOTAL COST VALUE OF CURRENT UNITS]] -> 0 | AJ27: =IF(INVESTORS_LIST[[#This Row],[TOTAL CURRENT UNITS]]=0,0,INVESTORS_LIST[[#This Row],[LS_TOTAL CURRENT UNITS]]/INVESTORS_LIST[[#This Row],[TOTAL CURRENT UNITS]]) -> 0 | AK27: =IF(INVESTORS_LIST[[#This Row],[TOTAL CURRENT UNITS]]=0,0,INVESTORS_LIST[[#This Row],[SIP_TOTAL CURRENT UNITS]]/INVESTORS_LIST[[#This Row],[TOTAL CURRENT UNITS]]) -> 0 | AL27: {=IF(INVESTORS_LIST[[#This Row],[LS_TOTAL UNITS BUY]]>0,INDEX(LS[NAV at Cost (Average)],MATCH(CONCATENATE(COUNTIFS(LS[Investor ID],INVESTORS_LIST[[#This Row],[INVESTOR CODE]]),INVESTORS_LIST[[#This Row],[INVESTOR CODE]]),LS[Unique Code],0),),0)} -> 0 | AM27: {=IF(INVESTORS_LIST[[#This Row],[SIP_TOTAL UNITS BUY]]>0,INDEX(SIP[NAV at Cost (Average)],MATCH(CONCATENATE(COUNTIFS(SIP[Investor ID],INVESTORS_LIST[[#This Row],[INVESTOR CODE]]),INVESTORS_LIST[[#This Row],[INVESTOR CODE]]),SIP[Unique Code],0),),0)} -> 0 | AN27: =IF(INVESTORS_LIST[[#This Row],[TOTAL CURRENT UNITS]]=0,0,(INVESTORS_LIST[[#This Row],[LS_WEIGHT]]*INVESTORS_LIST[[#This Row],[LS_AVERAGE COST]])+(INVESTORS_LIST[[#This Row],[SIP_WEIGHT]]*INVESTORS_LIST[[#This Row],[SIP_AVERAGE COST]])) -> 0 | AO27: =NAV_MKT -> 14.224 | AP27: =IF(INVESTORS_LIST[[#This Row],[TOTAL CURRENT UNITS]]=0,0,INVESTORS_LIST[[#This Row],[TOTAL CURRENT UNITS]]*INVESTORS_LIST[[#This Row],[NAV]]) -> 0 | AQ27: =IF(INVESTORS_LIST[[#This Row],[LS_TOTAL CURRENT UNITS]]=0,0,INVESTORS_LIST[[#This Row],[LS_TOTAL CURRENT UNITS]]*INVESTORS_LIST[[#This Row],[NAV]]) -> 0 | AR27: =IF(INVESTORS_LIST[[#This Row],[SIP_TOTAL CURRENT UNITS]]=0,0,INVESTORS_LIST[[#This Row],[SIP_TOTAL CURRENT UNITS]]*INVESTORS_LIST[[#This Row],[NAV]]) -> 0 | AS27: =INVESTORS_LIST[[#This Row],[TOTAL CURRENT UNITS]] -> 0 | AT27: =IF(INVESTORS_LIST[[#This Row],[TOTAL SELLABLE UNITS]]=0,0,INVESTORS_LIST[[#This Row],[TOTAL SELLABLE UNITS]]*INVESTORS_LIST[[#This Row],[NAV]]) -> 0 | AU27: =INVESTORS_LIST[[#This Row],[LS_TOTAL REALIZED GAIN]]+INVESTORS_LIST[[#This Row],[SIP_TOTAL REALIZED GAIN]] -> 2850 | AV27: =INVESTORS_LIST[[#This Row],[TOTAL MARKET VALUE]]-INVESTORS_LIST[[#This Row],[TOTAL COST VALUE OF CURRENT INVESTMENT]] -> 0 | AW27: =IFERROR(INVESTORS_LIST[[#This Row],[TOTAL CURRENT UNITS]]/SUM(INVESTORS_LIST[TOTAL CURRENT UNITS]),0) -> 0
A28: PRATIMA DEV | B28: A00028 | C28: Dear Mrs. | D28: Individual | E28: =SUMIFS(LS[Unit],LS[Investor ID],INVESTORS_LIST[[#This Row],[INVESTOR CODE]],LS[B/S],"B") -> 0 | F28: =-SUMIFS(LS[Unit],LS[Investor ID],INVESTORS_LIST[[#This Row],[INVESTOR CODE]],LS[B/S],"S") -> 0 | G28: =IF(INVESTORS_LIST[[#This Row],[LS_TOTAL UNITS BUY]]=0,0,INVESTORS_LIST[[#This Row],[LS_TOTAL UNITS BUY]]-INVESTORS_LIST[[#This Row],[LS_TOTAL UNITS SOLD]]) -> 0 | H28: =IF(INVESTORS_LIST[[#This Row],[LS_TOTAL UNITS BUY]]=0,0,SUMIFS(LS[Amount],LS[Investor ID],INVESTORS_LIST[[#This Row],[INVESTOR CODE]],LS[B/S],"B")) -> 0 | I28: =IF(INVESTORS_LIST[[#This Row],[LS_TOTAL UNITS SOLD]]=0,0,SUMIFS(LS[Cost of Units Sold],LS[Investor ID],INVESTORS_LIST[[#This Row],[INVESTOR CODE]],LS[B/S],"S")) -> 0 | J28: =IF(INVESTORS_LIST[[#This Row],[LS_TOTAL CURRENT UNITS]]=0,0,INVESTORS_LIST[[#This Row],[LS_TOTAL CURRENT UNITS]]*INVESTORS_LIST[[#This Row],[LS_AVERAGE COST]]) -> 0 | K28: =IF(INVESTORS_LIST[[#This Row],[LS_TOTAL UNITS SOLD]]=0,0,SUMIFS(LS[Realized Gain],LS[Investor ID],INVESTORS_LIST[[#This Row],[INVESTOR CODE]],LS[B/S],"S")) -> 0 | L28: =SUMIFS(SIP[Unit],SIP[Investor ID],INVESTORS_LIST[[#This Row],[INVESTOR CODE]],SIP[B/S],"B") -> 0 | M28: =-SUMIFS(SIP[Unit],SIP[Investor ID],INVESTORS_LIST[[#This Row],[INVESTOR CODE]],SIP[B/S],"S") -> 0 | N28: =IF(INVESTORS_LIST[[#This Row],[SIP_TOTAL UNITS BUY]]=0,0,INVESTORS_LIST[[#This Row],[SIP_TOTAL UNITS BUY]]-INVESTORS_LIST[[#This Row],[SIP_TOTAL UNITS SOLD]]) -> 0 | O28: =IF(INVESTORS_LIST[[#This Row],[SIP_TOTAL UNITS BUY]]=0,0,SUMIFS(SIP[Amount],SIP[Investor ID],INVESTORS_LIST[[#This Row],[INVESTOR CODE]],SIP[B/S],"B")) -> 0 | P28: =IF(INVESTORS_LIST[[#This Row],[SIP_TOTAL UNITS SOLD]]=0,0,SUMIFS(SIP[Cost of Units Sold],SIP[Investor ID],INVESTORS_LIST[[#This Row],[INVESTOR CODE]],SIP[B/S],"S")) -> 0 | Q28: =IF(INVESTORS_LIST[[#This Row],[SIP_TOTAL CURRENT UNITS]]=0,0,INVESTORS_LIST[[#This Row],[SIP_TOTAL CURRENT UNITS]]*INVESTORS_LIST[[#This Row],[SIP_AVERAGE COST]]) -> 0 | R28: =IF(INVESTORS_LIST[[#This Row],[SIP_TOTAL UNITS SOLD]]=0,0,SUMIFS(SIP[Realized Gain],SIP[Investor ID],INVESTORS_LIST[[#This Row],[INVESTOR CODE]],SIP[B/S],"S")) -> 0 | S28: =INVESTORS_LIST[[#This Row],[LS_TOTAL UNITS BUY]]+INVESTORS_LIST[[#This Row],[SIP_TOTAL UNITS BUY]] -> 0 | T28: =INVESTORS_LIST[[#This Row],[LS_TOTAL UNITS SOLD]]+INVESTORS_LIST[[#This Row],[SIP_TOTAL UNITS SOLD]] -> 0 | V28: =SUMIFS(LS[BO UNIT TRANSFER],LS[Investor ID],INVESTORS_LIST[[#This Row],[INVESTOR CODE]],LS[B/S],"B") -> 0 | W28: =SUMIFS(SIP[BO UNIT TRANSFER],SIP[Investor ID],INVESTORS_LIST[[#This Row],[INVESTOR CODE]],SIP[B/S],"B") -> 0 | X28: =SUMIFS(LS[BO UNIT TRANSFER],LS[Investor ID],INVESTORS_LIST[[#This Row],[INVESTOR CODE]],LS[B/S],"S") -> 0 | Y28: =SUMIFS(SIP[BO UNIT TRANSFER],SIP[Investor ID],INVESTORS_LIST[[#This Row],[INVESTOR CODE]],SIP[B/S],"S") -> 0 | Z28: =SUM(INVESTORS_LIST[[#This Row],[BO OPENING BALANCE]:[BO SIP UNITS REPURCHASE]]) -> 0 | AA28: =INVESTORS_LIST[[#This Row],[TOTAL UNITS BUY]]-INVESTORS_LIST[[#This Row],[TOTAL UNITS SOLD]] -> 0 | AB28: =INVESTORS_LIST[[#This Row],[TOTAL CURRENT UNITS]]-INVESTORS_LIST[[#This Row],[BO UNITS HOLD]] -> 0 | AC28: =INDEX([3]!Table_1[BO ID],MATCH(INVESTORS_LIST[[#This Row],[INVESTOR CODE]],[3]!Table_1[INVESTOR CODE],0)) -> #REF! | AD28: =INDEX([3]!Table_1[Brokerage Name2],MATCH(INVESTORS_LIST[[#This Row],[INVESTOR CODE]],[3]!Table_1[INVESTOR CODE],0)) -> #REF! | AE28: =MID(INVESTORS_LIST[[#This Row],[BO ID]],4,5) -> #REF! | AF28: =MID(INVESTORS_LIST[[#This Row],[BO ID]],2,7) -> #REF! | AG28: =MID(INVESTORS_LIST[[#This Row],[BO ID]],9,7) -> #REF! | AH28: =RIGHT(INVESTORS_LIST[[#This Row],[BO ID]],1) -> #REF! | AI28: =INVESTORS_LIST[[#This Row],[LS_TOTAL COST VALUE OF CURRENT UNITS]]+INVESTORS_LIST[[#This Row],[SIP_TOTAL COST VALUE OF CURRENT UNITS]] -> 0 | AJ28: =IF(INVESTORS_LIST[[#This Row],[TOTAL CURRENT UNITS]]=0,0,INVESTORS_LIST[[#This Row],[LS_TOTAL CURRENT UNITS]]/INVESTORS_LIST[[#This Row],[TOTAL CURRENT UNITS]]) -> 0 | AK28: =IF(INVESTORS_LIST[[#This Row],[TOTAL CURRENT UNITS]]=0,0,INVESTORS_LIST[[#This Row],[SIP_TOTAL CURRENT UNITS]]/INVESTORS_LIST[[#This Row],[TOTAL CURRENT UNITS]]) -> 0 | AL28: {=IF(INVESTORS_LIST[[#This Row],[LS_TOTAL UNITS BUY]]>0,INDEX(LS[NAV at Cost (Average)],MATCH(CONCATENATE(COUNTIFS(LS[Investor ID],INVESTORS_LIST[[#This Row],[INVESTOR CODE]]),INVESTORS_LIST[[#This Row],[INVESTOR CODE]]),LS[Unique Code],0),),0)} -> 0 | AM28: {=IF(INVESTORS_LIST[[#This Row],[SIP_TOTAL UNITS BUY]]>0,INDEX(SIP[NAV at Cost (Average)],MATCH(CONCATENATE(COUNTIFS(SIP[Investor ID],INVESTORS_LIST[[#This Row],[INVESTOR CODE]]),INVESTORS_LIST[[#This Row],[INVESTOR CODE]]),SIP[Unique Code],0),),0)} -> 0 | AN28: =IF(INVESTORS_LIST[[#This Row],[TOTAL CURRENT UNITS]]=0,0,(INVESTORS_LIST[[#This Row],[LS_WEIGHT]]*INVESTORS_LIST[[#This Row],[LS_AVERAGE COST]])+(INVESTORS_LIST[[#This Row],[SIP_WEIGHT]]*INVESTORS_LIST[[#This Row],[SIP_AVERAGE COST]])) -> 0 | AO28: =NAV_MKT -> 14.224 | AP28: =IF(INVESTORS_LIST[[#This Row],[TOTAL CURRENT UNITS]]=0,0,INVESTORS_LIST[[#This Row],[TOTAL CURRENT UNITS]]*INVESTORS_LIST[[#This Row],[NAV]]) -> 0 | AQ28: =IF(INVESTORS_LIST[[#This Row],[LS_TOTAL CURRENT UNITS]]=0,0,INVESTORS_LIST[[#This Row],[LS_TOTAL CURRENT UNITS]]*INVESTORS_LIST[[#This Row],[NAV]]) -> 0 | AR28: =IF(INVESTORS_LIST[[#This Row],[SIP_TOTAL CURRENT UNITS]]=0,0,INVESTORS_LIST[[#This Row],[SIP_TOTAL CURRENT UNITS]]*INVESTORS_LIST[[#This Row],[NAV]]) -> 0 | AS28: =INVESTORS_LIST[[#This Row],[TOTAL CURRENT UNITS]] -> 0 | AT28: =IF(INVESTORS_LIST[[#This Row],[TOTAL SELLABLE UNITS]]=0,0,INVESTORS_LIST[[#This Row],[TOTAL SELLABLE UNITS]]*INVESTORS_LIST[[#This Row],[NAV]]) -> 0 | AU28: =INVESTORS_LIST[[#This Row],[LS_TOTAL REALIZED GAIN]]+INVESTORS_LIST[[#This Row],[SIP_TOTAL REALIZED GAIN]] -> 0 | AV28: =INVESTORS_LIST[[#This Row],[TOTAL MARKET VALUE]]-INVESTORS_LIST[[#This Row],[TOTAL COST VALUE OF CURRENT INVESTMENT]] -> 0 | AW28: =IFERROR(INVESTORS_LIST[[#This Row],[TOTAL CURRENT UNITS]]/SUM(INVESTORS_LIST[TOTAL CURRENT UNITS]),0) -> 0
A29: NUR HAIDAR SARKER | B29: A00029 | C29: Dear Mr. | D29: Individual | E29: =SUMIFS(LS[Unit],LS[Investor ID],INVESTORS_LIST[[#This Row],[INVESTOR CODE]],LS[B/S],"B") -> 0 | F29: =-SUMIFS(LS[Unit],LS[Investor ID],INVESTORS_LIST[[#This Row],[INVESTOR CODE]],LS[B/S],"S") -> 0 | G29: =IF(INVESTORS_LIST[[#This Row],[LS_TOTAL UNITS BUY]]=0,0,INVESTORS_LIST[[#This Row],[LS_TOTAL UNITS BUY]]-INVESTORS_LIST[[#This Row],[LS_TOTAL UNITS SOLD]]) -> 0 | H29: =IF(INVESTORS_LIST[[#This Row],[LS_TOTAL UNITS BUY]]=0,0,SUMIFS(LS[Amount],LS[Investor ID],INVESTORS_LIST[[#This Row],[INVESTOR CODE]],LS[B/S],"B")) -> 0 | I29: =IF(INVESTORS_LIST[[#This Row],[LS_TOTAL UNITS SOLD]]=0,0,SUMIFS(LS[Cost of Units Sold],LS[Investor ID],INVESTORS_LIST[[#This Row],[INVESTOR CODE]],LS[B/S],"S")) -> 0 | J29: =IF(INVESTORS_LIST[[#This Row],[LS_TOTAL CURRENT UNITS]]=0,0,INVESTORS_LIST[[#This Row],[LS_TOTAL CURRENT UNITS]]*INVESTORS_LIST[[#This Row],[LS_AVERAGE COST]]) -> 0 | K29: =IF(INVESTORS_LIST[[#This Row],[LS_TOTAL UNITS SOLD]]=0,0,SUMIFS(LS[Realized Gain],LS[Investor ID],INVESTORS_LIST[[#This Row],[INVESTOR CODE]],LS[B/S],"S")) -> 0 | L29: =SUMIFS(SIP[Unit],SIP[Investor ID],INVESTORS_LIST[[#This Row],[INVESTOR CODE]],SIP[B/S],"B") -> 0 | M29: =-SUMIFS(SIP[Unit],SIP[Investor ID],INVESTORS_LIST[[#This Row],[INVESTOR CODE]],SIP[B/S],"S") -> 0 | N29: =IF(INVESTORS_LIST[[#This Row],[SIP_TOTAL UNITS BUY]]=0,0,INVESTORS_LIST[[#This Row],[SIP_TOTAL UNITS BUY]]-INVESTORS_LIST[[#This Row],[SIP_TOTAL UNITS SOLD]]) -> 0 | O29: =IF(INVESTORS_LIST[[#This Row],[SIP_TOTAL UNITS BUY]]=0,0,SUMIFS(SIP[Amount],SIP[Investor ID],INVESTORS_LIST[[#This Row],[INVESTOR CODE]],SIP[B/S],"B")) -> 0 | P29: =IF(INVESTORS_LIST[[#This Row],[SIP_TOTAL UNITS SOLD]]=0,0,SUMIFS(SIP[Cost of Units Sold],SIP[Investor ID],INVESTORS_LIST[[#This Row],[INVESTOR CODE]],SIP[B/S],"S")) -> 0 | Q29: =IF(INVESTORS_LIST[[#This Row],[SIP_TOTAL CURRENT UNITS]]=0,0,INVESTORS_LIST[[#This Row],[SIP_TOTAL CURRENT UNITS]]*INVESTORS_LIST[[#This Row],[SIP_AVERAGE COST]]) -> 0 | R29: =IF(INVESTORS_LIST[[#This Row],[SIP_TOTAL UNITS SOLD]]=0,0,SUMIFS(SIP[Realized Gain],SIP[Investor ID],INVESTORS_LIST[[#This Row],[INVESTOR CODE]],SIP[B/S],"S")) -> 0 | S29: =INVESTORS_LIST[[#This Row],[LS_TOTAL UNITS BUY]]+INVESTORS_LIST[[#This Row],[SIP_TOTAL UNITS BUY]] -> 0 | T29: =INVESTORS_LIST[[#This Row],[LS_TOTAL UNITS SOLD]]+INVESTORS_LIST[[#This Row],[SIP_TOTAL UNITS SOLD]] -> 0 | V29: =SUMIFS(LS[BO UNIT TRANSFER],LS[Investor ID],INVESTORS_LIST[[#This Row],[INVESTOR CODE]],LS[B/S],"B") -> 0 | W29: =SUMIFS(SIP[BO UNIT TRANSFER],SIP[Investor ID],INVESTORS_LIST[[#This Row],[INVESTOR CODE]],SIP[B/S],"B") -> 0 | X29: =SUMIFS(LS[BO UNIT TRANSFER],LS[Investor ID],INVESTORS_LIST[[#This Row],[INVESTOR CODE]],LS[B/S],"S") -> 0 | Y29: =SUMIFS(SIP[BO UNIT TRANSFER],SIP[Investor ID],INVESTORS_LIST[[#This Row],[INVESTOR CODE]],SIP[B/S],"S") -> 0 | Z29: =SUM(INVESTORS_LIST[[#This Row],[BO OPENING BALANCE]:[BO SIP UNITS REPURCHASE]]) -> 0 | AA29: =INVESTORS_LIST[[#This Row],[TOTAL UNITS BUY]]-INVESTORS_LIST[[#This Row],[TOTAL UNITS SOLD]] -> 0 | AB29: =INVESTORS_LIST[[#This Row],[TOTAL CURRENT UNITS]]-INVESTORS_LIST[[#This Row],[BO UNITS HOLD]] -> 0 | AC29: =INDEX([3]!Table_1[BO ID],MATCH(INVESTORS_LIST[[#This Row],[INVESTOR CODE]],[3]!Table_1[INVESTOR CODE],0)) -> #REF! | AD29: =INDEX([3]!Table_1[Brokerage Name2],MATCH(INVESTORS_LIST[[#This Row],[INVESTOR CODE]],[3]!Table_1[INVESTOR CODE],0)) -> #REF! | AE29: =MID(INVESTORS_LIST[[#This Row],[BO ID]],4,5) -> #REF! | AF29: =MID(INVESTORS_LIST[[#This Row],[BO ID]],2,7) -> #REF! | AG29: =MID(INVESTORS_LIST[[#This Row],[BO ID]],9,7) -> #REF! | AH29: =RIGHT(INVESTORS_LIST[[#This Row],[BO ID]],1) -> #REF! | AI29: =INVESTORS_LIST[[#This Row],[LS_TOTAL COST VALUE OF CURRENT UNITS]]+INVESTORS_LIST[[#This Row],[SIP_TOTAL COST VALUE OF CURRENT UNITS]] -> 0 | AJ29: =IF(INVESTORS_LIST[[#This Row],[TOTAL CURRENT UNITS]]=0,0,INVESTORS_LIST[[#This Row],[LS_TOTAL CURRENT UNITS]]/INVESTORS_LIST[[#This Row],[TOTAL CURRENT UNITS]]) -> 0 | AK29: =IF(INVESTORS_LIST[[#This Row],[TOTAL CURRENT UNITS]]=0,0,INVESTORS_LIST[[#This Row],[SIP_TOTAL CURRENT UNITS]]/INVESTORS_LIST[[#This Row],[TOTAL CURRENT UNITS]]) -> 0 | AL29: {=IF(INVESTORS_LIST[[#This Row],[LS_TOTAL UNITS BUY]]>0,INDEX(LS[NAV at Cost (Average)],MATCH(CONCATENATE(COUNTIFS(LS[Investor ID],INVESTORS_LIST[[#This Row],[INVESTOR CODE]]),INVESTORS_LIST[[#This Row],[INVESTOR CODE]]),LS[Unique Code],0),),0)} -> 0 | AM29: {=IF(INVESTORS_LIST[[#This Row],[SIP_TOTAL UNITS BUY]]>0,INDEX(SIP[NAV at Cost (Average)],MATCH(CONCATENATE(COUNTIFS(SIP[Investor ID],INVESTORS_LIST[[#This Row],[INVESTOR CODE]]),INVESTORS_LIST[[#This Row],[INVESTOR CODE]]),SIP[Unique Code],0),),0)} -> 0 | AN29: =IF(INVESTORS_LIST[[#This Row],[TOTAL CURRENT UNITS]]=0,0,(INVESTORS_LIST[[#This Row],[LS_WEIGHT]]*INVESTORS_LIST[[#This Row],[LS_AVERAGE COST]])+(INVESTORS_LIST[[#This Row],[SIP_WEIGHT]]*INVESTORS_LIST[[#This Row],[SIP_AVERAGE COST]])) -> 0 | AO29: =NAV_MKT -> 14.224 | AP29: =IF(INVESTORS_LIST[[#This Row],[TOTAL CURRENT UNITS]]=0,0,INVESTORS_LIST[[#This Row],[TOTAL CURRENT UNITS]]*INVESTORS_LIST[[#This Row],[NAV]]) -> 0 | AQ29: =IF(INVESTORS_LIST[[#This Row],[LS_TOTAL CURRENT UNITS]]=0,0,INVESTORS_LIST[[#This Row],[LS_TOTAL CURRENT UNITS]]*INVESTORS_LIST[[#This Row],[NAV]]) -> 0 | AR29: =IF(INVESTORS_LIST[[#This Row],[SIP_TOTAL CURRENT UNITS]]=0,0,INVESTORS_LIST[[#This Row],[SIP_TOTAL CURRENT UNITS]]*INVESTORS_LIST[[#This Row],[NAV]]) -> 0 | AS29: =INVESTORS_LIST[[#This Row],[TOTAL CURRENT UNITS]] -> 0 | AT29: =IF(INVESTORS_LIST[[#This Row],[TOTAL SELLABLE UNITS]]=0,0,INVESTORS_LIST[[#This Row],[TOTAL SELLABLE UNITS]]*INVESTORS_LIST[[#This Row],[NAV]]) -> 0 | AU29: =INVESTORS_LIST[[#This Row],[LS_TOTAL REALIZED GAIN]]+INVESTORS_LIST[[#This Row],[SIP_TOTAL REALIZED GAIN]] -> 0 | AV29: =INVESTORS_LIST[[#This Row],[TOTAL MARKET VALUE]]-INVESTORS_LIST[[#This Row],[TOTAL COST VALUE OF CURRENT INVESTMENT]] -> 0 | AW29: =IFERROR(INVESTORS_LIST[[#This Row],[TOTAL CURRENT UNITS]]/SUM(INVESTORS_LIST[TOTAL CURRENT UNITS]),0) -> 0
A30: UNICAP SECURITIES LIMITED | B30: A00030 | C30: Dear | D30: Company/Organization | E30: =SUMIFS(LS[Unit],LS[Investor ID],INVESTORS_LIST[[#This Row],[INVESTOR CODE]],LS[B/S],"B") -> 0 | F30: =-SUMIFS(LS[Unit],LS[Investor ID],INVESTORS_LIST[[#This Row],[INVESTOR CODE]],LS[B/S],"S") -> 0 | G30: =IF(INVESTORS_LIST[[#This Row],[LS_TOTAL UNITS BUY]]=0,0,INVESTORS_LIST[[#This Row],[LS_TOTAL UNITS BUY]]-INVESTORS_LIST[[#This Row],[LS_TOTAL UNITS SOLD]]) -> 0 | H30: =IF(INVESTORS_LIST[[#This Row],[LS_TOTAL UNITS BUY]]=0,0,SUMIFS(LS[Amount],LS[Investor ID],INVESTORS_LIST[[#This Row],[INVESTOR CODE]],LS[B/S],"B")) -> 0 | I30: =IF(INVESTORS_LIST[[#This Row],[LS_TOTAL UNITS SOLD]]=0,0,SUMIFS(LS[Cost of Units Sold],LS[Investor ID],INVESTORS_LIST[[#This Row],[INVESTOR CODE]],LS[B/S],"S")) -> 0 | J30: =IF(INVESTORS_LIST[[#This Row],[LS_TOTAL CURRENT UNITS]]=0,0,INVESTORS_LIST[[#This Row],[LS_TOTAL CURRENT UNITS]]*INVESTORS_LIST[[#This Row],[LS_AVERAGE COST]]) -> 0 | K30: =IF(INVESTORS_LIST[[#This Row],[LS_TOTAL UNITS SOLD]]=0,0,SUMIFS(LS[Realized Gain],LS[Investor ID],INVESTORS_LIST[[#This Row],[INVESTOR CODE]],LS[B/S],"S")) -> 0 | L30: =SUMIFS(SIP[Unit],SIP[Investor ID],INVESTORS_LIST[[#This Row],[INVESTOR CODE]],SIP[B/S],"B") -> 0 | M30: =-SUMIFS(SIP[Unit],SIP[Investor ID],INVESTORS_LIST[[#This Row],[INVESTOR CODE]],SIP[B/S],"S") -> 0 | N30: =IF(INVESTORS_LIST[[#This Row],[SIP_TOTAL UNITS BUY]]=0,0,INVESTORS_LIST[[#This Row],[SIP_TOTAL UNITS BUY]]-INVESTORS_LIST[[#This Row],[SIP_TOTAL UNITS SOLD]]) -> 0 | O30: =IF(INVESTORS_LIST[[#This Row],[SIP_TOTAL UNITS BUY]]=0,0,SUMIFS(SIP[Amount],SIP[Investor ID],INVESTORS_LIST[[#This Row],[INVESTOR CODE]],SIP[B/S],"B")) -> 0 | P30: =IF(INVESTORS_LIST[[#This Row],[SIP_TOTAL UNITS SOLD]]=0,0,SUMIFS(SIP[Cost of Units Sold],SIP[Investor ID],INVESTORS_LIST[[#This Row],[INVESTOR CODE]],SIP[B/S],"S")) -> 0 | Q30: =IF(INVESTORS_LIST[[#This Row],[SIP_TOTAL CURRENT UNITS]]=0,0,INVESTORS_LIST[[#This Row],[SIP_TOTAL CURRENT UNITS]]*INVESTORS_LIST[[#This Row],[SIP_AVERAGE COST]]) -> 0 | R30: =IF(INVESTORS_LIST[[#This Row],[SIP_TOTAL UNITS SOLD]]=0,0,SUMIFS(SIP[Realized Gain],SIP[Investor ID],INVESTORS_LIST[[#This Row],[INVESTOR CODE]],SIP[B/S],"S")) -> 0 | S30: =INVESTORS_LIST[[#This Row],[LS_TOTAL UNITS BUY]]+INVESTORS_LIST[[#This Row],[SIP_TOTAL UNITS BUY]] -> 0 | T30: =INVESTORS_LIST[[#This Row],[LS_TOTAL UNITS SOLD]]+INVESTORS_LIST[[#This Row],[SIP_TOTAL UNITS SOLD]] -> 0 | V30: =SUMIFS(LS[BO UNIT TRANSFER],LS[Investor ID],INVESTORS_LIST[[#This Row],[INVESTOR CODE]],LS[B/S],"B") -> 0 | W30: =SUMIFS(SIP[BO UNIT TRANSFER],SIP[Investor ID],INVESTORS_LIST[[#This Row],[INVESTOR CODE]],SIP[B/S],"B") -> 0 | X30: =SUMIFS(LS[BO UNIT TRANSFER],LS[Investor ID],INVESTORS_LIST[[#This Row],[INVESTOR CODE]],LS[B/S],"S") -> 0 | Y30: =SUMIFS(SIP[BO UNIT TRANSFER],SIP[Investor ID],INVESTORS_LIST[[#This Row],[INVESTOR CODE]],SIP[B/S],"S") -> 0 | Z30: =SUM(INVESTORS_LIST[[#This Row],[BO OPENING BALANCE]:[BO SIP UNITS REPURCHASE]]) -> 0 | AA30: =INVESTORS_LIST[[#This Row],[TOTAL UNITS BUY]]-INVESTORS_LIST[[#This Row],[TOTAL UNITS SOLD]] -> 0 | AB30: =INVESTORS_LIST[[#This Row],[TOTAL CURRENT UNITS]]-INVESTORS_LIST[[#This Row],[BO UNITS HOLD]] -> 0 | AC30: =INDEX([3]!Table_1[BO ID],MATCH(INVESTORS_LIST[[#This Row],[INVESTOR CODE]],[3]!Table_1[INVESTOR CODE],0)) -> #REF! | AD30: =INDEX([3]!Table_1[Brokerage Name2],MATCH(INVESTORS_LIST[[#This Row],[INVESTOR CODE]],[3]!Table_1[INVESTOR CODE],0)) -> #REF! | AE30: =MID(INVESTORS_LIST[[#This Row],[BO ID]],4,5) -> #REF! | AF30: =MID(INVESTORS_LIST[[#This Row],[BO ID]],2,7) -> #REF! | AG30: =MID(INVESTORS_LIST[[#This Row],[BO ID]],9,7) -> #REF! | AH30: =RIGHT(INVESTORS_LIST[[#This Row],[BO ID]],1) -> #REF! | AI30: =INVESTORS_LIST[[#This Row],[LS_TOTAL COST VALUE OF CURRENT UNITS]]+INVESTORS_LIST[[#This Row],[SIP_TOTAL COST VALUE OF CURRENT UNITS]] -> 0 | AJ30: =IF(INVESTORS_LIST[[#This Row],[TOTAL CURRENT UNITS]]=0,0,INVESTORS_LIST[[#This Row],[LS_TOTAL CURRENT UNITS]]/INVESTORS_LIST[[#This Row],[TOTAL CURRENT UNITS]]) -> 0 | AK30: =IF(INVESTORS_LIST[[#This Row],[TOTAL CURRENT UNITS]]=0,0,INVESTORS_LIST[[#This Row],[SIP_TOTAL CURRENT UNITS]]/INVESTORS_LIST[[#This Row],[TOTAL CURRENT UNITS]]) -> 0 | AL30: {=IF(INVESTORS_LIST[[#This Row],[LS_TOTAL UNITS BUY]]>0,INDEX(LS[NAV at Cost (Average)],MATCH(CONCATENATE(COUNTIFS(LS[Investor ID],INVESTORS_LIST[[#This Row],[INVESTOR CODE]]),INVESTORS_LIST[[#This Row],[INVESTOR CODE]]),LS[Unique Code],0),),0)} -> 0 | AM30: {=IF(INVESTORS_LIST[[#This Row],[SIP_TOTAL UNITS BUY]]>0,INDEX(SIP[NAV at Cost (Average)],MATCH(CONCATENATE(COUNTIFS(SIP[Investor ID],INVESTORS_LIST[[#This Row],[INVESTOR CODE]]),INVESTORS_LIST[[#This Row],[INVESTOR CODE]]),SIP[Unique Code],0),),0)} -> 0 | AN30: =IF(INVESTORS_LIST[[#This Row],[TOTAL CURRENT UNITS]]=0,0,(INVESTORS_LIST[[#This Row],[LS_WEIGHT]]*INVESTORS_LIST[[#This Row],[LS_AVERAGE COST]])+(INVESTORS_LIST[[#This Row],[SIP_WEIGHT]]*INVESTORS_LIST[[#This Row],[SIP_AVERAGE COST]])) -> 0 | AO30: =NAV_MKT -> 14.224 | AP30: =IF(INVESTORS_LIST[[#This Row],[TOTAL CURRENT UNITS]]=0,0,INVESTORS_LIST[[#This Row],[TOTAL CURRENT UNITS]]*INVESTORS_LIST[[#This Row],[NAV]]) -> 0 | AQ30: =IF(INVESTORS_LIST[[#This Row],[LS_TOTAL CURRENT UNITS]]=0,0,INVESTORS_LIST[[#This Row],[LS_TOTAL CURRENT UNITS]]*INVESTORS_LIST[[#This Row],[NAV]]) -> 0 | AR30: =IF(INVESTORS_LIST[[#This Row],[SIP_TOTAL CURRENT UNITS]]=0,0,INVESTORS_LIST[[#This Row],[SIP_TOTAL CURRENT UNITS]]*INVESTORS_LIST[[#This Row],[NAV]]) -> 0 | AS30: =INVESTORS_LIST[[#This Row],[TOTAL CURRENT UNITS]] -> 0 | AT30: =IF(INVESTORS_LIST[[#This Row],[TOTAL SELLABLE UNITS]]=0,0,INVESTORS_LIST[[#This Row],[TOTAL SELLABLE UNITS]]*INVESTORS_LIST[[#This Row],[NAV]]) -> 0 | AU30: =INVESTORS_LIST[[#This Row],[LS_TOTAL REALIZED GAIN]]+INVESTORS_LIST[[#This Row],[SIP_TOTAL REALIZED GAIN]] -> 0 | AV30: =INVESTORS_LIST[[#This Row],[TOTAL MARKET VALUE]]-INVESTORS_LIST[[#This Row],[TOTAL COST VALUE OF CURRENT INVESTMENT]] -> 0 | AW30: =IFERROR(INVESTORS_LIST[[#This Row],[TOTAL CURRENT UNITS]]/SUM(INVESTORS_LIST[TOTAL CURRENT UNITS]),0) -> 0
A31: ICB ASSET MANAGEMENT COMPANY LIMITED | B31: A00031 | C31: Dear | D31: Company/Organization | E31: =SUMIFS(LS[Unit],LS[Investor ID],INVESTORS_LIST[[#This Row],[INVESTOR CODE]],LS[B/S],"B") -> 500000 | F31: =-SUMIFS(LS[Unit],LS[Investor ID],INVESTORS_LIST[[#This Row],[INVESTOR CODE]],LS[B/S],"S") -> 0 | G31: =IF(INVESTORS_LIST[[#This Row],[LS_TOTAL UNITS BUY]]=0,0,INVESTORS_LIST[[#This Row],[LS_TOTAL UNITS BUY]]-INVESTORS_LIST[[#This Row],[LS_TOTAL UNITS SOLD]]) -> 500000 | H31: =IF(INVESTORS_LIST[[#This Row],[LS_TOTAL UNITS BUY]]=0,0,SUMIFS(LS[Amount],LS[Investor ID],INVESTORS_LIST[[#This Row],[INVESTOR CODE]],LS[B/S],"B")) -> 5000000 | I31: =IF(INVESTORS_LIST[[#This Row],[LS_TOTAL UNITS SOLD]]=0,0,SUMIFS(LS[Cost of Units Sold],LS[Investor ID],INVESTORS_LIST[[#This Row],[INVESTOR CODE]],LS[B/S],"S")) -> 0 | J31: =IF(INVESTORS_LIST[[#This Row],[LS_TOTAL CURRENT UNITS]]=0,0,INVESTORS_LIST[[#This Row],[LS_TOTAL CURRENT UNITS]]*INVESTORS_LIST[[#This Row],[LS_AVERAGE COST]]) -> 5000000 | K31: =IF(INVESTORS_LIST[[#This Row],[LS_TOTAL UNITS SOLD]]=0,0,SUMIFS(LS[Realized Gain],LS[Investor ID],INVESTORS_LIST[[#This Row],[INVESTOR CODE]],LS[B/S],"S")) -> 0 | L31: =SUMIFS(SIP[Unit],SIP[Investor ID],INVESTORS_LIST[[#This Row],[INVESTOR CODE]],SIP[B/S],"B") -> 0 | M31: =-SUMIFS(SIP[Unit],SIP[Investor ID],INVESTORS_LIST[[#This Row],[INVESTOR CODE]],SIP[B/S],"S") -> 0 | N31: =IF(INVESTORS_LIST[[#This Row],[SIP_TOTAL UNITS BUY]]=0,0,INVESTORS_LIST[[#This Row],[SIP_TOTAL UNITS BUY]]-INVESTORS_LIST[[#This Row],[SIP_TOTAL UNITS SOLD]]) -> 0 | O31: =IF(INVESTORS_LIST[[#This Row],[SIP_TOTAL UNITS BUY]]=0,0,SUMIFS(SIP[Amount],SIP[Investor ID],INVESTORS_LIST[[#This Row],[INVESTOR CODE]],SIP[B/S],"B")) -> 0 | P31: =IF(INVESTORS_LIST[[#This Row],[SIP_TOTAL UNITS SOLD]]=0,0,SUMIFS(SIP[Cost of Units Sold],SIP[Investor ID],INVESTORS_LIST[[#This Row],[INVESTOR CODE]],SIP[B/S],"S")) -> 0 | Q31: =IF(INVESTORS_LIST[[#This Row],[SIP_TOTAL CURRENT UNITS]]=0,0,INVESTORS_LIST[[#This Row],[SIP_TOTAL CURRENT UNITS]]*INVESTORS_LIST[[#This Row],[SIP_AVERAGE COST]]) -> 0 | R31: =IF(INVESTORS_LIST[[#This Row],[SIP_TOTAL UNITS SOLD]]=0,0,SUMIFS(SIP[Realized Gain],SIP[Investor ID],INVESTORS_LIST[[#This Row],[INVESTOR CODE]],SIP[B/S],"S")) -> 0 | S31: =INVESTORS_LIST[[#This Row],[LS_TOTAL UNITS BUY]]+INVESTORS_LIST[[#This Row],[SIP_TOTAL UNITS BUY]] -> 500000 | T31: =INVESTORS_LIST[[#This Row],[LS_TOTAL UNITS SOLD]]+INVESTORS_LIST[[#This Row],[SIP_TOTAL UNITS SOLD]] -> 0 | U31: 500000 | V31: =SUMIFS(LS[BO UNIT TRANSFER],LS[Investor ID],INVESTORS_LIST[[#This Row],[INVESTOR CODE]],LS[B/S],"B") -> 0 | W31: =SUMIFS(SIP[BO UNIT TRANSFER],SIP[Investor ID],INVESTORS_LIST[[#This Row],[INVESTOR CODE]],SIP[B/S],"B") -> 0 | X31: =SUMIFS(LS[BO UNIT TRANSFER],LS[Investor ID],INVESTORS_LIST[[#This Row],[INVESTOR CODE]],LS[B/S],"S") -> 0 | Y31: =SUMIFS(SIP[BO UNIT TRANSFER],SIP[Investor ID],INVESTORS_LIST[[#This Row],[INVESTOR CODE]],SIP[B/S],"S") -> 0 | Z31: =SUM(INVESTORS_LIST[[#This Row],[BO OPENING BALANCE]:[BO SIP UNITS REPURCHASE]]) -> 500000 | AA31: =INVESTORS_LIST[[#This Row],[TOTAL UNITS BUY]]-INVESTORS_LIST[[#This Row],[TOTAL UNITS SOLD]] -> 500000 | AB31: =INVESTORS_LIST[[#This Row],[TOTAL CURRENT UNITS]]-INVESTORS_LIST[[#This Row],[BO UNITS HOLD]] -> 0 | AC31: =INDEX([3]!Table_1[BO ID],MATCH(INVESTORS_LIST[[#This Row],[INVESTOR CODE]],[3]!Table_1[INVESTOR CODE],0)) -> #REF! | AD31: =INDEX([3]!Table_1[Brokerage Name2],MATCH(INVESTORS_LIST[[#This Row],[INVESTOR CODE]],[3]!Table_1[INVESTOR CODE],0)) -> #REF! | AE31: =MID(INVESTORS_LIST[[#This Row],[BO ID]],4,5) -> #REF! | AF31: =MID(INVESTORS_LIST[[#This Row],[BO ID]],2,7) -> #REF! | AG31: =MID(INVESTORS_LIST[[#This Row],[BO ID]],9,7) -> #REF! | AH31: =RIGHT(INVESTORS_LIST[[#This Row],[BO ID]],1) -> #REF! | AI31: =INVESTORS_LIST[[#This Row],[LS_TOTAL COST VALUE OF CURRENT UNITS]]+INVESTORS_LIST[[#This Row],[SIP_TOTAL COST VALUE OF CURRENT UNITS]] -> 5000000 | AJ31: =IF(INVESTORS_LIST[[#This Row],[TOTAL CURRENT UNITS]]=0,0,INVESTORS_LIST[[#This Row],[LS_TOTAL CURRENT UNITS]]/INVESTORS_LIST[[#This Row],[TOTAL CURRENT UNITS]]) -> 1 | AK31: =IF(INVESTORS_LIST[[#This Row],[TOTAL CURRENT UNITS]]=0,0,INVESTORS_LIST[[#This Row],[SIP_TOTAL CURRENT UNITS]]/INVESTORS_LIST[[#This Row],[TOTAL CURRENT UNITS]]) -> 0 | AL31: {=IF(INVESTORS_LIST[[#This Row],[LS_TOTAL UNITS BUY]]>0,INDEX(LS[NAV at Cost (Average)],MATCH(CONCATENATE(COUNTIFS(LS[Investor ID],INVESTORS_LIST[[#This Row],[INVESTOR CODE]]),INVESTORS_LIST[[#This Row],[INVESTOR CODE]]),LS[Unique Code],0),),0)} -> 10 | AM31: {=IF(INVESTORS_LIST[[#This Row],[SIP_TOTAL UNITS BUY]]>0,INDEX(SIP[NAV at Cost (Average)],MATCH(CONCATENATE(COUNTIFS(SIP[Investor ID],INVESTORS_LIST[[#This Row],[INVESTOR CODE]]),INVESTORS_LIST[[#This Row],[INVESTOR CODE]]),SIP[Unique Code],0),),0)} -> 0 | AN31: =IF(INVESTORS_LIST[[#This Row],[TOTAL CURRENT UNITS]]=0,0,(INVESTORS_LIST[[#This Row],[LS_WEIGHT]]*INVESTORS_LIST[[#This Row],[LS_AVERAGE COST]])+(INVESTORS_LIST[[#This Row],[SIP_WEIGHT]]*INVESTORS_LIST[[#This Row],[SIP_AVERAGE COST]])) -> 10 | AO31: =NAV_MKT -> 14.224 | AP31: =IF(INVESTORS_LIST[[#This Row],[TOTAL CURRENT UNITS]]=0,0,INVESTORS_LIST[[#This Row],[TOTAL CURRENT UNITS]]*INVESTORS_LIST[[#This Row],[NAV]]) -> 7112000 | AQ31: =IF(INVESTORS_LIST[[#This Row],[LS_TOTAL CURRENT UNITS]]=0,0,INVESTORS_LIST[[#This Row],[LS_TOTAL CURRENT UNITS]]*INVESTORS_LIST[[#This Row],[NAV]]) -> 7112000 | AR31: =IF(INVESTORS_LIST[[#This Row],[SIP_TOTAL CURRENT UNITS]]=0,0,INVESTORS_LIST[[#This Row],[SIP_TOTAL CURRENT UNITS]]*INVESTORS_LIST[[#This Row],[NAV]]) -> 0 | AS31: =INVESTORS_LIST[[#This Row],[TOTAL CURRENT UNITS]] -> 500000 | AT31: =IF(INVESTORS_LIST[[#This Row],[TOTAL SELLABLE UNITS]]=0,0,INVESTORS_LIST[[#This Row],[TOTAL SELLABLE UNITS]]*INVESTORS_LIST[[#This Row],[NAV]]) -> 7112000 | AU31: =INVESTORS_LIST[[#This Row],[LS_TOTAL REALIZED GAIN]]+INVESTORS_LIST[[#This Row],[SIP_TOTAL REALIZED GAIN]] -> 0 | AV31: =INVESTORS_LIST[[#This Row],[TOTAL MARKET VALUE]]-INVESTORS_LIST[[#This Row],[TOTAL COST VALUE OF CURRENT INVESTMENT]] -> 2112000 | AW31: =IFERROR(INVESTORS_LIST[[#This Row],[TOTAL CURRENT UNITS]]/SUM(INVESTORS_LIST[TOTAL CURRENT UNITS]),0) -> 0.012138104
A32: TANVIR AHMED SIDDIQUI | B32: A00032 | C32: Dear Mr. | D32: Individual | E32: =SUMIFS(LS[Unit],LS[Investor ID],INVESTORS_LIST[[#This Row],[INVESTOR CODE]],LS[B/S],"B") -> 23471 | F32: =-SUMIFS(LS[Unit],LS[Investor ID],INVESTORS_LIST[[#This Row],[INVESTOR CODE]],LS[B/S],"S") -> 23471 | G32: =IF(INVESTORS_LIST[[#This Row],[LS_TOTAL UNITS BUY]]=0,0,INVESTORS_LIST[[#This Row],[LS_TOTAL UNITS BUY]]-INVESTORS_LIST[[#This Row],[LS_TOTAL UNITS SOLD]]) -> 0 | H32: =IF(INVESTORS_LIST[[#This Row],[LS_TOTAL UNITS BUY]]=0,0,SUMIFS(LS[Amount],LS[Investor ID],INVESTORS_LIST[[#This Row],[INVESTOR CODE]],LS[B/S],"B")) -> 250000 | I32: =IF(INVESTORS_LIST[[#This Row],[LS_TOTAL UNITS SOLD]]=0,0,SUMIFS(LS[Cost of Units Sold],LS[Investor ID],INVESTORS_LIST[[#This Row],[INVESTOR CODE]],LS[B/S],"S")) -> 250000 | J32: =IF(INVESTORS_LIST[[#This Row],[LS_TOTAL CURRENT UNITS]]=0,0,INVESTORS_LIST[[#This Row],[LS_TOTAL CURRENT UNITS]]*INVESTORS_LIST[[#This Row],[LS_AVERAGE COST]]) -> 0 | K32: =IF(INVESTORS_LIST[[#This Row],[LS_TOTAL UNITS SOLD]]=0,0,SUMIFS(LS[Realized Gain],LS[Investor ID],INVESTORS_LIST[[#This Row],[INVESTOR CODE]],LS[B/S],"S")) -> 53198.38 | L32: =SUMIFS(SIP[Unit],SIP[Investor ID],INVESTORS_LIST[[#This Row],[INVESTOR CODE]],SIP[B/S],"B") -> 0 | M32: =-SUMIFS(SIP[Unit],SIP[Investor ID],INVESTORS_LIST[[#This Row],[INVESTOR CODE]],SIP[B/S],"S") -> 0 | N32: =IF(INVESTORS_LIST[[#This Row],[SIP_TOTAL UNITS BUY]]=0,0,INVESTORS_LIST[[#This Row],[SIP_TOTAL UNITS BUY]]-INVESTORS_LIST[[#This Row],[SIP_TOTAL UNITS SOLD]]) -> 0 | O32: =IF(INVESTORS_LIST[[#This Row],[SIP_TOTAL UNITS BUY]]=0,0,SUMIFS(SIP[Amount],SIP[Investor ID],INVESTORS_LIST[[#This Row],[INVESTOR CODE]],SIP[B/S],"B")) -> 0 | P32: =IF(INVESTORS_LIST[[#This Row],[SIP_TOTAL UNITS SOLD]]=0,0,SUMIFS(SIP[Cost of Units Sold],SIP[Investor ID],INVESTORS_LIST[[#This Row],[INVESTOR CODE]],SIP[B/S],"S")) -> 0 | Q32: =IF(INVESTORS_LIST[[#This Row],[SIP_TOTAL CURRENT UNITS]]=0,0,INVESTORS_LIST[[#This Row],[SIP_TOTAL CURRENT UNITS]]*INVESTORS_LIST[[#This Row],[SIP_AVERAGE COST]]) -> 0 | R32: =IF(INVESTORS_LIST[[#This Row],[SIP_TOTAL UNITS SOLD]]=0,0,SUMIFS(SIP[Realized Gain],SIP[Investor ID],INVESTORS_LIST[[#This Row],[INVESTOR CODE]],SIP[B/S],"S")) -> 0 | S32: =INVESTORS_LIST[[#This Row],[LS_TOTAL UNITS BUY]]+INVESTORS_LIST[[#This Row],[SIP_TOTAL UNITS BUY]] -> 23471 | T32: =INVESTORS_LIST[[#This Row],[LS_TOTAL UNITS SOLD]]+INVESTORS_LIST[[#This Row],[SIP_TOTAL UNITS SOLD]] -> 23471 | V32: =SUMIFS(LS[BO UNIT TRANSFER],LS[Investor ID],INVESTORS_LIST[[#This Row],[INVESTOR CODE]],LS[B/S],"B") -> 0 | W32: =SUMIFS(SIP[BO UNIT TRANSFER],SIP[Investor ID],INVESTORS_LIST[[#This Row],[INVESTOR CODE]],SIP[B/S],"B") -> 0 | X32: =SUMIFS(LS[BO UNIT TRANSFER],LS[Investor ID],INVESTORS_LIST[[#This Row],[INVESTOR CODE]],LS[B/S],"S") -> 0 | Y32: =SUMIFS(SIP[BO UNIT TRANSFER],SIP[Investor ID],INVESTORS_LIST[[#This Row],[INVESTOR CODE]],SIP[B/S],"S") -> 0 | Z32: =SUM(INVESTORS_LIST[[#This Row],[BO OPENING BALANCE]:[BO SIP UNITS REPURCHASE]]) -> 0 | AA32: =INVESTORS_LIST[[#This Row],[TOTAL UNITS BUY]]-INVESTORS_LIST[[#This Row],[TOTAL UNITS SOLD]] -> 0 | AB32: =INVESTORS_LIST[[#This Row],[TOTAL CURRENT UNITS]]-INVESTORS_LIST[[#This Row],[BO UNITS HOLD]] -> 0 | AC32: =INDEX([3]!Table_1[BO ID],MATCH(INVESTORS_LIST[[#This Row],[INVESTOR CODE]],[3]!Table_1[INVESTOR CODE],0)) -> #REF! | AD32: =INDEX([3]!Table_1[Brokerage Name2],MATCH(INVESTORS_LIST[[#This Row],[INVESTOR CODE]],[3]!Table_1[INVESTOR CODE],0)) -> #REF! | AE32: =MID(INVESTORS_LIST[[#This Row],[BO ID]],4,5) -> #REF! | AF32: =MID(INVESTORS_LIST[[#This Row],[BO ID]],2,7) -> #REF! | AG32: =MID(INVESTORS_LIST[[#This Row],[BO ID]],9,7) -> #REF! | AH32: =RIGHT(INVESTORS_LIST[[#This Row],[BO ID]],1) -> #REF! | AI32: =INVESTORS_LIST[[#This Row],[LS_TOTAL COST VALUE OF CURRENT UNITS]]+INVESTORS_LIST[[#This Row],[SIP_TOTAL COST VALUE OF CURRENT UNITS]] -> 0 | AJ32: =IF(INVESTORS_LIST[[#This Row],[TOTAL CURRENT UNITS]]=0,0,INVESTORS_LIST[[#This Row],[LS_TOTAL CURRENT UNITS]]/INVESTORS_LIST[[#This Row],[TOTAL CURRENT UNITS]]) -> 0 | AK32: =IF(INVESTORS_LIST[[#This Row],[TOTAL CURRENT UNITS]]=0,0,INVESTORS_LIST[[#This Row],[SIP_TOTAL CURRENT UNITS]]/INVESTORS_LIST[[#This Row],[TOTAL CURRENT UNITS]]) -> 0 | AL32: {=IF(INVESTORS_LIST[[#This Row],[LS_TOTAL UNITS BUY]]>0,INDEX(LS[NAV at Cost (Average)],MATCH(CONCATENATE(COUNTIFS(LS[Investor ID],INVESTORS_LIST[[#This Row],[INVESTOR CODE]]),INVESTORS_LIST[[#This Row],[INVESTOR CODE]]),LS[Unique Code],0),),0)} -> 0 | AM32: {=IF(INVESTORS_LIST[[#This Row],[SIP_TOTAL UNITS BUY]]>0,INDEX(SIP[NAV at Cost (Average)],MATCH(CONCATENATE(COUNTIFS(SIP[Investor ID],INVESTORS_LIST[[#This Row],[INVESTOR CODE]]),INVESTORS_LIST[[#This Row],[INVESTOR CODE]]),SIP[Unique Code],0),),0)} -> 0 | AN32: =IF(INVESTORS_LIST[[#This Row],[TOTAL CURRENT UNITS]]=0,0,(INVESTORS_LIST[[#This Row],[LS_WEIGHT]]*INVESTORS_LIST[[#This Row],[LS_AVERAGE COST]])+(INVESTORS_LIST[[#This Row],[SIP_WEIGHT]]*INVESTORS_LIST[[#This Row],[SIP_AVERAGE COST]])) -> 0 | AO32: =NAV_MKT -> 14.224 | AP32: =IF(INVESTORS_LIST[[#This Row],[TOTAL CURRENT UNITS]]=0,0,INVESTORS_LIST[[#This Row],[TOTAL CURRENT UNITS]]*INVESTORS_LIST[[#This Row],[NAV]]) -> 0 | AQ32: =IF(INVESTORS_LIST[[#This Row],[LS_TOTAL CURRENT UNITS]]=0,0,INVESTORS_LIST[[#This Row],[LS_TOTAL CURRENT UNITS]]*INVESTORS_LIST[[#This Row],[NAV]]) -> 0 | AR32: =IF(INVESTORS_LIST[[#This Row],[SIP_TOTAL CURRENT UNITS]]=0,0,INVESTORS_LIST[[#This Row],[SIP_TOTAL CURRENT UNITS]]*INVESTORS_LIST[[#This Row],[NAV]]) -> 0 | AS32: =INVESTORS_LIST[[#This Row],[TOTAL CURRENT UNITS]] -> 0 | AT32: =IF(INVESTORS_LIST[[#This Row],[TOTAL SELLABLE UNITS]]=0,0,INVESTORS_LIST[[#This Row],[TOTAL SELLABLE UNITS]]*INVESTORS_LIST[[#This Row],[NAV]]) -> 0 | AU32: =INVESTORS_LIST[[#This Row],[LS_TOTAL REALIZED GAIN]]+INVESTORS_LIST[[#This Row],[SIP_TOTAL REALIZED GAIN]] -> 53198.38 | AV32: =INVESTORS_LIST[[#This Row],[TOTAL MARKET VALUE]]-INVESTORS_LIST[[#This Row],[TOTAL COST VALUE OF CURRENT INVESTMENT]] -> 0 | AW32: =IFERROR(INVESTORS_LIST[[#This Row],[TOTAL CURRENT UNITS]]/SUM(INVESTORS_LIST[TOTAL CURRENT UNITS]),0) -> 0
A33: MOHAMMED SELIM | B33: A00033 | C33: Dear Mr. | D33: Individual | E33: =SUMIFS(LS[Unit],LS[Investor ID],INVESTORS_LIST[[#This Row],[INVESTOR CODE]],LS[B/S],"B") -> 0 | F33: =-SUMIFS(LS[Unit],LS[Investor ID],INVESTORS_LIST[[#This Row],[INVESTOR CODE]],LS[B/S],"S") -> 0 | G33: =IF(INVESTORS_LIST[[#This Row],[LS_TOTAL UNITS BUY]]=0,0,INVESTORS_LIST[[#This Row],[LS_TOTAL UNITS BUY]]-INVESTORS_LIST[[#This Row],[LS_TOTAL UNITS SOLD]]) -> 0 | H33: =IF(INVESTORS_LIST[[#This Row],[LS_TOTAL UNITS BUY]]=0,0,SUMIFS(LS[Amount],LS[Investor ID],INVESTORS_LIST[[#This Row],[INVESTOR CODE]],LS[B/S],"B")) -> 0 | I33: =IF(INVESTORS_LIST[[#This Row],[LS_TOTAL UNITS SOLD]]=0,0,SUMIFS(LS[Cost of Units Sold],LS[Investor ID],INVESTORS_LIST[[#This Row],[INVESTOR CODE]],LS[B/S],"S")) -> 0 | J33: =IF(INVESTORS_LIST[[#This Row],[LS_TOTAL CURRENT UNITS]]=0,0,INVESTORS_LIST[[#This Row],[LS_TOTAL CURRENT UNITS]]*INVESTORS_LIST[[#This Row],[LS_AVERAGE COST]]) -> 0 | K33: =IF(INVESTORS_LIST[[#This Row],[LS_TOTAL UNITS SOLD]]=0,0,SUMIFS(LS[Realized Gain],LS[Investor ID],INVESTORS_LIST[[#This Row],[INVESTOR CODE]],LS[B/S],"S")) -> 0 | L33: =SUMIFS(SIP[Unit],SIP[Investor ID],INVESTORS_LIST[[#This Row],[INVESTOR CODE]],SIP[B/S],"B") -> 970 | M33: =-SUMIFS(SIP[Unit],SIP[Investor ID],INVESTORS_LIST[[#This Row],[INVESTOR CODE]],SIP[B/S],"S") -> 970 | N33: =IF(INVESTORS_LIST[[#This Row],[SIP_TOTAL UNITS BUY]]=0,0,INVESTORS_LIST[[#This Row],[SIP_TOTAL UNITS BUY]]-INVESTORS_LIST[[#This Row],[SIP_TOTAL UNITS SOLD]]) -> 0 | O33: =IF(INVESTORS_LIST[[#This Row],[SIP_TOTAL UNITS BUY]]=0,0,SUMIFS(SIP[Amount],SIP[Investor ID],INVESTORS_LIST[[#This Row],[INVESTOR CODE]],SIP[B/S],"B")) -> 10000 | P33: =IF(INVESTORS_LIST[[#This Row],[SIP_TOTAL UNITS SOLD]]=0,0,SUMIFS(SIP[Cost of Units Sold],SIP[Investor ID],INVESTORS_LIST[[#This Row],[INVESTOR CODE]],SIP[B/S],"S")) -> 10000 | Q33: =IF(INVESTORS_LIST[[#This Row],[SIP_TOTAL CURRENT UNITS]]=0,0,INVESTORS_LIST[[#This Row],[SIP_TOTAL CURRENT UNITS]]*INVESTORS_LIST[[#This Row],[SIP_AVERAGE COST]]) -> 0 | R33: =IF(INVESTORS_LIST[[#This Row],[SIP_TOTAL UNITS SOLD]]=0,0,SUMIFS(SIP[Realized Gain],SIP[Investor ID],INVESTORS_LIST[[#This Row],[INVESTOR CODE]],SIP[B/S],"S")) -> 20.97 | S33: =INVESTORS_LIST[[#This Row],[LS_TOTAL UNITS BUY]]+INVESTORS_LIST[[#This Row],[SIP_TOTAL UNITS BUY]] -> 970 | T33: =INVESTORS_LIST[[#This Row],[LS_TOTAL UNITS SOLD]]+INVESTORS_LIST[[#This Row],[SIP_TOTAL UNITS SOLD]] -> 970 | V33: =SUMIFS(LS[BO UNIT TRANSFER],LS[Investor ID],INVESTORS_LIST[[#This Row],[INVESTOR CODE]],LS[B/S],"B") -> 0 | W33: =SUMIFS(SIP[BO UNIT TRANSFER],SIP[Investor ID],INVESTORS_LIST[[#This Row],[INVESTOR CODE]],SIP[B/S],"B") -> 0 | X33: =SUMIFS(LS[BO UNIT TRANSFER],LS[Investor ID],INVESTORS_LIST[[#This Row],[INVESTOR CODE]],LS[B/S],"S") -> 0 | Y33: =SUMIFS(SIP[BO UNIT TRANSFER],SIP[Investor ID],INVESTORS_LIST[[#This Row],[INVESTOR CODE]],SIP[B/S],"S") -> 0 | Z33: =SUM(INVESTORS_LIST[[#This Row],[BO OPENING BALANCE]:[BO SIP UNITS REPURCHASE]]) -> 0 | AA33: =INVESTORS_LIST[[#This Row],[TOTAL UNITS BUY]]-INVESTORS_LIST[[#This Row],[TOTAL UNITS SOLD]] -> 0 | AB33: =INVESTORS_LIST[[#This Row],[TOTAL CURRENT UNITS]]-INVESTORS_LIST[[#This Row],[BO UNITS HOLD]] -> 0 | AC33: =INDEX([3]!Table_1[BO ID],MATCH(INVESTORS_LIST[[#This Row],[INVESTOR CODE]],[3]!Table_1[INVESTOR CODE],0)) -> #REF! | AD33: =INDEX([3]!Table_1[Brokerage Name2],MATCH(INVESTORS_LIST[[#This Row],[INVESTOR CODE]],[3]!Table_1[INVESTOR CODE],0)) -> #REF! | AE33: =MID(INVESTORS_LIST[[#This Row],[BO ID]],4,5) -> #REF! | AF33: =MID(INVESTORS_LIST[[#This Row],[BO ID]],2,7) -> #REF! | AG33: =MID(INVESTORS_LIST[[#This Row],[BO ID]],9,7) -> #REF! | AH33: =RIGHT(INVESTORS_LIST[[#This Row],[BO ID]],1) -> #REF! | AI33: =INVESTORS_LIST[[#This Row],[LS_TOTAL COST VALUE OF CURRENT UNITS]]+INVESTORS_LIST[[#This Row],[SIP_TOTAL COST VALUE OF CURRENT UNITS]] -> 0 | AJ33: =IF(INVESTORS_LIST[[#This Row],[TOTAL CURRENT UNITS]]=0,0,INVESTORS_LIST[[#This Row],[LS_TOTAL CURRENT UNITS]]/INVESTORS_LIST[[#This Row],[TOTAL CURRENT UNITS]]) -> 0 | AK33: =IF(INVESTORS_LIST[[#This Row],[TOTAL CURRENT UNITS]]=0,0,INVESTORS_LIST[[#This Row],[SIP_TOTAL CURRENT UNITS]]/INVESTORS_LIST[[#This Row],[TOTAL CURRENT UNITS]]) -> 0 | AL33: {=IF(INVESTORS_LIST[[#This Row],[LS_TOTAL UNITS BUY]]>0,INDEX(LS[NAV at Cost (Average)],MATCH(CONCATENATE(COUNTIFS(LS[Investor ID],INVESTORS_LIST[[#This Row],[INVESTOR CODE]]),INVESTORS_LIST[[#This Row],[INVESTOR CODE]]),LS[Unique Code],0),),0)} -> 0 | AM33: {=IF(INVESTORS_LIST[[#This Row],[SIP_TOTAL UNITS BUY]]>0,INDEX(SIP[NAV at Cost (Average)],MATCH(CONCATENATE(COUNTIFS(SIP[Investor ID],INVESTORS_LIST[[#This Row],[INVESTOR CODE]]),INVESTORS_LIST[[#This Row],[INVESTOR CODE]]),SIP[Unique Code],0),),0)} -> 0 | AN33: =IF(INVESTORS_LIST[[#This Row],[TOTAL CURRENT UNITS]]=0,0,(INVESTORS_LIST[[#This Row],[LS_WEIGHT]]*INVESTORS_LIST[[#This Row],[LS_AVERAGE COST]])+(INVESTORS_LIST[[#This Row],[SIP_WEIGHT]]*INVESTORS_LIST[[#This Row],[SIP_AVERAGE COST]])) -> 0 | AO33: =NAV_MKT -> 14.224 | AP33: =IF(INVESTORS_LIST[[#This Row],[TOTAL CURRENT UNITS]]=0,0,INVESTORS_LIST[[#This Row],[TOTAL CURRENT UNITS]]*INVESTORS_LIST[[#This Row],[NAV]]) -> 0 | AQ33: =IF(INVESTORS_LIST[[#This Row],[LS_TOTAL CURRENT UNITS]]=0,0,INVESTORS_LIST[[#This Row],[LS_TOTAL CURRENT UNITS]]*INVESTORS_LIST[[#This Row],[NAV]]) -> 0 | AR33: =IF(INVESTORS_LIST[[#This Row],[SIP_TOTAL CURRENT UNITS]]=0,0,INVESTORS_LIST[[#This Row],[SIP_TOTAL CURRENT UNITS]]*INVESTORS_LIST[[#This Row],[NAV]]) -> 0 | AS33: =INVESTORS_LIST[[#This Row],[TOTAL CURRENT UNITS]] -> 0 | AT33: =IF(INVESTORS_LIST[[#This Row],[TOTAL SELLABLE UNITS]]=0,0,INVESTORS_LIST[[#This Row],[TOTAL SELLABLE UNITS]]*INVESTORS_LIST[[#This Row],[NAV]]) -> 0 | AU33: =INVESTORS_LIST[[#This Row],[LS_TOTAL REALIZED GAIN]]+INVESTORS_LIST[[#This Row],[SIP_TOTAL REALIZED GAIN]] -> 20.97 | AV33: =INVESTORS_LIST[[#This Row],[TOTAL MARKET VALUE]]-INVESTORS_LIST[[#This Row],[TOTAL COST VALUE OF CURRENT INVESTMENT]] -> 0 | AW33: =IFERROR(INVESTORS_LIST[[#This Row],[TOTAL CURRENT UNITS]]/SUM(INVESTORS_LIST[TOTAL CURRENT UNITS]),0) -> 0
