Workbook
Name CURRENT_NAV: BS!$C$46
Name fsa: Journals!$T$1
Name NAV: BS!$C$44
Name NAV_MKT: Journals!$T$1
Name TCV_STOCKS: #REF!
Name TMV_STOCKS: #REF!

Sheet Chart of Accounts
B2: Accounts Name | C2: Normal Balance | E2: Stock List
B3: Investments in stock | C3: DEBIT | E3: =#REF! -> #REF!
B4: Interest Receivables from Bank A/C | C4: DEBIT | E4: =#REF! -> #REF!
B5: Preliminary & issue expenses | C5: DEBIT | E5: =#REF! -> #REF!
B6: Accrued Management Fee | C6: CREDIT | E6: =#REF! -> #REF!
B7: Accrued Trustee Fee | C7: CREDIT | E7: =#REF! -> #REF!
B8: Accrued Custodian Fee | C8: CREDIT | E8: =#REF! -> #REF!
B9: Accrued BSEC fee | C9: CREDIT | E9: =#REF! -> #REF!
B10: Accrued Audit Fee | C10: CREDIT | E10: =#REF! -> #REF!
B11: Accrued CDBL Fee | C11: CREDIT | E11: =#REF! -> #REF!
B12: Fixed Deposit Receipts (FDR) | C12: DEBIT | E12: =#REF! -> #REF!
B13: Cash and cash equivalents | C13: DEBIT | E13: =#REF! -> #REF!
B14: Unit Capital | C14: CREDIT | E14: =#REF! -> #REF!
... B16: Interest income | C16: CREDIT | E16: =#REF! -> #REF!
B17: Interest income from BXSUKUK
B18: Interest income from APSCL
B19: Interest income from Bank Asia Bond
B20: Interest income from BRAC Bank Bond
B21: Interest income from Bank Acc.
B22: Interest income from FDR
B23: Interest income reduce for Bond Premium | C23: CREDIT
B24: Bank charges and excise duties | C24: DEBIT | E24: =#REF! -> #REF!
B25: Brokerage commission | C25: DEBIT | E25: =#REF! -> #REF!
B26: Unrealized gain on securities | C26: CREDIT | E26: =#REF! -> #REF!
B27: Unrealized gain on T-Bill
B28: Unrealized gain on T-Bond
B29: Unrealized loss on securities | C29: DEBIT | E29: =#REF! -> #REF!
B30: Amortization of preliminary and issue expense | C30: DEBIT | E30: =#REF! -> #REF!
B31: Management Fee | C31: DEBIT | E31: =#REF! -> #REF!
B32: Trustee fee | C32: DEBIT | E32: =#REF! -> #REF!
B33: BSEC Annual Fee | C33: DEBIT | E33: =#REF! -> #REF!
B34: Audit fee | C34: DEBIT | E34: =#REF! -> #REF!
B35: CDBL charges | C35: DEBIT | E35: =#REF! -> #REF!
B36: Fair value adjustment | C36: DEBIT | E36: =#REF! -> #REF!
B37: Fair value adjustment in T-Bill
B38: Fair value adjustment in T-Bond
B39: Interest receivables from FDR | C39: DEBIT | E39: =#REF! -> #REF!
B40: Payable to broker | C40: CREDIT | E40: =#REF! -> #REF!
B41: Other operating expenses | C41: DEBIT | E41: =#REF! -> #REF!
B42: Dividend income | C42: CREDIT | E42: =#REF! -> #REF!
B43: Dividend receivable | C43: DEBIT | E43: =#REF! -> #REF!
B44: Custodian fee | C44: DEBIT | E44: =#REF! -> #REF!
B45: IPO Application | C45: DEBIT | E45: =#REF! -> #REF!
B46: IPO Application Fee | C46: DEBIT | E46: =#REF! -> #REF!
B47: Receivable from broker | C47: DEBIT | E47: =#REF! -> #REF!
B48: Realized gain | C48: CREDIT | E48: =#REF! -> #REF!
B49: Realized gain from Bond Premium
B50: Realized gain on T-Bill
B51: Realized gain on T-Bond
B52: Other Income | C52: CREDIT | E52: =#REF! -> #REF!
B53: Dividend Equalization Reserve | C53: CREDIT | E53: =#REF! -> #REF!
B54: Retained Earnings | E54: =#REF! -> #REF!
B55: Dividend Payable | C55: CREDIT | E55: =#REF! -> #REF!
B56: Withholding Tax Payable | C56: CREDIT | E56: =#REF! -> #REF!
B57: Realized Loss | E57: =#REF! -> #REF!
B58: Investments in Bond (BXSUKUK) | C58: DEBIT | E58: =#REF! -> #REF!
B59: Investments in Bond (APSCL) | C59: DEBIT
B60: Bond Premium | C60: DEBIT | E60: =#REF! -> #REF!
B61: Redemption Receivable | C61: DEBIT | E61: =#REF! -> #REF!
B62: Redemption of Investment | C62: CREDIT | E62: =#REF! -> #REF!
B63: Interest Receivables from Bond | C63: DEBIT | E63: =#REF! -> #REF!
B64: Interest Receivables from SUKUK
B65: Investments in T-Bond (Contract) | C65: DEBIT | E65: =#REF! -> #REF!
B66: Interest Receivables from T.Bond (Contract) | C66: DEBIT | E66: =#REF! -> #REF!
B67: Preliminary and issue expense (Liability) | C67: CREDIT | E67: =#REF! -> #REF!
B68: Investments in T-Bill | E68: =#REF! -> #REF!
B69: Interest Receivables from T-Bill | E69: =#REF! -> #REF!
B70: Investments in T-Bond | E70: =#REF! -> #REF!
B71: Investments in BRAC Bank 2nd Subordinated Bond | E71: =#REF! -> #REF!
B72: Interest Receivables from BRAC Bank Bond | E72: =#REF! -> #REF!
B73: Investments in Bank Asia 4th Subordinated Bond | E73: =#REF! -> #REF!
B74: Interest Receivables from Bank Asia Bond | E74: =#REF! -> #REF!
E75: =#REF! -> #REF!
E76: =#REF! -> #REF!
E77: =#REF! -> #REF!
E78: =#REF! -> #REF!
E79: =#REF! -> #REF!
E80: =#REF! -> #REF!
E81: =#REF! -> #REF!
E82: =#REF! -> #REF!
E83: =#REF! -> #REF!
E84: =#REF! -> #REF!
E85: =#REF! -> #REF!
E86: =#REF! -> #REF!
... E599: =#REF! -> #REF!

Sheet INVESTOR_LIST
A1: INVESTOR NAME | B1: INVESTOR CODE
A2: HARI PADA SAHA | B2: A00002
A3: EKUSH WEALTH MANAGEMENT LIMITED | B3: A00003
A4: SADIA AHMED | B4: A00004
A5: MORSHEDA MIM | B5: A00005
A6: MD. JAHANGIR ALAM | B6: A00006
A7: BISWAS ARIFUR RAHMAN | B7: A00007
A8: JEWEL SAHA | B8: A00008
A9: SHIBBIR AHMED | B9: A00009
A10: SHYAMAL KRISHNA SAHA | B10: A00010
A11: NASRIN AKHTER | B11: A00011
A12: MRINMOY GHOSH | B12: A00012
... A562: JAKARIA MD. JONY | B562: A00559

Sheet Journals
A2: Check of Journal Entries | G2: =K6-L6 -> -0.0033416748
A3: Check of Trial Balance | G3: =SUM('TB-C'!H7:H5021)-SUM('TB-C'!I7:I5021) -> -0.0072669387
A4: Check of Balance Seet | G4: =BS!C25-BS!C42 -> -0.0033406019
A5: Check of Cash Balance | G5: =BS!C23-CF!B43 -> 94994187
J6: =ROUND(L6-K6,0) -> 0 | K6: =SUBTOTAL(9,K9:K18768) -> 6.3668025e+09 | L6: =SUBTOTAL(9,L9:L18768) -> 6.3668025e+09
A7: Year | B7: Month | C7: Day | D7: Value | F7: Transaction | G7: Transaction Type | J7: Account Name | K7: Debit | L7: Credit | N7: Ref. Acc.
E8: Date
A9: 2022 | B9: 9 | C9: 7 | D9: =DATE(A9,B9,C9) -> 44811 | E9: =DATE(A9,B9,C9) -> 44811 | F9: Unit Subscription - LUMPSUM | G9: C | I9: A00003 | J9: Cash and cash equivalents | K9: 2000
A10: 2022 | B10: 9 | C10: 7 | D10: =DATE(A10,B10,C10) -> 44811 | E10: =DATE(A10,B10,C10) -> 44811 | G10: C | I10: A00003 | J10: Unit Capital | L10: 2000
A11: 2022 | B11: 10 | C11: 31 | D11: =DATE(A11,B11,C11) -> 44865 | E11: =DATE(A11,B11,C11) -> 44865 | F11: Bank Charges - Cheque Book Issue | G11: C | J11: Bank charges and excise duties | K11: 201.25
A12: 2022 | B12: 10 | C12: 31 | D12: =DATE(A12,B12,C12) -> 44865 | E12: =DATE(A12,B12,C12) -> 44865 | G12: C | J12: Cash and cash equivalents | L12: 201.25
A13: 2022 | B13: 11 | C13: 1 | D13: =DATE(A13,B13,C13) -> 44866 | E13: =DATE(A13,B13,C13) -> 44866 | F13: Unit Subscription - LUMPSUM | G13: C | I13: A00003 | J13: Cash and cash equivalents | K13: 25000000
A14: 2022 | B14: 11 | C14: 1 | D14: =DATE(A14,B14,C14) -> 44866 | E14: =DATE(A14,B14,C14) -> 44866 | G14: C | I14: A00003 | J14: Unit Capital | L14: 25000000
A15: 2022 | B15: 12 | C15: 29 | D15: =DATE(A15,B15,C15) -> 44924 | E15: =DATE(A15,B15,C15) -> 44924 | F15: Interest Income - Midland Bank | G15: C | J15: Cash and cash equivalents | K15: 129176
A16: 2022 | B16: 12 | C16: 29 | D16: =DATE(A16,B16,C16) -> 44924 | E16: =DATE(A16,B16,C16) -> 44924 | G16: C | J16: Interest income | L16: 129176
A17: 2022 | B17: 10 | C17: 31 | D17: =DATE(A17,B17,C17) -> 44865 | E17: =DATE(A17,B17,C17) -> 44865 | F17: Bank Charges - Source Tax Source Tax | G17: C | J17: Bank charges and excise duties | K17: 12917.64
A18: 2022 | B18: 10 | C18: 31 | D18: =DATE(A18,B18,C18) -> 44865 | E18: =DATE(A18,B18,C18) -> 44865 | G18: C | J18: Cash and cash equivalents | L18: 12917.64
A19: 2022 | B19: 10 | C19: 31 | D19: =DATE(A19,B19,C19) -> 44865 | E19: =DATE(A19,B19,C19) -> 44865 | F19: Bank Charges - Service Charge | G19: C | J19: Bank charges and excise duties | K19: 575
A20: 2022 | B20: 10 | C20: 31 | D20: =DATE(A20,B20,C20) -> 44865 | E20: =DATE(A20,B20,C20) -> 44865 | G20: C | J20: Cash and cash equivalents | L20: 575
A21: 2022 | B21: 10 | C21: 31 | D21: =DATE(A21,B21,C21) -> 44865 | E21: =DATE(A21,B21,C21) -> 44865 | F21: Bank Charges - Excise Duty | G21: C | J21: Bank charges and excise duties | K21: 15000
A22: 2022 | B22: 10 | C22: 31 | D22: =DATE(A22,B22,C22) -> 44865 | E22: =DATE(A22,B22,C22) -> 44865 | G22: C | J22: Cash and cash equivalents | L22: 15000
A23: 2023 | B23: 1 | C23: 16 | D23: =DATE(A23,B23,C23) -> 44942 | E23: =DATE(A23,B23,C23) -> 44942 | F23: Unit Subscription - LUMPSUM | G23: C | I23: A00018 | J23: Cash and cash equivalents | K23: 800000
A24: 2023 | B24: 1 | C24: 16 | D24: =DATE(A24,B24,C24) -> 44942 | E24: =DATE(A24,B24,C24) -> 44942 | G24: C | I24: A00018 | J24: Unit Capital | L24: 800000
A25: 2023 | B25: 1 | C25: 16 | D25: =DATE(A25,B25,C25) -> 44942 | E25: =DATE(A25,B25,C25) -> 44942 | F25: Bank Charges - Clearing Charge | G25: C | J25: Bank charges and excise duties | K25: 25
A26: 2023 | B26: 1 | C26: 16 | D26: =DATE(A26,B26,C26) -> 44942 | E26: =DATE(A26,B26,C26) -> 44942 | G26: C | J26: Cash and cash equivalents | L26: 25
A27: 2023 | B27: 1 | C27: 17 | D27: =DATE(A27,B27,C27) -> 44943 | E27: =DATE(A27,B27,C27) -> 44943 | F27: Unit Subscription - LUMPSUM | G27: C | I27: A00327 | J27: Cash and cash equivalents | K27: 500000
A28: 2023 | B28: 1 | C28: 17 | D28: =DATE(A28,B28,C28) -> 44943 | E28: =DATE(A28,B28,C28) -> 44943 | G28: C | I28: A00327 | J28: Unit Capital | L28: 500000
A29: 2023 | B29: 1 | C29: 17 | D29: =DATE(A29,B29,C29) -> 44943 | E29: =DATE(A29,B29,C29) -> 44943 | F29: Bank Charges - Clearing Charge | G29: C | J29: Bank charges and excise duties | K29: 60
A30: 2023 | B30: 1 | C30: 17 | D30: =DATE(A30,B30,C30) -> 44943 | E30: =DATE(A30,B30,C30) -> 44943 | G30: C | J30: Cash and cash equivalents | L30: 60
A31: 2023 | B31: 1 | C31: 19 | D31: =DATE(A31,B31,C31) -> 44945 | E31: =DATE(A31,B31,C31) -> 44945 | F31: Unit Subscription - LUMPSUM | G31: C | I31: A00444 | J31: Cash and cash equivalents | K31: 200000
A32: 2023 | B32: 1 | C32: 19 | D32: =DATE(A32,B32,C32) -> 44945 | E32: =DATE(A32,B32,C32) -> 44945 | G32: C | I32: A00444 | J32: Unit Capital | L32: 200000
A33: 2023 | B33: 1 | C33: 25 | D33: =DATE(A33,B33,C33) -> 44951 | E33: =DATE(A33,B33,C33) -> 44951 | F33: Unit Subscription - LUMPSUM | G33: C | I33: A00022 | J33: Cash and cash equivalents | K33: 850000
A34: 2023 | B34: 1 | C34: 25 | D34: =DATE(A34,B34,C34) -> 44951 | E34: =DATE(A34,B34,C34) -> 44951 | G34: C | I34: A00022 | J34: Unit Capital | L34: 850000
A35: 2023 | B35: 1 | C35: 25 | D35: =DATE(A35,B35,C35) -> 44951 | E35: =DATE(A35,B35,C35) -> 44951 | F35: Bank Charges - Clearing Charge | G35: C | J35: Bank charges and excise duties | K35: 60
A36: 2023 | B36: 1 | C36: 25 | D36: =DATE(A36,B36,C36) -> 44951 | E36: =DATE(A36,B36,C36) -> 44951 | G36: C | J36: Cash and cash equivalents | L36: 60
A37: 2023 | B37: 1 | C37: 26 | D37: =DATE(A37,B37,C37) -> 44952 | E37: =DATE(A37,B37,C37) -> 44952 | F37: Unit Subscription - LUMPSUM | G37: C | I37: A00252 | J37: Cash and cash equivalents | K37: 700000
A38: 2023 | B38: 1 | C38: 26 | D38: =DATE(A38,B38,C38) -> 44952 | E38: =DATE(A38,B38,C38) -> 44952 | G38: C | I38: A00252 | J38: Unit Capital | L38: 700000
A39: 2023 | B39: 2 | C39: 5 | D39: =DATE(A39,B39,C39) -> 44962 | E39: =DATE(A39,B39,C39) -> 44962 | F39: Unit Subscription - LUMPSUM | G39: C | I39: A00170 | J39: Cash and cash equivalents | K39: 800000
A40: 2023 | B40: 2 | C40: 5 | D40: =DATE(A40,B40,C40) -> 44962 | E40: =DATE(A40,B40,C40) -> 44962 | G40: C | I40: A00170 | J40: Unit Capital | L40: 800000
A41: 2023 | B41: 2 | C41: 5 | D41: =DATE(A41,B41,C41) -> 44962 | E41: =DATE(A41,B41,C41) -> 44962 | F41: Bank Charges - Clearing Charge | G41: C | J41: Bank charges and excise duties | K41: 25
A42: 2023 | B42: 2 | C42: 5 | D42: =DATE(A42,B42,C42) -> 44962 | E42: =DATE(A42,B42,C42) -> 44962 | G42: C | J42: Cash and cash equivalents | L42: 25
A43: 2023 | B43: 2 | C43: 7 | D43: =DATE(A43,B43,C43) -> 44964 | E43: =DATE(A43,B43,C43) -> 44964 | F43: Unit Subscription - LUMPSUM | G43: C | I43: A00445 | J43: Cash and cash equivalents | K43: 100000
A44: 2023 | B44: 2 | C44: 7 | D44: =DATE(A44,B44,C44) -> 44964 | E44: =DATE(A44,B44,C44) -> 44964 | G44: C | I44: A00445 | J44: Unit Capital | L44: 100000
A45: 2023 | B45: 2 | C45: 7 | D45: =DATE(A45,B45,C45) -> 44964 | E45: =DATE(A45,B45,C45) -> 44964 | F45: Unit Subscription - LUMPSUM | G45: C | I45: A00150 | J45: Cash and cash equivalents | K45: 100000
A46: 2023 | B46: 2 | C46: 7 | D46: =DATE(A46,B46,C46) -> 44964 | E46: =DATE(A46,B46,C46) -> 44964 | G46: C | I46: A00150 | J46: Unit Capital | L46: 100000
A47: 2023 | B47: 2 | C47: 7 | D47: =DATE(A47,B47,C47) -> 44964 | E47: =DATE(A47,B47,C47) -> 44964 | F47: Bank Charges - Clearing Charge | G47: C | J47: Bank charges and excise duties | K47: 10
A48: 2023 | B48: 2 | C48: 7 | D48: =DATE(A48,B48,C48) -> 44964 | E48: =DATE(A48,B48,C48) -> 44964 | G48: C | J48: Cash and cash equivalents | L48: 10
A49: 2023 | B49: 2 | C49: 8 | D49: =DATE(A49,B49,C49) -> 44965 | E49: =DATE(A49,B49,C49) -> 44965 | F49: Unit Subscription - LUMPSUM | G49: C | I49: A00447 | J49: Cash and cash equivalents | K49: 200000
A50: 2023 | B50: 2 | C50: 8 | D50: =DATE(A50,B50,C50) -> 44965 | E50: =DATE(A50,B50,C50) -> 44965 | G50: C | I50: A00447 | J50: Unit Capital | L50: 200000
A51: 2023 | B51: 2 | C51: 9 | D51: =DATE(A51,B51,C51) -> 44966 | E51: =DATE(A51,B51,C51) -> 44966 | F51: Unit Subscription - LUMPSUM | G51: C | I51: A00231 | J51: Cash and cash equivalents | K51: 1000000
A52: 2023 | B52: 2 | C52: 9 | D52: =DATE(A52,B52,C52) -> 44966 | E52: =DATE(A52,B52,C52) -> 44966 | G52: C | I52: A00231 | J52: Unit Capital | L52: 1000000
A53: 2023 | B53: 2 | C53: 9 | D53: =DATE(A53,B53,C53) -> 44966 | E53: =DATE(A53,B53,C53) -> 44966 | F53: Bank Charges - Clearing Charge | G53: C | J53: Bank charges and excise duties | K53: 25
A54: 2023 | B54: 2 | C54: 9 | D54: =DATE(A54,B54,C54) -> 44966 | E54: =DATE(A54,B54,C54) -> 44966 | G54: C | J54: Cash and cash equivalents | L54: 25
A55: 2023 | B55: 2 | C55: 12 | D55: =DATE(A55,B55,C55) -> 44969 | E55: =DATE(A55,B55,C55) -> 44969 | F55: Unit Subscription - LUMPSUM | G55: C | I55: A00448 | J55: Cash and cash equivalents | K55: 1500000
A56: 2023 | B56: 2 | C56: 12 | D56: =DATE(A56,B56,C56) -> 44969 | E56: =DATE(A56,B56,C56) -> 44969 | G56: C | I56: A00448 | J56: Unit Capital | L56: 1500000
A57: 2023 | B57: 2 | C57: 12 | D57: =DATE(A57,B57,C57) -> 44969 | E57: =DATE(A57,B57,C57) -> 44969 | F57: Bank Charges - Clearing Charge | G57: C | J57: Bank charges and excise duties | K57: 50
A58: 2023 | B58: 2 | C58: 12 | D58: =DATE(A58,B58,C58) -> 44969 | E58: =DATE(A58,B58,C58) -> 44969 | G58: C | J58: Cash and cash equivalents | L58: 50
A59: 2023 | B59: 2 | C59: 14 | D59: =DATE(A59,B59,C59) -> 44971 | E59: =DATE(A59,B59,C59) -> 44971 | F59: Unit Subscription - LUMPSUM | G59: C | I59: A00456 | J59: Cash and cash equivalents | K59: 50000
A60: 2023 | B60: 2 | C60: 14 | D60: =DATE(A60,B60,C60) -> 44971 | E60: =DATE(A60,B60,C60) -> 44971 | G60: C | I60: A00456 | J60: Unit Capital | L60: 50000
A61: 2023 | B61: 2 | C61: 14 | D61: =DATE(A61,B61,C61) -> 44971 | E61: =DATE(A61,B61,C61) -> 44971 | F61: Unit Subscription - LUMPSUM | G61: C | I61: A00456 | J61: Cash and cash equivalents | K61: 20000
A62: 2023 | B62: 2 | C62: 14 | D62: =DATE(A62,B62,C62) -> 44971 | E62: =DATE(A62,B62,C62) -> 44971 | G62: C | I62: A00456 | J62: Unit Capital | L62: 20000
A63: 2023 | B63: 2 | C63: 15 | D63: =DATE(A63,B63,C63) -> 44972 | E63: =DATE(A63,B63,C63) -> 44972 | F63: Unit Subscription - LUMPSUM | G63: C | I63: A00449 | J63: Cash and cash equivalents | K63: 10000000
A64: 2023 | B64: 2 | C64: 15 | D64: =DATE(A64,B64,C64) -> 44972 | E64: =DATE(A64,B64,C64) -> 44972 | G64: C | I64: A00449 | J64: Unit Capital | L64: 10000000
A65: 2023 | B65: 2 | C65: 15 | D65: =DATE(A65,B65,C65) -> 44972 | E65: =DATE(A65,B65,C65) -> 44972 | F65: Unit Subscription - LUMPSUM | G65: C | I65: A00450 | J65: Cash and cash equivalents | K65: 500000
A66: 2023 | B66: 2 | C66: 15 | D66: =DATE(A66,B66,C66) -> 44972 | E66: =DATE(A66,B66,C66) -> 44972 | G66: C | I66: A00450 | J66: Unit Capital | L66: 500000
A67: 2023 | B67: 2 | C67: 15 | D67: =DATE(A67,B67,C67) -> 44972 | E67: =DATE(A67,B67,C67) -> 44972 | F67: Bank Charges - Clearing Charge | G67: C | J67: Bank charges and excise duties | K67: 120
A68: 2023 | B68: 2 | C68: 15 | D68: =DATE(A68,B68,C68) -> 44972 | E68: =DATE(A68,B68,C68) -> 44972 | G68: C | J68: Cash and cash equivalents | L68: 120
A69: 2023 | B69: 2 | C69: 16 | D69: =DATE(A69,B69,C69) -> 44973 | E69: =DATE(A69,B69,C69) -> 44973 | F69: Unit Subscription - LUMPSUM | G69: C | I69: A00125 | J69: Cash and cash equivalents | K69: 400000
A70: 2023 | B70: 2 | C70: 16 | D70: =DATE(A70,B70,C70) -> 44973 | E70: =DATE(A70,B70,C70) -> 44973 | G70: C | I70: A00125 | J70: Unit Capital | L70: 400000
A71: 2023 | B71: 2 | C71: 16 | D71: =DATE(A71,B71,C71) -> 44973 | E71: =DATE(A71,B71,C71) -> 44973 | F71: Bank Charges - Clearing Charge | G71: C | J71: Bank charges and excise duties | K71: 10
A72: 2023 | B72: 2 | C72: 16 | D72: =DATE(A72,B72,C72) -> 44973 | E72: =DATE(A72,B72,C72) -> 44973 | G72: C | J72: Cash and cash equivalents | L72: 10
A73: 2023 | B73: 2 | C73: 19 | D73: =DATE(A73,B73,C73) -> 44976 | E73: =DATE(A73,B73,C73) -> 44976 | F73: Unit Subscription - LUMPSUM | G73: C | I73: A00452 | J73: Cash and cash equivalents | K73: 1500000
A74: 2023 | B74: 2 | C74: 19 | D74: =DATE(A74,B74,C74) -> 44976 | E74: =DATE(A74,B74,C74) -> 44976 | G74: C | I74: A00452 | J74: Unit Capital | L74: 1500000
A75: 2023 | B75: 2 | C75: 19 | D75: =DATE(A75,B75,C75) -> 44976 | E75: =DATE(A75,B75,C75) -> 44976 | F75: Unit Subscription - LUMPSUM | G75: C | I75: A00446 | J75: Cash and cash equivalents | K75: 1000000
A76: 2023 | B76: 2 | C76: 19 | D76: =DATE(A76,B76,C76) -> 44976 | E76: =DATE(A76,B76,C76) -> 44976 | G76: C | I76: A00446 | J76: Unit Capital | L76: 1000000
A77: 2023 | B77: 2 | C77: 19 | D77: =DATE(A77,B77,C77) -> 44976 | E77: =DATE(A77,B77,C77) -> 44976 | F77: Unit Subscription - LUMPSUM | G77: C | I77: A00014 | J77: Cash and cash equivalents | K77: 1500000
A78: 2023 | B78: 2 | C78: 19 | D78: =DATE(A78,B78,C78) -> 44976 | E78: =DATE(A78,B78,C78) -> 44976 | G78: C | I78: A00014 | J78: Unit Capital | L78: 1500000
A79: 2023 | B79: 2 | C79: 19 | D79: =DATE(A79,B79,C79) -> 44976 | E79: =DATE(A79,B79,C79) -> 44976 | F79: Bank Charges - Clearing Charge | G79: C | J79: Bank charges and excise duties | K79: 180
A80: 2023 | B80: 2 | C80: 19 | D80: =DATE(A80,B80,C80) -> 44976 | E80: =DATE(A80,B80,C80) -> 44976 | G80: C | J80: Cash and cash equivalents | L80: 180
A81: 2023 | B81: 2 | C81: 20 | D81: =DATE(A81,B81,C81) -> 44977 | E81: =DATE(A81,B81,C81) -> 44977 | F81: Bank Charges - Clearing Charge | G81: C | J81: Bank charges and excise duties | K81: 50
A82: 2023 | B82: 2 | C82: 20 | D82: =DATE(A82,B82,C82) -> 44977 | E82: =DATE(A82,B82,C82) -> 44977 | G82: C | J82: Cash and cash equivalents | L82: 50
A83: 2023 | B83: 2 | C83: 20 | D83: =DATE(A83,B83,C83) -> 44977 | E83: =DATE(A83,B83,C83) -> 44977 | F83: Unit Subscription - LUMPSUM | G83: C | I83: A00194 | J83: Cash and cash equivalents | K83: 2000000
A84: 2023 | B84: 2 | C84: 20 | D84: =DATE(A84,B84,C84) -> 44977 | E84: =DATE(A84,B84,C84) -> 44977 | G84: C | I84: A00194 | J84: Unit Capital | L84: 2000000
A85: 2023 | B85: 2 | C85: 20 | D85: =DATE(A85,B85,C85) -> 44977 | E85: =DATE(A85,B85,C85) -> 44977 | F85: Unit Subscription - LUMPSUM | G85: C | I85: A00455 | J85: Cash and cash equivalents | K85: 1000000
A86: 2023 | B86: 2 | C86: 20 | D86: =DATE(A86,B86,C86) -> 44977 | E86: =DATE(A86,B86,C86) -> 44977 | G86: C | I86: A00455 | J86: Unit Capital | L86: 1000000
A87: 2023 | B87: 2 | C87: 22 | D87: =DATE(A87,B87,C87) -> 44979 | E87: =DATE(A87,B87,C87) -> 44979 | F87: Unit Subscription - LUMPSUM | G87: C | I87: A00223 | J87: Cash and cash equivalents | K87: 5000
A88: 2023 | B88: 2 | C88: 22 | D88: =DATE(A88,B88,C88) -> 44979 | E88: =DATE(A88,B88,C88) -> 44979 | G88: C | I88: A00223 | J88: Unit Capital | L88: 5000
A89: 2023 | B89: 2 | C89: 22 | D89: =DATE(A89,B89,C89) -> 44979 | E89: =DATE(A89,B89,C89) -> 44979 | F89: Unit Subscription - LUMPSUM | G89: C | I89: A00223 | J89: Cash and cash equivalents | K89: 195000
A90: 2023 | B90: 2 | C90: 22 | D90: =DATE(A90,B90,C90) -> 44979 | E90: =DATE(A90,B90,C90) -> 44979 | G90: C | I90: A00223 | J90: Unit Capital | L90: 195000
A91: 2023 | B91: 2 | C91: 23 | D91: =DATE(A91,B91,C91) -> 44980 | E91: =DATE(A91,B91,C91) -> 44980 | F91: Unit Subscription - LUMPSUM | G91: C | I91: A00073 | J91: Cash and cash equivalents | K91: 1000000
A92: 2023 | B92: 2 | C92: 23 | D92: =DATE(A92,B92,C92) -> 44980 | E92: =DATE(A92,B92,C92) -> 44980 | G92: C | I92: A00073 | J92: Unit Capital | L92: 1000000
A93: 2023 | B93: 2 | C93: 23 | D93: =DATE(A93,B93,C93) -> 44980 | E93: =DATE(A93,B93,C93) -> 44980 | F93: Unit Subscription - LUMPSUM | G93: C | I93: A00451 | J93: Cash and cash equivalents | K93: 50000
A94: 2023 | B94: 2 | C94: 23 | D94: =DATE(A94,B94,C94) -> 44980 | E94: =DATE(A94,B94,C94) -> 44980 | G94: C | I94: A00451 | J94: Unit Capital | L94: 50000
A95: 2023 | B95: 2 | C95: 23 | D95: =DATE(A95,B95,C95) -> 44980 | E95: =DATE(A95,B95,C95) -> 44980 | F95: Unit Subscription - LUMPSUM | G95: C | I95: A00045 | J95: Cash and cash equivalents | K95: 4500000
A96: 2023 | B96: 2 | C96: 23 | D96: =DATE(A96,B96,C96) -> 44980 | E96: =DATE(A96,B96,C96) -> 44980 | G96: C | I96: A00045 | J96: Unit Capital | L96: 4500000
A97: 2023 | B97: 2 | C97: 23 | D97: =DATE(A97,B97,C97) -> 44980 | E97: =DATE(A97,B97,C97) -> 44980 | F97: Unit Subscription - LUMPSUM | G97: C | I97: A00248 | J97: Cash and cash equivalents | K97: 2000000
A98: 2023 | B98: 2 | C98: 23 | D98: =DATE(A98,B98,C98) -> 44980 | E98: =DATE(A98,B98,C98) -> 44980 | G98: C | I98: A00248 | J98: Unit Capital | L98: 2000000
A99: 2023 | B99: 2 | C99: 23 | D99: =DATE(A99,B99,C99) -> 44980 | E99: =DATE(A99,B99,C99) -> 44980 | F99: Unit Subscription - LUMPSUM | G99: C | I99: A00459 | J99: Cash and cash equivalents | K99: 2500000
A100: 2023 | B100: 2 | C100: 23 | D100: =DATE(A100,B100,C100) -> 44980 | E100: =DATE(A100,B100,C100) -> 44980 | G100: C | I100: A00459 | J100: Unit Capital | L100: 2500000
A101: 2023 | B101: 2 | C101: 23 | D101: =DATE(A101,B101,C101) -> 44980 | E101: =DATE(A101,B101,C101) -> 44980 | F101: Unit Subscription - LUMPSUM | G101: C | I101: A00344 | J101: Cash and cash equivalents | K101: 2500000
...

Sheet TB-C
A1: Check of Trial Balance | G1: =SUM(H7:H98)-SUM(I7:I98) -> -0.0072669387
A2: Check of Balance Sheet | G2: =BS!C25-BS!C42 -> -0.0033406019
A3: Check of Cash Balance | G3: =BS!C23-CF!B43 -> 94994187
B5: Desired Reporting Period | H5: During the Reporting Period | J5: For Balance Sheet | N5: For Retained Earnings
B6: Year | C6: Month | D6: Day | E6: Value | F6: Value | G6: Accounts | H6: Debit | I6: Credit | J6: Carry Forward Balance | K6: Carry Forward Balance | L6: On date | M6: On date | N6: Debit | O6: Credit
A7: Beginning | B7: 2025 | C7: 7 | D7: 1 | E7: =DATE(B7,C7,D7)-1 -> 45838 | F7: =DATE(B7,C7,D7) -> 45839 | G7: ='Chart of Accounts'!B3 -> Investments in stock | H7: =MAX(0,SUMIFS(Journals!$K$9:$K$1007564,Journals!$D$9:$D$1007564,">"&$E$7,Journals!$D$9:$D$1007564,"<"&$E$8,Journals!$J$9:$J$1007564,"investments in stock")-SUMIFS(Journals!$L$9:$L$1007564,Journals!$D$9:$D$1007564,">"&$E$7,Journals!$D$9:$D$1007564,"<"&$E$8,Journals!$J$9:$J$1007564,"investments in stock")) -> 30202480 | I7: =MAX(0,SUMIFS(Journals!$L$9:$L$1007564,Journals!$D$9:$D$1007564,">"&$E$7,Journals!$D$9:$D$1007564,"<"&$E$8,Journals!$J$9:$J$1007564,"Investments in stock")-SUMIFS(Journals!$K$9:$K$1007564,Journals!$D$9:$D$1007564,">"&$E$7,Journals!$D$9:$D$1007564,"<"&$E$8,Journals!$J$9:$J$1007564,"Investments in stock")) -> 0 | J7: =SUMIFS(Journals!$K$9:$K$1007564,Journals!$D$9:$D$1007564,"<"&$F$7,Journals!$J$9:$J$1007564,"investments in stock")-SUMIFS(Journals!$L$9:$L$1007564,Journals!$D$9:$D$1007564,"<"&$F$7,Journals!$J$9:$J$1007564,"investments in stock") -> 2797650.6 | L7: =J7+H7-I7 -> 33000130
A8: Ending | B8: 2026 | C8: 6 | D8: 30 | E8: =DATE(B8,C8,D8)+1 -> 46204 | F8: =DATE(B8,C8,D8)-1 -> 46202 | G8: ='Chart of Accounts'!B4 -> Interest Receivables from Bank A/C | H8: =MAX(0,SUMIFS(Journals!$K$9:$K$1007564,Journals!$D$9:$D$1007564,">"&$E$7,Journals!$D$9:$D$1007564,"<"&$E$8,Journals!$J$9:$J$1007564,"Interest Receivables from Bank A/C")-SUMIFS(Journals!$L$9:$L$1007564,Journals!$D$9:$D$1007564,">"&$E$7,Journals!$D$9:$D$1007564,"<"&$E$8,Journals!$J$9:$J$1007564,"Interest Receivables from Bank A/C")) -> 130333.46 | I8: =MAX(0,SUMIFS(Journals!$L$9:$L$1007564,Journals!$D$9:$D$1007564,">"&$E$7,Journals!$D$9:$D$1007564,"<"&$E$8,Journals!$J$9:$J$1007564,"Interest Receivables from Bank A/C")-SUMIFS(Journals!$K$9:$K$1007564,Journals!$D$9:$D$1007564,">"&$E$7,Journals!$D$9:$D$1007564,"<"&$E$8,Journals!$J$9:$J$1007564,"Interest Receivables from Bank A/C")) -> 0 | J8: =SUMIFS(Journals!$K$9:$K$1007564,Journals!$D$9:$D$1007564,"<"&$F$7,Journals!$J$9:$J$1007564,"Interest Receivables from Bank A/C")-SUMIFS(Journals!$L$9:$L$1007564,Journals!$D$9:$D$1007564,"<"&$F$7,Journals!$J$9:$J$1007564,"Interest Receivables from Bank A/C") -> 2762.8079 | L8: =J8+H8-I8 -> 133096.27
G9: Interest Receivables from Sukuk | H9: =MAX(0,SUMIFS(Journals!$K$9:$K$1007564,Journals!$D$9:$D$1007564,">"&$E$7,Journals!$D$9:$D$1007564,"<"&$E$8,Journals!$J$9:$J$1007564,"Interest Receivables from Sukuk")-SUMIFS(Journals!$L$9:$L$1007564,Journals!$D$9:$D$1007564,">"&$E$7,Journals!$D$9:$D$1007564,"<"&$E$8,Journals!$J$9:$J$1007564,"Interest Receivables from Sukuk")) -> 0 | I9: =MAX(0,SUMIFS(Journals!$L$9:$L$1007564,Journals!$D$9:$D$1007564,">"&$E$7,Journals!$D$9:$D$1007564,"<"&$E$8,Journals!$J$9:$J$1007564,"Interest Receivables from Sukuk")-SUMIFS(Journals!$K$9:$K$1007564,Journals!$D$9:$D$1007564,">"&$E$7,Journals!$D$9:$D$1007564,"<"&$E$8,Journals!$J$9:$J$1007564,"Interest Receivables from Sukuk")) -> 0 | J9: =SUMIFS(Journals!$K$9:$K$1007564,Journals!$D$9:$D$1007564,"<"&$F$7,Journals!$J$9:$J$1007564,"Interest Receivables from Sukuk")-SUMIFS(Journals!$L$9:$L$1007564,Journals!$D$9:$D$1007564,"<"&$F$7,Journals!$J$9:$J$1007564,"Interest Receivables from Sukuk") -> 1.1641532e-09 | L9: =J9+H9-I9 -> 1.1641532e-09
G10: Interest Receivables from Bond | H10: =MAX(0,SUMIFS(Journals!$K$9:$K$1007564,Journals!$D$9:$D$1007564,">"&$E$7,Journals!$D$9:$D$1007564,"<"&$E$8,Journals!$J$9:$J$1007564,"Interest Receivables from Bond")-SUMIFS(Journals!$L$9:$L$1007564,Journals!$D$9:$D$1007564,">"&$E$7,Journals!$D$9:$D$1007564,"<"&$E$8,Journals!$J$9:$J$1007564,"Interest Receivables from Bond")) -> 0 | I10: =MAX(0,SUMIFS(Journals!$L$9:$L$1007564,Journals!$D$9:$D$1007564,">"&$E$7,Journals!$D$9:$D$1007564,"<"&$E$8,Journals!$J$9:$J$1007564,"Interest Receivables from Bond")-SUMIFS(Journals!$K$9:$K$1007564,Journals!$D$9:$D$1007564,">"&$E$7,Journals!$D$9:$D$1007564,"<"&$E$8,Journals!$J$9:$J$1007564,"Interest Receivables from Bond")) -> 32785.351 | J10: =SUMIFS(Journals!$K$9:$K$1007564,Journals!$D$9:$D$1007564,"<"&$F$7,Journals!$J$9:$J$1007564,"Interest Receivables from Bond")-SUMIFS(Journals!$L$9:$L$1007564,Journals!$D$9:$D$1007564,"<"&$F$7,Journals!$J$9:$J$1007564,"Interest Receivables from Bond") -> 59214.369 | L10: =J10+H10-I10 -> 26429.019
B11: =CURRENT_NAV -> 14.267139 | G11: ='Chart of Accounts'!B5 -> Preliminary & issue expenses | H11: =MAX(0,SUMIFS(Journals!$K$9:$K$1007564,Journals!$D$9:$D$1007564,">"&$E$7,Journals!$D$9:$D$1007564,"<"&$E$8,Journals!$J$9:$J$1007564,"Preliminary & issue expenses")-SUMIFS(Journals!$L$9:$L$1007564,Journals!$D$9:$D$1007564,">"&$E$7,Journals!$D$9:$D$1007564,"<"&$E$8,Journals!$J$9:$J$1007564,"Preliminary & issue expenses")) -> 0 | I11: =MAX(0,SUMIFS(Journals!$L$9:$L$1007564,Journals!$D$9:$D$1007564,">"&$E$7,Journals!$D$9:$D$1007564,"<"&$E$8,Journals!$J$9:$J$1007564,"Preliminary & issue expenses")-SUMIFS(Journals!$K$9:$K$1007564,Journals!$D$9:$D$1007564,">"&$E$7,Journals!$D$9:$D$1007564,"<"&$E$8,Journals!$J$9:$J$1007564,"Preliminary & issue expenses")) -> 138713.88 | J11: =SUMIFS(Journals!$K$9:$K$1007564,Journals!$D$9:$D$1007564,"<"&$F$7,Journals!$J$9:$J$1007564,"Preliminary & issue expenses")-SUMIFS(Journals!$L$9:$L$1007564,Journals!$D$9:$D$1007564,"<"&$F$7,Journals!$J$9:$J$1007564,"Preliminary & issue expenses") -> 559729.36 | L11: =J11+H11-I11 -> 421015.48
G12: ='Chart of Accounts'!B6 -> Accrued Management Fee | H12: =SUMIFS(Journals!$K$9:$K$1007564,Journals!$D$9:$D$1007564,">"&$E$7,Journals!$D$9:$D$1007564,"<"&$E$8,Journals!$J$9:$J$1007564,"Accrued Management Fee") -> 2188653.6 | I12: =MAX(0,SUMIFS(Journals!$L$9:$L$1007564,Journals!$D$9:$D$1007564,">"&$E$7,Journals!$D$9:$D$1007564,"<"&$E$8,Journals!$J$9:$J$1007564,"Accrued Management Fee")) -> 2130135.1 | K12: =SUMIFS(Journals!$L$9:$L$1007564,Journals!$D$9:$D$1007564,"<"&$F$7,Journals!$J$9:$J$1007564,"Accrued Management Fee")-SUMIFS(Journals!$K$9:$K$1007564,Journals!$D$9:$D$1007564,"<"&$F$7,Journals!$J$9:$J$1007564,"Accrued Management Fee") -> 236441.3 | M12: =K12+I12-H12 -> 177922.86
E13: 203746.91 | G13: ='Chart of Accounts'!B7 -> Accrued Trustee Fee | H13: =MAX(0,SUMIFS(Journals!$K$9:$K$1007564,Journals!$D$9:$D$1007564,">"&$E$7,Journals!$D$9:$D$1007564,"<"&$E$8,Journals!$J$9:$J$1007564,"accrued trustee fee")-SUMIFS(Journals!$L$9:$L$1007564,Journals!$D$9:$D$1007564,">"&$E$7,Journals!$D$9:$D$1007564,"<"&$E$8,Journals!$J$9:$J$1007564,"accrued trustee fee")) -> 0 | I13: =MAX(0,SUMIFS(Journals!$L$9:$L$1007564,Journals!$D$9:$D$1007564,">"&$E$7,Journals!$D$9:$D$1007564,"<"&$E$8,Journals!$J$9:$J$1007564,"accrued trustee fee")-SUMIFS(Journals!$K$9:$K$1007564,Journals!$D$9:$D$1007564,">"&$E$7,Journals!$D$9:$D$1007564,"<"&$E$8,Journals!$J$9:$J$1007564,"accrued trustee fee")) -> 147197 | K13: =SUMIFS(Journals!$L$9:$L$1007564,Journals!$D$9:$D$1007564,"<"&$F$7,Journals!$J$9:$J$1007564,"Accrued Trustee Fee")-SUMIFS(Journals!$K$9:$K$1007564,Journals!$D$9:$D$1007564,"<"&$F$7,Journals!$J$9:$J$1007564,"Accrued Trustee Fee") -> 65816.504 | M13: =K13+I13-H13 -> 213013.5
E14: 65816.504 | G14: ='Chart of Accounts'!B8 -> Accrued Custodian Fee | H14: =MAX(0,SUMIFS(Journals!$K$9:$K$1007564,Journals!$D$9:$D$1007564,">"&$E$7,Journals!$D$9:$D$1007564,"<"&$E$8,Journals!$J$9:$J$1007564,"accrued custodian fee")-SUMIFS(Journals!$L$9:$L$1007564,Journals!$D$9:$D$1007564,">"&$E$7,Journals!$D$9:$D$1007564,"<"&$E$8,Journals!$J$9:$J$1007564,"accrued custodian fee")) -> 0 | I14: =MAX(0,SUMIFS(Journals!$L$9:$L$1007564,Journals!$D$9:$D$1007564,">"&$E$7,Journals!$D$9:$D$1007564,"<"&$E$8,Journals!$J$9:$J$1007564,"accrued custodian fee")-SUMIFS(Journals!$K$9:$K$1007564,Journals!$D$9:$D$1007564,">"&$E$7,Journals!$D$9:$D$1007564,"<"&$E$8,Journals!$J$9:$J$1007564,"accrued custodian fee")) -> 56173.838 | K14: =SUMIFS(Journals!$L$9:$L$1007564,Journals!$D$9:$D$1007564,"<"&$F$7,Journals!$J$9:$J$1007564,"Accrued Custodian Fee")-SUMIFS(Journals!$K$9:$K$1007564,Journals!$D$9:$D$1007564,"<"&$F$7,Journals!$J$9:$J$1007564,"Accrued Custodian Fee") -> 123123.68 | M14: =K14+I14-H14 -> 179297.52
E15: =E13-E14 -> 137930.41 | G15: ='Chart of Accounts'!B9 -> Accrued BSEC fee | H15: =MAX(0,SUMIFS(Journals!$K$9:$K$1007564,Journals!$D$9:$D$1007564,">"&$E$7,Journals!$D$9:$D$1007564,"<"&$E$8,Journals!$J$9:$J$1007564,"accrued bsec fee")-SUMIFS(Journals!$L$9:$L$1007564,Journals!$D$9:$D$1007564,">"&$E$7,Journals!$D$9:$D$1007564,"<"&$E$8,Journals!$J$9:$J$1007564,"accrued bsec fee")) -> 0 | I15: =MAX(0,SUMIFS(Journals!$L$9:$L$1007564,Journals!$D$9:$D$1007564,">"&$E$7,Journals!$D$9:$D$1007564,"<"&$E$8,Journals!$J$9:$J$1007564,"accrued bsec fee")-SUMIFS(Journals!$K$9:$K$1007564,Journals!$D$9:$D$1007564,">"&$E$7,Journals!$D$9:$D$1007564,"<"&$E$8,Journals!$J$9:$J$1007564,"accrued bsec fee")) -> 0 | K15: =SUMIFS(Journals!$L$9:$L$1007564,Journals!$D$9:$D$1007564,"<"&$F$7,Journals!$J$9:$J$1007564,"accrued bsec fee")-SUMIFS(Journals!$K$9:$K$1007564,Journals!$D$9:$D$1007564,"<"&$F$7,Journals!$J$9:$J$1007564,"accrued bsec fee") -> 0 | M15: =K15+I15-H15 -> 0
G16: ='Chart of Accounts'!B10 -> Accrued Audit Fee | H16: =MAX(0,SUMIFS(Journals!$K$9:$K$1007564,Journals!$D$9:$D$1007564,">"&$E$7,Journals!$D$9:$D$1007564,"<"&$E$8,Journals!$J$9:$J$1007564,"accrued audit fee")) -> 40250 | I16: =MAX(0,SUMIFS(Journals!$L$9:$L$1007564,Journals!$D$9:$D$1007564,">"&$E$7,Journals!$D$9:$D$1007564,"<"&$E$8,Journals!$J$9:$J$1007564,"accrued audit fee")) -> 0 | K16: =SUMIFS(Journals!$L$9:$L$1007564,Journals!$D$9:$D$1007564,"<"&$F$7,Journals!$J$9:$J$1007564,"accrued audit fee")-SUMIFS(Journals!$K$9:$K$1007564,Journals!$D$9:$D$1007564,"<"&$F$7,Journals!$J$9:$J$1007564,"accrued audit fee") -> 40250 | M16: =K16+I16-H16 -> 0
G17: ='Chart of Accounts'!B11 -> Accrued CDBL Fee | H17: =MAX(0,SUMIFS(Journals!$K$9:$K$1007564,Journals!$D$9:$D$1007564,">"&$E$7,Journals!$D$9:$D$1007564,"<"&$E$8,Journals!$J$9:$J$1007564,"accrued CDBL fee")-SUMIFS(Journals!$L$9:$L$1007564,Journals!$D$9:$D$1007564,">"&$E$7,Journals!$D$9:$D$1007564,"<"&$E$8,Journals!$J$9:$J$1007564,"accrued CDBL fee")) -> 0 | I17: =MAX(0,SUMIFS(Journals!$L$9:$L$1007564,Journals!$D$9:$D$1007564,">"&$E$7,Journals!$D$9:$D$1007564,"<"&$E$8,Journals!$J$9:$J$1007564,"accrued CDBL fee")-SUMIFS(Journals!$K$9:$K$1007564,Journals!$D$9:$D$1007564,">"&$E$7,Journals!$D$9:$D$1007564,"<"&$E$8,Journals!$J$9:$J$1007564,"accrued CDBL fee")) -> 0 | K17: =SUMIFS(Journals!$L$9:$L$1007564,Journals!$D$9:$D$1007564,"<"&$F$7,Journals!$J$9:$J$1007564,"accrued cdbl fee")-SUMIFS(Journals!$K$9:$K$1007564,Journals!$D$9:$D$1007564,"<"&$F$7,Journals!$J$9:$J$1007564,"accrued cdbl fee") -> 0 | M17: =K17+I17-H17 -> 0
G18: ='Chart of Accounts'!B12 -> Fixed Deposit Receipts (FDR) | H18: =MAX(0,SUMIFS(Journals!$K$9:$K$1007564,Journals!$D$9:$D$1007564,">"&$E$7,Journals!$D$9:$D$1007564,"<"&$E$8,Journals!$J$9:$J$1007564,"Fixed Deposit Receipts (FDR)")-SUMIFS(Journals!$L$9:$L$1007564,Journals!$D$9:$D$1007564,">"&$E$7,Journals!$D$9:$D$1007564,"<"&$E$8,Journals!$J$9:$J$1007564,"Fixed Deposit Receipts (FDR)")) -> 0 | I18: =MAX(0,SUMIFS(Journals!$L$9:$L$1007564,Journals!$D$9:$D$1007564,">"&$E$7,Journals!$D$9:$D$1007564,"<"&$E$8,Journals!$J$9:$J$1007564,"Fixed Deposit Receipts (FDR)")-SUMIFS(Journals!$K$9:$K$1007564,Journals!$D$9:$D$1007564,">"&$E$7,Journals!$D$9:$D$1007564,"<"&$E$8,Journals!$J$9:$J$1007564,"Fixed Deposit Receipts (FDR)")) -> 31000000 | J18: =SUMIFS(Journals!$K$9:$K$1007564,Journals!$D$9:$D$1007564,"<"&$F$7,Journals!$J$9:$J$1007564,"Fixed Deposit Receipts (FDR)")-SUMIFS(Journals!$L$9:$L$1007564,Journals!$D$9:$D$1007564,"<"&$F$7,Journals!$J$9:$J$1007564,"Fixed Deposit Receipts (FDR)") -> 85000000 | L18: =J18+H18-I18 -> 54000000
G19: ='Chart of Accounts'!B13 -> Cash and cash equivalents | H19: =MAX(0,SUMIFS(Journals!$K$9:$K$1006910,Journals!$D$9:$D$1006910,">"&$E$7,Journals!$D$9:$D$1006910,"<"&$E$8,Journals!$J$9:$J$1006910,"Cash and cash equivalents")-SUMIFS(Journals!$L$9:$L$1006910,Journals!$D$9:$D$1006910,">"&$E$7,Journals!$D$9:$D$1006910,"<"&$E$8,Journals!$J$9:$J$1006910,"Cash and cash equivalents")) -> 15938868 | I19: =MAX(0,SUMIFS(Journals!$L$9:$L$1006910,Journals!$D$9:$D$1006910,">"&$E$7,Journals!$D$9:$D$1006910,"<"&$E$8,Journals!$J$9:$J$1006910,"Cash and cash equivalents")-SUMIFS(Journals!$K$9:$K$1006910,Journals!$D$9:$D$1006910,">"&$E$7,Journals!$D$9:$D$1006910,"<"&$E$8,Journals!$J$9:$J$1006910,"Cash and cash equivalents")) -> 0 | J19: =SUMIFS(Journals!$K$9:$K$1007564,Journals!$D$9:$D$1007564,"<"&$F$7,Journals!$J$9:$J$1007564,"Cash and cash equivalents")-SUMIFS(Journals!$L$9:$L$1007564,Journals!$D$9:$D$1007564,"<"&$F$7,Journals!$J$9:$J$1007564,"Cash and cash equivalents") -> 15519657 | L19: =J19+H19-I19 -> 31458525
G20: ='Chart of Accounts'!B14 -> Unit Capital | H20: =SUMIFS(Journals!$K$9:$K$1007564,Journals!$D$9:$D$1007564,">"&$E$7,Journals!$D$9:$D$1007564,"<"&$E$8,Journals!$J$9:$J$1007564,"unit capital") -> 263102130 | I20: =MAX(0,SUMIFS(Journals!$L$9:$L$1007564,Journals!$D$9:$D$1007564,">"&$E$7,Journals!$D$9:$D$1007564,"<"&$E$8,Journals!$J$9:$J$1007564,"unit capital")) -> 212650510 | K20: =SUMIFS(Journals!$L$9:$L$1007564,Journals!$D$9:$D$1007564,"<"&$F$7,Journals!$J$9:$J$1007564,"unit capital")-SUMIFS(Journals!$K$9:$K$1007564,Journals!$D$9:$D$1007564,"<"&$F$7,Journals!$J$9:$J$1007564,"unit capital") -> 462377570 | M20: =K20+I20-H20 -> 411925950
G21: ='Chart of Accounts'!B15 -> Unit premium reserve | H21: =SUMIFS(Journals!$K$9:$K$1007564,Journals!$D$9:$D$1007564,">"&$E$7,Journals!$D$9:$D$1007564,"<"&$E$8,Journals!$J$9:$J$1007564,"unit premium reserve") -> 88676215 | I21: =SUMIFS(Journals!$L$9:$L$1007564,Journals!$D$9:$D$1007564,">"&$E$7,Journals!$D$9:$D$1007564,"<"&$E$8,Journals!$J$9:$J$1007564,"unit premium reserve") -> 70419620 | K21: =SUMIFS(Journals!$L$9:$L$1007564,Journals!$D$9:$D$1007564,"<"&$F$7,Journals!$J$9:$J$1007564,"unit premium reserve")-SUMIFS(Journals!$K$9:$K$1007564,Journals!$D$9:$D$1007564,"<"&$F$7,Journals!$J$9:$J$1007564,"unit premium reserve") -> 41293538 | M21: =K21+I21-H21 -> 23036942
G22: Interest income | H22: =MAX(0,SUMIFS(Journals!$K$9:$K$1007564,Journals!$D$9:$D$1007564,">"&$E$7,Journals!$D$9:$D$1007564,"<"&$E$8,Journals!$J$9:$J$1007564,"interest income")-SUMIFS(Journals!$L$9:$L$1007564,Journals!$D$9:$D$1007564,">"&$E$7,Journals!$D$9:$D$1007564,"<"&$E$8,Journals!$J$9:$J$1007564,"interest income")) -> 0 | I22: =MAX(0,SUMIFS(Journals!$L$9:$L$1007564,Journals!$D$9:$D$1007564,">"&$E$7,Journals!$D$9:$D$1007564,"<"&$E$8,Journals!$J$9:$J$1007564,"interest income")-SUMIFS(Journals!$K$9:$K$1007564,Journals!$D$9:$D$1007564,">"&$E$7,Journals!$D$9:$D$1007564,"<"&$E$8,Journals!$J$9:$J$1007564,"interest income")) -> 7800790.8 | K22: =SUMIFS(Journals!$L$9:$L$1007564,Journals!$D$9:$D$1007564,"<"&$F$7,Journals!$J$9:$J$1007564,"Interest income")-SUMIFS(Journals!$K$9:$K$1007564,Journals!$D$9:$D$1007564,"<"&$F$7,Journals!$J$9:$J$1007564,"Interest income") -> 19919416 | M22: =K22+I22-H22 -> 27720207 | O22: =SUMIFS(Journals!$L$9:$L$1007564,Journals!$D$9:$D$1007564,"<"&$F$7,Journals!$J$9:$J$1007564,"interest income")-SUMIFS(Journals!$K$9:$K$1007564,Journals!$D$9:$D$1007564,"<"&$F$7,Journals!$J$9:$J$1007564,"interest income") -> 19919416
G23: Interest income from T-Bond | H23: =MAX(0,SUMIFS(Journals!$K$9:$K$1007494,Journals!$D$9:$D$1007494,">"&$E$7,Journals!$D$9:$D$1007494,"<"&$E$8,Journals!$J$9:$J$1007494,"Interest income from T-Bond")-SUMIFS(Journals!$L$9:$L$1007494,Journals!$D$9:$D$1007494,">"&$E$7,Journals!$D$9:$D$1007494,"<"&$E$8,Journals!$J$9:$J$1007494,"Interest income from T-Bond")) -> 0 | I23: =MAX(0,SUMIFS(Journals!$L$9:$L$1007494,Journals!$D$9:$D$1007494,">"&$E$7,Journals!$D$9:$D$1007494,"<"&$E$8,Journals!$J$9:$J$1007494,"Interest income from T-Bond")-SUMIFS(Journals!$K$9:$K$1007494,Journals!$D$9:$D$1007494,">"&$E$7,Journals!$D$9:$D$1007494,"<"&$E$8,Journals!$J$9:$J$1007494,"Interest income from T-Bond")) -> 23849013 | K23: =SUMIFS(Journals!$L$9:$L$1007494,Journals!$D$9:$D$1007494,"<"&$F$7,Journals!$J$9:$J$1007494,"Interest income from T-Bond")-SUMIFS(Journals!$K$9:$K$1007494,Journals!$D$9:$D$1007494,"<"&$F$7,Journals!$J$9:$J$1007494,"Interest income from T-Bond") -> 33626216 | M23: =K23+I23-H23 -> 57475229 | O23: =SUMIFS(Journals!$L$9:$L$1007494,Journals!$D$9:$D$1007494,"<"&$F$7,Journals!$J$9:$J$1007494,"Interest income from T-Bond")-SUMIFS(Journals!$K$9:$K$1007494,Journals!$D$9:$D$1007494,"<"&$F$7,Journals!$J$9:$J$1007494,"Interest income from T-Bond") -> 33626216
G24: Interest income from BXSUKUK | H24: =MAX(0,SUMIFS(Journals!$K$9:$K$1007564,Journals!$D$9:$D$1007564,">"&$E$7,Journals!$D$9:$D$1007564,"<"&$E$8,Journals!$J$9:$J$1007564,"Interest income from BXSUKUK")-SUMIFS(Journals!$L$9:$L$1007564,Journals!$D$9:$D$1007564,">"&$E$7,Journals!$D$9:$D$1007564,"<"&$E$8,Journals!$J$9:$J$1007564,"Interest income from BXSUKUK")) -> 0 | I24: =MAX(0,SUMIFS(Journals!$L$9:$L$1007492,Journals!$D$9:$D$1007492,">"&$E$7,Journals!$D$9:$D$1007492,"<"&$E$8,Journals!$J$9:$J$1007492,"Interest income from BXSUKUK")-SUMIFS(Journals!$K$9:$K$1007492,Journals!$D$9:$D$1007492,">"&$E$7,Journals!$D$9:$D$1007492,"<"&$E$8,Journals!$J$9:$J$1007492,"Interest income from BXSUKUK")) -> 0 | K24: =SUMIFS(Journals!$L$9:$L$1007564,Journals!$D$9:$D$1007564,"<"&$F$7,Journals!$J$9:$J$1007564,"Interest income from BXSUKUK")-SUMIFS(Journals!$K$9:$K$1007564,Journals!$D$9:$D$1007564,"<"&$F$7,Journals!$J$9:$J$1007564,"Interest income from BXSUKUK") -> 448642.74 | M24: =K24+I24-H24 -> 448642.74 | O24: =SUMIFS(Journals!$L$9:$L$1007564,Journals!$D$9:$D$1007564,"<"&$F$7,Journals!$J$9:$J$1007564,"Interest income from BXSUKUK")-SUMIFS(Journals!$K$9:$K$1007564,Journals!$D$9:$D$1007564,"<"&$F$7,Journals!$J$9:$J$1007564,"Interest income from BXSUKUK") -> 448642.74
G25: Interest income from APSCL | H25: =MAX(0,SUMIFS(Journals!$K$9:$K$1007564,Journals!$D$9:$D$1007564,">"&$E$7,Journals!$D$9:$D$1007564,"<"&$E$8,Journals!$J$9:$J$1007564,"Interest income from APSCL")-SUMIFS(Journals!$L$9:$L$1007564,Journals!$D$9:$D$1007564,">"&$E$7,Journals!$D$9:$D$1007564,"<"&$E$8,Journals!$J$9:$J$1007564,"Interest income from APSCL")) -> 0 | I25: =MAX(0,SUMIFS(Journals!$L$9:$L$1007564,Journals!$D$9:$D$1007564,">"&$E$7,Journals!$D$9:$D$1007564,"<"&$E$8,Journals!$J$9:$J$1007564,"Interest income from APSCL")-SUMIFS(Journals!$K$9:$K$1007564,Journals!$D$9:$D$1007564,">"&$E$7,Journals!$D$9:$D$1007564,"<"&$E$8,Journals!$J$9:$J$1007564,"Interest income from APSCL")) -> 304658.4 | K25: =SUMIFS(Journals!$L$9:$L$1007564,Journals!$D$9:$D$1007564,"<"&$F$7,Journals!$J$9:$J$1007564,"Interest income from APSCL")-SUMIFS(Journals!$K$9:$K$1007564,Journals!$D$9:$D$1007564,"<"&$F$7,Journals!$J$9:$J$1007564,"Interest income from APSCL") -> 1278526.9 | M25: =K25+I25-H25 -> 1583185.3 | O25: =SUMIFS(Journals!$L$9:$L$1007564,Journals!$D$9:$D$1007564,"<"&$F$7,Journals!$J$9:$J$1007564,"Interest income from APSCL")-SUMIFS(Journals!$K$9:$K$1007564,Journals!$D$9:$D$1007564,"<"&$F$7,Journals!$J$9:$J$1007564,"Interest income from APSCL") -> 1278526.9
G26: Interest income from Bank Asia Bond | H26: =MAX(0,SUMIFS(Journals!$K$9:$K$1007564,Journals!$D$9:$D$1007564,">"&$E$7,Journals!$D$9:$D$1007564,"<"&$E$8,Journals!$J$9:$J$1007564,"Interest income from Bank Asia Bond")-SUMIFS(Journals!$L$9:$L$1007564,Journals!$D$9:$D$1007564,">"&$E$7,Journals!$D$9:$D$1007564,"<"&$E$8,Journals!$J$9:$J$1007564,"Interest income from Bank Asia Bond")) -> 0 | I26: =MAX(0,SUMIFS(Journals!$L$9:$L$1007564,Journals!$D$9:$D$1007564,">"&$E$7,Journals!$D$9:$D$1007564,"<"&$E$8,Journals!$J$9:$J$1007564,"Interest income from Bank Asia Bond")-SUMIFS(Journals!$K$9:$K$1007564,Journals!$D$9:$D$1007564,">"&$E$7,Journals!$D$9:$D$1007564,"<"&$E$8,Journals!$J$9:$J$1007564,"Interest income from Bank Asia Bond")) -> 3805011.2 | K26: =SUMIFS(Journals!$L$9:$L$1007564,Journals!$D$9:$D$1007564,"<"&$F$7,Journals!$J$9:$J$1007564,"Interest income from Bank Asia Bond")-SUMIFS(Journals!$K$9:$K$1007564,Journals!$D$9:$D$1007564,"<"&$F$7,Journals!$J$9:$J$1007564,"Interest income from Bank Asia Bond") -> 873164.87 | M26: =K26+I26-H26 -> 4678176 | O26: =SUMIFS(Journals!$L$9:$L$1007564,Journals!$D$9:$D$1007564,"<"&$F$7,Journals!$J$9:$J$1007564,"Interest income from Bank Asia Bond")-SUMIFS(Journals!$K$9:$K$1007564,Journals!$D$9:$D$1007564,"<"&$F$7,Journals!$J$9:$J$1007564,"Interest income from Bank Asia Bond") -> 873164.87
G27: Interest income from BRAC Bank Bond | H27: =MAX(0,SUMIFS(Journals!$K$9:$K$1007564,Journals!$D$9:$D$1007564,">"&$E$7,Journals!$D$9:$D$1007564,"<"&$E$8,Journals!$J$9:$J$1007564,"Interest income from BRAC Bank Bond")-SUMIFS(Journals!$L$9:$L$1007564,Journals!$D$9:$D$1007564,">"&$E$7,Journals!$D$9:$D$1007564,"<"&$E$8,Journals!$J$9:$J$1007564,"Interest income from BRAC Bank Bond")) -> 0 | I27: =MAX(0,SUMIFS(Journals!$L$9:$L$1007564,Journals!$D$9:$D$1007564,">"&$E$7,Journals!$D$9:$D$1007564,"<"&$E$8,Journals!$J$9:$J$1007564,"Interest income from BRAC Bank Bond")-SUMIFS(Journals!$K$9:$K$1007564,Journals!$D$9:$D$1007564,">"&$E$7,Journals!$D$9:$D$1007564,"<"&$E$8,Journals!$J$9:$J$1007564,"Interest income from BRAC Bank Bond")) -> 5594936.2 | K27: =SUMIFS(Journals!$L$9:$L$1007564,Journals!$D$9:$D$1007564,"<"&$F$7,Journals!$J$9:$J$1007564,"Interest income from BRAC Bank Bond")-SUMIFS(Journals!$K$9:$K$1007564,Journals!$D$9:$D$1007564,"<"&$F$7,Journals!$J$9:$J$1007564,"Interest income from BRAC Bank Bond") -> 2800879.1 | M27: =K27+I27-H27 -> 8395815.4 | O27: =SUMIFS(Journals!$L$9:$L$1007564,Journals!$D$9:$D$1007564,"<"&$F$7,Journals!$J$9:$J$1007564,"Interest income from BRAC Bank Bond")-SUMIFS(Journals!$K$9:$K$1007564,Journals!$D$9:$D$1007564,"<"&$F$7,Journals!$J$9:$J$1007564,"Interest income from BRAC Bank Bond") -> 2800879.1
G28: Interest income from Dhaka Bank Bond | H28: =MAX(0,SUMIFS(Journals!$K$9:$K$1007564,Journals!$D$9:$D$1007564,">"&$E$7,Journals!$D$9:$D$1007564,"<"&$E$8,Journals!$J$9:$J$1007564,"Interest income from Dhaka Bank Bond")-SUMIFS(Journals!$L$9:$L$1007564,Journals!$D$9:$D$1007564,">"&$E$7,Journals!$D$9:$D$1007564,"<"&$E$8,Journals!$J$9:$J$1007564,"Interest income from Dhaka Bank Bond")) -> 0 | I28: =MAX(0,SUMIFS(Journals!$L$9:$L$1007564,Journals!$D$9:$D$1007564,">"&$E$7,Journals!$D$9:$D$1007564,"<"&$E$8,Journals!$J$9:$J$1007564,"Interest income from Dhaka Bank Bond")-SUMIFS(Journals!$K$9:$K$1007564,Journals!$D$9:$D$1007564,">"&$E$7,Journals!$D$9:$D$1007564,"<"&$E$8,Journals!$J$9:$J$1007564,"Interest income from Dhaka Bank Bond")) -> 442019.01 | K28: =SUMIFS(Journals!$L$9:$L$1007564,Journals!$D$9:$D$1007564,"<"&$F$7,Journals!$J$9:$J$1007564,"Interest income from Dhaka Bank Bond")-SUMIFS(Journals!$K$9:$K$1007564,Journals!$D$9:$D$1007564,"<"&$F$7,Journals!$J$9:$J$1007564,"Interest income from Dhaka Bank Bond") -> 0 | M28: =K28+I28-H28 -> 442019.01 | O28: =SUMIFS(Journals!$L$9:$L$1007564,Journals!$D$9:$D$1007564,"<"&$F$7,Journals!$J$9:$J$1007564,"Interest income from Dhaka Bank Bond")-SUMIFS(Journals!$K$9:$K$1007564,Journals!$D$9:$D$1007564,"<"&$F$7,Journals!$J$9:$J$1007564,"Interest income from Dhaka Bank Bond") -> 0
G29: Interest income from Bank Acc. | H29: =MAX(0,SUMIFS(Journals!$K$9:$K$1007564,Journals!$D$9:$D$1007564,">"&$E$7,Journals!$D$9:$D$1007564,"<"&$E$8,Journals!$J$9:$J$1007564,"Interest income from Bank Acc.")-SUMIFS(Journals!$L$9:$L$1007564,Journals!$D$9:$D$1007564,">"&$E$7,Journals!$D$9:$D$1007564,"<"&$E$8,Journals!$J$9:$J$1007564,"Interest income from Bank Acc.")) -> 0 | I29: =MAX(0,SUMIFS(Journals!$L$9:$L$1007564,Journals!$D$9:$D$1007564,">"&$E$7,Journals!$D$9:$D$1007564,"<"&$E$8,Journals!$J$9:$J$1007564,"Interest income from Bank Acc.")-SUMIFS(Journals!$K$9:$K$1007564,Journals!$D$9:$D$1007564,">"&$E$7,Journals!$D$9:$D$1007564,"<"&$E$8,Journals!$J$9:$J$1007564,"Interest income from Bank Acc.")) -> 0 | K29: =SUMIFS(Journals!$L$9:$L$1007564,Journals!$D$9:$D$1007564,"<"&$F$7,Journals!$J$9:$J$1007564,"Interest income from Bank Acc.")-SUMIFS(Journals!$K$9:$K$1007564,Journals!$D$9:$D$1007564,"<"&$F$7,Journals!$J$9:$J$1007564,"Interest income from Bank Acc.") -> 0 | M29: =K29+I29-H29 -> 0 | O29: =SUMIFS(Journals!$L$9:$L$1007564,Journals!$D$9:$D$1007564,"<"&$F$7,Journals!$J$9:$J$1007564,"Interest income from Bank Acc.")-SUMIFS(Journals!$K$9:$K$1007564,Journals!$D$9:$D$1007564,"<"&$F$7,Journals!$J$9:$J$1007564,"Interest income from Bank Acc.") -> 0
G30: Interest income from FDR | H30: =MAX(0,SUMIFS(Journals!$K$9:$K$1007564,Journals!$D$9:$D$1007564,">"&$E$7,Journals!$D$9:$D$1007564,"<"&$E$8,Journals!$J$9:$J$1007564,"Interest income from FDR")-SUMIFS(Journals!$L$9:$L$1007564,Journals!$D$9:$D$1007564,">"&$E$7,Journals!$D$9:$D$1007564,"<"&$E$8,Journals!$J$9:$J$1007564,"Interest income from FDR")) -> 0 | I30: =MAX(0,SUMIFS(Journals!$L$9:$L$1007564,Journals!$D$9:$D$1007564,">"&$E$7,Journals!$D$9:$D$1007564,"<"&$E$8,Journals!$J$9:$J$1007564,"Interest income from FDR")-SUMIFS(Journals!$K$9:$K$1007564,Journals!$D$9:$D$1007564,">"&$E$7,Journals!$D$9:$D$1007564,"<"&$E$8,Journals!$J$9:$J$1007564,"Interest income from FDR")) -> 0 | K30: =SUMIFS(Journals!$L$9:$L$1007564,Journals!$D$9:$D$1007564,"<"&$F$7,Journals!$J$9:$J$1007564,"Interest income from FDR")-SUMIFS(Journals!$K$9:$K$1007564,Journals!$D$9:$D$1007564,"<"&$F$7,Journals!$J$9:$J$1007564,"Interest income from FDR") -> 0 | M30: =K30+I30-H30 -> 0 | O30: =SUMIFS(Journals!$L$9:$L$1007564,Journals!$D$9:$D$1007564,"<"&$F$7,Journals!$J$9:$J$1007564,"Interest income from FDR")-SUMIFS(Journals!$K$9:$K$1007564,Journals!$D$9:$D$1007564,"<"&$F$7,Journals!$J$9:$J$1007564,"Interest income from FDR") -> 0
G31: Interest income reduce for Bond Premium | H31: =MAX(0,SUMIFS(Journals!$K$9:$K$1007564,Journals!$D$9:$D$1007564,">"&$E$7,Journals!$D$9:$D$1007564,"<"&$E$8,Journals!$J$9:$J$1007564,"Interest income reduce for Bond Premium")-SUMIFS(Journals!$L$9:$L$1007564,Journals!$D$9:$D$1007564,">"&$E$7,Journals!$D$9:$D$1007564,"<"&$E$8,Journals!$J$9:$J$1007564,"Interest income reduce for Bond Premium")) -> 0 | I31: =MAX(0,SUMIFS(Journals!$L$9:$L$1007564,Journals!$D$9:$D$1007564,">"&$E$7,Journals!$D$9:$D$1007564,"<"&$E$8,Journals!$J$9:$J$1007564,"Interest income reduce for Bond Premium")-SUMIFS(Journals!$K$9:$K$1007564,Journals!$D$9:$D$1007564,">"&$E$7,Journals!$D$9:$D$1007564,"<"&$E$8,Journals!$J$9:$J$1007564,"Interest income reduce for Bond Premium")) -> 0 | J31: =SUMIFS(Journals!$K$9:$K$1007564,Journals!$D$9:$D$1007564,"<"&$F$7,Journals!$J$9:$J$1007564,"Interest income reduce for Bond Premium")-SUMIFS(Journals!$L$9:$L$1007564,Journals!$D$9:$D$1007564,"<"&$F$7,Journals!$J$9:$J$1007564,"Interest income reduce for Bond Premium") -> 0 | L31: =J31+H31-I31 -> 0
G32: Bank charges and excise duties | H32: =MAX(0,SUMIFS(Journals!$K$9:$K$1007564,Journals!$D$9:$D$1007564,">"&$E$7,Journals!$D$9:$D$1007564,"<"&$E$8,Journals!$J$9:$J$1007564,"Bank charges and excise duties")-SUMIFS(Journals!$L$9:$L$1007564,Journals!$D$9:$D$1007564,">"&$E$7,Journals!$D$9:$D$1007564,"<"&$E$8,Journals!$J$9:$J$1007564,"Bank charges and excise duties")) -> 167021.48 | I32: =MAX(0,SUMIFS(Journals!$L$9:$L$1007564,Journals!$D$9:$D$1007564,">"&$E$7,Journals!$D$9:$D$1007564,"<"&$E$8,Journals!$J$9:$J$1007564,"Bank charges and excise duties")-SUMIFS(Journals!$K$9:$K$1007564,Journals!$D$9:$D$1007564,">"&$E$7,Journals!$D$9:$D$1007564,"<"&$E$8,Journals!$J$9:$J$1007564,"Bank charges and excise duties")) -> 0 | N32: =SUMIFS(Journals!$K$9:$K$1007564,Journals!$D$9:$D$1007564,"<"&$F$7,Journals!$J$9:$J$1007564,"Bank charges and excise duties")-SUMIFS(Journals!$L$9:$L$1007564,Journals!$D$9:$D$1007564,"<"&$F$7,Journals!$J$9:$J$1007564,"Bank charges and excise duties") -> 646075.36
G33: ='Chart of Accounts'!B25 -> Brokerage commission | H33: =MAX(0,SUMIFS(Journals!$K$9:$K$1007564,Journals!$D$9:$D$1007564,">"&$E$7,Journals!$D$9:$D$1007564,"<"&$E$8,Journals!$J$9:$J$1007564,"Brokerage Commission")-SUMIFS(Journals!$L$9:$L$1007564,Journals!$D$9:$D$1007564,">"&$E$7,Journals!$D$9:$D$1007564,"<"&$E$8,Journals!$J$9:$J$1007564,"Brokerage Commission")) -> 3714.73 | I33: =MAX(0,SUMIFS(Journals!$L$9:$L$1007564,Journals!$D$9:$D$1007564,">"&$E$7,Journals!$D$9:$D$1007564,"<"&$E$8,Journals!$J$9:$J$1007564,"brokerage commission")-SUMIFS(Journals!$K$9:$K$1007564,Journals!$D$9:$D$1007564,">"&$E$7,Journals!$D$9:$D$1007564,"<"&$E$8,Journals!$J$9:$J$1007564,"brokerage commission")) -> 0 | N33: =SUMIFS(Journals!$K$9:$K$1007564,Journals!$D$9:$D$1007564,"<"&$F$7,Journals!$J$9:$J$1007564,"brokerage commission")-SUMIFS(Journals!$L$9:$L$1007564,Journals!$D$9:$D$1007564,"<"&$F$7,Journals!$J$9:$J$1007564,"brokerage commission") -> 22405.918
G34: Unrealized gain on securities | H34: =MAX(0,SUMIFS(Journals!$K$9:$K$1007564,Journals!$D$9:$D$1007564,">"&$E$7,Journals!$D$9:$D$1007564,"<"&$E$8,Journals!$J$9:$J$1007564,"Unrealized gain on securities")-SUMIFS(Journals!$L$9:$L$1007564,Journals!$D$9:$D$1007564,">"&$E$7,Journals!$D$9:$D$1007564,"<"&$E$8,Journals!$J$9:$J$1007564,"Unrealized gain on securities")) -> 0 | I34: =MAX(0,SUMIFS(Journals!$L$9:$L$1007564,Journals!$D$9:$D$1007564,">"&$E$7,Journals!$D$9:$D$1007564,"<"&$E$8,Journals!$J$9:$J$1007564,"Unrealized gain on securities")-SUMIFS(Journals!$K$9:$K$1007564,Journals!$D$9:$D$1007564,">"&$E$7,Journals!$D$9:$D$1007564,"<"&$E$8,Journals!$J$9:$J$1007564,"Unrealized gain on securities")) -> 396063.49 | J34: =SUMIFS(Journals!$K$9:$K$1007564,Journals!$D$9:$D$1007564,"<"&$F$7,Journals!$J$9:$J$1007564,"Unrealized gain on securities")-SUMIFS(Journals!$L$9:$L$1007564,Journals!$D$9:$D$1007564,"<"&$F$7,Journals!$J$9:$J$1007564,"Unrealized gain on securities") -> -160630.88 | N34: =SUMIFS(Journals!K6:K1007561,Journals!D6:D1007561,"<"&F4,Journals!J6:J1007561,"Unrealized gain on securities")-SUMIFS(Journals!L6:L1007561,Journals!D6:D1007561,"<"&F4,Journals!J6:J1007561,"Unrealized gain on securities") -> 0 | O34: =SUMIFS(Journals!$L$9:$L$1003833,Journals!$D$9:$D$1003833,"<"&$F$7,Journals!$J$9:$J$1003833,"unrealized gain on securities")-SUMIFS(Journals!$K$9:$K$1003833,Journals!$D$9:$D$1003833,"<"&$F$7,Journals!$J$9:$J$1003833,"unrealized gain on securities") -> 160630.88
G35: Unrealized gain on T-Bill | H35: =MAX(0,SUMIFS(Journals!$K$9:$K$1007564,Journals!$D$9:$D$1007564,">"&$E$7,Journals!$D$9:$D$1007564,"<"&$E$8,Journals!$J$9:$J$1007564,"Unrealized gain on T-Bill")-SUMIFS(Journals!$L$9:$L$1007564,Journals!$D$9:$D$1007564,">"&$E$7,Journals!$D$9:$D$1007564,"<"&$E$8,Journals!$J$9:$J$1007564,"Unrealized gain on T-Bill")) -> 0 | I35: =MAX(0,SUMIFS(Journals!$L$9:$L$1007564,Journals!$D$9:$D$1007564,">"&$E$7,Journals!$D$9:$D$1007564,"<"&$E$8,Journals!$J$9:$J$1007564,"Unrealized gain on T-Bill")-SUMIFS(Journals!$K$9:$K$1007564,Journals!$D$9:$D$1007564,">"&$E$7,Journals!$D$9:$D$1007564,"<"&$E$8,Journals!$J$9:$J$1007564,"Unrealized gain on T-Bill")) -> 0 | K35: =SUMIFS(Journals!$L$9:$L$1007564,Journals!$D$9:$D$1007564,"<"&$F$7,Journals!$J$9:$J$1007564,"Unrealized gain on T-Bill")-SUMIFS(Journals!$K$9:$K$1007564,Journals!$D$9:$D$1007564,"<"&$F$7,Journals!$J$9:$J$1007564,"Unrealized gain on T-Bill") -> -0.19999999 | N35: =SUMIFS(Journals!K7:K1007562,Journals!D7:D1007562,"<"&F5,Journals!J7:J1007562,"Unrealized gain on T-Bill")-SUMIFS(Journals!L7:L1007562,Journals!D7:D1007562,"<"&F5,Journals!J7:J1007562,"Unrealized gain on T-Bill") -> 0 | O35: =SUMIFS(Journals!$L$9:$L$1003833,Journals!$D$9:$D$1003833,"<"&$F$7,Journals!$J$9:$J$1003833,"Unrealized gain on T-Bill")-SUMIFS(Journals!$K$9:$K$1003833,Journals!$D$9:$D$1003833,"<"&$F$7,Journals!$J$9:$J$1003833,"Unrealized gain on T-Bill") -> -0.19999999
G36: Unrealized gain on T-Bond | H36: =MAX(0,SUMIFS(Journals!$K$9:$K$1007564,Journals!$D$9:$D$1007564,">"&$E$7,Journals!$D$9:$D$1007564,"<"&$E$8,Journals!$J$9:$J$1007564,"Unrealized gain on T-Bond")-SUMIFS(Journals!$L$9:$L$1007564,Journals!$D$9:$D$1007564,">"&$E$7,Journals!$D$9:$D$1007564,"<"&$E$8,Journals!$J$9:$J$1007564,"Unrealized gain on T-Bond")) -> 0 | I36: =MAX(0,SUMIFS(Journals!$L$9:$L$1007564,Journals!$D$9:$D$1007564,">"&$E$7,Journals!$D$9:$D$1007564,"<"&$E$8,Journals!$J$9:$J$1007564,"Unrealized gain on T-Bond")-SUMIFS(Journals!$K$9:$K$1007564,Journals!$D$9:$D$1007564,">"&$E$7,Journals!$D$9:$D$1007564,"<"&$E$8,Journals!$J$9:$J$1007564,"Unrealized gain on T-Bond")) -> 24729620 | K36: =SUMIFS(Journals!$L$9:$L$1007564,Journals!$D$9:$D$1007564,"<"&$F$7,Journals!$J$9:$J$1007564,"Unrealized gain on T-Bond")-SUMIFS(Journals!$K$9:$K$1007564,Journals!$D$9:$D$1007564,"<"&$F$7,Journals!$J$9:$J$1007564,"Unrealized gain on T-Bond") -> 4692855.2 | N36: =SUMIFS(Journals!K8:K1007563,Journals!D8:D1007563,"<"&F6,Journals!J8:J1007563,"Unrealized gain on T-Bond")-SUMIFS(Journals!L8:L1007563,Journals!D8:D1007563,"<"&F6,Journals!J8:J1007563,"Unrealized gain on T-Bond") -> 0 | O36: =SUMIFS(Journals!$L$9:$L$1003833,Journals!$D$9:$D$1003833,"<"&$F$7,Journals!$J$9:$J$1003833,"Unrealized gain on T-Bond")-SUMIFS(Journals!$K$9:$K$1003833,Journals!$D$9:$D$1003833,"<"&$F$7,Journals!$J$9:$J$1003833,"Unrealized gain on T-Bond") -> 4692855.2
G37: ='Chart of Accounts'!B29 -> Unrealized loss on securities | H37: =MAX(0,SUMIFS(Journals!$K$9:$K$1007564,Journals!$D$9:$D$1007564,">"&$E$7,Journals!$D$9:$D$1007564,"<"&$E$8,Journals!$J$9:$J$1007564,"Unrealized loss on securities")-SUMIFS(Journals!$L$9:$L$1007564,Journals!$D$9:$D$1007564,">"&$E$7,Journals!$D$9:$D$1007564,"<"&$E$8,Journals!$J$9:$J$1007564,"Unrealized loss on securities")) -> 0 | I37: =MAX(0,SUMIFS(Journals!$L$9:$L$1007564,Journals!$D$9:$D$1007564,">"&$E$7,Journals!$D$9:$D$1007564,"<"&$E$8,Journals!$J$9:$J$1007564,"Unrealized loss on securities")-SUMIFS(Journals!$K$9:$K$1007564,Journals!$D$9:$D$1007564,">"&$E$7,Journals!$D$9:$D$1007564,"<"&$E$8,Journals!$J$9:$J$1007564,"Unrealized loss on securities")) -> 0 | N37: =SUMIFS(Journals!K9:K1007564,Journals!D9:D1007564,"<"&F7,Journals!J9:J1007564,"unrealized loss on securities")-SUMIFS(Journals!L9:L1007564,Journals!D9:D1007564,"<"&F7,Journals!J9:J1007564,"unrealized loss on securities") -> 0
G38: ='Chart of Accounts'!B30 -> Amortization of preliminary and issue expense | H38: =MAX(0,SUMIFS(Journals!$K$9:$K$1007564,Journals!$D$9:$D$1007564,">"&$E$7,Journals!$D$9:$D$1007564,"<"&$E$8,Journals!$J$9:$J$1007564,"Amortization of preliminary and issue expense")-SUMIFS(Journals!$L$9:$L$1007564,Journals!$D$9:$D$1007564,">"&$E$7,Journals!$D$9:$D$1007564,"<"&$E$8,Journals!$J$9:$J$1007564,"Amortization of preliminary and issue expense")) -> 138713.88 | I38: =MAX(0,SUMIFS(Journals!$L$9:$L$1007564,Journals!$D$9:$D$1007564,">"&$E$7,Journals!$D$9:$D$1007564,"<"&$E$8,Journals!$J$9:$J$1007564,"Amortization of preliminary and issue expense")-SUMIFS(Journals!$K$9:$K$1007564,Journals!$D$9:$D$1007564,">"&$E$7,Journals!$D$9:$D$1007564,"<"&$E$8,Journals!$J$9:$J$1007564,"Amortization of preliminary and issue expense")) -> 0 | N38: =SUMIFS(Journals!$K$9:$K$1007564,Journals!$D$9:$D$1007564,"<"&$F$7,Journals!$J$9:$J$1007564,"Amortization of preliminary and issue expense")-SUMIFS(Journals!$L$9:$L$1007564,Journals!$D$9:$D$1007564,"<"&$F$7,Journals!$J$9:$J$1007564,"Amortization of preliminary and issue expense") -> 440270.64
G39: ='Chart of Accounts'!B31 -> Management Fee | H39: =MAX(0,SUMIFS(Journals!$K$9:$K$1007564,Journals!$D$9:$D$1007564,">"&$E$7,Journals!$D$9:$D$1007564,"<"&$E$8,Journals!$J$9:$J$1007564,"management fee")-SUMIFS(Journals!$L$9:$L$1007564,Journals!$D$9:$D$1007564,">"&$E$7,Journals!$D$9:$D$1007564,"<"&$E$8,Journals!$J$9:$J$1007564,"management fee")) -> 2130135.1 | I39: =MAX(0,SUMIFS(Journals!$L$9:$L$1007564,Journals!$D$9:$D$1007564,">"&$E$7,Journals!$D$9:$D$1007564,"<"&$E$8,Journals!$J$9:$J$1007564,"management fee")-SUMIFS(Journals!$K$9:$K$1007564,Journals!$D$9:$D$1007564,">"&$E$7,Journals!$D$9:$D$1007564,"<"&$E$8,Journals!$J$9:$J$1007564,"management fee")) -> 0 | N39: =SUMIFS(Journals!$K$9:$K$1007564,Journals!$D$9:$D$1007564,"<"&$F$7,Journals!$J$9:$J$1007564,"management fee")-SUMIFS(Journals!$L$9:$L$1007564,Journals!$D$9:$D$1007564,"<"&$F$7,Journals!$J$9:$J$1007564,"management fee") -> 3385722.9
G40: ='Chart of Accounts'!B32 -> Trustee fee | H40: =MAX(0,SUMIFS(Journals!$K$9:$K$1007564,Journals!$D$9:$D$1007564,">"&$E$7,Journals!$D$9:$D$1007564,"<"&$E$8,Journals!$J$9:$J$1007564,"trustee fee")-SUMIFS(Journals!$L$9:$L$1007564,Journals!$D$9:$D$1007564,">"&$E$7,Journals!$D$9:$D$1007564,"<"&$E$8,Journals!$J$9:$J$1007564,"trustee fee")) -> 213013.5 | I40: =MAX(0,SUMIFS(Journals!$L$9:$L$1007564,Journals!$D$9:$D$1007564,">"&$E$7,Journals!$D$9:$D$1007564,"<"&$E$8,Journals!$J$9:$J$1007564,"trustee fee")-SUMIFS(Journals!$K$9:$K$1007564,Journals!$D$9:$D$1007564,">"&$E$7,Journals!$D$9:$D$1007564,"<"&$E$8,Journals!$J$9:$J$1007564,"trustee fee")) -> 0 | N40: =SUMIFS(Journals!$K$9:$K$1007564,Journals!$D$9:$D$1007564,"<"&$F$7,Journals!$J$9:$J$1007564,"trustee fee")-SUMIFS(Journals!$L$9:$L$1007564,Journals!$D$9:$D$1007564,"<"&$F$7,Journals!$J$9:$J$1007564,"trustee fee") -> 361206.69
G41: Advanced BSEC Annual Fee | H41: =MAX(0,SUMIFS(Journals!$K$9:$K$1007494,Journals!$D$9:$D$1007494,">"&$E$7,Journals!$D$9:$D$1007494,"<"&$E$8,Journals!$J$9:$J$1007494,"Advanced BSEC Annual Fee")-SUMIFS(Journals!$L$9:$L$1007494,Journals!$D$9:$D$1007494,">"&$E$7,Journals!$D$9:$D$1007494,"<"&$E$8,Journals!$J$9:$J$1007494,"Advanced BSEC Annual Fee")) -> 138836.11 | I41: =MAX(0,SUMIFS(Journals!$L$9:$L$1007494,Journals!$D$9:$D$1007494,">"&$E$7,Journals!$D$9:$D$1007494,"<"&$E$8,Journals!$J$9:$J$1007494,"Advanced BSEC Annual Fee")-SUMIFS(Journals!$K$9:$K$1007494,Journals!$D$9:$D$1007494,">"&$E$7,Journals!$D$9:$D$1007494,"<"&$E$8,Journals!$J$9:$J$1007494,"Advanced BSEC Annual Fee")) -> 0 | J41: =SUMIFS(Journals!$K$9:$K$1007494,Journals!$D$9:$D$1007494,"<"&$F$7,Journals!$J$9:$J$1007494,"Advanced BSEC Annual Fee")-SUMIFS(Journals!$L$9:$L$1007494,Journals!$D$9:$D$1007494,"<"&$F$7,Journals!$J$9:$J$1007494,"Advanced BSEC Annual Fee") -> 0 | L41: =J41+H41-I41 -> 138836.11
G42: ='Chart of Accounts'!B33 -> BSEC Annual Fee | H42: =MAX(0,SUMIFS(Journals!$K$9:$K$1007564,Journals!$D$9:$D$1007564,">"&$E$7,Journals!$D$9:$D$1007564,"<"&$E$8,Journals!$J$9:$J$1007564,"bsec annual fee")-SUMIFS(Journals!$L$9:$L$1007564,Journals!$D$9:$D$1007564,">"&$E$7,Journals!$D$9:$D$1007564,"<"&$E$8,Journals!$J$9:$J$1007564,"bsec annual fee")) -> 442041.41 | I42: =MAX(0,SUMIFS(Journals!$L$9:$L$1007564,Journals!$D$9:$D$1007564,">"&$E$7,Journals!$D$9:$D$1007564,"<"&$E$8,Journals!$J$9:$J$1007564,"bsec annual fee")-SUMIFS(Journals!$K$9:$K$1007564,Journals!$D$9:$D$1007564,">"&$E$7,Journals!$D$9:$D$1007564,"<"&$E$8,Journals!$J$9:$J$1007564,"bsec annual fee")) -> 0 | N42: =SUMIFS(Journals!$K$9:$K$1007564,Journals!$D$9:$D$1007564,"<"&$F$7,Journals!$J$9:$J$1007564,"bsec annual fee")-SUMIFS(Journals!$L$9:$L$1007564,Journals!$D$9:$D$1007564,"<"&$F$7,Journals!$J$9:$J$1007564,"bsec annual fee") -> 481302.24
G43: ='Chart of Accounts'!B34 -> Audit fee | H43: =MAX(0,SUMIFS(Journals!$K$9:$K$1007564,Journals!$D$9:$D$1007564,">"&$E$7,Journals!$D$9:$D$1007564,"<"&$E$8,Journals!$J$9:$J$1007564,"audit fee")-SUMIFS(Journals!$L$9:$L$1007564,Journals!$D$9:$D$1007564,">"&$E$7,Journals!$D$9:$D$1007564,"<"&$E$8,Journals!$J$9:$J$1007564,"audit fee")) -> 0 | I43: =MAX(0,SUMIFS(Journals!$L$9:$L$1007564,Journals!$D$9:$D$1007564,">"&$E$7,Journals!$D$9:$D$1007564,"<"&$E$8,Journals!$J$9:$J$1007564,"audit fee")-SUMIFS(Journals!$K$9:$K$1007564,Journals!$D$9:$D$1007564,">"&$E$7,Journals!$D$9:$D$1007564,"<"&$E$8,Journals!$J$9:$J$1007564,"audit fee")) -> 0 | N43: =SUMIFS(Journals!$K$9:$K$1007564,Journals!$D$9:$D$1007564,"<"&$F$7,Journals!$J$9:$J$1007564,"audit fee")-SUMIFS(Journals!$L$9:$L$1007564,Journals!$D$9:$D$1007564,"<"&$F$7,Journals!$J$9:$J$1007564,"audit fee") -> 89500
G44: ='Chart of Accounts'!B35 -> CDBL charges | H44: =MAX(0,SUMIFS(Journals!$K$9:$K$1007564,Journals!$D$9:$D$1007564,">"&$E$7,Journals!$D$9:$D$1007564,"<"&$E$8,Journals!$J$9:$J$1007564,"cdbl charges")-SUMIFS(Journals!$L$9:$L$1007564,Journals!$D$9:$D$1007564,">"&$E$7,Journals!$D$9:$D$1007564,"<"&$E$8,Journals!$J$9:$J$1007564,"cdbl charges")) -> 96969 | I44: =MAX(0,SUMIFS(Journals!$L$9:$L$1007564,Journals!$D$9:$D$1007564,">"&$E$7,Journals!$D$9:$D$1007564,"<"&$E$8,Journals!$J$9:$J$1007564,"cdbl charges")-SUMIFS(Journals!$K$9:$K$1007564,Journals!$D$9:$D$1007564,">"&$E$7,Journals!$D$9:$D$1007564,"<"&$E$8,Journals!$J$9:$J$1007564,"cdbl charges")) -> 0 | N44: =SUMIFS(Journals!$K$9:$K$1007564,Journals!$D$9:$D$1007564,"<"&$F$7,Journals!$J$9:$J$1007564,"cdbl charges")-SUMIFS(Journals!$L$9:$L$1007564,Journals!$D$9:$D$1007564,"<"&$F$7,Journals!$J$9:$J$1007564,"cdbl charges") -> 4583.34
G45: ='Chart of Accounts'!B36 -> Fair value adjustment | H45: =MAX(0,SUMIFS(Journals!$K$9:$K$1007564,Journals!$D$9:$D$1007564,">"&$E$7,Journals!$D$9:$D$1007564,"<"&$E$8,Journals!$J$9:$J$1007564,"Fair value adjustment")-SUMIFS(Journals!$L$9:$L$1007564,Journals!$D$9:$D$1007564,">"&$E$7,Journals!$D$9:$D$1007564,"<"&$E$8,Journals!$J$9:$J$1007564,"Fair value adjustment")) -> 396063.49 | I45: =MAX(0,SUMIFS(Journals!$L$9:$L$1007564,Journals!$D$9:$D$1007564,">"&$E$7,Journals!$D$9:$D$1007564,"<"&$E$8,Journals!$J$9:$J$1007564,"fair value adjustment")-SUMIFS(Journals!$K$9:$K$1007564,Journals!$D$9:$D$1007564,">"&$E$7,Journals!$D$9:$D$1007564,"<"&$E$8,Journals!$J$9:$J$1007564,"fair value adjustment")) -> 0 | J45: =MAX(0,SUMIFS(Journals!K9:K1007564,Journals!D9:D1007564,"<"&F7,Journals!J9:J1007564,"fair value adjustment")-SUMIFS(Journals!L9:L1007564,Journals!D9:D1007564,"<"&F7,Journals!J9:J1007564,"fair value adjustment")) -> 160630.88 | K45: =MAX(0,SUMIFS(Journals!L9:L1007564,Journals!D9:D1007564,"<"&F7,Journals!J9:J1007564,"Fair value adjustment")-SUMIFS(Journals!K9:K1007564,Journals!D9:D1007564,"<"&F7,Journals!J9:J1007564,"fair value adjustment")) -> 0 | L45: =MAX(0,H45-I45+J45-K45) -> 556694.37 | M45: =MAX(0,I45-H45-J45+K45) -> 0
G46: Fair value adjustment in T-Bill | H46: =MAX(0,SUMIFS(Journals!$K$9:$K$1007564,Journals!$D$9:$D$1007564,">"&$E$7,Journals!$D$9:$D$1007564,"<"&$E$8,Journals!$J$9:$J$1007564,"Fair value adjustment in T-Bill")-SUMIFS(Journals!$L$9:$L$1007564,Journals!$D$9:$D$1007564,">"&$E$7,Journals!$D$9:$D$1007564,"<"&$E$8,Journals!$J$9:$J$1007564,"Fair value adjustment in T-Bill")) -> 0 | I46: =MAX(0,SUMIFS(Journals!$L$9:$L$1007564,Journals!$D$9:$D$1007564,">"&$E$7,Journals!$D$9:$D$1007564,"<"&$E$8,Journals!$J$9:$J$1007564,"Fair value adjustment in T-Bill")-SUMIFS(Journals!$K$9:$K$1007564,Journals!$D$9:$D$1007564,">"&$E$7,Journals!$D$9:$D$1007564,"<"&$E$8,Journals!$J$9:$J$1007564,"Fair value adjustment in T-Bill")) -> 0 | J46: =MAX(0,SUMIFS(Journals!K9:K1007564,Journals!D9:D1007564,"<"&F7,Journals!J9:J1007564,"Fair value adjustment in T-Bill")-SUMIFS(Journals!L9:L1007564,Journals!D9:D1007564,"<"&F7,Journals!J9:J1007564,"Fair value adjustment in T-Bill")) -> 0 | K46: =MAX(0,SUMIFS(Journals!L9:L1007564,Journals!D9:D1007564,"<"&F7,Journals!J9:J1007564,"Fair value adjustment in T-Bill")-SUMIFS(Journals!K9:K1007564,Journals!D9:D1007564,"<"&F7,Journals!J9:J1007564,"Fair value adjustment in T-Bill")) -> 0.19999999 | L46: =MAX(0,H46-I46+J46-K46) -> 0 | M46: =MAX(0,I46-H46-J46+K46) -> 0.19999999
G47: Fair value adjustment in T-Bond | H47: =MAX(0,SUMIFS(Journals!$K$9:$K$1007564,Journals!$D$9:$D$1007564,">"&$E$7,Journals!$D$9:$D$1007564,"<"&$E$8,Journals!$J$9:$J$1007564,"Fair value adjustment in T-Bond")-SUMIFS(Journals!$L$9:$L$1007564,Journals!$D$9:$D$1007564,">"&$E$7,Journals!$D$9:$D$1007564,"<"&$E$8,Journals!$J$9:$J$1007564,"Fair value adjustment in T-Bond")) -> 24729620 | I47: =MAX(0,SUMIFS(Journals!$L$9:$L$1007564,Journals!$D$9:$D$1007564,">"&$E$7,Journals!$D$9:$D$1007564,"<"&$E$8,Journals!$J$9:$J$1007564,"fair value adjustment in T-Bond")-SUMIFS(Journals!$K$9:$K$1007564,Journals!$D$9:$D$1007564,">"&$E$7,Journals!$D$9:$D$1007564,"<"&$E$8,Journals!$J$9:$J$1007564,"fair value adjustment in T-Bond")) -> 0 | J47: =MAX(0,SUMIFS(Journals!K9:K1007564,Journals!D9:D1007564,"<"&F7,Journals!J9:J1007564,"Fair value adjustment in T-Bond")-SUMIFS(Journals!L9:L1007564,Journals!D9:D1007564,"<"&F7,Journals!J9:J1007564,"Fair value adjustment in T-Bond")) -> 4692855.2 | K47: =MAX(0,SUMIFS(Journals!L9:L1007564,Journals!D9:D1007564,"<"&F7,Journals!J9:J1007564,"Fair value adjustment in T-Bond")-SUMIFS(Journals!K9:K1007564,Journals!D9:D1007564,"<"&F7,Journals!J9:J1007564,"fair value adjustment in T-Bond")) -> 0 | L47: =MAX(0,H47-I47+J47-K47) -> 29422475 | M47: =MAX(0,I47-H47-J47+K47) -> 0
G48: Interest receivables from FDR | H48: =MAX(0,SUMIFS(Journals!$K$9:$K$1007564,Journals!$D$9:$D$1007564,">"&$E$7,Journals!$D$9:$D$1007564,"<"&$E$8,Journals!$J$9:$J$1007564,"Interest receivables from FDR")-SUMIFS(Journals!$L$9:$L$1007564,Journals!$D$9:$D$1007564,">"&$E$7,Journals!$D$9:$D$1007564,"<"&$E$8,Journals!$J$9:$J$1007564,"Interest receivables from FDR")) -> 728800.18 | I48: =MAX(0,SUMIFS(Journals!$L$9:$L$1007564,Journals!$D$9:$D$1007564,">"&$E$7,Journals!$D$9:$D$1007564,"<"&$E$8,Journals!$J$9:$J$1007564,"Interest receivables from FDR")-SUMIFS(Journals!$K$9:$K$1007564,Journals!$D$9:$D$1007564,">"&$E$7,Journals!$D$9:$D$1007564,"<"&$E$8,Journals!$J$9:$J$1007564,"Interest receivables from FDR")) -> 0 | J48: =SUMIFS(Journals!$K$9:$K$1007564,Journals!$D$9:$D$1007564,"<"&$F$7,Journals!$J$9:$J$1007564,"Interest receivables from FDR")-SUMIFS(Journals!$L$9:$L$1007564,Journals!$D$9:$D$1007564,"<"&$F$7,Journals!$J$9:$J$1007564,"Interest receivables from FDR") -> 1361753 | L48: =J48+H48-I48 -> 2090553.2
G49: ='Chart of Accounts'!B40 -> Payable to broker | H49: =MAX(0,SUMIFS(Journals!$K$9:$K$1007564,Journals!$D$9:$D$1007564,">"&$E$7,Journals!$D$9:$D$1007564,"<"&$E$8,Journals!$J$9:$J$1007564,"payable to broker")-SUMIFS(Journals!$L$9:$L$1007564,Journals!$D$9:$D$1007564,">"&$E$7,Journals!$D$9:$D$1007564,"<"&$E$8,Journals!$J$9:$J$1007564,"payable to broker")) -> 0 | I49: =MAX(0,SUMIFS(Journals!$L$9:$L$1007564,Journals!$D$9:$D$1007564,">"&$E$7,Journals!$D$9:$D$1007564,"<"&$E$8,Journals!$J$9:$J$1007564,"payable to broker")-SUMIFS(Journals!$K$9:$K$1007564,Journals!$D$9:$D$1007564,">"&$E$7,Journals!$D$9:$D$1007564,"<"&$E$8,Journals!$J$9:$J$1007564,"payable to broker")) -> 0 | K49: =SUMIFS(Journals!$L$9:$L$1007564,Journals!$D$9:$D$1007564,"<"&$F$7,Journals!$J$9:$J$1007564,"payable to broker")-SUMIFS(Journals!$K$9:$K$1007564,Journals!$D$9:$D$1007564,"<"&$F$7,Journals!$J$9:$J$1007564,"payable to broker") -> 0 | M49: =K49+I49-H49 -> 0
G50: ='Chart of Accounts'!B41 -> Other operating expenses | H50: =MAX(0,SUMIFS(Journals!$K$9:$K$1007564,Journals!$D$9:$D$1007564,">"&$E$7,Journals!$D$9:$D$1007564,"<"&$E$8,Journals!$J$9:$J$1007564,"OTHER OPERATING EXPENSES")-SUMIFS(Journals!$L$9:$L$1007564,Journals!$D$9:$D$1007564,">"&$E$7,Journals!$D$9:$D$1007564,"<"&$E$8,Journals!$J$9:$J$1007564,"OTHER OPERATING EXPENSES")) -> 0 | I50: =MAX(0,SUMIFS(Journals!$L$9:$L$1007564,Journals!$D$9:$D$1007564,">"&$E$7,Journals!$D$9:$D$1007564,"<"&$E$8,Journals!$J$9:$J$1007564,"OTHER OPERATING EXPENSES")-SUMIFS(Journals!$K$9:$K$1007564,Journals!$D$9:$D$1007564,">"&$E$7,Journals!$D$9:$D$1007564,"<"&$E$8,Journals!$J$9:$J$1007564,"OTHER OPERATING EXPENSES")) -> 0 | N50: =SUMIFS(Journals!$K$9:$K$1007564,Journals!$D$9:$D$1007564,"<"&$F$7,Journals!$J$9:$J$1007564,"OTHER OPERATING EXPENSES")-SUMIFS(Journals!$L$9:$L$1007564,Journals!$D$9:$D$1007564,"<"&$F$7,Journals!$J$9:$J$1007564,"OTHER OPERATING EXPENSES") -> 46800
G51: ='Chart of Accounts'!B42 -> Dividend income | H51: =MAX(0,SUMIFS(Journals!$K$9:$K$1007564,Journals!$D$9:$D$1007564,">"&$E$7,Journals!$D$9:$D$1007564,"<"&$E$8,Journals!$J$9:$J$1007564,"dividend income")) -> 0 | I51: =MAX(0,SUMIFS(Journals!$L$9:$L$1007564,Journals!$D$9:$D$1007564,">"&$E$7,Journals!$D$9:$D$1007564,"<"&$E$8,Journals!$J$9:$J$1007564,"dividend income")) -> 201382.5 | O51: =SUMIFS(Journals!$L$9:$L$1007564,Journals!$D$9:$D$1007564,"<"&$F$7,Journals!$J$9:$J$1007564,"dividend income")-SUMIFS(Journals!$K$9:$K$1007564,Journals!$D$9:$D$1007564,"<"&$F$7,Journals!$J$9:$J$1007564,"dividend income") -> 1124298.6
G52: ='Chart of Accounts'!B43 -> Dividend receivable | H52: =MAX(0,SUMIFS(Journals!$K$9:$K$1007564,Journals!$D$9:$D$1007564,">"&$E$7,Journals!$D$9:$D$1007564,"<"&$E$8,Journals!$J$9:$J$1007564,"dividend receivable")) -> 201382.5 | I52: =MAX(0,SUMIFS(Journals!$L$9:$L$1007564,Journals!$D$9:$D$1007564,">"&$E$7,Journals!$D$9:$D$1007564,"<"&$E$8,Journals!$J$9:$J$1007564,"dividend receivable")) -> 201382.5 | J52: =SUMIFS(Journals!$K$9:$K$1007564,Journals!$D$9:$D$1007564,"<"&$F$7,Journals!$J$9:$J$1007564,"dividend receivable")-SUMIFS(Journals!$L$9:$L$1007564,Journals!$D$9:$D$1007564,"<"&$F$7,Journals!$J$9:$J$1007564,"dividend receivable") -> 0 | L52: =J52+H52-I52 -> 0
G53: ='Chart of Accounts'!B44 -> Custodian fee | H53: =MAX(0,SUMIFS(Journals!$K$9:$K$1007564,Journals!$D$9:$D$1007564,">"&$E$7,Journals!$D$9:$D$1007564,"<"&$E$8,Journals!$J$9:$J$1007564,"custodian fee")-SUMIFS(Journals!$L$9:$L$1007564,Journals!$D$9:$D$1007564,">"&$E$7,Journals!$D$9:$D$1007564,"<"&$E$8,Journals!$J$9:$J$1007564,"custodian fee")) -> 220439.89 | N53: =SUMIFS(Journals!$K$9:$K$1007564,Journals!$D$9:$D$1007564,"<"&$F$7,Journals!$J$9:$J$1007564,"custodian fee")-SUMIFS(Journals!$L$9:$L$1007564,Journals!$D$9:$D$1007564,"<"&$F$7,Journals!$J$9:$J$1007564,"custodian fee") -> 369248.69
G54: ='Chart of Accounts'!B45 -> IPO Application | H54: =MAX(0,SUMIFS(Journals!$K$9:$K$1007564,Journals!$D$9:$D$1007564,">"&$E$7,Journals!$D$9:$D$1007564,"<"&$E$8,Journals!$J$9:$J$1007564,"IPO APPLICATION")-SUMIFS(Journals!$L$9:$L$1007564,Journals!$D$9:$D$1007564,">"&$E$7,Journals!$D$9:$D$1007564,"<"&$E$8,Journals!$J$9:$J$1007564,"IPO APPLICATION")) -> 0 | I54: =MAX(0,SUMIFS(Journals!$L$9:$L$1007564,Journals!$D$9:$D$1007564,">"&$E$7,Journals!$D$9:$D$1007564,"<"&$E$8,Journals!$J$9:$J$1007564,"IPO APPLICATION")-SUMIFS(Journals!$K$9:$K$1007564,Journals!$D$9:$D$1007564,">"&$E$7,Journals!$D$9:$D$1007564,"<"&$E$8,Journals!$J$9:$J$1007564,"IPO APPLICATION")) -> 0 | J54: =SUMIFS(Journals!$K$9:$K$1007564,Journals!$D$9:$D$1007564,"<"&$F$7,Journals!$J$9:$J$1007564,"IPO APPLICATION")-SUMIFS(Journals!$L$9:$L$1007564,Journals!$D$9:$D$1007564,"<"&$F$7,Journals!$J$9:$J$1007564,"IPO APPLICATION") -> 0 | L54: =J54+H54-I54 -> 0
G55: ='Chart of Accounts'!B46 -> IPO Application Fee | H55: =MAX(0,SUMIFS(Journals!$K$9:$K$1007564,Journals!$D$9:$D$1007564,">"&$E$7,Journals!$D$9:$D$1007564,"<"&$E$8,Journals!$J$9:$J$1007564,"IPO APPLICATION FEE")-SUMIFS(Journals!$L$9:$L$1007564,Journals!$D$9:$D$1007564,">"&$E$7,Journals!$D$9:$D$1007564,"<"&$E$8,Journals!$J$9:$J$1007564,"IPO APPLICATION FEE")) -> 0 | N55: =SUMIFS(Journals!$K$9:$K$1007564,Journals!$D$9:$D$1007564,"<"&$F$7,Journals!$J$9:$J$1007564,"IPO APPLICATION FEE")-SUMIFS(Journals!$L$9:$L$1007564,Journals!$D$9:$D$1007564,"<"&$F$7,Journals!$J$9:$J$1007564,"IPO APPLICATION FEE") -> 6000
G56: Realized gain | H56: =MAX(0,SUMIFS(Journals!$K$9:$K$1007564,Journals!$D$9:$D$1007564,">"&$E$7,Journals!$D$9:$D$1007564,"<"&$E$8,Journals!$J$9:$J$1007564,"realized gain")-SUMIFS(Journals!$L$9:$L$1007564,Journals!$D$9:$D$1007564,">"&$E$7,Journals!$D$9:$D$1007564,"<"&$E$8,Journals!$J$9:$J$1007564,"realized gain")) -> 0 | I56: =MAX(0,SUMIFS(Journals!$L$9:$L$1007564,Journals!$D$9:$D$1007564,">"&$E$7,Journals!$D$9:$D$1007564,"<"&$E$8,Journals!$J$9:$J$1007564,"realized gain")-SUMIFS(Journals!$K$9:$K$1007564,Journals!$D$9:$D$1007564,">"&$E$7,Journals!$D$9:$D$1007564,"<"&$E$8,Journals!$J$9:$J$1007564,"realized gain")) -> 4382688.7 | O56: =SUMIFS(Journals!$L$9:$L$1007564,Journals!$D$9:$D$1007564,"<"&$F$7,Journals!$J$9:$J$1007564,"realized gain")-SUMIFS(Journals!$K$9:$K$1007564,Journals!$D$9:$D$1007564,"<"&$F$7,Journals!$J$9:$J$1007564,"realized gain") -> 651705.05
G57: Realized gain from Bond Premium | H57: =MAX(0,SUMIFS(Journals!$K$9:$K$1007564,Journals!$D$9:$D$1007564,">"&$E$7,Journals!$D$9:$D$1007564,"<"&$E$8,Journals!$J$9:$J$1007564,"Realized gain from Bond Premium")-SUMIFS(Journals!$L$9:$L$1007564,Journals!$D$9:$D$1007564,">"&$E$7,Journals!$D$9:$D$1007564,"<"&$E$8,Journals!$J$9:$J$1007564,"Realized gain from Bond Premium")) -> 0 | I57: =MAX(0,SUMIFS(Journals!$L$9:$L$1007564,Journals!$D$9:$D$1007564,">"&$E$7,Journals!$D$9:$D$1007564,"<"&$E$8,Journals!$J$9:$J$1007564,"Realized gain from Bond Premium")-SUMIFS(Journals!$K$9:$K$1007564,Journals!$D$9:$D$1007564,">"&$E$7,Journals!$D$9:$D$1007564,"<"&$E$8,Journals!$J$9:$J$1007564,"Realized gain from Bond Premium")) -> 0 | O57: =SUMIFS(Journals!$L$9:$L$1007564,Journals!$D$9:$D$1007564,"<"&$F$7,Journals!$J$9:$J$1007564,"Realized gain from Bond Premium")-SUMIFS(Journals!$K$9:$K$1007564,Journals!$D$9:$D$1007564,"<"&$F$7,Journals!$J$9:$J$1007564,"Realized gain from Bond Premium") -> 0
G58: Realized gain on T-Bill | H58: =MAX(0,SUMIFS(Journals!$K$9:$K$1007564,Journals!$D$9:$D$1007564,">"&$E$7,Journals!$D$9:$D$1007564,"<"&$E$8,Journals!$J$9:$J$1007564,"realized gain on T-Bill")-SUMIFS(Journals!$L$9:$L$1007564,Journals!$D$9:$D$1007564,">"&$E$7,Journals!$D$9:$D$1007564,"<"&$E$8,Journals!$J$9:$J$1007564,"realized gain on T-Bill")) -> 0 | I58: =MAX(0,SUMIFS(Journals!$L$9:$L$1007564,Journals!$D$9:$D$1007564,">"&$E$7,Journals!$D$9:$D$1007564,"<"&$E$8,Journals!$J$9:$J$1007564,"realized gain on T-Bill")-SUMIFS(Journals!$K$9:$K$1007564,Journals!$D$9:$D$1007564,">"&$E$7,Journals!$D$9:$D$1007564,"<"&$E$8,Journals!$J$9:$J$1007564,"realized gain on T-Bill")) -> 0 | O58: =SUMIFS(Journals!$L$9:$L$1007564,Journals!$D$9:$D$1007564,"<"&$F$7,Journals!$J$9:$J$1007564,"realized gain on T-Bill")-SUMIFS(Journals!$K$9:$K$1007564,Journals!$D$9:$D$1007564,"<"&$F$7,Journals!$J$9:$J$1007564,"realized gain on T-Bill") -> 13371355
G59: Realized gain on T-Bond | H59: =MAX(0,SUMIFS(Journals!$K$9:$K$1007564,Journals!$D$9:$D$1007564,">"&$E$7,Journals!$D$9:$D$1007564,"<"&$E$8,Journals!$J$9:$J$1007564,"realized gain on T-Bond")-SUMIFS(Journals!$L$9:$L$1007564,Journals!$D$9:$D$1007564,">"&$E$7,Journals!$D$9:$D$1007564,"<"&$E$8,Journals!$J$9:$J$1007564,"realized gain on T-Bond")) -> 0 | I59: =MAX(0,SUMIFS(Journals!$L$9:$L$1007564,Journals!$D$9:$D$1007564,">"&$E$7,Journals!$D$9:$D$1007564,"<"&$E$8,Journals!$J$9:$J$1007564,"realized gain on T-Bond")-SUMIFS(Journals!$K$9:$K$1007564,Journals!$D$9:$D$1007564,">"&$E$7,Journals!$D$9:$D$1007564,"<"&$E$8,Journals!$J$9:$J$1007564,"realized gain on T-Bond")) -> 7438790 | O59: =SUMIFS(Journals!$L$9:$L$1007564,Journals!$D$9:$D$1007564,"<"&$F$7,Journals!$J$9:$J$1007564,"realized gain on T-Bond")-SUMIFS(Journals!$K$9:$K$1007564,Journals!$D$9:$D$1007564,"<"&$F$7,Journals!$J$9:$J$1007564,"realized gain on T-Bond") -> 4110088.8
G60: Receivable from broker | H60: =MAX(0,SUMIFS(Journals!$K$9:$K$1007564,Journals!$D$9:$D$1007564,">"&$E$7,Journals!$D$9:$D$1007564,"<"&$E$8,Journals!$J$9:$J$1007564,"receivable from broker")-SUMIFS(Journals!$L$9:$L$1007564,Journals!$D$9:$D$1007564,">"&$E$7,Journals!$D$9:$D$1007564,"<"&$E$8,Journals!$J$9:$J$1007564,"receivable from broker")) -> 0 | I60: =MAX(0,SUMIFS(Journals!$L$9:$L$1007564,Journals!$D$9:$D$1007564,">"&$E$7,Journals!$D$9:$D$1007564,"<"&$E$8,Journals!$J$9:$J$1007564,"Receivable from broker")-SUMIFS(Journals!$K$9:$K$1007564,Journals!$D$9:$D$1007564,">"&$E$7,Journals!$D$9:$D$1007564,"<"&$E$8,Journals!$J$9:$J$1007564,"Receivable from broker")) -> 134104.5 | J60: =SUMIFS(Journals!$K$9:$K$1007564,Journals!$D$9:$D$1007564,"<"&$F$7,Journals!$J$9:$J$1007564,"receivable from broker")-SUMIFS(Journals!$L$9:$L$1007564,Journals!$D$9:$D$1007564,"<"&$F$7,Journals!$J$9:$J$1007564,"receivable from broker") -> 134104.64 | L60: =J60+H60-I60 -> 0.1418
G61: Dividend Equalization Reserve | H61: =MAX(0,SUMIFS(Journals!$K$9:$K$1007564,Journals!$D$9:$D$1007564,">"&$E$7,Journals!$D$9:$D$1007564,"<"&$E$8,Journals!$J$9:$J$1007564,"Dividend Equalization Reserve")-SUMIFS(Journals!$L$9:$L$1007564,Journals!$D$9:$D$1007564,">"&$E$7,Journals!$D$9:$D$1007564,"<"&$E$8,Journals!$J$9:$J$1007564,"Dividend Equalization Reserve")) -> 0 | I61: =MAX(0,SUMIFS(Journals!$L$9:$L$1007564,Journals!$D$9:$D$1007564,">"&$E$7,Journals!$D$9:$D$1007564,"<"&$E$8,Journals!$J$9:$J$1007564,"Dividend Equalization Reserve")-SUMIFS(Journals!$K$9:$K$1007564,Journals!$D$9:$D$1007564,">"&$E$7,Journals!$D$9:$D$1007564,"<"&$E$8,Journals!$J$9:$J$1007564,"Dividend Equalization Reserve")) -> 0 | K61: =SUMIFS(Journals!$L$9:$L$1007564,Journals!$D$9:$D$1007564,"<"&$F$7,Journals!$J$9:$J$1007564,"Dividend Equalization Reserve")-SUMIFS(Journals!$K$9:$K$1007564,Journals!$D$9:$D$1007564,"<"&$F$7,Journals!$J$9:$J$1007564,"Dividend Equalization Reserve") -> 0 | M61: =K61+I61-H61 -> 0 | N61: =K61 -> 0
G62: Retained Earnings | H62: =MAX(0,SUMIFS(Journals!$K$9:$K$1007564,Journals!$D$9:$D$1007564,">"&$E$7,Journals!$D$9:$D$1007564,"<"&$E$8,Journals!$J$9:$J$1007564,"Retained Earnings")-SUMIFS(Journals!$L$9:$L$1007564,Journals!$D$9:$D$1007564,">"&$E$7,Journals!$D$9:$D$1007564,"<"&$E$8,Journals!$J$9:$J$1007564,"Retained Earnings")) -> 0 | I62: =MAX(0,SUMIFS(Journals!$L$9:$L$1007564,Journals!$D$9:$D$1007564,">"&$E$7,Journals!$D$9:$D$1007564,"<"&$E$8,Journals!$J$9:$J$1007564,"Retained Earnigs")-SUMIFS(Journals!$K$9:$K$1007564,Journals!$D$9:$D$1007564,">"&$E$7,Journals!$D$9:$D$1007564,"<"&$E$8,Journals!$J$9:$J$1007564,"Retained Earnigs")) -> 0
G63: Dividend Payable | H63: =SUMIFS(Journals!$K$9:$K$1007564,Journals!$D$9:$D$1007564,">"&$E$7,Journals!$D$9:$D$1007564,"<"&$E$8,Journals!$J$9:$J$1007564,"Dividend Payable") -> 0 | I63: =MAX(0,SUMIFS(Journals!$L$9:$L$1007564,Journals!$D$9:$D$1007564,">"&$E$7,Journals!$D$9:$D$1007564,"<"&$E$8,Journals!$J$9:$J$1007564,"Dividend Payable")) -> 0 | J63: =SUMIFS(Journals!$K$9:$K$1007564,Journals!$D$9:$D$1007564,"<"&$F$7,Journals!$J$9:$J$1007564,"Dividend Payable") -> 0 | K63: =SUMIFS(Journals!$L$9:$L$1007564,Journals!$D$9:$D$1007564,"<"&$F$7,Journals!$J$9:$J$1007564,"Dividend Payable") -> 0 | M63: =I63-H63 -> 0 | N63: =J63 -> 0
G64: Withholding Tax Payable | H64: =SUMIFS(Journals!$K$9:$K$1007564,Journals!$D$9:$D$1007564,">"&$E$7,Journals!$D$9:$D$1007564,"<"&$E$8,Journals!$J$9:$J$1007564,"Withholding Tax Payable") -> 355701.13 | I64: =SUMIFS(Journals!$L$9:$L$1007564,Journals!$D$9:$D$1007564,">"&$E$7,Journals!$D$9:$D$1007564,"<"&$E$8,Journals!$J$9:$J$1007564,"Withholding Tax Payable") -> 353100.63 | J64: =SUMIFS(Journals!$K$9:$K$1007564,Journals!$D$9:$D$1007564,"<"&$F$7,Journals!$J$9:$J$1007564,"Withholding Tax Payable")-SUMIFS(Journals!$L$9:$L$1007564,Journals!$D$9:$D$1007564,"<"&$F$7,Journals!$J$9:$J$1007564,"Withholding Tax Payable") -> -103140.79 | K64: =SUMIFS(Journals!$L$9:$L$1007564,Journals!$D$9:$D$1007564,"<"&$F$7,Journals!$J$9:$J$1007564,"Withholding Tax Payable")-SUMIFS(Journals!$K$9:$K$1007564,Journals!$D$9:$D$1007564,"<"&$F$7,Journals!$J$9:$J$1007564,"Withholding Tax Payable") -> 103140.79 | M64: =K64+I64-H64 -> 100540.28
G65: Investments in Bond (BXSUKUK) | H65: =MAX(0,SUMIFS(Journals!$K$9:$K$1007564,Journals!$D$9:$D$1007564,">"&$E$7,Journals!$D$9:$D$1007564,"<"&$E$8,Journals!$J$9:$J$1007564,"Investments in Bond (BXSUKUK)")-SUMIFS(Journals!$L$9:$L$1007564,Journals!$D$9:$D$1007564,">"&$E$7,Journals!$D$9:$D$1007564,"<"&$E$8,Journals!$J$9:$J$1007564,"Investments in Bond (BXSUKUK)")) -> 0 | I65: =MAX(0,SUMIFS(Journals!$L$9:$L$1007564,Journals!$D$9:$D$1007564,">"&$E$7,Journals!$D$9:$D$1007564,"<"&$E$8,Journals!$J$9:$J$1007564,"Investments in Bond (BXSUKUK)")-SUMIFS(Journals!$K$9:$K$1007564,Journals!$D$9:$D$1007564,">"&$E$7,Journals!$D$9:$D$1007564,"<"&$E$8,Journals!$J$9:$J$1007564,"Investments in Bond (BXSUKUK)")) -> 0 | J65: =SUMIFS(Journals!$K$9:$K$1007564,Journals!$D$9:$D$1007564,"<"&$F$7,Journals!$J$9:$J$1007564,"Investments in Bond (BXSUKUK)")-SUMIFS(Journals!$L$9:$L$1007564,Journals!$D$9:$D$1007564,"<"&$F$7,Journals!$J$9:$J$1007564,"Investments in Bond (BXSUKUK)") -> 0 | L65: =J65+H65-I65 -> 0
G66: Investments in Bond (APSCL) | H66: =SUMIFS(Journals!$K$9:$K$1007564,Journals!$D$9:$D$1007564,">"&$E$7,Journals!$D$9:$D$1007564,"<"&$E$8,Journals!$J$9:$J$1007564,"Investments in Bond (APSCL)") -> 395250 | I66: =MAX(0,SUMIFS(Journals!$L$9:$L$1007564,Journals!$D$9:$D$1007564,">"&$E$7,Journals!$D$9:$D$1007564,"<"&$E$8,Journals!$J$9:$J$1007564,"Investments in Bond (APSCL)")) -> 1840050 | J66: =SUMIFS(Journals!$K$9:$K$1007564,Journals!$D$9:$D$1007564,"<"&$F$7,Journals!$J$9:$J$1007564,"Investments in Bond (APSCL)")-SUMIFS(Journals!$L$9:$L$1007564,Journals!$D$9:$D$1007564,"<"&$F$7,Journals!$J$9:$J$1007564,"Investments in Bond (APSCL)") -> 3207563.5 | L66: =J66+H66-I66 -> 1762763.5
G67: ='Chart of Accounts'!B60 -> Bond Premium | H67: =SUMIFS(Journals!$K$9:$K$1007564,Journals!$D$9:$D$1007564,">"&$E$7,Journals!$D$9:$D$1007564,"<"&$E$8,Journals!$J$9:$J$1007564,"Bond Premium") -> 0 | I67: =MAX(0,SUMIFS(Journals!$L$9:$L$1007564,Journals!$D$9:$D$1007564,">"&$E$7,Journals!$D$9:$D$1007564,"<"&$E$8,Journals!$J$9:$J$1007564,"Bond Premium")) -> 0 | J67: =SUMIFS(Journals!$K$9:$K$1007564,Journals!$D$9:$D$1007564,"<"&$F$7,Journals!$J$9:$J$1007564,"Bond Premium")-SUMIFS(Journals!$L$9:$L$1007564,Journals!$D$9:$D$1007564,"<"&$F$7,Journals!$J$9:$J$1007564,"Bond Premium") -> 0 | L67: =J67+H67-I67 -> 0
G68: ='Chart of Accounts'!B61 -> Redemption Receivable | H68: =MAX(0,SUMIFS(Journals!$K$9:$K$1007564,Journals!$D$9:$D$1007564,">"&$E$7,Journals!$D$9:$D$1007564,"<"&$E$8,Journals!$J$9:$J$1007564,"Redemption Receivable")-SUMIFS(Journals!$L$9:$L$1007564,Journals!$D$9:$D$1007564,">"&$E$7,Journals!$D$9:$D$1007564,"<"&$E$8,Journals!$J$9:$J$1007564,"Redemption Receivable")) -> 0 | I68: =MAX(0,SUMIFS(Journals!$L$9:$L$1007564,Journals!$D$9:$D$1007564,">"&$E$7,Journals!$D$9:$D$1007564,"<"&$E$8,Journals!$J$9:$J$1007564,"Redemption Receivable")-SUMIFS(Journals!$K$9:$K$1007564,Journals!$D$9:$D$1007564,">"&$E$7,Journals!$D$9:$D$1007564,"<"&$E$8,Journals!$J$9:$J$1007564,"Redemption Receivable")) -> 0 | J68: =SUMIFS(Journals!$K$9:$K$1007564,Journals!$D$9:$D$1007564,"<"&$F$7,Journals!$J$9:$J$1007564,"Redemption Receivable")-SUMIFS(Journals!$L$9:$L$1007564,Journals!$D$9:$D$1007564,"<"&$F$7,Journals!$J$9:$J$1007564,"Redemption Receivable") -> 0 | L68: =J68+H68-I68 -> 0
G69: ='Chart of Accounts'!B62 -> Redemption of Investment | H69: =MAX(0,SUMIFS(Journals!$K$9:$K$1007564,Journals!$D$9:$D$1007564,">"&$E$7,Journals!$D$9:$D$1007564,"<"&$E$8,Journals!$J$9:$J$1007564,"Redemption of Investment")-SUMIFS(Journals!$L$9:$L$1007564,Journals!$D$9:$D$1007564,">"&$E$7,Journals!$D$9:$D$1007564,"<"&$E$8,Journals!$J$9:$J$1007564,"Redemption of Investment")) -> 0 | I69: =MAX(0,SUMIFS(Journals!$L$9:$L$1007564,Journals!$D$9:$D$1007564,">"&$E$7,Journals!$D$9:$D$1007564,"<"&$E$8,Journals!$J$9:$J$1007564,"Redemption of Investment")-SUMIFS(Journals!$K$9:$K$1007564,Journals!$D$9:$D$1007564,">"&$E$7,Journals!$D$9:$D$1007564,"<"&$E$8,Journals!$J$9:$J$1007564,"Redemption of Investment")) -> 0
G70: Investments in T-Bond (Contract) | H70: =MAX(0,SUMIFS(Journals!$K$9:$K$1007564,Journals!$D$9:$D$1007564,">"&$E$7,Journals!$D$9:$D$1007564,"<"&$E$8,Journals!$J$9:$J$1007564,"Investments in T-Bond (Contract)")-SUMIFS(Journals!$L$9:$L$1007564,Journals!$D$9:$D$1007564,">"&$E$7,Journals!$D$9:$D$1007564,"<"&$E$8,Journals!$J$9:$J$1007564,"Investments in T-Bond (Contract)")) -> 0 | I70: =MAX(0,SUMIFS(Journals!$L$9:$L$1007564,Journals!$D$9:$D$1007564,">"&$E$7,Journals!$D$9:$D$1007564,"<"&$E$8,Journals!$J$9:$J$1007564,"Investments in T-Bond (Contract)")-SUMIFS(Journals!$K$9:$K$1007564,Journals!$D$9:$D$1007564,">"&$E$7,Journals!$D$9:$D$1007564,"<"&$E$8,Journals!$J$9:$J$1007564,"Investments in T-Bond (Contract)")) -> 0 | J70: =SUMIFS(Journals!$K$9:$K$1007564,Journals!$D$9:$D$1007564,"<"&$F$7,Journals!$J$9:$J$1007564,"Investments in T-Bond (Contract)")-SUMIFS(Journals!$L$9:$L$1007564,Journals!$D$9:$D$1007564,"<"&$F$7,Journals!$J$9:$J$1007564,"Investments in T-Bond (Contract)") -> 0 | L70: =J70+H70-I70 -> 0
G71: Interest Receivables from T.Bond (Contract) | H71: =MAX(0,SUMIFS(Journals!$K$9:$K$1007564,Journals!$D$9:$D$1007564,">"&$E$7,Journals!$D$9:$D$1007564,"<"&$E$8,Journals!$J$9:$J$1007564,"Interest Receivables from T.Bond (Contract)")-SUMIFS(Journals!$L$9:$L$1007564,Journals!$D$9:$D$1007564,">"&$E$7,Journals!$D$9:$D$1007564,"<"&$E$8,Journals!$J$9:$J$1007564,"Interest Receivables from T.Bond (Contract)")) -> 0 | I71: =MAX(0,SUMIFS(Journals!$L$9:$L$1007564,Journals!$D$9:$D$1007564,">"&$E$7,Journals!$D$9:$D$1007564,"<"&$E$8,Journals!$J$9:$J$1007564,"Interest Receivables from T.Bond (Contract)")-SUMIFS(Journals!$K$9:$K$1007564,Journals!$D$9:$D$1007564,">"&$E$7,Journals!$D$9:$D$1007564,"<"&$E$8,Journals!$J$9:$J$1007564,"Interest Receivables from T.Bond (Contract)")) -> 0 | J71: =SUMIFS(Journals!$K$9:$K$1007564,Journals!$D$9:$D$1007564,"<"&$F$7,Journals!$J$9:$J$1007564,"Interest Receivables from T.Bond (Contract)")-SUMIFS(Journals!$L$9:$L$1007564,Journals!$D$9:$D$1007564,"<"&$F$7,Journals!$J$9:$J$1007564,"Interest Receivables from T.Bond (Contract)") -> 0.0099999986 | L71: =J71+H71-I71 -> 0.0099999986
G72: Preliminary and issue expense (Liability) | H72: =MAX(0,SUMIFS(Journals!$K$9:$K$1007306,Journals!$D$9:$D$1007306,">"&$E$7,Journals!$D$9:$D$1007306,"<"&$E$8,Journals!$J$9:$J$1007306,"Preliminary and issue expense (Liability)")) -> 0 | I72: =MAX(0,SUMIFS(Journals!$L$9:$L$1007306,Journals!$D$9:$D$1007306,">"&$E$7,Journals!$D$9:$D$1007306,"<"&$E$8,Journals!$J$9:$J$1007306,"Preliminary and issue expense (Liability)")) -> 0 | J72: =MAX(0,SUMIFS(Journals!K30:K1007585,Journals!D30:D1007585,"<"&F40,Journals!J30:J1007585,"Preliminary and issue expense (Liability)")-SUMIFS(Journals!L30:L1007585,Journals!D30:D1007585,"<"&F40,Journals!J30:J1007585,"Preliminary and issue expense (Liability)")) -> 0 | K72: =SUMIFS(Journals!$L$9:$L$1007564,Journals!$D$9:$D$1007564,"<"&$F$7,Journals!$J$9:$J$1007564,"Preliminary and issue expense (Liability)")-SUMIFS(Journals!$K$9:$K$1007564,Journals!$D$9:$D$1007564,"<"&$F$7,Journals!$J$9:$J$1007564,"Preliminary and issue expense (Liability)") -> 0 | L72: 0 | M72: =K72+I72-H72 -> 0
G73: Investments in T-Bill | H73: =MAX(0,SUMIFS(Journals!$K$9:$K$1007564,Journals!$D$9:$D$1007564,">"&$E$7,Journals!$D$9:$D$1007564,"<"&$E$8,Journals!$J$9:$J$1007564,"Investments in T-Bill")-SUMIFS(Journals!$L$9:$L$1007564,Journals!$D$9:$D$1007564,">"&$E$7,Journals!$D$9:$D$1007564,"<"&$E$8,Journals!$J$9:$J$1007564,"Investments in T-Bill")) -> 0 | I73: =MAX(0,SUMIFS(Journals!$L$9:$L$1007564,Journals!$D$9:$D$1007564,">"&$E$7,Journals!$D$9:$D$1007564,"<"&$E$8,Journals!$J$9:$J$1007564,"Investments in T-Bill")-SUMIFS(Journals!$K$9:$K$1007564,Journals!$D$9:$D$1007564,">"&$E$7,Journals!$D$9:$D$1007564,"<"&$E$8,Journals!$J$9:$J$1007564,"Investments in T-Bill")) -> 0 | J73: =SUMIFS(Journals!$K$9:$K$1007564,Journals!$D$9:$D$1007564,"<"&$F$7,Journals!$J$9:$J$1007564,"Investments in T-Bill")-SUMIFS(Journals!$L$9:$L$1007564,Journals!$D$9:$D$1007564,"<"&$F$7,Journals!$J$9:$J$1007564,"Investments in T-Bill") -> 0.20000005 | L73: =J73+H73-I73 -> 0.20000005
G74: Interest Receivables from T-Bill | H74: =MAX(0,SUMIFS(Journals!$K$9:$K$1007564,Journals!$D$9:$D$1007564,">"&$E$7,Journals!$D$9:$D$1007564,"<"&$E$8,Journals!$J$9:$J$1007564,"Interest Receivables from T-Bill")-SUMIFS(Journals!$L$9:$L$1007564,Journals!$D$9:$D$1007564,">"&$E$7,Journals!$D$9:$D$1007564,"<"&$E$8,Journals!$J$9:$J$1007564,"Interest Receivables from T-Bill")) -> 0 | I74: =MAX(0,SUMIFS(Journals!$L$9:$L$1007564,Journals!$D$9:$D$1007564,">"&$E$7,Journals!$D$9:$D$1007564,"<"&$E$8,Journals!$J$9:$J$1007564,"Interest Receivables from T-Bill")-SUMIFS(Journals!$K$9:$K$1007564,Journals!$D$9:$D$1007564,">"&$E$7,Journals!$D$9:$D$1007564,"<"&$E$8,Journals!$J$9:$J$1007564,"Interest Receivables from T-Bill")) -> 0 | L74: =J74+H74-I74 -> 0
G75: Investments in T-Bond | H75: =MAX(0,SUMIFS(Journals!$K$9:$K$1007564,Journals!$D$9:$D$1007564,">"&$E$7,Journals!$D$9:$D$1007564,"<"&$E$8,Journals!$J$9:$J$1007564,"Investments in T-Bond")-SUMIFS(Journals!$L$9:$L$1007564,Journals!$D$9:$D$1007564,">"&$E$7,Journals!$D$9:$D$1007564,"<"&$E$8,Journals!$J$9:$J$1007564,"Investments in T-Bond")) -> 0 | I75: =MAX(0,SUMIFS(Journals!$L$9:$L$1007564,Journals!$D$9:$D$1007564,">"&$E$7,Journals!$D$9:$D$1007564,"<"&$E$8,Journals!$J$9:$J$1007564,"Investments in T-Bond")-SUMIFS(Journals!$K$9:$K$1007564,Journals!$D$9:$D$1007564,">"&$E$7,Journals!$D$9:$D$1007564,"<"&$E$8,Journals!$J$9:$J$1007564,"Investments in T-Bond")) -> 57249083 | J75: =SUMIFS(Journals!$K$9:$K$1007564,Journals!$D$9:$D$1007564,"<"&$F$7,Journals!$J$9:$J$1007564,"Investments in T-Bond")-SUMIFS(Journals!$L$9:$L$1007564,Journals!$D$9:$D$1007564,"<"&$F$7,Journals!$J$9:$J$1007564,"Investments in T-Bond") -> 3.6527458e+08 | L75: =J75+H75-I75 -> 3.0802549e+08
G76: Interest Receivables from T-Bond | H76: =MAX(0,SUMIFS(Journals!$K$9:$K$1007494,Journals!$D$9:$D$1007494,">"&$E$7,Journals!$D$9:$D$1007494,"<"&$E$8,Journals!$J$9:$J$1007494,"Interest Receivables from T-Bond")-SUMIFS(Journals!$L$9:$L$1007494,Journals!$D$9:$D$1007494,">"&$E$7,Journals!$D$9:$D$1007494,"<"&$E$8,Journals!$J$9:$J$1007494,"Interest Receivables from T-Bond")) -> 0 | I76: =MAX(0,SUMIFS(Journals!$L$9:$L$1007494,Journals!$D$9:$D$1007494,">"&$E$7,Journals!$D$9:$D$1007494,"<"&$E$8,Journals!$J$9:$J$1007494,"Interest Receivables from T-Bond")-SUMIFS(Journals!$K$9:$K$1007494,Journals!$D$9:$D$1007494,">"&$E$7,Journals!$D$9:$D$1007494,"<"&$E$8,Journals!$J$9:$J$1007494,"Interest Receivables from T-Bond")) -> 0 | L76: =J76+H76-I76 -> 0
G77: Investments in BRAC Bank 2nd Subordinated Bond | H77: =MAX(0,SUMIFS(Journals!$K$9:$K$1007564,Journals!$D$9:$D$1007564,">"&$E$7,Journals!$D$9:$D$1007564,"<"&$E$8,Journals!$J$9:$J$1007564,"Investments in BRAC Bank 2nd Subordinated Bond")-SUMIFS(Journals!$L$9:$L$1007564,Journals!$D$9:$D$1007564,">"&$E$7,Journals!$D$9:$D$1007564,"<"&$E$8,Journals!$J$9:$J$1007564,"Investments in BRAC Bank 2nd Subordinated Bond")) -> 0 | I77: =MAX(0,SUMIFS(Journals!$L$9:$L$1007564,Journals!$D$9:$D$1007564,">"&$E$7,Journals!$D$9:$D$1007564,"<"&$E$8,Journals!$J$9:$J$1007564,"Investments in BRAC Bank 2nd Subordinated Bond")-SUMIFS(Journals!$K$9:$K$1007564,Journals!$D$9:$D$1007564,">"&$E$7,Journals!$D$9:$D$1007564,"<"&$E$8,Journals!$J$9:$J$1007564,"Investments in BRAC Bank 2nd Subordinated Bond")) -> 0 | J77: =SUMIFS(Journals!$K$9:$K$1007564,Journals!$D$9:$D$1007564,"<"&$F$7,Journals!$J$9:$J$1007564,"Investments in BRAC Bank 2nd Subordinated Bond")-SUMIFS(Journals!$L$9:$L$1007564,Journals!$D$9:$D$1007564,"<"&$F$7,Journals!$J$9:$J$1007564,"Investments in BRAC Bank 2nd Subordinated Bond") -> 59000000 | L77: =J77+H77-I77 -> 59000000
G78: Interest Receivables from BRAC Bank Bond | H78: =MAX(0,SUMIFS(Journals!$K$9:$K$1007564,Journals!$D$9:$D$1007564,">"&$E$7,Journals!$D$9:$D$1007564,"<"&$E$8,Journals!$J$9:$J$1007564,"Interest Receivables from BRAC Bank Bond")-SUMIFS(Journals!$L$9:$L$1007564,Journals!$D$9:$D$1007564,">"&$E$7,Journals!$D$9:$D$1007564,"<"&$E$8,Journals!$J$9:$J$1007564,"Interest Receivables from BRAC Bank Bond")) -> 0 | I78: =MAX(0,SUMIFS(Journals!$L$9:$L$1007564,Journals!$D$9:$D$1007564,">"&$E$7,Journals!$D$9:$D$1007564,"<"&$E$8,Journals!$J$9:$J$1007564,"Interest Receivables from BRAC Bank Bond")-SUMIFS(Journals!$K$9:$K$1007564,Journals!$D$9:$D$1007564,">"&$E$7,Journals!$D$9:$D$1007564,"<"&$E$8,Journals!$J$9:$J$1007564,"Interest Receivables from BRAC Bank Bond")) -> 2049264.8 | J78: =SUMIFS(Journals!$K$9:$K$1007564,Journals!$D$9:$D$1007564,"<"&$F$7,Journals!$J$9:$J$1007564,"Interest Receivables from BRAC Bank Bond")-SUMIFS(Journals!$L$9:$L$1007564,Journals!$D$9:$D$1007564,"<"&$F$7,Journals!$J$9:$J$1007564,"Interest Receivables from BRAC Bank Bond") -> 2800879.1 | L78: =J78+H78-I78 -> 751614.36
G79: Investments in Bank Asia 4th Subordinated Bond | H79: =MAX(0,SUMIFS(Journals!$K$9:$K$1007564,Journals!$D$9:$D$1007564,">"&$E$7,Journals!$D$9:$D$1007564,"<"&$E$8,Journals!$J$9:$J$1007564,"Investments in Bank Asia 4th Subordinated Bond")-SUMIFS(Journals!$L$9:$L$1007564,Journals!$D$9:$D$1007564,">"&$E$7,Journals!$D$9:$D$1007564,"<"&$E$8,Journals!$J$9:$J$1007564,"Investments in Bank Asia 4th Subordinated Bond")) -> 20000000 | I79: =MAX(0,SUMIFS(Journals!$L$9:$L$1007564,Journals!$D$9:$D$1007564,">"&$E$7,Journals!$D$9:$D$1007564,"<"&$E$8,Journals!$J$9:$J$1007564,"Investments in Bank Asia 4th Subordinated Bond")-SUMIFS(Journals!$K$9:$K$1007564,Journals!$D$9:$D$1007564,">"&$E$7,Journals!$D$9:$D$1007564,"<"&$E$8,Journals!$J$9:$J$1007564,"Investments in Bank Asia 4th Subordinated Bond")) -> 0 | J79: =SUMIFS(Journals!$K$9:$K$1007564,Journals!$D$9:$D$1007564,"<"&$F$7,Journals!$J$9:$J$1007564,"Investments in Bank Asia 4th Subordinated Bond")-SUMIFS(Journals!$L$9:$L$1007564,Journals!$D$9:$D$1007564,"<"&$F$7,Journals!$J$9:$J$1007564,"Investments in Bank Asia 4th Subordinated Bond") -> 40000000 | L79: =J79+H79-I79 -> 60000000
G80: Interest Receivables from Bank Asia Bond | H80: =MAX(0,SUMIFS(Journals!$K$9:$K$1007564,Journals!$D$9:$D$1007564,">"&$E$7,Journals!$D$9:$D$1007564,"<"&$E$8,Journals!$J$9:$J$1007564,"Interest Receivables from Bank Asia Bond")-SUMIFS(Journals!$L$9:$L$1007564,Journals!$D$9:$D$1007564,">"&$E$7,Journals!$D$9:$D$1007564,"<"&$E$8,Journals!$J$9:$J$1007564,"Interest Receivables from Bank Asia Bond")) -> 1268443.5 | I80: =MAX(0,SUMIFS(Journals!$L$9:$L$1007564,Journals!$D$9:$D$1007564,">"&$E$7,Journals!$D$9:$D$1007564,"<"&$E$8,Journals!$J$9:$J$1007564,"Interest Receivables from Bank Asia Bond")-SUMIFS(Journals!$K$9:$K$1007564,Journals!$D$9:$D$1007564,">"&$E$7,Journals!$D$9:$D$1007564,"<"&$E$8,Journals!$J$9:$J$1007564,"Interest Receivables from Bank Asia Bond")) -> 0 | J80: =SUMIFS(Journals!$K$9:$K$1007564,Journals!$D$9:$D$1007564,"<"&$F$7,Journals!$J$9:$J$1007564,"Interest Receivables from Bank Asia Bond")-SUMIFS(Journals!$L$9:$L$1007564,Journals!$D$9:$D$1007564,"<"&$F$7,Journals!$J$9:$J$1007564,"Interest Receivables from Bank Asia Bond") -> 873164.87 | L80: =J80+H80-I80 -> 2141608.4
G81: Investments in Dhaka Bank 4th Subordinated Bond | H81: =MAX(0,SUMIFS(Journals!$K$9:$K$1007564,Journals!$D$9:$D$1007564,">"&$E$7,Journals!$D$9:$D$1007564,"<"&$E$8,Journals!$J$9:$J$1007564,"Investments in Dhaka Bank 4th Subordinated Bond")-SUMIFS(Journals!$L$9:$L$1007564,Journals!$D$9:$D$1007564,">"&$E$7,Journals!$D$9:$D$1007564,"<"&$E$8,Journals!$J$9:$J$1007564,"Investments in Dhaka Bank 4th Subordinated Bond")) -> 5000000 | I81: =MAX(0,SUMIFS(Journals!$L$9:$L$1007564,Journals!$D$9:$D$1007564,">"&$E$7,Journals!$D$9:$D$1007564,"<"&$E$8,Journals!$J$9:$J$1007564,"Investments in Dhaka Bank 4th Subordinated Bond")-SUMIFS(Journals!$K$9:$K$1007564,Journals!$D$9:$D$1007564,">"&$E$7,Journals!$D$9:$D$1007564,"<"&$E$8,Journals!$J$9:$J$1007564,"Investments in Dhaka Bank 4th Subordinated Bond")) -> 0 | J81: =SUMIFS(Journals!$K$9:$K$1007564,Journals!$D$9:$D$1007564,"<"&$F$7,Journals!$J$9:$J$1007564,"Investments in Dhaka Bank 4th Subordinated Bond")-SUMIFS(Journals!$L$9:$L$1007564,Journals!$D$9:$D$1007564,"<"&$F$7,Journals!$J$9:$J$1007564,"Investments in Dhaka Bank 4th Subordinated Bond") -> 0 | L81: =J81+H81-I81 -> 5000000
G82: Interest Receivables from Dhaka Bank 4th Subordinated Bond | H82: =MAX(0,SUMIFS(Journals!$K$9:$K$1007564,Journals!$D$9:$D$1007564,">"&$E$7,Journals!$D$9:$D$1007564,"<"&$E$8,Journals!$J$9:$J$1007564,"Interest Receivables from Dhaka Bank 4th Subordinated Bond")-SUMIFS(Journals!$L$9:$L$1007564,Journals!$D$9:$D$1007564,">"&$E$7,Journals!$D$9:$D$1007564,"<"&$E$8,Journals!$J$9:$J$1007564,"Interest Receivables from Dhaka Bank 4th Subordinated Bond")) -> 442019.01 | I82: =MAX(0,SUMIFS(Journals!$L$9:$L$1007564,Journals!$D$9:$D$1007564,">"&$E$7,Journals!$D$9:$D$1007564,"<"&$E$8,Journals!$J$9:$J$1007564,"Interest Receivables from Dhaka Bank 4th Subordinated Bond")-SUMIFS(Journals!$K$9:$K$1007564,Journals!$D$9:$D$1007564,">"&$E$7,Journals!$D$9:$D$1007564,"<"&$E$8,Journals!$J$9:$J$1007564,"Interest Receivables from Dhaka Bank 4th Subordinated Bond")) -> 0 | J82: =SUMIFS(Journals!$K$9:$K$1007564,Journals!$D$9:$D$1007564,"<"&$F$7,Journals!$J$9:$J$1007564,"Interest Receivables from Dhaka Bank 4th Subordinated Bond")-SUMIFS(Journals!$L$9:$L$1007564,Journals!$D$9:$D$1007564,"<"&$F$7,Journals!$J$9:$J$1007564,"Interest Receivables from Dhaka Bank 4th Subordinated Bond") -> 0 | L82: =J82+H82-I82 -> 442019.01
E84: =L67-D84 -> 0

Sheet TB-P
A1: Check of Trial Balance | G1: =SUM(H7:H103)-SUM(I7:I103) -> 1.5326144e+08
A2: Check of Balance Sheet | G2: =BS!C25-BS!C42 -> -0.0033406019
A3: Check of Cash Balance | G3: =BS!C23-CF!B43 -> 94994187
B5: Desired Reporting Period | H5: During the Reporting Period | J5: For Balance Sheet | N5: For Retained Earnings
B6: Year | C6: Month | D6: Day | E6: Value | F6: Value | G6: Accounts | H6: Debit | I6: Credit | J6: Carry Forward Balance | K6: Carry Forward Balance | L6: On date | M6: On date | N6: Debit | O6: Credit
A7: Beginning | B7: 2024 | C7: 7 | D7: 1 | E7: =DATE(B7,C7,D7)-1 -> 45473 | F7: =DATE(B7,C7,D7) -> 45474 | G7: ='Chart of Accounts'!B3 -> Investments in stock | H7: =MAX(0,SUMIFS(Journals!$K$9:$K$1007564,Journals!$D$9:$D$1007564,">"&$E$7,Journals!$D$9:$D$1007564,"<"&$E$8,Journals!$J$9:$J$1007564,"investments in stock")-SUMIFS(Journals!$L$9:$L$1007564,Journals!$D$9:$D$1007564,">"&$E$7,Journals!$D$9:$D$1007564,"<"&$E$8,Journals!$J$9:$J$1007564,"investments in stock")) -> 0 | I7: =MAX(0,SUMIFS(Journals!$L$9:$L$1007564,Journals!$D$9:$D$1007564,">"&$E$7,Journals!$D$9:$D$1007564,"<"&$E$8,Journals!$J$9:$J$1007564,"Investments in stock")-SUMIFS(Journals!$K$9:$K$1007564,Journals!$D$9:$D$1007564,">"&$E$7,Journals!$D$9:$D$1007564,"<"&$E$8,Journals!$J$9:$J$1007564,"Investments in stock")) -> 0 | J7: =SUMIFS(Journals!$K$9:$K$1007564,Journals!$D$9:$D$1007564,"<"&$F$7,Journals!$J$9:$J$1007564,"investments in stock")-SUMIFS(Journals!$L$9:$L$1007564,Journals!$D$9:$D$1007564,"<"&$F$7,Journals!$J$9:$J$1007564,"investments in stock") -> 2797650.6 | L7: =J7+H7-I7 -> 2797650.6
A8: Ending | B8: 2025 | C8: 6 | D8: 30 | E8: =DATE(B8,C8,D8)+1 -> 45839 | F8: =DATE(B8,C8,D8) -> 45838 | G8: ='Chart of Accounts'!B4 -> Interest Receivables from Bank A/C | H8: =MAX(0,SUMIFS(Journals!$K$9:$K$1007564,Journals!$D$9:$D$1007564,">"&$E$7,Journals!$D$9:$D$1007564,"<"&$E$8,Journals!$J$9:$J$1007564,"Interest Receivables from Bank A/C")-SUMIFS(Journals!$L$9:$L$1007564,Journals!$D$9:$D$1007564,">"&$E$7,Journals!$D$9:$D$1007564,"<"&$E$8,Journals!$J$9:$J$1007564,"Interest Receivables from Bank A/C")) -> 369.04647 | I8: =MAX(0,SUMIFS(Journals!$L$9:$L$1007564,Journals!$D$9:$D$1007564,">"&$E$7,Journals!$D$9:$D$1007564,"<"&$E$8,Journals!$J$9:$J$1007564,"Interest Receivables from Bank A/C")-SUMIFS(Journals!$K$9:$K$1007564,Journals!$D$9:$D$1007564,">"&$E$7,Journals!$D$9:$D$1007564,"<"&$E$8,Journals!$J$9:$J$1007564,"Interest Receivables from Bank A/C")) -> 0 | J8: =SUMIFS(Journals!$K$9:$K$1007564,Journals!$D$9:$D$1007564,"<"&$F$7,Journals!$J$9:$J$1007564,"Interest Receivables from Bank A/C")-SUMIFS(Journals!$L$9:$L$1007564,Journals!$D$9:$D$1007564,"<"&$F$7,Journals!$J$9:$J$1007564,"Interest Receivables from Bank A/C") -> 2393.7615 | L8: =J8+H8-I8 -> 2762.8079
G9: Interest Receivables from Sukuk | H9: =MAX(0,SUMIFS(Journals!$K$9:$K$1007564,Journals!$D$9:$D$1007564,">"&$E$7,Journals!$D$9:$D$1007564,"<"&$E$8,Journals!$J$9:$J$1007564,"Interest Receivables from Sukuk")-SUMIFS(Journals!$L$9:$L$1007564,Journals!$D$9:$D$1007564,">"&$E$7,Journals!$D$9:$D$1007564,"<"&$E$8,Journals!$J$9:$J$1007564,"Interest Receivables from Sukuk")) -> 0 | I9: =MAX(0,SUMIFS(Journals!$L$9:$L$1007564,Journals!$D$9:$D$1007564,">"&$E$7,Journals!$D$9:$D$1007564,"<"&$E$8,Journals!$J$9:$J$1007564,"Interest Receivables from Sukuk")-SUMIFS(Journals!$K$9:$K$1007564,Journals!$D$9:$D$1007564,">"&$E$7,Journals!$D$9:$D$1007564,"<"&$E$8,Journals!$J$9:$J$1007564,"Interest Receivables from Sukuk")) -> 205490.74 | J9: =SUMIFS(Journals!$K$9:$K$1007564,Journals!$D$9:$D$1007564,"<"&$F$7,Journals!$J$9:$J$1007564,"Interest Receivables from Sukuk")-SUMIFS(Journals!$L$9:$L$1007564,Journals!$D$9:$D$1007564,"<"&$F$7,Journals!$J$9:$J$1007564,"Interest Receivables from Sukuk") -> 205490.74 | L9: =J9+H9-I9 -> 0
G10: Interest Receivables from Bond | H10: =MAX(0,SUMIFS(Journals!$K$9:$K$1007564,Journals!$D$9:$D$1007564,">"&$E$7,Journals!$D$9:$D$1007564,"<"&$E$8,Journals!$J$9:$J$1007564,"Interest Receivables from Bond")-SUMIFS(Journals!$L$9:$L$1007564,Journals!$D$9:$D$1007564,">"&$E$7,Journals!$D$9:$D$1007564,"<"&$E$8,Journals!$J$9:$J$1007564,"Interest Receivables from Bond")) -> 0 | I10: =MAX(0,SUMIFS(Journals!$L$9:$L$1007564,Journals!$D$9:$D$1007564,">"&$E$7,Journals!$D$9:$D$1007564,"<"&$E$8,Journals!$J$9:$J$1007564,"Interest Receivables from Bond")-SUMIFS(Journals!$K$9:$K$1007564,Journals!$D$9:$D$1007564,">"&$E$7,Journals!$D$9:$D$1007564,"<"&$E$8,Journals!$J$9:$J$1007564,"Interest Receivables from Bond")) -> 208338.76 | J10: =SUMIFS(Journals!$K$9:$K$1007564,Journals!$D$9:$D$1007564,"<"&$F$7,Journals!$J$9:$J$1007564,"Interest Receivables from Bond")-SUMIFS(Journals!$L$9:$L$1007564,Journals!$D$9:$D$1007564,"<"&$F$7,Journals!$J$9:$J$1007564,"Interest Receivables from Bond") -> 267553.13 | L10: =J10+H10-I10 -> 59214.369
G11: ='Chart of Accounts'!B5 -> Preliminary & issue expenses | H11: =MAX(0,SUMIFS(Journals!$K$9:$K$1007564,Journals!$D$9:$D$1007564,">"&$E$7,Journals!$D$9:$D$1007564,"<"&$E$8,Journals!$J$9:$J$1007564,"Preliminary & issue expenses")-SUMIFS(Journals!$L$9:$L$1007564,Journals!$D$9:$D$1007564,">"&$E$7,Journals!$D$9:$D$1007564,"<"&$E$8,Journals!$J$9:$J$1007564,"Preliminary & issue expenses")) -> 0 | I11: =MAX(0,SUMIFS(Journals!$L$9:$L$1007564,Journals!$D$9:$D$1007564,">"&$E$7,Journals!$D$9:$D$1007564,"<"&$E$8,Journals!$J$9:$J$1007564,"Preliminary & issue expenses")-SUMIFS(Journals!$K$9:$K$1007564,Journals!$D$9:$D$1007564,">"&$E$7,Journals!$D$9:$D$1007564,"<"&$E$8,Journals!$J$9:$J$1007564,"Preliminary & issue expenses")) -> 184261.73 | J11: =SUMIFS(Journals!$K$9:$K$1007564,Journals!$D$9:$D$1007564,"<"&$F$7,Journals!$J$9:$J$1007564,"Preliminary & issue expenses")-SUMIFS(Journals!$L$9:$L$1007564,Journals!$D$9:$D$1007564,"<"&$F$7,Journals!$J$9:$J$1007564,"Preliminary & issue expenses") -> 743991.09 | L11: =J11+H11-I11 -> 559729.36
G12: ='Chart of Accounts'!B6 -> Accrued Management Fee | H12: =SUMIFS(Journals!$K$9:$K$1006910,Journals!$D$9:$D$1006910,">"&$E$7,Journals!$D$9:$D$1006910,"<"&$E$8,Journals!$J$9:$J$1006910,"Accrued Management Fee") -> 2674281.6 | I12: =MAX(0,SUMIFS(Journals!$L$9:$L$1006910,Journals!$D$9:$D$1006910,">"&$E$7,Journals!$D$9:$D$1006910,"<"&$E$8,Journals!$J$9:$J$1006910,"Accrued Management Fee")) -> 2325669.4 | K12: =SUMIFS(Journals!$L$9:$L$1007564,Journals!$D$9:$D$1007564,"<"&$F$7,Journals!$J$9:$J$1007564,"Accrued Management Fee")-SUMIFS(Journals!$K$9:$K$1007564,Journals!$D$9:$D$1007564,"<"&$F$7,Journals!$J$9:$J$1007564,"Accrued Management Fee") -> 585053.54 | M12: =K12+I12-H12 -> 236441.3
G13: ='Chart of Accounts'!B7 -> Accrued Trustee Fee | H13: =MAX(0,SUMIFS(Journals!$K$9:$K$1007564,Journals!$D$9:$D$1007564,">"&$E$7,Journals!$D$9:$D$1007564,"<"&$E$8,Journals!$J$9:$J$1007564,"accrued trustee fee")-SUMIFS(Journals!$L$9:$L$1007564,Journals!$D$9:$D$1007564,">"&$E$7,Journals!$D$9:$D$1007564,"<"&$E$8,Journals!$J$9:$J$1007564,"accrued trustee fee")) -> 207.91499 | I13: =MAX(0,SUMIFS(Journals!$L$9:$L$1007564,Journals!$D$9:$D$1007564,">"&$E$7,Journals!$D$9:$D$1007564,"<"&$E$8,Journals!$J$9:$J$1007564,"accrued trustee fee")-SUMIFS(Journals!$K$9:$K$1007564,Journals!$D$9:$D$1007564,">"&$E$7,Journals!$D$9:$D$1007564,"<"&$E$8,Journals!$J$9:$J$1007564,"accrued trustee fee")) -> 0 | K13: =SUMIFS(Journals!$L$9:$L$1007564,Journals!$D$9:$D$1007564,"<"&$F$7,Journals!$J$9:$J$1007564,"Accrued Trustee Fee")-SUMIFS(Journals!$K$9:$K$1007564,Journals!$D$9:$D$1007564,"<"&$F$7,Journals!$J$9:$J$1007564,"Accrued Trustee Fee") -> 66024.419 | M13: =K13+I13-H13 -> 65816.504
G14: ='Chart of Accounts'!B8 -> Accrued Custodian Fee | H14: =MAX(0,SUMIFS(Journals!$K$9:$K$1007564,Journals!$D$9:$D$1007564,">"&$E$7,Journals!$D$9:$D$1007564,"<"&$E$8,Journals!$J$9:$J$1007564,"accrued custodian fee")-SUMIFS(Journals!$L$9:$L$1007564,Journals!$D$9:$D$1007564,">"&$E$7,Journals!$D$9:$D$1007564,"<"&$E$8,Journals!$J$9:$J$1007564,"accrued custodian fee")) -> 0 | I14: =MAX(0,SUMIFS(Journals!$L$9:$L$1007564,Journals!$D$9:$D$1007564,">"&$E$7,Journals!$D$9:$D$1007564,"<"&$E$8,Journals!$J$9:$J$1007564,"accrued custodian fee")-SUMIFS(Journals!$K$9:$K$1007564,Journals!$D$9:$D$1007564,">"&$E$7,Journals!$D$9:$D$1007564,"<"&$E$8,Journals!$J$9:$J$1007564,"accrued custodian fee")) -> 123123.68 | K14: =SUMIFS(Journals!$L$9:$L$1007564,Journals!$D$9:$D$1007564,"<"&$F$7,Journals!$J$9:$J$1007564,"Accrued Custodian Fee")-SUMIFS(Journals!$K$9:$K$1007564,Journals!$D$9:$D$1007564,"<"&$F$7,Journals!$J$9:$J$1007564,"Accrued Custodian Fee") -> 0 | M14: =K14+I14-H14 -> 123123.68
G15: ='Chart of Accounts'!B9 -> Accrued BSEC fee | H15: =MAX(0,SUMIFS(Journals!$K$9:$K$1007564,Journals!$D$9:$D$1007564,">"&$E$7,Journals!$D$9:$D$1007564,"<"&$E$8,Journals!$J$9:$J$1007564,"accrued bsec fee")-SUMIFS(Journals!$L$9:$L$1007564,Journals!$D$9:$D$1007564,">"&$E$7,Journals!$D$9:$D$1007564,"<"&$E$8,Journals!$J$9:$J$1007564,"accrued bsec fee")) -> 0 | I15: =MAX(0,SUMIFS(Journals!$L$9:$L$1007564,Journals!$D$9:$D$1007564,">"&$E$7,Journals!$D$9:$D$1007564,"<"&$E$8,Journals!$J$9:$J$1007564,"accrued bsec fee")-SUMIFS(Journals!$K$9:$K$1007564,Journals!$D$9:$D$1007564,">"&$E$7,Journals!$D$9:$D$1007564,"<"&$E$8,Journals!$J$9:$J$1007564,"accrued bsec fee")) -> 0 | K15: =SUMIFS(Journals!$L$9:$L$1007564,Journals!$D$9:$D$1007564,"<"&$F$7,Journals!$J$9:$J$1007564,"accrued bsec fee")-SUMIFS(Journals!$K$9:$K$1007564,Journals!$D$9:$D$1007564,"<"&$F$7,Journals!$J$9:$J$1007564,"accrued bsec fee") -> 0 | M15: =K15+I15-H15 -> 0
G16: ='Chart of Accounts'!B10 -> Accrued Audit Fee | H16: =MAX(0,SUMIFS(Journals!$K$9:$K$1006983,Journals!$D$9:$D$1006983,">"&$E$7,Journals!$D$9:$D$1006983,"<"&$E$8,Journals!$J$9:$J$1006983,"accrued audit fee")) -> 34500 | I16: =MAX(0,SUMIFS(Journals!$L$9:$L$1006983,Journals!$D$9:$D$1006983,">"&$E$7,Journals!$D$9:$D$1006983,"<"&$E$8,Journals!$J$9:$J$1006983,"accrued audit fee")) -> 40250 | K16: =SUMIFS(Journals!$L$9:$L$1007564,Journals!$D$9:$D$1007564,"<"&$F$7,Journals!$J$9:$J$1007564,"accrued audit fee")-SUMIFS(Journals!$K$9:$K$1007564,Journals!$D$9:$D$1007564,"<"&$F$7,Journals!$J$9:$J$1007564,"accrued audit fee") -> 34500 | M16: =K16+I16-H16 -> 40250
G17: ='Chart of Accounts'!B11 -> Accrued CDBL Fee | H17: =MAX(0,SUMIFS(Journals!$K$9:$K$1007564,Journals!$D$9:$D$1007564,">"&$E$7,Journals!$D$9:$D$1007564,"<"&$E$8,Journals!$J$9:$J$1007564,"accrued CDBL fee")-SUMIFS(Journals!$L$9:$L$1007564,Journals!$D$9:$D$1007564,">"&$E$7,Journals!$D$9:$D$1007564,"<"&$E$8,Journals!$J$9:$J$1007564,"accrued CDBL fee")) -> 0 | I17: =MAX(0,SUMIFS(Journals!$L$9:$L$1007564,Journals!$D$9:$D$1007564,">"&$E$7,Journals!$D$9:$D$1007564,"<"&$E$8,Journals!$J$9:$J$1007564,"accrued CDBL fee")-SUMIFS(Journals!$K$9:$K$1007564,Journals!$D$9:$D$1007564,">"&$E$7,Journals!$D$9:$D$1007564,"<"&$E$8,Journals!$J$9:$J$1007564,"accrued CDBL fee")) -> 0 | K17: =SUMIFS(Journals!$L$9:$L$1007564,Journals!$D$9:$D$1007564,"<"&$F$7,Journals!$J$9:$J$1007564,"accrued cdbl fee")-SUMIFS(Journals!$K$9:$K$1007564,Journals!$D$9:$D$1007564,"<"&$F$7,Journals!$J$9:$J$1007564,"accrued cdbl fee") -> 0 | M17: =K17+I17-H17 -> 0
G18: ='Chart of Accounts'!B12 -> Fixed Deposit Receipts (FDR) | H18: =MAX(0,SUMIFS(Journals!$K$9:$K$1007564,Journals!$D$9:$D$1007564,">"&$E$7,Journals!$D$9:$D$1007564,"<"&$E$8,Journals!$J$9:$J$1007564,"Fixed Deposit Receipts (FDR)")-SUMIFS(Journals!$L$9:$L$1007564,Journals!$D$9:$D$1007564,">"&$E$7,Journals!$D$9:$D$1007564,"<"&$E$8,Journals!$J$9:$J$1007564,"Fixed Deposit Receipts (FDR)")) -> 0 | I18: =MAX(0,SUMIFS(Journals!$L$9:$L$1007564,Journals!$D$9:$D$1007564,">"&$E$7,Journals!$D$9:$D$1007564,"<"&$E$8,Journals!$J$9:$J$1007564,"Fixed Deposit Receipts (FDR)")-SUMIFS(Journals!$K$9:$K$1007564,Journals!$D$9:$D$1007564,">"&$E$7,Journals!$D$9:$D$1007564,"<"&$E$8,Journals!$J$9:$J$1007564,"Fixed Deposit Receipts (FDR)")) -> 5000000 | J18: =SUMIFS(Journals!$K$9:$K$1007564,Journals!$D$9:$D$1007564,"<"&$F$7,Journals!$J$9:$J$1007564,"Fixed Deposit Receipts (FDR)")-SUMIFS(Journals!$L$9:$L$1007564,Journals!$D$9:$D$1007564,"<"&$F$7,Journals!$J$9:$J$1007564,"Fixed Deposit Receipts (FDR)") -> 90000000 | L18: =J18+H18-I18 -> 85000000
G19: ='Chart of Accounts'!B13 -> Cash and cash equivalents | H19: =MAX(0,SUMIFS(Journals!$K$9:$K$1007564,Journals!$D$9:$D$1007564,">"&$E$7,Journals!$D$9:$D$1007564,"<"&$E$8,Journals!$J$9:$J$1007564,"Cash and cash equivalents")-SUMIFS(Journals!$L$9:$L$1007564,Journals!$D$9:$D$1007564,">"&$E$7,Journals!$D$9:$D$1007564,"<"&$E$8,Journals!$J$9:$J$1007564,"Cash and cash equivalents")) -> 2160071.8 | I19: =MAX(0,SUMIFS(Journals!$L$9:$L$1007564,Journals!$D$9:$D$1007564,">"&$E$7,Journals!$D$9:$D$1007564,"<"&$E$8,Journals!$J$9:$J$1007564,"Cash and cash equivalents")-SUMIFS(Journals!$K$9:$K$1007564,Journals!$D$9:$D$1007564,">"&$E$7,Journals!$D$9:$D$1007564,"<"&$E$8,Journals!$J$9:$J$1007564,"Cash and cash equivalents")) -> 0 | J19: =SUMIFS(Journals!$K$9:$K$1007564,Journals!$D$9:$D$1007564,"<"&$F$7,Journals!$J$9:$J$1007564,"Cash and cash equivalents")-SUMIFS(Journals!$L$9:$L$1007564,Journals!$D$9:$D$1007564,"<"&$F$7,Journals!$J$9:$J$1007564,"Cash and cash equivalents") -> 13359585 | L19: =J19+H19-I19 -> 15519657
G20: ='Chart of Accounts'!B14 -> Unit Capital | H20: =MAX(0,SUMIFS(Journals!$K$9:$K$1007564,Journals!$D$9:$D$1007564,">"&$E$7,Journals!$D$9:$D$1007564,"<"&$E$8,Journals!$J$9:$J$1007564,"unit capital")) -> 250287210 | I20: =MAX(0,SUMIFS(Journals!$L$9:$L$1007564,Journals!$D$9:$D$1007564,">"&$E$7,Journals!$D$9:$D$1007564,"<"&$E$8,Journals!$J$9:$J$1007564,"unit capital")) -> 394108550 | K20: =SUMIFS(Journals!$L$9:$L$1007564,Journals!$D$9:$D$1007564,"<"&$F$7,Journals!$J$9:$J$1007564,"unit capital")-SUMIFS(Journals!$K$9:$K$1007564,Journals!$D$9:$D$1007564,"<"&$F$7,Journals!$J$9:$J$1007564,"unit capital") -> 318556230 | M20: =K20+I20-H20 -> 462377570
G21: ='Chart of Accounts'!B15 -> Unit premium reserve | H21: =MAX(0,SUMIFS(Journals!$K$9:$K$1007564,Journals!$D$9:$D$1007564,">"&$E$7,Journals!$D$9:$D$1007564,"<"&$E$8,Journals!$J$9:$J$1007564,"Unit premium reserve")) -> 53649164 | I21: =MAX(0,SUMIFS(Journals!$L$9:$L$1007564,Journals!$D$9:$D$1007564,">"&$E$7,Journals!$D$9:$D$1007564,"<"&$E$8,Journals!$J$9:$J$1007564,"unit premium reserve")) -> 79033602 | K21: =SUMIFS(Journals!$L$9:$L$1007564,Journals!$D$9:$D$1007564,"<"&$F$7,Journals!$J$9:$J$1007564,"unit premium reserve")-SUMIFS(Journals!$K$9:$K$1007564,Journals!$D$9:$D$1007564,"<"&$F$7,Journals!$J$9:$J$1007564,"unit premium reserve") -> 15909100 | M21: =K21+I21-H21 -> 41293538
G22: ='Chart of Accounts'!B16 -> Interest income | H22: =MAX(0,SUMIFS(Journals!$K$9:$K$1007564,Journals!$D$9:$D$1007564,">"&$E$7,Journals!$D$9:$D$1007564,"<"&$E$8,Journals!$J$9:$J$1007564,"interest income")-SUMIFS(Journals!$L$9:$L$1007564,Journals!$D$9:$D$1007564,">"&$E$7,Journals!$D$9:$D$1007564,"<"&$E$8,Journals!$J$9:$J$1007564,"interest income")) -> 0 | I22: =MAX(0,SUMIFS(Journals!$L$9:$L$1007564,Journals!$D$9:$D$1007564,">"&$E$7,Journals!$D$9:$D$1007564,"<"&$E$8,Journals!$J$9:$J$1007564,"interest income")-SUMIFS(Journals!$K$9:$K$1007564,Journals!$D$9:$D$1007564,">"&$E$7,Journals!$D$9:$D$1007564,"<"&$E$8,Journals!$J$9:$J$1007564,"interest income")) -> 10083228 | K22: =SUMIFS(Journals!$L$9:$L$1006983,Journals!$D$9:$D$1006983,"<"&$F$7,Journals!$J$9:$J$1006983,"Interest income")-SUMIFS(Journals!$K$9:$K$1006983,Journals!$D$9:$D$1006983,"<"&$F$7,Journals!$J$9:$J$1006983,"Interest income") -> 9836187.7 | M22: =K22+I22-H22 -> 19919416 | O22: =SUMIFS(Journals!$L$9:$L$1007564,Journals!$D$9:$D$1007564,"<"&$F$7,Journals!$J$9:$J$1007564,"interest income")-SUMIFS(Journals!$K$9:$K$1007564,Journals!$D$9:$D$1007564,"<"&$F$7,Journals!$J$9:$J$1007564,"interest income") -> 9836187.7
G23: Interest income from T-Bond | H23: =MAX(0,SUMIFS(Journals!$K$9:$K$1007494,Journals!$D$9:$D$1007494,">"&$E$7,Journals!$D$9:$D$1007494,"<"&$E$8,Journals!$J$9:$J$1007494,"Interest income from T-Bond")-SUMIFS(Journals!$L$9:$L$1007494,Journals!$D$9:$D$1007494,">"&$E$7,Journals!$D$9:$D$1007494,"<"&$E$8,Journals!$J$9:$J$1007494,"Interest income from T-Bond")) -> 0 | I23: =MAX(0,SUMIFS(Journals!$L$9:$L$1007564,Journals!$D$9:$D$1007564,">"&$E$7,Journals!$D$9:$D$1007564,"<"&$E$8,Journals!$J$9:$J$1007564,"Interest income from T-Bond")-SUMIFS(Journals!$K$9:$K$1007564,Journals!$D$9:$D$1007564,">"&$E$7,Journals!$D$9:$D$1007564,"<"&$E$8,Journals!$J$9:$J$1007564,"Interest income from T-Bond")) -> 33626216 | K23: =SUMIFS(Journals!$L$9:$L$1007494,Journals!$D$9:$D$1007494,"<"&$F$7,Journals!$J$9:$J$1007494,"Interest income from T-Bond")-SUMIFS(Journals!$K$9:$K$1007494,Journals!$D$9:$D$1007494,"<"&$F$7,Journals!$J$9:$J$1007494,"Interest income from T-Bond") -> 0 | M23: =K23+I23-H23 -> 33626216 | O23: =SUMIFS(Journals!$L$9:$L$1007494,Journals!$D$9:$D$1007494,"<"&$F$7,Journals!$J$9:$J$1007494,"Interest income from T-Bond")-SUMIFS(Journals!$K$9:$K$1007494,Journals!$D$9:$D$1007494,"<"&$F$7,Journals!$J$9:$J$1007494,"Interest income from T-Bond") -> 0
G24: Interest income from BXSUKUK | H24: =MAX(0,SUMIFS(Journals!$K$9:$K$1007564,Journals!$D$9:$D$1007564,">"&$E$7,Journals!$D$9:$D$1007564,"<"&$E$8,Journals!$J$9:$J$1007564,"Interest income from BXSUKUK")-SUMIFS(Journals!$L$9:$L$1007564,Journals!$D$9:$D$1007564,">"&$E$7,Journals!$D$9:$D$1007564,"<"&$E$8,Journals!$J$9:$J$1007564,"Interest income from BXSUKUK")) -> 0 | I24: =MAX(0,SUMIFS(Journals!$L$9:$L$1007564,Journals!$D$9:$D$1007564,">"&$E$7,Journals!$D$9:$D$1007564,"<"&$E$8,Journals!$J$9:$J$1007564,"Interest income from BXSUKUK")-SUMIFS(Journals!$K$9:$K$1007564,Journals!$D$9:$D$1007564,">"&$E$7,Journals!$D$9:$D$1007564,"<"&$E$8,Journals!$J$9:$J$1007564,"Interest income from BXSUKUK")) -> 15985.711 | K24: =SUMIFS(Journals!$L$9:$L$1007564,Journals!$D$9:$D$1007564,"<"&$F$7,Journals!$J$9:$J$1007564,"Interest income from BXSUKUK")-SUMIFS(Journals!$K$9:$K$1007564,Journals!$D$9:$D$1007564,"<"&$F$7,Journals!$J$9:$J$1007564,"Interest income from BXSUKUK") -> 432657.03 | M24: =K24+I24-H24 -> 448642.74 | O24: =SUMIFS(Journals!$L$9:$L$1007564,Journals!$D$9:$D$1007564,"<"&$F$7,Journals!$J$9:$J$1007564,"Interest income from BXSUKUK")-SUMIFS(Journals!$K$9:$K$1007564,Journals!$D$9:$D$1007564,"<"&$F$7,Journals!$J$9:$J$1007564,"Interest income from BXSUKUK") -> 432657.03
G25: Interest income from APSCL | H25: =MAX(0,SUMIFS(Journals!$K$9:$K$1007564,Journals!$D$9:$D$1007564,">"&$E$7,Journals!$D$9:$D$1007564,"<"&$E$8,Journals!$J$9:$J$1007564,"Interest income from APSCL")-SUMIFS(Journals!$L$9:$L$1007564,Journals!$D$9:$D$1007564,">"&$E$7,Journals!$D$9:$D$1007564,"<"&$E$8,Journals!$J$9:$J$1007564,"Interest income from APSCL")) -> 0 | I25: =MAX(0,SUMIFS(Journals!$L$9:$L$1007564,Journals!$D$9:$D$1007564,">"&$E$7,Journals!$D$9:$D$1007564,"<"&$E$8,Journals!$J$9:$J$1007564,"Interest income from APSCL")-SUMIFS(Journals!$K$9:$K$1007564,Journals!$D$9:$D$1007564,">"&$E$7,Journals!$D$9:$D$1007564,"<"&$E$8,Journals!$J$9:$J$1007564,"Interest income from APSCL")) -> 294873.75 | K25: =SUMIFS(Journals!$L$9:$L$1007564,Journals!$D$9:$D$1007564,"<"&$F$7,Journals!$J$9:$J$1007564,"Interest income from APSCL")-SUMIFS(Journals!$K$9:$K$1007564,Journals!$D$9:$D$1007564,"<"&$F$7,Journals!$J$9:$J$1007564,"Interest income from APSCL") -> 983653.13 | M25: =K25+I25-H25 -> 1278526.9 | O25: =SUMIFS(Journals!$L$9:$L$1007564,Journals!$D$9:$D$1007564,"<"&$F$7,Journals!$J$9:$J$1007564,"Interest income from APSCL")-SUMIFS(Journals!$K$9:$K$1007564,Journals!$D$9:$D$1007564,"<"&$F$7,Journals!$J$9:$J$1007564,"Interest income from APSCL") -> 983653.13
G26: Interest income from Bank Asia Bond | H26: =MAX(0,SUMIFS(Journals!$K$9:$K$1007564,Journals!$D$9:$D$1007564,">"&$E$7,Journals!$D$9:$D$1007564,"<"&$E$8,Journals!$J$9:$J$1007564,"Interest income from Bank Asia Bond")-SUMIFS(Journals!$L$9:$L$1007564,Journals!$D$9:$D$1007564,">"&$E$7,Journals!$D$9:$D$1007564,"<"&$E$8,Journals!$J$9:$J$1007564,"Interest income from Bank Asia Bond")) -> 0 | I26: =MAX(0,SUMIFS(Journals!$L$9:$L$1007564,Journals!$D$9:$D$1007564,">"&$E$7,Journals!$D$9:$D$1007564,"<"&$E$8,Journals!$J$9:$J$1007564,"Interest income from Bank Asia Bond")-SUMIFS(Journals!$K$9:$K$1007564,Journals!$D$9:$D$1007564,">"&$E$7,Journals!$D$9:$D$1007564,"<"&$E$8,Journals!$J$9:$J$1007564,"Interest income from Bank Asia Bond")) -> 873164.87 | K26: =SUMIFS(Journals!$L$9:$L$1007564,Journals!$D$9:$D$1007564,"<"&$F$7,Journals!$J$9:$J$1007564,"Interest income from Bank Asia Bond")-SUMIFS(Journals!$K$9:$K$1007564,Journals!$D$9:$D$1007564,"<"&$F$7,Journals!$J$9:$J$1007564,"Interest income from Bank Asia Bond") -> 0 | M26: =K26+I26-H26 -> 873164.87 | O26: =SUMIFS(Journals!$L$9:$L$1007564,Journals!$D$9:$D$1007564,"<"&$F$7,Journals!$J$9:$J$1007564,"Interest income from Bank Asia Bond")-SUMIFS(Journals!$K$9:$K$1007564,Journals!$D$9:$D$1007564,"<"&$F$7,Journals!$J$9:$J$1007564,"Interest income from Bank Asia Bond") -> 0
G27: Interest income from BRAC Bank Bond | H27: =MAX(0,SUMIFS(Journals!$K$9:$K$1007564,Journals!$D$9:$D$1007564,">"&$E$7,Journals!$D$9:$D$1007564,"<"&$E$8,Journals!$J$9:$J$1007564,"Interest income from BRAC Bank Bond")-SUMIFS(Journals!$L$9:$L$1007564,Journals!$D$9:$D$1007564,">"&$E$7,Journals!$D$9:$D$1007564,"<"&$E$8,Journals!$J$9:$J$1007564,"Interest income from BRAC Bank Bond")) -> 0 | I27: =MAX(0,SUMIFS(Journals!$L$9:$L$1007564,Journals!$D$9:$D$1007564,">"&$E$7,Journals!$D$9:$D$1007564,"<"&$E$8,Journals!$J$9:$J$1007564,"Interest income from BRAC Bank Bond")-SUMIFS(Journals!$K$9:$K$1007564,Journals!$D$9:$D$1007564,">"&$E$7,Journals!$D$9:$D$1007564,"<"&$E$8,Journals!$J$9:$J$1007564,"Interest income from BRAC Bank Bond")) -> 2800879.1 | K27: =SUMIFS(Journals!$L$9:$L$1007564,Journals!$D$9:$D$1007564,"<"&$F$7,Journals!$J$9:$J$1007564,"Interest income from BRAC Bank Bond")-SUMIFS(Journals!$K$9:$K$1007564,Journals!$D$9:$D$1007564,"<"&$F$7,Journals!$J$9:$J$1007564,"Interest income from BRAC Bank Bond") -> 0 | M27: =K27+I27-H27 -> 2800879.1 | O27: =SUMIFS(Journals!$L$9:$L$1007564,Journals!$D$9:$D$1007564,"<"&$F$7,Journals!$J$9:$J$1007564,"Interest income from BRAC Bank Bond")-SUMIFS(Journals!$K$9:$K$1007564,Journals!$D$9:$D$1007564,"<"&$F$7,Journals!$J$9:$J$1007564,"Interest income from BRAC Bank Bond") -> 0
G28: Interest income from Dhaka Bank Bond | H28: =MAX(0,SUMIFS(Journals!$K$9:$K$1007564,Journals!$D$9:$D$1007564,">"&$E$7,Journals!$D$9:$D$1007564,"<"&$E$8,Journals!$J$9:$J$1007564,"Interest income from Dhaka Bank Bond")-SUMIFS(Journals!$L$9:$L$1007564,Journals!$D$9:$D$1007564,">"&$E$7,Journals!$D$9:$D$1007564,"<"&$E$8,Journals!$J$9:$J$1007564,"Interest income from Dhaka Bank Bond")) -> 0 | I28: =MAX(0,SUMIFS(Journals!$L$9:$L$1007564,Journals!$D$9:$D$1007564,">"&$E$7,Journals!$D$9:$D$1007564,"<"&$E$8,Journals!$J$9:$J$1007564,"Interest income from Dhaka Bank Bond")-SUMIFS(Journals!$K$9:$K$1007564,Journals!$D$9:$D$1007564,">"&$E$7,Journals!$D$9:$D$1007564,"<"&$E$8,Journals!$J$9:$J$1007564,"Interest income from Dhaka Bank Bond")) -> 0 | K28: =SUMIFS(Journals!$L$9:$L$1007564,Journals!$D$9:$D$1007564,"<"&$F$7,Journals!$J$9:$J$1007564,"Interest income from Dhaka Bank Bond")-SUMIFS(Journals!$K$9:$K$1007564,Journals!$D$9:$D$1007564,"<"&$F$7,Journals!$J$9:$J$1007564,"Interest income from Dhaka Bank Bond") -> 0 | M28: =K28+I28-H28 -> 0 | O28: =SUMIFS(Journals!$L$9:$L$1007564,Journals!$D$9:$D$1007564,"<"&$F$7,Journals!$J$9:$J$1007564,"Interest income from Dhaka Bank Bond")-SUMIFS(Journals!$K$9:$K$1007564,Journals!$D$9:$D$1007564,"<"&$F$7,Journals!$J$9:$J$1007564,"Interest income from Dhaka Bank Bond") -> 0
G29: Interest income from Bank Acc. | H29: =MAX(0,SUMIFS(Journals!$K$9:$K$1007564,Journals!$D$9:$D$1007564,">"&$E$7,Journals!$D$9:$D$1007564,"<"&$E$8,Journals!$J$9:$J$1007564,"Interest income from Bank Acc.")-SUMIFS(Journals!$L$9:$L$1007564,Journals!$D$9:$D$1007564,">"&$E$7,Journals!$D$9:$D$1007564,"<"&$E$8,Journals!$J$9:$J$1007564,"Interest income from Bank Acc.")) -> 0 | I29: =MAX(0,SUMIFS(Journals!$L$9:$L$1007564,Journals!$D$9:$D$1007564,">"&$E$7,Journals!$D$9:$D$1007564,"<"&$E$8,Journals!$J$9:$J$1007564,"Interest income from Bank Acc.")-SUMIFS(Journals!$K$9:$K$1007564,Journals!$D$9:$D$1007564,">"&$E$7,Journals!$D$9:$D$1007564,"<"&$E$8,Journals!$J$9:$J$1007564,"Interest income from Bank Acc.")) -> 0 | K29: =SUMIFS(Journals!$L$9:$L$1007564,Journals!$D$9:$D$1007564,"<"&$F$7,Journals!$J$9:$J$1007564,"Interest income from Bank Acc.")-SUMIFS(Journals!$K$9:$K$1007564,Journals!$D$9:$D$1007564,"<"&$F$7,Journals!$J$9:$J$1007564,"Interest income from Bank Acc.") -> 0 | M29: =K29+I29-H29 -> 0 | O29: =SUMIFS(Journals!$L$9:$L$1007564,Journals!$D$9:$D$1007564,"<"&$F$7,Journals!$J$9:$J$1007564,"Interest income from Bank Acc.")-SUMIFS(Journals!$K$9:$K$1007564,Journals!$D$9:$D$1007564,"<"&$F$7,Journals!$J$9:$J$1007564,"Interest income from Bank Acc.") -> 0
G30: Interest income from FDR | H30: =MAX(0,SUMIFS(Journals!$K$9:$K$1007564,Journals!$D$9:$D$1007564,">"&$E$7,Journals!$D$9:$D$1007564,"<"&$E$8,Journals!$J$9:$J$1007564,"Interest income from FDR")-SUMIFS(Journals!$L$9:$L$1007564,Journals!$D$9:$D$1007564,">"&$E$7,Journals!$D$9:$D$1007564,"<"&$E$8,Journals!$J$9:$J$1007564,"Interest income from FDR")) -> 0 | I30: =MAX(0,SUMIFS(Journals!$L$9:$L$1007564,Journals!$D$9:$D$1007564,">"&$E$7,Journals!$D$9:$D$1007564,"<"&$E$8,Journals!$J$9:$J$1007564,"Interest income from FDR")-SUMIFS(Journals!$K$9:$K$1007564,Journals!$D$9:$D$1007564,">"&$E$7,Journals!$D$9:$D$1007564,"<"&$E$8,Journals!$J$9:$J$1007564,"Interest income from FDR")) -> 0 | K30: =SUMIFS(Journals!$L$9:$L$1007564,Journals!$D$9:$D$1007564,"<"&$F$7,Journals!$J$9:$J$1007564,"Interest income from FDR")-SUMIFS(Journals!$K$9:$K$1007564,Journals!$D$9:$D$1007564,"<"&$F$7,Journals!$J$9:$J$1007564,"Interest income from FDR") -> 0 | M30: =K30+I30-H30 -> 0 | O30: =SUMIFS(Journals!$L$9:$L$1007564,Journals!$D$9:$D$1007564,"<"&$F$7,Journals!$J$9:$J$1007564,"Interest income from FDR")-SUMIFS(Journals!$K$9:$K$1007564,Journals!$D$9:$D$1007564,"<"&$F$7,Journals!$J$9:$J$1007564,"Interest income from FDR") -> 0
G31: Interest income reduce for Bond Premium | H31: =MAX(0,SUMIFS(Journals!$K$9:$K$1007564,Journals!$D$9:$D$1007564,">"&$E$7,Journals!$D$9:$D$1007564,"<"&$E$8,Journals!$J$9:$J$1007564,"Interest income reduce for Bond Premium")-SUMIFS(Journals!$L$9:$L$1007564,Journals!$D$9:$D$1007564,">"&$E$7,Journals!$D$9:$D$1007564,"<"&$E$8,Journals!$J$9:$J$1007564,"Interest income reduce for Bond Premium")) -> 0 | I31: =MAX(0,SUMIFS(Journals!$L$9:$L$1007564,Journals!$D$9:$D$1007564,">"&$E$7,Journals!$D$9:$D$1007564,"<"&$E$8,Journals!$J$9:$J$1007564,"Interest income reduce for Bond Premium")-SUMIFS(Journals!$K$9:$K$1007564,Journals!$D$9:$D$1007564,">"&$E$7,Journals!$D$9:$D$1007564,"<"&$E$8,Journals!$J$9:$J$1007564,"Interest income reduce for Bond Premium")) -> 0 | J31: =SUMIFS(Journals!$K$9:$K$1006983,Journals!$D$9:$D$1006983,"<"&$F$7,Journals!$J$9:$J$1006983,"Interest income reduce for Bond Premium")-SUMIFS(Journals!$L$9:$L$1006983,Journals!$D$9:$D$1006983,"<"&$F$7,Journals!$J$9:$J$1006983,"Interest income reduce for Bond Premium") -> 0 | L31: =J31+H31-I31 -> 0
G32: ='Chart of Accounts'!B24 -> Bank charges and excise duties | H32: =MAX(0,SUMIFS(Journals!$K$9:$K$1007564,Journals!$D$9:$D$1007564,">"&$E$7,Journals!$D$9:$D$1007564,"<"&$E$8,Journals!$J$9:$J$1007564,"Bank charges and excise duties")-SUMIFS(Journals!$L$9:$L$1007564,Journals!$D$9:$D$1007564,">"&$E$7,Journals!$D$9:$D$1007564,"<"&$E$8,Journals!$J$9:$J$1007564,"Bank charges and excise duties")) -> 197576.65 | I32: =MAX(0,SUMIFS(Journals!$L$9:$L$1007564,Journals!$D$9:$D$1007564,">"&$E$7,Journals!$D$9:$D$1007564,"<"&$E$8,Journals!$J$9:$J$1007564,"Bank charges and excise duties")-SUMIFS(Journals!$K$9:$K$1007564,Journals!$D$9:$D$1007564,">"&$E$7,Journals!$D$9:$D$1007564,"<"&$E$8,Journals!$J$9:$J$1007564,"Bank charges and excise duties")) -> 0 | N32: =SUMIFS(Journals!$K$9:$K$1007564,Journals!$D$9:$D$1007564,"<"&$F$7,Journals!$J$9:$J$1007564,"Bank charges and excise duties")-SUMIFS(Journals!$L$9:$L$1007564,Journals!$D$9:$D$1007564,"<"&$F$7,Journals!$J$9:$J$1007564,"Bank charges and excise duties") -> 448498.71
G33: ='Chart of Accounts'!B25 -> Brokerage commission | H33: =MAX(0,SUMIFS(Journals!$K$9:$K$1007564,Journals!$D$9:$D$1007564,">"&$E$7,Journals!$D$9:$D$1007564,"<"&$E$8,Journals!$J$9:$J$1007564,"brokerage commission")-SUMIFS(Journals!$L$9:$L$1007564,Journals!$D$9:$D$1007564,">"&$E$7,Journals!$D$9:$D$1007564,"<"&$E$8,Journals!$J$9:$J$1007564,"brokerage commission")) -> 16190.198 | I33: =MAX(0,SUMIFS(Journals!$L$9:$L$1007564,Journals!$D$9:$D$1007564,">"&$E$7,Journals!$D$9:$D$1007564,"<"&$E$8,Journals!$J$9:$J$1007564,"brokerage commission")-SUMIFS(Journals!$K$9:$K$1007564,Journals!$D$9:$D$1007564,">"&$E$7,Journals!$D$9:$D$1007564,"<"&$E$8,Journals!$J$9:$J$1007564,"brokerage commission")) -> 0 | N33: =SUMIFS(Journals!$K$9:$K$1007564,Journals!$D$9:$D$1007564,"<"&$F$7,Journals!$J$9:$J$1007564,"brokerage commission")-SUMIFS(Journals!$L$9:$L$1007564,Journals!$D$9:$D$1007564,"<"&$F$7,Journals!$J$9:$J$1007564,"brokerage commission") -> 6215.72
G34: Unrealized gain on securities | H34: =MAX(0,SUMIFS(Journals!$K$9:$K$1007564,Journals!$D$9:$D$1007564,">"&$E$7,Journals!$D$9:$D$1007564,"<"&$E$8,Journals!$J$9:$J$1007564,"Unrealized gain on securities")-SUMIFS(Journals!$L$9:$L$1007564,Journals!$D$9:$D$1007564,">"&$E$7,Journals!$D$9:$D$1007564,"<"&$E$8,Journals!$J$9:$J$1007564,"Unrealized gain on securities")) -> 0 | I34: =MAX(0,SUMIFS(Journals!$L$9:$L$1007564,Journals!$D$9:$D$1007564,">"&$E$7,Journals!$D$9:$D$1007564,"<"&$E$8,Journals!$J$9:$J$1007564,"Unrealized gain on securities")-SUMIFS(Journals!$K$9:$K$1007564,Journals!$D$9:$D$1007564,">"&$E$7,Journals!$D$9:$D$1007564,"<"&$E$8,Journals!$J$9:$J$1007564,"Unrealized gain on securities")) -> 903883.5 | J34: =SUMIFS(Journals!$K$9:$K$1006983,Journals!$D$9:$D$1006983,"<"&$F$7,Journals!$J$9:$J$1006983,"Unrealized gain on securities")-SUMIFS(Journals!$L$9:$L$1006983,Journals!$D$9:$D$1006983,"<"&$F$7,Journals!$J$9:$J$1006983,"Unrealized gain on securities") -> 743252.62 | N34: =SUMIFS(Journals!K6:K1007561,Journals!D6:D1007561,"<"&F4,Journals!J6:J1007561,"Unrealized gain on securities")-SUMIFS(Journals!L6:L1007561,Journals!D6:D1007561,"<"&F4,Journals!J6:J1007561,"Unrealized gain on securities") -> 0 | O34: =SUMIFS(Journals!$L$9:$L$1003833,Journals!$D$9:$D$1003833,"<"&$F$7,Journals!$J$9:$J$1003833,"unrealized gain on securities")-SUMIFS(Journals!$K$9:$K$1003833,Journals!$D$9:$D$1003833,"<"&$F$7,Journals!$J$9:$J$1003833,"unrealized gain on securities") -> -743252.62
G35: Unrealized gain on T-Bill | H35: =MAX(0,SUMIFS(Journals!$K$9:$K$1007564,Journals!$D$9:$D$1007564,">"&$E$7,Journals!$D$9:$D$1007564,"<"&$E$8,Journals!$J$9:$J$1007564,"Unrealized gain on T-Bill")-SUMIFS(Journals!$L$9:$L$1007564,Journals!$D$9:$D$1007564,">"&$E$7,Journals!$D$9:$D$1007564,"<"&$E$8,Journals!$J$9:$J$1007564,"Unrealized gain on T-Bill")) -> 1185081 | I35: =MAX(0,SUMIFS(Journals!$L$9:$L$1007564,Journals!$D$9:$D$1007564,">"&$E$7,Journals!$D$9:$D$1007564,"<"&$E$8,Journals!$J$9:$J$1007564,"Unrealized gain on T-Bill")-SUMIFS(Journals!$K$9:$K$1007564,Journals!$D$9:$D$1007564,">"&$E$7,Journals!$D$9:$D$1007564,"<"&$E$8,Journals!$J$9:$J$1007564,"Unrealized gain on T-Bill")) -> 0 | K35: =SUMIFS(Journals!$L$9:$L$1007564,Journals!$D$9:$D$1007564,"<"&$F$7,Journals!$J$9:$J$1007564,"Unrealized gain on T-Bill")-SUMIFS(Journals!$K$9:$K$1007564,Journals!$D$9:$D$1007564,"<"&$F$7,Journals!$J$9:$J$1007564,"Unrealized gain on T-Bill") -> 1185080.8 | N35: =SUMIFS(Journals!K7:K1007562,Journals!D7:D1007562,"<"&F5,Journals!J7:J1007562,"Unrealized gain on T-Bill")-SUMIFS(Journals!L7:L1007562,Journals!D7:D1007562,"<"&F5,Journals!J7:J1007562,"Unrealized gain on T-Bill") -> 0 | O35: =SUMIFS(Journals!$L$9:$L$995849,Journals!$D$9:$D$995849,"<"&$F$7,Journals!$J$9:$J$995849,"Unrealized gain on T-Bill")-SUMIFS(Journals!$K$9:$K$995849,Journals!$D$9:$D$995849,"<"&$F$7,Journals!$J$9:$J$995849,"Unrealized gain on T-Bill") -> 1185080.8
G36: Unrealized gain on T-Bond | H36: =MAX(0,SUMIFS(Journals!$K$9:$K$1007564,Journals!$D$9:$D$1007564,">"&$E$7,Journals!$D$9:$D$1007564,"<"&$E$8,Journals!$J$9:$J$1007564,"Unrealized gain on T-Bond")-SUMIFS(Journals!$L$9:$L$1007564,Journals!$D$9:$D$1007564,">"&$E$7,Journals!$D$9:$D$1007564,"<"&$E$8,Journals!$J$9:$J$1007564,"Unrealized gain on T-Bond")) -> 0 | I36: =MAX(0,SUMIFS(Journals!$L$9:$L$1007564,Journals!$D$9:$D$1007564,">"&$E$7,Journals!$D$9:$D$1007564,"<"&$E$8,Journals!$J$9:$J$1007564,"Unrealized gain on T-Bond")-SUMIFS(Journals!$K$9:$K$1007564,Journals!$D$9:$D$1007564,">"&$E$7,Journals!$D$9:$D$1007564,"<"&$E$8,Journals!$J$9:$J$1007564,"Unrealized gain on T-Bond")) -> 2659228.1 | K36: =SUMIFS(Journals!$L$9:$L$1007564,Journals!$D$9:$D$1007564,"<"&$F$7,Journals!$J$9:$J$1007564,"Unrealized gain on T-Bond")-SUMIFS(Journals!$K$9:$K$1007564,Journals!$D$9:$D$1007564,"<"&$F$7,Journals!$J$9:$J$1007564,"Unrealized gain on T-Bond") -> 2033627.1 | N36: =SUMIFS(Journals!K8:K1007563,Journals!D8:D1007563,"<"&F6,Journals!J8:J1007563,"Unrealized gain on T-Bond")-SUMIFS(Journals!L8:L1007563,Journals!D8:D1007563,"<"&F6,Journals!J8:J1007563,"Unrealized gain on T-Bond") -> 0 | O36: =SUMIFS(Journals!$L$9:$L$995849,Journals!$D$9:$D$995849,"<"&$F$7,Journals!$J$9:$J$995849,"Unrealized gain on T-Bond")-SUMIFS(Journals!$K$9:$K$995849,Journals!$D$9:$D$995849,"<"&$F$7,Journals!$J$9:$J$995849,"Unrealized gain on T-Bond") -> 2033627.1
G37: ='Chart of Accounts'!B29 -> Unrealized loss on securities | H37: =MAX(0,SUMIFS(Journals!$K$9:$K$1007564,Journals!$D$9:$D$1007564,">"&$E$7,Journals!$D$9:$D$1007564,"<"&$E$8,Journals!$J$9:$J$1007564,"Unrealized loss on securities")-SUMIFS(Journals!$L$9:$L$1007564,Journals!$D$9:$D$1007564,">"&$E$7,Journals!$D$9:$D$1007564,"<"&$E$8,Journals!$J$9:$J$1007564,"Unrealized loss on securities")) -> 0 | I37: =MAX(0,SUMIFS(Journals!$L$9:$L$1007564,Journals!$D$9:$D$1007564,">"&$E$7,Journals!$D$9:$D$1007564,"<"&$E$8,Journals!$J$9:$J$1007564,"Unrealized loss on securities")-SUMIFS(Journals!$K$9:$K$1007564,Journals!$D$9:$D$1007564,">"&$E$7,Journals!$D$9:$D$1007564,"<"&$E$8,Journals!$J$9:$J$1007564,"Unrealized loss on securities")) -> 0 | N37: =SUMIFS(Journals!K9:K1007564,Journals!D9:D1007564,"<"&F7,Journals!J9:J1007564,"unrealized loss on securities")-SUMIFS(Journals!L9:L1007564,Journals!D9:D1007564,"<"&F7,Journals!J9:J1007564,"unrealized loss on securities") -> 0
G38: ='Chart of Accounts'!B30 -> Amortization of preliminary and issue expense | H38: =MAX(0,SUMIFS(Journals!$K$9:$K$1007564,Journals!$D$9:$D$1007564,">"&$E$7,Journals!$D$9:$D$1007564,"<"&$E$8,Journals!$J$9:$J$1007564,"Amortization of preliminary and issue expense")-SUMIFS(Journals!$L$9:$L$1007564,Journals!$D$9:$D$1007564,">"&$E$7,Journals!$D$9:$D$1007564,"<"&$E$8,Journals!$J$9:$J$1007564,"Amortization of preliminary and issue expense")) -> 184261.73 | I38: =MAX(0,SUMIFS(Journals!$L$9:$L$1007564,Journals!$D$9:$D$1007564,">"&$E$7,Journals!$D$9:$D$1007564,"<"&$E$8,Journals!$J$9:$J$1007564,"Amortization of preliminary and issue expense")-SUMIFS(Journals!$K$9:$K$1007564,Journals!$D$9:$D$1007564,">"&$E$7,Journals!$D$9:$D$1007564,"<"&$E$8,Journals!$J$9:$J$1007564,"Amortization of preliminary and issue expense")) -> 0 | N38: =SUMIFS(Journals!$K$9:$K$1007564,Journals!$D$9:$D$1007564,"<"&$F$7,Journals!$J$9:$J$1007564,"Amortization of preliminary and issue expense")-SUMIFS(Journals!$L$9:$L$1007564,Journals!$D$9:$D$1007564,"<"&$F$7,Journals!$J$9:$J$1007564,"Amortization of preliminary and issue expense") -> 256008.91
G39: ='Chart of Accounts'!B31 -> Management Fee | H39: =MAX(0,SUMIFS(Journals!$K$9:$K$1007564,Journals!$D$9:$D$1007564,">"&$E$7,Journals!$D$9:$D$1007564,"<"&$E$8,Journals!$J$9:$J$1007564,"management fee")-SUMIFS(Journals!$L$9:$L$1007564,Journals!$D$9:$D$1007564,">"&$E$7,Journals!$D$9:$D$1007564,"<"&$E$8,Journals!$J$9:$J$1007564,"management fee")) -> 2325669.4 | I39: =MAX(0,SUMIFS(Journals!$L$9:$L$1007564,Journals!$D$9:$D$1007564,">"&$E$7,Journals!$D$9:$D$1007564,"<"&$E$8,Journals!$J$9:$J$1007564,"management fee")-SUMIFS(Journals!$K$9:$K$1007564,Journals!$D$9:$D$1007564,">"&$E$7,Journals!$D$9:$D$1007564,"<"&$E$8,Journals!$J$9:$J$1007564,"management fee")) -> 0 | N39: =SUMIFS(Journals!$K$9:$K$1007564,Journals!$D$9:$D$1007564,"<"&$F$7,Journals!$J$9:$J$1007564,"management fee")-SUMIFS(Journals!$L$9:$L$1007564,Journals!$D$9:$D$1007564,"<"&$F$7,Journals!$J$9:$J$1007564,"management fee") -> 1060053.5
G40: ='Chart of Accounts'!B32 -> Trustee fee | H40: =MAX(0,SUMIFS(Journals!$K$9:$K$1007564,Journals!$D$9:$D$1007564,">"&$E$7,Journals!$D$9:$D$1007564,"<"&$E$8,Journals!$J$9:$J$1007564,"trustee fee")-SUMIFS(Journals!$L$9:$L$1007564,Journals!$D$9:$D$1007564,">"&$E$7,Journals!$D$9:$D$1007564,"<"&$E$8,Journals!$J$9:$J$1007564,"trustee fee")) -> 233022.32 | I40: =MAX(0,SUMIFS(Journals!$L$9:$L$1007564,Journals!$D$9:$D$1007564,">"&$E$7,Journals!$D$9:$D$1007564,"<"&$E$8,Journals!$J$9:$J$1007564,"trustee fee")-SUMIFS(Journals!$K$9:$K$1007564,Journals!$D$9:$D$1007564,">"&$E$7,Journals!$D$9:$D$1007564,"<"&$E$8,Journals!$J$9:$J$1007564,"trustee fee")) -> 0 | N40: =SUMIFS(Journals!$K$9:$K$1007564,Journals!$D$9:$D$1007564,"<"&$F$7,Journals!$J$9:$J$1007564,"trustee fee")-SUMIFS(Journals!$L$9:$L$1007564,Journals!$D$9:$D$1007564,"<"&$F$7,Journals!$J$9:$J$1007564,"trustee fee") -> 128184.38
G41: Advanced BSEC Annual Fee | H41: =MAX(0,SUMIFS(Journals!$K$9:$K$1007494,Journals!$D$9:$D$1007494,">"&$E$7,Journals!$D$9:$D$1007494,"<"&$E$8,Journals!$J$9:$J$1007494,"Advanced BSEC Annual Fee")-SUMIFS(Journals!$L$9:$L$1007494,Journals!$D$9:$D$1007494,">"&$E$7,Journals!$D$9:$D$1007494,"<"&$E$8,Journals!$J$9:$J$1007494,"Advanced BSEC Annual Fee")) -> 0 | I41: =MAX(0,SUMIFS(Journals!$L$9:$L$1007494,Journals!$D$9:$D$1007494,">"&$E$7,Journals!$D$9:$D$1007494,"<"&$E$8,Journals!$J$9:$J$1007494,"Advanced BSEC Annual Fee")-SUMIFS(Journals!$K$9:$K$1007494,Journals!$D$9:$D$1007494,">"&$E$7,Journals!$D$9:$D$1007494,"<"&$E$8,Journals!$J$9:$J$1007494,"Advanced BSEC Annual Fee")) -> 0 | J41: =SUMIFS(Journals!$K$9:$K$1007494,Journals!$D$9:$D$1007494,"<"&$F$7,Journals!$J$9:$J$1007494,"Advanced BSEC Annual Fee")-SUMIFS(Journals!$L$9:$L$1007494,Journals!$D$9:$D$1007494,"<"&$F$7,Journals!$J$9:$J$1007494,"Advanced BSEC Annual Fee") -> 0 | L41: =J41+H41-I41 -> 0
G42: ='Chart of Accounts'!B33 -> BSEC Annual Fee | H42: =MAX(0,SUMIFS(Journals!$K$9:$K$1007564,Journals!$D$9:$D$1007564,">"&$E$7,Journals!$D$9:$D$1007564,"<"&$E$8,Journals!$J$9:$J$1007564,"bsec annual fee")-SUMIFS(Journals!$L$9:$L$1007564,Journals!$D$9:$D$1007564,">"&$E$7,Journals!$D$9:$D$1007564,"<"&$E$8,Journals!$J$9:$J$1007564,"bsec annual fee")) -> 355635.5 | I42: =MAX(0,SUMIFS(Journals!$L$9:$L$1007564,Journals!$D$9:$D$1007564,">"&$E$7,Journals!$D$9:$D$1007564,"<"&$E$8,Journals!$J$9:$J$1007564,"bsec annual fee")-SUMIFS(Journals!$K$9:$K$1007564,Journals!$D$9:$D$1007564,">"&$E$7,Journals!$D$9:$D$1007564,"<"&$E$8,Journals!$J$9:$J$1007564,"bsec annual fee")) -> 0 | N42: =SUMIFS(Journals!$K$9:$K$1007564,Journals!$D$9:$D$1007564,"<"&$F$7,Journals!$J$9:$J$1007564,"bsec annual fee")-SUMIFS(Journals!$L$9:$L$1007564,Journals!$D$9:$D$1007564,"<"&$F$7,Journals!$J$9:$J$1007564,"bsec annual fee") -> 125666.74
G43: ='Chart of Accounts'!B34 -> Audit fee | H43: =MAX(0,SUMIFS(Journals!$K$9:$K$1007564,Journals!$D$9:$D$1007564,">"&$E$7,Journals!$D$9:$D$1007564,"<"&$E$8,Journals!$J$9:$J$1007564,"audit fee")-SUMIFS(Journals!$L$9:$L$1007564,Journals!$D$9:$D$1007564,">"&$E$7,Journals!$D$9:$D$1007564,"<"&$E$8,Journals!$J$9:$J$1007564,"audit fee")) -> 35000 | I43: =MAX(0,SUMIFS(Journals!$L$9:$L$1007564,Journals!$D$9:$D$1007564,">"&$E$7,Journals!$D$9:$D$1007564,"<"&$E$8,Journals!$J$9:$J$1007564,"audit fee")-SUMIFS(Journals!$K$9:$K$1007564,Journals!$D$9:$D$1007564,">"&$E$7,Journals!$D$9:$D$1007564,"<"&$E$8,Journals!$J$9:$J$1007564,"audit fee")) -> 0 | N43: =SUMIFS(Journals!$K$9:$K$1007564,Journals!$D$9:$D$1007564,"<"&$F$7,Journals!$J$9:$J$1007564,"audit fee")-SUMIFS(Journals!$L$9:$L$1007564,Journals!$D$9:$D$1007564,"<"&$F$7,Journals!$J$9:$J$1007564,"audit fee") -> 54500
G44: ='Chart of Accounts'!B35 -> CDBL charges | H44: =MAX(0,SUMIFS(Journals!$K$9:$K$1007564,Journals!$D$9:$D$1007564,">"&$E$7,Journals!$D$9:$D$1007564,"<"&$E$8,Journals!$J$9:$J$1007564,"cdbl charges")-SUMIFS(Journals!$L$9:$L$1007564,Journals!$D$9:$D$1007564,">"&$E$7,Journals!$D$9:$D$1007564,"<"&$E$8,Journals!$J$9:$J$1007564,"cdbl charges")) -> 1903.25 | I44: =MAX(0,SUMIFS(Journals!$L$9:$L$1007564,Journals!$D$9:$D$1007564,">"&$E$7,Journals!$D$9:$D$1007564,"<"&$E$8,Journals!$J$9:$J$1007564,"cdbl charges")-SUMIFS(Journals!$K$9:$K$1007564,Journals!$D$9:$D$1007564,">"&$E$7,Journals!$D$9:$D$1007564,"<"&$E$8,Journals!$J$9:$J$1007564,"cdbl charges")) -> 0 | N44: =SUMIFS(Journals!$K$9:$K$1007564,Journals!$D$9:$D$1007564,"<"&$F$7,Journals!$J$9:$J$1007564,"cdbl charges")-SUMIFS(Journals!$L$9:$L$1007564,Journals!$D$9:$D$1007564,"<"&$F$7,Journals!$J$9:$J$1007564,"cdbl charges") -> 2680.09
G45: ='Chart of Accounts'!B36 -> Fair value adjustment | H45: =MAX(0,SUMIFS(Journals!$K$9:$K$1007564,Journals!$D$9:$D$1007564,">"&$E$7,Journals!$D$9:$D$1007564,"<"&$E$8,Journals!$J$9:$J$1007564,"Fair value adjustment")-SUMIFS(Journals!$L$9:$L$1007564,Journals!$D$9:$D$1007564,">"&$E$7,Journals!$D$9:$D$1007564,"<"&$E$8,Journals!$J$9:$J$1007564,"Fair value adjustment")) -> 903883.5 | I45: =MAX(0,SUMIFS(Journals!$L$9:$L$1007564,Journals!$D$9:$D$1007564,">"&$E$7,Journals!$D$9:$D$1007564,"<"&$E$8,Journals!$J$9:$J$1007564,"fair value adjustment")-SUMIFS(Journals!$K$9:$K$1007564,Journals!$D$9:$D$1007564,">"&$E$7,Journals!$D$9:$D$1007564,"<"&$E$8,Journals!$J$9:$J$1007564,"fair value adjustment")) -> 0 | J45: =MAX(0,SUMIFS(Journals!K9:K1007564,Journals!D9:D1007564,"<"&F7,Journals!J9:J1007564,"fair value adjustment")-SUMIFS(Journals!L9:L1007564,Journals!D9:D1007564,"<"&F7,Journals!J9:J1007564,"fair value adjustment")) -> 0 | K45: =MAX(0,SUMIFS(Journals!L9:L1007564,Journals!D9:D1007564,"<"&F7,Journals!J9:J1007564,"Fair value adjustment")-SUMIFS(Journals!K9:K1007564,Journals!D9:D1007564,"<"&F7,Journals!J9:J1007564,"fair value adjustment")) -> 743252.62 | L45: =MAX(0,H45+J45-K45) -> 160630.88 | M45: =MAX(0,I45+K45-L45) -> 582621.74
G46: Fair value adjustment in T-Bill | H46: =MAX(0,SUMIFS(Journals!$K$9:$K$1007564,Journals!$D$9:$D$1007564,">"&$E$7,Journals!$D$9:$D$1007564,"<"&$E$8,Journals!$J$9:$J$1007564,"Fair value adjustment in T-Bill")-SUMIFS(Journals!$L$9:$L$1007564,Journals!$D$9:$D$1007564,">"&$E$7,Journals!$D$9:$D$1007564,"<"&$E$8,Journals!$J$9:$J$1007564,"Fair value adjustment in T-Bill")) -> 0 | I46: =MAX(0,SUMIFS(Journals!$L$9:$L$1007564,Journals!$D$9:$D$1007564,">"&$E$7,Journals!$D$9:$D$1007564,"<"&$E$8,Journals!$J$9:$J$1007564,"fair value adjustment in T-Bill")-SUMIFS(Journals!$K$9:$K$1007564,Journals!$D$9:$D$1007564,">"&$E$7,Journals!$D$9:$D$1007564,"<"&$E$8,Journals!$J$9:$J$1007564,"fair value adjustment in T-Bill")) -> 1185081 | J46: =MAX(0,SUMIFS(Journals!K9:K1007564,Journals!D9:D1007564,"<"&F7,Journals!J9:J1007564,"fair value adjustment in T-Bill")-SUMIFS(Journals!L9:L1007564,Journals!D9:D1007564,"<"&F7,Journals!J9:J1007564,"fair value adjustment in T-Bill")) -> 1185080.8 | K46: =MAX(0,SUMIFS(Journals!L9:L1007564,Journals!D9:D1007564,"<"&F7,Journals!J9:J1007564,"Fair value adjustment in T-Bill")-SUMIFS(Journals!K9:K1007564,Journals!D9:D1007564,"<"&F7,Journals!J9:J1007564,"fair value adjustment in T-Bill")) -> 0 | L46: =MAX(0,H46-I46+J46-K46) -> 0 | M46: =MAX(0,I46-H46-J46+K46) -> 0.19999999
G47: Fair value adjustment in T-Bond | H47: =MAX(0,SUMIFS(Journals!$K$9:$K$1007564,Journals!$D$9:$D$1007564,">"&$E$7,Journals!$D$9:$D$1007564,"<"&$E$8,Journals!$J$9:$J$1007564,"Fair value adjustment in T-Bond")-SUMIFS(Journals!$L$9:$L$1007564,Journals!$D$9:$D$1007564,">"&$E$7,Journals!$D$9:$D$1007564,"<"&$E$8,Journals!$J$9:$J$1007564,"Fair value adjustment in T-Bond")) -> 2659228.1 | I47: =MAX(0,SUMIFS(Journals!$L$9:$L$1007564,Journals!$D$9:$D$1007564,">"&$E$7,Journals!$D$9:$D$1007564,"<"&$E$8,Journals!$J$9:$J$1007564,"fair value adjustment in T-Bond")-SUMIFS(Journals!$K$9:$K$1007564,Journals!$D$9:$D$1007564,">"&$E$7,Journals!$D$9:$D$1007564,"<"&$E$8,Journals!$J$9:$J$1007564,"fair value adjustment in T-Bond")) -> 0 | J47: =MAX(0,SUMIFS(Journals!K9:K1003833,Journals!D9:D1003833,"<"&F7,Journals!J9:J1003833,"Fair value adjustment in T-Bond")-SUMIFS(Journals!L9:L1003833,Journals!D9:D1003833,"<"&F7,Journals!J9:J1003833,"Fair value adjustment in T-Bond")) -> 2033627.1 | K47: =MAX(0,SUMIFS(Journals!L9:L1007564,Journals!D9:D1007564,"<"&F7,Journals!J9:J1007564,"Fair value adjustment in T-Bond")-SUMIFS(Journals!K9:K1007564,Journals!D9:D1007564,"<"&F7,Journals!J9:J1007564,"fair value adjustment in T-Bond")) -> 0 | L47: =MAX(0,H47-I47+J47-K47) -> 4692855.2 | M47: =MAX(0,I47-H47-J47+K47) -> 0
G48: ='Chart of Accounts'!B39 -> Interest receivables from FDR | H48: =MAX(0,SUMIFS(Journals!$K$9:$K$1007564,Journals!$D$9:$D$1007564,">"&$E$7,Journals!$D$9:$D$1007564,"<"&$E$8,Journals!$J$9:$J$1007564,"Interest receivables from FDR")-SUMIFS(Journals!$L$9:$L$1007564,Journals!$D$9:$D$1007564,">"&$E$7,Journals!$D$9:$D$1007564,"<"&$E$8,Journals!$J$9:$J$1007564,"Interest receivables from FDR")) -> 196601.92 | I48: =MAX(0,SUMIFS(Journals!$L$9:$L$1007564,Journals!$D$9:$D$1007564,">"&$E$7,Journals!$D$9:$D$1007564,"<"&$E$8,Journals!$J$9:$J$1007564,"Interest receivables from FDR")-SUMIFS(Journals!$K$9:$K$1007564,Journals!$D$9:$D$1007564,">"&$E$7,Journals!$D$9:$D$1007564,"<"&$E$8,Journals!$J$9:$J$1007564,"Interest receivables from FDR")) -> 0 | J48: =SUMIFS(Journals!$K$9:$K$1007564,Journals!$D$9:$D$1007564,"<"&$F$7,Journals!$J$9:$J$1007564,"Interest receivables from FDR")-SUMIFS(Journals!$L$9:$L$1007564,Journals!$D$9:$D$1007564,"<"&$F$7,Journals!$J$9:$J$1007564,"Interest receivables from FDR") -> 1165151.1 | L48: =J48+H48-I48 -> 1361753
G49: ='Chart of Accounts'!B40 -> Payable to broker | H49: =MAX(0,SUMIFS(Journals!$K$9:$K$1007564,Journals!$D$9:$D$1007564,">"&$E$7,Journals!$D$9:$D$1007564,"<"&$E$8,Journals!$J$9:$J$1007564,"payable to broker")-SUMIFS(Journals!$L$9:$L$1007564,Journals!$D$9:$D$1007564,">"&$E$7,Journals!$D$9:$D$1007564,"<"&$E$8,Journals!$J$9:$J$1007564,"payable to broker")) -> 0 | I49: =MAX(0,SUMIFS(Journals!$L$9:$L$1007564,Journals!$D$9:$D$1007564,">"&$E$7,Journals!$D$9:$D$1007564,"<"&$E$8,Journals!$J$9:$J$1007564,"payable to broker")-SUMIFS(Journals!$K$9:$K$1007564,Journals!$D$9:$D$1007564,">"&$E$7,Journals!$D$9:$D$1007564,"<"&$E$8,Journals!$J$9:$J$1007564,"payable to broker")) -> 0 | K49: =SUMIFS(Journals!$L$9:$L$1007564,Journals!$D$9:$D$1007564,"<"&$F$7,Journals!$J$9:$J$1007564,"payable to broker")-SUMIFS(Journals!$K$9:$K$1007564,Journals!$D$9:$D$1007564,"<"&$F$7,Journals!$J$9:$J$1007564,"payable to broker") -> 0 | M49: =K49+I49-H49 -> 0
G50: ='Chart of Accounts'!B41 -> Other operating expenses | H50: =MAX(0,SUMIFS(Journals!$K$9:$K$1007564,Journals!$D$9:$D$1007564,">"&$E$7,Journals!$D$9:$D$1007564,"<"&$E$8,Journals!$J$9:$J$1007564,"OTHER OPERATING EXPENSES")-SUMIFS(Journals!$L$9:$L$1007564,Journals!$D$9:$D$1007564,">"&$E$7,Journals!$D$9:$D$1007564,"<"&$E$8,Journals!$J$9:$J$1007564,"OTHER OPERATING EXPENSES")) -> 0 | I50: =MAX(0,SUMIFS(Journals!$L$9:$L$1007564,Journals!$D$9:$D$1007564,">"&$E$7,Journals!$D$9:$D$1007564,"<"&$E$8,Journals!$J$9:$J$1007564,"OTHER OPERATING EXPENSES")-SUMIFS(Journals!$K$9:$K$1007564,Journals!$D$9:$D$1007564,">"&$E$7,Journals!$D$9:$D$1007564,"<"&$E$8,Journals!$J$9:$J$1007564,"OTHER OPERATING EXPENSES")) -> 0 | N50: =SUMIFS(Journals!$K$9:$K$1007564,Journals!$D$9:$D$1007564,"<"&$F$7,Journals!$J$9:$J$1007564,"OTHER OPERATING EXPENSES")-SUMIFS(Journals!$L$9:$L$1007564,Journals!$D$9:$D$1007564,"<"&$F$7,Journals!$J$9:$J$1007564,"OTHER OPERATING EXPENSES") -> 46800
G51: ='Chart of Accounts'!B42 -> Dividend income | H51: =MAX(0,SUMIFS(Journals!$K$9:$K$1007564,Journals!$D$9:$D$1007564,">"&$E$7,Journals!$D$9:$D$1007564,"<"&$E$8,Journals!$J$9:$J$1007564,"dividend income")-SUMIFS(Journals!$L$9:$L$1007564,Journals!$D$9:$D$1007564,">"&$E$7,Journals!$D$9:$D$1007564,"<"&$E$8,Journals!$J$9:$J$1007564,"dividend income")) -> 0 | I51: =MAX(0,SUMIFS(Journals!$L$9:$L$1007564,Journals!$D$9:$D$1007564,">"&$E$7,Journals!$D$9:$D$1007564,"<"&$E$8,Journals!$J$9:$J$1007564,"dividend income")-SUMIFS(Journals!$K$9:$K$1007564,Journals!$D$9:$D$1007564,">"&$E$7,Journals!$D$9:$D$1007564,"<"&$E$8,Journals!$J$9:$J$1007564,"dividend income")) -> 0 | O51: =SUMIFS(Journals!$L$9:$L$1007564,Journals!$D$9:$D$1007564,"<"&$F$7,Journals!$J$9:$J$1007564,"dividend income")-SUMIFS(Journals!$K$9:$K$1007564,Journals!$D$9:$D$1007564,"<"&$F$7,Journals!$J$9:$J$1007564,"dividend income") -> 1124298.6
G52: ='Chart of Accounts'!B43 -> Dividend receivable | H52: =MAX(0,SUMIFS(Journals!$K$9:$K$1007494,Journals!$D$9:$D$1007494,">"&$E$7,Journals!$D$9:$D$1007494,"<"&$E$8,Journals!$J$9:$J$1007494,"dividend receivable")) -> 0 | I52: =MAX(0,SUMIFS(Journals!$L$9:$L$1007494,Journals!$D$9:$D$1007494,">"&$E$7,Journals!$D$9:$D$1007494,"<"&$E$8,Journals!$J$9:$J$1007494,"dividend receivable")) -> 0 | J52: =SUMIFS(Journals!$K$9:$K$1007564,Journals!$D$9:$D$1007564,"<"&$F$7,Journals!$J$9:$J$1007564,"dividend receivable")-SUMIFS(Journals!$L$9:$L$1007564,Journals!$D$9:$D$1007564,"<"&$F$7,Journals!$J$9:$J$1007564,"dividend receivable") -> 0 | L52: =J52+H52-I52 -> 0
G53: ='Chart of Accounts'!B44 -> Custodian fee | H53: =MAX(0,SUMIFS(Journals!$K$9:$K$1007564,Journals!$D$9:$D$1007564,">"&$E$7,Journals!$D$9:$D$1007564,"<"&$E$8,Journals!$J$9:$J$1007564,"custodian fee")-SUMIFS(Journals!$L$9:$L$1007564,Journals!$D$9:$D$1007564,">"&$E$7,Journals!$D$9:$D$1007564,"<"&$E$8,Journals!$J$9:$J$1007564,"custodian fee")) -> 313675.02 | N53: =SUMIFS(Journals!$K$9:$K$1007564,Journals!$D$9:$D$1007564,"<"&$F$7,Journals!$J$9:$J$1007564,"custodian fee")-SUMIFS(Journals!$L$9:$L$1007564,Journals!$D$9:$D$1007564,"<"&$F$7,Journals!$J$9:$J$1007564,"custodian fee") -> 55573.67
G54: ='Chart of Accounts'!B45 -> IPO Application | H54: =MAX(0,SUMIFS(Journals!$K$9:$K$1007564,Journals!$D$9:$D$1007564,">"&$E$7,Journals!$D$9:$D$1007564,"<"&$E$8,Journals!$J$9:$J$1007564,"IPO APPLICATION")-SUMIFS(Journals!$L$9:$L$1007564,Journals!$D$9:$D$1007564,">"&$E$7,Journals!$D$9:$D$1007564,"<"&$E$8,Journals!$J$9:$J$1007564,"IPO APPLICATION")) -> 0 | I54: =MAX(0,SUMIFS(Journals!$L$9:$L$1007564,Journals!$D$9:$D$1007564,">"&$E$7,Journals!$D$9:$D$1007564,"<"&$E$8,Journals!$J$9:$J$1007564,"IPO APPLICATION")-SUMIFS(Journals!$K$9:$K$1007564,Journals!$D$9:$D$1007564,">"&$E$7,Journals!$D$9:$D$1007564,"<"&$E$8,Journals!$J$9:$J$1007564,"IPO APPLICATION")) -> 0 | J54: =SUMIFS(Journals!$K$9:$K$1007564,Journals!$D$9:$D$1007564,"<"&$F$7,Journals!$J$9:$J$1007564,"IPO APPLICATION")-SUMIFS(Journals!$L$9:$L$1007564,Journals!$D$9:$D$1007564,"<"&$F$7,Journals!$J$9:$J$1007564,"IPO APPLICATION") -> 0 | L54: =J54+H54-I54 -> 0
G55: ='Chart of Accounts'!B46 -> IPO Application Fee | H55: =MAX(0,SUMIFS(Journals!$K$9:$K$1007564,Journals!$D$9:$D$1007564,">"&$E$7,Journals!$D$9:$D$1007564,"<"&$E$8,Journals!$J$9:$J$1007564,"IPO APPLICATION FEE")-SUMIFS(Journals!$L$9:$L$1007564,Journals!$D$9:$D$1007564,">"&$E$7,Journals!$D$9:$D$1007564,"<"&$E$8,Journals!$J$9:$J$1007564,"IPO APPLICATION FEE")) -> 0 | N55: =SUMIFS(Journals!$K$9:$K$1007564,Journals!$D$9:$D$1007564,"<"&$F$7,Journals!$J$9:$J$1007564,"IPO APPLICATION FEE")-SUMIFS(Journals!$L$9:$L$1007564,Journals!$D$9:$D$1007564,"<"&$F$7,Journals!$J$9:$J$1007564,"IPO APPLICATION FEE") -> 6000
G56: Realized gain | H56: =MAX(0,SUMIFS(Journals!$K$9:$K$1007564,Journals!$D$9:$D$1007564,">"&$E$7,Journals!$D$9:$D$1007564,"<"&$E$8,Journals!$J$9:$J$1007564,"realized gain")-SUMIFS(Journals!$L$9:$L$1007564,Journals!$D$9:$D$1007564,">"&$E$7,Journals!$D$9:$D$1007564,"<"&$E$8,Journals!$J$9:$J$1007564,"realized gain")) -> 565912.5 | I56: =MAX(0,SUMIFS(Journals!$L$9:$L$1007564,Journals!$D$9:$D$1007564,">"&$E$7,Journals!$D$9:$D$1007564,"<"&$E$8,Journals!$J$9:$J$1007564,"realized gain")-SUMIFS(Journals!$K$9:$K$1007564,Journals!$D$9:$D$1007564,">"&$E$7,Journals!$D$9:$D$1007564,"<"&$E$8,Journals!$J$9:$J$1007564,"realized gain")) -> 0 | O56: =SUMIFS(Journals!$L$9:$L$1007564,Journals!$D$9:$D$1007564,"<"&$F$7,Journals!$J$9:$J$1007564,"realized gain")-SUMIFS(Journals!$K$9:$K$1007564,Journals!$D$9:$D$1007564,"<"&$F$7,Journals!$J$9:$J$1007564,"realized gain") -> 1217617.6
G57: Realized gain from Bond Premium | H57: =MAX(0,SUMIFS(Journals!$K$9:$K$1007564,Journals!$D$9:$D$1007564,">"&$E$7,Journals!$D$9:$D$1007564,"<"&$E$8,Journals!$J$9:$J$1007564,"Realized gain from Bond Premium")-SUMIFS(Journals!$L$9:$L$1007564,Journals!$D$9:$D$1007564,">"&$E$7,Journals!$D$9:$D$1007564,"<"&$E$8,Journals!$J$9:$J$1007564,"Realized gain from Bond Premium")) -> 0 | I57: =MAX(0,SUMIFS(Journals!$L$9:$L$1007564,Journals!$D$9:$D$1007564,">"&$E$7,Journals!$D$9:$D$1007564,"<"&$E$8,Journals!$J$9:$J$1007564,"Realized gain from Bond Premium")-SUMIFS(Journals!$K$9:$K$1007564,Journals!$D$9:$D$1007564,">"&$E$7,Journals!$D$9:$D$1007564,"<"&$E$8,Journals!$J$9:$J$1007564,"Realized gain from Bond Premium")) -> 0 | O57: =SUMIFS(Journals!$L$9:$L$1007564,Journals!$D$9:$D$1007564,"<"&$F$7,Journals!$J$9:$J$1007564,"Realized gain from Bond Premium")-SUMIFS(Journals!$K$9:$K$1007564,Journals!$D$9:$D$1007564,"<"&$F$7,Journals!$J$9:$J$1007564,"Realized gain from Bond Premium") -> 0
G58: Realized gain on T-Bill | H58: =MAX(0,SUMIFS(Journals!$K$9:$K$1007564,Journals!$D$9:$D$1007564,">"&$E$7,Journals!$D$9:$D$1007564,"<"&$E$8,Journals!$J$9:$J$1007564,"realized gain on T-Bill")-SUMIFS(Journals!$L$9:$L$1007564,Journals!$D$9:$D$1007564,">"&$E$7,Journals!$D$9:$D$1007564,"<"&$E$8,Journals!$J$9:$J$1007564,"realized gain on T-Bill")) -> 0 | I58: =MAX(0,SUMIFS(Journals!$L$9:$L$1007564,Journals!$D$9:$D$1007564,">"&$E$7,Journals!$D$9:$D$1007564,"<"&$E$8,Journals!$J$9:$J$1007564,"realized gain on T-Bill")-SUMIFS(Journals!$K$9:$K$1007564,Journals!$D$9:$D$1007564,">"&$E$7,Journals!$D$9:$D$1007564,"<"&$E$8,Journals!$J$9:$J$1007564,"realized gain on T-Bill")) -> 5614592.5 | O58: =SUMIFS(Journals!$L$9:$L$1007564,Journals!$D$9:$D$1007564,"<"&$F$7,Journals!$J$9:$J$1007564,"realized gain on T-Bill")-SUMIFS(Journals!$K$9:$K$1007564,Journals!$D$9:$D$1007564,"<"&$F$7,Journals!$J$9:$J$1007564,"realized gain on T-Bill") -> 7756762.7
G59: Realized gain on T-Bond | H59: =MAX(0,SUMIFS(Journals!$K$9:$K$1007564,Journals!$D$9:$D$1007564,">"&$E$7,Journals!$D$9:$D$1007564,"<"&$E$8,Journals!$J$9:$J$1007564,"realized gain on T-Bond")-SUMIFS(Journals!$L$9:$L$1007564,Journals!$D$9:$D$1007564,">"&$E$7,Journals!$D$9:$D$1007564,"<"&$E$8,Journals!$J$9:$J$1007564,"realized gain on T-Bond")) -> 0 | I59: =MAX(0,SUMIFS(Journals!$L$9:$L$1007564,Journals!$D$9:$D$1007564,">"&$E$7,Journals!$D$9:$D$1007564,"<"&$E$8,Journals!$J$9:$J$1007564,"realized gain on T-Bond")-SUMIFS(Journals!$K$9:$K$1007564,Journals!$D$9:$D$1007564,">"&$E$7,Journals!$D$9:$D$1007564,"<"&$E$8,Journals!$J$9:$J$1007564,"realized gain on T-Bond")) -> 4592616.9 | O59: =SUMIFS(Journals!$L$9:$L$1007564,Journals!$D$9:$D$1007564,"<"&$F$7,Journals!$J$9:$J$1007564,"realized gain on T-Bond")-SUMIFS(Journals!$K$9:$K$1007564,Journals!$D$9:$D$1007564,"<"&$F$7,Journals!$J$9:$J$1007564,"realized gain on T-Bond") -> -482528.1
G60: Receivable from broker | H60: =MAX(0,SUMIFS(Journals!$K$9:$K$1007564,Journals!$D$9:$D$1007564,">"&$E$7,Journals!$D$9:$D$1007564,"<"&$E$8,Journals!$J$9:$J$1007564,"receivable from broker")-SUMIFS(Journals!$L$9:$L$1007564,Journals!$D$9:$D$1007564,">"&$E$7,Journals!$D$9:$D$1007564,"<"&$E$8,Journals!$J$9:$J$1007564,"receivable from broker")) -> 134104.64 | I60: =MAX(0,SUMIFS(Journals!$L$9:$L$1007564,Journals!$D$9:$D$1007564,">"&$E$7,Journals!$D$9:$D$1007564,"<"&$E$8,Journals!$J$9:$J$1007564,"receivable from broker")-SUMIFS(Journals!$K$9:$K$1007564,Journals!$D$9:$D$1007564,">"&$E$7,Journals!$D$9:$D$1007564,"<"&$E$8,Journals!$J$9:$J$1007564,"receivable from broker")) -> 0 | J60: =SUMIFS(Journals!$K$9:$K$1007564,Journals!$D$9:$D$1007564,"<"&$F$7,Journals!$J$9:$J$1007564,"receivable from broker")-SUMIFS(Journals!$L$9:$L$1007564,Journals!$D$9:$D$1007564,"<"&$F$7,Journals!$J$9:$J$1007564,"receivable from broker") -> 0 | L60: =J60+H60-I60 -> 134104.64
G61: Dividend Equalization Reserve | H61: =MAX(0,SUMIFS(Journals!$K$9:$K$1007564,Journals!$D$9:$D$1007564,">"&$E$7,Journals!$D$9:$D$1007564,"<"&$E$8,Journals!$J$9:$J$1007564,"dividend equalization reserve")) -> 0 | I61: =MAX(0,SUMIFS(Journals!$L$9:$L$1007564,Journals!$D$9:$D$1007564,">"&$E$7,Journals!$D$9:$D$1007564,"<"&$E$8,Journals!$J$9:$J$1007564,"dividend equalization reserve")) -> 0 | K61: =SUMIFS(Journals!$L$9:$L$1007564,Journals!$D$9:$D$1007564,"<"&$F$7,Journals!$J$9:$J$1007564,"Dividend Equalization Reserve")-SUMIFS(Journals!$K$9:$K$1007564,Journals!$D$9:$D$1007564,"<"&$F$7,Journals!$J$9:$J$1007564,"Dividend Equalization Reserve") -> 0 | L61: =H61 -> 0 | M61: =I61 -> 0
G62: Retained Earnings | H62: =MAX(0,SUMIFS(Journals!$K$9:$K$1007564,Journals!$D$9:$D$1007564,">"&$E$7,Journals!$D$9:$D$1007564,"<"&$E$8,Journals!$J$9:$J$1007564,"retained earnings")-SUMIFS(Journals!$L$9:$L$1007564,Journals!$D$9:$D$1007564,">"&$E$7,Journals!$D$9:$D$1007564,"<"&$E$8,Journals!$J$9:$J$1007564,"retained earnings")) -> 0 | I62: =MAX(0,SUMIFS(Journals!$L$9:$L$1007564,Journals!$D$9:$D$1007564,">"&$E$7,Journals!$D$9:$D$1007564,"<"&$E$8,Journals!$J$9:$J$1007564,"retained earnings")-SUMIFS(Journals!$K$9:$K$1007564,Journals!$D$9:$D$1007564,">"&$E$7,Journals!$D$9:$D$1007564,"<"&$E$8,Journals!$J$9:$J$1007564,"retained earnings")) -> 0
G63: Dividend Payable | H63: =MAX(0,SUMIFS(Journals!$K$9:$K$1007564,Journals!$D$9:$D$1007564,">"&$E$7,Journals!$D$9:$D$1007564,"<"&$E$8,Journals!$J$9:$J$1007564,"dividend payable")) -> 0 | I63: =MAX(0,SUMIFS(Journals!$L$9:$L$1007564,Journals!$D$9:$D$1007564,">"&$E$7,Journals!$D$9:$D$1007564,"<"&$E$8,Journals!$J$9:$J$1007564,"dividend payable")) -> 0
G64: Withholding Tax Payable | H64: =MAX(0,SUMIFS(Journals!$K$9:$K$1007564,Journals!$D$9:$D$1007564,">"&$E$7,Journals!$D$9:$D$1007564,"<"&$E$8,Journals!$J$9:$J$1007564,"Withholding Tax Payable")) -> 535456.32 | I64: =MAX(0,SUMIFS(Journals!$L$9:$L$1007564,Journals!$D$9:$D$1007564,">"&$E$7,Journals!$D$9:$D$1007564,"<"&$E$8,Journals!$J$9:$J$1007564,"Withholding Tax Payable")) -> 585347.11 | J64: =SUMIFS(Journals!$K$9:$K$1003833,Journals!$D$9:$D$1003833,"<"&$F$7,Journals!$J$9:$J$1003833,"Withholding Tax Payable")-SUMIFS(Journals!$L$9:$L$1003833,Journals!$D$9:$D$1003833,"<"&$F$7,Journals!$J$9:$J$1003833,"Withholding Tax Payable") -> -53250 | K64: =SUMIFS(Journals!$L$9:$L$1003833,Journals!$D$9:$D$1003833,"<"&$F$7,Journals!$J$9:$J$1003833,"Withholding Tax Payable")-SUMIFS(Journals!$K$9:$K$1003833,Journals!$D$9:$D$1003833,"<"&$F$7,Journals!$J$9:$J$1003833,"Withholding Tax Payable") -> 53250 | M64: =K64+I64-H64 -> 103140.79
G65: Investments in Bond (BXSUKUK) | H65: =MAX(0,SUMIFS(Journals!$K$9:$K$1007564,Journals!$D$9:$D$1007564,">"&$E$7,Journals!$D$9:$D$1007564,"<"&$E$8,Journals!$J$9:$J$1007564,"Investments in Bond (BXSUKUK)")-SUMIFS(Journals!$L$9:$L$1007564,Journals!$D$9:$D$1007564,">"&$E$7,Journals!$D$9:$D$1007564,"<"&$E$8,Journals!$J$9:$J$1007564,"Investments in Bond (BXSUKUK)")) -> 0 | I65: =MAX(0,SUMIFS(Journals!$L$9:$L$1007564,Journals!$D$9:$D$1007564,">"&$E$7,Journals!$D$9:$D$1007564,"<"&$E$8,Journals!$J$9:$J$1007564,"Investments in Bond (BXSUKUK)")-SUMIFS(Journals!$K$9:$K$1007564,Journals!$D$9:$D$1007564,">"&$E$7,Journals!$D$9:$D$1007564,"<"&$E$8,Journals!$J$9:$J$1007564,"Investments in Bond (BXSUKUK)")) -> 3041240 | J65: =SUMIFS(Journals!$K$9:$K$1007564,Journals!$D$9:$D$1007564,"<"&$F$7,Journals!$J$9:$J$1007564,"Investments in Bond (BXSUKUK)")-SUMIFS(Journals!$L$9:$L$1007564,Journals!$D$9:$D$1007564,"<"&$F$7,Journals!$J$9:$J$1007564,"Investments in Bond (BXSUKUK)") -> 3041240 | L65: =J65+H65-I65 -> 0
G66: ='Chart of Accounts'!B59 -> Investments in Bond (APSCL) | H66: =MAX(0,SUMIFS(Journals!$K$9:$K$1007564,Journals!$D$9:$D$1007564,">"&$E$7,Journals!$D$9:$D$1007564,"<"&$E$8,Journals!$J$9:$J$1007564,"Investments in Bond (APSCL)")-SUMIFS(Journals!$L$9:$L$1007564,Journals!$D$9:$D$1007564,">"&$E$7,Journals!$D$9:$D$1007564,"<"&$E$8,Journals!$J$9:$J$1007564,"Investments in Bond (APSCL)")) -> 0 | I66: =MAX(0,SUMIFS(Journals!$L$9:$L$1007564,Journals!$D$9:$D$1007564,">"&$E$7,Journals!$D$9:$D$1007564,"<"&$E$8,Journals!$J$9:$J$1007564,"Investments in Bond (APSCL)")-SUMIFS(Journals!$K$9:$K$1007564,Journals!$D$9:$D$1007564,">"&$E$7,Journals!$D$9:$D$1007564,"<"&$E$8,Journals!$J$9:$J$1007564,"Investments in Bond (APSCL)")) -> 2296386.5 | J66: =SUMIFS(Journals!$K$9:$K$1007564,Journals!$D$9:$D$1007564,"<"&$F$7,Journals!$J$9:$J$1007564,"Investments in Bond (APSCL)")-SUMIFS(Journals!$L$9:$L$1007564,Journals!$D$9:$D$1007564,"<"&$F$7,Journals!$J$9:$J$1007564,"Investments in Bond (APSCL)") -> 5503950 | L66: =J66+H66-I66 -> 3207563.5
G67: Bond Premium | H67: =SUMIFS(Journals!$K$9:$K$1007564,Journals!$D$9:$D$1007564,">"&$E$7,Journals!$D$9:$D$1007564,"<"&$E$8,Journals!$J$9:$J$1007564,"Bond Premium") -> 0 | I67: =MAX(0,SUMIFS(Journals!$L$9:$L$1007564,Journals!$D$9:$D$1007564,">"&$E$7,Journals!$D$9:$D$1007564,"<"&$E$8,Journals!$J$9:$J$1007564,"Bond Premium")) -> 0 | J67: =SUMIFS(Journals!$K$9:$K$1007564,Journals!$D$9:$D$1007564,"<"&$F$7,Journals!$J$9:$J$1007564,"Bond Premium")-SUMIFS(Journals!$L$9:$L$1007564,Journals!$D$9:$D$1007564,"<"&$F$7,Journals!$J$9:$J$1007564,"Bond Premium") -> 0 | L67: =J67+H67-I67 -> 0 | M67: =K67+I67-H67 -> 0
G68: Redemption Receivable | H68: =MAX(0,SUMIFS(Journals!$K$9:$K$1007564,Journals!$D$9:$D$1007564,">"&$E$7,Journals!$D$9:$D$1007564,"<"&$E$8,Journals!$J$9:$J$1007564,"Redemption Receivable")-SUMIFS(Journals!$L$9:$L$1007564,Journals!$D$9:$D$1007564,">"&$E$7,Journals!$D$9:$D$1007564,"<"&$E$8,Journals!$J$9:$J$1007564,"Redemption Receivable")) -> 0 | I68: =MAX(0,SUMIFS(Journals!$L$9:$L$1007564,Journals!$D$9:$D$1007564,">"&$E$7,Journals!$D$9:$D$1007564,"<"&$E$8,Journals!$J$9:$J$1007564,"Redemption Receivable")-SUMIFS(Journals!$K$9:$K$1007564,Journals!$D$9:$D$1007564,">"&$E$7,Journals!$D$9:$D$1007564,"<"&$E$8,Journals!$J$9:$J$1007564,"Redemption Receivable")) -> 0 | J68: =SUMIFS(Journals!$K$9:$K$1007564,Journals!$D$9:$D$1007564,"<"&$F$7,Journals!$J$9:$J$1007564,"Redemption Receivable")-SUMIFS(Journals!$L$9:$L$1007564,Journals!$D$9:$D$1007564,"<"&$F$7,Journals!$J$9:$J$1007564,"Redemption Receivable") -> 0 | L68: =J68+H68-I68 -> 0
G69: Redemption of Investment | H69: =MAX(0,SUMIFS(Journals!$K$9:$K$1007564,Journals!$D$9:$D$1007564,">"&$E$7,Journals!$D$9:$D$1007564,"<"&$E$8,Journals!$J$9:$J$1007564,"Redemption of Investment")-SUMIFS(Journals!$L$9:$L$1007564,Journals!$D$9:$D$1007564,">"&$E$7,Journals!$D$9:$D$1007564,"<"&$E$8,Journals!$J$9:$J$1007564,"Redemption of Investment")) -> 0 | I69: =MAX(0,SUMIFS(Journals!$L$9:$L$1007564,Journals!$D$9:$D$1007564,">"&$E$7,Journals!$D$9:$D$1007564,"<"&$E$8,Journals!$J$9:$J$1007564,"Redemption of Investment")-SUMIFS(Journals!$K$9:$K$1007564,Journals!$D$9:$D$1007564,">"&$E$7,Journals!$D$9:$D$1007564,"<"&$E$8,Journals!$J$9:$J$1007564,"Redemption of Investment")) -> 0
G70: Investments in T-Bond (Contract) | H70: =MAX(0,SUMIFS(Journals!$K$9:$K$1007564,Journals!$D$9:$D$1007564,">"&$E$7,Journals!$D$9:$D$1007564,"<"&$E$8,Journals!$J$9:$J$1007564,"Investments in T-Bond (Contract)")-SUMIFS(Journals!$L$9:$L$1007564,Journals!$D$9:$D$1007564,">"&$E$7,Journals!$D$9:$D$1007564,"<"&$E$8,Journals!$J$9:$J$1007564,"Investments in T-Bond (Contract)")) -> 0 | I70: =MAX(0,SUMIFS(Journals!$L$9:$L$1007564,Journals!$D$9:$D$1007564,">"&$E$7,Journals!$D$9:$D$1007564,"<"&$E$8,Journals!$J$9:$J$1007564,"Investments in T-Bond (Contract)")-SUMIFS(Journals!$K$9:$K$1007564,Journals!$D$9:$D$1007564,">"&$E$7,Journals!$D$9:$D$1007564,"<"&$E$8,Journals!$J$9:$J$1007564,"Investments in T-Bond (Contract)")) -> 0 | J70: =SUMIFS(Journals!$K$9:$K$1007564,Journals!$D$9:$D$1007564,"<"&$F$7,Journals!$J$9:$J$1007564,"Investments in T-Bond (Contract)")-SUMIFS(Journals!$L$9:$L$1007564,Journals!$D$9:$D$1007564,"<"&$F$7,Journals!$J$9:$J$1007564,"Investments in T-Bond (Contract)") -> 0 | L70: =J70+H70-I70 -> 0
G71: Interest Receivables from T.Bond (Contract) | H71: =MAX(0,SUMIFS(Journals!$K$9:$K$1007564,Journals!$D$9:$D$1007564,">"&$E$7,Journals!$D$9:$D$1007564,"<"&$E$8,Journals!$J$9:$J$1007564,"Interest Receivables from T.Bond (Contract)")-SUMIFS(Journals!$L$9:$L$1007564,Journals!$D$9:$D$1007564,">"&$E$7,Journals!$D$9:$D$1007564,"<"&$E$8,Journals!$J$9:$J$1007564,"Interest Receivables from T.Bond (Contract)")) -> 0 | I71: =MAX(0,SUMIFS(Journals!$L$9:$L$1007564,Journals!$D$9:$D$1007564,">"&$E$7,Journals!$D$9:$D$1007564,"<"&$E$8,Journals!$J$9:$J$1007564,"Interest Receivables from T.Bond (Contract)")-SUMIFS(Journals!$K$9:$K$1007564,Journals!$D$9:$D$1007564,">"&$E$7,Journals!$D$9:$D$1007564,"<"&$E$8,Journals!$J$9:$J$1007564,"Interest Receivables from T.Bond (Contract)")) -> 0 | J71: =SUMIFS(Journals!$K$9:$K$1007564,Journals!$D$9:$D$1007564,"<"&$F$7,Journals!$J$9:$J$1007564,"Interest Receivables from T.Bond (Contract)")-SUMIFS(Journals!$L$9:$L$1007564,Journals!$D$9:$D$1007564,"<"&$F$7,Journals!$J$9:$J$1007564,"Interest Receivables from T.Bond (Contract)") -> 0.0099999986 | L71: =J71+H71-I71 -> 0.0099999986
G72: Preliminary and issue expense (Liability) | H72: =MAX(0,SUMIFS(Journals!$K$9:$K$1007306,Journals!$D$9:$D$1007306,">"&$E$7,Journals!$D$9:$D$1007306,"<"&$E$8,Journals!$J$9:$J$1007306,"Preliminary and issue expense (Liability)")) -> 942012.2 | I72: =MAX(0,SUMIFS(Journals!$L$9:$L$1007306,Journals!$D$9:$D$1007306,">"&$E$7,Journals!$D$9:$D$1007306,"<"&$E$8,Journals!$J$9:$J$1007306,"Preliminary and issue expense (Liability)")) -> 0 | J72: =MAX(0,SUMIFS(Journals!K30:K1007515,Journals!D30:D1007515,"<"&F40,Journals!J30:J1007515,"Preliminary and issue expense (Liability)")-SUMIFS(Journals!L30:L1007515,Journals!D30:D1007515,"<"&F40,Journals!J30:J1007515,"Preliminary and issue expense (Liability)")) -> 0 | K72: =SUMIFS(Journals!$L$9:$L$1007494,Journals!$D$9:$D$1007494,"<"&$F$7,Journals!$J$9:$J$1007494,"Preliminary and issue expense (Liability)")-SUMIFS(Journals!$K$9:$K$1007494,Journals!$D$9:$D$1007494,"<"&$F$7,Journals!$J$9:$J$1007494,"Preliminary and issue expense (Liability)") -> 942012.2 | M72: =K72+I72-H72 -> 0
G73: Investments in T-Bill | H73: =MAX(0,SUMIFS(Journals!$K$9:$K$1007564,Journals!$D$9:$D$1007564,">"&$E$7,Journals!$D$9:$D$1007564,"<"&$E$8,Journals!$J$9:$J$1007564,"Investments in T-Bill")-SUMIFS(Journals!$L$9:$L$1007564,Journals!$D$9:$D$1007564,">"&$E$7,Journals!$D$9:$D$1007564,"<"&$E$8,Journals!$J$9:$J$1007564,"Investments in T-Bill")) -> 0 | I73: =MAX(0,SUMIFS(Journals!$L$9:$L$1003833,Journals!$D$9:$D$1003833,">"&$E$7,Journals!$D$9:$D$1003833,"<"&$E$8,Journals!$J$9:$J$1003833,"Interest Receivables from T-Bill")-SUMIFS(Journals!$K$9:$K$1003833,Journals!$D$9:$D$1003833,">"&$E$7,Journals!$D$9:$D$1003833,"<"&$E$8,Journals!$J$9:$J$1003833,"Interest Receivables from T-Bill")) -> 0 | L73: =J73+H73-I73 -> 0
G74: Interest Receivables from T-Bill | H74: =MAX(0,SUMIFS(Journals!$K$9:$K$1007564,Journals!$D$9:$D$1007564,">"&$E$7,Journals!$D$9:$D$1007564,"<"&$E$8,Journals!$J$9:$J$1007564,"Interest Receivables from T-Bill")-SUMIFS(Journals!$L$9:$L$1007564,Journals!$D$9:$D$1007564,">"&$E$7,Journals!$D$9:$D$1007564,"<"&$E$8,Journals!$J$9:$J$1007564,"Interest Receivables from T-Bill")) -> 0 | I74: =MAX(0,SUMIFS(Journals!$L$9:$L$1007564,Journals!$D$9:$D$1007564,">"&$E$7,Journals!$D$9:$D$1007564,"<"&$E$8,Journals!$J$9:$J$1007564,"Interest Receivables from T-Bill")-SUMIFS(Journals!$K$9:$K$1007564,Journals!$D$9:$D$1007564,">"&$E$7,Journals!$D$9:$D$1007564,"<"&$E$8,Journals!$J$9:$J$1007564,"Interest Receivables from T-Bill")) -> 0 | L74: =J74+H74-I74 -> 0
G75: Investments in T-Bond | H75: =MAX(0,SUMIFS(Journals!$K$9:$K$1007564,Journals!$D$9:$D$1007564,">"&$E$7,Journals!$D$9:$D$1007564,"<"&$E$8,Journals!$J$9:$J$1007564,"Investments in T-Bond")-SUMIFS(Journals!$L$9:$L$1007564,Journals!$D$9:$D$1007564,">"&$E$7,Journals!$D$9:$D$1007564,"<"&$E$8,Journals!$J$9:$J$1007564,"Investments in T-Bond")) -> 2.8079838e+08 | I75: =MAX(0,SUMIFS(Journals!$L$9:$L$1007564,Journals!$D$9:$D$1007564,">"&$E$7,Journals!$D$9:$D$1007564,"<"&$E$8,Journals!$J$9:$J$1007564,"Investments in T-Bond")-SUMIFS(Journals!$K$9:$K$1007564,Journals!$D$9:$D$1007564,">"&$E$7,Journals!$D$9:$D$1007564,"<"&$E$8,Journals!$J$9:$J$1007564,"Investments in T-Bond")) -> 0 | J75: =SUMIFS(Journals!$K$9:$K$1003833,Journals!$D$9:$D$1003833,"<"&$F$7,Journals!$J$9:$J$1003833,"Investments in T-Bond")-SUMIFS(Journals!$L$9:$L$1003833,Journals!$D$9:$D$1003833,"<"&$F$7,Journals!$J$9:$J$1003833,"Investments in T-Bond") -> 84476195 | L75: =J75+H75-I75 -> 3.6527458e+08
G76: Interest Receivables from T-Bond | H76: =MAX(0,SUMIFS(Journals!$K$9:$K$1003763,Journals!$D$9:$D$1003763,">"&$E$7,Journals!$D$9:$D$1003763,"<"&$E$8,Journals!$J$9:$J$1003763,"Interest Receivables from T-Bond")-SUMIFS(Journals!$L$9:$L$1003763,Journals!$D$9:$D$1003763,">"&$E$7,Journals!$D$9:$D$1003763,"<"&$E$8,Journals!$J$9:$J$1003763,"Interest Receivables from T-Bond")) -> 0 | I76: =MAX(0,SUMIFS(Journals!$L$9:$L$1003833,Journals!$D$9:$D$1003833,">"&$E$7,Journals!$D$9:$D$1003833,"<"&$E$8,Journals!$J$9:$J$1003833,"Interest Receivables from T-Bond")-SUMIFS(Journals!$K$9:$K$1003833,Journals!$D$9:$D$1003833,">"&$E$7,Journals!$D$9:$D$1003833,"<"&$E$8,Journals!$J$9:$J$1003833,"Interest Receivables from T-Bond")) -> 0 | L76: =J76+H76-I76 -> 0
G77: Investments in BRAC Bank 2nd Subordinated Bond | H77: =MAX(0,SUMIFS(Journals!$K$9:$K$1007564,Journals!$D$9:$D$1007564,">"&$E$7,Journals!$D$9:$D$1007564,"<"&$E$8,Journals!$J$9:$J$1007564,"Investments in BRAC Bank 2nd Subordinated Bond")-SUMIFS(Journals!$L$9:$L$1007564,Journals!$D$9:$D$1007564,">"&$E$7,Journals!$D$9:$D$1007564,"<"&$E$8,Journals!$J$9:$J$1007564,"Investments in BRAC Bank 2nd Subordinated Bond")) -> 59000000 | I77: =MAX(0,SUMIFS(Journals!$L$9:$L$1007564,Journals!$D$9:$D$1007564,">"&$E$7,Journals!$D$9:$D$1007564,"<"&$E$8,Journals!$J$9:$J$1007564,"Investments in BRAC Bank 2nd Subordinated Bond")-SUMIFS(Journals!$K$9:$K$1007564,Journals!$D$9:$D$1007564,">"&$E$7,Journals!$D$9:$D$1007564,"<"&$E$8,Journals!$J$9:$J$1007564,"Investments in BRAC Bank 2nd Subordinated Bond")) -> 0 | J77: =SUMIFS(Journals!$K$9:$K$1007564,Journals!$D$9:$D$1007564,"<"&$F$7,Journals!$J$9:$J$1007564,"Investments in BRAC Bank 2nd Subordinated Bond")-SUMIFS(Journals!$L$9:$L$1007564,Journals!$D$9:$D$1007564,"<"&$F$7,Journals!$J$9:$J$1007564,"Investments in BRAC Bank 2nd Subordinated Bond") -> 0 | L77: =J77+H77-I77 -> 59000000
G78: Interest Receivables from BRAC Bank Bond | H78: =MAX(0,SUMIFS(Journals!$K$9:$K$1007564,Journals!$D$9:$D$1007564,">"&$E$7,Journals!$D$9:$D$1007564,"<"&$E$8,Journals!$J$9:$J$1007564,"Interest Receivables from BRAC Bank Bond")-SUMIFS(Journals!$L$9:$L$1007564,Journals!$D$9:$D$1007564,">"&$E$7,Journals!$D$9:$D$1007564,"<"&$E$8,Journals!$J$9:$J$1007564,"Interest Receivables from BRAC Bank Bond")) -> 2800879.1 | I78: =MAX(0,SUMIFS(Journals!$L$9:$L$1007564,Journals!$D$9:$D$1007564,">"&$E$7,Journals!$D$9:$D$1007564,"<"&$E$8,Journals!$J$9:$J$1007564,"Interest Receivables from BRAC Bank Bond")-SUMIFS(Journals!$K$9:$K$1007564,Journals!$D$9:$D$1007564,">"&$E$7,Journals!$D$9:$D$1007564,"<"&$E$8,Journals!$J$9:$J$1007564,"Interest Receivables from BRAC Bank Bond")) -> 0 | J78: =SUMIFS(Journals!$K$9:$K$1007564,Journals!$D$9:$D$1007564,"<"&$F$7,Journals!$J$9:$J$1007564,"Interest Receivables from BRAC Bank Bond")-SUMIFS(Journals!$L$9:$L$1007564,Journals!$D$9:$D$1007564,"<"&$F$7,Journals!$J$9:$J$1007564,"Interest Receivables from BRAC Bank Bond") -> 0 | L78: =J78+H78-I78 -> 2800879.1
G79: Investments in Bank Asia 4th Subordinated Bond | H79: =MAX(0,SUMIFS(Journals!$K$9:$K$1007564,Journals!$D$9:$D$1007564,">"&$E$7,Journals!$D$9:$D$1007564,"<"&$E$8,Journals!$J$9:$J$1007564,"Investments in Bank Asia 4th Subordinated Bond")-SUMIFS(Journals!$L$9:$L$1007564,Journals!$D$9:$D$1007564,">"&$E$7,Journals!$D$9:$D$1007564,"<"&$E$8,Journals!$J$9:$J$1007564,"Investments in Bank Asia 4th Subordinated Bond")) -> 40000000 | I79: =MAX(0,SUMIFS(Journals!$L$9:$L$1007564,Journals!$D$9:$D$1007564,">"&$E$7,Journals!$D$9:$D$1007564,"<"&$E$8,Journals!$J$9:$J$1007564,"Investments in Bank Asia 4th Subordinated Bond")-SUMIFS(Journals!$K$9:$K$1007564,Journals!$D$9:$D$1007564,">"&$E$7,Journals!$D$9:$D$1007564,"<"&$E$8,Journals!$J$9:$J$1007564,"Investments in Bank Asia 4th Subordinated Bond")) -> 0 | J79: =SUMIFS(Journals!$K$9:$K$1007564,Journals!$D$9:$D$1007564,"<"&$F$7,Journals!$J$9:$J$1007564,"Investments in Bank Asia 4th Subordinated Bond")-SUMIFS(Journals!$L$9:$L$1007564,Journals!$D$9:$D$1007564,"<"&$F$7,Journals!$J$9:$J$1007564,"Investments in Bank Asia 4th Subordinated Bond") -> 0 | L79: =J79+H79-I79 -> 40000000
G80: Interest Receivables from Bank Asia Bond | H80: =MAX(0,SUMIFS(Journals!$K$9:$K$1007564,Journals!$D$9:$D$1007564,">"&$E$7,Journals!$D$9:$D$1007564,"<"&$E$8,Journals!$J$9:$J$1007564,"Interest Receivables from Bank Asia Bond")-SUMIFS(Journals!$L$9:$L$1007564,Journals!$D$9:$D$1007564,">"&$E$7,Journals!$D$9:$D$1007564,"<"&$E$8,Journals!$J$9:$J$1007564,"Interest Receivables from Bank Asia Bond")) -> 873164.87 | I80: =MAX(0,SUMIFS(Journals!$L$9:$L$1007564,Journals!$D$9:$D$1007564,">"&$E$7,Journals!$D$9:$D$1007564,"<"&$E$8,Journals!$J$9:$J$1007564,"Interest Receivables from Bank Asia Bond")-SUMIFS(Journals!$K$9:$K$1007564,Journals!$D$9:$D$1007564,">"&$E$7,Journals!$D$9:$D$1007564,"<"&$E$8,Journals!$J$9:$J$1007564,"Interest Receivables from Bank Asia Bond")) -> 0 | J80: =SUMIFS(Journals!$K$9:$K$1007564,Journals!$D$9:$D$1007564,"<"&$F$7,Journals!$J$9:$J$1007564,"Interest Receivables from Bank Asia Bond")-SUMIFS(Journals!$L$9:$L$1007564,Journals!$D$9:$D$1007564,"<"&$F$7,Journals!$J$9:$J$1007564,"Interest Receivables from Bank Asia Bond") -> 0 | L80: =J80+H80-I80 -> 873164.87
G81: Investments in Dhaka Bank 4th Subordinated Bond | H81: =MAX(0,SUMIFS(Journals!$K$9:$K$1003833,Journals!$D$9:$D$1003833,">"&$E$7,Journals!$D$9:$D$1003833,"<"&$E$8,Journals!$J$9:$J$1003833,"Investments in Dhaka Bank 4th Subordinated Bond")-SUMIFS(Journals!$L$9:$L$1003833,Journals!$D$9:$D$1003833,">"&$E$7,Journals!$D$9:$D$1003833,"<"&$E$8,Journals!$J$9:$J$1003833,"Investments in Dhaka Bank 4th Subordinated Bond")) -> 0 | I81: =MAX(0,SUMIFS(Journals!$L$9:$L$1003833,Journals!$D$9:$D$1003833,">"&$E$7,Journals!$D$9:$D$1003833,"<"&$E$8,Journals!$J$9:$J$1003833,"Investments in Dhaka Bank 4th Subordinated Bond")-SUMIFS(Journals!$K$9:$K$1003833,Journals!$D$9:$D$1003833,">"&$E$7,Journals!$D$9:$D$1003833,"<"&$E$8,Journals!$J$9:$J$1003833,"Investments in Dhaka Bank 4th Subordinated Bond")) -> 0 | J81: =SUMIFS(Journals!$K$9:$K$1003833,Journals!$D$9:$D$1003833,"<"&$F$7,Journals!$J$9:$J$1003833,"Investments in Dhaka Bank 4th Subordinated Bond")-SUMIFS(Journals!$L$9:$L$1003833,Journals!$D$9:$D$1003833,"<"&$F$7,Journals!$J$9:$J$1003833,"Investments in Dhaka Bank 4th Subordinated Bond") -> 0 | L81: =J81+H81-I81 -> 0
G82: Interest Receivables from Dhaka Bank 4th Subordinated Bond | H82: =MAX(0,SUMIFS(Journals!$K$9:$K$1007564,Journals!$D$9:$D$1007564,">"&$E$7,Journals!$D$9:$D$1007564,"<"&$E$8,Journals!$J$9:$J$1007564,"Interest Receivables from Dhaka Bank 4th Subordinated Bond")-SUMIFS(Journals!$L$9:$L$1007564,Journals!$D$9:$D$1007564,">"&$E$7,Journals!$D$9:$D$1007564,"<"&$E$8,Journals!$J$9:$J$1007564,"Interest Receivables from Dhaka Bank 4th Subordinated Bond")) -> 0 | I82: =MAX(0,SUMIFS(Journals!$L$9:$L$1007564,Journals!$D$9:$D$1007564,">"&$E$7,Journals!$D$9:$D$1007564,"<"&$E$8,Journals!$J$9:$J$1007564,"Interest Receivables from Dhaka Bank 4th Subordinated Bond")-SUMIFS(Journals!$K$9:$K$1007564,Journals!$D$9:$D$1007564,">"&$E$7,Journals!$D$9:$D$1007564,"<"&$E$8,Journals!$J$9:$J$1007564,"Interest Receivables from Dhaka Bank 4th Subordinated Bond")) -> 0 | J82: =SUMIFS(Journals!$K$9:$K$1007564,Journals!$D$9:$D$1007564,"<"&$F$7,Journals!$J$9:$J$1007564,"Interest Receivables from Dhaka Bank 4th Subordinated Bond")-SUMIFS(Journals!$L$9:$L$1007564,Journals!$D$9:$D$1007564,"<"&$F$7,Journals!$J$9:$J$1007564,"Interest Receivables from Dhaka Bank 4th Subordinated Bond") -> 0 | L82: =J82+H82-I82 -> 0

Sheet BS
A2: EKUSH STABLE RETURN FUND
A3: STATEMENT OF FINANCIAL POSITION | H3: Fair value of Securities | I3: 35319588 | J3: =TODAY() -> 46110
A4: As on December 29, 2024 | I4: 0
H5: Fair value of T-Bond | I5: 3.3744797e+08
A6: Particulars | B6: Notes | C6: ='TB-C'!F8 -> 46202 | E6: ='TB-P'!F8 -> 45838
C7: Taka | E7: Taka | I7: =ABS(I9) -> 0
A8: Assets | H8: UG/(UL) | I8: FVA | J8: NAV*
A9: Investment at cost price | C9: ='TB-C'!$L$7+'TB-C'!L65+'TB-C'!L66 -> 34762894 | E9: ='TB-P'!$L$7+'TB-P'!L65+'TB-P'!L66 -> 6005214.1 | H9: =I3-C9 -> 556694.37 | I9: =H9-C10 -> 0 | J9: =C35+I9+I13+I16 -> 5.8770048e+08
A10: fair value adjustment | C10: =IF('TB-C'!$L$45>0,'TB-C'!$L$45,-'TB-C'!$M$45) -> 556694.37 | E10: =IF('TB-P'!$L$45>0,'TB-P'!$L$45,-'TB-P'!$M$45) -> 160630.88 | H10: =J9/C51 -> 14.267139
A11: Investment in Securities at Market Price | B11: 1 | C11: =C9+C10 -> 35319588 | D11: =D9+D10 -> 0 | E11: =E9+E10 -> 6165845 | H11: T-Bill | I11: =ABS(I13) -> 5.9604645e-08
A12: Investment at cost price T-Bill | C12: ='TB-C'!L73 -> 0.20000005 | E12: ='TB-P'!L73 -> 0 | H12: UG/(UL) | I12: FVA
A13: fair value adjustment T-Bill | C13: =IF('TB-C'!$L$46>0,'TB-C'!$L$46,-'TB-C'!$M$46) -> -0.19999999 | E13: =IF('TB-P'!$L$46>0,'TB-P'!$L$46,-'TB-P'!$M$46) -> -0.19999999 | H13: =I4-C12 -> -0.20000005 | I13: =H13-C13 -> -5.9604645e-08
A14: Investments in T-Bill | B14: 1 | C14: =C13+C12 -> 5.9604645e-08 | E14: =E13+E12 -> -0.19999999 | H14: T-Bond | I14: =ABS(I16) -> 0
A15: Investment at cost price T-Bond | C15: ='TB-C'!L75+'TB-C'!L70 -> 3.0802549e+08 | E15: ='TB-P'!L75+'TB-P'!L70 -> 3.6527458e+08 | H15: UG/(UL) | I15: FVA
A16: fair value adjustment T-Bond | C16: =IF('TB-C'!$L$47>0,'TB-C'!$L$47,-'TB-C'!$M$47) -> 29422475 | E16: =IF('TB-P'!$L$47>0,'TB-P'!$L$47,-'TB-P'!$M$47) -> 4692855.2 | H16: =I5-C15 -> 29422475 | I16: =H16-C16 -> 0
A17: Investments in T-Bond | B17: 1 | C17: =C16+C15 -> 3.3744797e+08 | E17: =E16+E15 -> 3.6996743e+08
A18: Investments in Corporate Bond | B18: 1 | C18: ='TB-C'!L77+'TB-C'!L79+'TB-C'!L81 -> 124000000 | E18: ='TB-P'!L77+'TB-P'!L79+'TB-P'!L81 -> 99000000
A19: Fixed Deposit Receipts (FDR) | B19: 2 | C19: ='TB-C'!$L$18 -> 54000000 | E19: ='TB-P'!$L$18 -> 85000000
A20: IPO Application | B20: 3 | C20: ='TB-C'!$L$54 -> 0 | E20: ='TB-P'!$L$54 -> 0 | G20: Midland | H20: 0001-1090001017 | I20: 5972545.4 | J20: =SUM(I20:I27) -> 31458525
A21: Accounts Receivable | B21: 3 | C21: ='TB-C'!$L$48+'TB-C'!$L$52+'TB-C'!$L$60+'TB-C'!L8+'TB-C'!L10+'TB-C'!L68+'TB-C'!L71+'TB-C'!L9+'TB-C'!L76+'TB-C'!L78+'TB-C'!L80+'TB-C'!L82 -> 5585320.4 | E21: ='TB-P'!$L$48+'TB-P'!$L$52+'TB-P'!$L$60+'TB-P'!L8+'TB-P'!L10+'TB-P'!L68+'TB-P'!L71+'TB-P'!L9+'TB-P'!L76+'TB-P'!L78+'TB-P'!L80+'TB-P'!L82 -> 5231878.8 | H21: 0001-1060000146 | I21: 1692096.1 | J21: =J20-C23 -> 0
A22: Advance, deposit & prepayments | C22: ='TB-C'!L41 -> 138836.11 | E22: 0 | G22: Brac | H22: 2055-604070001 | I22: =23650677.9-8000 -> 23642678
A23: Cash & Cash equivalent | B23: 4 | C23: ='TB-C'!$L$19 -> 31458525 | E23: ='TB-P'!$L$19 -> 15519657 | G23: Modhumoti | H23: 1135-12700000001 | I23: 40037.12
A24: Preliminary & Issue Expenses | B24: 5 | C24: ='TB-C'!L11 -> 421015.48 | E24: ='TB-P'!$L$11 -> 559729.36 | H24: 1101-11100001029 | I24: 0
A25: Total Assets | C25: =SUM(C17:C24)+C14+C11 -> 5.8837125e+08 | E25: =SUM(E17:E24)+E14+E11 -> 5.8144454e+08 | G25: SBAC | H25: 2130-001440 | I25: 2715.57
G26: MTB | H26: 1310-000147462 | I26: 42593.7
A27: Equity & Liabilities | G27: NRB | H27: 1012-050203836 | I27: 65858.88
A28: Unitholders' Equity
A29: Unitholders' Equity
A30: Unit Capital | B30: 6 | C30: ='TB-C'!$M$20 -> 411925950 | E30: ='TB-P'!$M$20 -> 462377570
A31: Unit Premium | B31: 7 | C31: ='TB-C'!$M$21 -> 23036942 | E31: ='TB-P'!$M$21 -> 41293538
A32: Dividend Equalization Reserve | C32: =E!E16 -> 0 | E32: =E!E31 -> 0
A33: Other Comprehensive Income | B33: 8 | C33: =E!F16 -> 31164251 | E33: =E!F31 -> 6038566.8
A34: Retained Earnings | C34: =E!$D$16 -> 1.2157334e+08 | E34: =E!D31 -> 71166097
A35: Total Equity | C35: =SUM(C30:C34) -> 5.8770048e+08 | D35: =SUM(D30:D34) -> 0 | E35: =SUM(E30:E34) -> 5.8087577e+08
A36: Current Liabilities
A37: Accounts Payable | C37: ='TB-C'!M64+'TB-C'!M49 -> 100540.28 | E37: ='TB-P'!M64+'TB-P'!M49 -> 103140.79
A38: Dividend Payable | C38: 0 | E38: ='TB-P'!M63 -> 0
A39: Liability for expenses | B39: 9 | C39: =SUM('TB-C'!$M$12:$M$17)+'TB-C'!K71 -> 570233.89 | E39: =SUM('TB-P'!$M$12:$M$17)+'TB-P'!M72 -> 465631.49
A40: Total Liabilities | C40: =SUM(C37:C39) -> 670774.17 | D40: =SUM(D37) -> 0 | E40: =SUM(E37:E39) -> 568772.28
A42: Total Equity and Liabilities | C42: =SUM(C35,C40) -> 5.8837125e+08 | D42: =D35+D40 -> 0 | E42: =E35+E40 -> 5.8144454e+08
A44: Net Asset Value (NAV) | C44: =C35 -> 5.8770048e+08 | E44: =E35 -> 5.8087577e+08
A46: Net Asset Value (NAV) per unit: | C46: =C44/C51 -> 14.267139 | E46: =E35/E51 -> 12.562802
A47: At Cost | B47: 10 | C47: =(C35-C10-C13-C16)/C51 -> 13.539358 | E47: =(E35-E10-E13-E16)/E51 -> 12.457834
A48: At Market Price | B48: 11 | C48: =(C35)/(C51) -> 14.267139 | E48: =(E35)/(E51) -> 12.562802
A50: These financial statement should be read in conjunction with annexed notes.
A51: No of Units Outstanding | C51: =ROUND(C30/10,0) -> 41192595 | E51: =E!B31/10 -> 46237757
A56: Head of Compliance | C56: Managing Director
A57: Ekush Wealth Management Limited | C57: Ekush Wealth Management Limited
A62: Trustee
A63: Shandhani Life Insurance Company Limited

Sheet IS
A1: EKUSH STABLE RETURN FUND
A2: STATEMENT OF PROFIT & LOSS AND OTHER COMPREHENSIVE INCOME
A3: For the period of July 1 to December 31, 2024
A5: Particulars | B5: Notes | C5: ='TB-C'!F8 -> 46202 | E5: ='TB-P'!F8 -> 45838
C6: Taka | E6: Taka
A8: INCOME
A9: Interest income | B9: 12 | C9: =SUM('TB-C'!I22:I30)-SUM('TB-C'!H22:H30) -> 41796429 | E9: =SUM('TB-P'!I22:I30)-SUM('TB-P'!H22:H30) -> 47694348
A10: Net gain on sale of marketable securities | B10: 13 | C10: =IF('TB-C'!I56>0,'TB-C'!I56,-'TB-C'!H56)+IF('TB-C'!I57>0,'TB-C'!I57-'TB-C'!H57) -> 4382688.7 | E10: =IF('TB-P'!I56>0,'TB-P'!I56,-'TB-P'!H56)+IF('TB-P'!I57>0,'TB-P'!I520-'TB-P'!H57) -> -565912.5
A11: Net gain on sale of T-Bill | B11: 14 | C11: =IF('TB-C'!I58>0,'TB-C'!I58,-'TB-C'!H58) -> 0 | E11: =IF('TB-P'!I58>0,'TB-P'!I58,-'TB-P'!H58) -> 5614592.5
A12: Net gain on sale of T-Bond | B12: 15 | C12: =IF('TB-C'!I59>0,'TB-C'!I59,-'TB-C'!H59) -> 7438790 | E12: =IF('TB-P'!I59>0,'TB-P'!I59,-'TB-P'!H59) -> 4592616.9
A13: Dividend income | B13: 16 | C13: ='TB-C'!$I$51 -> 201382.5 | E13: ='TB-P'!$I$51 -> 0
A14: Total Income | C14: =SUM(C9:C13) -> 53819290 | D14: =SUM(D9:D13) -> 0 | E14: =SUM(E9:E13) -> 57335645
A16: EXPENSES
A17: Management fees | C17: ='TB-C'!$H$39 -> 2130135.1 | E17: ='TB-P'!$H$39 -> 2325669.4
A18: BSEC annual fees | C18: ='TB-C'!$H$42 -> 442041.41 | E18: ='TB-P'!$H$42 -> 355635.5
A19: Amortization of preliminary & issue expenses | C19: ='TB-C'!$H$38 -> 138713.88 | E19: ='TB-P'!$H$38 -> 184261.73
A20: CDBL settlement & demat charges | C20: 0 | E20: 0
A21: CDBL charges | C21: ='TB-C'!$H$44 -> 96969 | E21: ='TB-P'!$H$44 -> 1903.25
A22: Trustee fees | C22: ='TB-C'!$H$40 -> 213013.5 | E22: ='TB-P'!$H$40 -> 233022.32
A23: Custodian fees | C23: ='TB-C'!$H$53 -> 220439.89 | E23: ='TB-P'!$H$53 -> 313675.02
A24: IPO application fees | C24: ='TB-C'!$H$55 -> 0 | E24: ='TB-P'!$H$55 -> 0
A25: Brokerage commission | C25: ='TB-C'!$H$33 -> 3714.73 | E25: ='TB-P'!$H$33 -> 16190.198
A26: Audit fees | C26: ='TB-C'!$H$43 -> 0 | E26: ='TB-P'!$H$43 -> 35000
A27: Bank charge & excise duty | C27: =IF('TB-C'!H32>0,'TB-C'!H32,-'TB-C'!I32) -> 167021.48 | E27: ='TB-P'!$H$32 -> 197576.65
A28: Newspaper publication expense | C28: 0 | E28: 0
A29: Other operating expense | C29: ='TB-C'!$H$50 -> 0 | E29: ='TB-P'!$H$50 -> 0
A30: Total Expenses | C30: =SUM(C17:C29) -> 3412049 | D30: =SUM(D17:D29) -> 0 | E30: =SUM(E17:E29) -> 3662934.1
A31: Profit Before Provision | C31: =C14-C30 -> 50407241 | E31: =E14-E30 -> 53672711
A32: Provision Against Diminution in Value of Investment | B32: 17 | C32: =-IF('TB-C'!$I$45>0,'TB-C'!$I$45,0)-IF('TB-C'!$I$46>0,'TB-C'!$I$46,0)-IF('TB-C'!$I$47>0,'TB-C'!$I$47,0) -> 0 | E32: =-IF('TB-P'!$I$45>0,'TB-P'!$I$45,0)-IF('TB-P'!$I$46>0,'TB-P'!$I$46,0)-IF('TB-P'!$I$47>0,'TB-P'!$I$47,0) -> -1185081
A33: Net Profit For the Period | C33: =C31+C32 -> 50407241 | E33: =E31+E32 -> 52487630
A36: Earnings Per Unit | B36: 18 | C36: =C33/C39 -> 1.2236967 | E36: =E33/E39 -> 1.1351682
A38: These financial statement should be read in conjunction with annexed notes.
A39: No of Units Outstanding | C39: =BS!C51 -> 41192595 | E39: =BS!E51 -> 46237757
A44: Head of Compliance | C44: Managing Director
A45: Ekush Wealth Management Limited | C45: Ekush Wealth Management Limited
A50: Trustee
A51: Shandhani Life Insurance Company Limited

Sheet E
A1: EKUSH STABLE RETURN FUND
A2: STATEMENT OF CHANGES IN EQUITY
A3: For the period from July 1 to December 31, 2024
A6: Particulars | B6: Unit Capital | C6: Unit Premium Reserve | D6: Retained Earnings | E6: Dividend Equalization Reserve | F6: Other Comprehensive Income | G6: Total Equity
A8: Opening balance | B8: ='TB-C'!$K$20 -> 462377570 | C8: ='TB-C'!K21 -> 41293538 | D8: =D31 -> 71166097 | E8: 0 | F8: =F31 -> 6038566.8 | G8: =SUM(B8:F8) -> 5.8087577e+08
A9: Unit capital raised during the period | B9: ='TB-C'!I20 -> 212650510 | C9: ='TB-C'!I21 -> 70419620 | D9: 0 | E9: 0 | F9: 0 | G9: =SUM(B9:E9) -> 2.8307013e+08
A10: Unit surrendered | B10: =-'TB-C'!H20 -> -263102130 | C10: =-'TB-C'!H21 -> -88676215 | D10: 0 | E10: 0 | F10: 0 | G10: =SUM(B10:E10) -> -3.5177835e+08
A11: Dividend equalization reserve | B11: 0 | C11: 0 | D11: =-'TB-C'!I61 -> 0 | E11: ='TB-C'!I61 -> 0 | F11: 0 | G11: =SUM(B11:E11) -> 0
A12: Dividend payable | B12: 0 | C12: 0 | D12: =-'TB-C'!M63 -> 0 | E12: 0 | F12: 0 | G12: =SUM(B12:F12) -> 0
A13: Dividend paid during the year | B13: 0 | C13: 0 | D13: =-'TB-C'!H63 -> 0 | E13: 0 | F13: 0 | G13: =SUM(B13:F13) -> 0
A14: Other comprehensive inome | B14: 0 | C14: 0 | D14: 0 | E14: 0 | F14: =IF('TB-C'!H45>0,'TB-C'!$H$45,0)+IF('TB-C'!H46>0,'TB-C'!$H$46,0)+IF('TB-C'!H47>0,'TB-C'!$H$47,0) -> 25125684 | G14: =SUM(B14:F14) -> 25125684
A15: Net profit during the period | B15: 0 | C15: 0 | D15: =IS!$C$33 -> 50407241 | E15: 0 | F15: 0 | G15: =SUM(B15:F15) -> 50407241
A16: Ending Balance | B16: =SUM(B8:B15) -> 411925950 | C16: =SUM(C8:C15) -> 23036942 | D16: =SUM(D8:D15) -> 1.2157334e+08 | E16: =SUM(E8:E15) -> 0 | F16: =SUM(F8:F15) -> 31164251 | G16: =SUM(G8:G15) -> 5.8770048e+08
A19: For the period from January 1 to December 31, 2022
A21: Particulars | B21: Unit Capital | C21: Unit Premium Reserve | D21: Retained Earnings | E21: Dividend Equalization Reserve | F21: Other Comprehensive Income | G21: Total Equity
A23: Opening Balance | B23: ='TB-P'!$K$20 -> 318556230 | C23: ='TB-P'!K21 -> 15909100 | D23: =SUM('TB-P'!$O$7:$O$82)-SUM('TB-P'!$N$7:$N$82)-SUM('TB-P'!O34:O36) -> 18678467 | E23: ='TB-P'!K61 -> 0 | F23: =SUM('TB-P'!O34:O36) -> 2475455.3 | G23: =SUM(B23:F23) -> 3.5561925e+08
A24: Unit capital raised during the period | B24: ='TB-P'!I20 -> 394108550 | C24: ='TB-P'!I21 -> 79033602 | D24: 0 | E24: 0 | F24: 0 | G24: =SUM(B24:F24) -> 4.7314215e+08
A25: Unit surrendered | B25: =-'TB-P'!H20 -> -250287210 | C25: =-'TB-P'!H21 -> -53649164 | D25: 0 | E25: 0 | F25: 0 | G25: =SUM(B25:F25) -> -3.0393637e+08
A26: Dividend Equalization Reserve | B26: 0 | C26: 0 | D26: =-'TB-P'!I77 -> 0 | E26: ='TB-P'!I61 -> 0 | F26: 0 | G26: =SUM(B26:F26) -> 0
A27: Dividend Payable | B27: 0 | C27: 0 | D27: =-'TB-P'!M81 -> 0 | E27: 0 | F27: 0 | G27: =SUM(B27:F27) -> 0
A28: Dividend paid during the year | B28: 0 | C28: 0 | D28: =-'TB-P'!H81 -> 0 | E28: 0 | F28: 0 | G28: =SUM(B28:F28) -> 0
A29: Other comprehensive inome | B29: 0 | C29: 0 | D29: 0 | E29: 0 | F29: =IF('TB-P'!H45>0,'TB-P'!$H$45,0)+IF('TB-P'!H46>0,'TB-P'!$H$46,0)+IF('TB-P'!H47>0,'TB-P'!$H$47,0) -> 3563111.6 | G29: =SUM(B29:F29) -> 3563111.6
A30: Net profit during the period | B30: 0 | C30: 0 | D30: =IS!E33 -> 52487630 | E30: 0 | F30: 0 | G30: =SUM(B30:F30) -> 52487630
A31: Ending Balance | B31: =SUM(B23:B30) -> 462377570 | C31: =SUM(C23:C30) -> 41293538 | D31: =SUM(D23:D30) -> 71166097 | E31: =SUM(E23:E30) -> 0 | F31: =SUM(F23:F30) -> 6038566.8 | G31: =SUM(G23:G30) -> 5.8087577e+08
A33: These financial statement should be read in conjunction with annexed notes.
A38: Head of Compliance | C38: Managing Director
A39: Ekush Wealth Management Limited | C39: Ekush Wealth Management Limited
A44: Trustee
A45: Shandhani Life Insurance Company Limited

Sheet CF
A1: EKUSH STABLE RETURN FUND
A2: STATEMENT OF CASH FLOW
A3: For the period from January 01 to December 31, 2022
A5: Particulars | B5: ='TB-C'!F8 -> 46202 | D5: ='TB-P'!F8 -> 45838
B6: Taka | D6: Taka | G6: BS | H6: =BS!C23 -> 31458525
A8: Cash flows from operating activities: | H8: =H6-B43 -> 94994187
A9: Interest Income | B9: 53644386 | D9: 720525.53
A10: Gain on Sale of Investments | B10: =SUM(IS!C10:'IS'!C12) -> 11821479 | D10: 494233.3
A11: Dividend Income | B11: ='TB-C'!I52+('TB-C'!I51-'TB-C'!H52) -> 201382.5 | D11: 0
A12: Management Fees | B12: =-'TB-C'!H12 -> -2188653.6 | D12: 0
A13: Trustee Fees | B13: =-IF('TB-C'!I13='TB-C'!H40,0,IF('TB-C'!I13=0,'TB-C'!H13+'TB-C'!H40,'TB-C'!H40-'TB-C'!I13)) -> -65816.504 | D13: 0
A14: BSEC Annual Fee | B14: =-IF('TB-C'!I15='TB-C'!H42,0,IF('TB-C'!I15=0,'TB-C'!H15+'TB-C'!H42,'TB-C'!H42-'TB-C'!H15)) -> -442041.41 | D14: 0
A15: Brokerage Commission | B15: =-IS!$C$25 -> -3714.73 | D15: -3262.35
A16: Bank Charges & Excise Duty | B16: =-IS!$C$27 -> -167021.48 | D16: -35752.64
A17: CDBL Fee | B17: =-IF('TB-C'!I135='TB-C'!H44,0,IF('TB-C'!I17=0,'TB-C'!H17+'TB-C'!H44,'TB-C'!H44-'TB-C'!H17)) -> -96969 | D17: -2467.29
A18: Custodian Fee | B18: =-IF('TB-C'!I14='TB-C'!H53,0,IF('TB-C'!I14=0,'TB-C'!H14+'TB-C'!H53,'TB-C'!H53-'TB-C'!H14)) -> -220439.89 | D18: 0
A19: IPO Application Fee | B19: =-'TB-C'!$H$55 -> 0 | D19: -3000
A20: Audit Fee | B20: =-'TB-C'!H16 -> -40250 | D20: 0
A21: Withholding Tax Payable | B21: =-'TB-C'!H64 -> -355701.13
A22: Other Operating Expense | B22: =-'TB-C'!$H$50 -> 0 | D22: -46800
A23: Net Cash Flow from Operating Activities | B23: =SUM(B9:B22) -> 62086639 | C23: 0 | D23: 1123476.6
A25: Cash Flow from Investing Activities:
A26: Net Investment in Shares, Securities & Bonds | B26: -4433743 | D26: -30173550
A27: Net Investment in T-Bill | B27: ='TB-C'!I73 -> 0 | D27: 0
A28: Net Investment in T-Bond | B28: =-'TB-C'!H75 -> 0 | D28: -10851038
A29: Investments in Corporate Bond | B29: -99000000 | D29: 0
A30: IPO Application | B30: =-'TB-C'!H54 -> 0 | D30: 0
A31: Investment in FDR | B31: ='TB-C'!I18 -> 31000000 | D31: -73500000
A32: Preliminary & issue expenses | B32: 0 | D32: -57987.8
A33: Net Cash from Investing Activities | B33: =SUM(B26:B32) -> -72433743 | C33: 0 | D33: -1.1458258e+08
A35: Cash Flow from Financing Activities:
A36: Proceeds from Issuance of Units | B36: ='TB-C'!I20+'TB-C'!I21 -> 2.8307013e+08 | D36: 146701841
A37: Proceeds made for Re-purchase of Units | B37: =-('TB-C'!H20+'TB-C'!H21) -> -3.5177835e+08 | D37: -23818623
A38: Dividend Payment | B38: =-'TB-C'!H63 -> 0 | D38: 0
A39: Net Cash from Financing Activities | B39: =SUM(B36:B38) -> -68708215 | C39: 0 | D39: 1.2288322e+08
A41: Net Cash Flows | B41: =SUM(B23,B33,B39) -> -79055319 | C41: 0 | D41: 9424118.3
A42: Cash & Cash Equivalent at the beginning of the Period | B42: ='TB-C'!J19 -> 15519657 | D42: 0
A43: Cash & Cash Equivalent at the end of the Period | B43: =B41+B42 -> -63535662 | C43: =C41+C42 -> 0 | D43: =D41+D42 -> 9424118.3
A45: Net Operating Cash Flow per Unit | B45: =B23/B47 -> 1.5072282 | D45: =D23/D47 -> 0.024297817
A47: No of Units Outstanding | B47: =BS!C51 -> 41192595 | D47: =BS!E51 -> 46237757
A49: These financial statement should be read in conjunction with annexed notes.
A54: Head of Compliance | B54: Managing Director
A55: Ekush Wealth Management Limited | B55: Ekush Wealth Management Limited
A60: Trustee
A61: Shandhani Life Insurance Company Limited

Sheet W C & I
I2: Preliminary & Issue Expenses
I3: 1 | J3: Formation Fee Payable to AMC | K3: Formation Fee Payable to AMC | L3: 201191
C4: Date | D4: =TODAY() -> 46110 | I4: 2 | J4: Legal & Compliance related Expenses | K4: BSEC Application Fees | L4: 100000
C5: Fund Initiation Day | D5: 43908 | K5: BSEC Registration Fees (0.2% of Initial Fund Size) | L5: 500000
C6: Last Day of Accounting Period | D6: 44196 | K6: Trust Deed Registration related expenses | L6: 75000
K7: CDBL Fee (Distribution of 1.00057 crore unit* BDT 10* 0.00015) | L7: 15009 | M7: 15487.8
C8: Net Asset Value | D8: =NAV -> 5.8770048e+08 | K8: CDBL Annual Fee | L8: 20000 | M8: 40000
C9: Preliminary & Issue Expenses | D9: 1000000 | F9: 942012.2 | K9: CDBL Documentation Fee | L9: 2500 | M9: 2500
I10: 3 | J10: Printing & Publication | K10: Publication of abridge version of prospectus and IPO notification on daily newspaper. | L10: 66800
C11: Weekly Expenses: | E11: Daily | K11: Printing of Prospectus | L11: 19500
C12: Preliminary & Issue Expenses | D12: =F9/(52*5) -> 3623.1238 | E12: =D12/7 -> 517.58912 | I12: Total | L12: 1000000 | M12: =SUM(M7:M11) -> 57987.8
C13: Management Fee | D13: =D8*F13/52 -> 56509.662 | E13: =D13/7 -> 8072.8088 | F13: 0.005 | G13: Quarterly | K13: Paid to CDBL | L13: =M7+M8+M9 -> 57987.8
C14: Trustee Fee | D14: =D8*F14/52 -> 5650.9662 | E14: =D14/7 -> 807.28088 | F14: 0.0005 | G14: Semi Annual | K14: Actual Liability | L14: =L12-L13 -> 942012.2
C17: BSEC Annual Fee | D17: {=_xlfn.IFS(NAV<100000000,100000,NAV>100000000,(NAV*0.1%))} -> 587700.48 | F17: 0.001 | G17: 580877.52 | H17: =G17/52 -> 11170.722
C18: Custodian Fee | D18: =(IF(NAV<50000001,NAV*2.5%,IF(NAV<250000001,(50000000*2.5%)+(NAV-50000000)*2%,IF(NAV<500000001,(50000000*2.5%)+(200000000*2%)+((NAV-250000000)*1.5%),(50000000*2.5%)+(200000000*2%)+(250000000*1.5%)+((NAV-500000000)*1%)))))/52 -> 189942.4
C19: CDBL Fee | D19: 40000 | F19: Includes Tax
C20: CDS Connection Fee | D20: 6000 | F20: Includes Tax
C21: Audit Fee | D21: 20000

Sheet Custodian Fee
C1: T-Bond | D1: T-Bill | E1: FDR | F1: Capital Market | G1: Fee of .05%
B2: Weekly | C2: =BS!C17 -> 3.3744797e+08 | D2: =BS!C12 -> 0.20000005 | E2: =BS!C19 -> 54000000 | F2: =BS!C11 -> 35319588 | G2: =(((F2+E2+D2+C2)*0.05%/360)) -> 592.73272
B3: Weekly | C3: =BS!C17 -> 3.3744797e+08 | D3: =BS!C12 -> 0.20000005 | E3: =BS!C19 -> 54000000 | F3: =BS!C11 -> 35319588 | G3: =((F3+E3+D3+C3)*0.05%/12)/4 -> 4445.4954
B4: Month End | C4: =C3 -> 3.3744797e+08 | D4: =D3 -> 0.20000005 | E4: =E3 -> 54000000 | F4: =F3 -> 35319588 | G4: =((F3+E3+D3+C3)*0.05%/12) -> 17781.982 | I4: Date | J4: Weekly | L4: Monthly | M4: Difference
I5: 45554 | J5: 4072.4282
I6: =I5+7 -> 45561
I7: =I6+7 -> 45568
I8: =I7+7 -> 45575
I9: =I8+7 -> 45582
I10: =I9+7 -> 45589
I11: =I10+7 -> 45596 | M11: =L11-SUM(J7:J11) -> 0
I12: =I11+7 -> 45603 | J12: 4389.8175
I13: =I12+7 -> 45610 | J13: 4313.1195
I14: =I13+7 -> 45617 | J14: 4029.679
I15: =I14+7 -> 45624 | J15: 4336.8559 | M15: =L15-SUM(J12:J15) -> -17069.472
I16: =I15+7 -> 45631 | J16: 4386.4045
I17: =I16+7 -> 45638 | J17: 4124.1136
I18: =I17+7 -> 45645 | J18: 4357.2476
I19: =I18+7 -> 45652 | J19: 4332.6896 | M19: =L19-SUM(J16:J19) -> -17200.455
I20: =I19+7 -> 45659 | J20: 4332.6896
I21: =I20+7 -> 45666 | J21: 4428.4385
I22: =I21+7 -> 45673 | J22: 4465.044
I23: =I22+7 -> 45680 | J23: 4662.9077
I24: =I23+7 -> 45687 | J24: 4730.9739
I25: =I24+7 -> 45694 | J25: 4918.0636
I26: =I25+7 -> 45701 | J26: 5169.8316
I27: =I26+7 -> 45708 | J27: 5383.5447
I28: =I27+7 -> 45715 | J28: 5387.663
I29: =I28+7 -> 45722 | J29: 5373.5749
I30: =I29+7 -> 45729 | J30: 5339.4975
I31: =I30+7 -> 45736 | J31: 4868.4779
... I36: =I35+7 -> 45771 | J36: 4174.0959
I37: 45777 | J37: 4584.2896
I38: =I37+8 -> 45785 | J38: 4620.3411
I39: =I38+7 -> 45792 | J39: 4632.4914
I40: =I39+7 -> 45799 | J40: 4632.4914
I41: =I40+7 -> 45806 | J41: 4632.4914
I42: =I41+7 -> 45813 | J42: 4825.2086
I43: =I42+7 -> 45820 | J43: 4801.8745
I44: =I43+7 -> 45827 | J44: 4762.8642
I45: =I44+7 -> 45834 | J45: 4812.0953
I46: =I45+4 -> 45838 | J46: =4761.95/7*2 -> 1360.5571
I47: =I46+3 -> 45841 | J47: =G3-J46 -> 3084.9383
I48: =I47+7 -> 45848 | J48: 4793.4051
I49: =I48+7 -> 45855 | J49: 5220.6938
I50: =I49+7 -> 45862 | J50: 5362.4467
I51: =I50+7 -> 45869 | J51: 5504.0312
I52: =I51+7 -> 45876 | J52: 5497.4878
I53: =I52+7 -> 45883 | J53: 5551.9314
I54: =I53+7 -> 45890 | J54: 5369.3702
I55: =I54+7 -> 45897 | J55: 5348.7566
I56: =I55+7 -> 45904 | J56: 5006.7592
I57: =I56+7 -> 45911 | J57: 5025.2644
I58: =I57+7 -> 45918 | J58: 5054.5536
I59: =I58+7 -> 45925 | J59: 5119.2019
... I68: =I67+7 -> 45988 | J68: 4353.2717
I69: 45991 | J69: 621.89596
I70: =I69+1 -> 45992 | J70: 619.42843
I71: =I70+1 -> 45993 | J71: 619.56925
I72: =I71+1 -> 45994 | J72: 619.00454
I73: =I72+1 -> 45995 | J73: 619.42382
I74: =I73+1 -> 45996 | J74: 619.42382
I75: =I74+1 -> 45997 | J75: 619.42382
I76: =I75+1 -> 45998 | J76: 619.42382
I77: =I76+1 -> 45999 | J77: 621.41721
I78: =I77+1 -> 46000 | J78: 621.41721
I79: =I78+1 -> 46001 | J79: 625.46112
I80: =I79+1 -> 46002 | J80: 625.44688
I81: =I80+1 -> 46003 | J81: 625.44688
... I168: =I167+1 -> 46090 | J168: 591.39243
I169: 46091 | J169: 591.56017
I170: 46092 | J170: 592.06659
I171: 46093 | J171: 592.20623
I172: 46094 | J172: 592.60772
I173: 46095 | J173: 592.60772
I174: 46096 | J174: 592.60772
I175: 46097 | J175: 592.7459
I176: 46098 | J176: 593.69474
I177: 46099 | J177: 593.69474
I178: 46100 | J178: 593.69474
I179: 46101 | J179: 593.69474
I180: 46102 | J180: 593.69474
... I184: 46106 | J184: 592.73272

Sheet Bank Int.
B1: =D2+F2+H2+J2+L2+N2 -> 350913.58 | C1: MIDLAND (0001-1090001017) | E1: MIDLAND ( 0001-1060000146) | G1: BRAC (2055-604070001) | I1: Modhumoti (1135-12700000001) | K1: MTB (1310-000147462) | M1: NRB (1012-050203836)
A2: =TODAY()+2 -> 46112 | D2: =SUM(D97:D279) -> 195581.3 | F2: =SUM(F97:F279) -> 134597.11 | H2: =SUM(H97:H279) -> 4677.4726 | J2: =SUM(J97:J279) -> 1334.2925 | L2: =SUM(L97:L279) -> 1427.8913 | N2: =SUM(N97:N279) -> 13295.517
B3: Date | C3: Mid 1017 | D3: Interest | E3: Mid 146 | F3: Interest2 | G3: Brac | H3: Interest4 | I3: Modhu 01 | J3: Interest42 | K3: MTBL | L3: Interest5 | M3: NRB | N3: Interest6
D4: ='Bank Int.'!$C4*7.5%/360 -> 0 | J4: ='Bank Int.'!$I4*6.5%/360 -> 0 | L4: ='Bank Int.'!$J4*6.5%/360 -> 0
D5: ='Bank Int.'!$C5*7.5%/360 -> 0 | J5: ='Bank Int.'!$I5*6.5%/360 -> 0 | L5: ='Bank Int.'!$J5*6.5%/360 -> 0
D6: ='Bank Int.'!$C6*7.5%/360 -> 0 | J6: ='Bank Int.'!$I6*6.5%/360 -> 0 | L6: ='Bank Int.'!$J6*6.5%/360 -> 0
D7: ='Bank Int.'!$C7*7.5%/360 -> 0 | J7: ='Bank Int.'!$I7*6.5%/360 -> 0 | L7: ='Bank Int.'!$J7*6.5%/360 -> 0
D8: ='Bank Int.'!$C8*7.5%/360 -> 0 | J8: ='Bank Int.'!$I8*6.5%/360 -> 0 | L8: ='Bank Int.'!$J8*6.5%/360 -> 0
D9: ='Bank Int.'!$C9*7.5%/360 -> 0 | J9: ='Bank Int.'!$I9*6.5%/360 -> 0 | L9: ='Bank Int.'!$J9*6.5%/360 -> 0
D10: ='Bank Int.'!$C10*7.5%/360 -> 0 | J10: ='Bank Int.'!$I10*6.5%/360 -> 0 | L10: ='Bank Int.'!$J10*6.5%/360 -> 0
D11: ='Bank Int.'!$C11*7.5%/360 -> 0 | J11: ='Bank Int.'!$I11*6.5%/360 -> 0 | L11: ='Bank Int.'!$J11*6.5%/360 -> 0
A12: =Table3[[#This Row],[Interest]]+Table3[[#This Row],[Interest2]]+Table3[[#This Row],[Interest4]]+Table3[[#This Row],[Interest42]]+Table3[[#This Row],[Interest5]]+N12 -> 1870.6657 | B12: =B13+1 -> 45741 | C12: 5972545.4 | D12: ='Bank Int.'!$C12*7.5%/360 -> 1244.2803 | E12: 2147681.1 | F12: =Table3[[#This Row],[Mid 146]]*4.5%/360 -> 268.46013 | G12: 23642678 | H12: ='Bank Int.'!$G12*0.5%/360 -> 328.37053 | I12: 40037.12 | J12: ='Bank Int.'!$I12*6.5%/360 -> 7.2289244 | K12: 42593.7 | L12: ='Bank Int.'!$K12*6.5%/360 -> 7.6905292 | M12: 65858.88 | N12: ='Bank Int.'!$M12*8%/360 -> 14.635307
A13: =Table3[[#This Row],[Interest]]+Table3[[#This Row],[Interest2]]+Table3[[#This Row],[Interest4]]+Table3[[#This Row],[Interest42]]+Table3[[#This Row],[Interest5]]+N13 -> 1828.6431 | B13: =B14+1 -> 45740 | C13: 5972545.4 | D13: ='Bank Int.'!$C13*7.5%/360 -> 1244.2803 | E13: 1820787.9 | F13: =Table3[[#This Row],[Mid 146]]*4.5%/360 -> 227.59849 | G13: 23559092 | H13: ='Bank Int.'!$G13*0.5%/360 -> 327.20961 | I13: 40037.12 | J13: ='Bank Int.'!$I13*6.5%/360 -> 7.2289244 | K13: 42593.7 | L13: ='Bank Int.'!$K13*6.5%/360 -> 7.6905292 | M13: 65858.88 | N13: ='Bank Int.'!$M13*8%/360 -> 14.635307
A14: =Table3[[#This Row],[Interest]]+Table3[[#This Row],[Interest2]]+Table3[[#This Row],[Interest4]]+Table3[[#This Row],[Interest42]]+Table3[[#This Row],[Interest5]]+N14 -> 1717.9338 | B14: =B15+1 -> 45739 | C14: 5972545.4 | D14: ='Bank Int.'!$C14*7.5%/360 -> 1244.2803 | E14: 935112.93 | F14: =Table3[[#This Row],[Mid 146]]*4.5%/360 -> 116.88912 | G14: 23559092 | H14: ='Bank Int.'!$G14*0.5%/360 -> 327.20961 | I14: 40037.12 | J14: ='Bank Int.'!$I14*6.5%/360 -> 7.2289244 | K14: 42593.7 | L14: ='Bank Int.'!$K14*6.5%/360 -> 7.6905292 | M14: 65858.88 | N14: ='Bank Int.'!$M14*8%/360 -> 14.635307
A15: =Table3[[#This Row],[Interest]]+Table3[[#This Row],[Interest2]]+Table3[[#This Row],[Interest4]]+Table3[[#This Row],[Interest42]]+Table3[[#This Row],[Interest5]]+N15 -> 1717.9338 | B15: =B16+1 -> 45738 | C15: 5972545.4 | D15: ='Bank Int.'!$C15*7.5%/360 -> 1244.2803 | E15: 935112.93 | F15: =Table3[[#This Row],[Mid 146]]*4.5%/360 -> 116.88912 | G15: 23559092 | H15: ='Bank Int.'!$G15*0.5%/360 -> 327.20961 | I15: 40037.12 | J15: ='Bank Int.'!$I15*6.5%/360 -> 7.2289244 | K15: 42593.7 | L15: ='Bank Int.'!$K15*6.5%/360 -> 7.6905292 | M15: 65858.88 | N15: ='Bank Int.'!$M15*8%/360 -> 14.635307
