Workbook
Name CURRENT_NAV: BS!$C$44
Name NAV: [1]BS!$C$43
Name NAV: BS!$C$42
Name NAV_MKT: Journals!$T$1
Name TCV_STOCKS: #REF!
Name TCV_STOCKS: #REF!
Name TMV_STOCKS: #REF!
Name TMV_STOCKS: #REF!

Sheet Chart of Accounts
B2: Accounts Name | C2: Normal Balance | E2: Stock List
B3: Investments in stock | C3: DEBIT | E3: =#REF! -> #REF!
B4: Interest Receivables from Bank A/C | C4: DEBIT | E4: =#REF! -> #REF!
B5: Preliminary & issue expenses | C5: DEBIT | E5: =#REF! -> #REF!
B6: Accrued Management Fee | C6: CREDIT | E6: =#REF! -> #REF!
B7: Accrued Trustee Fee | C7: CREDIT | E7: =#REF! -> #REF!
B8: Accrued Custodian Fee | C8: CREDIT | E8: =#REF! -> #REF!
B9: Accrued BSEC fee | C9: CREDIT | E9: =#REF! -> #REF!
B10: Accrued Audit Fee | C10: CREDIT | E10: =#REF! -> #REF!
B11: Accrued CDBL Fee | C11: CREDIT | E11: =#REF! -> #REF!
B12: Fixed Deposit Receipts (FDR) | C12: DEBIT | E12: =#REF! -> #REF!
B13: Cash and cash equivalents | C13: DEBIT | E13: =#REF! -> #REF!
B14: Unit Capital | C14: CREDIT | E14: =#REF! -> #REF!
... B16: Interest income | C16: CREDIT | E16: =#REF! -> #REF!
B17: Interest income from FDR | C17: CREDIT
B18: Interest income from Renata Pref. Share | C18: CREDIT
B19: Interest income from Bank Acc. | C19: CREDIT
B20: Interest income from T-Bill | C20: CREDIT
B21: Interest income from T-Bond | C21: CREDIT
B22: Bank charges and excise duties | C22: DEBIT | E22: =#REF! -> #REF!
B23: Brokerage commission | C23: DEBIT | E23: =#REF! -> #REF!
B24: Unrealized gain on securities | C24: CREDIT | E24: =#REF! -> #REF!
B25: Unrealized gain on T-Bill
B26: Unrealized gain on T-Bond
B27: Unrealized loss on securities | C27: DEBIT | E27: =#REF! -> #REF!
B28: Amortization of preliminary and issue expense | C28: DEBIT | E28: =#REF! -> #REF!
B29: Management Fee | C29: DEBIT | E29: =#REF! -> #REF!
B30: Trustee fee | C30: DEBIT | E30: =#REF! -> #REF!
B31: BSEC Annual Fee | C31: DEBIT | E31: =#REF! -> #REF!
B32: Audit fee | C32: DEBIT | E32: =#REF! -> #REF!
B33: CDBL charges | C33: DEBIT | E33: =#REF! -> #REF!
B34: Fair value adjustment | C34: DEBIT | E34: =#REF! -> #REF!
B35: Fair value adjustment T-Bill | C35: DEBIT
B36: Fair value adjustment T-Bond | C36: DEBIT
B37: Interest receivables from FDR | C37: DEBIT | E37: =#REF! -> #REF!
B38: Interest receivables from Renata Pref. Share | C38: DEBIT
B39: Interest receivables from Bank Acc. | C39: DEBIT
B40: Payable to broker | C40: CREDIT | E40: =#REF! -> #REF!
B41: Other operating expenses | C41: DEBIT | E41: =#REF! -> #REF!
B42: Dividend income | C42: CREDIT | E42: =#REF! -> #REF!
B43: Dividend receivable | C43: DEBIT | E43: =#REF! -> #REF!
B44: Custodian fee | C44: DEBIT | E44: =#REF! -> #REF!
B45: IPO Application | C45: DEBIT | E45: =#REF! -> #REF!
B46: IPO Application Fee | C46: DEBIT | E46: =#REF! -> #REF!
B47: Receivable from broker | C47: DEBIT | E47: =#REF! -> #REF!
B48: Realized gain | C48: CREDIT | E48: =#REF! -> #REF!
B49: Realized gain on T-Bill
B50: Realized gain on T-Bond
B51: Other Income | C51: CREDIT | E51: =#REF! -> #REF!
B52: Dividend Equalization Reserve | C52: CREDIT | E52: =#REF! -> #REF!
B53: Retained Earnings | E53: =#REF! -> #REF!
B54: Dividend Payable | C54: CREDIT | E54: =#REF! -> #REF!
B55: Withholding Tax Payable | C55: CREDIT | E55: =#REF! -> #REF!
B56: Withholding Tax Payable of News Paper | C56: CREDIT | E56: =#REF! -> #REF!
B57: Withholding Tax Payable of Telnet | C57: CREDIT | E57: =#REF! -> #REF!
B58: Realized Loss | E58: =#REF! -> #REF!
B59: Investments in T-Bill | E59: =#REF! -> #REF!
B60: Interest receivables from T-Bill | E60: =#REF! -> #REF!
B61: Investments in T-Bond | E61: =#REF! -> #REF!
B62: Interest receivables from T-Bond | E62: =#REF! -> #REF!
E63: =#REF! -> #REF!
E64: =#REF! -> #REF!
E65: =#REF! -> #REF!
E66: =#REF! -> #REF!
E67: =#REF! -> #REF!
E68: =#REF! -> #REF!
E69: =#REF! -> #REF!
E70: =#REF! -> #REF!
E71: =#REF! -> #REF!
E72: =#REF! -> #REF!
E73: =#REF! -> #REF!
E74: =#REF! -> #REF!
... E598: =#REF! -> #REF!

Sheet INVESTOR_LIST
A1: INVESTOR NAME | B1: INVESTOR CODE
A2: HARI PADA SAHA | B2: A00002
A3: EKUSH WEALTH MANAGEMENT LIMITED | B3: A00003
A4: SADIA AHMED | B4: A00004
A5: MORSHEDA MIM | B5: A00005
A6: MD. JAHANGIR ALAM | B6: A00006
A7: BISWAS ARIFUR RAHMAN | B7: A00007
A8: JEWEL SAHA | B8: A00008
A9: SHIBBIR AHMED | B9: A00009
A10: SHYAMAL KRISHNA SAHA | B10: A00010
A11: NASRIN AKHTER | B11: A00011
A12: MRINMOY GHOSH | B12: A00012
... A493: SIKDER FAZLE RABBI | B493: A00493

Sheet Journals
A2: Check of Journal Entries | L2: =K6-L6 -> -0.00157547
A3: Check of Trial Balance | L3: =SUM('TB-C'!H7:H5014)-SUM('TB-C'!I7:I5014) -> 0.0028882474
A4: Check of Balance Seet | L4: =BS!C25-BS!C40 -> 0
A5: Check of Cash Balance | G5: =BS!C23-CF!B44 -> -2739690.1
J6: =ROUND(L6-K6,0) -> 0 | K6: =SUBTOTAL(9,K9:K22408) -> 6.7264836e+09 | L6: =SUBTOTAL(9,L9:L22408) -> 6.7264836e+09
A7: Year | B7: Month | C7: Day | D7: Value | F7: Transaction | G7: Transaction Type | J7: Account Name | K7: Debit | L7: Credit | N7: Ref. Acc.
E8: Date
A9: 2019 | B9: 11 | C9: 26 | D9: =DATE(A9,B9,C9) -> 43795 | E9: =DATE(A9,B9,C9) -> 43795 | F9: Unit Subscription - LUMPSUM | G9: C | H9: {=IFERROR(INDEX(INVESTOR_LIST[INVESTOR NAME],MATCH(I9,INVESTOR_LIST[INVESTOR CODE],0),)," ")} -> HARI PADA SAHA | I9: A00002 | J9: Cash and cash equivalents | K9: 500000 | Q9: A00002
A10: 2019 | B10: 11 | C10: 26 | D10: =DATE(A10,B10,C10) -> 43795 | E10: =DATE(A10,B10,C10) -> 43795 | G10: C | H10: {=IFERROR(INDEX(INVESTOR_LIST[INVESTOR NAME],MATCH(I10,INVESTOR_LIST[INVESTOR CODE],0),)," ")} -> HARI PADA SAHA | I10: A00002 | J10: Unit Capital | L10: 500000 | M10: 0 | O10: =SUMIF(J9:L3763,"UNIT PREMIUM RESERVE",L9:L3763) -> 39052552 | Q10: A00002
A11: 2019 | B11: 11 | C11: 26 | D11: =DATE(A11,B11,C11) -> 43795 | E11: =DATE(A11,B11,C11) -> 43795 | F11: Unit Subscription - LUMPSUM | G11: C | H11: {=IFERROR(INDEX(INVESTOR_LIST[INVESTOR NAME],MATCH(I11,INVESTOR_LIST[INVESTOR CODE],0),)," ")} -> EKUSH WEALTH MANAGEMENT LIMITED | I11: A00003 | J11: Cash and cash equivalents | K11: 10000000 | M11: 0 | Q11: A00003
A12: 2019 | B12: 11 | C12: 26 | D12: =DATE(A12,B12,C12) -> 43795 | E12: =DATE(A12,B12,C12) -> 43795 | G12: C | H12: {=IFERROR(INDEX(INVESTOR_LIST[INVESTOR NAME],MATCH(I12,INVESTOR_LIST[INVESTOR CODE],0),)," ")} -> EKUSH WEALTH MANAGEMENT LIMITED | I12: A00003 | J12: Unit Capital | L12: 10000000 | M12: 0 | Q12: A00003
A13: 2019 | B13: 11 | C13: 26 | D13: =DATE(A13,B13,C13) -> 43795 | E13: =DATE(A13,B13,C13) -> 43795 | F13: Bank charge has been charged | G13: C | H13: {=IFERROR(INDEX(INVESTOR_LIST[INVESTOR NAME],MATCH(I13,INVESTOR_LIST[INVESTOR CODE],0),)," ")} | J13: Bank charges and excise duties | K13: 60 | M13: 26
A14: 2019 | B14: 11 | C14: 26 | D14: =DATE(A14,B14,C14) -> 43795 | E14: =DATE(A14,B14,C14) -> 43795 | G14: C | H14: {=IFERROR(INDEX(INVESTOR_LIST[INVESTOR NAME],MATCH(I14,INVESTOR_LIST[INVESTOR CODE],0),)," ")} | J14: Cash and cash equivalents | L14: 60 | M14: 0
A15: 2019 | B15: 12 | C15: 22 | D15: =DATE(A15,B15,C15) -> 43821 | E15: =DATE(A15,B15,C15) -> 43821 | F15: Unit Subscription - LUMPSUM | G15: C | H15: {=IFERROR(INDEX(INVESTOR_LIST[INVESTOR NAME],MATCH(I15,INVESTOR_LIST[INVESTOR CODE],0),)," ")} -> SADIA AHMED | I15: A00004 | J15: Cash and cash equivalents | K15: 700000 | M15: 8 | Q15: A00004
A16: 2019 | B16: 12 | C16: 22 | D16: =DATE(A16,B16,C16) -> 43821 | E16: =DATE(A16,B16,C16) -> 43821 | G16: C | H16: {=IFERROR(INDEX(INVESTOR_LIST[INVESTOR NAME],MATCH(I16,INVESTOR_LIST[INVESTOR CODE],0),)," ")} -> SADIA AHMED | I16: A00004 | J16: Unit Capital | L16: 700000 | M16: 0 | Q16: A00004
A17: 2019 | B17: 12 | C17: 22 | D17: =DATE(A17,B17,C17) -> 43821 | E17: =DATE(A17,B17,C17) -> 43821 | F17: Bank charge has been charged | G17: C | H17: {=IFERROR(INDEX(INVESTOR_LIST[INVESTOR NAME],MATCH(I17,INVESTOR_LIST[INVESTOR CODE],0),)," ")} | J17: Bank charges and excise duties | K17: 25 | M17: 0
A18: 2019 | B18: 12 | C18: 22 | D18: =DATE(A18,B18,C18) -> 43821 | E18: =DATE(A18,B18,C18) -> 43821 | G18: C | H18: {=IFERROR(INDEX(INVESTOR_LIST[INVESTOR NAME],MATCH(I18,INVESTOR_LIST[INVESTOR CODE],0),)," ")} | J18: Cash and cash equivalents | L18: 25 | M18: 0
A19: 2019 | B19: 12 | C19: 30 | D19: =DATE(A19,B19,C19) -> 43829 | E19: =DATE(A19,B19,C19) -> 43829 | F19: Interest Credited in the Bank Account-1090000732 | G19: C | H19: {=IFERROR(INDEX(INVESTOR_LIST[INVESTOR NAME],MATCH(I19,INVESTOR_LIST[INVESTOR CODE],0),)," ")} | J19: Cash and cash equivalents | K19: 66136
A20: 2019 | B20: 12 | C20: 30 | D20: =DATE(A20,B20,C20) -> 43829 | E20: =DATE(A20,B20,C20) -> 43829 | G20: C | H20: {=IFERROR(INDEX(INVESTOR_LIST[INVESTOR NAME],MATCH(I20,INVESTOR_LIST[INVESTOR CODE],0),)," ")} | J20: Interest income | L20: 66136 | M20: 0
A21: 2019 | B21: 12 | C21: 30 | D21: =DATE(A21,B21,C21) -> 43829 | E21: =DATE(A21,B21,C21) -> 43829 | F21: Unit Subscription - LUMPSUM | G21: C | H21: {=IFERROR(INDEX(INVESTOR_LIST[INVESTOR NAME],MATCH(I21,INVESTOR_LIST[INVESTOR CODE],0),)," ")} -> MORSHEDA MIM | I21: A00005 | J21: Cash and cash equivalents | K21: 50000 | M21: 1 | Q21: A00005
A22: 2019 | B22: 12 | C22: 30 | D22: =DATE(A22,B22,C22) -> 43829 | E22: =DATE(A22,B22,C22) -> 43829 | G22: C | H22: {=IFERROR(INDEX(INVESTOR_LIST[INVESTOR NAME],MATCH(I22,INVESTOR_LIST[INVESTOR CODE],0),)," ")} -> MORSHEDA MIM | I22: A00005 | J22: Unit Capital | L22: 50000 | M22: 0 | Q22: A00005
A23: 2019 | B23: 12 | C23: 30 | D23: =DATE(A23,B23,C23) -> 43829 | E23: =DATE(A23,B23,C23) -> 43829 | F23: Bank charge has been charged | G23: C | H23: {=IFERROR(INDEX(INVESTOR_LIST[INVESTOR NAME],MATCH(I23,INVESTOR_LIST[INVESTOR CODE],0),)," ")} | J23: Bank charges and excise duties | K23: 9920 | M23: 2
A24: 2019 | B24: 12 | C24: 30 | D24: =DATE(A24,B24,C24) -> 43829 | E24: =DATE(A24,B24,C24) -> 43829 | G24: C | H24: {=IFERROR(INDEX(INVESTOR_LIST[INVESTOR NAME],MATCH(I24,INVESTOR_LIST[INVESTOR CODE],0),)," ")} | J24: Cash and cash equivalents | L24: 9920 | M24: 0
A25: 2019 | B25: 12 | C25: 30 | D25: =DATE(A25,B25,C25) -> 43829 | E25: =DATE(A25,B25,C25) -> 43829 | F25: Bank charge has been charged | G25: C | H25: {=IFERROR(INDEX(INVESTOR_LIST[INVESTOR NAME],MATCH(I25,INVESTOR_LIST[INVESTOR CODE],0),)," ")} | J25: Bank charges and excise duties | K25: 575 | M25: 5
A26: 2019 | B26: 12 | C26: 30 | D26: =DATE(A26,B26,C26) -> 43829 | E26: =DATE(A26,B26,C26) -> 43829 | G26: C | H26: {=IFERROR(INDEX(INVESTOR_LIST[INVESTOR NAME],MATCH(I26,INVESTOR_LIST[INVESTOR CODE],0),)," ")} | J26: Cash and cash equivalents | L26: 575 | M26: 0
A27: 2019 | B27: 12 | C27: 30 | D27: =DATE(A27,B27,C27) -> 43829 | E27: =DATE(A27,B27,C27) -> 43829 | F27: Bank charge has been charged | G27: C | H27: {=IFERROR(INDEX(INVESTOR_LIST[INVESTOR NAME],MATCH(I27,INVESTOR_LIST[INVESTOR CODE],0),)," ")} | J27: Bank charges and excise duties | K27: 12000 | M27: 0
A28: 2019 | B28: 12 | C28: 30 | D28: =DATE(A28,B28,C28) -> 43829 | E28: =DATE(A28,B28,C28) -> 43829 | G28: C | H28: {=IFERROR(INDEX(INVESTOR_LIST[INVESTOR NAME],MATCH(I28,INVESTOR_LIST[INVESTOR CODE],0),)," ")} | J28: Cash and cash equivalents | L28: 12000 | M28: 0
A29: 2019 | B29: 12 | C29: 31 | D29: =DATE(A29,B29,C29) -> 43830 | E29: =DATE(A29,B29,C29) -> 43830 | F29: Audit fee expense has been occurred | G29: NC | H29: {=IFERROR(INDEX(INVESTOR_LIST[INVESTOR NAME],MATCH(I29,INVESTOR_LIST[INVESTOR CODE],0),)," ")} | J29: Audit fee | K29: 10000
A30: 2019 | B30: 12 | C30: 31 | D30: =DATE(A30,B30,C30) -> 43830 | E30: =DATE(A30,B30,C30) -> 43830 | G30: NC | H30: {=IFERROR(INDEX(INVESTOR_LIST[INVESTOR NAME],MATCH(I30,INVESTOR_LIST[INVESTOR CODE],0),)," ")} | J30: Accrued Audit Fee | L30: 10000
A31: 2020 | B31: 1 | C31: 12 | D31: =DATE(A31,B31,C31) -> 43842 | E31: =DATE(A31,B31,C31) -> 43842 | F31: Unit Subscription - LUMPSUM | G31: C | H31: {=IFERROR(INDEX(INVESTOR_LIST[INVESTOR NAME],MATCH(I31,INVESTOR_LIST[INVESTOR CODE],0),)," ")} -> MD. JAHANGIR ALAM | I31: A00006 | J31: Cash and cash equivalents | K31: 50000 | M31: 2 | Q31: A00006
A32: 2020 | B32: 1 | C32: 12 | D32: =DATE(A32,B32,C32) -> 43842 | E32: =DATE(A32,B32,C32) -> 43842 | G32: C | H32: {=IFERROR(INDEX(INVESTOR_LIST[INVESTOR NAME],MATCH(I32,INVESTOR_LIST[INVESTOR CODE],0),)," ")} -> MD. JAHANGIR ALAM | I32: A00006 | J32: Unit Capital | L32: =K31 -> 50000 | M32: 0 | Q32: A00006
A33: 2020 | B33: 1 | C33: 12 | D33: =DATE(A33,B33,C33) -> 43842 | E33: =DATE(A33,B33,C33) -> 43842 | F33: Bank charge has been charged | G33: C | H33: {=IFERROR(INDEX(INVESTOR_LIST[INVESTOR NAME],MATCH(I33,INVESTOR_LIST[INVESTOR CODE],0),)," ")} | J33: Bank charges and excise duties | K33: 10 | M33: 1
A34: 2020 | B34: 1 | C34: 12 | D34: =DATE(A34,B34,C34) -> 43842 | E34: =DATE(A34,B34,C34) -> 43842 | G34: C | H34: {=IFERROR(INDEX(INVESTOR_LIST[INVESTOR NAME],MATCH(I34,INVESTOR_LIST[INVESTOR CODE],0),)," ")} | J34: Cash and cash equivalents | L34: 10 | M34: 0
A35: 2020 | B35: 1 | C35: 13 | D35: =DATE(A35,B35,C35) -> 43843 | E35: =DATE(A35,B35,C35) -> 43843 | F35: Unit Subscription - LUMPSUM | G35: C | H35: {=IFERROR(INDEX(INVESTOR_LIST[INVESTOR NAME],MATCH(I35,INVESTOR_LIST[INVESTOR CODE],0),)," ")} -> BISWAS ARIFUR RAHMAN | I35: A00007 | J35: Cash and cash equivalents | K35: 10000 | M35: 3 | Q35: A00007
A36: 2020 | B36: 1 | C36: 13 | D36: =DATE(A36,B36,C36) -> 43843 | E36: =DATE(A36,B36,C36) -> 43843 | G36: C | H36: {=IFERROR(INDEX(INVESTOR_LIST[INVESTOR NAME],MATCH(I36,INVESTOR_LIST[INVESTOR CODE],0),)," ")} -> BISWAS ARIFUR RAHMAN | I36: A00007 | J36: Unit Capital | L36: =K35 -> 10000 | M36: 0 | Q36: A00007
A37: 2020 | B37: 1 | C37: 15 | D37: =DATE(A37,B37,C37) -> 43845 | E37: =DATE(A37,B37,C37) -> 43845 | F37: Unit Subscription - LUMPSUM | G37: C | H37: {=IFERROR(INDEX(INVESTOR_LIST[INVESTOR NAME],MATCH(I37,INVESTOR_LIST[INVESTOR CODE],0),)," ")} -> JEWEL SAHA | I37: A00008 | J37: Cash and cash equivalents | K37: 5000 | M37: 2 | Q37: A00008
A38: 2020 | B38: 1 | C38: 15 | D38: =DATE(A38,B38,C38) -> 43845 | E38: =DATE(A38,B38,C38) -> 43845 | G38: C | H38: {=IFERROR(INDEX(INVESTOR_LIST[INVESTOR NAME],MATCH(I38,INVESTOR_LIST[INVESTOR CODE],0),)," ")} -> JEWEL SAHA | I38: A00008 | J38: Unit Capital | L38: =K37 -> 5000 | M38: 0 | Q38: A00008
A39: 2020 | B39: 1 | C39: 20 | D39: =DATE(A39,B39,C39) -> 43850 | E39: =DATE(A39,B39,C39) -> 43850 | F39: Bank charge has been charged | G39: C | H39: {=IFERROR(INDEX(INVESTOR_LIST[INVESTOR NAME],MATCH(I39,INVESTOR_LIST[INVESTOR CODE],0),)," ")} | J39: Bank charges and excise duties | K39: 10 | M39: 0
A40: 2020 | B40: 1 | C40: 20 | D40: =DATE(A40,B40,C40) -> 43850 | E40: =DATE(A40,B40,C40) -> 43850 | G40: C | H40: {=IFERROR(INDEX(INVESTOR_LIST[INVESTOR NAME],MATCH(I40,INVESTOR_LIST[INVESTOR CODE],0),)," ")} | J40: Cash and cash equivalents | L40: 10 | M40: 0
A41: 2020 | B41: 1 | C41: 20 | D41: =DATE(A41,B41,C41) -> 43850 | E41: =DATE(A41,B41,C41) -> 43850 | F41: Unit Subscription - LUMPSUM | G41: C | H41: {=IFERROR(INDEX(INVESTOR_LIST[INVESTOR NAME],MATCH(I41,INVESTOR_LIST[INVESTOR CODE],0),)," ")} -> SHIBBIR AHMED | I41: A00009 | J41: Cash and cash equivalents | K41: 100000 | M41: 6 | Q41: A00009
A42: 2020 | B42: 1 | C42: 20 | D42: =DATE(A42,B42,C42) -> 43850 | E42: =DATE(A42,B42,C42) -> 43850 | G42: C | H42: {=IFERROR(INDEX(INVESTOR_LIST[INVESTOR NAME],MATCH(I42,INVESTOR_LIST[INVESTOR CODE],0),)," ")} -> SHIBBIR AHMED | I42: A00009 | J42: Unit Capital | L42: =K41 -> 100000 | M42: 0 | Q42: A00009
A43: 2020 | B43: 1 | C43: 20 | D43: =DATE(A43,B43,C43) -> 43850 | E43: =DATE(A43,B43,C43) -> 43850 | F43: Unit Subscription - LUMPSUM | G43: C | H43: {=IFERROR(INDEX(INVESTOR_LIST[INVESTOR NAME],MATCH(I43,INVESTOR_LIST[INVESTOR CODE],0),)," ")} -> SHYAMAL KRISHNA SAHA | I43: A00010 | J43: Cash and cash equivalents | K43: 100000 | M43: 1 | Q43: A00010
A44: 2020 | B44: 1 | C44: 20 | D44: =DATE(A44,B44,C44) -> 43850 | E44: =DATE(A44,B44,C44) -> 43850 | G44: C | H44: {=IFERROR(INDEX(INVESTOR_LIST[INVESTOR NAME],MATCH(I44,INVESTOR_LIST[INVESTOR CODE],0),)," ")} -> SHYAMAL KRISHNA SAHA | I44: A00010 | J44: Unit Capital | L44: =K43 -> 100000 | M44: 0 | Q44: A00010
A45: 2020 | B45: 1 | C45: 22 | D45: =DATE(A45,B45,C45) -> 43852 | E45: =DATE(A45,B45,C45) -> 43852 | F45: Unit Subscription - LUMPSUM | G45: C | H45: {=IFERROR(INDEX(INVESTOR_LIST[INVESTOR NAME],MATCH(I45,INVESTOR_LIST[INVESTOR CODE],0),)," ")} -> NASRIN AKHTER | I45: A00011 | J45: Cash and cash equivalents | K45: 6000 | M45: 5 | Q45: A00011
A46: 2020 | B46: 1 | C46: 22 | D46: =DATE(A46,B46,C46) -> 43852 | E46: =DATE(A46,B46,C46) -> 43852 | G46: C | H46: {=IFERROR(INDEX(INVESTOR_LIST[INVESTOR NAME],MATCH(I46,INVESTOR_LIST[INVESTOR CODE],0),)," ")} -> NASRIN AKHTER | I46: A00011 | J46: Unit Capital | L46: =K45 -> 6000 | M46: 0 | Q46: A00011
A47: 2020 | B47: 1 | C47: 23 | D47: =DATE(A47,B47,C47) -> 43853 | E47: =DATE(A47,B47,C47) -> 43853 | F47: Unit Subscription - LUMPSUM | G47: C | H47: {=IFERROR(INDEX(INVESTOR_LIST[INVESTOR NAME],MATCH(I47,INVESTOR_LIST[INVESTOR CODE],0),)," ")} -> MRINMOY GHOSH | I47: A00012 | J47: Cash and cash equivalents | K47: 10000 | M47: 0 | Q47: A00012
A48: 2020 | B48: 1 | C48: 23 | D48: =DATE(A48,B48,C48) -> 43853 | E48: =DATE(A48,B48,C48) -> 43853 | G48: C | H48: {=IFERROR(INDEX(INVESTOR_LIST[INVESTOR NAME],MATCH(I48,INVESTOR_LIST[INVESTOR CODE],0),)," ")} -> MRINMOY GHOSH | I48: A00012 | J48: Unit Capital | L48: =K47 -> 10000 | M48: 0 | Q48: A00012
A49: 2020 | B49: 1 | C49: 26 | D49: =DATE(A49,B49,C49) -> 43856 | E49: =DATE(A49,B49,C49) -> 43856 | F49: Unit Subscription - LUMPSUM | G49: C | H49: {=IFERROR(INDEX(INVESTOR_LIST[INVESTOR NAME],MATCH(I49,INVESTOR_LIST[INVESTOR CODE],0),)," ")} -> MORSHEDA MIM | I49: A00005 | J49: Cash and cash equivalents | K49: 5000 | M49: 9 | Q49: A00005
A50: 2020 | B50: 1 | C50: 26 | D50: =DATE(A50,B50,C50) -> 43856 | E50: =DATE(A50,B50,C50) -> 43856 | G50: C | H50: {=IFERROR(INDEX(INVESTOR_LIST[INVESTOR NAME],MATCH(I50,INVESTOR_LIST[INVESTOR CODE],0),)," ")} -> MORSHEDA MIM | I50: A00005 | J50: Unit Capital | L50: =K49 -> 5000 | M50: 0 | Q50: A00005
A51: 2020 | B51: 1 | C51: 28 | D51: =DATE(A51,B51,C51) -> 43858 | E51: =DATE(A51,B51,C51) -> 43858 | F51: Unit Subscription - LUMPSUM | G51: C | H51: {=IFERROR(INDEX(INVESTOR_LIST[INVESTOR NAME],MATCH(I51,INVESTOR_LIST[INVESTOR CODE],0),)," ")} -> MOHAMMAD NAZMUL HOSSAIN | I51: A00013 | J51: Cash and cash equivalents | K51: 200000 | M51: 2 | Q51: A00013
A52: 2020 | B52: 1 | C52: 28 | D52: =DATE(A52,B52,C52) -> 43858 | E52: =DATE(A52,B52,C52) -> 43858 | G52: C | H52: {=IFERROR(INDEX(INVESTOR_LIST[INVESTOR NAME],MATCH(I52,INVESTOR_LIST[INVESTOR CODE],0),)," ")} -> MOHAMMAD NAZMUL HOSSAIN | I52: A00013 | J52: Unit Capital | L52: =K51 -> 200000 | M52: 0 | Q52: A00013
A53: 2020 | B53: 1 | C53: 28 | D53: =DATE(A53,B53,C53) -> 43858 | E53: =DATE(A53,B53,C53) -> 43858 | F53: Unit Subscription - LUMPSUM | G53: C | H53: {=IFERROR(INDEX(INVESTOR_LIST[INVESTOR NAME],MATCH(I53,INVESTOR_LIST[INVESTOR CODE],0),)," ")} -> ANJANA SAHA | I53: A00014 | J53: Cash and cash equivalents | K53: 800000 | M53: 0 | Q53: A00014
A54: 2020 | B54: 1 | C54: 28 | D54: =DATE(A54,B54,C54) -> 43858 | E54: =DATE(A54,B54,C54) -> 43858 | G54: C | H54: {=IFERROR(INDEX(INVESTOR_LIST[INVESTOR NAME],MATCH(I54,INVESTOR_LIST[INVESTOR CODE],0),)," ")} -> ANJANA SAHA | I54: A00014 | J54: Unit Capital | L54: =K53 -> 800000 | M54: 0 | Q54: A00014
A55: 2020 | B55: 1 | C55: 28 | D55: =DATE(A55,B55,C55) -> 43858 | E55: =DATE(A55,B55,C55) -> 43858 | F55: Bank charge has been charged | G55: C | H55: {=IFERROR(INDEX(INVESTOR_LIST[INVESTOR NAME],MATCH(I55,INVESTOR_LIST[INVESTOR CODE],0),)," ")} | J55: Bank charges and excise duties | K55: 10 | M55: 0
A56: 2020 | B56: 1 | C56: 28 | D56: =DATE(A56,B56,C56) -> 43858 | E56: =DATE(A56,B56,C56) -> 43858 | G56: C | H56: {=IFERROR(INDEX(INVESTOR_LIST[INVESTOR NAME],MATCH(I56,INVESTOR_LIST[INVESTOR CODE],0),)," ")} | J56: Cash and cash equivalents | L56: 10 | M56: 0
A57: 2020 | B57: 1 | C57: 28 | D57: =DATE(A57,B57,C57) -> 43858 | E57: =DATE(A57,B57,C57) -> 43858 | F57: Bank charge has been charged | G57: C | H57: {=IFERROR(INDEX(INVESTOR_LIST[INVESTOR NAME],MATCH(I57,INVESTOR_LIST[INVESTOR CODE],0),)," ")} | J57: Bank charges and excise duties | K57: 25 | M57: 6
A58: 2020 | B58: 1 | C58: 28 | D58: =DATE(A58,B58,C58) -> 43858 | E58: =DATE(A58,B58,C58) -> 43858 | G58: C | H58: {=IFERROR(INDEX(INVESTOR_LIST[INVESTOR NAME],MATCH(I58,INVESTOR_LIST[INVESTOR CODE],0),)," ")} | J58: Cash and cash equivalents | L58: 25 | M58: 0
A59: 2020 | B59: 2 | C59: 3 | D59: =DATE(A59,B59,C59) -> 43864 | E59: =DATE(A59,B59,C59) -> 43864 | F59: Unit Subscription - LUMPSUM | G59: C | H59: {=IFERROR(INDEX(INVESTOR_LIST[INVESTOR NAME],MATCH(I59,INVESTOR_LIST[INVESTOR CODE],0),)," ")} -> ABDUL HAI BHUYAN | I59: A00015 | J59: Cash and cash equivalents | K59: 100000 | M59: 0 | Q59: A00015
A60: 2020 | B60: 2 | C60: 3 | D60: =DATE(A60,B60,C60) -> 43864 | E60: =DATE(A60,B60,C60) -> 43864 | G60: C | H60: {=IFERROR(INDEX(INVESTOR_LIST[INVESTOR NAME],MATCH(I60,INVESTOR_LIST[INVESTOR CODE],0),)," ")} -> ABDUL HAI BHUYAN | I60: A00015 | J60: Unit Capital | L60: =K59 -> 100000 | M60: 0 | Q60: A00015
A61: 2020 | B61: 2 | C61: 3 | D61: =DATE(A61,B61,C61) -> 43864 | E61: =DATE(A61,B61,C61) -> 43864 | F61: Bank charge has been charged | G61: C | H61: {=IFERROR(INDEX(INVESTOR_LIST[INVESTOR NAME],MATCH(I61,INVESTOR_LIST[INVESTOR CODE],0),)," ")} | J61: Bank charges and excise duties | K61: 10 | M61: 1
A62: 2020 | B62: 2 | C62: 3 | D62: =DATE(A62,B62,C62) -> 43864 | E62: =DATE(A62,B62,C62) -> 43864 | G62: C | H62: {=IFERROR(INDEX(INVESTOR_LIST[INVESTOR NAME],MATCH(I62,INVESTOR_LIST[INVESTOR CODE],0),)," ")} | J62: Cash and cash equivalents | L62: 10 | M62: 0
A63: 2020 | B63: 2 | C63: 4 | D63: =DATE(A63,B63,C63) -> 43865 | E63: =DATE(A63,B63,C63) -> 43865 | F63: Unit Subscription - LUMPSUM | G63: C | H63: {=IFERROR(INDEX(INVESTOR_LIST[INVESTOR NAME],MATCH(I63,INVESTOR_LIST[INVESTOR CODE],0),)," ")} -> ALI IMAM | I63: A00016 | J63: Cash and cash equivalents | K63: 50000 | M63: 5 | Q63: A00016
A64: 2020 | B64: 2 | C64: 4 | D64: =DATE(A64,B64,C64) -> 43865 | E64: =DATE(A64,B64,C64) -> 43865 | G64: C | H64: {=IFERROR(INDEX(INVESTOR_LIST[INVESTOR NAME],MATCH(I64,INVESTOR_LIST[INVESTOR CODE],0),)," ")} -> ALI IMAM | I64: A00016 | J64: Unit Capital | L64: =K63 -> 50000 | M64: 0 | Q64: A00016
A65: 2020 | B65: 2 | C65: 9 | D65: =DATE(A65,B65,C65) -> 43870 | E65: =DATE(A65,B65,C65) -> 43870 | F65: Unit Subscription - LUMPSUM | G65: C | H65: {=IFERROR(INDEX(INVESTOR_LIST[INVESTOR NAME],MATCH(I65,INVESTOR_LIST[INVESTOR CODE],0),)," ")} -> UCIL EMPLOYEES' PROVIDENT FUND | I65: A00017 | J65: Cash and cash equivalents | K65: 500000 | M65: 0 | Q65: A00017
A66: 2020 | B66: 2 | C66: 9 | D66: =DATE(A66,B66,C66) -> 43870 | E66: =DATE(A66,B66,C66) -> 43870 | G66: C | H66: {=IFERROR(INDEX(INVESTOR_LIST[INVESTOR NAME],MATCH(I66,INVESTOR_LIST[INVESTOR CODE],0),)," ")} -> UCIL EMPLOYEES' PROVIDENT FUND | I66: A00017 | J66: Unit Capital | L66: =K65 -> 500000 | M66: 0 | Q66: A00017
A67: 2020 | B67: 2 | C67: 9 | D67: =DATE(A67,B67,C67) -> 43870 | E67: =DATE(A67,B67,C67) -> 43870 | F67: Unit Subscription - LUMPSUM | G67: C | H67: {=IFERROR(INDEX(INVESTOR_LIST[INVESTOR NAME],MATCH(I67,INVESTOR_LIST[INVESTOR CODE],0),)," ")} -> MD. ZAKIR HOSSEN | I67: A00018 | J67: Cash and cash equivalents | K67: 5000 | M67: 9 | Q67: A00018
A68: 2020 | B68: 2 | C68: 9 | D68: =DATE(A68,B68,C68) -> 43870 | E68: =DATE(A68,B68,C68) -> 43870 | G68: C | H68: {=IFERROR(INDEX(INVESTOR_LIST[INVESTOR NAME],MATCH(I68,INVESTOR_LIST[INVESTOR CODE],0),)," ")} -> MD. ZAKIR HOSSEN | I68: A00018 | J68: Unit Capital | L68: =K67 -> 5000 | M68: 0 | Q68: A00018
A69: 2020 | B69: 2 | C69: 9 | D69: =DATE(A69,B69,C69) -> 43870 | E69: =DATE(A69,B69,C69) -> 43870 | F69: Bank charge has been charged | G69: C | H69: {=IFERROR(INDEX(INVESTOR_LIST[INVESTOR NAME],MATCH(I69,INVESTOR_LIST[INVESTOR CODE],0),)," ")} | J69: Bank charges and excise duties | K69: 60 | M69: 0
A70: 2020 | B70: 2 | C70: 9 | D70: =DATE(A70,B70,C70) -> 43870 | E70: =DATE(A70,B70,C70) -> 43870 | G70: C | H70: {=IFERROR(INDEX(INVESTOR_LIST[INVESTOR NAME],MATCH(I70,INVESTOR_LIST[INVESTOR CODE],0),)," ")} | J70: Cash and cash equivalents | L70: 60 | M70: 0
A71: 2020 | B71: 2 | C71: 18 | D71: =DATE(A71,B71,C71) -> 43879 | E71: =DATE(A71,B71,C71) -> 43879 | F71: Bank charge has been charged | G71: C | H71: {=IFERROR(INDEX(INVESTOR_LIST[INVESTOR NAME],MATCH(I71,INVESTOR_LIST[INVESTOR CODE],0),)," ")} | J71: Bank charges and excise duties | K71: 10 | M71: 0
A72: 2020 | B72: 2 | C72: 18 | D72: =DATE(A72,B72,C72) -> 43879 | E72: =DATE(A72,B72,C72) -> 43879 | G72: C | H72: {=IFERROR(INDEX(INVESTOR_LIST[INVESTOR NAME],MATCH(I72,INVESTOR_LIST[INVESTOR CODE],0),)," ")} | J72: Cash and cash equivalents | L72: 10 | M72: 0
A73: 2020 | B73: 2 | C73: 18 | D73: =DATE(A73,B73,C73) -> 43879 | E73: =DATE(A73,B73,C73) -> 43879 | F73: Unit Subscription - LUMPSUM | G73: C | H73: {=IFERROR(INDEX(INVESTOR_LIST[INVESTOR NAME],MATCH(I73,INVESTOR_LIST[INVESTOR CODE],0),)," ")} -> TANIZA MAZED | I73: A00019 | J73: Cash and cash equivalents | K73: 100000 | M73: 3 | Q73: A00019
A74: 2020 | B74: 2 | C74: 18 | D74: =DATE(A74,B74,C74) -> 43879 | E74: =DATE(A74,B74,C74) -> 43879 | G74: C | H74: {=IFERROR(INDEX(INVESTOR_LIST[INVESTOR NAME],MATCH(I74,INVESTOR_LIST[INVESTOR CODE],0),)," ")} -> TANIZA MAZED | I74: A00019 | J74: Unit Capital | L74: =K73 -> 100000 | M74: 0 | Q74: A00019
A75: 2020 | B75: 2 | C75: 20 | D75: =DATE(A75,B75,C75) -> 43881 | E75: =DATE(A75,B75,C75) -> 43881 | F75: Unit Subscription - LUMPSUM | G75: C | H75: {=IFERROR(INDEX(INVESTOR_LIST[INVESTOR NAME],MATCH(I75,INVESTOR_LIST[INVESTOR CODE],0),)," ")} -> MRIDUL KUMAR DEY | I75: A00020 | J75: Cash and cash equivalents | K75: 100000 | M75: 0 | Q75: A00020
A76: 2020 | B76: 2 | C76: 20 | D76: =DATE(A76,B76,C76) -> 43881 | E76: =DATE(A76,B76,C76) -> 43881 | G76: C | H76: {=IFERROR(INDEX(INVESTOR_LIST[INVESTOR NAME],MATCH(I76,INVESTOR_LIST[INVESTOR CODE],0),)," ")} -> MRIDUL KUMAR DEY | I76: A00020 | J76: Unit Capital | L76: =K75 -> 100000 | M76: 0 | Q76: A00020
A77: 2020 | B77: 2 | C77: 20 | D77: =DATE(A77,B77,C77) -> 43881 | E77: =DATE(A77,B77,C77) -> 43881 | F77: Unit Subscription - LUMPSUM | G77: C | H77: {=IFERROR(INDEX(INVESTOR_LIST[INVESTOR NAME],MATCH(I77,INVESTOR_LIST[INVESTOR CODE],0),)," ")} -> MAMUNUR RASHID | I77: A00021 | J77: Cash and cash equivalents | K77: 10000 | M77: 0 | Q77: A00021
A78: 2020 | B78: 2 | C78: 20 | D78: =DATE(A78,B78,C78) -> 43881 | E78: =DATE(A78,B78,C78) -> 43881 | G78: C | H78: {=IFERROR(INDEX(INVESTOR_LIST[INVESTOR NAME],MATCH(I78,INVESTOR_LIST[INVESTOR CODE],0),)," ")} -> MAMUNUR RASHID | I78: A00021 | J78: Unit Capital | L78: =K77 -> 10000 | M78: 0 | Q78: A00021
A79: 2020 | B79: 2 | C79: 20 | D79: =DATE(A79,B79,C79) -> 43881 | E79: =DATE(A79,B79,C79) -> 43881 | F79: Unit Subscription - LUMPSUM | G79: C | H79: {=IFERROR(INDEX(INVESTOR_LIST[INVESTOR NAME],MATCH(I79,INVESTOR_LIST[INVESTOR CODE],0),)," ")} -> MINHAJ UDDIN | I79: A00022 | J79: Cash and cash equivalents | K79: 220000 | M79: 0 | Q79: A00022
A80: 2020 | B80: 2 | C80: 20 | D80: =DATE(A80,B80,C80) -> 43881 | E80: =DATE(A80,B80,C80) -> 43881 | G80: C | H80: {=IFERROR(INDEX(INVESTOR_LIST[INVESTOR NAME],MATCH(I80,INVESTOR_LIST[INVESTOR CODE],0),)," ")} -> MINHAJ UDDIN | I80: A00022 | J80: Unit Capital | L80: =K79 -> 220000 | M80: 0 | Q80: A00022
A81: 2020 | B81: 2 | C81: 20 | D81: =DATE(A81,B81,C81) -> 43881 | E81: =DATE(A81,B81,C81) -> 43881 | F81: Bank charge has been charged | G81: C | H81: {=IFERROR(INDEX(INVESTOR_LIST[INVESTOR NAME],MATCH(I81,INVESTOR_LIST[INVESTOR CODE],0),)," ")} | J81: Bank charges and excise duties | K81: 10 | M81: 0
A82: 2020 | B82: 2 | C82: 20 | D82: =DATE(A82,B82,C82) -> 43881 | E82: =DATE(A82,B82,C82) -> 43881 | G82: C | H82: {=IFERROR(INDEX(INVESTOR_LIST[INVESTOR NAME],MATCH(I82,INVESTOR_LIST[INVESTOR CODE],0),)," ")} | J82: Cash and cash equivalents | L82: 10 | M82: 0
A83: 2020 | B83: 2 | C83: 20 | D83: =DATE(A83,B83,C83) -> 43881 | E83: =DATE(A83,B83,C83) -> 43881 | F83: Bank charge has been charged | G83: C | H83: {=IFERROR(INDEX(INVESTOR_LIST[INVESTOR NAME],MATCH(I83,INVESTOR_LIST[INVESTOR CODE],0),)," ")} | J83: Bank charges and excise duties | K83: 10 | M83: 1
A84: 2020 | B84: 2 | C84: 20 | D84: =DATE(A84,B84,C84) -> 43881 | E84: =DATE(A84,B84,C84) -> 43881 | G84: C | H84: {=IFERROR(INDEX(INVESTOR_LIST[INVESTOR NAME],MATCH(I84,INVESTOR_LIST[INVESTOR CODE],0),)," ")} | J84: Cash and cash equivalents | L84: 10 | M84: 0
A85: 2020 | B85: 2 | C85: 26 | D85: =DATE(A85,B85,C85) -> 43887 | E85: =DATE(A85,B85,C85) -> 43887 | F85: Unit Subscription - LUMPSUM | G85: C | H85: {=IFERROR(INDEX(INVESTOR_LIST[INVESTOR NAME],MATCH(I85,INVESTOR_LIST[INVESTOR CODE],0),)," ")} -> CRAB EMPLOYEES GRATUITY FUND | I85: A00024 | J85: Cash and cash equivalents | K85: 250000 | M85: 0 | Q85: A00024
A86: 2020 | B86: 2 | C86: 26 | D86: =DATE(A86,B86,C86) -> 43887 | E86: =DATE(A86,B86,C86) -> 43887 | G86: C | H86: {=IFERROR(INDEX(INVESTOR_LIST[INVESTOR NAME],MATCH(I86,INVESTOR_LIST[INVESTOR CODE],0),)," ")} -> CRAB EMPLOYEES GRATUITY FUND | I86: A00024 | J86: Unit Capital | L86: =K85 -> 250000 | M86: 0 | Q86: A00024
A87: 2020 | B87: 2 | C87: 26 | D87: =DATE(A87,B87,C87) -> 43887 | E87: =DATE(A87,B87,C87) -> 43887 | F87: Unit Subscription - LUMPSUM | G87: C | H87: {=IFERROR(INDEX(INVESTOR_LIST[INVESTOR NAME],MATCH(I87,INVESTOR_LIST[INVESTOR CODE],0),)," ")} -> CRAB EMPLOYEES PROVIDENT FUND | I87: A00023 | J87: Cash and cash equivalents | K87: 250000 | M87: 0 | Q87: A00023
A88: 2020 | B88: 2 | C88: 26 | D88: =DATE(A88,B88,C88) -> 43887 | E88: =DATE(A88,B88,C88) -> 43887 | G88: C | H88: {=IFERROR(INDEX(INVESTOR_LIST[INVESTOR NAME],MATCH(I88,INVESTOR_LIST[INVESTOR CODE],0),)," ")} -> CRAB EMPLOYEES PROVIDENT FUND | I88: A00023 | J88: Unit Capital | L88: =K87 -> 250000 | M88: 0 | Q88: A00023
A89: 2020 | B89: 2 | C89: 26 | D89: =DATE(A89,B89,C89) -> 43887 | E89: =DATE(A89,B89,C89) -> 43887 | F89: Bank charge has been charged | G89: C | H89: {=IFERROR(INDEX(INVESTOR_LIST[INVESTOR NAME],MATCH(I89,INVESTOR_LIST[INVESTOR CODE],0),)," ")} | J89: Bank charges and excise duties | K89: 10 | M89: 0
A90: 2020 | B90: 2 | C90: 26 | D90: =DATE(A90,B90,C90) -> 43887 | E90: =DATE(A90,B90,C90) -> 43887 | G90: C | H90: {=IFERROR(INDEX(INVESTOR_LIST[INVESTOR NAME],MATCH(I90,INVESTOR_LIST[INVESTOR CODE],0),)," ")} | J90: Cash and cash equivalents | L90: 10 | M90: 0
A91: 2020 | B91: 2 | C91: 26 | D91: =DATE(A91,B91,C91) -> 43887 | E91: =DATE(A91,B91,C91) -> 43887 | F91: Bank charge has been charged | G91: C | H91: {=IFERROR(INDEX(INVESTOR_LIST[INVESTOR NAME],MATCH(I91,INVESTOR_LIST[INVESTOR CODE],0),)," ")} | J91: Bank charges and excise duties | K91: 10 | M91: 0
A92: 2020 | B92: 2 | C92: 26 | D92: =DATE(A92,B92,C92) -> 43887 | E92: =DATE(A92,B92,C92) -> 43887 | G92: C | H92: {=IFERROR(INDEX(INVESTOR_LIST[INVESTOR NAME],MATCH(I92,INVESTOR_LIST[INVESTOR CODE],0),)," ")} | J92: Cash and cash equivalents | L92: 10 | M92: 0
A93: 2020 | B93: 2 | C93: 26 | D93: =DATE(A93,B93,C93) -> 43887 | E93: =DATE(A93,B93,C93) -> 43887 | F93: Bank charge has been charged | G93: C | H93: {=IFERROR(INDEX(INVESTOR_LIST[INVESTOR NAME],MATCH(I93,INVESTOR_LIST[INVESTOR CODE],0),)," ")} | J93: Bank charges and excise duties | K93: 25 | M93: 0
A94: 2020 | B94: 2 | C94: 26 | D94: =DATE(A94,B94,C94) -> 43887 | E94: =DATE(A94,B94,C94) -> 43887 | G94: C | H94: {=IFERROR(INDEX(INVESTOR_LIST[INVESTOR NAME],MATCH(I94,INVESTOR_LIST[INVESTOR CODE],0),)," ")} | J94: Cash and cash equivalents | L94: 25 | M94: 0
A95: 2020 | B95: 2 | C95: 27 | D95: =DATE(A95,B95,C95) -> 43888 | E95: =DATE(A95,B95,C95) -> 43888 | F95: Unit Subscription - LUMPSUM | G95: C | H95: {=IFERROR(INDEX(INVESTOR_LIST[INVESTOR NAME],MATCH(I95,INVESTOR_LIST[INVESTOR CODE],0),)," ")} -> MD. BADI-UZ-ZAMAN | I95: A00025 | J95: Cash and cash equivalents | K95: 100000 | M95: 2 | Q95: A00025
A96: 2020 | B96: 2 | C96: 27 | D96: =DATE(A96,B96,C96) -> 43888 | E96: =DATE(A96,B96,C96) -> 43888 | G96: C | H96: {=IFERROR(INDEX(INVESTOR_LIST[INVESTOR NAME],MATCH(I96,INVESTOR_LIST[INVESTOR CODE],0),)," ")} -> MD. BADI-UZ-ZAMAN | I96: A00025 | J96: Unit Capital | L96: =K95 -> 100000 | M96: 0 | Q96: A00025
A97: 2020 | B97: 2 | C97: 27 | D97: =DATE(A97,B97,C97) -> 43888 | E97: =DATE(A97,B97,C97) -> 43888 | F97: Bank charge has been charged | G97: C | H97: {=IFERROR(INDEX(INVESTOR_LIST[INVESTOR NAME],MATCH(I97,INVESTOR_LIST[INVESTOR CODE],0),)," ")} | J97: Bank charges and excise duties | K97: 10 | M97: 0
A98: 2020 | B98: 2 | C98: 27 | D98: =DATE(A98,B98,C98) -> 43888 | E98: =DATE(A98,B98,C98) -> 43888 | G98: C | H98: {=IFERROR(INDEX(INVESTOR_LIST[INVESTOR NAME],MATCH(I98,INVESTOR_LIST[INVESTOR CODE],0),)," ")} | J98: Cash and cash equivalents | L98: 10 | M98: 0
A99: 2020 | B99: 3 | C99: 3 | D99: =DATE(A99,B99,C99) -> 43893 | E99: =DATE(A99,B99,C99) -> 43893 | F99: Unit Subscription - LUMPSUM | G99: C | H99: {=IFERROR(INDEX(INVESTOR_LIST[INVESTOR NAME],MATCH(I99,INVESTOR_LIST[INVESTOR CODE],0),)," ")} -> MD. SHAHIDUL ISLAM | I99: A00027 | J99: Cash and cash equivalents | K99: 500000 | M99: 0 | Q99: A00027
A100: 2020 | B100: 3 | C100: 3 | D100: =DATE(A100,B100,C100) -> 43893 | E100: =DATE(A100,B100,C100) -> 43893 | G100: C | H100: {=IFERROR(INDEX(INVESTOR_LIST[INVESTOR NAME],MATCH(I100,INVESTOR_LIST[INVESTOR CODE],0),)," ")} -> MD. SHAHIDUL ISLAM | I100: A00027 | J100: Unit Capital | L100: =K99 -> 500000 | M100: 0 | Q100: A00027
A101: 2020 | B101: 3 | C101: 3 | D101: =DATE(A101,B101,C101) -> 43893 | E101: =DATE(A101,B101,C101) -> 43893 | F101: Unit Subscription - LUMPSUM | G101: C | H101: {=IFERROR(INDEX(INVESTOR_LIST[INVESTOR NAME],MATCH(I101,INVESTOR_LIST[INVESTOR CODE],0),)," ")} -> FAHMIDA HAQUE | I101: A00026 | J101: Cash and cash equivalents | K101: 500000 | M101: 0 | Q101: A00026
...

Sheet TB-C
A1: Check of Trial Balance | G1: =SUM(H7:H91)-SUM(I7:I91) -> 0.0028882474
A2: Check of Balance Sheet | G2: =BS!C25-BS!C40 -> 0
A3: Check of Cash Balance | G3: =BS!C23-CF!B44 -> -2739690.1
B5: Desired Reporting Period | H5: During the Reporting Period | J5: For Balance Sheet | N5: For Retained Earnings
B6: Year | C6: Month | D6: Day | E6: Value | F6: Value | G6: Accounts | H6: Debit | I6: Credit | J6: Carry Forward Balance | K6: Carry Forward Balance | L6: On date | M6: On date | N6: Debit | O6: Credit
A7: Beginning | B7: 2026 | C7: 1 | D7: 1 | E7: =DATE(B7,C7,D7)-1 -> 46022 | F7: =DATE(B7,C7,D7) -> 46023 | G7: ='Chart of Accounts'!B3 -> Investments in stock | H7: =MAX(0,SUMIFS(Journals!$K$9:$K$1011204,Journals!$D$9:$D$1011204,">"&$E$7,Journals!$D$9:$D$1011204,"<"&$E$8,Journals!$J$9:$J$1011204,"investments in stock")-SUMIFS(Journals!$L$9:$L$1011204,Journals!$D$9:$D$1011204,">"&$E$7,Journals!$D$9:$D$1011204,"<"&$E$8,Journals!$J$9:$J$1011204,"investments in stock")) -> 42662512 | I7: =MAX(0,SUMIFS(Journals!$L$9:$L$1011204,Journals!$D$9:$D$1011204,">"&$E$7,Journals!$D$9:$D$1011204,"<"&$E$8,Journals!$J$9:$J$1011204,"Investments in stock")-SUMIFS(Journals!$K$9:$K$1011204,Journals!$D$9:$D$1011204,">"&$E$7,Journals!$D$9:$D$1011204,"<"&$E$8,Journals!$J$9:$J$1011204,"Investments in stock")) -> 0 | J7: =SUMIFS(Journals!$K$9:$K$1011204,Journals!$D$9:$D$1011204,"<"&$F$7,Journals!$J$9:$J$1011204,"investments in stock")-SUMIFS(Journals!$L$9:$L$1011204,Journals!$D$9:$D$1011204,"<"&$F$7,Journals!$J$9:$J$1011204,"investments in stock") -> 2.0852119e+08 | L7: =J7+H7-I7 -> 2.511837e+08
A8: Ending | B8: 2026 | C8: 12 | D8: 31 | E8: =DATE(B8,C8,D8)+1 -> 46388 | F8: =DATE(B8,C8,D8) -> 46387 | G8: ='Chart of Accounts'!B4 -> Interest Receivables from Bank A/C | H8: =MAX(0,SUMIFS(Journals!$K$9:$K$1011204,Journals!$D$9:$D$1011204,">"&$E$7,Journals!$D$9:$D$1011204,"<"&$E$8,Journals!$J$9:$J$1011204,"Interest Receivables from Bank A/C")-SUMIFS(Journals!$L$9:$L$1011204,Journals!$D$9:$D$1011204,">"&$E$7,Journals!$D$9:$D$1011204,"<"&$E$8,Journals!$J$9:$J$1011204,"Interest Receivables from Bank A/C")) -> 113337.69 | I8: =MAX(0,SUMIFS(Journals!$L$9:$L$1011204,Journals!$D$9:$D$1011204,">"&$E$7,Journals!$D$9:$D$1011204,"<"&$E$8,Journals!$J$9:$J$1011204,"Interest Receivables from Bank A/C")-SUMIFS(Journals!$K$9:$K$1011204,Journals!$D$9:$D$1011204,">"&$E$7,Journals!$D$9:$D$1011204,"<"&$E$8,Journals!$J$9:$J$1011204,"Interest Receivables from Bank A/C")) -> 0 | J8: =SUMIFS(Journals!$K$9:$K$1011204,Journals!$D$9:$D$1011204,"<"&$F$7,Journals!$J$9:$J$1011204,"Interest Receivables from Bank A/C")-SUMIFS(Journals!$L$9:$L$1011204,Journals!$D$9:$D$1011204,"<"&$F$7,Journals!$J$9:$J$1011204,"Interest Receivables from Bank A/C") -> 7601.57 | L8: =J8+H8-I8 -> 120939.26 | P8: 463070.35 | Q8: =L8-P8 -> -342131.09
G9: ='Chart of Accounts'!B5 -> Preliminary & issue expenses | H9: =MAX(0,SUMIFS(Journals!$K$9:$K$1011204,Journals!$D$9:$D$1011204,">"&$E$7,Journals!$D$9:$D$1011204,"<"&$E$8,Journals!$J$9:$J$1011204,"Preliminary & issue expenses")-SUMIFS(Journals!$L$9:$L$1011204,Journals!$D$9:$D$1011204,">"&$E$7,Journals!$D$9:$D$1011204,"<"&$E$8,Journals!$J$9:$J$1011204,"Preliminary & issue expenses")) -> 0 | I9: =MAX(0,SUMIFS(Journals!$L$9:$L$1011204,Journals!$D$9:$D$1011204,">"&$E$7,Journals!$D$9:$D$1011204,"<"&$E$8,Journals!$J$9:$J$1011204,"Preliminary & issue expenses")-SUMIFS(Journals!$K$9:$K$1011204,Journals!$D$9:$D$1011204,">"&$E$7,Journals!$D$9:$D$1011204,"<"&$E$8,Journals!$J$9:$J$1011204,"Preliminary & issue expenses")) -> 32967.033 | J9: =SUMIFS(Journals!$K$9:$K$1011204,Journals!$D$9:$D$1011204,"<"&$F$7,Journals!$J$9:$J$1011204,"Preliminary & issue expenses")-SUMIFS(Journals!$L$9:$L$1011204,Journals!$D$9:$D$1011204,"<"&$F$7,Journals!$J$9:$J$1011204,"Preliminary & issue expenses") -> 173862.83 | L9: =J9+H9-I9 -> 140895.8
G10: ='Chart of Accounts'!B6 -> Accrued Management Fee | H10: =SUMIFS(Journals!$K$9:$K$1011204,Journals!$D$9:$D$1011204,">"&$E$7,Journals!$D$9:$D$1011204,"<"&$E$8,Journals!$J$9:$J$1011204,"Accrued Management Fee") -> 1766038.9 | I10: =MAX(0,SUMIFS(Journals!$L$9:$L$1011204,Journals!$D$9:$D$1011204,">"&$E$7,Journals!$D$9:$D$1011204,"<"&$E$8,Journals!$J$9:$J$1011204,"Accrued Management Fee")) -> 1199767.6 | K10: =SUMIFS(Journals!$L$9:$L$1011204,Journals!$D$9:$D$1011204,"<"&$F$7,Journals!$J$9:$J$1011204,"Accrued Management Fee")-SUMIFS(Journals!$K$9:$K$1011204,Journals!$D$9:$D$1011204,"<"&$F$7,Journals!$J$9:$J$1011204,"Accrued Management Fee") -> 2956354.5 | M10: =K10+I10-H10 -> 2390083.3
G11: ='Chart of Accounts'!B7 -> Accrued Trustee Fee | H11: =MAX(0,SUMIFS(Journals!$K$9:$K$1011204,Journals!$D$9:$D$1011204,">"&$E$7,Journals!$D$9:$D$1011204,"<"&$E$8,Journals!$J$9:$J$1011204,"accrued trustee fee")-SUMIFS(Journals!$L$9:$L$1011204,Journals!$D$9:$D$1011204,">"&$E$7,Journals!$D$9:$D$1011204,"<"&$E$8,Journals!$J$9:$J$1011204,"accrued trustee fee")) -> 0 | I11: =MAX(0,SUMIFS(Journals!$L$9:$L$1011204,Journals!$D$9:$D$1011204,">"&$E$7,Journals!$D$9:$D$1011204,"<"&$E$8,Journals!$J$9:$J$1011204,"accrued trustee fee")-SUMIFS(Journals!$K$9:$K$1011204,Journals!$D$9:$D$1011204,">"&$E$7,Journals!$D$9:$D$1011204,"<"&$E$8,Journals!$J$9:$J$1011204,"accrued trustee fee")) -> 98794.008 | K11: =SUMIFS(Journals!$L$9:$L$1011204,Journals!$D$9:$D$1011204,"<"&$F$7,Journals!$J$9:$J$1011204,"Accrued Trustee Fee")-SUMIFS(Journals!$K$9:$K$1011204,Journals!$D$9:$D$1011204,"<"&$F$7,Journals!$J$9:$J$1011204,"Accrued Trustee Fee") -> 106016.66 | M11: =K11+I11-H11 -> 204810.67
G12: ='Chart of Accounts'!B8 -> Accrued Custodian Fee | H12: =MAX(0,SUMIFS(Journals!$K$9:$K$1011204,Journals!$D$9:$D$1011204,">"&$E$7,Journals!$D$9:$D$1011204,"<"&$E$8,Journals!$J$9:$J$1011204,"accrued custodian fee")-SUMIFS(Journals!$L$9:$L$1011204,Journals!$D$9:$D$1011204,">"&$E$7,Journals!$D$9:$D$1011204,"<"&$E$8,Journals!$J$9:$J$1011204,"accrued custodian fee")) -> 0 | I12: =MAX(0,SUMIFS(Journals!$L$9:$L$1011204,Journals!$D$9:$D$1011204,">"&$E$7,Journals!$D$9:$D$1011204,"<"&$E$8,Journals!$J$9:$J$1011204,"accrued custodian fee")-SUMIFS(Journals!$K$9:$K$1011204,Journals!$D$9:$D$1011204,">"&$E$7,Journals!$D$9:$D$1011204,"<"&$E$8,Journals!$J$9:$J$1011204,"accrued custodian fee")) -> 0 | K12: =SUMIFS(Journals!$L$9:$L$1011204,Journals!$D$9:$D$1011204,"<"&$F$7,Journals!$J$9:$J$1011204,"Accrued Custodian Fee")-SUMIFS(Journals!$K$9:$K$1011204,Journals!$D$9:$D$1011204,"<"&$F$7,Journals!$J$9:$J$1011204,"Accrued Custodian Fee") -> 0 | M12: =K12+I12-H12 -> 0
G13: ='Chart of Accounts'!B9 -> Accrued BSEC fee | H13: =MAX(0,SUMIFS(Journals!$K$9:$K$1011204,Journals!$D$9:$D$1011204,">"&$E$7,Journals!$D$9:$D$1011204,"<"&$E$8,Journals!$J$9:$J$1011204,"accrued bsec fee")-SUMIFS(Journals!$L$9:$L$1011204,Journals!$D$9:$D$1011204,">"&$E$7,Journals!$D$9:$D$1011204,"<"&$E$8,Journals!$J$9:$J$1011204,"accrued bsec fee")) -> 0 | I13: =MAX(0,SUMIFS(Journals!$L$9:$L$1011204,Journals!$D$9:$D$1011204,">"&$E$7,Journals!$D$9:$D$1011204,"<"&$E$8,Journals!$J$9:$J$1011204,"accrued bsec fee")-SUMIFS(Journals!$K$9:$K$1011204,Journals!$D$9:$D$1011204,">"&$E$7,Journals!$D$9:$D$1011204,"<"&$E$8,Journals!$J$9:$J$1011204,"accrued bsec fee")) -> 0 | K13: =SUMIFS(Journals!$L$9:$L$1011204,Journals!$D$9:$D$1011204,"<"&$F$7,Journals!$J$9:$J$1011204,"accrued bsec fee")-SUMIFS(Journals!$K$9:$K$1011204,Journals!$D$9:$D$1011204,"<"&$F$7,Journals!$J$9:$J$1011204,"accrued bsec fee") -> 0 | M13: =K13+I13-H13 -> 0
G14: ='Chart of Accounts'!B10 -> Accrued Audit Fee | H14: =MAX(0,SUMIFS(Journals!$K$9:$K$1011204,Journals!$D$9:$D$1011204,">"&$E$7,Journals!$D$9:$D$1011204,"<"&$E$8,Journals!$J$9:$J$1011204,"accrued audit fee")) -> 46000 | I14: =MAX(0,SUMIFS(Journals!$L$9:$L$1011204,Journals!$D$9:$D$1011204,">"&$E$7,Journals!$D$9:$D$1011204,"<"&$E$8,Journals!$J$9:$J$1011204,"accrued audit fee")) -> 0 | K14: =SUMIFS(Journals!$L$9:$L$1011204,Journals!$D$9:$D$1011204,"<"&$F$7,Journals!$J$9:$J$1011204,"accrued audit fee")-SUMIFS(Journals!$K$9:$K$1011204,Journals!$D$9:$D$1011204,"<"&$F$7,Journals!$J$9:$J$1011204,"accrued audit fee") -> 45999.997 | M14: =K14+I14-H14 -> -0.0033333334
G15: ='Chart of Accounts'!B11 -> Accrued CDBL Fee | H15: =MAX(0,SUMIFS(Journals!$K$9:$K$1011204,Journals!$D$9:$D$1011204,">"&$E$7,Journals!$D$9:$D$1011204,"<"&$E$8,Journals!$J$9:$J$1011204,"accrued CDBL fee")-SUMIFS(Journals!$L$9:$L$1011204,Journals!$D$9:$D$1011204,">"&$E$7,Journals!$D$9:$D$1011204,"<"&$E$8,Journals!$J$9:$J$1011204,"accrued CDBL fee")) -> 0 | I15: =MAX(0,SUMIFS(Journals!$L$9:$L$1011204,Journals!$D$9:$D$1011204,">"&$E$7,Journals!$D$9:$D$1011204,"<"&$E$8,Journals!$J$9:$J$1011204,"accrued CDBL fee")-SUMIFS(Journals!$K$9:$K$1011204,Journals!$D$9:$D$1011204,">"&$E$7,Journals!$D$9:$D$1011204,"<"&$E$8,Journals!$J$9:$J$1011204,"accrued CDBL fee")) -> 0 | K15: =SUMIFS(Journals!$L$9:$L$1011204,Journals!$D$9:$D$1011204,"<"&$F$7,Journals!$J$9:$J$1011204,"accrued cdbl fee")-SUMIFS(Journals!$K$9:$K$1011204,Journals!$D$9:$D$1011204,"<"&$F$7,Journals!$J$9:$J$1011204,"accrued cdbl fee") -> 0 | M15: =K15+I15-H15 -> 0
G16: ='Chart of Accounts'!B12 -> Fixed Deposit Receipts (FDR) | H16: =MAX(0,SUMIFS(Journals!$K$9:$K$1011204,Journals!$D$9:$D$1011204,">"&$E$7,Journals!$D$9:$D$1011204,"<"&$E$8,Journals!$J$9:$J$1011204,"Fixed Deposit Receipts (FDR)")-SUMIFS(Journals!$L$9:$L$1011204,Journals!$D$9:$D$1011204,">"&$E$7,Journals!$D$9:$D$1011204,"<"&$E$8,Journals!$J$9:$J$1011204,"Fixed Deposit Receipts (FDR)")) -> 0 | I16: =MAX(0,SUMIFS(Journals!$L$9:$L$1011204,Journals!$D$9:$D$1011204,">"&$E$7,Journals!$D$9:$D$1011204,"<"&$E$8,Journals!$J$9:$J$1011204,"Fixed Deposit Receipts (FDR)")-SUMIFS(Journals!$K$9:$K$1011204,Journals!$D$9:$D$1011204,">"&$E$7,Journals!$D$9:$D$1011204,"<"&$E$8,Journals!$J$9:$J$1011204,"Fixed Deposit Receipts (FDR)")) -> 6000000 | J16: =SUMIFS(Journals!$K$9:$K$1011204,Journals!$D$9:$D$1011204,"<"&$F$7,Journals!$J$9:$J$1011204,"Fixed Deposit Receipts (FDR)")-SUMIFS(Journals!$L$9:$L$1011204,Journals!$D$9:$D$1011204,"<"&$F$7,Journals!$J$9:$J$1011204,"Fixed Deposit Receipts (FDR)") -> 6000000 | L16: =J16+H16-I16 -> 0
G17: ='Chart of Accounts'!B13 -> Cash and cash equivalents | H17: =MAX(0,SUMIFS(Journals!$K$9:$K$1011204,Journals!$D$9:$D$1011204,">"&$E$7,Journals!$D$9:$D$1011204,"<"&$E$8,Journals!$J$9:$J$1011204,"Cash and cash equivalents")-SUMIFS(Journals!$L$9:$L$1011204,Journals!$D$9:$D$1011204,">"&$E$7,Journals!$D$9:$D$1011204,"<"&$E$8,Journals!$J$9:$J$1011204,"Cash and cash equivalents")) -> 0 | I17: =MAX(0,SUMIFS(Journals!$L$9:$L$1011204,Journals!$D$9:$D$1011204,">"&$E$7,Journals!$D$9:$D$1011204,"<"&$E$8,Journals!$J$9:$J$1011204,"Cash and cash equivalents")-SUMIFS(Journals!$K$9:$K$1011204,Journals!$D$9:$D$1011204,">"&$E$7,Journals!$D$9:$D$1011204,"<"&$E$8,Journals!$J$9:$J$1011204,"Cash and cash equivalents")) -> 1311849.8 | J17: =SUMIFS(Journals!$K$9:$K$1011204,Journals!$D$9:$D$1011204,"<"&$F$7,Journals!$J$9:$J$1011204,"Cash and cash equivalents")-SUMIFS(Journals!$L$9:$L$1011204,Journals!$D$9:$D$1011204,"<"&$F$7,Journals!$J$9:$J$1011204,"Cash and cash equivalents") -> 1784563.8 | L17: =J17+H17-I17 -> 472714.03
G18: ='Chart of Accounts'!B14 -> Unit Capital | H18: =SUMIFS(Journals!$K$9:$K$1011204,Journals!$D$9:$D$1011204,">"&$E$7,Journals!$D$9:$D$1011204,"<"&$E$8,Journals!$J$9:$J$1011204,"unit capital") -> 15641800 | I18: =MAX(0,SUMIFS(Journals!$L$9:$L$1011204,Journals!$D$9:$D$1011204,">"&$E$7,Journals!$D$9:$D$1011204,"<"&$E$8,Journals!$J$9:$J$1011204,"unit capital")) -> 41360240 | K18: =SUMIFS(Journals!$L$9:$L$1011204,Journals!$D$9:$D$1011204,"<"&$F$7,Journals!$J$9:$J$1011204,"unit capital")-SUMIFS(Journals!$K$9:$K$1011204,Journals!$D$9:$D$1011204,"<"&$F$7,Journals!$J$9:$J$1011204,"unit capital") -> 156111010 | M18: =K18+I18-H18 -> 181829450
G19: ='Chart of Accounts'!B15 -> Unit premium reserve | H19: =SUMIFS(Journals!$K$9:$K$1011204,Journals!$D$9:$D$1011204,">"&$E$7,Journals!$D$9:$D$1011204,"<"&$E$8,Journals!$J$9:$J$1011204,"unit premium reserve") -> 7711214.3 | I19: =SUMIFS(Journals!$L$9:$L$1011204,Journals!$D$9:$D$1011204,">"&$E$7,Journals!$D$9:$D$1011204,"<"&$E$8,Journals!$J$9:$J$1011204,"unit premium reserve") -> 19849776 | K19: =SUMIFS(Journals!$L$9:$L$1011204,Journals!$D$9:$D$1011204,"<"&$F$7,Journals!$J$9:$J$1011204,"unit premium reserve")-SUMIFS(Journals!$K$9:$K$1011204,Journals!$D$9:$D$1011204,"<"&$F$7,Journals!$J$9:$J$1011204,"unit premium reserve") -> 10427123 | M19: =K19+I19-H19 -> 22565685
G20: ='Chart of Accounts'!B16 -> Interest income | H20: =MAX(0,SUMIFS(Journals!$K$9:$K$1011204,Journals!$D$9:$D$1011204,">"&$E$7,Journals!$D$9:$D$1011204,"<"&$E$8,Journals!$J$9:$J$1011204,"interest income")-SUMIFS(Journals!$L$9:$L$1011204,Journals!$D$9:$D$1011204,">"&$E$7,Journals!$D$9:$D$1011204,"<"&$E$8,Journals!$J$9:$J$1011204,"interest income")) -> 0 | I20: =MAX(0,SUMIFS(Journals!$L$9:$L$1011204,Journals!$D$9:$D$1011204,">"&$E$7,Journals!$D$9:$D$1011204,"<"&$E$8,Journals!$J$9:$J$1011204,"interest income")-SUMIFS(Journals!$K$9:$K$1011204,Journals!$D$9:$D$1011204,">"&$E$7,Journals!$D$9:$D$1011204,"<"&$E$8,Journals!$J$9:$J$1011204,"interest income")) -> 0 | O20: =SUMIFS(Journals!$L$9:$L$1011204,Journals!$D$9:$D$1011204,"<"&$F$7,Journals!$J$9:$J$1011204,"interest income")-SUMIFS(Journals!$K$9:$K$1011204,Journals!$D$9:$D$1011204,"<"&$F$7,Journals!$J$9:$J$1011204,"interest income") -> 16114040
G21: Interest income from FDR | H21: =MAX(0,SUMIFS(Journals!$K$9:$K$1011204,Journals!$D$9:$D$1011204,">"&$E$7,Journals!$D$9:$D$1011204,"<"&$E$8,Journals!$J$9:$J$1011204,"Interest income from FDR")-SUMIFS(Journals!$L$9:$L$1011204,Journals!$D$9:$D$1011204,">"&$E$7,Journals!$D$9:$D$1011204,"<"&$E$8,Journals!$J$9:$J$1011204,"Interest income from FDR")) -> 0 | I21: =MAX(0,SUMIFS(Journals!$L$9:$L$1011204,Journals!$D$9:$D$1011204,">"&$E$7,Journals!$D$9:$D$1011204,"<"&$E$8,Journals!$J$9:$J$1011204,"Interest income from FDR")-SUMIFS(Journals!$K$9:$K$1011204,Journals!$D$9:$D$1011204,">"&$E$7,Journals!$D$9:$D$1011204,"<"&$E$8,Journals!$J$9:$J$1011204,"Interest income from FDR")) -> 74749.798 | O21: =SUMIFS(Journals!$L$9:$L$1011204,Journals!$D$9:$D$1011204,"<"&$F$7,Journals!$J$9:$J$1011204,"Interest income from FDR")-SUMIFS(Journals!$K$9:$K$1011204,Journals!$D$9:$D$1011204,"<"&$F$7,Journals!$J$9:$J$1011204,"Interest income from FDR") -> 0
G22: Interest income from Renata Pref. Share | H22: =MAX(0,SUMIFS(Journals!$K$9:$K$1011204,Journals!$D$9:$D$1011204,">"&$E$7,Journals!$D$9:$D$1011204,"<"&$E$8,Journals!$J$9:$J$1011204,"Interest income from Renata Pref. Share")-SUMIFS(Journals!$L$9:$L$1011204,Journals!$D$9:$D$1011204,">"&$E$7,Journals!$D$9:$D$1011204,"<"&$E$8,Journals!$J$9:$J$1011204,"Interest income from Renata Pref. Share")) -> 0 | I22: =MAX(0,SUMIFS(Journals!$L$9:$L$1011204,Journals!$D$9:$D$1011204,">"&$E$7,Journals!$D$9:$D$1011204,"<"&$E$8,Journals!$J$9:$J$1011204,"Interest income from Renata Pref. Share")-SUMIFS(Journals!$K$9:$K$1011204,Journals!$D$9:$D$1011204,">"&$E$7,Journals!$D$9:$D$1011204,"<"&$E$8,Journals!$J$9:$J$1011204,"Interest income from Renata Pref. Share")) -> 519576.92 | O22: =SUMIFS(Journals!$L$9:$L$1011204,Journals!$D$9:$D$1011204,"<"&$F$7,Journals!$J$9:$J$1011204,"Interest income from Renata Pref. Share")-SUMIFS(Journals!$K$9:$K$1011204,Journals!$D$9:$D$1011204,"<"&$F$7,Journals!$J$9:$J$1011204,"Interest income from Renata Pref. Share") -> 402053.57
G23: Interest income from Bank Acc. | H23: =MAX(0,SUMIFS(Journals!$K$9:$K$1011204,Journals!$D$9:$D$1011204,">"&$E$7,Journals!$D$9:$D$1011204,"<"&$E$8,Journals!$J$9:$J$1011204,"Interest income from Bank Acc.")-SUMIFS(Journals!$L$9:$L$1011204,Journals!$D$9:$D$1011204,">"&$E$7,Journals!$D$9:$D$1011204,"<"&$E$8,Journals!$J$9:$J$1011204,"Interest income from Bank Acc.")) -> 0 | I23: =MAX(0,SUMIFS(Journals!$L$9:$L$1011204,Journals!$D$9:$D$1011204,">"&$E$7,Journals!$D$9:$D$1011204,"<"&$E$8,Journals!$J$9:$J$1011204,"Interest income from Bank Acc.")-SUMIFS(Journals!$K$9:$K$1011204,Journals!$D$9:$D$1011204,">"&$E$7,Journals!$D$9:$D$1011204,"<"&$E$8,Journals!$J$9:$J$1011204,"Interest income from Bank Acc.")) -> 113337.69 | O23: =SUMIFS(Journals!$L$9:$L$1011204,Journals!$D$9:$D$1011204,"<"&$F$7,Journals!$J$9:$J$1011204,"Interest income from Bank Acc.")-SUMIFS(Journals!$K$9:$K$1011204,Journals!$D$9:$D$1011204,"<"&$F$7,Journals!$J$9:$J$1011204,"Interest income from Bank Acc.") -> 0
G24: Interest income from T-Bill | H24: =MAX(0,SUMIFS(Journals!$K$9:$K$1011204,Journals!$D$9:$D$1011204,">"&$E$7,Journals!$D$9:$D$1011204,"<"&$E$8,Journals!$J$9:$J$1011204,"Interest income from T-Bill")-SUMIFS(Journals!$L$9:$L$1011204,Journals!$D$9:$D$1011204,">"&$E$7,Journals!$D$9:$D$1011204,"<"&$E$8,Journals!$J$9:$J$1011204,"Interest income from T-Bill")) -> 0 | I24: =MAX(0,SUMIFS(Journals!$L$9:$L$1011204,Journals!$D$9:$D$1011204,">"&$E$7,Journals!$D$9:$D$1011204,"<"&$E$8,Journals!$J$9:$J$1011204,"Interest income from T-Bill")-SUMIFS(Journals!$K$9:$K$1011204,Journals!$D$9:$D$1011204,">"&$E$7,Journals!$D$9:$D$1011204,"<"&$E$8,Journals!$J$9:$J$1011204,"Interest income from T-Bill")) -> 0 | O24: =SUMIFS(Journals!$L$9:$L$1011204,Journals!$D$9:$D$1011204,"<"&$F$7,Journals!$J$9:$J$1011204,"Interest income from T-Bill")-SUMIFS(Journals!$K$9:$K$1011204,Journals!$D$9:$D$1011204,"<"&$F$7,Journals!$J$9:$J$1011204,"Interest income from T-Bill") -> 0
G25: Interest income from T-Bond | H25: =MAX(0,SUMIFS(Journals!$K$9:$K$1011204,Journals!$D$9:$D$1011204,">"&$E$7,Journals!$D$9:$D$1011204,"<"&$E$8,Journals!$J$9:$J$1011204,"Interest income from T-Bond")-SUMIFS(Journals!$L$9:$L$1011204,Journals!$D$9:$D$1011204,">"&$E$7,Journals!$D$9:$D$1011204,"<"&$E$8,Journals!$J$9:$J$1011204,"Interest income from T-Bond")) -> 0 | I25: =MAX(0,SUMIFS(Journals!$L$9:$L$1011204,Journals!$D$9:$D$1011204,">"&$E$7,Journals!$D$9:$D$1011204,"<"&$E$8,Journals!$J$9:$J$1011204,"Interest income from T-Bond")-SUMIFS(Journals!$K$9:$K$1011204,Journals!$D$9:$D$1011204,">"&$E$7,Journals!$D$9:$D$1011204,"<"&$E$8,Journals!$J$9:$J$1011204,"Interest income from T-Bond")) -> 0 | O25: =SUMIFS(Journals!$L$9:$L$1011204,Journals!$D$9:$D$1011204,"<"&$F$7,Journals!$J$9:$J$1011204,"Interest income from T-Bond")-SUMIFS(Journals!$K$9:$K$1011204,Journals!$D$9:$D$1011204,"<"&$F$7,Journals!$J$9:$J$1011204,"Interest income from T-Bond") -> 0
G26: ='Chart of Accounts'!B22 -> Bank charges and excise duties | H26: =MAX(0,SUMIFS(Journals!$K$9:$K$1011204,Journals!$D$9:$D$1011204,">"&$E$7,Journals!$D$9:$D$1011204,"<"&$E$8,Journals!$J$9:$J$1011204,"Bank charges and excise duties")-SUMIFS(Journals!$L$9:$L$1011204,Journals!$D$9:$D$1011204,">"&$E$7,Journals!$D$9:$D$1011204,"<"&$E$8,Journals!$J$9:$J$1011204,"Bank charges and excise duties")) -> 26469 | I26: =MAX(0,SUMIFS(Journals!$L$9:$L$1011204,Journals!$D$9:$D$1011204,">"&$E$7,Journals!$D$9:$D$1011204,"<"&$E$8,Journals!$J$9:$J$1011204,"Bank charges and excise duties")-SUMIFS(Journals!$K$9:$K$1011204,Journals!$D$9:$D$1011204,">"&$E$7,Journals!$D$9:$D$1011204,"<"&$E$8,Journals!$J$9:$J$1011204,"Bank charges and excise duties")) -> 0 | N26: =SUMIFS(Journals!$K$9:$K$1011204,Journals!$D$9:$D$1011204,"<"&$F$7,Journals!$J$9:$J$1011204,"Bank charges and excise duties")-SUMIFS(Journals!$L$9:$L$1011204,Journals!$D$9:$D$1011204,"<"&$F$7,Journals!$J$9:$J$1011204,"Bank charges and excise duties") -> 548004.57
G27: ='Chart of Accounts'!B23 -> Brokerage commission | H27: =MAX(0,SUMIFS(Journals!$K$9:$K$1011204,Journals!$D$9:$D$1011204,">"&$E$7,Journals!$D$9:$D$1011204,"<"&$E$8,Journals!$J$9:$J$1011204,"brokerage commission")-SUMIFS(Journals!$L$9:$L$1011204,Journals!$D$9:$D$1011204,">"&$E$7,Journals!$D$9:$D$1011204,"<"&$E$8,Journals!$J$9:$J$1011204,"brokerage commission")) -> 485345.52 | I27: =MAX(0,SUMIFS(Journals!$L$9:$L$1011204,Journals!$D$9:$D$1011204,">"&$E$7,Journals!$D$9:$D$1011204,"<"&$E$8,Journals!$J$9:$J$1011204,"brokerage commission")-SUMIFS(Journals!$K$9:$K$1011204,Journals!$D$9:$D$1011204,">"&$E$7,Journals!$D$9:$D$1011204,"<"&$E$8,Journals!$J$9:$J$1011204,"brokerage commission")) -> 0 | N27: =SUMIFS(Journals!$K$9:$K$1011204,Journals!$D$9:$D$1011204,"<"&$F$7,Journals!$J$9:$J$1011204,"brokerage commission")-SUMIFS(Journals!$L$9:$L$1011204,Journals!$D$9:$D$1011204,"<"&$F$7,Journals!$J$9:$J$1011204,"brokerage commission") -> 3755798.7
G28: ='Chart of Accounts'!B24 -> Unrealized gain on securities | H28: =MAX(0,SUMIFS(Journals!$K$9:$K$1011204,Journals!$D$9:$D$1011204,">"&$E$7,Journals!$D$9:$D$1011204,"<"&$E$8,Journals!$J$9:$J$1011204,"Unrealized gain on securities")-SUMIFS(Journals!$L$9:$L$1011204,Journals!$D$9:$D$1011204,">"&$E$7,Journals!$D$9:$D$1011204,"<"&$E$8,Journals!$J$9:$J$1011204,"Unrealized gain on securities")) -> 0 | I28: =MAX(0,SUMIFS(Journals!$L$9:$L$1011204,Journals!$D$9:$D$1011204,">"&$E$7,Journals!$D$9:$D$1011204,"<"&$E$8,Journals!$J$9:$J$1011204,"Unrealized gain on securities")-SUMIFS(Journals!$K$9:$K$1011204,Journals!$D$9:$D$1011204,">"&$E$7,Journals!$D$9:$D$1011204,"<"&$E$8,Journals!$J$9:$J$1011204,"Unrealized gain on securities")) -> 10155077 | O28: =SUMIFS(Journals!$L$9:$L$1011204,Journals!$D$9:$D$1011204,"<"&$F$7,Journals!$J$9:$J$1011204,"unrealized gain on securities")-SUMIFS(Journals!$K$9:$K$1011204,Journals!$D$9:$D$1011204,"<"&$F$7,Journals!$J$9:$J$1011204,"unrealized gain on securities") -> 91188891
G29: Unrealized gain on T-Bill | H29: =MAX(0,SUMIFS(Journals!$K$9:$K$1011204,Journals!$D$9:$D$1011204,">"&$E$7,Journals!$D$9:$D$1011204,"<"&$E$8,Journals!$J$9:$J$1011204,"Unrealized gain on T-Bill")-SUMIFS(Journals!$L$9:$L$1011204,Journals!$D$9:$D$1011204,">"&$E$7,Journals!$D$9:$D$1011204,"<"&$E$8,Journals!$J$9:$J$1011204,"Unrealized gain on T-Bill")) -> 0 | I29: =MAX(0,SUMIFS(Journals!$L$9:$L$1011204,Journals!$D$9:$D$1011204,">"&$E$7,Journals!$D$9:$D$1011204,"<"&$E$8,Journals!$J$9:$J$1011204,"Unrealized gain on T-Bill")-SUMIFS(Journals!$K$9:$K$1011204,Journals!$D$9:$D$1011204,">"&$E$7,Journals!$D$9:$D$1011204,"<"&$E$8,Journals!$J$9:$J$1011204,"Unrealized gain on T-Bill")) -> 0 | O29: =SUMIFS(Journals!$L$9:$L$1011204,Journals!$D$9:$D$1011204,"<"&$F$7,Journals!$J$9:$J$1011204,"Unrealized gain on T-Bill")-SUMIFS(Journals!$K$9:$K$1011204,Journals!$D$9:$D$1011204,"<"&$F$7,Journals!$J$9:$J$1011204,"Unrealized gain on T-Bill") -> 0
G30: Unrealized gain on T-Bond | H30: =MAX(0,SUMIFS(Journals!$K$9:$K$1011204,Journals!$D$9:$D$1011204,">"&$E$7,Journals!$D$9:$D$1011204,"<"&$E$8,Journals!$J$9:$J$1011204,"Unrealized gain on T-Bond")-SUMIFS(Journals!$L$9:$L$1011204,Journals!$D$9:$D$1011204,">"&$E$7,Journals!$D$9:$D$1011204,"<"&$E$8,Journals!$J$9:$J$1011204,"Unrealized gain on T-Bond")) -> 0 | I30: =MAX(0,SUMIFS(Journals!$L$9:$L$1011204,Journals!$D$9:$D$1011204,">"&$E$7,Journals!$D$9:$D$1011204,"<"&$E$8,Journals!$J$9:$J$1011204,"Unrealized gain on T-Bond")-SUMIFS(Journals!$K$9:$K$1011204,Journals!$D$9:$D$1011204,">"&$E$7,Journals!$D$9:$D$1011204,"<"&$E$8,Journals!$J$9:$J$1011204,"Unrealized gain on T-Bond")) -> 0 | O30: =SUMIFS(Journals!$L$9:$L$1011204,Journals!$D$9:$D$1011204,"<"&$F$7,Journals!$J$9:$J$1011204,"Unrealized gain on T-Bond")-SUMIFS(Journals!$K$9:$K$1011204,Journals!$D$9:$D$1011204,"<"&$F$7,Journals!$J$9:$J$1011204,"Unrealized gain on T-Bond") -> 0
G31: ='Chart of Accounts'!B27 -> Unrealized loss on securities | H31: =MAX(0,SUMIFS(Journals!$K$9:$K$1011204,Journals!$D$9:$D$1011204,">"&$E$7,Journals!$D$9:$D$1011204,"<"&$E$8,Journals!$J$9:$J$1011204,"Unrealized loss on securities")-SUMIFS(Journals!$L$9:$L$1011204,Journals!$D$9:$D$1011204,">"&$E$7,Journals!$D$9:$D$1011204,"<"&$E$8,Journals!$J$9:$J$1011204,"Unrealized loss on securities")) -> 0 | I31: =MAX(0,SUMIFS(Journals!$L$9:$L$1011204,Journals!$D$9:$D$1011204,">"&$E$7,Journals!$D$9:$D$1011204,"<"&$E$8,Journals!$J$9:$J$1011204,"Unrealized loss on securities")-SUMIFS(Journals!$K$9:$K$1011204,Journals!$D$9:$D$1011204,">"&$E$7,Journals!$D$9:$D$1011204,"<"&$E$8,Journals!$J$9:$J$1011204,"Unrealized loss on securities")) -> 0 | N31: =SUMIFS(Journals!K9:K1011204,Journals!D9:D1011204,"<"&F7,Journals!J9:J1011204,"unrealized loss on securities")-SUMIFS(Journals!L9:L1011204,Journals!D9:D1011204,"<"&F7,Journals!J9:J1011204,"unrealized loss on securities") -> 87355603
G32: ='Chart of Accounts'!B28 -> Amortization of preliminary and issue expense | H32: =MAX(0,SUMIFS(Journals!$K$9:$K$1011204,Journals!$D$9:$D$1011204,">"&$E$7,Journals!$D$9:$D$1011204,"<"&$E$8,Journals!$J$9:$J$1011204,"Amortization of preliminary and issue expense")-SUMIFS(Journals!$L$9:$L$1011204,Journals!$D$9:$D$1011204,">"&$E$7,Journals!$D$9:$D$1011204,"<"&$E$8,Journals!$J$9:$J$1011204,"Amortization of preliminary and issue expense")) -> 32967.033 | I32: =MAX(0,SUMIFS(Journals!$L$9:$L$1011204,Journals!$D$9:$D$1011204,">"&$E$7,Journals!$D$9:$D$1011204,"<"&$E$8,Journals!$J$9:$J$1011204,"Amortization of preliminary and issue expense")-SUMIFS(Journals!$K$9:$K$1011204,Journals!$D$9:$D$1011204,">"&$E$7,Journals!$D$9:$D$1011204,"<"&$E$8,Journals!$J$9:$J$1011204,"Amortization of preliminary and issue expense")) -> 0 | N32: =SUMIFS(Journals!$K$9:$K$1011204,Journals!$D$9:$D$1011204,"<"&$F$7,Journals!$J$9:$J$1011204,"Amortization of preliminary and issue expense")-SUMIFS(Journals!$L$9:$L$1011204,Journals!$D$9:$D$1011204,"<"&$F$7,Journals!$J$9:$J$1011204,"Amortization of preliminary and issue expense") -> 826137.17
G33: ='Chart of Accounts'!B29 -> Management Fee | H33: =MAX(0,SUMIFS(Journals!$K$9:$K$1011204,Journals!$D$9:$D$1011204,">"&$E$7,Journals!$D$9:$D$1011204,"<"&$E$8,Journals!$J$9:$J$1011204,"management fee")-SUMIFS(Journals!$L$9:$L$1011204,Journals!$D$9:$D$1011204,">"&$E$7,Journals!$D$9:$D$1011204,"<"&$E$8,Journals!$J$9:$J$1011204,"management fee")) -> 1199767.6 | I33: =MAX(0,SUMIFS(Journals!$L$9:$L$1011204,Journals!$D$9:$D$1011204,">"&$E$7,Journals!$D$9:$D$1011204,"<"&$E$8,Journals!$J$9:$J$1011204,"management fee")-SUMIFS(Journals!$K$9:$K$1011204,Journals!$D$9:$D$1011204,">"&$E$7,Journals!$D$9:$D$1011204,"<"&$E$8,Journals!$J$9:$J$1011204,"management fee")) -> 0 | N33: =SUMIFS(Journals!$K$9:$K$1011204,Journals!$D$9:$D$1011204,"<"&$F$7,Journals!$J$9:$J$1011204,"management fee")-SUMIFS(Journals!$L$9:$L$1011204,Journals!$D$9:$D$1011204,"<"&$F$7,Journals!$J$9:$J$1011204,"management fee") -> 19811568
G34: ='Chart of Accounts'!B30 -> Trustee fee | H34: =MAX(0,SUMIFS(Journals!$K$9:$K$1011204,Journals!$D$9:$D$1011204,">"&$E$7,Journals!$D$9:$D$1011204,"<"&$E$8,Journals!$J$9:$J$1011204,"trustee fee")-SUMIFS(Journals!$L$9:$L$1011204,Journals!$D$9:$D$1011204,">"&$E$7,Journals!$D$9:$D$1011204,"<"&$E$8,Journals!$J$9:$J$1011204,"trustee fee")) -> 98794.008 | I34: =MAX(0,SUMIFS(Journals!$L$9:$L$1011204,Journals!$D$9:$D$1011204,">"&$E$7,Journals!$D$9:$D$1011204,"<"&$E$8,Journals!$J$9:$J$1011204,"trustee fee")-SUMIFS(Journals!$K$9:$K$1011204,Journals!$D$9:$D$1011204,">"&$E$7,Journals!$D$9:$D$1011204,"<"&$E$8,Journals!$J$9:$J$1011204,"trustee fee")) -> 0 | N34: =SUMIFS(Journals!$K$9:$K$1011204,Journals!$D$9:$D$1011204,"<"&$F$7,Journals!$J$9:$J$1011204,"trustee fee")-SUMIFS(Journals!$L$9:$L$1011204,Journals!$D$9:$D$1011204,"<"&$F$7,Journals!$J$9:$J$1011204,"trustee fee") -> 970223.91
G35: ='Chart of Accounts'!B31 -> BSEC Annual Fee | H35: =MAX(0,SUMIFS(Journals!$K$9:$K$1011204,Journals!$D$9:$D$1011204,">"&$E$7,Journals!$D$9:$D$1011204,"<"&$E$8,Journals!$J$9:$J$1011204,"bsec annual fee")-SUMIFS(Journals!$L$9:$L$1011204,Journals!$D$9:$D$1011204,">"&$E$7,Journals!$D$9:$D$1011204,"<"&$E$8,Journals!$J$9:$J$1011204,"bsec annual fee")) -> 0 | I35: =MAX(0,SUMIFS(Journals!$L$9:$L$1011204,Journals!$D$9:$D$1011204,">"&$E$7,Journals!$D$9:$D$1011204,"<"&$E$8,Journals!$J$9:$J$1011204,"bsec annual fee")-SUMIFS(Journals!$K$9:$K$1011204,Journals!$D$9:$D$1011204,">"&$E$7,Journals!$D$9:$D$1011204,"<"&$E$8,Journals!$J$9:$J$1011204,"bsec annual fee")) -> 0 | N35: =SUMIFS(Journals!$K$9:$K$1011204,Journals!$D$9:$D$1011204,"<"&$F$7,Journals!$J$9:$J$1011204,"bsec annual fee")-SUMIFS(Journals!$L$9:$L$1011204,Journals!$D$9:$D$1011204,"<"&$F$7,Journals!$J$9:$J$1011204,"bsec annual fee") -> 952709.73
G36: ='Chart of Accounts'!B32 -> Audit fee | H36: =MAX(0,SUMIFS(Journals!$K$9:$K$1011204,Journals!$D$9:$D$1011204,">"&$E$7,Journals!$D$9:$D$1011204,"<"&$E$8,Journals!$J$9:$J$1011204,"audit fee")-SUMIFS(Journals!$L$9:$L$1011204,Journals!$D$9:$D$1011204,">"&$E$7,Journals!$D$9:$D$1011204,"<"&$E$8,Journals!$J$9:$J$1011204,"audit fee")) -> 0 | I36: =MAX(0,SUMIFS(Journals!$L$9:$L$1011204,Journals!$D$9:$D$1011204,">"&$E$7,Journals!$D$9:$D$1011204,"<"&$E$8,Journals!$J$9:$J$1011204,"audit fee")-SUMIFS(Journals!$K$9:$K$1011204,Journals!$D$9:$D$1011204,">"&$E$7,Journals!$D$9:$D$1011204,"<"&$E$8,Journals!$J$9:$J$1011204,"audit fee")) -> 0 | N36: =SUMIFS(Journals!$K$9:$K$1011204,Journals!$D$9:$D$1011204,"<"&$F$7,Journals!$J$9:$J$1011204,"audit fee")-SUMIFS(Journals!$L$9:$L$1011204,Journals!$D$9:$D$1011204,"<"&$F$7,Journals!$J$9:$J$1011204,"audit fee") -> 247000
G37: ='Chart of Accounts'!B33 -> CDBL charges | H37: =MAX(0,SUMIFS(Journals!$K$9:$K$1011204,Journals!$D$9:$D$1011204,">"&$E$7,Journals!$D$9:$D$1011204,"<"&$E$8,Journals!$J$9:$J$1011204,"cdbl charges")-SUMIFS(Journals!$L$9:$L$1011204,Journals!$D$9:$D$1011204,">"&$E$7,Journals!$D$9:$D$1011204,"<"&$E$8,Journals!$J$9:$J$1011204,"cdbl charges")) -> 13687.862 | I37: =MAX(0,SUMIFS(Journals!$L$9:$L$1011204,Journals!$D$9:$D$1011204,">"&$E$7,Journals!$D$9:$D$1011204,"<"&$E$8,Journals!$J$9:$J$1011204,"cdbl charges")-SUMIFS(Journals!$K$9:$K$1011204,Journals!$D$9:$D$1011204,">"&$E$7,Journals!$D$9:$D$1011204,"<"&$E$8,Journals!$J$9:$J$1011204,"cdbl charges")) -> 0 | N37: =SUMIFS(Journals!$K$9:$K$1011204,Journals!$D$9:$D$1011204,"<"&$F$7,Journals!$J$9:$J$1011204,"cdbl charges")-SUMIFS(Journals!$L$9:$L$1011204,Journals!$D$9:$D$1011204,"<"&$F$7,Journals!$J$9:$J$1011204,"cdbl charges") -> 336428.67
G38: ='Chart of Accounts'!B34 -> Fair value adjustment | H38: =MAX(0,SUMIFS(Journals!$K$9:$K$1011204,Journals!$D$9:$D$1011204,">"&$E$7,Journals!$D$9:$D$1011204,"<"&$E$8,Journals!$J$9:$J$1011204,"Fair value adjustment")-SUMIFS(Journals!$L$9:$L$1011204,Journals!$D$9:$D$1011204,">"&$E$7,Journals!$D$9:$D$1011204,"<"&$E$8,Journals!$J$9:$J$1011204,"Fair value adjustment")) -> 10155077 | I38: =MAX(0,SUMIFS(Journals!$L$9:$L$1011204,Journals!$D$9:$D$1011204,">"&$E$7,Journals!$D$9:$D$1011204,"<"&$E$8,Journals!$J$9:$J$1011204,"fair value adjustment")-SUMIFS(Journals!$K$9:$K$1011204,Journals!$D$9:$D$1011204,">"&$E$7,Journals!$D$9:$D$1011204,"<"&$E$8,Journals!$J$9:$J$1011204,"fair value adjustment")) -> 0 | J38: =MAX(0,SUMIFS(Journals!K9:K1011204,Journals!D9:D1011204,"<"&F7,Journals!J9:J1011204,"fair value adjustment")-SUMIFS(Journals!L9:L1011204,Journals!D9:D1011204,"<"&F7,Journals!J9:J1011204,"fair value adjustment")) -> 3833287.7 | K38: =MAX(0,SUMIFS(Journals!L9:L1011204,Journals!D9:D1011204,"<"&F7,Journals!J9:J1011204,"Fair value adjustment")-SUMIFS(Journals!K9:K1011204,Journals!D9:D1011204,"<"&F7,Journals!J9:J1011204,"fair value adjustment")) -> 0 | L38: =MAX(0,H38-I38+J38-K38) -> 13988365 | M38: =MAX(0,I38-H38-J38+K38) -> 0
G39: Fair value adjustment T-Bill | H39: =MAX(0,SUMIFS(Journals!$K$9:$K$1011204,Journals!$D$9:$D$1011204,">"&$E$7,Journals!$D$9:$D$1011204,"<"&$E$8,Journals!$J$9:$J$1011204,"Fair value adjustment T-Bill")-SUMIFS(Journals!$L$9:$L$1011204,Journals!$D$9:$D$1011204,">"&$E$7,Journals!$D$9:$D$1011204,"<"&$E$8,Journals!$J$9:$J$1011204,"Fair value adjustment T-Bill")) -> 0 | I39: =MAX(0,SUMIFS(Journals!$L$9:$L$1011204,Journals!$D$9:$D$1011204,">"&$E$7,Journals!$D$9:$D$1011204,"<"&$E$8,Journals!$J$9:$J$1011204,"Fair value adjustment T-Bill")-SUMIFS(Journals!$K$9:$K$1011204,Journals!$D$9:$D$1011204,">"&$E$7,Journals!$D$9:$D$1011204,"<"&$E$8,Journals!$J$9:$J$1011204,"Fair value adjustment T-Bill")) -> 0 | J39: =MAX(0,SUMIFS(Journals!K9:K1011204,Journals!D9:D1011204,"<"&F7,Journals!J9:J1011204,"Fair value adjustment T-Bill")-SUMIFS(Journals!L9:L1011204,Journals!D9:D1011204,"<"&F7,Journals!J9:J1011204,"Fair value adjustment T-Bill")) -> 0 | K39: =MAX(0,SUMIFS(Journals!L9:L1011204,Journals!D9:D1011204,"<"&F7,Journals!J9:J1011204,"Fair value adjustment T-Bill")-SUMIFS(Journals!K9:K1011204,Journals!D9:D1011204,"<"&F7,Journals!J9:J1011204,"Fair value adjustment T-Bill")) -> 0 | L39: =MAX(0,H39-I39+J39-K39) -> 0 | M39: =MAX(0,I39-H39-J39+K39) -> 0
G40: Fair value adjustment T-Bond | H40: =MAX(0,SUMIFS(Journals!$K$9:$K$1011204,Journals!$D$9:$D$1011204,">"&$E$7,Journals!$D$9:$D$1011204,"<"&$E$8,Journals!$J$9:$J$1011204,"Fair value adjustment T-Bond")-SUMIFS(Journals!$L$9:$L$1011204,Journals!$D$9:$D$1011204,">"&$E$7,Journals!$D$9:$D$1011204,"<"&$E$8,Journals!$J$9:$J$1011204,"Fair value adjustment T-Bond")) -> 0 | I40: =MAX(0,SUMIFS(Journals!$L$9:$L$1011204,Journals!$D$9:$D$1011204,">"&$E$7,Journals!$D$9:$D$1011204,"<"&$E$8,Journals!$J$9:$J$1011204,"Fair value adjustment T-Bond")-SUMIFS(Journals!$K$9:$K$1011204,Journals!$D$9:$D$1011204,">"&$E$7,Journals!$D$9:$D$1011204,"<"&$E$8,Journals!$J$9:$J$1011204,"Fair value adjustment T-Bond")) -> 0 | J40: =MAX(0,SUMIFS(Journals!K9:K1011204,Journals!D9:D1011204,"<"&F7,Journals!J9:J1011204,"Fair value adjustment T-Bond")-SUMIFS(Journals!L9:L1011204,Journals!D9:D1011204,"<"&F7,Journals!J9:J1011204,"Fair value adjustment T-Bond")) -> 0 | K40: =MAX(0,SUMIFS(Journals!L9:L1011204,Journals!D9:D1011204,"<"&F7,Journals!J9:J1011204,"Fair value adjustment T-Bond")-SUMIFS(Journals!K9:K1011204,Journals!D9:D1011204,"<"&F7,Journals!J9:J1011204,"Fair value adjustment T-Bond")) -> 0 | L40: =MAX(0,H40-I40+J40-K40) -> 0 | M40: =MAX(0,I40-H40-J40+K40) -> 0
G41: Interest receivables from FDR | H41: =MAX(0,SUMIFS(Journals!$K$9:$K$1011204,Journals!$D$9:$D$1011204,">"&$E$7,Journals!$D$9:$D$1011204,"<"&$E$8,Journals!$J$9:$J$1011204,"Interest receivables from FDR")-SUMIFS(Journals!$L$9:$L$1011204,Journals!$D$9:$D$1011204,">"&$E$7,Journals!$D$9:$D$1011204,"<"&$E$8,Journals!$J$9:$J$1011204,"Interest receivables from FDR")) -> 0 | I41: =MAX(0,SUMIFS(Journals!$L$9:$L$1011204,Journals!$D$9:$D$1011204,">"&$E$7,Journals!$D$9:$D$1011204,"<"&$E$8,Journals!$J$9:$J$1011204,"Interest receivables from FDR")-SUMIFS(Journals!$K$9:$K$1011204,Journals!$D$9:$D$1011204,">"&$E$7,Journals!$D$9:$D$1011204,"<"&$E$8,Journals!$J$9:$J$1011204,"Interest receivables from FDR")) -> 118833.53 | J41: =SUMIFS(Journals!$K$9:$K$1011204,Journals!$D$9:$D$1011204,"<"&$F$7,Journals!$J$9:$J$1011204,"Interest receivables from FDR")-SUMIFS(Journals!$L$9:$L$1011204,Journals!$D$9:$D$1011204,"<"&$F$7,Journals!$J$9:$J$1011204,"Interest receivables from FDR") -> 118833.54 | L41: =J41+H41-I41 -> 0.0033333333
G42: Interest receivables from Renata Pref. Share | H42: =MAX(0,SUMIFS(Journals!$K$9:$K$1011204,Journals!$D$9:$D$1011204,">"&$E$7,Journals!$D$9:$D$1011204,"<"&$E$8,Journals!$J$9:$J$1011204,"Interest receivables from Renata Pref. Share")-SUMIFS(Journals!$L$9:$L$1011204,Journals!$D$9:$D$1011204,">"&$E$7,Journals!$D$9:$D$1011204,"<"&$E$8,Journals!$J$9:$J$1011204,"Interest receivables from Renata Pref. Share")) -> 519576.92 | I42: =MAX(0,SUMIFS(Journals!$L$9:$L$1011204,Journals!$D$9:$D$1011204,">"&$E$7,Journals!$D$9:$D$1011204,"<"&$E$8,Journals!$J$9:$J$1011204,"Interest receivables from Renata Pref. Share")-SUMIFS(Journals!$K$9:$K$1011204,Journals!$D$9:$D$1011204,">"&$E$7,Journals!$D$9:$D$1011204,"<"&$E$8,Journals!$J$9:$J$1011204,"Interest receivables from Renata Pref. Share")) -> 0 | J42: =SUMIFS(Journals!$K$9:$K$1011204,Journals!$D$9:$D$1011204,"<"&$F$7,Journals!$J$9:$J$1011204,"Interest receivables from Renata Pref. Share")-SUMIFS(Journals!$L$9:$L$1011204,Journals!$D$9:$D$1011204,"<"&$F$7,Journals!$J$9:$J$1011204,"Interest receivables from Renata Pref. Share") -> 402053.57 | L42: =J42+H42-I42 -> 921630.49
G43: ='Chart of Accounts'!B40 -> Payable to broker | H43: =MAX(0,SUMIFS(Journals!$K$9:$K$1011204,Journals!$D$9:$D$1011204,">"&$E$7,Journals!$D$9:$D$1011204,"<"&$E$8,Journals!$J$9:$J$1011204,"payable to broker")-SUMIFS(Journals!$L$9:$L$1011204,Journals!$D$9:$D$1011204,">"&$E$7,Journals!$D$9:$D$1011204,"<"&$E$8,Journals!$J$9:$J$1011204,"payable to broker")) -> 71699.897 | I43: =MAX(0,SUMIFS(Journals!$L$9:$L$1011204,Journals!$D$9:$D$1011204,">"&$E$7,Journals!$D$9:$D$1011204,"<"&$E$8,Journals!$J$9:$J$1011204,"payable to broker")-SUMIFS(Journals!$K$9:$K$1011204,Journals!$D$9:$D$1011204,">"&$E$7,Journals!$D$9:$D$1011204,"<"&$E$8,Journals!$J$9:$J$1011204,"payable to broker")) -> 0 | K43: =SUMIFS(Journals!$L$9:$L$1011204,Journals!$D$9:$D$1011204,"<"&$F$7,Journals!$J$9:$J$1011204,"payable to broker")-SUMIFS(Journals!$K$9:$K$1011204,Journals!$D$9:$D$1011204,"<"&$F$7,Journals!$J$9:$J$1011204,"payable to broker") -> 64518.854 | M43: =K43+I43-H43 -> -7181.0422
G44: ='Chart of Accounts'!B41 -> Other operating expenses | H44: =MAX(0,SUMIFS(Journals!$K$9:$K$1011204,Journals!$D$9:$D$1011204,">"&$E$7,Journals!$D$9:$D$1011204,"<"&$E$8,Journals!$J$9:$J$1011204,"OTHER OPERATING EXPENSES")-SUMIFS(Journals!$L$9:$L$1011204,Journals!$D$9:$D$1011204,">"&$E$7,Journals!$D$9:$D$1011204,"<"&$E$8,Journals!$J$9:$J$1011204,"OTHER OPERATING EXPENSES")) -> 4725 | I44: =MAX(0,SUMIFS(Journals!$L$9:$L$1011204,Journals!$D$9:$D$1011204,">"&$E$7,Journals!$D$9:$D$1011204,"<"&$E$8,Journals!$J$9:$J$1011204,"OTHER OPERATING EXPENSES")-SUMIFS(Journals!$K$9:$K$1011204,Journals!$D$9:$D$1011204,">"&$E$7,Journals!$D$9:$D$1011204,"<"&$E$8,Journals!$J$9:$J$1011204,"OTHER OPERATING EXPENSES")) -> 0 | N44: =SUMIFS(Journals!$K$9:$K$1011204,Journals!$D$9:$D$1011204,"<"&$F$7,Journals!$J$9:$J$1011204,"OTHER OPERATING EXPENSES")-SUMIFS(Journals!$L$9:$L$1011204,Journals!$D$9:$D$1011204,"<"&$F$7,Journals!$J$9:$J$1011204,"OTHER OPERATING EXPENSES") -> 734305.86
G45: ='Chart of Accounts'!B42 -> Dividend income | H45: =MAX(0,SUMIFS(Journals!$K$9:$K$1011204,Journals!$D$9:$D$1011204,">"&$E$7,Journals!$D$9:$D$1011204,"<"&$E$8,Journals!$J$9:$J$1011204,"dividend income")) -> 0 | I45: =MAX(0,SUMIFS(Journals!$L$9:$L$1011204,Journals!$D$9:$D$1011204,">"&$E$7,Journals!$D$9:$D$1011204,"<"&$E$8,Journals!$J$9:$J$1011204,"dividend income")) -> 432567.46 | O45: =SUMIFS(Journals!$L$9:$L$1011204,Journals!$D$9:$D$1011204,"<"&$F$7,Journals!$J$9:$J$1011204,"dividend income")-SUMIFS(Journals!$K$9:$K$1011204,Journals!$D$9:$D$1011204,"<"&$F$7,Journals!$J$9:$J$1011204,"dividend income") -> 24781269
G46: ='Chart of Accounts'!B43 -> Dividend receivable | H46: =MAX(0,SUMIFS(Journals!$K$9:$K$1011204,Journals!$D$9:$D$1011204,">"&$E$7,Journals!$D$9:$D$1011204,"<"&$E$8,Journals!$J$9:$J$1011204,"dividend receivable")) -> 268232.5 | I46: =MAX(0,SUMIFS(Journals!$L$9:$L$1011204,Journals!$D$9:$D$1011204,">"&$E$7,Journals!$D$9:$D$1011204,"<"&$E$8,Journals!$J$9:$J$1011204,"dividend receivable")) -> 1501967 | J46: =SUMIFS(Journals!$K$9:$K$1011204,Journals!$D$9:$D$1011204,"<"&$F$7,Journals!$J$9:$J$1011204,"dividend receivable")-SUMIFS(Journals!$L$9:$L$1011204,Journals!$D$9:$D$1011204,"<"&$F$7,Journals!$J$9:$J$1011204,"dividend receivable") -> 1233734.5 | L46: =J46+H46-I46 -> 0
G47: ='Chart of Accounts'!B44 -> Custodian fee | H47: =MAX(0,SUMIFS(Journals!$K$9:$K$1011204,Journals!$D$9:$D$1011204,">"&$E$7,Journals!$D$9:$D$1011204,"<"&$E$8,Journals!$J$9:$J$1011204,"custodian fee")-SUMIFS(Journals!$L$9:$L$1011204,Journals!$D$9:$D$1011204,">"&$E$7,Journals!$D$9:$D$1011204,"<"&$E$8,Journals!$J$9:$J$1011204,"custodian fee")) -> 0 | N47: =SUMIFS(Journals!$K$9:$K$1011204,Journals!$D$9:$D$1011204,"<"&$F$7,Journals!$J$9:$J$1011204,"custodian fee")-SUMIFS(Journals!$L$9:$L$1011204,Journals!$D$9:$D$1011204,"<"&$F$7,Journals!$J$9:$J$1011204,"custodian fee") -> 632196.97
G48: ='Chart of Accounts'!B45 -> IPO Application | H48: =MAX(0,SUMIFS(Journals!$K$9:$K$1011204,Journals!$D$9:$D$1011204,">"&$E$7,Journals!$D$9:$D$1011204,"<"&$E$8,Journals!$J$9:$J$1011204,"IPO APPLICATION")-SUMIFS(Journals!$L$9:$L$1011204,Journals!$D$9:$D$1011204,">"&$E$7,Journals!$D$9:$D$1011204,"<"&$E$8,Journals!$J$9:$J$1011204,"IPO APPLICATION")) -> 0 | I48: =MAX(0,SUMIFS(Journals!$L$9:$L$1011204,Journals!$D$9:$D$1011204,">"&$E$7,Journals!$D$9:$D$1011204,"<"&$E$8,Journals!$J$9:$J$1011204,"IPO APPLICATION")-SUMIFS(Journals!$K$9:$K$1011204,Journals!$D$9:$D$1011204,">"&$E$7,Journals!$D$9:$D$1011204,"<"&$E$8,Journals!$J$9:$J$1011204,"IPO APPLICATION")) -> 0 | J48: =SUMIFS(Journals!$K$9:$K$1011204,Journals!$D$9:$D$1011204,"<"&$F$7,Journals!$J$9:$J$1011204,"IPO APPLICATION")-SUMIFS(Journals!$L$9:$L$1011204,Journals!$D$9:$D$1011204,"<"&$F$7,Journals!$J$9:$J$1011204,"IPO APPLICATION") -> 0 | L48: =J48+H48-I48 -> 0
G49: ='Chart of Accounts'!B46 -> IPO Application Fee | H49: =MAX(0,SUMIFS(Journals!$K$9:$K$1011204,Journals!$D$9:$D$1011204,">"&$E$7,Journals!$D$9:$D$1011204,"<"&$E$8,Journals!$J$9:$J$1011204,"IPO APPLICATION FEE")-SUMIFS(Journals!$L$9:$L$1011204,Journals!$D$9:$D$1011204,">"&$E$7,Journals!$D$9:$D$1011204,"<"&$E$8,Journals!$J$9:$J$1011204,"IPO APPLICATION FEE")) -> 0 | N49: =SUMIFS(Journals!$K$9:$K$1011204,Journals!$D$9:$D$1011204,"<"&$F$7,Journals!$J$9:$J$1011204,"IPO APPLICATION FEE")-SUMIFS(Journals!$L$9:$L$1011204,Journals!$D$9:$D$1011204,"<"&$F$7,Journals!$J$9:$J$1011204,"IPO APPLICATION FEE") -> 106000
G50: Realized gain | H50: =MAX(0,SUMIFS(Journals!$K$9:$K$1011204,Journals!$D$9:$D$1011204,">"&$E$7,Journals!$D$9:$D$1011204,"<"&$E$8,Journals!$J$9:$J$1011204,"realized gain")-SUMIFS(Journals!$L$9:$L$1011204,Journals!$D$9:$D$1011204,">"&$E$7,Journals!$D$9:$D$1011204,"<"&$E$8,Journals!$J$9:$J$1011204,"realized gain")) -> 0 | I50: =MAX(0,SUMIFS(Journals!$L$9:$L$1011204,Journals!$D$9:$D$1011204,">"&$E$7,Journals!$D$9:$D$1011204,"<"&$E$8,Journals!$J$9:$J$1011204,"realized gain")-SUMIFS(Journals!$K$9:$K$1011204,Journals!$D$9:$D$1011204,">"&$E$7,Journals!$D$9:$D$1011204,"<"&$E$8,Journals!$J$9:$J$1011204,"realized gain")) -> 10078118 | O50: =SUMIFS(Journals!$L$9:$L$1011204,Journals!$D$9:$D$1011204,"<"&$F$7,Journals!$J$9:$J$1011204,"realized gain")-SUMIFS(Journals!$K$9:$K$1011204,Journals!$D$9:$D$1011204,"<"&$F$7,Journals!$J$9:$J$1011204,"realized gain") -> 86210941
G51: Realized gain on T-Bill | H51: =MAX(0,SUMIFS(Journals!$K$9:$K$1011204,Journals!$D$9:$D$1011204,">"&$E$7,Journals!$D$9:$D$1011204,"<"&$E$8,Journals!$J$9:$J$1011204,"realized gain on T-Bill")-SUMIFS(Journals!$L$9:$L$1011204,Journals!$D$9:$D$1011204,">"&$E$7,Journals!$D$9:$D$1011204,"<"&$E$8,Journals!$J$9:$J$1011204,"realized gain on T-Bill")) -> 0 | I51: =MAX(0,SUMIFS(Journals!$L$9:$L$1011204,Journals!$D$9:$D$1011204,">"&$E$7,Journals!$D$9:$D$1011204,"<"&$E$8,Journals!$J$9:$J$1011204,"realized gain on T-Bill")-SUMIFS(Journals!$K$9:$K$1011204,Journals!$D$9:$D$1011204,">"&$E$7,Journals!$D$9:$D$1011204,"<"&$E$8,Journals!$J$9:$J$1011204,"realized gain on T-Bill")) -> 0 | O51: =SUMIFS(Journals!$L$9:$L$1011204,Journals!$D$9:$D$1011204,"<"&$F$7,Journals!$J$9:$J$1011204,"realized gain on T-Bill")-SUMIFS(Journals!$K$9:$K$1011204,Journals!$D$9:$D$1011204,"<"&$F$7,Journals!$J$9:$J$1011204,"realized gain on T-Bill") -> 2509121.3
G52: Realized gain on T-Bond | H52: =MAX(0,SUMIFS(Journals!$K$9:$K$1011204,Journals!$D$9:$D$1011204,">"&$E$7,Journals!$D$9:$D$1011204,"<"&$E$8,Journals!$J$9:$J$1011204,"realized gain on T-Bond")-SUMIFS(Journals!$L$9:$L$1011204,Journals!$D$9:$D$1011204,">"&$E$7,Journals!$D$9:$D$1011204,"<"&$E$8,Journals!$J$9:$J$1011204,"realized gain on T-Bond")) -> 0 | I52: =MAX(0,SUMIFS(Journals!$L$9:$L$1011204,Journals!$D$9:$D$1011204,">"&$E$7,Journals!$D$9:$D$1011204,"<"&$E$8,Journals!$J$9:$J$1011204,"realized gain on T-Bond")-SUMIFS(Journals!$K$9:$K$1011204,Journals!$D$9:$D$1011204,">"&$E$7,Journals!$D$9:$D$1011204,"<"&$E$8,Journals!$J$9:$J$1011204,"realized gain on T-Bond")) -> 0 | O52: =SUMIFS(Journals!$L$9:$L$1011204,Journals!$D$9:$D$1011204,"<"&$F$7,Journals!$J$9:$J$1011204,"realized gain on T-Bond")-SUMIFS(Journals!$K$9:$K$1011204,Journals!$D$9:$D$1011204,"<"&$F$7,Journals!$J$9:$J$1011204,"realized gain on T-Bond") -> 5389530.8
D53: =L53-M43 -> 4633816.6 | G53: Receivable from broker | H53: =MAX(0,SUMIFS(Journals!$K$9:$K$1011204,Journals!$D$9:$D$1011204,">"&$E$7,Journals!$D$9:$D$1011204,"<"&$E$8,Journals!$J$9:$J$1011204,"receivable from broker")-SUMIFS(Journals!$L$9:$L$1011204,Journals!$D$9:$D$1011204,">"&$E$7,Journals!$D$9:$D$1011204,"<"&$E$8,Journals!$J$9:$J$1011204,"receivable from broker")) -> 3542330.3 | I53: =MAX(0,SUMIFS(Journals!$L$9:$L$1011204,Journals!$D$9:$D$1011204,">"&$E$7,Journals!$D$9:$D$1011204,"<"&$E$8,Journals!$J$9:$J$1011204,"Receivable from broker")-SUMIFS(Journals!$K$9:$K$1011204,Journals!$D$9:$D$1011204,">"&$E$7,Journals!$D$9:$D$1011204,"<"&$E$8,Journals!$J$9:$J$1011204,"Receivable from broker")) -> 0 | J53: =SUMIFS(Journals!$K$9:$K$1011204,Journals!$D$9:$D$1011204,"<"&$F$7,Journals!$J$9:$J$1011204,"receivable from broker")-SUMIFS(Journals!$L$9:$L$1011204,Journals!$D$9:$D$1011204,"<"&$F$7,Journals!$J$9:$J$1011204,"receivable from broker") -> 1084305.3 | L53: =J53+H53-I53 -> 4626635.6
G54: Dividend Equalization Reserve | H54: =MAX(0,SUMIFS(Journals!$K$9:$K$1011204,Journals!$D$9:$D$1011204,">"&$E$7,Journals!$D$9:$D$1011204,"<"&$E$8,Journals!$J$9:$J$1011204,"Dividend Equalization Reserve")-SUMIFS(Journals!$L$9:$L$1011204,Journals!$D$9:$D$1011204,">"&$E$7,Journals!$D$9:$D$1011204,"<"&$E$8,Journals!$J$9:$J$1011204,"Dividend Equalization Reserve")) -> 0 | I54: =MAX(0,SUMIFS(Journals!$L$9:$L$1011204,Journals!$D$9:$D$1011204,">"&$E$7,Journals!$D$9:$D$1011204,"<"&$E$8,Journals!$J$9:$J$1011204,"Dividend Equalization Reserve")-SUMIFS(Journals!$K$9:$K$1011204,Journals!$D$9:$D$1011204,">"&$E$7,Journals!$D$9:$D$1011204,"<"&$E$8,Journals!$J$9:$J$1011204,"Dividend Equalization Reserve")) -> 0 | K54: =SUMIFS(Journals!$L$9:$L$1011204,Journals!$D$9:$D$1011204,"<"&$F$7,Journals!$J$9:$J$1011204,"Dividend Equalization Reserve")-SUMIFS(Journals!$K$9:$K$1011204,Journals!$D$9:$D$1011204,"<"&$F$7,Journals!$J$9:$J$1011204,"Dividend Equalization Reserve") -> 150000 | M54: =K54+I54-H54 -> 150000 | N54: =K54 -> 150000
G55: Retained Earnings | H55: =MAX(0,SUMIFS(Journals!$K$9:$K$1011204,Journals!$D$9:$D$1011204,">"&$E$7,Journals!$D$9:$D$1011204,"<"&$E$8,Journals!$J$9:$J$1011204,"Retained Earnings")-SUMIFS(Journals!$L$9:$L$1011204,Journals!$D$9:$D$1011204,">"&$E$7,Journals!$D$9:$D$1011204,"<"&$E$8,Journals!$J$9:$J$1011204,"Retained Earnings")) -> 9054438.6 | I55: =MAX(0,SUMIFS(Journals!$L$9:$L$1011204,Journals!$D$9:$D$1011204,">"&$E$7,Journals!$D$9:$D$1011204,"<"&$E$8,Journals!$J$9:$J$1011204,"Retained Earnigs")-SUMIFS(Journals!$K$9:$K$1011204,Journals!$D$9:$D$1011204,">"&$E$7,Journals!$D$9:$D$1011204,"<"&$E$8,Journals!$J$9:$J$1011204,"Retained Earnigs")) -> 0
G56: Dividend Payable | H56: =SUMIFS(Journals!$K$9:$K$1011204,Journals!$D$9:$D$1011204,">"&$E$7,Journals!$D$9:$D$1011204,"<"&$E$8,Journals!$J$9:$J$1011204,"Dividend Payable") -> 9054438.6 | I56: =MAX(0,SUMIFS(Journals!$L$9:$L$1011204,Journals!$D$9:$D$1011204,">"&$E$7,Journals!$D$9:$D$1011204,"<"&$E$8,Journals!$J$9:$J$1011204,"Dividend Payable")) -> 9054438.6 | J56: =SUMIFS(Journals!$K$9:$K$1011204,Journals!$D$9:$D$1011204,"<"&$F$7,Journals!$J$9:$J$1011204,"Dividend Payable") -> 56893216 | K56: =SUMIFS(Journals!$L$9:$L$1011204,Journals!$D$9:$D$1011204,"<"&$F$7,Journals!$J$9:$J$1011204,"Dividend Payable") -> 56893216 | M56: =I56-H56 -> 0 | N56: =J56 -> 56893216
G57: Withholding Tax Payable | H57: =SUMIFS(Journals!$K$9:$K$1011204,Journals!$D$9:$D$1011204,">"&$E$7,Journals!$D$9:$D$1011204,"<"&$E$8,Journals!$J$9:$J$1011204,"Withholding Tax Payable") -> 287451.08 | I57: =MAX(0,SUMIFS(Journals!$L$9:$L$1011204,Journals!$D$9:$D$1011204,">"&$E$7,Journals!$D$9:$D$1011204,"<"&$E$8,Journals!$J$9:$J$1011204,"Withholding Tax Payable")) -> 854267.68 | K57: =SUMIFS(Journals!$L$9:$L$1011204,Journals!$D$9:$D$1011204,"<"&$F$7,Journals!$J$9:$J$1011204,"Withholding Tax Payable")-SUMIFS(Journals!$K$9:$K$1011204,Journals!$D$9:$D$1011204,"<"&$F$7,Journals!$J$9:$J$1011204,"Withholding Tax Payable") -> 21176.575 | M57: =K57+I57-H57 -> 587993.18
G58: Withholding Tax Payable of News Paper | H58: =SUMIFS(Journals!$K$9:$K$1011204,Journals!$D$9:$D$1011204,">"&$E$7,Journals!$D$9:$D$1011204,"<"&$E$8,Journals!$J$9:$J$1011204,"Withholding Tax Payable of News Paper") -> 500 | I58: =MAX(0,SUMIFS(Journals!$L$9:$L$1011204,Journals!$D$9:$D$1011204,">"&$E$7,Journals!$D$9:$D$1011204,"<"&$E$8,Journals!$J$9:$J$1011204,"Withholding Tax Payable of News Paper")) -> 0 | K58: =SUMIFS(Journals!$L$9:$L$1011204,Journals!$D$9:$D$1011204,"<"&$F$7,Journals!$J$9:$J$1011204,"Withholding Tax Payable of News Paper")-SUMIFS(Journals!$K$9:$K$1011204,Journals!$D$9:$D$1011204,"<"&$F$7,Journals!$J$9:$J$1011204,"Withholding Tax Payable of News Paper") -> 500 | M58: =K58+I58-H58 -> 0
G59: Withholding Tax Payable of Telnet | H59: =SUMIFS(Journals!$K$9:$K$1011204,Journals!$D$9:$D$1011204,">"&$E$7,Journals!$D$9:$D$1011204,"<"&$E$8,Journals!$J$9:$J$1011204,"Withholding Tax Payable of Telnet") -> 150 | I59: =MAX(0,SUMIFS(Journals!$L$9:$L$1011204,Journals!$D$9:$D$1011204,">"&$E$7,Journals!$D$9:$D$1011204,"<"&$E$8,Journals!$J$9:$J$1011204,"Withholding Tax Payable of Telnet")) -> 225 | K59: =SUMIFS(Journals!$L$9:$L$1011204,Journals!$D$9:$D$1011204,"<"&$F$7,Journals!$J$9:$J$1011204,"Withholding Tax Payable of Telnet")-SUMIFS(Journals!$K$9:$K$1011204,Journals!$D$9:$D$1011204,"<"&$F$7,Journals!$J$9:$J$1011204,"Withholding Tax Payable of Telnet") -> 75 | M59: =K59+I59-H59 -> 150
G60: Investments in T-Bill | H60: =MAX(0,SUMIFS(Journals!$K$9:$K$1011204,Journals!$D$9:$D$1011204,">"&$E$7,Journals!$D$9:$D$1011204,"<"&$E$8,Journals!$J$9:$J$1011204,"Investments in T-Bill")-SUMIFS(Journals!$L$9:$L$1011204,Journals!$D$9:$D$1011204,">"&$E$7,Journals!$D$9:$D$1011204,"<"&$E$8,Journals!$J$9:$J$1011204,"Investments in T-Bill")) -> 0 | I60: =MAX(0,SUMIFS(Journals!$L$9:$L$1011204,Journals!$D$9:$D$1011204,">"&$E$7,Journals!$D$9:$D$1011204,"<"&$E$8,Journals!$J$9:$J$1011204,"Investments in T-Bill")-SUMIFS(Journals!$K$9:$K$1011204,Journals!$D$9:$D$1011204,">"&$E$7,Journals!$D$9:$D$1011204,"<"&$E$8,Journals!$J$9:$J$1011204,"Investments in T-Bill")) -> 0 | J60: =SUMIFS(Journals!$K$9:$K$1011204,Journals!$D$9:$D$1011204,"<"&$F$7,Journals!$J$9:$J$1011204,"Investments in T-Bill")-SUMIFS(Journals!$L$9:$L$1011204,Journals!$D$9:$D$1011204,"<"&$F$7,Journals!$J$9:$J$1011204,"Investments in T-Bill") -> 0 | L60: =J60+H60-I60 -> 0
G61: Interest receivables from T-Bill | H61: =MAX(0,SUMIFS(Journals!$K$9:$K$1011204,Journals!$D$9:$D$1011204,">"&$E$7,Journals!$D$9:$D$1011204,"<"&$E$8,Journals!$J$9:$J$1011204,"Interest receivables from T-Bill")-SUMIFS(Journals!$L$9:$L$1011204,Journals!$D$9:$D$1011204,">"&$E$7,Journals!$D$9:$D$1011204,"<"&$E$8,Journals!$J$9:$J$1011204,"Interest receivables from T-Bill")) -> 0 | I61: =MAX(0,SUMIFS(Journals!$L$9:$L$1011204,Journals!$D$9:$D$1011204,">"&$E$7,Journals!$D$9:$D$1011204,"<"&$E$8,Journals!$J$9:$J$1011204,"Interest receivables from T-Bill")-SUMIFS(Journals!$K$9:$K$1011204,Journals!$D$9:$D$1011204,">"&$E$7,Journals!$D$9:$D$1011204,"<"&$E$8,Journals!$J$9:$J$1011204,"Interest receivables from T-Bill")) -> 0 | J61: =SUMIFS(Journals!$K$9:$K$1011204,Journals!$D$9:$D$1011204,"<"&$F$7,Journals!$J$9:$J$1011204,"Interest receivables from T-Bill")-SUMIFS(Journals!$L$9:$L$1011204,Journals!$D$9:$D$1011204,"<"&$F$7,Journals!$J$9:$J$1011204,"Interest receivables from T-Bill") -> 0 | L61: =J61+H61-I61 -> 0
G62: Investments in T-Bond | H62: =MAX(0,SUMIFS(Journals!$K$9:$K$1011204,Journals!$D$9:$D$1011204,">"&$E$7,Journals!$D$9:$D$1011204,"<"&$E$8,Journals!$J$9:$J$1011204,"Investments in T-Bond")-SUMIFS(Journals!$L$9:$L$1011204,Journals!$D$9:$D$1011204,">"&$E$7,Journals!$D$9:$D$1011204,"<"&$E$8,Journals!$J$9:$J$1011204,"Investments in T-Bond")) -> 0 | I62: =MAX(0,SUMIFS(Journals!$L$9:$L$1011204,Journals!$D$9:$D$1011204,">"&$E$7,Journals!$D$9:$D$1011204,"<"&$E$8,Journals!$J$9:$J$1011204,"Investments in T-Bond")-SUMIFS(Journals!$K$9:$K$1011204,Journals!$D$9:$D$1011204,">"&$E$7,Journals!$D$9:$D$1011204,"<"&$E$8,Journals!$J$9:$J$1011204,"Investments in T-Bond")) -> 0 | J62: =SUMIFS(Journals!$K$9:$K$1011204,Journals!$D$9:$D$1011204,"<"&$F$7,Journals!$J$9:$J$1011204,"Investments in T-Bond")-SUMIFS(Journals!$L$9:$L$1011204,Journals!$D$9:$D$1011204,"<"&$F$7,Journals!$J$9:$J$1011204,"Investments in T-Bond") -> 0 | L62: =J62+H62-I62 -> 0
G63: Interest receivables from T-Bond | H63: =MAX(0,SUMIFS(Journals!$K$9:$K$1011204,Journals!$D$9:$D$1011204,">"&$E$7,Journals!$D$9:$D$1011204,"<"&$E$8,Journals!$J$9:$J$1011204,"Interest receivables from T-Bond")-SUMIFS(Journals!$L$9:$L$1011204,Journals!$D$9:$D$1011204,">"&$E$7,Journals!$D$9:$D$1011204,"<"&$E$8,Journals!$J$9:$J$1011204,"Interest receivables from T-Bond")) -> 0 | I63: =MAX(0,SUMIFS(Journals!$L$9:$L$1011204,Journals!$D$9:$D$1011204,">"&$E$7,Journals!$D$9:$D$1011204,"<"&$E$8,Journals!$J$9:$J$1011204,"Interest receivables from T-Bond")-SUMIFS(Journals!$K$9:$K$1011204,Journals!$D$9:$D$1011204,">"&$E$7,Journals!$D$9:$D$1011204,"<"&$E$8,Journals!$J$9:$J$1011204,"Interest receivables from T-Bond")) -> 0 | J63: =SUMIFS(Journals!$K$9:$K$1011204,Journals!$D$9:$D$1011204,"<"&$F$7,Journals!$J$9:$J$1011204,"Interest receivables from T-Bond")-SUMIFS(Journals!$L$9:$L$1011204,Journals!$D$9:$D$1011204,"<"&$F$7,Journals!$J$9:$J$1011204,"Interest receivables from T-Bond") -> 0 | L63: =J63+H63-I63 -> 0

Sheet TB-P
A1: Check of Trial Balance | G1: =SUM(H7:H95)-SUM(I7:I95) -> 3.2961369e-05
A2: Check of Balance Sheet | G2: =BS!C25-BS!C40 -> 0
A3: Check of Cash Balance | G3: =BS!C23-CF!B44 -> -2739690.1
B5: Desired Reporting Period | H5: During the Reporting Period | J5: For Balance Sheet | N5: For Retained Earnings
B6: Year | C6: Month | D6: Day | E6: Value | F6: Value | G6: Accounts | H6: Debit | I6: Credit | J6: Carry Forward Balance | K6: Carry Forward Balance | L6: On date | M6: On date | N6: Debit | O6: Credit
A7: Beginning | B7: 2025 | C7: 1 | D7: 1 | E7: =DATE(B7,C7,D7)-1 -> 45657 | F7: =DATE(B7,C7,D7) -> 45658 | G7: ='Chart of Accounts'!B3 -> Investments in stock | H7: =MAX(0,SUMIFS(Journals!$K$9:$K$1011204,Journals!$D$9:$D$1011204,">"&$E$7,Journals!$D$9:$D$1011204,"<"&$E$8,Journals!$J$9:$J$1011204,"investments in stock")-SUMIFS(Journals!$L$9:$L$1011204,Journals!$D$9:$D$1011204,">"&$E$7,Journals!$D$9:$D$1011204,"<"&$E$8,Journals!$J$9:$J$1011204,"investments in stock")) -> 1.2163911e+08 | I7: =MAX(0,SUMIFS(Journals!$L$9:$L$1011204,Journals!$D$9:$D$1011204,">"&$E$7,Journals!$D$9:$D$1011204,"<"&$E$8,Journals!$J$9:$J$1011204,"Investments in stock")-SUMIFS(Journals!$K$9:$K$1011204,Journals!$D$9:$D$1011204,">"&$E$7,Journals!$D$9:$D$1011204,"<"&$E$8,Journals!$J$9:$J$1011204,"Investments in stock")) -> 0 | J7: =SUMIFS(Journals!$K$9:$K$1011204,Journals!$D$9:$D$1011204,"<"&$F$7,Journals!$J$9:$J$1011204,"investments in stock")-SUMIFS(Journals!$L$9:$L$1011204,Journals!$D$9:$D$1011204,"<"&$F$7,Journals!$J$9:$J$1011204,"investments in stock") -> 86882081 | L7: =J7+H7-I7 -> 2.0852119e+08
A8: Ending | B8: 2025 | C8: 12 | D8: 31 | E8: =DATE(B8,C8,D8)+1 -> 46023 | F8: =DATE(B8,C8,D8) -> 46022 | G8: ='Chart of Accounts'!B4 -> Interest Receivables from Bank A/C | H8: =MAX(0,SUMIFS(Journals!$K$9:$K$1011204,Journals!$D$9:$D$1011204,">"&$E$7,Journals!$D$9:$D$1011204,"<"&$E$8,Journals!$J$9:$J$1011204,"Interest Receivables from Bank A/C")-SUMIFS(Journals!$L$9:$L$1011204,Journals!$D$9:$D$1011204,">"&$E$7,Journals!$D$9:$D$1011204,"<"&$E$8,Journals!$J$9:$J$1011204,"Interest Receivables from Bank A/C")) -> 6917.47 | I8: =MAX(0,SUMIFS(Journals!$L$9:$L$1011204,Journals!$D$9:$D$1011204,">"&$E$7,Journals!$D$9:$D$1011204,"<"&$E$8,Journals!$J$9:$J$1011204,"Interest Receivables from Bank A/C")-SUMIFS(Journals!$K$9:$K$1011204,Journals!$D$9:$D$1011204,">"&$E$7,Journals!$D$9:$D$1011204,"<"&$E$8,Journals!$J$9:$J$1011204,"Interest Receivables from Bank A/C")) -> 0 | J8: =SUMIFS(Journals!$K$9:$K$1011204,Journals!$D$9:$D$1011204,"<"&$F$7,Journals!$J$9:$J$1011204,"Interest Receivables from Bank A/C")-SUMIFS(Journals!$L$9:$L$1011204,Journals!$D$9:$D$1011204,"<"&$F$7,Journals!$J$9:$J$1011204,"Interest Receivables from Bank A/C") -> 684.1 | L8: =J8+H8-I8 -> 7601.57
G9: ='Chart of Accounts'!B5 -> Preliminary & issue expenses | H9: =MAX(0,SUMIFS(Journals!$K$9:$K$1011204,Journals!$D$9:$D$1011204,">"&$E$7,Journals!$D$9:$D$1011204,"<"&$E$8,Journals!$J$9:$J$1011204,"Preliminary & issue expenses")-SUMIFS(Journals!$L$9:$L$1011204,Journals!$D$9:$D$1011204,">"&$E$7,Journals!$D$9:$D$1011204,"<"&$E$8,Journals!$J$9:$J$1011204,"Preliminary & issue expenses")) -> 0 | I9: =MAX(0,SUMIFS(Journals!$L$9:$L$1011204,Journals!$D$9:$D$1011204,">"&$E$7,Journals!$D$9:$D$1011204,"<"&$E$8,Journals!$J$9:$J$1011204,"Preliminary & issue expenses")-SUMIFS(Journals!$K$9:$K$1011204,Journals!$D$9:$D$1011204,">"&$E$7,Journals!$D$9:$D$1011204,"<"&$E$8,Journals!$J$9:$J$1011204,"Preliminary & issue expenses")) -> 142464.68 | J9: =SUMIFS(Journals!$K$9:$K$1011204,Journals!$D$9:$D$1011204,"<"&$F$7,Journals!$J$9:$J$1011204,"Preliminary & issue expenses")-SUMIFS(Journals!$L$9:$L$1011204,Journals!$D$9:$D$1011204,"<"&$F$7,Journals!$J$9:$J$1011204,"Preliminary & issue expenses") -> 316327.51 | L9: =J9+H9-I9 -> 173862.83
G10: Accrued Management Fee | H10: =SUMIFS(Journals!$K$9:$K$1010900,Journals!$D$9:$D$1010900,">"&$E$7,Journals!$D$9:$D$1010900,"<"&$E$8,Journals!$J$9:$J$1010900,"Accrued Management Fee") -> 1705923.3 | I10: =MAX(0,SUMIFS(Journals!$L$9:$L$1011204,Journals!$D$9:$D$1011204,">"&$E$7,Journals!$D$9:$D$1011204,"<"&$E$8,Journals!$J$9:$J$1011204,"Accrued Management Fee")) -> 3748377.1 | K10: =SUMIFS(Journals!$L$9:$L$1011204,Journals!$D$9:$D$1011204,"<"&$F$7,Journals!$J$9:$J$1011204,"Accrued Management Fee")-SUMIFS(Journals!$K$9:$K$1011204,Journals!$D$9:$D$1011204,"<"&$F$7,Journals!$J$9:$J$1011204,"Accrued Management Fee") -> 913900.67 | M10: =K10+I10-H10 -> 2956354.5
G11: ='Chart of Accounts'!B7 -> Accrued Trustee Fee | H11: =MAX(0,SUMIFS(Journals!$K$9:$K$1011204,Journals!$D$9:$D$1011204,">"&$E$7,Journals!$D$9:$D$1011204,"<"&$E$8,Journals!$J$9:$J$1011204,"accrued trustee fee")-SUMIFS(Journals!$L$9:$L$1011204,Journals!$D$9:$D$1011204,">"&$E$7,Journals!$D$9:$D$1011204,"<"&$E$8,Journals!$J$9:$J$1011204,"accrued trustee fee")) -> 0 | I11: =MAX(0,SUMIFS(Journals!$L$9:$L$1011204,Journals!$D$9:$D$1011204,">"&$E$7,Journals!$D$9:$D$1011204,"<"&$E$8,Journals!$J$9:$J$1011204,"accrued trustee fee")-SUMIFS(Journals!$K$9:$K$1011204,Journals!$D$9:$D$1011204,">"&$E$7,Journals!$D$9:$D$1011204,"<"&$E$8,Journals!$J$9:$J$1011204,"accrued trustee fee")) -> 37067.556 | K11: =SUMIFS(Journals!$L$9:$L$1011204,Journals!$D$9:$D$1011204,"<"&$F$7,Journals!$J$9:$J$1011204,"Accrued Trustee Fee")-SUMIFS(Journals!$K$9:$K$1011204,Journals!$D$9:$D$1011204,"<"&$F$7,Journals!$J$9:$J$1011204,"Accrued Trustee Fee") -> 68949.105 | M11: =K11+I11-H11 -> 106016.66
G12: ='Chart of Accounts'!B8 -> Accrued Custodian Fee | H12: =MAX(0,SUMIFS(Journals!$K$9:$K$1011204,Journals!$D$9:$D$1011204,">"&$E$7,Journals!$D$9:$D$1011204,"<"&$E$8,Journals!$J$9:$J$1011204,"accrued custodian fee")-SUMIFS(Journals!$L$9:$L$1011204,Journals!$D$9:$D$1011204,">"&$E$7,Journals!$D$9:$D$1011204,"<"&$E$8,Journals!$J$9:$J$1011204,"accrued custodian fee")) -> 0 | I12: =MAX(0,SUMIFS(Journals!$L$9:$L$1011204,Journals!$D$9:$D$1011204,">"&$E$7,Journals!$D$9:$D$1011204,"<"&$E$8,Journals!$J$9:$J$1011204,"accrued custodian fee")-SUMIFS(Journals!$K$9:$K$1011204,Journals!$D$9:$D$1011204,">"&$E$7,Journals!$D$9:$D$1011204,"<"&$E$8,Journals!$J$9:$J$1011204,"accrued custodian fee")) -> 0 | K12: =SUMIFS(Journals!$L$9:$L$1011204,Journals!$D$9:$D$1011204,"<"&$F$7,Journals!$J$9:$J$1011204,"Accrued Custodian Fee")-SUMIFS(Journals!$K$9:$K$1011204,Journals!$D$9:$D$1011204,"<"&$F$7,Journals!$J$9:$J$1011204,"Accrued Custodian Fee") -> 0 | M12: =K12+I12-H12 -> 0
G13: ='Chart of Accounts'!B9 -> Accrued BSEC fee | H13: =MAX(0,SUMIFS(Journals!$K$9:$K$1011204,Journals!$D$9:$D$1011204,">"&$E$7,Journals!$D$9:$D$1011204,"<"&$E$8,Journals!$J$9:$J$1011204,"accrued bsec fee")-SUMIFS(Journals!$L$9:$L$1011204,Journals!$D$9:$D$1011204,">"&$E$7,Journals!$D$9:$D$1011204,"<"&$E$8,Journals!$J$9:$J$1011204,"accrued bsec fee")) -> 0 | I13: =MAX(0,SUMIFS(Journals!$L$9:$L$1011204,Journals!$D$9:$D$1011204,">"&$E$7,Journals!$D$9:$D$1011204,"<"&$E$8,Journals!$J$9:$J$1011204,"accrued bsec fee")-SUMIFS(Journals!$K$9:$K$1011204,Journals!$D$9:$D$1011204,">"&$E$7,Journals!$D$9:$D$1011204,"<"&$E$8,Journals!$J$9:$J$1011204,"accrued bsec fee")) -> 0 | K13: =SUMIFS(Journals!$L$9:$L$1011204,Journals!$D$9:$D$1011204,"<"&$F$7,Journals!$J$9:$J$1011204,"accrued bsec fee")-SUMIFS(Journals!$K$9:$K$1011204,Journals!$D$9:$D$1011204,"<"&$F$7,Journals!$J$9:$J$1011204,"accrued bsec fee") -> 0 | M13: =K13+I13-H13 -> 0
G14: ='Chart of Accounts'!B10 -> Accrued Audit Fee | H14: =MAX(0,SUMIFS(Journals!$K$9:$K$1011204,Journals!$D$9:$D$1011204,">"&$E$7,Journals!$D$9:$D$1011204,"<"&$E$8,Journals!$J$9:$J$1011204,"accrued audit fee")-SUMIFS(Journals!$L$9:$L$1011204,Journals!$D$9:$D$1011204,">"&$E$7,Journals!$D$9:$D$1011204,"<"&$E$8,Journals!$J$9:$J$1011204,"accrued audit fee")) -> 0 | I14: =MAX(0,SUMIFS(Journals!$L$9:$L$1011204,Journals!$D$9:$D$1011204,">"&$E$7,Journals!$D$9:$D$1011204,"<"&$E$8,Journals!$J$9:$J$1011204,"accrued audit fee")-SUMIFS(Journals!$K$9:$K$1011204,Journals!$D$9:$D$1011204,">"&$E$7,Journals!$D$9:$D$1011204,"<"&$E$8,Journals!$J$9:$J$1011204,"accrued audit fee")) -> 0 | K14: =SUMIFS(Journals!$L$9:$L$1011204,Journals!$D$9:$D$1011204,"<"&$F$7,Journals!$J$9:$J$1011204,"accrued audit fee")-SUMIFS(Journals!$K$9:$K$1011204,Journals!$D$9:$D$1011204,"<"&$F$7,Journals!$J$9:$J$1011204,"accrued audit fee") -> 45999.997 | M14: =K14+I14-H14 -> 45999.997
G15: ='Chart of Accounts'!B11 -> Accrued CDBL Fee | H15: =MAX(0,SUMIFS(Journals!$K$9:$K$1011204,Journals!$D$9:$D$1011204,">"&$E$7,Journals!$D$9:$D$1011204,"<"&$E$8,Journals!$J$9:$J$1011204,"accrued CDBL fee")-SUMIFS(Journals!$L$9:$L$1011204,Journals!$D$9:$D$1011204,">"&$E$7,Journals!$D$9:$D$1011204,"<"&$E$8,Journals!$J$9:$J$1011204,"accrued CDBL fee")) -> 0 | I15: =MAX(0,SUMIFS(Journals!$L$9:$L$1011204,Journals!$D$9:$D$1011204,">"&$E$7,Journals!$D$9:$D$1011204,"<"&$E$8,Journals!$J$9:$J$1011204,"accrued CDBL fee")-SUMIFS(Journals!$K$9:$K$1011204,Journals!$D$9:$D$1011204,">"&$E$7,Journals!$D$9:$D$1011204,"<"&$E$8,Journals!$J$9:$J$1011204,"accrued CDBL fee")) -> 0 | K15: =SUMIFS(Journals!$L$9:$L$1011204,Journals!$D$9:$D$1011204,"<"&$F$7,Journals!$J$9:$J$1011204,"accrued cdbl fee")-SUMIFS(Journals!$K$9:$K$1011204,Journals!$D$9:$D$1011204,"<"&$F$7,Journals!$J$9:$J$1011204,"accrued cdbl fee") -> 0 | M15: =K15+I15-H15 -> 0
G16: ='Chart of Accounts'!B12 -> Fixed Deposit Receipts (FDR) | H16: =MAX(0,SUMIFS(Journals!$K$9:$K$1011204,Journals!$D$9:$D$1011204,">"&$E$7,Journals!$D$9:$D$1011204,"<"&$E$8,Journals!$J$9:$J$1011204,"Fixed Deposit Receipts (FDR)")-SUMIFS(Journals!$L$9:$L$1011204,Journals!$D$9:$D$1011204,">"&$E$7,Journals!$D$9:$D$1011204,"<"&$E$8,Journals!$J$9:$J$1011204,"Fixed Deposit Receipts (FDR)")) -> 0 | I16: =MAX(0,SUMIFS(Journals!$L$9:$L$1011204,Journals!$D$9:$D$1011204,">"&$E$7,Journals!$D$9:$D$1011204,"<"&$E$8,Journals!$J$9:$J$1011204,"Fixed Deposit Receipts (FDR)")-SUMIFS(Journals!$K$9:$K$1011204,Journals!$D$9:$D$1011204,">"&$E$7,Journals!$D$9:$D$1011204,"<"&$E$8,Journals!$J$9:$J$1011204,"Fixed Deposit Receipts (FDR)")) -> 0 | J16: =SUMIFS(Journals!$K$9:$K$1011204,Journals!$D$9:$D$1011204,"<"&$F$7,Journals!$J$9:$J$1011204,"Fixed Deposit Receipts (FDR)")-SUMIFS(Journals!$L$9:$L$1011204,Journals!$D$9:$D$1011204,"<"&$F$7,Journals!$J$9:$J$1011204,"Fixed Deposit Receipts (FDR)") -> 6000000 | L16: =J16+H16-I16 -> 6000000
G17: ='Chart of Accounts'!B13 -> Cash and cash equivalents | H17: =MAX(0,SUMIFS(Journals!$K$9:$K$1011204,Journals!$D$9:$D$1011204,">"&$E$7,Journals!$D$9:$D$1011204,"<"&$E$8,Journals!$J$9:$J$1011204,"Cash and cash equivalents")-SUMIFS(Journals!$L$9:$L$1011204,Journals!$D$9:$D$1011204,">"&$E$7,Journals!$D$9:$D$1011204,"<"&$E$8,Journals!$J$9:$J$1011204,"Cash and cash equivalents")) -> 0 | I17: =MAX(0,SUMIFS(Journals!$L$9:$L$1011204,Journals!$D$9:$D$1011204,">"&$E$7,Journals!$D$9:$D$1011204,"<"&$E$8,Journals!$J$9:$J$1011204,"Cash and cash equivalents")-SUMIFS(Journals!$K$9:$K$1011204,Journals!$D$9:$D$1011204,">"&$E$7,Journals!$D$9:$D$1011204,"<"&$E$8,Journals!$J$9:$J$1011204,"Cash and cash equivalents")) -> 21065069 | J17: =SUMIFS(Journals!$K$9:$K$1011204,Journals!$D$9:$D$1011204,"<"&$F$7,Journals!$J$9:$J$1011204,"Cash and cash equivalents")-SUMIFS(Journals!$L$9:$L$1011204,Journals!$D$9:$D$1011204,"<"&$F$7,Journals!$J$9:$J$1011204,"Cash and cash equivalents") -> 22849633 | L17: =J17+H17-I17 -> 1784563.8
G18: ='Chart of Accounts'!B14 -> Unit Capital | H18: =MAX(0,SUMIFS(Journals!$K$9:$K$1011204,Journals!$D$9:$D$1011204,">"&$E$7,Journals!$D$9:$D$1011204,"<"&$E$8,Journals!$J$9:$J$1011204,"unit capital")) -> 34224720 | I18: =MAX(0,SUMIFS(Journals!$L$9:$L$1011204,Journals!$D$9:$D$1011204,">"&$E$7,Journals!$D$9:$D$1011204,"<"&$E$8,Journals!$J$9:$J$1011204,"unit capital")) -> 82095460 | K18: =SUMIFS(Journals!$L$9:$L$1011204,Journals!$D$9:$D$1011204,"<"&$F$7,Journals!$J$9:$J$1011204,"unit capital")-SUMIFS(Journals!$K$9:$K$1011204,Journals!$D$9:$D$1011204,"<"&$F$7,Journals!$J$9:$J$1011204,"unit capital") -> 108240270 | M18: =K18+I18-H18 -> 156111010
G19: ='Chart of Accounts'!B15 -> Unit premium reserve | H19: =MAX(0,SUMIFS(Journals!$K$9:$K$1011204,Journals!$D$9:$D$1011204,">"&$E$7,Journals!$D$9:$D$1011204,"<"&$E$8,Journals!$J$9:$J$1011204,"Unit premium reserve")) -> 12007798 | I19: =MAX(0,SUMIFS(Journals!$L$9:$L$1011204,Journals!$D$9:$D$1011204,">"&$E$7,Journals!$D$9:$D$1011204,"<"&$E$8,Journals!$J$9:$J$1011204,"unit premium reserve")) -> 30623394 | K19: =SUMIFS(Journals!$L$9:$L$1011204,Journals!$D$9:$D$1011204,"<"&$F$7,Journals!$J$9:$J$1011204,"unit premium reserve")-SUMIFS(Journals!$K$9:$K$1011204,Journals!$D$9:$D$1011204,"<"&$F$7,Journals!$J$9:$J$1011204,"unit premium reserve") -> -8188472.1 | M19: =K19+I19-H19 -> 10427123
G20: Interest income | H20: =MAX(0,SUMIFS(Journals!$K$9:$K$1011204,Journals!$D$9:$D$1011204,">"&$E$7,Journals!$D$9:$D$1011204,"<"&$E$8,Journals!$J$9:$J$1011204,"Interest income")-SUMIFS(Journals!$L$9:$L$1011204,Journals!$D$9:$D$1011204,">"&$E$7,Journals!$D$9:$D$1011204,"<"&$E$8,Journals!$J$9:$J$1011204,"Interest income")) -> 0 | I20: =MAX(0,SUMIFS(Journals!$L$9:$L$1011204,Journals!$D$9:$D$1011204,">"&$E$7,Journals!$D$9:$D$1011204,"<"&$E$8,Journals!$J$9:$J$1011204,"Interest income")-SUMIFS(Journals!$K$9:$K$1011204,Journals!$D$9:$D$1011204,">"&$E$7,Journals!$D$9:$D$1011204,"<"&$E$8,Journals!$J$9:$J$1011204,"Interest income")) -> 3480053.4 | O20: =SUMIFS(Journals!$L$9:$L$1011204,Journals!$D$9:$D$1011204,"<"&$F$7,Journals!$J$9:$J$1011204,"interest income")-SUMIFS(Journals!$K$9:$K$1011204,Journals!$D$9:$D$1011204,"<"&$F$7,Journals!$J$9:$J$1011204,"interest income") -> 12633987
G21: Interest income from FDR | H21: =MAX(0,SUMIFS(Journals!$K$9:$K$1011204,Journals!$D$9:$D$1011204,">"&$E$7,Journals!$D$9:$D$1011204,"<"&$E$8,Journals!$J$9:$J$1011204,"Interest income from FDR")-SUMIFS(Journals!$L$9:$L$1011204,Journals!$D$9:$D$1011204,">"&$E$7,Journals!$D$9:$D$1011204,"<"&$E$8,Journals!$J$9:$J$1011204,"Interest income from FDR")) -> 0 | I21: =MAX(0,SUMIFS(Journals!$L$9:$L$1011204,Journals!$D$9:$D$1011204,">"&$E$7,Journals!$D$9:$D$1011204,"<"&$E$8,Journals!$J$9:$J$1011204,"Interest income from FDR")-SUMIFS(Journals!$K$9:$K$1011204,Journals!$D$9:$D$1011204,">"&$E$7,Journals!$D$9:$D$1011204,"<"&$E$8,Journals!$J$9:$J$1011204,"Interest income from FDR")) -> 0 | O21: =SUMIFS(Journals!$L$9:$L$1011204,Journals!$D$9:$D$1011204,"<"&$F$7,Journals!$J$9:$J$1011204,"Interest income from FDR")-SUMIFS(Journals!$K$9:$K$1011204,Journals!$D$9:$D$1011204,"<"&$F$7,Journals!$J$9:$J$1011204,"Interest income from FDR") -> 0
G22: Interest income from Renata Pref. Share | H22: =MAX(0,SUMIFS(Journals!$K$9:$K$1011204,Journals!$D$9:$D$1011204,">"&$E$7,Journals!$D$9:$D$1011204,"<"&$E$8,Journals!$J$9:$J$1011204,"Interest income from Renata Pref. Share")-SUMIFS(Journals!$L$9:$L$1011204,Journals!$D$9:$D$1011204,">"&$E$7,Journals!$D$9:$D$1011204,"<"&$E$8,Journals!$J$9:$J$1011204,"Interest income from Renata Pref. Share")) -> 0 | I22: =MAX(0,SUMIFS(Journals!$L$9:$L$1011204,Journals!$D$9:$D$1011204,">"&$E$7,Journals!$D$9:$D$1011204,"<"&$E$8,Journals!$J$9:$J$1011204,"Interest income from Renata Pref. Share")-SUMIFS(Journals!$K$9:$K$1011204,Journals!$D$9:$D$1011204,">"&$E$7,Journals!$D$9:$D$1011204,"<"&$E$8,Journals!$J$9:$J$1011204,"Interest income from Renata Pref. Share")) -> 402053.57 | O22: =SUMIFS(Journals!$L$9:$L$1011204,Journals!$D$9:$D$1011204,"<"&$F$7,Journals!$J$9:$J$1011204,"Interest income from Renata Pref. Share")-SUMIFS(Journals!$K$9:$K$1011204,Journals!$D$9:$D$1011204,"<"&$F$7,Journals!$J$9:$J$1011204,"Interest income from Renata Pref. Share") -> 0
G23: Interest income from Bank Acc. | H23: =MAX(0,SUMIFS(Journals!$K$9:$K$1011204,Journals!$D$9:$D$1011204,">"&$E$7,Journals!$D$9:$D$1011204,"<"&$E$8,Journals!$J$9:$J$1011204,"Interest income from Bank Acc.")-SUMIFS(Journals!$L$9:$L$1011204,Journals!$D$9:$D$1011204,">"&$E$7,Journals!$D$9:$D$1011204,"<"&$E$8,Journals!$J$9:$J$1011204,"Interest income from Bank Acc.")) -> 0 | I23: =MAX(0,SUMIFS(Journals!$L$9:$L$1011204,Journals!$D$9:$D$1011204,">"&$E$7,Journals!$D$9:$D$1011204,"<"&$E$8,Journals!$J$9:$J$1011204,"Interest income from Bank Acc.")-SUMIFS(Journals!$K$9:$K$1011204,Journals!$D$9:$D$1011204,">"&$E$7,Journals!$D$9:$D$1011204,"<"&$E$8,Journals!$J$9:$J$1011204,"Interest income from Bank Acc.")) -> 0 | O23: =SUMIFS(Journals!$L$9:$L$1011204,Journals!$D$9:$D$1011204,"<"&$F$7,Journals!$J$9:$J$1011204,"Interest income from Bank Acc.")-SUMIFS(Journals!$K$9:$K$1011204,Journals!$D$9:$D$1011204,"<"&$F$7,Journals!$J$9:$J$1011204,"Interest income from Bank Acc.") -> 0
G24: ='Chart of Accounts'!B22 -> Bank charges and excise duties | H24: =MAX(0,SUMIFS(Journals!$K$9:$K$1011204,Journals!$D$9:$D$1011204,">"&$E$7,Journals!$D$9:$D$1011204,"<"&$E$8,Journals!$J$9:$J$1011204,"Bank charges and excise duties")-SUMIFS(Journals!$L$9:$L$1011204,Journals!$D$9:$D$1011204,">"&$E$7,Journals!$D$9:$D$1011204,"<"&$E$8,Journals!$J$9:$J$1011204,"Bank charges and excise duties")) -> 85743.16 | I24: =MAX(0,SUMIFS(Journals!$L$9:$L$1011204,Journals!$D$9:$D$1011204,">"&$E$7,Journals!$D$9:$D$1011204,"<"&$E$8,Journals!$J$9:$J$1011204,"Bank charges and excise duties")-SUMIFS(Journals!$K$9:$K$1011204,Journals!$D$9:$D$1011204,">"&$E$7,Journals!$D$9:$D$1011204,"<"&$E$8,Journals!$J$9:$J$1011204,"Bank charges and excise duties")) -> 0 | N24: =SUMIFS(Journals!$K$9:$K$1011204,Journals!$D$9:$D$1011204,"<"&$F$7,Journals!$J$9:$J$1011204,"Bank charges and excise duties")-SUMIFS(Journals!$L$9:$L$1011204,Journals!$D$9:$D$1011204,"<"&$F$7,Journals!$J$9:$J$1011204,"Bank charges and excise duties") -> 462261.41
G25: ='Chart of Accounts'!B23 -> Brokerage commission | H25: =MAX(0,SUMIFS(Journals!$K$9:$K$1011204,Journals!$D$9:$D$1011204,">"&$E$7,Journals!$D$9:$D$1011204,"<"&$E$8,Journals!$J$9:$J$1011204,"brokerage commission")-SUMIFS(Journals!$L$9:$L$1011204,Journals!$D$9:$D$1011204,">"&$E$7,Journals!$D$9:$D$1011204,"<"&$E$8,Journals!$J$9:$J$1011204,"brokerage commission")) -> 950852.53 | I25: =MAX(0,SUMIFS(Journals!$L$9:$L$1011204,Journals!$D$9:$D$1011204,">"&$E$7,Journals!$D$9:$D$1011204,"<"&$E$8,Journals!$J$9:$J$1011204,"brokerage commission")-SUMIFS(Journals!$K$9:$K$1011204,Journals!$D$9:$D$1011204,">"&$E$7,Journals!$D$9:$D$1011204,"<"&$E$8,Journals!$J$9:$J$1011204,"brokerage commission")) -> 0 | N25: =SUMIFS(Journals!$K$9:$K$1011204,Journals!$D$9:$D$1011204,"<"&$F$7,Journals!$J$9:$J$1011204,"brokerage commission")-SUMIFS(Journals!$L$9:$L$1011204,Journals!$D$9:$D$1011204,"<"&$F$7,Journals!$J$9:$J$1011204,"brokerage commission") -> 2804946.1
G26: ='Chart of Accounts'!B24 -> Unrealized gain on securities | H26: =MAX(0,SUMIFS(Journals!$K$9:$K$1011204,Journals!$D$9:$D$1011204,">"&$E$7,Journals!$D$9:$D$1011204,"<"&$E$8,Journals!$J$9:$J$1011204,"Unrealized gain on securities")-SUMIFS(Journals!$L$9:$L$1011204,Journals!$D$9:$D$1011204,">"&$E$7,Journals!$D$9:$D$1011204,"<"&$E$8,Journals!$J$9:$J$1011204,"Unrealized gain on securities")) -> 0 | I26: =MAX(0,SUMIFS(Journals!$L$9:$L$1011204,Journals!$D$9:$D$1011204,">"&$E$7,Journals!$D$9:$D$1011204,"<"&$E$8,Journals!$J$9:$J$1011204,"Unrealized gain on securities")-SUMIFS(Journals!$K$9:$K$1011204,Journals!$D$9:$D$1011204,">"&$E$7,Journals!$D$9:$D$1011204,"<"&$E$8,Journals!$J$9:$J$1011204,"Unrealized gain on securities")) -> 2872990.2 | O26: =SUMIFS(Journals!$L$9:$L$1011204,Journals!$D$9:$D$1011204,"<"&$F$7,Journals!$J$9:$J$1011204,"unrealized gain on securities")-SUMIFS(Journals!$K$9:$K$1011204,Journals!$D$9:$D$1011204,"<"&$F$7,Journals!$J$9:$J$1011204,"unrealized gain on securities") -> 88315901
G27: Unrealized gain on T-Bill | H27: =MAX(0,SUMIFS(Journals!$K$9:$K$1011204,Journals!$D$9:$D$1011204,">"&$E$7,Journals!$D$9:$D$1011204,"<"&$E$8,Journals!$J$9:$J$1011204,"Unrealized gain on T-Bill")-SUMIFS(Journals!$L$9:$L$1011204,Journals!$D$9:$D$1011204,">"&$E$7,Journals!$D$9:$D$1011204,"<"&$E$8,Journals!$J$9:$J$1011204,"Unrealized gain on T-Bill")) -> 0 | I27: =MAX(0,SUMIFS(Journals!$L$9:$L$1011204,Journals!$D$9:$D$1011204,">"&$E$7,Journals!$D$9:$D$1011204,"<"&$E$8,Journals!$J$9:$J$1011204,"Unrealized gain on T-Bill")-SUMIFS(Journals!$K$9:$K$1011204,Journals!$D$9:$D$1011204,">"&$E$7,Journals!$D$9:$D$1011204,"<"&$E$8,Journals!$J$9:$J$1011204,"Unrealized gain on T-Bill")) -> 0 | O27: =SUMIFS(Journals!$L$9:$L$1011204,Journals!$D$9:$D$1011204,"<"&$F$7,Journals!$J$9:$J$1011204,"Unrealized gain on T-Bill")-SUMIFS(Journals!$K$9:$K$1011204,Journals!$D$9:$D$1011204,"<"&$F$7,Journals!$J$9:$J$1011204,"Unrealized gain on T-Bill") -> 0
G28: Unrealized gain on T-Bond | H28: =MAX(0,SUMIFS(Journals!$K$9:$K$1011204,Journals!$D$9:$D$1011204,">"&$E$7,Journals!$D$9:$D$1011204,"<"&$E$8,Journals!$J$9:$J$1011204,"Unrealized gain on T-Bond")-SUMIFS(Journals!$L$9:$L$1011204,Journals!$D$9:$D$1011204,">"&$E$7,Journals!$D$9:$D$1011204,"<"&$E$8,Journals!$J$9:$J$1011204,"Unrealized gain on T-Bond")) -> 304567.49 | I28: =MAX(0,SUMIFS(Journals!$L$9:$L$1011204,Journals!$D$9:$D$1011204,">"&$E$7,Journals!$D$9:$D$1011204,"<"&$E$8,Journals!$J$9:$J$1011204,"Unrealized gain on T-Bond")-SUMIFS(Journals!$K$9:$K$1011204,Journals!$D$9:$D$1011204,">"&$E$7,Journals!$D$9:$D$1011204,"<"&$E$8,Journals!$J$9:$J$1011204,"Unrealized gain on T-Bond")) -> 0 | O28: =SUMIFS(Journals!$L$9:$L$1011204,Journals!$D$9:$D$1011204,"<"&$F$7,Journals!$J$9:$J$1011204,"Unrealized gain on T-Bond")-SUMIFS(Journals!$K$9:$K$1011204,Journals!$D$9:$D$1011204,"<"&$F$7,Journals!$J$9:$J$1011204,"Unrealized gain on T-Bond") -> 304567.49
G29: Interest income from T-Bill | H29: =MAX(0,SUMIFS(Journals!$K$9:$K$1011204,Journals!$D$9:$D$1011204,">"&$E$7,Journals!$D$9:$D$1011204,"<"&$E$8,Journals!$J$9:$J$1011204,"Interest income from T-Bill")-SUMIFS(Journals!$L$9:$L$1011204,Journals!$D$9:$D$1011204,">"&$E$7,Journals!$D$9:$D$1011204,"<"&$E$8,Journals!$J$9:$J$1011204,"Interest income from T-Bill")) -> 0 | I29: =MAX(0,SUMIFS(Journals!$L$9:$L$1011204,Journals!$D$9:$D$1011204,">"&$E$7,Journals!$D$9:$D$1011204,"<"&$E$8,Journals!$J$9:$J$1011204,"Interest income from T-Bill")-SUMIFS(Journals!$K$9:$K$1011204,Journals!$D$9:$D$1011204,">"&$E$7,Journals!$D$9:$D$1011204,"<"&$E$8,Journals!$J$9:$J$1011204,"Interest income from T-Bill")) -> 0 | O29: =SUMIFS(Journals!$L$9:$L$1011204,Journals!$D$9:$D$1011204,"<"&$F$7,Journals!$J$9:$J$1011204,"Interest income from T-Bill")-SUMIFS(Journals!$K$9:$K$1011204,Journals!$D$9:$D$1011204,"<"&$F$7,Journals!$J$9:$J$1011204,"Interest income from T-Bill") -> 0
G30: Interest income from T-Bond | H30: =MAX(0,SUMIFS(Journals!$K$9:$K$1011204,Journals!$D$9:$D$1011204,">"&$E$7,Journals!$D$9:$D$1011204,"<"&$E$8,Journals!$J$9:$J$1011204,"Interest income from T-Bond")-SUMIFS(Journals!$L$9:$L$1011204,Journals!$D$9:$D$1011204,">"&$E$7,Journals!$D$9:$D$1011204,"<"&$E$8,Journals!$J$9:$J$1011204,"Interest income from T-Bond")) -> 0 | I30: =MAX(0,SUMIFS(Journals!$L$9:$L$1011204,Journals!$D$9:$D$1011204,">"&$E$7,Journals!$D$9:$D$1011204,"<"&$E$8,Journals!$J$9:$J$1011204,"Interest income from T-Bond")-SUMIFS(Journals!$K$9:$K$1011204,Journals!$D$9:$D$1011204,">"&$E$7,Journals!$D$9:$D$1011204,"<"&$E$8,Journals!$J$9:$J$1011204,"Interest income from T-Bond")) -> 0 | O30: =SUMIFS(Journals!$L$9:$L$1011204,Journals!$D$9:$D$1011204,"<"&$F$7,Journals!$J$9:$J$1011204,"Interest income from T-Bond")-SUMIFS(Journals!$K$9:$K$1011204,Journals!$D$9:$D$1011204,"<"&$F$7,Journals!$J$9:$J$1011204,"Interest income from T-Bond") -> 0
G31: ='Chart of Accounts'!B27 -> Unrealized loss on securities | H31: =MAX(0,SUMIFS(Journals!$K$9:$K$1011204,Journals!$D$9:$D$1011204,">"&$E$7,Journals!$D$9:$D$1011204,"<"&$E$8,Journals!$J$9:$J$1011204,"Unrealized loss on securities")-SUMIFS(Journals!$L$9:$L$1011204,Journals!$D$9:$D$1011204,">"&$E$7,Journals!$D$9:$D$1011204,"<"&$E$8,Journals!$J$9:$J$1011204,"Unrealized loss on securities")) -> 0 | I31: =MAX(0,SUMIFS(Journals!$L$9:$L$1011204,Journals!$D$9:$D$1011204,">"&$E$7,Journals!$D$9:$D$1011204,"<"&$E$8,Journals!$J$9:$J$1011204,"Unrealized loss on securities")-SUMIFS(Journals!$K$9:$K$1011204,Journals!$D$9:$D$1011204,">"&$E$7,Journals!$D$9:$D$1011204,"<"&$E$8,Journals!$J$9:$J$1011204,"Unrealized loss on securities")) -> 0 | N31: =SUMIFS(Journals!K9:K1011204,Journals!D9:D1011204,"<"&F7,Journals!J9:J1011204,"unrealized loss on securities")-SUMIFS(Journals!L9:L1011204,Journals!D9:D1011204,"<"&F7,Journals!J9:J1011204,"unrealized loss on securities") -> 87355603
G32: ='Chart of Accounts'!B28 -> Amortization of preliminary and issue expense | H32: =MAX(0,SUMIFS(Journals!$K$9:$K$1011204,Journals!$D$9:$D$1011204,">"&$E$7,Journals!$D$9:$D$1011204,"<"&$E$8,Journals!$J$9:$J$1011204,"Amortization of preliminary and issue expense")-SUMIFS(Journals!$L$9:$L$1011204,Journals!$D$9:$D$1011204,">"&$E$7,Journals!$D$9:$D$1011204,"<"&$E$8,Journals!$J$9:$J$1011204,"Amortization of preliminary and issue expense")) -> 142464.68 | I32: =MAX(0,SUMIFS(Journals!$L$9:$L$1011204,Journals!$D$9:$D$1011204,">"&$E$7,Journals!$D$9:$D$1011204,"<"&$E$8,Journals!$J$9:$J$1011204,"Amortization of preliminary and issue expense")-SUMIFS(Journals!$K$9:$K$1011204,Journals!$D$9:$D$1011204,">"&$E$7,Journals!$D$9:$D$1011204,"<"&$E$8,Journals!$J$9:$J$1011204,"Amortization of preliminary and issue expense")) -> 0 | N32: =SUMIFS(Journals!$K$9:$K$1011204,Journals!$D$9:$D$1011204,"<"&$F$7,Journals!$J$9:$J$1011204,"Amortization of preliminary and issue expense")-SUMIFS(Journals!$L$9:$L$1011204,Journals!$D$9:$D$1011204,"<"&$F$7,Journals!$J$9:$J$1011204,"Amortization of preliminary and issue expense") -> 683672.49
G33: ='Chart of Accounts'!B29 -> Management Fee | H33: =MAX(0,SUMIFS(Journals!$K$9:$K$1011204,Journals!$D$9:$D$1011204,">"&$E$7,Journals!$D$9:$D$1011204,"<"&$E$8,Journals!$J$9:$J$1011204,"management fee")-SUMIFS(Journals!$L$9:$L$1011204,Journals!$D$9:$D$1011204,">"&$E$7,Journals!$D$9:$D$1011204,"<"&$E$8,Journals!$J$9:$J$1011204,"management fee")) -> 3748377.1 | I33: =MAX(0,SUMIFS(Journals!$L$9:$L$1011204,Journals!$D$9:$D$1011204,">"&$E$7,Journals!$D$9:$D$1011204,"<"&$E$8,Journals!$J$9:$J$1011204,"management fee")-SUMIFS(Journals!$K$9:$K$1011204,Journals!$D$9:$D$1011204,">"&$E$7,Journals!$D$9:$D$1011204,"<"&$E$8,Journals!$J$9:$J$1011204,"management fee")) -> 0 | N33: =SUMIFS(Journals!$K$9:$K$1011204,Journals!$D$9:$D$1011204,"<"&$F$7,Journals!$J$9:$J$1011204,"management fee")-SUMIFS(Journals!$L$9:$L$1011204,Journals!$D$9:$D$1011204,"<"&$F$7,Journals!$J$9:$J$1011204,"management fee") -> 16063191
G34: ='Chart of Accounts'!B30 -> Trustee fee | H34: =MAX(0,SUMIFS(Journals!$K$9:$K$1011204,Journals!$D$9:$D$1011204,">"&$E$7,Journals!$D$9:$D$1011204,"<"&$E$8,Journals!$J$9:$J$1011204,"trustee fee")-SUMIFS(Journals!$L$9:$L$1011204,Journals!$D$9:$D$1011204,">"&$E$7,Journals!$D$9:$D$1011204,"<"&$E$8,Journals!$J$9:$J$1011204,"trustee fee")) -> 174953.16 | I34: =MAX(0,SUMIFS(Journals!$L$9:$L$1011204,Journals!$D$9:$D$1011204,">"&$E$7,Journals!$D$9:$D$1011204,"<"&$E$8,Journals!$J$9:$J$1011204,"trustee fee")-SUMIFS(Journals!$K$9:$K$1011204,Journals!$D$9:$D$1011204,">"&$E$7,Journals!$D$9:$D$1011204,"<"&$E$8,Journals!$J$9:$J$1011204,"trustee fee")) -> 0 | N34: =SUMIFS(Journals!$K$9:$K$1011204,Journals!$D$9:$D$1011204,"<"&$F$7,Journals!$J$9:$J$1011204,"trustee fee")-SUMIFS(Journals!$L$9:$L$1011204,Journals!$D$9:$D$1011204,"<"&$F$7,Journals!$J$9:$J$1011204,"trustee fee") -> 795270.75
G35: ='Chart of Accounts'!B31 -> BSEC Annual Fee | H35: =MAX(0,SUMIFS(Journals!$K$9:$K$1011204,Journals!$D$9:$D$1011204,">"&$E$7,Journals!$D$9:$D$1011204,"<"&$E$8,Journals!$J$9:$J$1011204,"bsec annual fee")-SUMIFS(Journals!$L$9:$L$1011204,Journals!$D$9:$D$1011204,">"&$E$7,Journals!$D$9:$D$1011204,"<"&$E$8,Journals!$J$9:$J$1011204,"bsec annual fee")) -> 154911.16 | I35: =MAX(0,SUMIFS(Journals!$L$9:$L$1011204,Journals!$D$9:$D$1011204,">"&$E$7,Journals!$D$9:$D$1011204,"<"&$E$8,Journals!$J$9:$J$1011204,"bsec annual fee")-SUMIFS(Journals!$K$9:$K$1011204,Journals!$D$9:$D$1011204,">"&$E$7,Journals!$D$9:$D$1011204,"<"&$E$8,Journals!$J$9:$J$1011204,"bsec annual fee")) -> 0 | N35: =SUMIFS(Journals!$K$9:$K$1011204,Journals!$D$9:$D$1011204,"<"&$F$7,Journals!$J$9:$J$1011204,"bsec annual fee")-SUMIFS(Journals!$L$9:$L$1011204,Journals!$D$9:$D$1011204,"<"&$F$7,Journals!$J$9:$J$1011204,"bsec annual fee") -> 797798.57
G36: ='Chart of Accounts'!B32 -> Audit fee | H36: =MAX(0,SUMIFS(Journals!$K$9:$K$1011204,Journals!$D$9:$D$1011204,">"&$E$7,Journals!$D$9:$D$1011204,"<"&$E$8,Journals!$J$9:$J$1011204,"audit fee")-SUMIFS(Journals!$L$9:$L$1011204,Journals!$D$9:$D$1011204,">"&$E$7,Journals!$D$9:$D$1011204,"<"&$E$8,Journals!$J$9:$J$1011204,"audit fee")) -> 46000 | I36: =MAX(0,SUMIFS(Journals!$L$9:$L$1011204,Journals!$D$9:$D$1011204,">"&$E$7,Journals!$D$9:$D$1011204,"<"&$E$8,Journals!$J$9:$J$1011204,"audit fee")-SUMIFS(Journals!$K$9:$K$1011204,Journals!$D$9:$D$1011204,">"&$E$7,Journals!$D$9:$D$1011204,"<"&$E$8,Journals!$J$9:$J$1011204,"audit fee")) -> 0 | N36: =SUMIFS(Journals!$K$9:$K$1011204,Journals!$D$9:$D$1011204,"<"&$F$7,Journals!$J$9:$J$1011204,"audit fee")-SUMIFS(Journals!$L$9:$L$1011204,Journals!$D$9:$D$1011204,"<"&$F$7,Journals!$J$9:$J$1011204,"audit fee") -> 201000
G37: ='Chart of Accounts'!B33 -> CDBL charges | H37: =MAX(0,SUMIFS(Journals!$K$9:$K$1011204,Journals!$D$9:$D$1011204,">"&$E$7,Journals!$D$9:$D$1011204,"<"&$E$8,Journals!$J$9:$J$1011204,"cdbl charges")-SUMIFS(Journals!$L$9:$L$1011204,Journals!$D$9:$D$1011204,">"&$E$7,Journals!$D$9:$D$1011204,"<"&$E$8,Journals!$J$9:$J$1011204,"cdbl charges")) -> 88735.48 | I37: =MAX(0,SUMIFS(Journals!$L$9:$L$1011204,Journals!$D$9:$D$1011204,">"&$E$7,Journals!$D$9:$D$1011204,"<"&$E$8,Journals!$J$9:$J$1011204,"cdbl charges")-SUMIFS(Journals!$K$9:$K$1011204,Journals!$D$9:$D$1011204,">"&$E$7,Journals!$D$9:$D$1011204,"<"&$E$8,Journals!$J$9:$J$1011204,"cdbl charges")) -> 0 | N37: =SUMIFS(Journals!$K$9:$K$1011204,Journals!$D$9:$D$1011204,"<"&$F$7,Journals!$J$9:$J$1011204,"cdbl charges")-SUMIFS(Journals!$L$9:$L$1011204,Journals!$D$9:$D$1011204,"<"&$F$7,Journals!$J$9:$J$1011204,"cdbl charges") -> 247693.19
G38: ='Chart of Accounts'!B34 -> Fair value adjustment | H38: =MAX(0,SUMIFS(Journals!$K$9:$K$1011204,Journals!$D$9:$D$1011204,">"&$E$7,Journals!$D$9:$D$1011204,"<"&$E$8,Journals!$J$9:$J$1011204,"Fair value adjustment")-SUMIFS(Journals!$L$9:$L$1011204,Journals!$D$9:$D$1011204,">"&$E$7,Journals!$D$9:$D$1011204,"<"&$E$8,Journals!$J$9:$J$1011204,"Fair value adjustment")) -> 2872990.2 | I38: =MAX(0,SUMIFS(Journals!$L$9:$L$1011204,Journals!$D$9:$D$1011204,">"&$E$7,Journals!$D$9:$D$1011204,"<"&$E$8,Journals!$J$9:$J$1011204,"fair value adjustment")-SUMIFS(Journals!$K$9:$K$1011204,Journals!$D$9:$D$1011204,">"&$E$7,Journals!$D$9:$D$1011204,"<"&$E$8,Journals!$J$9:$J$1011204,"fair value adjustment")) -> 0 | J38: =MAX(0,SUMIFS(Journals!K9:K1011204,Journals!D9:D1011204,"<"&F7,Journals!J9:J1011204,"fair value adjustment")-SUMIFS(Journals!L9:L1011204,Journals!D9:D1011204,"<"&F7,Journals!J9:J1011204,"fair value adjustment")) -> 960297.45 | K38: =MAX(0,SUMIFS(Journals!L9:L1011204,Journals!D9:D1011204,"<"&F7,Journals!J9:J1011204,"Fair value adjustment")-SUMIFS(Journals!K9:K1011204,Journals!D9:D1011204,"<"&F7,Journals!J9:J1011204,"fair value adjustment")) -> 0 | L38: =MAX(0,H38-I38+J38-K38) -> 3833287.7 | M38: =MAX(0,I38-H38-J38+K38) -> 0
G39: Fair value adjustment T-Bill | H39: =MAX(0,SUMIFS(Journals!$K$9:$K$1011204,Journals!$D$9:$D$1011204,">"&$E$7,Journals!$D$9:$D$1011204,"<"&$E$8,Journals!$J$9:$J$1011204,"Fair value adjustment T-Bill")-SUMIFS(Journals!$L$9:$L$1011204,Journals!$D$9:$D$1011204,">"&$E$7,Journals!$D$9:$D$1011204,"<"&$E$8,Journals!$J$9:$J$1011204,"Fair value adjustment T-Bill")) -> 0 | I39: =MAX(0,SUMIFS(Journals!$L$9:$L$1011204,Journals!$D$9:$D$1011204,">"&$E$7,Journals!$D$9:$D$1011204,"<"&$E$8,Journals!$J$9:$J$1011204,"Fair value adjustment T-Bill")-SUMIFS(Journals!$K$9:$K$1011204,Journals!$D$9:$D$1011204,">"&$E$7,Journals!$D$9:$D$1011204,"<"&$E$8,Journals!$J$9:$J$1011204,"Fair value adjustment T-Bill")) -> 0 | J39: =MAX(0,SUMIFS(Journals!K10:K1011205,Journals!D10:D1011205,"<"&F8,Journals!J10:J1011205,"Fair value adjustment T-Bill")-SUMIFS(Journals!L10:L1011205,Journals!D10:D1011205,"<"&F8,Journals!J10:J1011205,"Fair value adjustment T-Bill")) -> 0 | K39: =MAX(0,SUMIFS(Journals!L10:L1011205,Journals!D10:D1011205,"<"&F8,Journals!J10:J1011205,"Fair value adjustment T-Bill")-SUMIFS(Journals!K10:K1011205,Journals!D10:D1011205,"<"&F8,Journals!J10:J1011205,"Fair value adjustment T-Bill")) -> 0 | L39: =MAX(0,H39-I39+J39-K39) -> 0 | M39: =MAX(0,I39-H39-J39+K39) -> 0
G40: Fair value adjustment T-Bond | H40: =MAX(0,SUMIFS(Journals!$K$9:$K$1011204,Journals!$D$9:$D$1011204,">"&$E$7,Journals!$D$9:$D$1011204,"<"&$E$8,Journals!$J$9:$J$1011204,"Fair value adjustment T-Bond")-SUMIFS(Journals!$L$9:$L$1011204,Journals!$D$9:$D$1011204,">"&$E$7,Journals!$D$9:$D$1011204,"<"&$E$8,Journals!$J$9:$J$1011204,"Fair value adjustment T-Bond")) -> 0 | I40: =MAX(0,SUMIFS(Journals!$L$9:$L$1011204,Journals!$D$9:$D$1011204,">"&$E$7,Journals!$D$9:$D$1011204,"<"&$E$8,Journals!$J$9:$J$1011204,"Fair value adjustment T-Bond")-SUMIFS(Journals!$K$9:$K$1011204,Journals!$D$9:$D$1011204,">"&$E$7,Journals!$D$9:$D$1011204,"<"&$E$8,Journals!$J$9:$J$1011204,"Fair value adjustment T-Bond")) -> 304567.49 | J40: =MAX(0,SUMIFS(Journals!K9:K1011204,Journals!D9:D1011204,"<"&F7,Journals!J9:J1011204,"Fair value adjustment T-Bond")-SUMIFS(Journals!L9:L1011204,Journals!D9:D1011204,"<"&F7,Journals!J9:J1011204,"Fair value adjustment T-Bond")) -> 304567.49 | K40: =MAX(0,SUMIFS(Journals!L9:L1011204,Journals!D9:D1011204,"<"&F7,Journals!J9:J1011204,"Fair value adjustment T-Bond")-SUMIFS(Journals!K9:K1011204,Journals!D9:D1011204,"<"&F7,Journals!J9:J1011204,"Fair value adjustment T-Bond")) -> 0 | L40: =MAX(0,H40-I40+J40-K40) -> 0 | M40: =MAX(0,I40-H40-J40+K40) -> 0
G41: ='Chart of Accounts'!B37 -> Interest receivables from FDR | H41: =MAX(0,SUMIFS(Journals!$K$9:$K$1011204,Journals!$D$9:$D$1011204,">"&$E$7,Journals!$D$9:$D$1011204,"<"&$E$8,Journals!$J$9:$J$1011204,"Interest receivables from FDR")-SUMIFS(Journals!$L$9:$L$1011204,Journals!$D$9:$D$1011204,">"&$E$7,Journals!$D$9:$D$1011204,"<"&$E$8,Journals!$J$9:$J$1011204,"Interest receivables from FDR")) -> 0 | I41: =MAX(0,SUMIFS(Journals!$L$9:$L$1011204,Journals!$D$9:$D$1011204,">"&$E$7,Journals!$D$9:$D$1011204,"<"&$E$8,Journals!$J$9:$J$1011204,"Interest receivables from FDR")-SUMIFS(Journals!$K$9:$K$1011204,Journals!$D$9:$D$1011204,">"&$E$7,Journals!$D$9:$D$1011204,"<"&$E$8,Journals!$J$9:$J$1011204,"Interest receivables from FDR")) -> 74749.795 | J41: =SUMIFS(Journals!$K$9:$K$1011204,Journals!$D$9:$D$1011204,"<"&$F$7,Journals!$J$9:$J$1011204,"Interest receivables from FDR")-SUMIFS(Journals!$L$9:$L$1011204,Journals!$D$9:$D$1011204,"<"&$F$7,Journals!$J$9:$J$1011204,"Interest receivables from FDR") -> 193583.33 | L41: =J41+H41-I41 -> 118833.54
G42: Interest receivables from Renata Pref. Share | H42: =MAX(0,SUMIFS(Journals!$K$9:$K$1011204,Journals!$D$9:$D$1011204,">"&$E$7,Journals!$D$9:$D$1011204,"<"&$E$8,Journals!$J$9:$J$1011204,"Interest receivables from Renata Pref. Share")-SUMIFS(Journals!$L$9:$L$1011204,Journals!$D$9:$D$1011204,">"&$E$7,Journals!$D$9:$D$1011204,"<"&$E$8,Journals!$J$9:$J$1011204,"Interest receivables from Renata Pref. Share")) -> 402053.57 | I42: =MAX(0,SUMIFS(Journals!$L$9:$L$1011204,Journals!$D$9:$D$1011204,">"&$E$7,Journals!$D$9:$D$1011204,"<"&$E$8,Journals!$J$9:$J$1011204,"Interest receivables from Renata Pref. Share")-SUMIFS(Journals!$K$9:$K$1011204,Journals!$D$9:$D$1011204,">"&$E$7,Journals!$D$9:$D$1011204,"<"&$E$8,Journals!$J$9:$J$1011204,"Interest receivables from Renata Pref. Share")) -> 0 | J42: =SUMIFS(Journals!$K$9:$K$1011204,Journals!$D$9:$D$1011204,"<"&$F$7,Journals!$J$9:$J$1011204,"Interest receivables from Renata Pref. Share")-SUMIFS(Journals!$L$9:$L$1011204,Journals!$D$9:$D$1011204,"<"&$F$7,Journals!$J$9:$J$1011204,"Interest receivables from Renata Pref. Share") -> 0 | L42: =J42+H42-I42 -> 402053.57
G43: ='Chart of Accounts'!B40 -> Payable to broker | H43: =MAX(0,SUMIFS(Journals!$K$9:$K$1011204,Journals!$D$9:$D$1011204,">"&$E$7,Journals!$D$9:$D$1011204,"<"&$E$8,Journals!$J$9:$J$1011204,"payable to broker")-SUMIFS(Journals!$L$9:$L$1011204,Journals!$D$9:$D$1011204,">"&$E$7,Journals!$D$9:$D$1011204,"<"&$E$8,Journals!$J$9:$J$1011204,"payable to broker")) -> 0 | I43: =MAX(0,SUMIFS(Journals!$L$9:$L$1011204,Journals!$D$9:$D$1011204,">"&$E$7,Journals!$D$9:$D$1011204,"<"&$E$8,Journals!$J$9:$J$1011204,"payable to broker")-SUMIFS(Journals!$K$9:$K$1011204,Journals!$D$9:$D$1011204,">"&$E$7,Journals!$D$9:$D$1011204,"<"&$E$8,Journals!$J$9:$J$1011204,"payable to broker")) -> 64518.847 | K43: =SUMIFS(Journals!$L$9:$L$1011204,Journals!$D$9:$D$1011204,"<"&$F$7,Journals!$J$9:$J$1011204,"payable to broker")-SUMIFS(Journals!$K$9:$K$1011204,Journals!$D$9:$D$1011204,"<"&$F$7,Journals!$J$9:$J$1011204,"payable to broker") -> 0.0069999695 | M43: =K43+I43-H43 -> 64518.854
G44: ='Chart of Accounts'!B41 -> Other operating expenses | H44: =MAX(0,SUMIFS(Journals!$K$9:$K$1011204,Journals!$D$9:$D$1011204,">"&$E$7,Journals!$D$9:$D$1011204,"<"&$E$8,Journals!$J$9:$J$1011204,"OTHER OPERATING EXPENSES")-SUMIFS(Journals!$L$9:$L$1011204,Journals!$D$9:$D$1011204,">"&$E$7,Journals!$D$9:$D$1011204,"<"&$E$8,Journals!$J$9:$J$1011204,"OTHER OPERATING EXPENSES")) -> 85162.5 | I44: =MAX(0,SUMIFS(Journals!$L$9:$L$1011204,Journals!$D$9:$D$1011204,">"&$E$7,Journals!$D$9:$D$1011204,"<"&$E$8,Journals!$J$9:$J$1011204,"OTHER OPERATING EXPENSES")-SUMIFS(Journals!$K$9:$K$1011204,Journals!$D$9:$D$1011204,">"&$E$7,Journals!$D$9:$D$1011204,"<"&$E$8,Journals!$J$9:$J$1011204,"OTHER OPERATING EXPENSES")) -> 0 | N44: =SUMIFS(Journals!$K$9:$K$1011204,Journals!$D$9:$D$1011204,"<"&$F$7,Journals!$J$9:$J$1011204,"OTHER OPERATING EXPENSES")-SUMIFS(Journals!$L$9:$L$1011204,Journals!$D$9:$D$1011204,"<"&$F$7,Journals!$J$9:$J$1011204,"OTHER OPERATING EXPENSES") -> 649143.36
G45: ='Chart of Accounts'!B42 -> Dividend income | H45: =MAX(0,SUMIFS(Journals!$K$9:$K$1011204,Journals!$D$9:$D$1011204,">"&$E$7,Journals!$D$9:$D$1011204,"<"&$E$8,Journals!$J$9:$J$1011204,"dividend income")-SUMIFS(Journals!$L$9:$L$1011204,Journals!$D$9:$D$1011204,">"&$E$7,Journals!$D$9:$D$1011204,"<"&$E$8,Journals!$J$9:$J$1011204,"dividend income")) -> 0 | I45: =MAX(0,SUMIFS(Journals!$L$9:$L$1011204,Journals!$D$9:$D$1011204,">"&$E$7,Journals!$D$9:$D$1011204,"<"&$E$8,Journals!$J$9:$J$1011204,"dividend income")-SUMIFS(Journals!$K$9:$K$1011204,Journals!$D$9:$D$1011204,">"&$E$7,Journals!$D$9:$D$1011204,"<"&$E$8,Journals!$J$9:$J$1011204,"dividend income")) -> 5060840.9 | O45: =SUMIFS(Journals!$L$9:$L$1011204,Journals!$D$9:$D$1011204,"<"&$F$7,Journals!$J$9:$J$1011204,"dividend income")-SUMIFS(Journals!$K$9:$K$1011204,Journals!$D$9:$D$1011204,"<"&$F$7,Journals!$J$9:$J$1011204,"dividend income") -> 19720428
G46: ='Chart of Accounts'!B43 -> Dividend receivable | H46: =MAX(0,SUMIFS(Journals!$K$9:$K$1011204,Journals!$D$9:$D$1011204,">"&$E$7,Journals!$D$9:$D$1011204,"<"&$E$8,Journals!$J$9:$J$1011204,"dividend receivable")-SUMIFS(Journals!$L$9:$L$1011204,Journals!$D$9:$D$1011204,">"&$E$7,Journals!$D$9:$D$1011204,"<"&$E$8,Journals!$J$9:$J$1011204,"dividend receivable")) -> 721299.3 | I46: =MAX(0,SUMIFS(Journals!$L$9:$L$1011204,Journals!$D$9:$D$1011204,">"&$E$7,Journals!$D$9:$D$1011204,"<"&$E$8,Journals!$J$9:$J$1011204,"dividend receivable")-SUMIFS(Journals!$K$9:$K$1011204,Journals!$D$9:$D$1011204,">"&$E$7,Journals!$D$9:$D$1011204,"<"&$E$8,Journals!$J$9:$J$1011204,"dividend receivable")) -> 0 | J46: =SUMIFS(Journals!$K$9:$K$1011204,Journals!$D$9:$D$1011204,"<"&$F$7,Journals!$J$9:$J$1011204,"dividend receivable")-SUMIFS(Journals!$L$9:$L$1011204,Journals!$D$9:$D$1011204,"<"&$F$7,Journals!$J$9:$J$1011204,"dividend receivable") -> 512435.2 | L46: =J46+H46-I46 -> 1233734.5
G47: ='Chart of Accounts'!B44 -> Custodian fee | H47: =MAX(0,SUMIFS(Journals!$K$9:$K$1011204,Journals!$D$9:$D$1011204,">"&$E$7,Journals!$D$9:$D$1011204,"<"&$E$8,Journals!$J$9:$J$1011204,"custodian fee")-SUMIFS(Journals!$L$9:$L$1011204,Journals!$D$9:$D$1011204,">"&$E$7,Journals!$D$9:$D$1011204,"<"&$E$8,Journals!$J$9:$J$1011204,"custodian fee")) -> 109206.14 | N47: =SUMIFS(Journals!$K$9:$K$1011204,Journals!$D$9:$D$1011204,"<"&$F$7,Journals!$J$9:$J$1011204,"custodian fee")-SUMIFS(Journals!$L$9:$L$1011204,Journals!$D$9:$D$1011204,"<"&$F$7,Journals!$J$9:$J$1011204,"custodian fee") -> 522990.83
G48: ='Chart of Accounts'!B45 -> IPO Application | H48: =MAX(0,SUMIFS(Journals!$K$9:$K$1011204,Journals!$D$9:$D$1011204,">"&$E$7,Journals!$D$9:$D$1011204,"<"&$E$8,Journals!$J$9:$J$1011204,"IPO APPLICATION")-SUMIFS(Journals!$L$9:$L$1011204,Journals!$D$9:$D$1011204,">"&$E$7,Journals!$D$9:$D$1011204,"<"&$E$8,Journals!$J$9:$J$1011204,"IPO APPLICATION")) -> 0 | I48: =MAX(0,SUMIFS(Journals!$L$9:$L$1011204,Journals!$D$9:$D$1011204,">"&$E$7,Journals!$D$9:$D$1011204,"<"&$E$8,Journals!$J$9:$J$1011204,"IPO APPLICATION")-SUMIFS(Journals!$K$9:$K$1011204,Journals!$D$9:$D$1011204,">"&$E$7,Journals!$D$9:$D$1011204,"<"&$E$8,Journals!$J$9:$J$1011204,"IPO APPLICATION")) -> 0 | J48: =SUMIFS(Journals!$K$9:$K$1011204,Journals!$D$9:$D$1011204,"<"&$F$7,Journals!$J$9:$J$1011204,"IPO APPLICATION")-SUMIFS(Journals!$L$9:$L$1011204,Journals!$D$9:$D$1011204,"<"&$F$7,Journals!$J$9:$J$1011204,"IPO APPLICATION") -> 0 | L48: =J48+H48-I48 -> 0
G49: ='Chart of Accounts'!B46 -> IPO Application Fee | H49: =MAX(0,SUMIFS(Journals!$K$9:$K$1011204,Journals!$D$9:$D$1011204,">"&$E$7,Journals!$D$9:$D$1011204,"<"&$E$8,Journals!$J$9:$J$1011204,"IPO APPLICATION FEE")-SUMIFS(Journals!$L$9:$L$1011204,Journals!$D$9:$D$1011204,">"&$E$7,Journals!$D$9:$D$1011204,"<"&$E$8,Journals!$J$9:$J$1011204,"IPO APPLICATION FEE")) -> 0 | N49: =SUMIFS(Journals!$K$9:$K$1011204,Journals!$D$9:$D$1011204,"<"&$F$7,Journals!$J$9:$J$1011204,"IPO APPLICATION FEE")-SUMIFS(Journals!$L$9:$L$1011204,Journals!$D$9:$D$1011204,"<"&$F$7,Journals!$J$9:$J$1011204,"IPO APPLICATION FEE") -> 106000
G50: Realized gain | H50: =MAX(0,SUMIFS(Journals!$K$9:$K$1011204,Journals!$D$9:$D$1011204,">"&$E$7,Journals!$D$9:$D$1011204,"<"&$E$8,Journals!$J$9:$J$1011204,"realized gain")-SUMIFS(Journals!$L$9:$L$1011204,Journals!$D$9:$D$1011204,">"&$E$7,Journals!$D$9:$D$1011204,"<"&$E$8,Journals!$J$9:$J$1011204,"realized gain")) -> 0 | I50: =MAX(0,SUMIFS(Journals!$L$9:$L$1011204,Journals!$D$9:$D$1011204,">"&$E$7,Journals!$D$9:$D$1011204,"<"&$E$8,Journals!$J$9:$J$1011204,"realized gain")-SUMIFS(Journals!$K$9:$K$1011204,Journals!$D$9:$D$1011204,">"&$E$7,Journals!$D$9:$D$1011204,"<"&$E$8,Journals!$J$9:$J$1011204,"realized gain")) -> 9695579.5 | O50: =SUMIFS(Journals!$L$9:$L$1011204,Journals!$D$9:$D$1011204,"<"&$F$7,Journals!$J$9:$J$1011204,"realized gain")-SUMIFS(Journals!$K$9:$K$1011204,Journals!$D$9:$D$1011204,"<"&$F$7,Journals!$J$9:$J$1011204,"realized gain") -> 76515362
G51: Realized gain on T-Bill | H51: =MAX(0,SUMIFS(Journals!$K$9:$K$1011204,Journals!$D$9:$D$1011204,">"&$E$7,Journals!$D$9:$D$1011204,"<"&$E$8,Journals!$J$9:$J$1011204,"realized gain on T-Bill")-SUMIFS(Journals!$L$9:$L$1011204,Journals!$D$9:$D$1011204,">"&$E$7,Journals!$D$9:$D$1011204,"<"&$E$8,Journals!$J$9:$J$1011204,"realized gain on T-Bill")) -> 0 | I51: =MAX(0,SUMIFS(Journals!$L$9:$L$1011204,Journals!$D$9:$D$1011204,">"&$E$7,Journals!$D$9:$D$1011204,"<"&$E$8,Journals!$J$9:$J$1011204,"realized gain on T-Bill")-SUMIFS(Journals!$K$9:$K$1011204,Journals!$D$9:$D$1011204,">"&$E$7,Journals!$D$9:$D$1011204,"<"&$E$8,Journals!$J$9:$J$1011204,"realized gain on T-Bill")) -> 0 | O51: =SUMIFS(Journals!$L$9:$L$1011204,Journals!$D$9:$D$1011204,"<"&$F$7,Journals!$J$9:$J$1011204,"realized gain on T-Bill")-SUMIFS(Journals!$K$9:$K$1011204,Journals!$D$9:$D$1011204,"<"&$F$7,Journals!$J$9:$J$1011204,"realized gain on T-Bill") -> 2509121.3
G52: Realized gain on T-Bond | H52: =MAX(0,SUMIFS(Journals!$K$9:$K$1011204,Journals!$D$9:$D$1011204,">"&$E$7,Journals!$D$9:$D$1011204,"<"&$E$8,Journals!$J$9:$J$1011204,"realized gain on T-Bond")-SUMIFS(Journals!$L$9:$L$1011204,Journals!$D$9:$D$1011204,">"&$E$7,Journals!$D$9:$D$1011204,"<"&$E$8,Journals!$J$9:$J$1011204,"realized gain on T-Bond")) -> 0 | I52: =MAX(0,SUMIFS(Journals!$L$9:$L$1011204,Journals!$D$9:$D$1011204,">"&$E$7,Journals!$D$9:$D$1011204,"<"&$E$8,Journals!$J$9:$J$1011204,"realized gain on T-Bond")-SUMIFS(Journals!$K$9:$K$1011204,Journals!$D$9:$D$1011204,">"&$E$7,Journals!$D$9:$D$1011204,"<"&$E$8,Journals!$J$9:$J$1011204,"realized gain on T-Bond")) -> 5060463.1 | O52: =SUMIFS(Journals!$L$9:$L$1011204,Journals!$D$9:$D$1011204,"<"&$F$7,Journals!$J$9:$J$1011204,"realized gain on T-Bond")-SUMIFS(Journals!$K$9:$K$1011204,Journals!$D$9:$D$1011204,"<"&$F$7,Journals!$J$9:$J$1011204,"realized gain on T-Bond") -> 329067.71
G53: Receivable from broker | H53: =MAX(0,SUMIFS(Journals!$K$9:$K$1011204,Journals!$D$9:$D$1011204,">"&$E$7,Journals!$D$9:$D$1011204,"<"&$E$8,Journals!$J$9:$J$1011204,"receivable from broker")-SUMIFS(Journals!$L$9:$L$1011204,Journals!$D$9:$D$1011204,">"&$E$7,Journals!$D$9:$D$1011204,"<"&$E$8,Journals!$J$9:$J$1011204,"receivable from broker")) -> 1084305.4 | I53: =MAX(0,SUMIFS(Journals!$L$9:$L$1011204,Journals!$D$9:$D$1011204,">"&$E$7,Journals!$D$9:$D$1011204,"<"&$E$8,Journals!$J$9:$J$1011204,"receivable from broker")-SUMIFS(Journals!$K$9:$K$1011204,Journals!$D$9:$D$1011204,">"&$E$7,Journals!$D$9:$D$1011204,"<"&$E$8,Journals!$J$9:$J$1011204,"receivable from broker")) -> 0 | J53: =SUMIFS(Journals!$K$9:$K$1010900,Journals!$D$9:$D$1010900,"<"&$F$7,Journals!$J$9:$J$1010900,"receivable from broker")-SUMIFS(Journals!$L$9:$L$1010900,Journals!$D$9:$D$1010900,"<"&$F$7,Journals!$J$9:$J$1010900,"receivable from broker") -> -0.10579967 | L53: =J53+H53-I53 -> 1084305.3
G54: Dividend Equalization Reserve | H54: =MAX(0,SUMIFS(Journals!$K$9:$K$1011204,Journals!$D$9:$D$1011204,">"&$E$7,Journals!$D$9:$D$1011204,"<"&$E$8,Journals!$J$9:$J$1011204,"dividend equalization reserve")) -> 0 | I54: =MAX(0,SUMIFS(Journals!$L$9:$L$1011204,Journals!$D$9:$D$1011204,">"&$E$7,Journals!$D$9:$D$1011204,"<"&$E$8,Journals!$J$9:$J$1011204,"dividend equalization reserve")) -> 0 | K54: =SUMIFS(Journals!$L$9:$L$1011204,Journals!$D$9:$D$1011204,"<"&$F$7,Journals!$J$9:$J$1011204,"Dividend Equalization Reserve")-SUMIFS(Journals!$K$9:$K$1011204,Journals!$D$9:$D$1011204,"<"&$F$7,Journals!$J$9:$J$1011204,"Dividend Equalization Reserve") -> 150000 | L54: =H54 -> 0 | M54: =K54+I54-H54 -> 150000 | N54: =K54 -> 150000
G55: Retained Earnings | H55: =MAX(0,SUMIFS(Journals!$K$9:$K$1011204,Journals!$D$9:$D$1011204,">"&$E$7,Journals!$D$9:$D$1011204,"<"&$E$8,Journals!$J$9:$J$1011204,"retained earnings")-SUMIFS(Journals!$L$9:$L$1011204,Journals!$D$9:$D$1011204,">"&$E$7,Journals!$D$9:$D$1011204,"<"&$E$8,Journals!$J$9:$J$1011204,"retained earnings")) -> 5412013.5 | I55: =MAX(0,SUMIFS(Journals!$L$9:$L$1011204,Journals!$D$9:$D$1011204,">"&$E$7,Journals!$D$9:$D$1011204,"<"&$E$8,Journals!$J$9:$J$1011204,"retained earnings")-SUMIFS(Journals!$K$9:$K$1011204,Journals!$D$9:$D$1011204,">"&$E$7,Journals!$D$9:$D$1011204,"<"&$E$8,Journals!$J$9:$J$1011204,"retained earnings")) -> 0
G56: Dividend Payable | H56: =MAX(0,SUMIFS(Journals!$K$9:$K$1011204,Journals!$D$9:$D$1011204,">"&$E$7,Journals!$D$9:$D$1011204,"<"&$E$8,Journals!$J$9:$J$1011204,"dividend payable")) -> 5412013.5 | I56: =MAX(0,SUMIFS(Journals!$L$9:$L$1011204,Journals!$D$9:$D$1011204,">"&$E$7,Journals!$D$9:$D$1011204,"<"&$E$8,Journals!$J$9:$J$1011204,"dividend payable")) -> 5412013.5 | J56: =SUMIFS(Journals!$K$9:$K$1010900,Journals!$D$9:$D$1010900,"<"&$F$7,Journals!$J$9:$J$1010900,"Dividend Payable") -> 51481202 | K56: =SUMIFS(Journals!$L$9:$L$1010900,Journals!$D$9:$D$1010900,"<"&$F$7,Journals!$J$9:$J$1010900,"Dividend Payable") -> 51481202 | M56: =I56-H56 -> 0 | N56: =J56 -> 51481202
G57: Withholding Tax Payable | H57: =MAX(0,SUMIFS(Journals!$K$9:$K$1011204,Journals!$D$9:$D$1011204,">"&$E$7,Journals!$D$9:$D$1011204,"<"&$E$8,Journals!$J$9:$J$1011204,"Withholding Tax Payable")) -> 1030512.4 | I57: =MAX(0,SUMIFS(Journals!$L$9:$L$1011204,Journals!$D$9:$D$1011204,">"&$E$7,Journals!$D$9:$D$1011204,"<"&$E$8,Journals!$J$9:$J$1011204,"Withholding Tax Payable")) -> 981966.32 | K57: =SUMIFS(Journals!$L$9:$L$1011204,Journals!$D$9:$D$1011204,"<"&$F$7,Journals!$J$9:$J$1011204,"Withholding Tax Payable")-SUMIFS(Journals!$K$9:$K$1011204,Journals!$D$9:$D$1011204,"<"&$F$7,Journals!$J$9:$J$1011204,"Withholding Tax Payable") -> 69722.7 | M57: =K57+I57-H57 -> 21176.575
G58: Withholding Tax Payable of News Paper | H58: =SUMIFS(Journals!$K$9:$K$1011204,Journals!$D$9:$D$1011204,">"&$E$7,Journals!$D$9:$D$1011204,"<"&$E$8,Journals!$J$9:$J$1011204,"Withholding Tax Payable of News Paper") -> 2562.5 | I58: =MAX(0,SUMIFS(Journals!$L$9:$L$1011204,Journals!$D$9:$D$1011204,">"&$E$7,Journals!$D$9:$D$1011204,"<"&$E$8,Journals!$J$9:$J$1011204,"Withholding Tax Payable of News Paper")) -> 2812.5 | K58: =SUMIFS(Journals!$L$9:$L$1011204,Journals!$D$9:$D$1011204,"<"&$F$7,Journals!$J$9:$J$1011204,"Withholding Tax Payable of News Paper")-SUMIFS(Journals!$K$9:$K$1011204,Journals!$D$9:$D$1011204,"<"&$F$7,Journals!$J$9:$J$1011204,"Withholding Tax Payable of News Paper") -> 250 | M58: =K58+I58-H58 -> 500
G59: Withholding Tax Payable of Telnet | H59: =SUMIFS(Journals!$K$9:$K$1011204,Journals!$D$9:$D$1011204,">"&$E$7,Journals!$D$9:$D$1011204,"<"&$E$8,Journals!$J$9:$J$1011204,"Withholding Tax Payable of Telnet") -> 1425 | I59: =MAX(0,SUMIFS(Journals!$L$9:$L$1011204,Journals!$D$9:$D$1011204,">"&$E$7,Journals!$D$9:$D$1011204,"<"&$E$8,Journals!$J$9:$J$1011204,"Withholding Tax Payable of Telnet")) -> 1500 | K59: =SUMIFS(Journals!$L$9:$L$1011204,Journals!$D$9:$D$1011204,"<"&$F$7,Journals!$J$9:$J$1011204,"Withholding Tax Payable of Telnet")-SUMIFS(Journals!$K$9:$K$1011204,Journals!$D$9:$D$1011204,"<"&$F$7,Journals!$J$9:$J$1011204,"Withholding Tax Payable of Telnet") -> 0 | M59: =K59+I59-H59 -> 75
G60: Investments in T-Bill | H60: =MAX(0,SUMIFS(Journals!$K$9:$K$1011204,Journals!$D$9:$D$1011204,">"&$E$7,Journals!$D$9:$D$1011204,"<"&$E$8,Journals!$J$9:$J$1011204,"Investments in T-Bill")-SUMIFS(Journals!$L$9:$L$1011204,Journals!$D$9:$D$1011204,">"&$E$7,Journals!$D$9:$D$1011204,"<"&$E$8,Journals!$J$9:$J$1011204,"Investments in T-Bill")) -> 0 | I60: =MAX(0,SUMIFS(Journals!$L$9:$L$1011204,Journals!$D$9:$D$1011204,">"&$E$7,Journals!$D$9:$D$1011204,"<"&$E$8,Journals!$J$9:$J$1011204,"Investments in T-Bill")-SUMIFS(Journals!$K$9:$K$1011204,Journals!$D$9:$D$1011204,">"&$E$7,Journals!$D$9:$D$1011204,"<"&$E$8,Journals!$J$9:$J$1011204,"Investments in T-Bill")) -> 0 | J60: =SUMIFS(Journals!$K$9:$K$1011204,Journals!$D$9:$D$1011204,"<"&$F$7,Journals!$J$9:$J$1011204,"Investments in T-Bill")-SUMIFS(Journals!$L$9:$L$1011204,Journals!$D$9:$D$1011204,"<"&$F$7,Journals!$J$9:$J$1011204,"Investments in T-Bill") -> 0 | L60: =J60+H60-I60 -> 0
G61: Interest receivables from T-Bill | H61: =MAX(0,SUMIFS(Journals!$K$9:$K$1011204,Journals!$D$9:$D$1011204,">"&$E$7,Journals!$D$9:$D$1011204,"<"&$E$8,Journals!$J$9:$J$1011204,"Interest receivables from T-Bill")-SUMIFS(Journals!$L$9:$L$1011204,Journals!$D$9:$D$1011204,">"&$E$7,Journals!$D$9:$D$1011204,"<"&$E$8,Journals!$J$9:$J$1011204,"Interest receivables from T-Bill")) -> 0 | I61: =MAX(0,SUMIFS(Journals!$L$9:$L$1011204,Journals!$D$9:$D$1011204,">"&$E$7,Journals!$D$9:$D$1011204,"<"&$E$8,Journals!$J$9:$J$1011204,"Interest receivables from T-Bill")-SUMIFS(Journals!$K$9:$K$1011204,Journals!$D$9:$D$1011204,">"&$E$7,Journals!$D$9:$D$1011204,"<"&$E$8,Journals!$J$9:$J$1011204,"Interest receivables from T-Bill")) -> 0 | J61: =SUMIFS(Journals!$K$9:$K$1011204,Journals!$D$9:$D$1011204,"<"&$F$7,Journals!$J$9:$J$1011204,"Interest receivables from T-Bill")-SUMIFS(Journals!$L$9:$L$1011204,Journals!$D$9:$D$1011204,"<"&$F$7,Journals!$J$9:$J$1011204,"Interest receivables from T-Bill") -> 0 | L61: =J61+H61-I61 -> 0
G62: Investments in T-Bond | H62: =MAX(0,SUMIFS(Journals!$K$9:$K$1011204,Journals!$D$9:$D$1011204,">"&$E$7,Journals!$D$9:$D$1011204,"<"&$E$8,Journals!$J$9:$J$1011204,"Investments in T-Bond")-SUMIFS(Journals!$L$9:$L$1011204,Journals!$D$9:$D$1011204,">"&$E$7,Journals!$D$9:$D$1011204,"<"&$E$8,Journals!$J$9:$J$1011204,"Investments in T-Bond")) -> 0 | I62: =MAX(0,SUMIFS(Journals!$L$9:$L$1011204,Journals!$D$9:$D$1011204,">"&$E$7,Journals!$D$9:$D$1011204,"<"&$E$8,Journals!$J$9:$J$1011204,"Investments in T-Bond")-SUMIFS(Journals!$K$9:$K$1011204,Journals!$D$9:$D$1011204,">"&$E$7,Journals!$D$9:$D$1011204,"<"&$E$8,Journals!$J$9:$J$1011204,"Investments in T-Bond")) -> 21288672 | J62: =SUMIFS(Journals!$K$9:$K$1011204,Journals!$D$9:$D$1011204,"<"&$F$7,Journals!$J$9:$J$1011204,"Investments in T-Bond")-SUMIFS(Journals!$L$9:$L$1011204,Journals!$D$9:$D$1011204,"<"&$F$7,Journals!$J$9:$J$1011204,"Investments in T-Bond") -> 21288672 | L62: =J62+H62-I62 -> 0
G63: Interest receivables from T-Bond | H63: =MAX(0,SUMIFS(Journals!$K$9:$K$1011204,Journals!$D$9:$D$1011204,">"&$E$7,Journals!$D$9:$D$1011204,"<"&$E$8,Journals!$J$9:$J$1011204,"Interest receivables from T-Bond")-SUMIFS(Journals!$L$9:$L$1011204,Journals!$D$9:$D$1011204,">"&$E$7,Journals!$D$9:$D$1011204,"<"&$E$8,Journals!$J$9:$J$1011204,"Interest receivables from T-Bond")) -> 0 | I63: =MAX(0,SUMIFS(Journals!$L$9:$L$1011204,Journals!$D$9:$D$1011204,">"&$E$7,Journals!$D$9:$D$1011204,"<"&$E$8,Journals!$J$9:$J$1011204,"Interest receivables from T-Bond")-SUMIFS(Journals!$K$9:$K$1011204,Journals!$D$9:$D$1011204,">"&$E$7,Journals!$D$9:$D$1011204,"<"&$E$8,Journals!$J$9:$J$1011204,"Interest receivables from T-Bond")) -> 0 | J63: =SUMIFS(Journals!$K$9:$K$1011204,Journals!$D$9:$D$1011204,"<"&$F$7,Journals!$J$9:$J$1011204,"Interest receivables from T-Bond")-SUMIFS(Journals!$L$9:$L$1011204,Journals!$D$9:$D$1011204,"<"&$F$7,Journals!$J$9:$J$1011204,"Interest receivables from T-Bond") -> 0 | L63: =J63+H63-I63 -> 0

Sheet BS
F1: =(C33-C11-C14-C17) -> 2.5429066e+08
F2: 2.5381691e+08
A3: EKUSH FIRST UNIT FUND | F3: =F2-C10 -> 2633213.9 | I3: =I4/NAV -> 0.98841893
A4: STATEMENT OF FINANCIAL POSITION | I4: 2.6517206e+08 | J4: =TODAY() -> 46106
A5: As on September 30, 2023 | I5: 0
I6: 0
A7: Particulars | B7: Notes | C7: 45199 | E7: 44926
C8: Taka | E8: Taka | I8: =ABS(I10) -> 0
A9: Assets | H9: UG/(UL) | I9: FVA | J9: NAV*
A10: Investment at cost price | C10: ='TB-C'!$L$7 -> 2.511837e+08 | E10: ='TB-P'!$L$7 -> 2.0852119e+08 | H10: =I4-C10 -> 13988365 | I10: =H10-C11 -> 0 | J10: =C33+I10+I14+I17 -> 2.6827902e+08
A11: fair value adjustment | C11: =IF('TB-C'!$L$38>0,'TB-C'!$L$38,-'TB-C'!$M$38) -> 13988365 | E11: =IF('TB-P'!$L$38>0,'TB-P'!$L$38,-'TB-P'!$M$38) -> 3833287.7 | H11: =J10/C49 -> 14.754432
A12: Investment in Securities at Market Price | B12: 1 | C12: =C10+C11 -> 2.6517206e+08 | D12: =D10+D11 -> 0 | E12: =E10+E11 -> 2.1235447e+08 | H12: T-Bill | I12: =ABS(I14) -> 0
A13: T-Bill at cost price | C13: ='TB-C'!L60 -> 0 | E13: ='TB-P'!L60 -> 0 | H13: UG/(UL) | I13: FVA
A14: T-Bill fair value adjustment | C14: =IF('TB-C'!$L$39>0,'TB-C'!$L$39,-'TB-C'!$M$39) -> 0 | E14: =IF('TB-P'!$L$39>0,'TB-P'!$L$39,-'TB-P'!$M$39) -> 0 | H14: =I5-C13 -> 0 | I14: =H14-C14 -> 0
A15: Investments in T-Bill | B15: 1 | C15: =C13+C14 -> 0 | E15: =E13+E14 -> 0 | H15: T-Bond | I15: =ABS(I17) -> 0
A16: T-Bond Investment at cost price | C16: ='TB-C'!L62 -> 0 | E16: ='TB-P'!L62 -> 0 | H16: UG/(UL) | I16: FVA
A17: T-Bond fair value adjustment | C17: =IF('TB-C'!$L$40>0,'TB-C'!$L$40,-'TB-C'!$M$40) -> 0 | E17: =IF('TB-P'!$L$40>0,'TB-P'!$L$40,-'TB-P'!$M$40) -> 0 | H17: =I6-C16 -> 0 | I17: =H17-C17 -> 0
A18: Investments in T-Bond | B18: 1 | C18: =C16+C17 -> 0 | E18: =E16+E17 -> 0
A19: Fixed Deposit Receipts (FDR) | B19: 2 | C19: ='TB-C'!$L$16 -> 0 | E19: ='TB-P'!$L$16 -> 6000000
A20: IPO Application | B20: 3 | C20: ='TB-C'!$L$48 -> 0 | E20: ='TB-P'!$L$48 -> 0 | G20: Midland | H20: 0001-1090000732 | I20: 115686.28 | J20: =SUM(I20:I28) -> 472714.83
A21: Accounts Receivable | B21: 4 | C21: =SUM('TB-C'!L41:L42)+'TB-C'!$L$46+'TB-C'!$L$53+'TB-C'!L61+'TB-C'!L8+'TB-C'!L63 -> 5669205.3 | E21: =SUM('TB-P'!L41:L42)+'TB-P'!$L$46+'TB-P'!$L$53+'TB-P'!L61+'TB-P'!L8+'TB-P'!L63 -> 2846528.4 | H21: 0001-1060000093 | I21: 38042.78 | J21: =J20-C23 -> 0.80228317
A22: Advance, Deposit & Prepayments | C22: 0 | E22: 0 | G22: Brac | H22: 1513-205101231001 | I22: 72958.93
A23: Cash & Cash Equivalent | B23: 5 | C23: ='TB-C'!$L$17 -> 472714.03 | E23: ='TB-P'!$L$17 -> 1784563.8 | H23: 2051-012310002 | I23: 25639.11
A24: Preliminary & Issue Expenses | B24: 6 | C24: ='TB-C'!$L$9 -> 140895.8 | E24: ='TB-P'!$L$9 -> 173862.83 | G24: Modhumoti | H24: 1135-12700000003 | I24: 22337.42
A25: Total Assets | C25: =ROUND(SUM(C18:C24)+C15+C12,1) -> 2.7145488e+08 | E25: =ROUND(SUM(E18:E24)+E12,1) -> 2.2315943e+08 | G25: SBAC | H25: 2130-001459 | I25: 2715.57
G26: MTB | H26: 1310-000147444 | I26: 162943.72
A27: Equity & Liabilities | G27: =C25-C40 -> 0 | I27: 32391.02
A28: Unitholders' Equity | G28: =E25-E40 -> -0.0077980161
A29: Unit Capital | B29: 7 | C29: ='TB-C'!$M$18 -> 181829450 | E29: ='TB-P'!$M$18 -> 156111010
A30: Unit Premium | B30: 8 | C30: ='TB-C'!$M$19 -> 22565685 | E30: ='TB-P'!$M$19 -> 10427123
A31: Dividend Equalization Reserve | C31: =E!E15 -> 150000 | E31: =E!$E$29 -> 150000
A32: Retained Earnings | C32: =E!$D$15 -> 63733888 | E32: =E!D$29 -> 53276655
A33: Total Equity | C33: =SUM(C29:C32) -> 2.6827902e+08 | D33: =SUM(D29:D32) -> 0 | E33: =SUM(E29:E32) -> 2.1996479e+08
A34: Current Liabilities
A35: Accounts Payable | C35: ='TB-C'!$M$43+'TB-C'!M57+'TB-C'!M58+'TB-C'!M59 -> 580962.13 | E35: ='TB-P'!$M$43+'TB-P'!M57+'TB-P'!M58+'TB-P'!M59 -> 86270.429
A36: Dividend Payable | C36: ='TB-C'!M56 -> 0 | E36: ='TB-P'!M56 -> 0
A37: Liability for expenses | B37: 9 | C37: =SUM('TB-C'!$M$10:$M$15) -> 2594894 | E37: =SUM('TB-P'!$M$10:$M$15) -> 3108371.2
A38: Total Liabilities | C38: =SUM(C35:C37) -> 3175856.1 | D38: =SUM(D35) -> 0 | E38: =SUM(E35:E37) -> 3194641.6
A40: Total Equity and Liabilities | C40: =ROUND(C33+C38,1) -> 2.7145488e+08 | D40: =D33+D38 -> 0 | E40: =E33+E38 -> 2.2315943e+08
A42: Net Asset Value (NAV) | C42: =C33 -> 2.6827902e+08 | E42: =E33 -> 2.1996479e+08
A44: Net Asset Value (NAV) per unit: | C44: =C42/C49 -> 14.754432 | E44: =E33/E49 -> 14.09028
A45: At Cost | B45: 10 | C45: =(C33-C11-C14-C17)/C49 -> 13.985119 | E45: =(E33-E11)/E49 -> 13.844731
A46: At Market Price | B46: 11 | C46: =(C33)/(C49) -> 14.754432 | E46: =(E33)/(E49) -> 14.09028
A48: These financial statement should be read in conjunction with annexed notes.
A49: No of Units Outstanding | C49: =ROUND(C29/10,0) -> 18182945 | E49: =ROUND(E29/10,0) -> 15611101
A54: Head of Compliance | C54: Managing Director
A55: Ekush Wealth Management Limited | C55: Ekush Wealth Management Limited
A60: Trustee
A61: Shandhani Life Insurance Company Limited

Sheet IS
A1: EKUSH FIRST UNIT FUND
A2: STATEMENT OF PROFIT & LOSS AND OTHER COMPREHENSIVE INCOME
A3: For the period of January 1 to December 31, 2023
A5: Particulars | B5: Notes | C5: January 01 to December 31, 2023 | E5: January 01 to December 31, 2022
C6: Taka | E6: Taka
A8: INCOME
A9: Interest Income | B9: 12 | C9: =SUM('TB-C'!I20:I23) -> 707664.41 | E9: =SUM('TB-P'!I20:I23) -> 3882107
A10: Net Gain on Sale of Marketable Securities | B10: 13 | C10: =IF('TB-C'!I50>0,'TB-C'!I50,-'TB-C'!H50) -> 10078118 | E10: =IF('TB-P'!I50>0,'TB-P'!I50,-'TB-P'!H50) -> 9695579.5 | G10: =((C9+C10+C13)-C34)*0.7 -> 6549616 | H10: Total Div
A11: Net Gain on Sale of T-Bill | B11: 14 | C11: =IF('TB-C'!I51>0,'TB-C'!I51,-'TB-C'!H51) -> 0 | E11: =IF('TB-P'!I51>0,'TB-P'!I51,-'TB-P'!H51) -> 0
A12: Net Gain on Sale of T-Bond | B12: 15 | C12: =IF('TB-C'!I52>0,'TB-C'!I52,-'TB-C'!H52) -> 0 | E12: =IF('TB-P'!I52>0,'TB-P'!I52,-'TB-P'!H52) -> 5060463.1
A13: Dividend Income | B13: 14 | C13: ='TB-C'!$I$45 -> 432567.46 | E13: ='TB-P'!$I$45 -> 5060840.9 | G13: =G10/C41 -> 0.36020655 | H13: Per Unit Dev
A14: Dividend Reverse | B14: 15 | C14: =-'TB-C'!H45 -> 0 | J14: 5857970
A15: Unrealized Gain/(Loss) on Securities | B15: 15 | C15: =IF('TB-C'!$I$38>0,-'TB-C'!$I$38,'TB-C'!$H$38) -> 10155077 | E15: =IF('TB-P'!$I$38>0,-'TB-P'!$I$38,'TB-P'!$H$38) -> 2872990.2 | J15: 5848314
A16: Unrealized Gain/(Loss) on T-Bill | B16: 16 | C16: =IF('TB-C'!$I$39>0,-'TB-C'!$I$39,'TB-C'!$H$39) -> 0 | E16: =IF('TB-P'!$I$39>0,-'TB-P'!$I$39,'TB-P'!$H$39) -> 0 | J16: =J14-J15 -> 9656
A17: Unrealized Gain/(Loss) on T-Bond | B17: 17 | C17: =IF('TB-C'!$I$40>0,-'TB-C'!$I$40,'TB-C'!$H$40) -> 0 | E17: =IF('TB-P'!$I$40>0,-'TB-P'!$I$40,'TB-P'!$H$40) -> -304567.49
A18: TOTAL | C18: =SUM(C9:C17) -> 21373428 | D18: =SUM(D9:D13) -> 0 | E18: =SUM(E9:E17) -> 26267413
A20: EXPENSES
A21: Management Fees | C21: ='TB-C'!$H$33 -> 1199767.6 | E21: ='TB-P'!$H$33 -> 3748377.1
A22: BSEC Annual Fees | C22: ='TB-C'!$H$35 -> 0 | E22: ='TB-P'!$H$35 -> 154911.16
A23: Amortization of Preliminary & Issue Expenses | C23: ='TB-C'!$H$32 -> 32967.033 | E23: ='TB-P'!$H$32 -> 142464.68
A24: CDBL Settlement & Demat Charges | C24: 0 | E24: 0
A25: CDBL Charges | C25: ='TB-C'!$H$37 -> 13687.862 | E25: ='TB-P'!$H$37 -> 88735.48
A26: Trustee Fees | C26: ='TB-C'!$H$34 -> 98794.008 | E26: ='TB-P'!$H$34 -> 174953.16
A27: Custodian Fees | C27: ='TB-C'!$H$47 -> 0 | E27: ='TB-P'!$H$47 -> 109206.14
A28: IPO Application Fees | C28: ='TB-C'!$H$49 -> 0 | E28: ='TB-P'!$H$49 -> 0
A29: Brokerage Commission | C29: ='TB-C'!$H$27 -> 485345.52 | E29: ='TB-P'!$H$25 -> 950852.53
A30: Audit Fees | C30: ='TB-C'!$H$36 -> 0 | E30: ='TB-P'!$H$36 -> 46000
A31: Bank Charge & Excise Duty | C31: ='TB-C'!$H$26 -> 26469 | E31: ='TB-P'!$H$24 -> 85743.16
A32: Newspaper Publication Expense | C32: 0 | E32: 0
A33: Other Operating Expense | C33: ='TB-C'!$H$44 -> 4725 | E33: ='TB-P'!$H$44 -> 85162.5
A34: TOTAL | C34: =SUM(C21:C33) -> 1861756 | D34: =SUM(D21:D33) -> 0 | E34: =SUM(E21:E33) -> 5586405.9 | G34: =C34/BS!C40 -> 0.0068584365
A36: Net Profit for the Period | C36: =C18-C34 -> 19511672 | E36: =E18-E34 -> 20681007
A38: Earnings Per Unit | B38: 16 | C38: =C36/C41 -> 1.0730754 | E38: =E36/E41 -> 1.3247629
A40: These financial statement should be read in conjunction with annexed notes.
A41: No of Units Outstanding | C41: =BS!C49 -> 18182945 | E41: =BS!E49 -> 15611101
A46: Head of Compliance | C46: Managing Director
A47: Ekush Wealth Management Limited | C47: Ekush Wealth Management Limited
A52: Trustee
A53: Shandhani Life Insurance Company Limited
C66: =C41*0.8 -> 14546356
C69: =C36-C17 -> 19511672
C74: =C69-C66 -> 4965315.6

Sheet E
A1: EKUSH FIRST UNIT FUND
A2: STATEMENT OF CHANGES IN EQUITY
A3: For the period from January 1 to December 31, 2023
A6: Particulars | B6: Unit Capital | C6: Unit Premium Reserve | D6: Retained Earnings | E6: Dividend Equalization Reserve | F6: Total Equity
A8: Opening Balance | B8: ='TB-C'!$K$18 -> 156111010 | C8: ='TB-C'!K19 -> 10427123 | D8: =SUM('TB-C'!$O$7:$O$217)-SUM('TB-C'!$N$7:$N$217) -> 53276655 | E8: ='TB-C'!K54 -> 150000 | F8: =SUM(B8:E8) -> 2.1996479e+08
A9: Unit Capital Raised During the Period | B9: ='TB-C'!D18 -> 0 | C9: ='TB-C'!I19 -> 19849776 | D9: 0 | E9: 0 | F9: =SUM(B9:E9) -> 19849776
A10: Unit Surrendered | B10: =-'TB-C'!C18 -> 0 | C10: =-'TB-C'!H19 -> -7711214.3 | D10: 0 | E10: 0 | F10: =SUM(B10:E10) -> -7711214.3
A11: Dividend Equalization Reserve | B11: 0 | C11: 0 | D11: =-'TB-C'!I54 -> 0 | E11: ='TB-C'!I54 -> 0 | F11: =SUM(B11:E11) -> 0
A12: Dividend Payable | B12: 0 | C12: 0 | D12: =-'TB-C'!M56 -> 0 | E12: 0 | F12: =SUM(B12:E12) -> 0
A13: Dividend Paid During the Year | B13: 0 | C13: 0 | D13: =-'TB-C'!H56 -> -9054438.6 | E13: 0 | F13: =SUM(B13:E13) -> -9054438.6
A14: Net Profit During the Period | B14: 0 | C14: 0 | D14: =IS!$C$36 -> 19511672 | E14: 0 | F14: =SUM(B14:E14) -> 19511672
A15: Ending Balance | B15: =SUM(B8:B14) -> 156111010 | C15: =SUM(C8:C14) -> 22565685 | D15: =SUM(D8:D14) -> 63733888 | E15: =SUM(E8:E14) -> 150000 | F15: =SUM(F8:F14) -> 2.4256058e+08
A18: For the period from January 1 to December 31, 2022
A20: Particulars | B20: Unit Capital | C20: Unit Premium Reserve | D20: Retained Earnings | E20: Dividend Equalization Reserve | F20: Total Equity
A22: Opening Balance | B22: ='TB-P'!$K$18 -> 108240270 | C22: ='TB-P'!K19 -> -8188472.1 | D22: =SUM('TB-P'!$O$7:$O$218)-SUM('TB-P'!$N$7:$N$218) -> 38007661 | E22: ='TB-P'!K54 -> 150000 | F22: =SUM(B22:E22) -> 1.3820946e+08
A23: Unit Capital Raised During the Period | B23: ='TB-P'!I18 -> 82095460 | C23: ='TB-P'!I19 -> 30623394 | D23: 0 | E23: 0 | F23: =SUM(B23:E23) -> 1.1271885e+08
A24: Unit Surrendered | B24: =-'TB-P'!H18 -> -34224720 | C24: =-'TB-P'!H19 -> -12007798 | D24: 0 | E24: 0 | F24: =SUM(B24:E24) -> -46232518
A25: Dividend Equalization Reserve | B25: 0 | C25: 0 | D25: 0 | E25: ='TB-P'!I54 -> 0 | F25: =SUM(B25:E25) -> 0
A26: Dividend Payable | B26: 0 | C26: 0 | D26: ='TB-P'!H56-'TB-P'!I56 -> 0 | E26: 0 | F26: =SUM(B26:E26) -> 0
A27: Dividend Paid During the Year | B27: 0 | C27: 0 | D27: =-'TB-P'!H56 -> -5412013.5 | E27: 0 | F27: =SUM(B27:E27) -> -5412013.5
A28: Net Profit During the Period | B28: 0 | C28: 0 | D28: =IS!$E$36 -> 20681007 | E28: 0 | F28: =SUM(B28:E28) -> 20681007
A29: Ending Balance | B29: =SUM(B22:B28) -> 156111010 | C29: =SUM(C22:C28) -> 10427123 | D29: =SUM(D22:D28) -> 53276655 | E29: =SUM(E22:E28) -> 150000 | F29: =SUM(F22:F28) -> 2.1996479e+08
A31: These financial statement should be read in conjunction with annexed notes.
A36: Head of Compliance | C36: Managing Director
A37: Ekush Wealth Management Limited | C37: Ekush Wealth Management Limited
A42: Trustee
A43: Shandhani Life Insurance Company Limited

Sheet CF
A1: EKUSH FIRST UNIT FUND
A2: STATEMENT OF CASH FLOW
A3: For the period from January 01 to December 31, 2023
A5: Particulars | B5: January 01 to December 31, 2022 | D5: January 01 to December 31, 2021
B6: Taka | D6: Taka | G6: BS | H6: =BS!C23 -> 472714.03
A8: Cash flows from operating activities: | G8: =H6-B44 -> -2739690.1
A9: Interest Income | B9: 3499665 | D9: =SUM('TB-P'!I20:I23)-'TB-P'!H41-'TB-P'!H62 -> 3882107
A10: Gain on Sale of Share and Securities | B10: =IS!C10 -> 10078118 | D10: =IS!$E$10 -> 9695579.5
A11: Gain on Sale of T-Bill | B11: =IS!C11 -> 0 | D11: 0
A12: Gain on Sale of T-Bond | B12: =IS!C12 -> 0 | D12: 0
A13: Dividend Income | B13: ='TB-C'!I46+('TB-C'!I45-'TB-C'!H46) -> 1666302 | D13: ='TB-P'!I46+('TB-P'!I45-'TB-P'!H46) -> 4339541.6
A14: Management Fees | B14: =-'TB-C'!H10 -> -1766038.9 | D14: =-'TB-P'!H10 -> -1705923.3
A15: Trustee Fees | B15: =-IF('TB-C'!I11='TB-C'!H34,0,IF('TB-C'!I11=0,'TB-C'!H11+'TB-C'!H34,'TB-C'!H34-'TB-C'!I11)) -> 0 | D15: =-IF('TB-P'!I11='TB-P'!H34,0,IF('TB-P'!I11=0,'TB-P'!H11+'TB-P'!H34,'TB-P'!H34-'TB-P'!I11)) -> -137885.61
A16: BSEC Annual Fee | B16: =-IF('TB-C'!I13='TB-C'!H35,0,IF('TB-C'!I13=0,'TB-C'!H13+'TB-C'!H35,'TB-C'!H35-'TB-C'!H13)) -> 0 | D16: =-IF('TB-P'!I13='TB-P'!H35,0,IF('TB-P'!I13=0,'TB-P'!H13+'TB-P'!H35,'TB-P'!H35-'TB-P'!H13)) -> -154911.16
A17: Brokerage commission | B17: =-IS!$C$29 -> -485345.52 | D17: =-IS!$E$29 -> -950852.53
A18: Bank Charges & Excise Duty | B18: =-IS!$C$31 -> -26469 | D18: =-IS!$E$31 -> -85743.16
A19: CDBL Fee | B19: =-IF('TB-C'!I129='TB-C'!H37,0,IF('TB-C'!I15=0,'TB-C'!H15+'TB-C'!H37,'TB-C'!H37-'TB-C'!H15)) -> -13687.862 | D19: =-IF('TB-P'!I133='TB-P'!H37,0,IF('TB-P'!I15=0,'TB-P'!H15+'TB-P'!H37,'TB-P'!H37-'TB-P'!H15)) -> -88735.48
A20: Custodian Fee | B20: =-IF('TB-C'!I12='TB-C'!H47,0,IF('TB-C'!I12=0,'TB-C'!H12+'TB-C'!H47,'TB-C'!H47-'TB-C'!H12)) -> 0 | D20: =-IF('TB-P'!I12='TB-P'!H47,0,IF('TB-P'!I12=0,'TB-P'!H12+'TB-P'!H47,'TB-P'!H47-'TB-P'!H12)) -> -109206.14
A21: IPO Application Fee | B21: =-'TB-C'!$H$49 -> 0 | D21: =-'TB-P'!$H$49 -> 0
A22: Audit Fee | B22: =-'TB-C'!$H$36-'TB-C'!$H$14+'TB-C'!I14 -> -46000 | D22: =-'TB-P'!$H$36+'TB-P'!$I$14 -> -46000
A23: Other Operating Expense | B23: =-'TB-C'!$H$44 -> -4725 | D23: =-'TB-P'!$H$44 -> -85162.5
A24: Net Cash Flow from Operating Activities | B24: =SUM(B9:B23) -> 12901819 | C24: =SUM(C9:C18) -> 0 | D24: =SUM(D9:D23) -> 14552808
A26: Cash Flow from Investing Activities:
A27: Net Investment in Shares and securities | B27: =IF('TB-C'!$H$7>0,-'TB-C'!$H$7,'TB-C'!$I$7)+'TB-C'!$I$43-'TB-C'!$H$53-'TB-C'!H43+'TB-C'!I53 -> -46276542 | D27: =IF('TB-P'!$H$7>0,-'TB-P'!$H$7,'TB-P'!$I$7)+'TB-P'!$I$43-'TB-P'!$H$53-'TB-P'!H43+'TB-P'!I53 -> -1.2265889e+08
A28: Net Investment in T- Bills | B28: =IF('TB-C'!$H$60>0,-'TB-C'!$H$60,'TB-C'!$I$60) -> 0 | D28: 0
A29: Net Investment in T- Bonds | B29: =IF('TB-C'!$H$62>0,-'TB-C'!$H$62,'TB-C'!$I$62) -> 0 | D29: 0
A30: IPO Application | B30: ='TB-C'!I48 -> 0 | D30: ='TB-P'!I48 -> 0
A31: Investment in FDR | B31: =-SUMIFS(Journals!$K$9:$K$22410,Journals!$D$9:$D$22410,">"&'TB-C'!$E$7,Journals!$D$9:$D$22410,"<"&'TB-C'!$E$8,Journals!$G$9:$G$22410,"c",Journals!$J$9:$J$22410,"fixed deposit receipts (fdr)") -> 0 | D31: =-SUMIFS(Journals!$K$9:$K$22410,Journals!$D$9:$D$22410,">"&'TB-P'!$E$7,Journals!$D$9:$D$22410,"<"&'TB-P'!$E$8,Journals!$G$9:$G$22410,"c",Journals!$J$9:$J$22410,"fixed deposit receipts (fdr)") -> -8500000
A32: Proceeds from Encashment of FDR | B32: =SUMIFS(Journals!$L$9:$L$22410,Journals!$D$9:$D$22410,">"&'TB-C'!$E$7,Journals!$D$9:$D$22410,"<"&'TB-C'!$E$8,Journals!$G$9:$G$22410,"c",Journals!$J$9:$J$22410,"fixed deposit receipts (fdr)") -> 6000000 | D32: =SUMIFS(Journals!$L$9:$L$22410,Journals!$D$9:$D$22410,">"&'TB-P'!$E$7,Journals!$D$9:$D$22410,"<"&'TB-P'!$E$8,Journals!$G$9:$G$22410,"c",Journals!$J$9:$J$22410,"fixed deposit receipts (fdr)") -> 8500000
A33: Preliminary & Issue Expenses | B33: 0 | D33: 0
A34: Net Cash from Investing Activities | B34: =SUM(B27:B33) -> -40276542 | C34: =SUM(C27:C33) -> 0 | D34: =SUM(D27:D33) -> -1.2265889e+08
A36: Cash Flow from Financing Activities:
A37: Proceeds from Issuance of Units | B37: ='TB-C'!I18+'TB-C'!I19 -> 61210016 | D37: ='TB-P'!I18+'TB-P'!I19 -> 1.1271885e+08
A38: Proceeds made for Re-purchase of Units | B38: =-('TB-C'!H18+'TB-C'!H19) -> -23353014 | D38: =-('TB-P'!H18+'TB-P'!H19) -> -46232518
A39: Dividend Payment | B39: =-'TB-C'!H56 -> -9054438.6 | D39: =-'TB-P'!H56 -> -5412013.5
A40: Net Cash from Financing Activities | B40: =SUM(B37:B39) -> 28802563 | C40: =C39 -> 0 | D40: =SUM(D37:D39) -> 61074322
A42: Net Cash Flows | B42: =SUM(B24,B34,B40) -> 1427840.3 | C42: =SUM(C24,C34,C40) -> 0 | D42: =SUM(D24,D34,D40) -> -47031762
A43: Cash & Cash Equivalent at the Beginning of the Period | B43: ='TB-C'!J17 -> 1784563.8 | D43: ='TB-P'!J17 -> 22849633
A44: Cash & Cash Equivalent at the End of the Period | B44: =B42+B43 -> 3212404.1 | C44: =C42+C43 -> 0 | D44: =D42+D43 -> -24182129
A46: Net Operating Cash Flow per Unit | B46: =B24/B48 -> 0.70955608 | D46: =IFERROR(D24/D48,0) -> 0.93220896
A48: No of Units Outstanding | B48: =BS!C49 -> 18182945 | D48: =BS!E49 -> 15611101
A49: These financial statement should be read in conjunction with annexed notes.
A55: Head of Compliance | B55: Managing Director
A56: Ekush Wealth Management Limited | B56: Ekush Wealth Management Limited
A61: Trustee
A62: Shandhani Life Insurance Company Limited

Sheet W C & I
C4: Date | D4: =TODAY() -> 46106
C5: Fund Initiation Day | D5: 43908
C6: Last Day of Accounting Period | D6: 44196
C8: Net Asset Value | D8: =BS!C33 -> 2.6827902e+08
C9: Preliminary & Issue Expenses | D9: 1000000
C10: Fixed Deposit Receipts (FDR):
C12: Weekly Expenses: | D12: Weekly | E12: Daily
C13: Preliminary & Issue Expenses | D13: =D9/(52*7) -> 2747.2527 | E13: =D13/7 -> 392.46468
C14: Management Fee | D14: =(IF(NAV<50000001,NAV*2.5%,IF(NAV<250000001,(50000000*2.5%)+(NAV-50000000)*2%,IF(NAV<500000001,(50000000*2.5%)+(200000000*2%)+((NAV-250000000)*1.5%),(50000000*2.5%)+(200000000*2%)+(250000000*1.5%)+((NAV-500000000)*1%)))))/52 -> 106234.33 | E14: =D14/7 -> 15176.333 | G14: =50000000*2.5% -> 1250000 | H14: =G14/52 -> 24038.462
C15: Trustee Fee | D15: =BS!C33*0.1%/52 -> 5159.212 | E15: =D15/7 -> 737.03028 | G15: =200000000*2% -> 4000000 | H15: =G15/52 -> 76923.077
C16: BSEC Annual Fee | D16: =MAX(50000,BS!C25*0.1%)*7/('W C & I'!D6-'W C & I'!D5) -> 6597.8616 | H16: =SUM(H14:H15) -> 100961.54
C17: Audit Fee | D17: =30000*7/(D6-D5) -> 729.16667
C18: CDBL Fee | D18: 0
E20: =D13/3 -> 915.75092
E21: =D14/3 -> 35411.444
E22: =D15/3 -> 1719.7373

Sheet Bank Interest
C1: Midland | G1: Brac | K1: Modhumoti | M1: SBAC | O1: MTB | Q1: NRB
A2: =TODAY() -> 46106 | B2: Date | C2: 0001-1090000732 | E2: 0001-1060000093 | G2: 1513-205101231001 | I2: 2051-012310002 | K2: 1135-12700000003 | M2: 2130-001459 | O2: 1310-000147444 | Q2: 1012-050203847
C3: Amount | D3: Interest | E3: Amount | F3: Interest | G3: Amount | H3: Interest | I3: Amount | J3: Interest | K3: Amount | L3: Interest | M3: Amount | N3: Interest | O3: Amount | P3: Interest | Q3: Amount | R3: Interest
B4: 45473 | D4: 816031 | F4: 32081 | H4: 7649.19 | J4: 274.64 | L4: 34999.7 | N4: 41.25 | P4: 105895.32
B5: 45474 | C5: 899611.39 | D5: =(C5*7.5%)/360 -> 187.41904 | E5: 30296100 | F5: =(E5*7.5%)/360 -> 6311.6876 | G5: 574415.7 | H5: =(G5*4.5%)/360 -> 71.801962 | I5: 7914.66 | J5: =(I5*4.5%)/360 -> 0.9893325 | K5: 22682.42 | L5: =(K5*6.5%)/360 -> 4.0954369 | M5: 3567.32 | N5: =(M5*2.5%)/360 -> 0.24773056 | O5: 169731.79 | P5: =(O5*6.5%)/360 -> 30.646018 | Q5: 7512779.9 | R5: =(Q5*8%)/360 -> 1669.5066
B6: =B5+1 -> 45475 | C6: 899611.39 | D6: =(C6*7.5%)/360 -> 187.41904 | E6: 30412755 | F6: =(E6*7.5%)/360 -> 6335.9906 | G6: 574415.7 | H6: =(G6*4.5%)/360 -> 71.801962 | I6: 7914.66 | J6: =(I6*4.5%)/360 -> 0.9893325 | K6: 22682.42 | L6: =(K6*6.5%)/360 -> 4.0954369 | M6: 3567.32 | N6: =(M6*2.5%)/360 -> 0.24773056 | O6: 169731.79 | P6: =(O6*6.5%)/360 -> 30.646018 | Q6: 7512779.9 | R6: =(Q6*8%)/360 -> 1669.5066
B7: =B6+1 -> 45476 | C7: 899611.39 | D7: =(C7*7.5%)/360 -> 187.41904 | E7: 33587454 | F7: =(E7*7.5%)/360 -> 6997.3862 | G7: 576415.7 | H7: =(G7*4.5%)/360 -> 72.051962 | I7: 7914.66 | J7: =(I7*4.5%)/360 -> 0.9893325 | K7: 22682.42 | L7: =(K7*6.5%)/360 -> 4.0954369 | M7: 3567.32 | N7: =(M7*2.5%)/360 -> 0.24773056 | O7: 169731.79 | P7: =(O7*6.5%)/360 -> 30.646018 | Q7: 7512779.9 | R7: =(Q7*8%)/360 -> 1669.5066
B8: =B7+1 -> 45477 | C8: 899611.39 | D8: =(C8*7.5%)/360 -> 187.41904 | E8: 33587454 | F8: =(E8*7.5%)/360 -> 6997.3862 | G8: 576415.7 | H8: =(G8*4.5%)/360 -> 72.051962 | I8: 7914.66 | J8: =(I8*4.5%)/360 -> 0.9893325 | K8: 22682.42 | L8: =(K8*6.5%)/360 -> 4.0954369 | M8: 3567.32 | N8: =(M8*2.5%)/360 -> 0.24773056 | O8: 169731.79 | P8: =(O8*6.5%)/360 -> 30.646018 | Q8: 7512779.9 | R8: =(Q8*8%)/360 -> 1669.5066
B9: =B8+1 -> 45478 | C9: 899611.39 | D9: =(C9*7.5%)/360 -> 187.41904 | E9: 33587454 | F9: =(E9*7.5%)/360 -> 6997.3862 | G9: 576415.7 | H9: =(G9*4.5%)/360 -> 72.051962 | I9: 7914.66 | J9: =(I9*4.5%)/360 -> 0.9893325 | K9: 22682.42 | L9: =(K9*6.5%)/360 -> 4.0954369 | M9: 3567.32 | N9: =(M9*2.5%)/360 -> 0.24773056 | O9: 169731.79 | P9: =(O9*6.5%)/360 -> 30.646018 | Q9: 7512779.9 | R9: =(Q9*8%)/360 -> 1669.5066
B10: =B9+1 -> 45479 | C10: 899611.39 | D10: =(C10*7.5%)/360 -> 187.41904 | E10: 33587454 | F10: =(E10*7.5%)/360 -> 6997.3862 | G10: 576415.7 | H10: =(G10*4.5%)/360 -> 72.051962 | I10: 7914.66 | J10: =(I10*4.5%)/360 -> 0.9893325 | K10: 22682.42 | L10: =(K10*6.5%)/360 -> 4.0954369 | M10: 3567.32 | N10: =(M10*2.5%)/360 -> 0.24773056 | O10: 169731.79 | P10: =(O10*6.5%)/360 -> 30.646018 | Q10: 7512779.9 | R10: =(Q10*8%)/360 -> 1669.5066
B11: =B10+1 -> 45480 | C11: 899611.39 | D11: =(C11*7.5%)/360 -> 187.41904 | E11: 33587454 | F11: =(E11*7.5%)/360 -> 6997.3862 | G11: 622915.7 | H11: =(G11*4.5%)/360 -> 77.864462 | I11: 7914.66 | J11: =(I11*4.5%)/360 -> 0.9893325 | K11: 22682.42 | L11: =(K11*6.5%)/360 -> 4.0954369 | M11: 3567.32 | N11: =(M11*2.5%)/360 -> 0.24773056 | O11: 169731.79 | P11: =(O11*6.5%)/360 -> 30.646018 | Q11: 7512779.9 | R11: =(Q11*8%)/360 -> 1669.5066
B12: =B11+1 -> 45481 | C12: 899611.39 | D12: =(C12*7.5%)/360 -> 187.41904 | E12: 33587454 | F12: =(E12*7.5%)/360 -> 6997.3862 | G12: 622915.7 | H12: =(G12*4.5%)/360 -> 77.864462 | I12: 7914.66 | J12: =(I12*4.5%)/360 -> 0.9893325 | K12: 22682.42 | L12: =(K12*6.5%)/360 -> 4.0954369 | M12: 3567.32 | N12: =(M12*2.5%)/360 -> 0.24773056 | O12: 169731.79 | P12: =(O12*6.5%)/360 -> 30.646018 | Q12: 7512779.9 | R12: =(Q12*8%)/360 -> 1669.5066
B13: =B12+1 -> 45482 | C13: 899611.39 | D13: =(C13*7.5%)/360 -> 187.41904 | E13: 33465889 | F13: =(E13*7.5%)/360 -> 6972.0602 | G13: 622915.7 | H13: =(G13*4.5%)/360 -> 77.864462 | I13: 7914.66 | J13: =(I13*4.5%)/360 -> 0.9893325 | K13: 22682.42 | L13: =(K13*6.5%)/360 -> 4.0954369 | M13: 3567.32 | N13: =(M13*2.5%)/360 -> 0.24773056 | O13: 169731.79 | P13: =(O13*6.5%)/360 -> 30.646018 | Q13: 7512779.9 | R13: =(Q13*8%)/360 -> 1669.5066
B14: =B13+1 -> 45483 | C14: 797500.66 | D14: =(C14*7.5%)/360 -> 166.14597 | E14: 33465889 | F14: =(E14*7.5%)/360 -> 6972.0602 | G14: 622915.7 | H14: =(G14*4.5%)/360 -> 77.864462 | I14: 7914.66 | J14: =(I14*4.5%)/360 -> 0.9893325 | K14: 22682.42 | L14: =(K14*6.5%)/360 -> 4.0954369 | M14: 3567.32 | N14: =(M14*2.5%)/360 -> 0.24773056 | O14: 169731.79 | P14: =(O14*6.5%)/360 -> 30.646018 | Q14: 7512779.9 | R14: =(Q14*8%)/360 -> 1669.5066
B15: =B14+1 -> 45484 | C15: 740110.9 | D15: =(C15*7.5%)/360 -> 154.18977 | E15: 33378044 | F15: =(E15*7.5%)/360 -> 6953.7592 | G15: 622915.7 | H15: =(G15*4.5%)/360 -> 77.864462 | I15: 7914.66 | J15: =(I15*4.5%)/360 -> 0.9893325 | K15: 22682.42 | L15: =(K15*6.5%)/360 -> 4.0954369 | M15: 3567.32 | N15: =(M15*2.5%)/360 -> 0.24773056 | O15: 169731.79 | P15: =(O15*6.5%)/360 -> 30.646018 | Q15: 7512779.9 | R15: =(Q15*8%)/360 -> 1669.5066
B16: =B15+1 -> 45485 | C16: 740110.9 | D16: =(C16*7.5%)/360 -> 154.18977 | E16: 33378044 | F16: =(E16*7.5%)/360 -> 6953.7592 | G16: 622915.7 | H16: =(G16*4.5%)/360 -> 77.864462 | I16: 7914.66 | J16: =(I16*4.5%)/360 -> 0.9893325 | K16: 22682.42 | L16: =(K16*6.5%)/360 -> 4.0954369 | M16: 3567.32 | N16: =(M16*2.5%)/360 -> 0.24773056 | O16: 169731.79 | P16: =(O16*6.5%)/360 -> 30.646018 | Q16: 7512779.9 | R16: =(Q16*8%)/360 -> 1669.5066
B17: =B16+1 -> 45486 | C17: 740110.9 | D17: =(C17*7.5%)/360 -> 154.18977 | E17: 33378044 | F17: =(E17*7.5%)/360 -> 6953.7592 | G17: 622915.7 | H17: =(G17*4.5%)/360 -> 77.864462 | I17: 7914.66 | J17: =(I17*4.5%)/360 -> 0.9893325 | K17: 22682.42 | L17: =(K17*6.5%)/360 -> 4.0954369 | M17: 3567.32 | N17: =(M17*2.5%)/360 -> 0.24773056 | O17: 169731.79 | P17: =(O17*6.5%)/360 -> 30.646018 | Q17: 7512779.9 | R17: =(Q17*8%)/360 -> 1669.5066
... B129: =B128+1 -> 45598 | C129: 2681116.8 | D129: =(C129*7.5%)/360 -> 558.56599 | E129: 844987.9 | F129: =(E129*7.5%)/360 -> 176.03915 | G129: 246890.7 | H129: =(G129*4.5%)/360 -> 30.861338 | I129: 154158.66 | J129: =(I129*4.5%)/360 -> 19.269832 | K129: 22689.42 | L129: =(K129*6.5%)/360 -> 4.0967008 | M129: 3581.32 | N129: =(M129*2.5%)/360 -> 0.24870278 | O129: 169745.79 | P129: =(O129*6.5%)/360 -> 30.648545 | Q129: 312779.89 | R129: =(Q129*8%)/360 -> 69.506642
B130: 45613 | C130: 2533808.3 | D130: =(C130*7.5%)/360 -> 527.87673 | E130: 2196047.2 | F130: =(E130*7.5%)/360 -> 457.50983 | G130: 60890.7 | H130: =(G130*4.5%)/360 -> 7.6113375 | I130: 154158.66 | J130: =(I130*4.5%)/360 -> 19.269832 | K130: 22689.42 | L130: =(K130*6.5%)/360 -> 4.0967008 | M130: 3581.32 | N130: =(M130*2.5%)/360 -> 0.24870278 | O130: 169745.79 | P130: =(O130*6.5%)/360 -> 30.648545 | Q130: 827838.03 | R130: =(Q130*8%)/360 -> 183.96401
B131: =B130+1 -> 45614 | C131: 2533808.3 | D131: =(C131*7.5%)/360 -> 527.87673 | E131: 2042744 | F131: =(E131*7.5%)/360 -> 425.57166 | G131: 60890.7 | H131: =(G131*4.5%)/360 -> 7.6113375 | I131: 154158.66 | J131: =(I131*4.5%)/360 -> 19.269832 | K131: 22689.42 | L131: =(K131*6.5%)/360 -> 4.0967008 | M131: 3581.32 | N131: =(M131*2.5%)/360 -> 0.24870278 | O131: 169745.79 | P131: =(O131*6.5%)/360 -> 30.648545 | Q131: 827838.03 | R131: =(Q131*8%)/360 -> 183.96401
B132: =B131+1 -> 45615 | C132: 2533808.3 | D132: =(C132*7.5%)/360 -> 527.87673 | E132: 2041319 | F132: =(E132*7.5%)/360 -> 425.27479 | G132: 60890.7 | H132: =(G132*4.5%)/360 -> 7.6113375 | I132: 154158.66 | J132: =(I132*4.5%)/360 -> 19.269832 | K132: 22689.42 | L132: =(K132*6.5%)/360 -> 4.0967008 | M132: 3581.32 | N132: =(M132*2.5%)/360 -> 0.24870278 | O132: 169745.79 | P132: =(O132*6.5%)/360 -> 30.648545 | Q132: 827838.03 | R132: =(Q132*8%)/360 -> 183.96401
B133: =B132+1 -> 45616 | C133: 2533808.3 | D133: =(C133*7.5%)/360 -> 527.87673 | E133: 3023145.3 | F133: =(E133*7.5%)/360 -> 629.82194 | G133: 60890.7 | H133: =(G133*4.5%)/360 -> 7.6113375 | I133: 151429.91 | J133: =(I133*4.5%)/360 -> 18.928739 | K133: 22689.42 | L133: =(K133*6.5%)/360 -> 4.0967008 | M133: 3581.32 | N133: =(M133*2.5%)/360 -> 0.24870278 | O133: 169745.79 | P133: =(O133*6.5%)/360 -> 30.648545 | Q133: 827838.03 | R133: =(Q133*8%)/360 -> 183.96401
B134: =B133+1 -> 45617 | C134: 2533808.3 | D134: =(C134*7.5%)/360 -> 527.87673 | E134: 3023145.3 | F134: =(E134*7.5%)/360 -> 629.82194 | G134: 60890.7 | H134: =(G134*4.5%)/360 -> 7.6113375 | I134: 151429.91 | J134: =(I134*4.5%)/360 -> 18.928739 | K134: 22689.42 | L134: =(K134*6.5%)/360 -> 4.0967008 | M134: 3581.32 | N134: =(M134*2.5%)/360 -> 0.24870278 | O134: 169745.79 | P134: =(O134*6.5%)/360 -> 30.648545 | Q134: 827838.03 | R134: =(Q134*8%)/360 -> 183.96401
B135: =B134+1 -> 45618 | C135: 2533808.3 | D135: =(C135*7.5%)/360 -> 527.87673 | E135: 3023145.3 | F135: =(E135*7.5%)/360 -> 629.82194 | G135: 60890.7 | H135: =(G135*4.5%)/360 -> 7.6113375 | I135: 151429.91 | J135: =(I135*4.5%)/360 -> 18.928739 | K135: 22689.42 | L135: =(K135*6.5%)/360 -> 4.0967008 | M135: 3581.32 | N135: =(M135*2.5%)/360 -> 0.24870278 | O135: 169745.79 | P135: =(O135*6.5%)/360 -> 30.648545 | Q135: 827838.03 | R135: =(Q135*8%)/360 -> 183.96401
B136: =B135+1 -> 45619 | C136: 2533808.3 | D136: =(C136*7.5%)/360 -> 527.87673 | E136: 3023145.3 | F136: =(E136*7.5%)/360 -> 629.82194 | G136: 60890.7 | H136: =(G136*4.5%)/360 -> 7.6113375 | I136: 151429.91 | J136: =(I136*4.5%)/360 -> 18.928739 | K136: 22689.42 | L136: =(K136*6.5%)/360 -> 4.0967008 | M136: 3581.32 | N136: =(M136*2.5%)/360 -> 0.24870278 | O136: 169745.79 | P136: =(O136*6.5%)/360 -> 30.648545 | Q136: 827838.03 | R136: =(Q136*8%)/360 -> 183.96401
B137: =B136+1 -> 45620 | C137: 2533808.3 | D137: =(C137*7.5%)/360 -> 527.87673 | E137: 3023145.3 | F137: =(E137*7.5%)/360 -> 629.82194 | G137: 171890.7 | H137: =(G137*4.5%)/360 -> 21.486338 | I137: 151429.91 | J137: =(I137*4.5%)/360 -> 18.928739 | K137: 22689.42 | L137: =(K137*6.5%)/360 -> 4.0967008 | M137: 3581.32 | N137: =(M137*2.5%)/360 -> 0.24870278 | O137: 169745.79 | P137: =(O137*6.5%)/360 -> 30.648545 | Q137: 827838.03 | R137: =(Q137*8%)/360 -> 183.96401
B138: =B137+1 -> 45621 | C138: 2533808.3 | D138: =(C138*7.5%)/360 -> 527.87673 | E138: 3023145.3 | F138: =(E138*7.5%)/360 -> 629.82194 | G138: 171890.7 | H138: =(G138*4.5%)/360 -> 21.486338 | I138: 151429.91 | J138: =(I138*4.5%)/360 -> 18.928739 | K138: 22689.42 | L138: =(K138*6.5%)/360 -> 4.0967008 | M138: 3581.32 | N138: =(M138*2.5%)/360 -> 0.24870278 | O138: 169745.79 | P138: =(O138*6.5%)/360 -> 30.648545 | Q138: 827838.03 | R138: =(Q138*8%)/360 -> 183.96401
B139: =B138+1 -> 45622 | C139: 2533808.3 | D139: =(C139*7.5%)/360 -> 527.87673 | E139: 8023145.3 | F139: =(E139*7.5%)/360 -> 1671.4886 | G139: 171890.7 | H139: =(G139*4.5%)/360 -> 21.486338 | I139: 151429.91 | J139: =(I139*4.5%)/360 -> 18.928739 | K139: 22689.42 | L139: =(K139*6.5%)/360 -> 4.0967008 | M139: 3581.32 | N139: =(M139*2.5%)/360 -> 0.24870278 | O139: 169745.79 | P139: =(O139*6.5%)/360 -> 30.648545 | Q139: 827838.03 | R139: =(Q139*8%)/360 -> 183.96401
B140: =B139+1 -> 45623 | C140: 2533808.3 | D140: =(C140*7.5%)/360 -> 527.87673 | E140: 8023145.3 | F140: =(E140*7.5%)/360 -> 1671.4886 | G140: 171890.7 | H140: =(G140*4.5%)/360 -> 21.486338 | I140: 151429.91 | J140: =(I140*4.5%)/360 -> 18.928739 | K140: 22689.42 | L140: =(K140*6.5%)/360 -> 4.0967008 | M140: 3581.32 | N140: =(M140*2.5%)/360 -> 0.24870278 | O140: 169745.79 | P140: =(O140*6.5%)/360 -> 30.648545 | Q140: 827838.03 | R140: =(Q140*8%)/360 -> 183.96401
B141: =B140+1 -> 45624 | C141: 2533808.3 | D141: =(C141*7.5%)/360 -> 527.87673 | E141: 8909532.3 | F141: =(E141*7.5%)/360 -> 1856.1526 | G141: 171890.7 | H141: =(G141*4.5%)/360 -> 21.486338 | I141: 151429.91 | J141: =(I141*4.5%)/360 -> 18.928739 | K141: 22689.42 | L141: =(K141*6.5%)/360 -> 4.0967008 | M141: 3581.32 | N141: =(M141*2.5%)/360 -> 0.24870278 | O141: 169745.79 | P141: =(O141*6.5%)/360 -> 30.648545 | Q141: 7527838 | R141: =(Q141*8%)/360 -> 1672.8529
B142: =B141+1 -> 45625 | C142: 2533808.3 | D142: =(C142*7.5%)/360 -> 527.87673 | E142: 8909532.3 | F142: =(E142*7.5%)/360 -> 1856.1526 | G142: 171890.7 | H142: =(G142*4.5%)/360 -> 21.486338 | I142: 151429.91 | J142: =(I142*4.5%)/360 -> 18.928739 | K142: 22689.42 | L142: =(K142*6.5%)/360 -> 4.0967008 | M142: 3581.32 | N142: =(M142*2.5%)/360 -> 0.24870278 | O142: 169745.79 | P142: =(O142*6.5%)/360 -> 30.648545 | Q142: 7527838 | R142: =(Q142*8%)/360 -> 1672.8529
... B171: =B170+1 -> 45654 | C171: 663505.05 | D171: =(C171*7.5%)/360 -> 138.23022 | E171: 13464344 | F171: =(E171*7.5%)/360 -> 2805.0717 | G171: 331890.7 | H171: =(G171*4.5%)/360 -> 41.486337 | I171: 150070.84 | J171: =(I171*4.5%)/360 -> 18.758855 | K171: 22689.42 | L171: =(K171*6.5%)/360 -> 4.0967008 | M171: 3581.32 | N171: =(M171*2.5%)/360 -> 0.24870278 | O171: 169745.79 | P171: =(O171*6.5%)/360 -> 30.648545 | Q171: 7527838 | R171: =(Q171*8%)/360 -> 1672.8529
B172: 45657 | D172: 3652.7 | F172: 4541.16 | H172: 263.66 | J172: 326.04 | L172: 0 | N172: -5.78 | P172: 882.29 | R172: 22412.49
B173: Total | D173: =SUM(D4:D172) -> 850213 | F173: =SUM(F4:F172) -> 522697 | H173: =SUM(H4:H172) -> 14871.309 | J173: =SUM(J4:J172) -> 2268.7486 | L173: =SUM(L4:L172) -> 35683.802 | N173: =SUM(N4:N172) -> 76.963989 | P173: =SUM(P4:P172) -> 111895.81 | R173: =SUM(R4:R172) -> 184694.07
B175: 45658 | C175: 528725.78 | D175: =(C175*7.5%)/360 -> 110.1512 | E175: 13928770 | F175: =(E175*7.5%)/360 -> 2901.8271 | G175: 335767.8 | H175: =(G175*4.5%)/360 -> 41.970975 | I175: 151569.97 | J175: =(I175*4.5%)/360 -> 18.946246 | K175: 22689.42 | L175: =(K175*6.5%)/360 -> 4.0967008 | M175: 3581.32 | N175: =(M175*2.5%)/360 -> 0.24870278 | O175: 169745.79 | P175: =(O175*6.5%)/360 -> 30.648545 | Q175: 7900670.4 | R175: =(Q175*8%)/360 -> 1755.7045
B176: =B175+1 -> 45659 | C176: 528725.78 | D176: =(C176*7.5%)/360 -> 110.1512 | E176: 13928770 | F176: =(E176*7.5%)/360 -> 2901.8271 | G176: 335767.8 | H176: =(G176*4.5%)/360 -> 41.970975 | I176: 151569.97 | J176: =(I176*4.5%)/360 -> 18.946246 | K176: 22689.42 | L176: =(K176*6.5%)/360 -> 4.0967008 | M176: 3581.32 | N176: =(M176*2.5%)/360 -> 0.24870278 | O176: 169745.79 | P176: =(O176*6.5%)/360 -> 30.648545 | Q176: 7900670.4 | R176: =(Q176*8%)/360 -> 1755.7045
B177: =B176+1 -> 45660 | C177: 528725.78 | D177: =(C177*7.5%)/360 -> 110.1512 | E177: 13928770 | F177: =(E177*7.5%)/360 -> 2901.8271 | G177: 335767.8 | H177: =(G177*4.5%)/360 -> 41.970975 | I177: 151569.97 | J177: =(I177*4.5%)/360 -> 18.946246 | K177: 22689.42 | L177: =(K177*6.5%)/360 -> 4.0967008 | M177: 3581.32 | N177: =(M177*2.5%)/360 -> 0.24870278 | O177: 169745.79 | P177: =(O177*6.5%)/360 -> 30.648545 | Q177: 7900670.4 | R177: =(Q177*8%)/360 -> 1755.7045
B178: =B177+1 -> 45661 | C178: 528725.78 | D178: =(C178*7.5%)/360 -> 110.1512 | E178: 13928770 | F178: =(E178*7.5%)/360 -> 2901.8271 | G178: 335767.8 | H178: =(G178*4.5%)/360 -> 41.970975 | I178: 151569.97 | J178: =(I178*4.5%)/360 -> 18.946246 | K178: 22689.42 | L178: =(K178*6.5%)/360 -> 4.0967008 | M178: 3581.32 | N178: =(M178*2.5%)/360 -> 0.24870278 | O178: 169745.79 | P178: =(O178*6.5%)/360 -> 30.648545 | Q178: 7900670.4 | R178: =(Q178*8%)/360 -> 1755.7045
B179: =B178+1 -> 45662 | C179: 528725.78 | D179: =(C179*7.5%)/360 -> 110.1512 | E179: 13928770 | F179: =(E179*7.5%)/360 -> 2901.8271 | G179: 335767.8 | H179: =(G179*4.5%)/360 -> 41.970975 | I179: 151569.97 | J179: =(I179*4.5%)/360 -> 18.946246 | K179: 22689.42 | L179: =(K179*6.5%)/360 -> 4.0967008 | M179: 3581.32 | N179: =(M179*2.5%)/360 -> 0.24870278 | O179: 169745.79 | P179: =(O179*6.5%)/360 -> 30.648545 | Q179: 7900670.4 | R179: =(Q179*8%)/360 -> 1755.7045
B180: =B179+1 -> 45663 | C180: 528725.78 | D180: =(C180*7.5%)/360 -> 110.1512 | E180: 13928770 | F180: =(E180*7.5%)/360 -> 2901.8271 | G180: 335767.8 | H180: =(G180*4.5%)/360 -> 41.970975 | I180: 151569.97 | J180: =(I180*4.5%)/360 -> 18.946246 | K180: 22689.42 | L180: =(K180*6.5%)/360 -> 4.0967008 | M180: 3581.32 | N180: =(M180*2.5%)/360 -> 0.24870278 | O180: 169745.79 | P180: =(O180*6.5%)/360 -> 30.648545 | Q180: 200570.43 | R180: =(Q180*8%)/360 -> 44.571207
B181: =B180+1 -> 45664 | C181: 528725.78 | D181: =(C181*7.5%)/360 -> 110.1512 | E181: 13928770 | F181: =(E181*7.5%)/360 -> 2901.8271 | G181: 335767.8 | H181: =(G181*4.5%)/360 -> 41.970975 | I181: 151569.97 | J181: =(I181*4.5%)/360 -> 18.946246 | K181: 22689.42 | L181: =(K181*6.5%)/360 -> 4.0967008 | M181: 3581.32 | N181: =(M181*2.5%)/360 -> 0.24870278 | O181: 169745.79 | P181: =(O181*6.5%)/360 -> 30.648545 | Q181: 200570.43 | R181: =(Q181*8%)/360 -> 44.571207
B182: =B181+1 -> 45665 | C182: 528725.78 | D182: =(C182*7.5%)/360 -> 110.1512 | E182: 13928770 | F182: =(E182*7.5%)/360 -> 2901.8271 | G182: 335767.8 | H182: =(G182*4.5%)/360 -> 41.970975 | I182: 151569.97 | J182: =(I182*4.5%)/360 -> 18.946246 | K182: 22689.42 | L182: =(K182*6.5%)/360 -> 4.0967008 | M182: 3581.32 | N182: =(M182*2.5%)/360 -> 0.24870278 | O182: 169745.79 | P182: =(O182*6.5%)/360 -> 30.648545 | Q182: 200570.43 | R182: =(Q182*8%)/360 -> 44.571207
B183: =B182+1 -> 45666 | C183: 528725.78 | D183: =(C183*7.5%)/360 -> 110.1512 | E183: 13928770 | F183: =(E183*7.5%)/360 -> 2901.8271 | G183: 335767.8 | H183: =(G183*4.5%)/360 -> 41.970975 | I183: 151569.97 | J183: =(I183*4.5%)/360 -> 18.946246 | K183: 22689.42 | L183: =(K183*6.5%)/360 -> 4.0967008 | M183: 3581.32 | N183: =(M183*2.5%)/360 -> 0.24870278 | O183: 169745.79 | P183: =(O183*6.5%)/360 -> 30.648545 | Q183: 200570.43 | R183: =(Q183*8%)/360 -> 44.571207
B184: =B183+1 -> 45667 | C184: 528725.78 | D184: =(C184*7.5%)/360 -> 110.1512 | E184: 13928770 | F184: =(E184*7.5%)/360 -> 2901.8271 | G184: 335767.8 | H184: =(G184*4.5%)/360 -> 41.970975 | I184: 151569.97 | J184: =(I184*4.5%)/360 -> 18.946246 | K184: 22689.42 | L184: =(K184*6.5%)/360 -> 4.0967008 | M184: 3581.32 | N184: =(M184*2.5%)/360 -> 0.24870278 | O184: 169745.79 | P184: =(O184*6.5%)/360 -> 30.648545 | Q184: 200570.43 | R184: =(Q184*8%)/360 -> 44.571207
B185: =B184+1 -> 45668 | C185: 528725.78 | D185: =(C185*7.5%)/360 -> 110.1512 | E185: 13928770 | F185: =(E185*7.5%)/360 -> 2901.8271 | G185: 335767.8 | H185: =(G185*4.5%)/360 -> 41.970975 | I185: 151569.97 | J185: =(I185*4.5%)/360 -> 18.946246 | K185: 22689.42 | L185: =(K185*6.5%)/360 -> 4.0967008 | M185: 3581.32 | N185: =(M185*2.5%)/360 -> 0.24870278 | O185: 169745.79 | P185: =(O185*6.5%)/360 -> 30.648545 | Q185: 200570.43 | R185: =(Q185*8%)/360 -> 44.571207
B186: =B185+1 -> 45669 | C186: 528725.78 | D186: =(C186*7.5%)/360 -> 110.1512 | E186: 20238593 | F186: =(E186*7.5%)/360 -> 4216.3736 | G186: 365767.8 | H186: =(G186*4.5%)/360 -> 45.720975 | I186: 151569.97 | J186: =(I186*4.5%)/360 -> 18.946246 | K186: 22689.42 | L186: =(K186*6.5%)/360 -> 4.0967008 | M186: 3581.32 | N186: =(M186*2.5%)/360 -> 0.24870278 | O186: 169745.79 | P186: =(O186*6.5%)/360 -> 30.648545 | Q186: 200570.43 | R186: =(Q186*8%)/360 -> 44.571207
B187: =B186+1 -> 45670 | C187: 528725.78 | D187: =(C187*7.5%)/360 -> 110.1512 | E187: 20168620 | F187: =(E187*7.5%)/360 -> 4201.7959 | G187: 365767.8 | H187: =(G187*4.5%)/360 -> 45.720975 | I187: 151569.97 | J187: =(I187*4.5%)/360 -> 18.946246 | K187: 22689.42 | L187: =(K187*6.5%)/360 -> 4.0967008 | M187: 3581.32 | N187: =(M187*2.5%)/360 -> 0.24870278 | O187: 169745.79 | P187: =(O187*6.5%)/360 -> 30.648545 | Q187: 200570.43 | R187: =(Q187*8%)/360 -> 44.571207
... B355: =B354+1 -> 45838 | C355: 67278.49 | D355: =(C355*7.5%)/360 -> 14.016352 | E355: 1941577 | F355: =(E355*7.5%)/360 -> 404.49521 | G355: 91767.8 | H355: =(G355*4.5%)/360 -> 11.470975 | I355: 87170.21 | J355: =(I355*4.5%)/360 -> 10.896276 | K355: 22689.42 | L355: =(K355*6.5%)/360 -> 4.0967008 | M355: 3581.32 | N355: =(M355*2.5%)/360 -> 0.24870278 | O355: 169745.79 | P355: =(O355*6.5%)/360 -> 30.648545 | Q355: 570.43 | R355: =(Q355*8%)/360 -> 0.12676222
B356: Total | D356: =SUM(D175:D355) -> 77192.416 | F356: =SUM(F175:F355) -> 234111.99 | H356: =SUM(H175:H355) -> 13699.621 | J356: =SUM(J175:J355) -> 2620.4707 | L356: =SUM(L175:L355) -> 741.50285 | N356: =SUM(N175:N355) -> 45.015203 | P356: =SUM(P175:P355) -> 5547.3867 | R356: =SUM(R175:R355) -> 129111.94
B358: =B355+1 -> 45839 | C358: 146724.49 | D358: =(C358*7.5%)/360 -> 30.567602 | E358: 1941577 | F358: =(E358*7.5%)/360 -> 404.49521 | G358: 105245.55 | H358: =(G358*4.5%)/360 -> 13.155694 | I358: 87170.21 | J358: =(I358*4.5%)/360 -> 10.896276 | K358: 22689.42 | L358: =(K358*6.5%)/360 -> 4.0967008 | M358: 3581.32 | N358: =(M358*2.5%)/360 -> 0.24870278 | O358: 169745.79 | P358: =(O358*6.5%)/360 -> 30.648545 | Q358: 4000570.4 | R358: =(Q358*8%)/360 -> 889.01565
B359: =B358+1 -> 45840 | C359: 146666.49 | D359: =(C359*7.5%)/360 -> 30.555519 | E359: 2450134.5 | F359: =(E359*7.5%)/360 -> 510.44469 | G359: 105245.55 | H359: =(G359*4.5%)/360 -> 13.155694 | I359: 89443.13 | J359: =(I359*4.5%)/360 -> 11.180391 | K359: 22690.42 | L359: =(K359*6.5%)/360 -> 4.0968814 | M359: 3582.32 | N359: =(M359*2.5%)/360 -> 0.24877222 | O359: 169746.79 | P359: =(O359*6.5%)/360 -> 30.648726 | Q359: 4000570.4 | R359: =(Q359*8%)/360 -> 889.01565
B360: =B359+1 -> 45841 | C360: 146666.49 | D360: =(C360*7.5%)/360 -> 30.555519 | E360: 9267649.7 | F360: =(E360*7.5%)/360 -> 1930.7603 | G360: 105245.55 | H360: =(G360*4.5%)/360 -> 13.155694 | I360: 89443.13 | J360: =(I360*4.5%)/360 -> 11.180391 | K360: 22691.42 | L360: =(K360*6.5%)/360 -> 4.0970619 | M360: 3583.32 | N360: =(M360*2.5%)/360 -> 0.24884167 | O360: 169747.79 | P360: =(O360*6.5%)/360 -> 30.648907 | Q360: 4000570.4 | R360: =(Q360*8%)/360 -> 889.01565
B361: =B360+1 -> 45842 | C361: 146666.49 | D361: =(C361*7.5%)/360 -> 30.555519 | E361: 9267649.7 | F361: =(E361*7.5%)/360 -> 1930.7603 | G361: 105245.55 | H361: =(G361*4.5%)/360 -> 13.155694 | I361: 89443.13 | J361: =(I361*4.5%)/360 -> 11.180391 | K361: 22692.42 | L361: =(K361*6.5%)/360 -> 4.0972425 | M361: 3584.32 | N361: =(M361*2.5%)/360 -> 0.24891111 | O361: 169748.79 | P361: =(O361*6.5%)/360 -> 30.649087 | Q361: 4000570.4 | R361: =(Q361*8%)/360 -> 889.01565
B362: =B361+1 -> 45843 | C362: 146666.49 | D362: =(C362*7.5%)/360 -> 30.555519 | E362: 9267649.7 | F362: =(E362*7.5%)/360 -> 1930.7603 | G362: 105245.55 | H362: =(G362*4.5%)/360 -> 13.155694 | I362: 89443.13 | J362: =(I362*4.5%)/360 -> 11.180391 | K362: 22693.42 | L362: =(K362*6.5%)/360 -> 4.0974231 | M362: 3585.32 | N362: =(M362*2.5%)/360 -> 0.24898056 | O362: 169749.79 | P362: =(O362*6.5%)/360 -> 30.649268 | Q362: 4000570.4 | R362: =(Q362*8%)/360 -> 889.01565
B363: =B362+1 -> 45844 | C363: 146666.49 | D363: =(C363*7.5%)/360 -> 30.555519 | E363: 9267649.7 | F363: =(E363*7.5%)/360 -> 1930.7603 | G363: 105245.55 | H363: =(G363*4.5%)/360 -> 13.155694 | I363: 89443.13 | J363: =(I363*4.5%)/360 -> 11.180391 | K363: 22693.42 | L363: =(K363*6.5%)/360 -> 4.0974231 | M363: 3585.32 | N363: =(M363*2.5%)/360 -> 0.24898056 | O363: 169749.79 | P363: =(O363*6.5%)/360 -> 30.649268 | Q363: 4000570.4 | R363: =(Q363*8%)/360 -> 889.01565
B364: =B363+1 -> 45845 | C364: 600146.49 | D364: =(C364*7.5%)/360 -> 125.03052 | E364: 11906218 | F364: =(E364*7.5%)/360 -> 2480.4622 | G364: 117245.55 | H364: =(G364*4.5%)/360 -> 14.655694 | I364: 89443.13 | J364: =(I364*4.5%)/360 -> 11.180391 | K364: 22693.42 | L364: =(K364*6.5%)/360 -> 4.0974231 | M364: 3585.32 | N364: =(M364*2.5%)/360 -> 0.24898056 | O364: 169749.79 | P364: =(O364*6.5%)/360 -> 30.649268 | Q364: 570.43 | R364: =(Q364*8%)/360 -> 0.12676222
B365: =B364+1 -> 45846 | C365: 900126.49 | D365: =(C365*7.5%)/360 -> 187.52635 | E365: 21265488 | F365: =(E365*7.5%)/360 -> 4430.31 | G365: 117245.55 | H365: =(G365*4.5%)/360 -> 14.655694 | I365: 89443.13 | J365: =(I365*4.5%)/360 -> 11.180391 | K365: 22693.42 | L365: =(K365*6.5%)/360 -> 4.0974231 | M365: 3585.32 | N365: =(M365*2.5%)/360 -> 0.24898056 | O365: 169749.79 | P365: =(O365*6.5%)/360 -> 30.649268 | Q365: 570.43 | R365: =(Q365*8%)/360 -> 0.12676222
B366: =B365+1 -> 45847 | C366: 1689606.5 | D366: =(C366*7.5%)/360 -> 352.00135 | E366: 18480413 | F366: =(E366*7.5%)/360 -> 3850.086 | G366: 117245.55 | H366: =(G366*4.5%)/360 -> 14.655694 | I366: 89443.13 | J366: =(I366*4.5%)/360 -> 11.180391 | K366: 22693.42 | L366: =(K366*6.5%)/360 -> 4.0974231 | M366: 3585.32 | N366: =(M366*2.5%)/360 -> 0.24898056 | O366: 169749.79 | P366: =(O366*6.5%)/360 -> 30.649268 | Q366: 570.43 | R366: =(Q366*8%)/360 -> 0.12676222
B367: =B366+1 -> 45848 | C367: 2689614.5 | D367: =(C367*7.5%)/360 -> 560.33635 | E367: 18133794 | F367: =(E367*7.5%)/360 -> 3777.8738 | G367: 117245.55 | H367: =(G367*4.5%)/360 -> 14.655694 | I367: 89443.13 | J367: =(I367*4.5%)/360 -> 11.180391 | K367: 22693.42 | L367: =(K367*6.5%)/360 -> 4.0974231 | M367: 3585.32 | N367: =(M367*2.5%)/360 -> 0.24898056 | O367: 169749.79 | P367: =(O367*6.5%)/360 -> 30.649268 | Q367: 570.43 | R367: =(Q367*8%)/360 -> 0.12676222
B368: =B367+1 -> 45849 | C368: 2689614.5 | D368: =(C368*7.5%)/360 -> 560.33635 | E368: 18133794 | F368: =(E368*7.5%)/360 -> 3777.8738 | G368: 117245.55 | H368: =(G368*4.5%)/360 -> 14.655694 | I368: 89443.13 | J368: =(I368*4.5%)/360 -> 11.180391 | K368: 22693.42 | L368: =(K368*6.5%)/360 -> 4.0974231 | M368: 3585.32 | N368: =(M368*2.5%)/360 -> 0.24898056 | O368: 169749.79 | P368: =(O368*6.5%)/360 -> 30.649268 | Q368: 570.43 | R368: =(Q368*8%)/360 -> 0.12676222
B369: =B368+1 -> 45850 | C369: 2689614.5 | D369: =(C369*7.5%)/360 -> 560.33635 | E369: 18133794 | F369: =(E369*7.5%)/360 -> 3777.8738 | G369: 117245.55 | H369: =(G369*4.5%)/360 -> 14.655694 | I369: 89443.13 | J369: =(I369*4.5%)/360 -> 11.180391 | K369: 22693.42 | L369: =(K369*6.5%)/360 -> 4.0974231 | M369: 3585.32 | N369: =(M369*2.5%)/360 -> 0.24898056 | O369: 169749.79 | P369: =(O369*6.5%)/360 -> 30.649268 | Q369: 327133.73 | R369: =(Q369*8%)/360 -> 72.696384
B370: =B369+1 -> 45851 | C370: 2689614.5 | D370: =(C370*7.5%)/360 -> 560.33635 | E370: 15750302 | F370: =(E370*7.5%)/360 -> 3281.3129 | G370: 117245.55 | H370: =(G370*4.5%)/360 -> 14.655694 | I370: 89443.13 | J370: =(I370*4.5%)/360 -> 11.180391 | K370: 22693.42 | L370: =(K370*6.5%)/360 -> 4.0974231 | M370: 3585.32 | N370: =(M370*2.5%)/360 -> 0.24898056 | O370: 169749.79 | P370: =(O370*6.5%)/360 -> 30.649268 | Q370: 327133.73 | R370: =(Q370*8%)/360 -> 72.696384
... B511: =B510+1 -> 45992 | C511: 146956.57 | D511: =(C511*7.5%)/360 -> 30.615952 | E511: 1135180.3 | F511: =(E511*7.5%)/360 -> 236.49589 | G511: 109579.93 | H511: =(G511*4.5%)/360 -> 13.697491 | I511: 65482.46 | J511: =(I511*4.5%)/360 -> 8.1853075 | K511: 22452.42 | L511: =(K511*6.5%)/360 -> 4.0539092 | M511: 2696.67 | N511: =(M511*2.5%)/360 -> 0.18726875 | O511: 163035.8 | P511: =(O511*6.5%)/360 -> 29.437019 | Q511: 200417.06 | R511: =(Q511*8%)/360 -> 44.537124
A512: =D512+F512+H512+J512+L512+N512+P512+R512 -> 679.49609 | B512: =B511+1 -> 45993 | C512: 146956.57 | D512: =(C512*7.5%)/360 -> 30.615952 | E512: 2634153.7 | F512: =(E512*7.5%)/360 -> 548.78201 | G512: 109579.93 | H512: =(G512*4.5%)/360 -> 13.697491 | I512: 65482.46 | J512: =(I512*4.5%)/360 -> 8.1853075 | K512: 22452.42 | L512: =(K512*6.5%)/360 -> 4.0539092 | M512: 2696.67 | N512: =(M512*2.5%)/360 -> 0.18726875 | O512: 163035.8 | P512: =(O512*6.5%)/360 -> 29.437019 | Q512: 200417.06 | R512: =(Q512*8%)/360 -> 44.537124
A513: =D513+F513+H513+J513+L513+N513+P513+R513 -> 1452.6166 | B513: =B512+1 -> 45994 | C513: 146956.57 | D513: =(C513*7.5%)/360 -> 30.615952 | E513: 6345132 | F513: =(E513*7.5%)/360 -> 1321.9025 | G513: 109579.93 | H513: =(G513*4.5%)/360 -> 13.697491 | I513: 65482.46 | J513: =(I513*4.5%)/360 -> 8.1853075 | K513: 22452.42 | L513: =(K513*6.5%)/360 -> 4.0539092 | M513: 2696.67 | N513: =(M513*2.5%)/360 -> 0.18726875 | O513: 163035.8 | P513: =(O513*6.5%)/360 -> 29.437019 | Q513: 200417.06 | R513: =(Q513*8%)/360 -> 44.537124
A514: =D514+F514+H514+J514+L514+N514+P514+R514 -> 365.53482 | B514: =B513+1 -> 45995 | C514: 127464.57 | D514: =(C514*7.5%)/360 -> 26.555119 | E514: 1140631.6 | F514: =(E514*7.5%)/360 -> 237.63158 | G514: 119579.93 | H514: =(G514*4.5%)/360 -> 14.947491 | I514: 65482.46 | J514: =(I514*4.5%)/360 -> 8.1853075 | K514: 22452.42 | L514: =(K514*6.5%)/360 -> 4.0539092 | M514: 2696.67 | N514: =(M514*2.5%)/360 -> 0.18726875 | O514: 163035.8 | P514: =(O514*6.5%)/360 -> 29.437019 | Q514: 200417.06 | R514: =(Q514*8%)/360 -> 44.537124
A515: =D515+F515+H515+J515+L515+N515+P515+R515 -> 408.55775 | B515: =B514+1 -> 45996 | C515: 127464.57 | D515: =(C515*7.5%)/360 -> 26.555119 | E515: 1341141.7 | F515: =(E515*7.5%)/360 -> 279.40451 | G515: 129579.93 | H515: =(G515*4.5%)/360 -> 16.197491 | I515: 65482.46 | J515: =(I515*4.5%)/360 -> 8.1853075 | K515: 22452.42 | L515: =(K515*6.5%)/360 -> 4.0539092 | M515: 2696.67 | N515: =(M515*2.5%)/360 -> 0.18726875 | O515: 163035.8 | P515: =(O515*6.5%)/360 -> 29.437019 | Q515: 200417.06 | R515: =(Q515*8%)/360 -> 44.537124
A516: =D516+F516+H516+J516+L516+N516+P516+R516 -> 366.78482 | B516: =B515+1 -> 45997 | C516: 127464.57 | D516: =(C516*7.5%)/360 -> 26.555119 | E516: 1140631.6 | F516: =(E516*7.5%)/360 -> 237.63158 | G516: 129579.93 | H516: =(G516*4.5%)/360 -> 16.197491 | I516: 65482.46 | J516: =(I516*4.5%)/360 -> 8.1853075 | K516: 22452.42 | L516: =(K516*6.5%)/360 -> 4.0539092 | M516: 2696.67 | N516: =(M516*2.5%)/360 -> 0.18726875 | O516: 163035.8 | P516: =(O516*6.5%)/360 -> 29.437019 | Q516: 200417.06 | R516: =(Q516*8%)/360 -> 44.537124
A517: =D517+F517+H517+J517+L517+N517+P517+R517 -> 300.09905 | B517: =B516+1 -> 45998 | C517: 127464.57 | D517: =(C517*7.5%)/360 -> 26.555119 | E517: 820539.91 | F517: =(E517*7.5%)/360 -> 170.94581 | G517: 129579.93 | H517: =(G517*4.5%)/360 -> 16.197491 | I517: 65482.46 | J517: =(I517*4.5%)/360 -> 8.1853075 | K517: 22452.42 | L517: =(K517*6.5%)/360 -> 4.0539092 | M517: 2696.67 | N517: =(M517*2.5%)/360 -> 0.18726875 | O517: 163035.8 | P517: =(O517*6.5%)/360 -> 29.437019 | Q517: 200417.06 | R517: =(Q517*8%)/360 -> 44.537124
A518: =D518+F518+H518+J518+L518+N518+P518+R518 -> 329.75713 | B518: =B517+1 -> 45999 | C518: 627464.57 | D518: =(C518*7.5%)/360 -> 130.72179 | E518: 443098.66 | F518: =(E518*7.5%)/360 -> 92.312221 | G518: 162579.93 | H518: =(G518*4.5%)/360 -> 20.322491 | I518: 65482.46 | J518: =(I518*4.5%)/360 -> 8.1853075 | K518: 22452.42 | L518: =(K518*6.5%)/360 -> 4.0539092 | M518: 2696.67 | N518: =(M518*2.5%)/360 -> 0.18726875 | O518: 163035.8 | P518: =(O518*6.5%)/360 -> 29.437019 | Q518: 200417.06 | R518: =(Q518*8%)/360 -> 44.537124
A519: =D519+F519+H519+J519+L519+N519+P519+R519 -> 659.83336 | B519: =B518+1 -> 46000 | C519: 627464.57 | D519: =(C519*7.5%)/360 -> 130.72179 | E519: 2027464.6 | F519: =(E519*7.5%)/360 -> 422.38845 | G519: 162579.93 | H519: =(G519*4.5%)/360 -> 20.322491 | I519: 65482.46 | J519: =(I519*4.5%)/360 -> 8.1853075 | K519: 22452.42 | L519: =(K519*6.5%)/360 -> 4.0539092 | M519: 2696.67 | N519: =(M519*2.5%)/360 -> 0.18726875 | O519: 163035.8 | P519: =(O519*6.5%)/360 -> 29.437019 | Q519: 200417.06 | R519: =(Q519*8%)/360 -> 44.537124
A520: =D520+F520+H520+J520+L520+N520+P520+R520 -> 621.42379 | B520: =B519+1 -> 46001 | C520: 443098.66 | D520: =(C520*7.5%)/360 -> 92.312221 | E520: 2027464.6 | F520: =(E520*7.5%)/360 -> 422.38845 | G520: 162579.93 | H520: =(G520*4.5%)/360 -> 20.322491 | I520: 65482.46 | J520: =(I520*4.5%)/360 -> 8.1853075 | K520: 22452.42 | L520: =(K520*6.5%)/360 -> 4.0539092 | M520: 2696.67 | N520: =(M520*2.5%)/360 -> 0.18726875 | O520: 163035.8 | P520: =(O520*6.5%)/360 -> 29.437019 | Q520: 200417.06 | R520: =(Q520*8%)/360 -> 44.537124
A521: =D521+F521+H521+J521+L521+N521+P521+R521 -> 471.69791 | B521: =B520+1 -> 46002 | C521: 1227464.6 | D521: =(C521*7.5%)/360 -> 255.72179 | E521: 524414.43 | F521: =(E521*7.5%)/360 -> 109.25301 | G521: 162579.93 | H521: =(G521*4.5%)/360 -> 20.322491 | I521: 65482.46 | J521: =(I521*4.5%)/360 -> 8.1853075 | K521: 22452.42 | L521: =(K521*6.5%)/360 -> 4.0539092 | M521: 2696.67 | N521: =(M521*2.5%)/360 -> 0.18726875 | O521: 163035.8 | P521: =(O521*6.5%)/360 -> 29.437019 | Q521: 200417.06 | R521: =(Q521*8%)/360 -> 44.537124
A522: =D522+F522+H522+J522+L522+N522+P522+R522 -> 471.69791 | B522: =B521+1 -> 46003 | C522: 1227464.6 | D522: =(C522*7.5%)/360 -> 255.72179 | E522: 524414.43 | F522: =(E522*7.5%)/360 -> 109.25301 | G522: 162579.93 | H522: =(G522*4.5%)/360 -> 20.322491 | I522: 65482.46 | J522: =(I522*4.5%)/360 -> 8.1853075 | K522: 22452.42 | L522: =(K522*6.5%)/360 -> 4.0539092 | M522: 2696.67 | N522: =(M522*2.5%)/360 -> 0.18726875 | O522: 163035.8 | P522: =(O522*6.5%)/360 -> 29.437019 | Q522: 200417.06 | R522: =(Q522*8%)/360 -> 44.537124
A523: =D523+F523+H523+J523+L523+N523+P523+R523 -> 471.69791 | B523: =B522+1 -> 46004 | C523: 1227464.6 | D523: =(C523*7.5%)/360 -> 255.72179 | E523: 524414.43 | F523: =(E523*7.5%)/360 -> 109.25301 | G523: 162579.93 | H523: =(G523*4.5%)/360 -> 20.322491 | I523: 65482.46 | J523: =(I523*4.5%)/360 -> 8.1853075 | K523: 22452.42 | L523: =(K523*6.5%)/360 -> 4.0539092 | M523: 2696.67 | N523: =(M523*2.5%)/360 -> 0.18726875 | O523: 163035.8 | P523: =(O523*6.5%)/360 -> 29.437019 | Q523: 200417.06 | R523: =(Q523*8%)/360 -> 44.537124
... A540: =D540+F540+H540+J540+L540+N540+P540+R540 -> 333.41309 | B540: =B539+1 -> 46021 | C540: 6485.82 | D540: =(C540*7.5%)/360 -> 1.3512125 | E540: 975787.39 | F540: =(E540*7.5%)/360 -> 203.28904 | G540: 519.93 | H540: =(G540*4.5%)/360 -> 0.06499125 | I540: 60303.19 | J540: =(I540*4.5%)/360 -> 7.5378987 | K540: 22452.42 | L540: =(K540*6.5%)/360 -> 4.0539092 | M540: 2696.67 | N540: =(M540*2.5%)/360 -> 0.18726875 | O540: 163035.8 | P540: =(O540*6.5%)/360 -> 29.437019 | Q540: 393712.89 | R540: =(Q540*8%)/360 -> 87.491753
B541: Total | D541: =SUM(D358:D540) -> 32349.602 | F541: =SUM(F358:F540) -> 114150.23 | H541: =SUM(H358:H540) -> 4550.4721 | J541: =SUM(J358:J540) -> 1788.6316 | L541: =SUM(L358:L540) -> 745.43171 | N541: =SUM(N358:N540) -> 39.329855 | P541: =SUM(P358:P540) -> 5486.3771 | R541: =SUM(R358:R540) -> 12129.169
B543: Receivable Remaining
A544: =D544+F544+H544+J544+L544+N544+P544+R544 -> 605.88069 | B544: 46023 | C544: 527452.82 | D544: =(C544*7.5%)/360 -> 109.886 | E544: 1121330.8 | F544: =(E544*7.5%)/360 -> 233.61058 | G544: 1297114.9 | H544: =(G544*4.5%)/360 -> 162.13937 | I544: 59958.19 | J544: =(I544*4.5%)/360 -> 7.4947738 | K544: 22452.42 | L544: =(K544*4.5%)/360 -> 2.8065525 | M544: 2696.67 | N544: =(M544*2.5%)/360 -> 0.18726875 | O544: 163035.8 | P544: =(O544*0.5%)/360 -> 2.2643861 | Q544: 393712.89 | R544: =(Q544*8%)/360 -> 87.491753
A545: =D545+F545+H545+J545+L545+N545+P545+R545 -> 493.75384 | B545: =B544+1 -> 46024 | C545: 527452.82 | D545: =(C545*7.5%)/360 -> 109.886 | E545: 1121330.8 | F545: =(E545*7.5%)/360 -> 233.61058 | G545: 1297114.9 | H545: =(G545*2.5%)/360 -> 90.077426 | I545: 59958.19 | J545: =(I545*2.5%)/360 -> 4.1637632 | K545: 22452.42 | L545: =(K545*4.5%)/360 -> 2.8065525 | M545: 2696.67 | N545: =(M545*0.5%)/360 -> 0.03745375 | O545: 163035.8 | P545: =(O545*6.5%)/360 -> 29.437019 | Q545: 106807.69 | R545: =(Q545*8%)/360 -> 23.735042
A546: =D546+F546+H546+J546+L546+N546+P546+R546 -> 493.75384 | B546: =B545+1 -> 46025 | C546: 527452.82 | D546: =(C546*7.5%)/360 -> 109.886 | E546: 1121330.8 | F546: =(E546*7.5%)/360 -> 233.61058 | G546: 1297114.9 | H546: =(G546*2.5%)/360 -> 90.077426 | I546: 59958.19 | J546: =(I546*2.5%)/360 -> 4.1637632 | K546: 22452.42 | L546: =(K546*4.5%)/360 -> 2.8065525 | M546: 2696.67 | N546: =(M546*0.5%)/360 -> 0.03745375 | O546: 163035.8 | P546: =(O546*6.5%)/360 -> 29.437019 | Q546: 106807.69 | R546: =(Q546*8%)/360 -> 23.735042
A547: =D547+F547+H547+J547+L547+N547+P547+R547 -> 314.4354 | B547: =B546+1 -> 46026 | C547: 442452.82 | D547: =(C547*7.5%)/360 -> 92.177671 | E547: 362935.59 | F547: =(E547*7.5%)/360 -> 75.611581 | G547: 1297114.9 | H547: =(G547*2.5%)/360 -> 90.077426 | I547: 7958.19 | J547: =(I547*2.5%)/360 -> 0.55265208 | K547: 22452.42 | L547: =(K547*4.5%)/360 -> 2.8065525 | M547: 2696.67 | N547: =(M547*0.5%)/360 -> 0.03745375 | O547: 163035.8 | P547: =(O547*6.5%)/360 -> 29.437019 | Q547: 106807.69 | R547: =(Q547*8%)/360 -> 23.735042
A548: =D548+F548+H548+J548+L548+N548+P548+R548 -> 324.10123 | B548: =B547+1 -> 46027 | C548: 467107.82 | D548: =(C548*7.5%)/360 -> 97.314129 | E548: 384676.59 | F548: =(E548*7.5%)/360 -> 80.140956 | G548: 1297114.9 | H548: =(G548*2.5%)/360 -> 90.077426 | I548: 7958.19 | J548: =(I548*2.5%)/360 -> 0.55265208 | K548: 22452.42 | L548: =(K548*4.5%)/360 -> 2.8065525 | M548: 2696.67 | N548: =(M548*0.5%)/360 -> 0.03745375 | O548: 163035.8 | P548: =(O548*6.5%)/360 -> 29.437019 | Q548: 106807.69 | R548: =(Q548*8%)/360 -> 23.735042
A549: =D549+F549+H549+J549+L549+N549+P549+R549 -> 577.08213 | B549: =B548+1 -> 46028 | C549: 1667082.8 | D549: =(C549*7.5%)/360 -> 347.30892 | E549: 384676.59 | F549: =(E549*7.5%)/360 -> 80.140956 | G549: 1340114.9 | H549: =(G549*2.5%)/360 -> 93.063537 | I549: 7958.19 | J549: =(I549*2.5%)/360 -> 0.55265208 | K549: 22452.42 | L549: =(K549*4.5%)/360 -> 2.8065525 | M549: 2696.67 | N549: =(M549*0.5%)/360 -> 0.03745375 | O549: 163035.8 | P549: =(O549*6.5%)/360 -> 29.437019 | Q549: 106807.69 | R549: =(Q549*8%)/360 -> 23.735042
A550: =D550+F550+H550+J550+L550+N550+P550+R550 -> 433.85401 | B550: =B549+1 -> 46029 | C550: 67082.82 | D550: =(C550*7.5%)/360 -> 13.975588 | E550: 1730514.9 | F550: =(E550*7.5%)/360 -> 360.52394 | G550: 40114.93 | H550: =(G550*2.5%)/360 -> 2.785759 | I550: 7958.19 | J550: =(I550*2.5%)/360 -> 0.55265208 | K550: 22452.42 | L550: =(K550*4.5%)/360 -> 2.8065525 | M550: 2696.67 | N550: =(M550*0.5%)/360 -> 0.03745375 | O550: 163035.8 | P550: =(O550*6.5%)/360 -> 29.437019 | Q550: 106807.69 | R550: =(Q550*8%)/360 -> 23.735042
A551: =D551+F551+H551+J551+L551+N551+P551+R551 -> 437.60301 | B551: =B550+1 -> 46030 | C551: 67082.82 | D551: =(C551*7.5%)/360 -> 13.975588 | E551: 1748510.1 | F551: =(E551*7.5%)/360 -> 364.27294 | G551: 40114.93 | H551: =(G551*2.5%)/360 -> 2.785759 | I551: 7958.19 | J551: =(I551*2.5%)/360 -> 0.55265208 | K551: 22452.42 | L551: =(K551*4.5%)/360 -> 2.8065525 | M551: 2696.67 | N551: =(M551*0.5%)/360 -> 0.03745375 | O551: 163035.8 | P551: =(O551*6.5%)/360 -> 29.437019 | Q551: 106807.69 | R551: =(Q551*8%)/360 -> 23.735042
A552: =D552+F552+H552+J552+L552+N552+P552+R552 -> 437.60301 | B552: =B551+1 -> 46031 | C552: 67082.82 | D552: =(C552*7.5%)/360 -> 13.975588 | E552: 1748510.1 | F552: =(E552*7.5%)/360 -> 364.27294 | G552: 40114.93 | H552: =(G552*2.5%)/360 -> 2.785759 | I552: 7958.19 | J552: =(I552*2.5%)/360 -> 0.55265208 | K552: 22452.42 | L552: =(K552*4.5%)/360 -> 2.8065525 | M552: 2696.67 | N552: =(M552*0.5%)/360 -> 0.03745375 | O552: 163035.8 | P552: =(O552*6.5%)/360 -> 29.437019 | Q552: 106807.69 | R552: =(Q552*8%)/360 -> 23.735042
A553: =D553+F553+H553+J553+L553+N553+P553+R553 -> 437.60301 | B553: =B552+1 -> 46032 | C553: 67082.82 | D553: =(C553*7.5%)/360 -> 13.975588 | E553: 1748510.1 | F553: =(E553*7.5%)/360 -> 364.27294 | G553: 40114.93 | H553: =(G553*2.5%)/360 -> 2.785759 | I553: 7958.19 | J553: =(I553*2.5%)/360 -> 0.55265208 | K553: 22452.42 | L553: =(K553*4.5%)/360 -> 2.8065525 | M553: 2696.67 | N553: =(M553*0.5%)/360 -> 0.03745375 | O553: 163035.8 | P553: =(O553*6.5%)/360 -> 29.437019 | Q553: 106807.69 | R553: =(Q553*8%)/360 -> 23.735042
A554: =D554+F554+H554+J554+L554+N554+P554+R554 -> 435.85161 | B554: =B553+1 -> 46033 | C554: 167082.82 | D554: =(C554*7.5%)/360 -> 34.808921 | E554: 1640103.4 | F554: =(E554*7.5%)/360 -> 341.68821 | G554: 40114.93 | H554: =(G554*2.5%)/360 -> 2.785759 | I554: 7958.19 | J554: =(I554*2.5%)/360 -> 0.55265208 | K554: 22452.42 | L554: =(K554*4.5%)/360 -> 2.8065525 | M554: 2696.67 | N554: =(M554*0.5%)/360 -> 0.03745375 | O554: 163035.8 | P554: =(O554*6.5%)/360 -> 29.437019 | Q554: 106807.69 | R554: =(Q554*8%)/360 -> 23.735042
A555: =D555+F555+H555+J555+L555+N555+P555+R555 -> 329.02347 | B555: =B554+1 -> 46034 | C555: 167082.82 | D555: =(C555*7.5%)/360 -> 34.808921 | E555: 460681.65 | F555: =(E555*7.5%)/360 -> 95.975344 | G555: 2040054.9 | H555: =(G555*2.5%)/360 -> 141.67048 | I555: 7958.19 | J555: =(I555*2.5%)/360 -> 0.55265208 | K555: 22452.42 | L555: =(K555*4.5%)/360 -> 2.8065525 | M555: 2696.67 | N555: =(M555*0.5%)/360 -> 0.03745375 | O555: 163035.8 | P555: =(O555*6.5%)/360 -> 29.437019 | Q555: 106807.69 | R555: =(Q555*8%)/360 -> 23.735042
A556: =D556+F556+H556+J556+L556+N556+P556+R556 -> 665.58586 | B556: =B555+1 -> 46035 | C556: 909077.53 | D556: =(C556*7.5%)/360 -> 189.39115 | E556: 2001000.6 | F556: =(E556*7.5%)/360 -> 416.87514 | G556: 40054.93 | H556: =(G556*2.5%)/360 -> 2.7815924 | I556: 7958.19 | J556: =(I556*2.5%)/360 -> 0.55265208 | K556: 22337.42 | L556: =(K556*4.5%)/360 -> 2.7921775 | M556: 2715.57 | N556: =(M556*0.5%)/360 -> 0.03771625 | O556: 162943.72 | P556: =(O556*6.5%)/360 -> 29.420394 | Q556: 106807.69 | R556: =(Q556*8%)/360 -> 23.735042
... A627: =D627+F627+H627+J627+L627+N627+P627+R627 -> 78.322266 | B627: =B626+1 -> 46106 | C627: 115686.28 | D627: =(C627*7.5%)/360 -> 24.101308 | E627: 38042.78 | F627: =(E627*7.5%)/360 -> 7.9255792 | G627: 72958.93 | H627: =(G627*2.5%)/360 -> 5.0665924 | I627: 25639.11 | J627: =(I627*2.5%)/360 -> 1.7804937 | K627: 22337.42 | L627: =(K627*4.5%)/360 -> 2.7921775 | M627: 2715.57 | N627: =(M627*0.5%)/360 -> 0.03771625 | O627: 162943.72 | P627: =(O627*6.5%)/360 -> 29.420394 | Q627: 32391.02 | R627: =(Q627*8%)/360 -> 7.1980044

Sheet Policy Notes
E2: Ekush First Unit Fund
E3: Notes to the Financial Statements
E4: for the year ended 31 December 2020
E6: 1 | F6: Legal Status and Nature of the Company
E8: 1.01 | F8: The Fund and Its Objectives
